{
  "type": "Feature",
  "properties": {
    "gn:admin1_code":"19",
    "gn:admin2_code":"1509",
    "gn:admin3_code":"150906.0",
    "gn:asciiname":"Vergeira",
    "gn:country_code":"PT",
    "gn:dem":186,
    "gn:feature_class":"P",
    "gn:feature_code":"PPL",
    "gn:name":"Vergeira",
    "gn:population":0,
    "gn:timezone":"Europe/Lisbon",
    "iso:country":"PT",
    "wof:name":"Vergeira",
    "wof:placetype":"locality"
},
  "geometry": {"coordinates":[-8.69954,38.0288],"type":"Point"}
}