{
  "type": "Feature",
  "properties": {
    "gn:admin1_code":"16",
    "gn:admin2_code":"1201",
    "gn:admin3_code":"120101.0",
    "gn:asciiname":"Alter Pedroso",
    "gn:country_code":"PT",
    "gn:dem":397,
    "gn:feature_class":"P",
    "gn:feature_code":"PPL",
    "gn:name":"Alter Pedroso",
    "gn:population":0,
    "gn:timezone":"Europe/Lisbon",
    "iso:country":"PT",
    "wof:name":"Alter Pedroso",
    "wof:placetype":"locality"
},
  "geometry": {"coordinates":[-7.62249,39.18799],"type":"Point"}
}