{
  "type": "Feature",
  "properties": {
    "gn:admin1_code":"02",
    "gn:admin2_code":"0110",
    "gn:admin3_code":"11004.0",
    "gn:asciiname":"Vista Alegre",
    "gn:country_code":"PT",
    "gn:dem":15,
    "gn:feature_class":"P",
    "gn:feature_code":"PPL",
    "gn:name":"Vista Alegre",
    "gn:population":0,
    "gn:timezone":"Europe/Lisbon",
    "iso:country":"PT",
    "name:cat_x_preferred":[
        "Vista Alegre"
    ],
    "name:ceb_x_preferred":[
        "Vista Alegre"
    ],
    "name:deu_x_preferred":[
        "Vista Alegre"
    ],
    "name:epo_x_preferred":[
        "Vista Alegre"
    ],
    "name:eus_x_preferred":[
        "Vista Alegre"
    ],
    "name:fra_x_preferred":[
        "Vista Alegre"
    ],
    "name:glg_x_preferred":[
        "Vista Alegre"
    ],
    "name:ita_x_preferred":[
        "Vista Alegre"
    ],
    "name:nld_x_preferred":[
        "Vista Alegre"
    ],
    "name:nor_x_preferred":[
        "Vista Alegre"
    ],
    "name:por_x_preferred":[
        "Vista Alegre"
    ],
    "name:spa_x_preferred":[
        "Vista Alegre"
    ],
    "name:srp_x_preferred":[
        "\u0412\u0438\u0441\u0442\u0430 \u0410\u043b\u0435\u0433\u0440\u0435"
    ],
    "name:swe_x_preferred":[
        "Vista Alegre"
    ],
    "wof:name":"Vista Alegre",
    "wof:placetype":"locality"
},
  "geometry": {"coordinates":[-8.68428,40.59002],"type":"Point"}
}