{
  "type": "Feature",
  "properties": {
    "gn:admin1_code":"2.0",
    "gn:admin2_code":"0119",
    "gn:admin3_code":"11902.0",
    "gn:asciiname":"Janardo",
    "gn:country_code":"PT",
    "gn:dem":561,
    "gn:feature_class":"P",
    "gn:feature_code":"PPL",
    "gn:name":"Janardo",
    "gn:population":0,
    "gn:timezone":"Europe/Lisbon",
    "iso:country":"PT",
    "wof:name":"Janardo",
    "wof:placetype":"locality"
},
  "geometry": {"coordinates":[-8.39837,40.79695],"type":"Point"}
}