{
  "type": "Feature",
  "properties": {
    "gn:admin1_code":"11.0",
    "gn:admin2_code":"0906",
    "gn:admin3_code":"90608.0",
    "gn:asciiname":"Mangualde da Serra",
    "gn:country_code":"PT",
    "gn:dem":707,
    "gn:feature_class":"P",
    "gn:feature_code":"PPL",
    "gn:name":"Mangualde da Serra",
    "gn:population":0,
    "gn:timezone":"Europe/Lisbon",
    "iso:country":"PT",
    "wof:name":"Mangualde da Serra",
    "wof:placetype":"locality"
},
  "geometry": {"coordinates":[-7.6212,40.46669],"type":"Point"}
}