{
  "type": "Feature",
  "properties": {
    "gn:admin1_code":"20.0",
    "gn:admin2_code":"1609",
    "gn:admin3_code":"160905.0",
    "gn:asciiname":"Lugar do Meio",
    "gn:country_code":"PT",
    "gn:dem":40,
    "gn:feature_class":"P",
    "gn:feature_code":"PPL",
    "gn:name":"Lugar do Meio",
    "gn:population":0,
    "gn:timezone":"Europe/Lisbon",
    "iso:country":"PT",
    "wof:name":"Lugar do Meio",
    "wof:placetype":"locality"
},
  "geometry": {"coordinates":[-8.85061,41.7147],"type":"Point"}
}