{
  "type": "Feature",
  "properties": {
    "gn:admin1_code":"06",
    "gn:admin2_code":"0506",
    "gn:admin3_code":"50611.0",
    "gn:asciiname":"Roda de Baixo",
    "gn:country_code":"PT",
    "gn:dem":488,
    "gn:feature_class":"P",
    "gn:feature_code":"PPL",
    "gn:name":"Roda de Baixo",
    "gn:population":0,
    "gn:timezone":"Europe/Lisbon",
    "iso:country":"PT",
    "wof:name":"Roda de Baixo",
    "wof:placetype":"locality"
},
  "geometry": {"coordinates":[-8.01164,39.94404],"type":"Point"}
}