{
  "type": "Feature",
  "properties": {
    "gn:admin1_code":"11",
    "gn:admin2_code":"0904",
    "gn:admin3_code":"90416.0",
    "gn:asciiname":"Vilar de Amargo",
    "gn:country_code":"PT",
    "gn:dem":613,
    "gn:feature_class":"P",
    "gn:feature_code":"PPL",
    "gn:name":"Vilar de Amargo",
    "gn:population":0,
    "gn:timezone":"Europe/Lisbon",
    "iso:country":"PT",
    "wof:name":"Vilar de Amargo",
    "wof:placetype":"locality"
},
  "geometry": {"coordinates":[-7.01384,40.94468],"type":"Point"}
}