{
  "type": "Feature",
  "properties": {
    "gn:admin1_code":"4.0",
    "gn:admin2_code":"0303",
    "gn:admin3_code":"30311.0",
    "gn:asciiname":"Escudeiros",
    "gn:country_code":"PT",
    "gn:dem":231,
    "gn:feature_class":"P",
    "gn:feature_code":"PPL",
    "gn:name":"Escudeiros",
    "gn:population":0,
    "gn:timezone":"Europe/Lisbon",
    "iso:country":"PT",
    "wof:name":"Escudeiros",
    "wof:placetype":"locality"
},
  "geometry": {"coordinates":[-8.42824,41.47755],"type":"Point"}
}