{
  "type": "Feature",
  "properties": {
    "gn:admin1_code":"11",
    "gn:admin2_code":"0912",
    "gn:admin3_code":"91222.0",
    "gn:asciiname":"Torrozelo",
    "gn:country_code":"PT",
    "gn:dem":564,
    "gn:feature_class":"P",
    "gn:feature_code":"PPL",
    "gn:name":"Torrozelo",
    "gn:population":0,
    "gn:timezone":"Europe/Lisbon",
    "iso:country":"PT",
    "wof:name":"Torrozelo",
    "wof:placetype":"locality"
},
  "geometry": {"coordinates":[-7.76208,40.38679000000001],"type":"Point"}
}