{
  "type": "Feature",
  "properties": {
    "gn:admin1_code":"20.0",
    "gn:admin2_code":"1610",
    "gn:admin3_code":"161011.0",
    "gn:asciiname":"Bemposta",
    "gn:country_code":"PT",
    "gn:dem":59,
    "gn:feature_class":"P",
    "gn:feature_code":"PPL",
    "gn:name":"Bemposta",
    "gn:population":0,
    "gn:timezone":"Europe/Lisbon",
    "iso:country":"PT",
    "name:ceb_x_preferred":[
        "Bemposta"
    ],
    "name:deu_x_preferred":[
        "Bemposta"
    ],
    "name:fra_x_preferred":[
        "Bemposta"
    ],
    "name:glg_x_preferred":[
        "Bemposta"
    ],
    "name:nld_x_preferred":[
        "Bemposta"
    ],
    "name:por_x_preferred":[
        "Bemposta"
    ],
    "wof:name":"Bemposta",
    "wof:placetype":"locality"
},
  "geometry": {"coordinates":[-8.70929,41.96006],"type":"Point"}
}