{
  "type": "Feature",
  "properties": {
    "gn:admin1_code":"4.0",
    "gn:admin2_code":"0308",
    "gn:admin3_code":"30809.0",
    "gn:asciiname":"Calvos",
    "gn:country_code":"PT",
    "gn:dem":325,
    "gn:feature_class":"P",
    "gn:feature_code":"PPL",
    "gn:name":"Calvos",
    "gn:population":0,
    "gn:timezone":"Europe/Lisbon",
    "iso:country":"PT",
    "wof:name":"Calvos",
    "wof:placetype":"locality"
},
  "geometry": {"coordinates":[-8.24466,41.40557],"type":"Point"}
}