{
  "type": "Feature",
  "properties": {
    "gn:admin1_code":"09",
    "gn:admin2_code":"0813",
    "gn:admin3_code":"81307.0",
    "gn:asciiname":"Norinha",
    "gn:country_code":"PT",
    "gn:dem":33,
    "gn:feature_class":"P",
    "gn:feature_code":"PPL",
    "gn:name":"Norinha",
    "gn:population":0,
    "gn:timezone":"Europe/Lisbon",
    "iso:country":"PT",
    "wof:name":"Norinha",
    "wof:placetype":"locality"
},
  "geometry": {"coordinates":[-8.40734,37.20983],"type":"Point"}
}