{
  "type": "Feature",
  "properties": {
    "gn:admin1_code":"03",
    "gn:admin2_code":"0202",
    "gn:admin3_code":"20206.0",
    "gn:asciiname":"Moimentos",
    "gn:country_code":"PT",
    "gn:dem":488,
    "gn:feature_class":"P",
    "gn:feature_code":"PPL",
    "gn:name":"Moimentos",
    "gn:population":0,
    "gn:timezone":"Europe/Lisbon",
    "iso:country":"PT",
    "wof:name":"Moimentos",
    "wof:placetype":"locality"
},
  "geometry": {"coordinates":[-8.06222,37.36059],"type":"Point"}
}