{
  "type": "Feature",
  "properties": {
    "gn:country":"PT",
    "gn:fcode":"ADM3",
    "gn:population":0,
    "iso:country":"PT",
    "name:ast_x_preferred":[
        "T\u00f4r"
    ],
    "name:ceb_x_preferred":[
        "T\u00f4r"
    ],
    "name:che_x_preferred":[
        "\u0422\u043e\u0440"
    ],
    "name:deu_x_preferred":[
        "T\u00f4r"
    ],
    "name:eng_x_preferred":[
        "T\u00f4r"
    ],
    "name:fra_x_preferred":[
        "T\u00f4r"
    ],
    "name:kaz_x_preferred":[
        "\u0422\u043e\u0440"
    ],
    "name:nld_x_preferred":[
        "T\u00f4r"
    ],
    "name:por_x_preferred":[
        "T\u00f4r"
    ],
    "name:rus_x_preferred":[
        "\u0422\u043e\u0440"
    ],
    "name:spa_x_preferred":[
        "T\u00f4r"
    ],
    "name:tat_x_preferred":[
        "\u0422\u043e\u0440"
    ],
    "name:tur_x_preferred":[
        "T\u00f4r"
    ],
    "qs_pg:aaroncc":"PT",
    "qs_pg:gn_country":"PT",
    "qs_pg:gn_fcode":"ADM3",
    "qs_pg:gn_pop":0,
    "qs_pg:name":"T\u00f4r",
    "qs_pg:name_adm0":"Portugal",
    "qs_pg:name_adm1":"Faro",
    "qs_pg:photos_9r":0,
    "qs_pg:photos_sr":0,
    "qs_pg:pop_sr":0,
    "qs_pg:qs_pg_placetype":"locality",
    "qs_pg:qs_pg_placetype_gp":"Town",
    "qs_pg:woe_adm0":23424925,
    "woe:adm0_id":23424925,
    "woe:name_adm0":"Portugal",
    "woe:name_adm1":"Faro",
    "woe:placetype":"Town",
    "wof:name":"T\u00f4r",
    "wof:placetype":"locality"
},
  "geometry": {"coordinates":[-8.04105,37.19556],"type":"Point"}
}