{
  "type": "Feature",
  "properties": {
    "gn:admin1_code":"18",
    "gn:admin2_code":"1416",
    "gn:admin3_code":"141627.0",
    "gn:asciiname":"Outeiro da Varzea",
    "gn:country_code":"PT",
    "gn:dem":59,
    "gn:feature_class":"P",
    "gn:feature_code":"PPL",
    "gn:name":"Outeiro da V\u00e1rzea",
    "gn:population":0,
    "gn:timezone":"Europe/Lisbon",
    "iso:country":"PT",
    "wof:name":"Outeiro da Varzea",
    "wof:placetype":"locality"
},
  "geometry": {"coordinates":[-8.75,39.28333],"type":"Point"}
}