{
  "type": "Feature",
  "properties": {
    "gn:admin1_code":"18",
    "gn:admin2_code":"1403",
    "gn:admin3_code":"140303.0",
    "gn:asciiname":"Pacos Negros",
    "gn:country_code":"PT",
    "gn:dem":76,
    "gn:feature_class":"P",
    "gn:feature_code":"PPL",
    "gn:name":"Pa\u00e7os Negros",
    "gn:population":0,
    "gn:timezone":"Europe/Lisbon",
    "iso:country":"PT",
    "wof:name":"Pacos Negros",
    "wof:placetype":"locality"
},
  "geometry": {"coordinates":[-8.54701,39.15705],"type":"Point"}
}