{
  "type": "Feature",
  "properties": {
    "gn:admin1_code":"23.0",
    "gn:admin2_code":"4501",
    "gn:admin3_code":"450103.0",
    "gn:asciiname":"Faja da Caldeira de Santo Cristo",
    "gn:country_code":"PT",
    "gn:dem":10,
    "gn:feature_class":"P",
    "gn:feature_code":"PPL",
    "gn:name":"Faj\u00e3 da Caldeira de Santo Cristo",
    "gn:population":0,
    "gn:timezone":"Atlantic/Azores",
    "iso:country":"PT",
    "wof:name":"Faja da Caldeira de Santo Cristo",
    "wof:placetype":"locality"
},
  "geometry": {"coordinates":[-27.9294,38.62488],"type":"Point"}
}