{
  "type": "Feature",
  "properties": {
    "gn:admin1_code":"7.0",
    "gn:admin2_code":"0605",
    "gn:admin3_code":"60506.0",
    "gn:asciiname":"Carvalhais",
    "gn:country_code":"PT",
    "gn:dem":82,
    "gn:feature_class":"P",
    "gn:feature_code":"PPL",
    "gn:name":"Carvalhais",
    "gn:population":0,
    "gn:timezone":"Europe/Lisbon",
    "iso:country":"PT",
    "wof:name":"Carvalhais",
    "wof:placetype":"locality"
},
  "geometry": {"coordinates":[-8.82044,40.06944],"type":"Point"}
}