{
  "type": "Feature",
  "properties": {
    "gn:admin1_code":"22.0",
    "gn:admin2_code":"1803",
    "gn:admin3_code":"180307.0",
    "gn:asciiname":"Faifa",
    "gn:country_code":"PT",
    "gn:dem":887,
    "gn:feature_class":"P",
    "gn:feature_code":"PPL",
    "gn:name":"Faifa",
    "gn:population":0,
    "gn:timezone":"Europe/Lisbon",
    "iso:country":"PT",
    "wof:name":"Faifa",
    "wof:placetype":"locality"
},
  "geometry": {"coordinates":[-8.00423,40.95094],"type":"Point"}
}