{
  "type": "Feature",
  "properties": {
    "gn:admin1_code":"7.0",
    "gn:admin2_code":"0613",
    "gn:admin3_code":"61301.0",
    "gn:asciiname":"Cerquedo",
    "gn:country_code":"PT",
    "gn:dem":327,
    "gn:feature_class":"P",
    "gn:feature_code":"PPL",
    "gn:name":"Cerquedo",
    "gn:population":0,
    "gn:timezone":"Europe/Lisbon",
    "iso:country":"PT",
    "wof:name":"Cerquedo",
    "wof:placetype":"locality"
},
  "geometry": {"coordinates":[-8.34252,40.36033],"type":"Point"}
}