{
  "type": "Feature",
  "properties": {
    "gn:admin1_code":"4.0",
    "gn:admin2_code":"0310",
    "gn:admin3_code":"31012.0",
    "gn:asciiname":"Campo",
    "gn:country_code":"PT",
    "gn:dem":195,
    "gn:feature_class":"P",
    "gn:feature_code":"PPL",
    "gn:name":"Campo",
    "gn:population":0,
    "gn:timezone":"Europe/Lisbon",
    "iso:country":"PT",
    "name:arg_x_preferred":[
        "Campo"
    ],
    "name:bre_x_preferred":[
        "Campo"
    ],
    "name:cat_x_preferred":[
        "Campo"
    ],
    "name:ceb_x_preferred":[
        "Campo"
    ],
    "name:deu_x_preferred":[
        "Campo"
    ],
    "name:epo_x_preferred":[
        "Campo"
    ],
    "name:fas_x_preferred":[
        "\u06a9\u0645\u067e\u0648"
    ],
    "name:fra_x_preferred":[
        "Campo"
    ],
    "name:glg_x_preferred":[
        "Campo"
    ],
    "name:ita_x_preferred":[
        "Campo"
    ],
    "name:nld_x_preferred":[
        "Campo"
    ],
    "name:pol_x_preferred":[
        "Campo"
    ],
    "name:por_x_preferred":[
        "Campo"
    ],
    "name:rus_x_preferred":[
        "\u041a\u0430\u043c\u043f\u0443"
    ],
    "name:spa_x_preferred":[
        "Campo"
    ],
    "name:swe_x_preferred":[
        "Campo"
    ],
    "name:ukr_x_preferred":[
        "\u041a\u0430\u043c\u043f\u0443"
    ],
    "name:vec_x_preferred":[
        "Canpo"
    ],
    "name:vol_x_preferred":[
        "Campo"
    ],
    "wof:name":"Campo",
    "wof:placetype":"locality"
},
  "geometry": {"coordinates":[-8.32971,41.6992],"type":"Point"}
}