{
  "type": "Feature",
  "properties": {
    "gn:admin1_code":"4.0",
    "gn:admin2_code":"0310",
    "gn:admin3_code":"31012.0",
    "gn:asciiname":"Campo",
    "gn:country_code":"PT",
    "gn:dem":195,
    "gn:feature_class":"P",
    "gn:feature_code":"PPL",
    "gn:name":"Campo",
    "gn:population":0,
    "gn:timezone":"Europe/Lisbon",
    "iso:country":"PT",
    "wof:name":"Campo",
    "wof:placetype":"locality"
},
  "geometry": {"coordinates":[-8.32971,41.6992],"type":"Point"}
}