{
  "type": "Feature",
  "properties": {
    "gn:admin1_code":"04",
    "gn:admin2_code":"0303",
    "gn:admin3_code":"30323.0",
    "gn:asciiname":"Ventoso",
    "gn:country_code":"PT",
    "gn:dem":172,
    "gn:feature_class":"P",
    "gn:feature_code":"PPL",
    "gn:name":"Ventoso",
    "gn:population":0,
    "gn:timezone":"Europe/Lisbon",
    "iso:country":"PT",
    "name:ceb_x_preferred":[
        "Ventoso"
    ],
    "name:fas_x_preferred":[
        "\u0648\u0646\u062a\u0633\u0648"
    ],
    "name:ita_x_preferred":[
        "Ventoso"
    ],
    "name:ltz_x_preferred":[
        "Ventoso"
    ],
    "name:spa_x_preferred":[
        "Ventoso"
    ],
    "name:ukr_x_preferred":[
        "\u0412\u0435\u043d\u0442\u043e\u0441\u043e"
    ],
    "wof:name":"Ventoso",
    "wof:placetype":"locality"
},
  "geometry": {"coordinates":[-8.42705,41.52617],"type":"Point"}
}