{
  "type": "Feature",
  "properties": {
    "gn:admin1_code":"04",
    "gn:admin2_code":"0303",
    "gn:admin3_code":"30323.0",
    "gn:asciiname":"Ventoso",
    "gn:country_code":"PT",
    "gn:dem":172,
    "gn:feature_class":"P",
    "gn:feature_code":"PPL",
    "gn:name":"Ventoso",
    "gn:population":0,
    "gn:timezone":"Europe/Lisbon",
    "iso:country":"PT",
    "wof:name":"Ventoso",
    "wof:placetype":"locality"
},
  "geometry": {"coordinates":[-8.42705,41.52617],"type":"Point"}
}