{
  "type": "Feature",
  "properties": {
    "gn:admin1_code":"20",
    "gn:admin2_code":"1605",
    "gn:admin3_code":"160508.0",
    "gn:asciiname":"Vale",
    "gn:country_code":"PT",
    "gn:dem":389,
    "gn:feature_class":"P",
    "gn:feature_code":"PPL",
    "gn:name":"Vale",
    "gn:population":0,
    "gn:timezone":"Europe/Lisbon",
    "iso:country":"PT",
    "wof:name":"Vale",
    "wof:placetype":"locality"
},
  "geometry": {"coordinates":[-8.58154,41.93815],"type":"Point"}
}