{
  "type": "Feature",
  "properties": {
    "gn:admin1_code":"11",
    "gn:admin2_code":"0912",
    "gn:admin3_code":"91201.0",
    "gn:asciiname":"Vasco Esteves de Cima",
    "gn:country_code":"PT",
    "gn:dem":638,
    "gn:feature_class":"P",
    "gn:feature_code":"PPL",
    "gn:name":"Vasco Esteves de Cima",
    "gn:population":0,
    "gn:timezone":"Europe/Lisbon",
    "iso:country":"PT",
    "wof:name":"Vasco Esteves de Cima",
    "wof:placetype":"locality"
},
  "geometry": {"coordinates":[-7.70944,40.27349],"type":"Point"}
}