{
  "type": "Feature",
  "properties": {
    "gn:admin1_code":"18",
    "gn:admin2_code":"1421",
    "gn:admin3_code":"142106.0",
    "gn:asciiname":"Moita",
    "gn:country_code":"PT",
    "gn:dem":376,
    "gn:feature_class":"P",
    "gn:feature_code":"PPL",
    "gn:name":"Moita",
    "gn:population":0,
    "gn:timezone":"Europe/Lisbon",
    "iso:country":"PT",
    "wof:name":"Moita",
    "wof:placetype":"locality"
},
  "geometry": {"coordinates":[-8.67315,39.63963],"type":"Point"}
}