{
  "type": "Feature",
  "properties": {
    "gn:admin1_code":"11",
    "gn:admin2_code":"0910",
    "gn:admin3_code":"91021.0",
    "gn:asciiname":"Safurdao",
    "gn:country_code":"PT",
    "gn:dem":771,
    "gn:feature_class":"P",
    "gn:feature_code":"PPL",
    "gn:name":"Safurd\u00e3o",
    "gn:population":0,
    "gn:timezone":"Europe/Lisbon",
    "iso:country":"PT",
    "name:und_x_variant":[
        "Safurd\u00e3o"
    ],
    "wof:name":"Safurdao",
    "wof:placetype":"locality"
},
  "geometry": {"coordinates":[-7.06959,40.63806],"type":"Point"}
}