{
  "type": "Feature",
  "properties": {
    "gn:admin1_code":"20.0",
    "gn:admin2_code":"1605",
    "gn:admin3_code":"160501.0",
    "gn:asciiname":"Cabanas",
    "gn:country_code":"PT",
    "gn:dem":297,
    "gn:feature_class":"P",
    "gn:feature_code":"PPL",
    "gn:name":"Cabanas",
    "gn:population":0,
    "gn:timezone":"Europe/Lisbon",
    "iso:country":"PT",
    "wof:name":"Cabanas",
    "wof:placetype":"locality"
},
  "geometry": {"coordinates":[-8.61617,41.87301],"type":"Point"}
}