{
  "type": "Feature",
  "properties": {
    "gn:admin1_code":"4.0",
    "gn:admin2_code":"0303",
    "gn:admin3_code":"30313.0",
    "gn:asciiname":"Alem",
    "gn:country_code":"PT",
    "gn:dem":175,
    "gn:feature_class":"P",
    "gn:feature_code":"PPL",
    "gn:name":"Al\u00e9m",
    "gn:population":0,
    "gn:timezone":"Europe/Lisbon",
    "iso:country":"PT",
    "wof:name":"Alem",
    "wof:placetype":"locality"
},
  "geometry": {"coordinates":[-8.41968,41.50789],"type":"Point"}
}