{
  "type": "Feature",
  "properties": {
    "gn:admin1_code":"7.0",
    "gn:admin2_code":"0610",
    "gn:admin3_code":"61010.0",
    "gn:asciiname":"Carapetos",
    "gn:country_code":"PT",
    "gn:dem":81,
    "gn:feature_class":"P",
    "gn:feature_code":"PPL",
    "gn:name":"Carapetos",
    "gn:population":0,
    "gn:timezone":"Europe/Lisbon",
    "iso:country":"PT",
    "wof:name":"Carapetos",
    "wof:placetype":"locality"
},
  "geometry": {"coordinates":[-8.667,40.23625],"type":"Point"}
}