{
  "type": "Feature",
  "properties": {
    "gn:admin1_code":"21.0",
    "gn:admin2_code":"1714",
    "gn:admin3_code":"171421.0",
    "gn:asciiname":"Gontaes",
    "gn:country_code":"PT",
    "gn:dem":781,
    "gn:feature_class":"P",
    "gn:feature_code":"PPL",
    "gn:name":"Gont\u00e3es",
    "gn:population":0,
    "gn:timezone":"Europe/Lisbon",
    "iso:country":"PT",
    "wof:name":"Gontaes",
    "wof:placetype":"locality"
},
  "geometry": {"coordinates":[-7.8376,41.29896],"type":"Point"}
}