{
  "type": "Feature",
  "properties": {
    "gn:admin1_code":"09",
    "gn:admin2_code":"0803",
    "gn:admin3_code":"80301.0",
    "gn:asciiname":"Aldeia Nova",
    "gn:country_code":"PT",
    "gn:dem":66,
    "gn:feature_class":"P",
    "gn:feature_code":"PPL",
    "gn:name":"Aldeia Nova",
    "gn:population":0,
    "gn:timezone":"Europe/Lisbon",
    "iso:country":"PT",
    "wof:name":"Aldeia Nova",
    "wof:placetype":"locality"
},
  "geometry": {"coordinates":[-8.78484,37.31814],"type":"Point"}
}