{
  "type": "Feature",
  "properties": {
    "gn:gn_country":"PT",
    "gn:gn_fcode":"PPL",
    "gn:gn_pop":39420,
    "gn:population":39420,
    "iso:country":"PT",
    "name:ara_x_preferred":[
        "\u0625\u064a\u0631\u0645\u064a\u0633\u0646\u062f\u064a"
    ],
    "name:ast_x_preferred":[
        "Ermesinde"
    ],
    "name:ceb_x_preferred":[
        "Ermesinde"
    ],
    "name:dan_x_preferred":[
        "Ermesinde"
    ],
    "name:deu_x_preferred":[
        "Ermesinde"
    ],
    "name:eng_x_preferred":[
        "Ermesinde"
    ],
    "name:fas_x_preferred":[
        "\u0627\u0631\u0645\u0633\u06cc\u0646\u062f\u0647"
    ],
    "name:fra_x_preferred":[
        "Ermesinde"
    ],
    "name:kat_x_preferred":[
        "\u10d4\u10e0\u10db\u10d4\u10d6\u10d8\u10dc\u10d3\u10d4"
    ],
    "name:kaz_x_preferred":[
        "\u042d\u0440\u043c\u0435\u0437\u0438\u043d\u0434\u0435"
    ],
    "name:mzn_x_preferred":[
        "\u0627\u0631\u0645\u0633\u06cc\u0646\u062f\u0647"
    ],
    "name:nan_x_preferred":[
        "Ermesinde"
    ],
    "name:nld_x_preferred":[
        "Ermesinde"
    ],
    "name:nob_x_preferred":[
        "Ermesinde"
    ],
    "name:por_x_preferred":[
        "Ermesinde"
    ],
    "name:ron_x_preferred":[
        "Ermesinde"
    ],
    "name:rus_x_preferred":[
        "\u042d\u0440\u043c\u0435\u0437\u0438\u043d\u0434\u0435"
    ],
    "name:slk_x_preferred":[
        "Ermesinde"
    ],
    "name:spa_x_preferred":[
        "Ermesinde"
    ],
    "name:tur_x_preferred":[
        "Ermesinde"
    ],
    "name:zho_x_preferred":[
        "Ermesinde"
    ],
    "qs_pg:aaroncc":"PT",
    "qs_pg:gn_country":"PT",
    "qs_pg:gn_fcode":"PPL",
    "qs_pg:gn_pop":39420,
    "qs_pg:name":"Ermezinde",
    "qs_pg:photos_9r":0,
    "qs_pg:photos_sr":0,
    "qs_pg:pop_sr":7,
    "qs_pg:qs_pg_placetype":"locality",
    "wof:name":"Ermezinde",
    "wof:placetype":"locality",
    "wof:population":39420
},
  "geometry": {"coordinates":[-8.55462,41.22176],"type":"Point"}
}