{
  "type": "Feature",
  "properties": {
    "gn:admin1_code":"07",
    "gn:admin2_code":"0604",
    "gn:admin3_code":"60408.0",
    "gn:asciiname":"Sebal Grande",
    "gn:country_code":"PT",
    "gn:dem":32,
    "gn:feature_class":"P",
    "gn:feature_code":"PPL",
    "gn:name":"Sebal Grande",
    "gn:population":0,
    "gn:timezone":"Europe/Lisbon",
    "iso:country":"PT",
    "name:und_x_variant":[
        "Sebal",
        "Sebal Grande"
    ],
    "wof:name":"Sebal Grande",
    "wof:placetype":"locality"
},
  "geometry": {"coordinates":[-8.5351,40.12007],"type":"Point"}
}