{
  "type": "Feature",
  "properties": {
    "gn:admin1_code":"20",
    "gn:admin2_code":"1609",
    "gn:admin3_code":"160938.0",
    "gn:asciiname":"Vila de Punhe",
    "gn:country_code":"PT",
    "gn:dem":102,
    "gn:feature_class":"P",
    "gn:feature_code":"PPL",
    "gn:name":"Vila de Punhe",
    "gn:population":0,
    "gn:timezone":"Europe/Lisbon",
    "iso:country":"PT",
    "wof:name":"Vila de Punhe",
    "wof:placetype":"locality"
},
  "geometry": {"coordinates":[-8.73456,41.6576],"type":"Point"}
}