{
  "type": "Feature",
  "properties": {
    "gn:admin1_code":"17",
    "gn:admin2_code":"1316",
    "gn:admin3_code":"131628.0",
    "gn:asciiname":"Povoacao",
    "gn:country_code":"PT",
    "gn:dem":25,
    "gn:feature_class":"P",
    "gn:feature_code":"PPL",
    "gn:name":"Povoa\u00e7\u00e3o",
    "gn:population":0,
    "gn:timezone":"Europe/Lisbon",
    "iso:country":"PT",
    "wof:name":"Povoacao",
    "wof:placetype":"locality"
},
  "geometry": {"coordinates":[-8.75,41.36667],"type":"Point"}
}