{
  "type": "Feature",
  "properties": {
    "gn:admin1_code":"09",
    "gn:admin2_code":"0813",
    "gn:admin3_code":"81306.0",
    "gn:asciiname":"Baiao",
    "gn:country_code":"PT",
    "gn:dem":135,
    "gn:feature_class":"P",
    "gn:feature_code":"PPL",
    "gn:name":"Bai\u00e3o",
    "gn:population":0,
    "gn:timezone":"Europe/Lisbon",
    "iso:country":"PT",
    "wof:name":"Baiao",
    "wof:placetype":"locality"
},
  "geometry": {"coordinates":[-8.33593,37.38755],"type":"Point"}
}