{
  "type": "Feature",
  "properties": {
    "gn:admin1_code":"14",
    "gn:admin2_code":"1113",
    "gn:admin3_code":"111308.0",
    "gn:asciiname":"Messejana",
    "gn:country_code":"PT",
    "gn:dem":91,
    "gn:feature_class":"P",
    "gn:feature_code":"PPL",
    "gn:name":"Messejana",
    "gn:population":0,
    "gn:timezone":"Europe/Lisbon",
    "iso:country":"PT",
    "wof:name":"Messejana",
    "wof:placetype":"locality"
},
  "geometry": {"coordinates":[-9.15096,39.16013],"type":"Point"}
}