{
  "type": "Feature",
  "properties": {
    "gn:admin1_code":"23.0",
    "gn:admin2_code":"4302",
    "gn:admin3_code":"430206.0",
    "gn:asciiname":"Malicias",
    "gn:country_code":"PT",
    "gn:dem":80,
    "gn:feature_class":"P",
    "gn:feature_code":"PPL",
    "gn:name":"Mal\u00edcias",
    "gn:population":0,
    "gn:timezone":"Atlantic/Azores",
    "iso:country":"PT",
    "wof:name":"Malicias",
    "wof:placetype":"locality"
},
  "geometry": {"coordinates":[-27.11667000000001,38.76667],"type":"Point"}
}