{
  "type": "Feature",
  "properties": {
    "gn:admin1_code":"13",
    "gn:admin2_code":"1015",
    "gn:admin3_code":"101509.0",
    "gn:asciiname":"Vinagres",
    "gn:country_code":"PT",
    "gn:dem":119,
    "gn:feature_class":"P",
    "gn:feature_code":"PPL",
    "gn:name":"Vinagres",
    "gn:population":0,
    "gn:timezone":"Europe/Lisbon",
    "iso:country":"PT",
    "wof:name":"Vinagres",
    "wof:placetype":"locality"
},
  "geometry": {"coordinates":[-8.61741,39.92273],"type":"Point"}
}