{
  "type": "Feature",
  "properties": {
    "gn:admin1_code":"5.0",
    "gn:admin2_code":"0407",
    "gn:admin3_code":"40706.0",
    "gn:asciiname":"Avidagos",
    "gn:country_code":"PT",
    "gn:dem":551,
    "gn:feature_class":"P",
    "gn:feature_code":"PPL",
    "gn:name":"Avidagos",
    "gn:population":0,
    "gn:timezone":"Europe/Lisbon",
    "iso:country":"PT",
    "wof:name":"Avidagos",
    "wof:placetype":"locality"
},
  "geometry": {"coordinates":[-7.30721,41.40055],"type":"Point"}
}