{
  "type": "Feature",
  "properties": {
    "gn:admin1_code":"4.0",
    "gn:admin2_code":"0304",
    "gn:admin3_code":"30415.0",
    "gn:asciiname":"Moscoso",
    "gn:country_code":"PT",
    "gn:dem":881,
    "gn:feature_class":"P",
    "gn:feature_code":"PPL",
    "gn:name":"Moscoso",
    "gn:population":0,
    "gn:timezone":"Europe/Lisbon",
    "iso:country":"PT",
    "name:deu_x_preferred":[
        "Moscoso"
    ],
    "name:fra_x_preferred":[
        "Moscoso"
    ],
    "name:glg_x_preferred":[
        "Moscoso"
    ],
    "wof:name":"Moscoso",
    "wof:placetype":"locality"
},
  "geometry": {"coordinates":[-7.92348,41.58325],"type":"Point"}
}