{
  "type": "Feature",
  "properties": {
    "gn:admin1_code":"08",
    "gn:admin2_code":"0711",
    "gn:admin3_code":"71101.0",
    "gn:asciiname":"Monte Roncao",
    "gn:country_code":"PT",
    "gn:dem":189,
    "gn:feature_class":"P",
    "gn:feature_code":"PPL",
    "gn:name":"Monte Ronc\u00e3o",
    "gn:population":0,
    "gn:timezone":"Europe/Lisbon",
    "iso:country":"PT",
    "wof:name":"Monte Roncao",
    "wof:placetype":"locality"
},
  "geometry": {"coordinates":[-7.44103,38.30851],"type":"Point"}
}