{
  "type": "Feature",
  "properties": {
    "gn:admin1_code":"21.0",
    "gn:admin2_code":"1714",
    "gn:admin3_code":"171429.0",
    "gn:asciiname":"Arnal",
    "gn:country_code":"PT",
    "gn:dem":911,
    "gn:feature_class":"P",
    "gn:feature_code":"PPL",
    "gn:name":"Arnal",
    "gn:population":0,
    "gn:timezone":"Europe/Lisbon",
    "iso:country":"PT",
    "wof:name":"Arnal",
    "wof:placetype":"locality"
},
  "geometry": {"coordinates":[-7.8097,41.33506],"type":"Point"}
}