{
  "type": "Feature",
  "properties": {
    "gn:admin1_code":"17.0",
    "gn:admin2_code":"1302",
    "gn:admin3_code":"130206.0",
    "gn:asciiname":"Eiriz",
    "gn:country_code":"PT",
    "gn:dem":396,
    "gn:feature_class":"P",
    "gn:feature_code":"PPL",
    "gn:name":"Eiriz",
    "gn:population":0,
    "gn:timezone":"Europe/Lisbon",
    "iso:country":"PT",
    "wof:name":"Eiriz",
    "wof:placetype":"locality"
},
  "geometry": {"coordinates":[-8.05849,41.12374000000001],"type":"Point"}
}