{
  "type": "Feature",
  "properties": {
    "gn:admin1_code":"20",
    "gn:admin2_code":"1605",
    "gn:admin3_code":"160511.0",
    "gn:asciiname":"Vilarinho",
    "gn:country_code":"PT",
    "gn:dem":509,
    "gn:feature_class":"P",
    "gn:feature_code":"PPL",
    "gn:name":"Vilarinho",
    "gn:population":0,
    "gn:timezone":"Europe/Lisbon",
    "iso:country":"PT",
    "name:ceb_x_preferred":[
        "Vilarinho"
    ],
    "name:deu_x_preferred":[
        "Vilarinho"
    ],
    "name:fra_x_preferred":[
        "Vilarinho"
    ],
    "name:kaz_x_preferred":[
        "\u0412\u0438\u043b\u0430\u0440\u0438\u043d\u044c\u044e"
    ],
    "name:nld_x_preferred":[
        "Vilarinho"
    ],
    "name:por_x_preferred":[
        "Vilarinho"
    ],
    "name:rus_x_preferred":[
        "\u0412\u0438\u043b\u0430\u0440\u0438\u043d\u044c\u044e"
    ],
    "wof:name":"Vilarinho",
    "wof:placetype":"locality"
},
  "geometry": {"coordinates":[-8.54517,41.95241],"type":"Point"}
}