{
  "type": "Feature",
  "properties": {
    "gn:admin1_code":"20",
    "gn:admin2_code":"1605",
    "gn:admin3_code":"160511.0",
    "gn:asciiname":"Vilarinho",
    "gn:country_code":"PT",
    "gn:dem":509,
    "gn:feature_class":"P",
    "gn:feature_code":"PPL",
    "gn:name":"Vilarinho",
    "gn:population":0,
    "gn:timezone":"Europe/Lisbon",
    "iso:country":"PT",
    "wof:name":"Vilarinho",
    "wof:placetype":"locality"
},
  "geometry": {"coordinates":[-8.54517,41.95241],"type":"Point"}
}