{
  "type": "Feature",
  "properties": {
    "gn:admin1_code":"17.0",
    "gn:admin2_code":"1317",
    "gn:admin3_code":"131704.0",
    "gn:asciiname":"Paniceiro",
    "gn:country_code":"PT",
    "gn:dem":54,
    "gn:feature_class":"P",
    "gn:feature_code":"PPL",
    "gn:name":"Paniceiro",
    "gn:population":0,
    "gn:timezone":"Europe/Lisbon",
    "iso:country":"PT",
    "wof:name":"Paniceiro",
    "wof:placetype":"locality"
},
  "geometry": {"coordinates":[-8.65087,41.12616],"type":"Point"}
}