{
  "type": "Feature",
  "properties": {
    "gn:admin1_code":"18",
    "gn:admin2_code":"1405",
    "gn:admin3_code":"140503.0",
    "gn:asciiname":"Monte dos Condes",
    "gn:country_code":"PT",
    "gn:dem":15,
    "gn:feature_class":"P",
    "gn:feature_code":"PPL",
    "gn:name":"Monte dos Condes",
    "gn:population":0,
    "gn:timezone":"Europe/Lisbon",
    "iso:country":"PT",
    "wof:name":"Monte dos Condes",
    "wof:placetype":"locality"
},
  "geometry": {"coordinates":[-8.77339,38.87612],"type":"Point"}
}