{
  "type": "Feature",
  "properties": {
    "gn:admin1_code":"17.0",
    "gn:admin2_code":"1317",
    "gn:admin3_code":"131701.0",
    "gn:asciiname":"Boavista da Estrada",
    "gn:country_code":"PT",
    "gn:dem":83,
    "gn:feature_class":"P",
    "gn:feature_code":"PPL",
    "gn:name":"Boavista da Estrada",
    "gn:population":0,
    "gn:timezone":"Europe/Lisbon",
    "iso:country":"PT",
    "wof:name":"Boavista da Estrada",
    "wof:placetype":"locality"
},
  "geometry": {"coordinates":[-8.62794,41.06441],"type":"Point"}
}