{
  "type": "Feature",
  "properties": {
    "gn:admin1_code":"20.0",
    "gn:admin2_code":"1606",
    "gn:admin3_code":"160605.0",
    "gn:asciiname":"Crasto",
    "gn:country_code":"PT",
    "gn:dem":127,
    "gn:feature_class":"P",
    "gn:feature_code":"PPL",
    "gn:name":"Crasto",
    "gn:population":0,
    "gn:timezone":"Europe/Lisbon",
    "iso:country":"PT",
    "wof:name":"Crasto",
    "wof:placetype":"locality"
},
  "geometry": {"coordinates":[-8.43006,41.77499],"type":"Point"}
}