{
  "type": "Feature",
  "properties": {
    "gn:admin1_code":"09",
    "gn:admin2_code":"0808",
    "gn:admin3_code":"80809.0",
    "gn:asciiname":"Varejota",
    "gn:country_code":"PT",
    "gn:dem":212,
    "gn:feature_class":"P",
    "gn:feature_code":"PPL",
    "gn:name":"Varejota",
    "gn:population":0,
    "gn:timezone":"Europe/Lisbon",
    "iso:country":"PT",
    "wof:name":"Varejota",
    "wof:placetype":"locality"
},
  "geometry": {"coordinates":[-8.08192,37.16321],"type":"Point"}
}