{
  "type": "Feature",
  "properties": {
    "gn:admin1_code":"18",
    "gn:admin2_code":"1407",
    "gn:admin3_code":"140706.0",
    "gn:asciiname":"Salvador",
    "gn:country_code":"PT",
    "gn:dem":75,
    "gn:feature_class":"P",
    "gn:feature_code":"PPL",
    "gn:name":"Salvador",
    "gn:population":0,
    "gn:timezone":"Europe/Lisbon",
    "iso:country":"PT",
    "name:ara_x_preferred":[
        "\u0633\u0644\u0641\u0627\u062f\u0648\u0631"
    ],
    "name:bpy_x_preferred":[
        "\u09b8\u09be\u09b2\u09ad\u09be\u09a1\u09cb\u09b0"
    ],
    "name:bre_x_preferred":[
        "Salvador"
    ],
    "name:bul_x_preferred":[
        "\u0421\u0430\u043b\u0432\u0430\u0434\u043e\u0440"
    ],
    "name:cat_x_preferred":[
        "Salvador"
    ],
    "name:ceb_x_preferred":[
        "Salvador"
    ],
    "name:ces_x_preferred":[
        "Salvador"
    ],
    "name:cym_x_preferred":[
        "Salvador"
    ],
    "name:deu_x_preferred":[
        "Salvador"
    ],
    "name:epo_x_preferred":[
        "Salvador"
    ],
    "name:est_x_preferred":[
        "Salvador"
    ],
    "name:fas_x_preferred":[
        "\u0633\u0627\u0644\u0648\u0627\u062f\u0648\u0631"
    ],
    "name:fin_x_preferred":[
        "Salvador"
    ],
    "name:fra_x_preferred":[
        "Salvador"
    ],
    "name:glg_x_preferred":[
        "Salvador"
    ],
    "name:heb_x_preferred":[
        "\u05e1\u05dc\u05d1\u05d3\u05d5\u05e8"
    ],
    "name:hrv_x_preferred":[
        "Salvador"
    ],
    "name:hun_x_preferred":[
        "Salvador"
    ],
    "name:ind_x_preferred":[
        "Salvador"
    ],
    "name:ita_x_preferred":[
        "Salvador"
    ],
    "name:jpn_x_preferred":[
        "\u30b5\u30eb\u30d0\u30c9\u30fc\u30eb"
    ],
    "name:kor_x_preferred":[
        "\uc0b4\ubc14\ub3c4\ub974"
    ],
    "name:lav_x_preferred":[
        "Salvadora"
    ],
    "name:nld_x_preferred":[
        "Salvador"
    ],
    "name:oci_x_preferred":[
        "Salvador"
    ],
    "name:pol_x_preferred":[
        "Salwador"
    ],
    "name:por_x_preferred":[
        "Salvador"
    ],
    "name:ron_x_preferred":[
        "Salvador"
    ],
    "name:rus_x_preferred":[
        "\u0421\u0430\u043b\u044c\u0432\u0430\u0434\u043e\u0440"
    ],
    "name:sco_x_preferred":[
        "Salvador"
    ],
    "name:slk_x_preferred":[
        "Salvador"
    ],
    "name:spa_x_preferred":[
        "Salvador"
    ],
    "name:srp_x_preferred":[
        "\u0421\u0430\u043b\u0432\u0430\u0434\u043e\u0440"
    ],
    "name:swe_x_preferred":[
        "Salvador"
    ],
    "name:tha_x_preferred":[
        "\u0e0b\u0e31\u0e25\u0e27\u0e32\u0e14\u0e2d\u0e23\u0e4c"
    ],
    "name:tur_x_preferred":[
        "Salvador"
    ],
    "name:ukr_x_preferred":[
        "\u0421\u0430\u043b\u044c\u0432\u0430\u0434\u043e\u0440"
    ],
    "name:vie_x_preferred":[
        "Salvador"
    ],
    "name:war_x_preferred":[
        "Salvador"
    ],
    "name:zho_x_preferred":[
        "\u85a9\u723e\u74e6\u591a"
    ],
    "wof:name":"Salvador",
    "wof:placetype":"locality"
},
  "geometry": {"coordinates":[-8.40506,39.21118],"type":"Point"}
}