{
  "type": "Feature",
  "properties": {
    "gn:admin1_code":"18",
    "gn:admin2_code":"1407",
    "gn:admin3_code":"140706.0",
    "gn:asciiname":"Salvador",
    "gn:country_code":"PT",
    "gn:dem":75,
    "gn:feature_class":"P",
    "gn:feature_code":"PPL",
    "gn:name":"Salvador",
    "gn:population":0,
    "gn:timezone":"Europe/Lisbon",
    "iso:country":"PT",
    "wof:name":"Salvador",
    "wof:placetype":"locality"
},
  "geometry": {"coordinates":[-8.40506,39.21118],"type":"Point"}
}