{
  "type": "Feature",
  "properties": {
    "gn:admin1_code":"13",
    "gn:admin2_code":"1015",
    "gn:admin3_code":"101510.0",
    "gn:asciiname":"Charneca",
    "gn:country_code":"PT",
    "gn:dem":116,
    "gn:feature_class":"P",
    "gn:feature_code":"PPL",
    "gn:name":"Charneca",
    "gn:population":0,
    "gn:timezone":"Europe/Lisbon",
    "iso:country":"PT",
    "wof:name":"Charneca",
    "wof:placetype":"locality"
},
  "geometry": {"coordinates":[-8.58645,39.97615],"type":"Point"}
}