{
  "type": "Feature",
  "properties": {
    "gn:admin1_code":"23.0",
    "gn:admin2_code":"4203",
    "gn:admin3_code":"420310.0",
    "gn:asciiname":"Varzea",
    "gn:cc2":"PT",
    "gn:country_code":"PT",
    "gn:dem":237,
    "gn:feature_class":"P",
    "gn:feature_code":"PPL",
    "gn:name":"V\u00e1rzea",
    "gn:population":0,
    "gn:timezone":"Atlantic/Azores",
    "iso:country":"PT",
    "name:und_x_variant":[
        "Varsea",
        "V\u00e1rzea"
    ],
    "wof:name":"Varzea",
    "wof:placetype":"locality"
},
  "geometry": {"coordinates":[-25.83333,37.86667],"type":"Point"}
}