{
  "type": "Feature",
  "properties": {
    "gn:admin1_code":"23.0",
    "gn:admin2_code":"4101",
    "gn:admin3_code":"410104.0",
    "gn:asciiname":"Cha de Joao Tome",
    "gn:country_code":"PT",
    "gn:dem":214,
    "gn:feature_class":"P",
    "gn:feature_code":"PPL",
    "gn:name":"Ch\u00e3 de Jo\u00e3o Tom\u00e9",
    "gn:population":0,
    "gn:timezone":"Atlantic/Azores",
    "iso:country":"PT",
    "wof:name":"Cha de Joao Tome",
    "wof:placetype":"locality"
},
  "geometry": {"coordinates":[-25.11667000000001,36.98333],"type":"Point"}
}