{
  "type": "Feature",
  "properties": {
    "gn:admin1_code":"22.0",
    "gn:admin2_code":"1806",
    "gn:admin3_code":"180603.0",
    "gn:asciiname":"Guimaraes de Tavares",
    "gn:country_code":"PT",
    "gn:dem":610,
    "gn:feature_class":"P",
    "gn:feature_code":"PPL",
    "gn:name":"Guimar\u00e3es de Tavares",
    "gn:population":0,
    "gn:timezone":"Europe/Lisbon",
    "iso:country":"PT",
    "wof:name":"Guimaraes de Tavares",
    "wof:placetype":"locality"
},
  "geometry": {"coordinates":[-7.62922,40.60547],"type":"Point"}
}