{
  "type": "Feature",
  "properties": {
    "gn:admin1_code":"22.0",
    "gn:admin2_code":"1806",
    "gn:admin3_code":"180607.0",
    "gn:asciiname":"Fornos de Maceira Dao",
    "gn:country_code":"PT",
    "gn:dem":383,
    "gn:feature_class":"P",
    "gn:feature_code":"PPL",
    "gn:name":"Fornos de Maceira D\u00e3o",
    "gn:population":0,
    "gn:timezone":"Europe/Lisbon",
    "iso:country":"PT",
    "name:und_x_variant":[
        "Fornos de Maceira D\u00e3o"
    ],
    "wof:name":"Fornos de Maceira Dao",
    "wof:placetype":"locality"
},
  "geometry": {"coordinates":[-7.81729,40.61355],"type":"Point"}
}