{
  "type": "Feature",
  "properties": {
    "gn:admin1_code":"06",
    "gn:admin2_code":"0503",
    "gn:admin3_code":"50327.0",
    "gn:asciiname":"Verdelhos",
    "gn:country_code":"PT",
    "gn:dem":588,
    "gn:feature_class":"P",
    "gn:feature_code":"PPL",
    "gn:name":"Verdelhos",
    "gn:population":0,
    "gn:timezone":"Europe/Lisbon",
    "iso:country":"PT",
    "wof:name":"Verdelhos",
    "wof:placetype":"locality"
},
  "geometry": {"coordinates":[-7.46897,40.37526],"type":"Point"}
}