{
  "type": "Feature",
  "properties": {
    "gn:admin1_code":"17.0",
    "gn:admin2_code":"1308",
    "gn:admin3_code":"130804.0",
    "gn:asciiname":"Agrela",
    "gn:country_code":"PT",
    "gn:dem":80,
    "gn:feature_class":"P",
    "gn:feature_code":"PPL",
    "gn:name":"Agrela",
    "gn:population":0,
    "gn:timezone":"Europe/Lisbon",
    "iso:country":"PT",
    "wof:name":"Agrela",
    "wof:placetype":"locality"
},
  "geometry": {"coordinates":[-8.63327,41.21499],"type":"Point"}
}