{
  "type": "Feature",
  "properties": {
    "gn:admin1_code":"18",
    "gn:admin2_code":"1409",
    "gn:admin3_code":"140903.0",
    "gn:asciiname":"Medronheira",
    "gn:country_code":"PT",
    "gn:dem":71,
    "gn:feature_class":"P",
    "gn:feature_code":"PPL",
    "gn:name":"Medronheira",
    "gn:population":0,
    "gn:timezone":"Europe/Lisbon",
    "iso:country":"PT",
    "wof:name":"Medronheira",
    "wof:placetype":"locality"
},
  "geometry": {"coordinates":[-8.48178,39.06115],"type":"Point"}
}