{
  "type": "Feature",
  "properties": {
    "gn:admin1_code":"20.0",
    "gn:admin2_code":"1608",
    "gn:admin3_code":"160813.0",
    "gn:asciiname":"Devesas",
    "gn:country_code":"PT",
    "gn:dem":70,
    "gn:feature_class":"P",
    "gn:feature_code":"PPL",
    "gn:name":"Devesas",
    "gn:population":0,
    "gn:timezone":"Europe/Lisbon",
    "iso:country":"PT",
    "wof:name":"Devesas",
    "wof:placetype":"locality"
},
  "geometry": {"coordinates":[-8.65991,41.96186],"type":"Point"}
}