{
  "type": "Feature",
  "properties": {
    "gn:gn_country":"PT",
    "gn:gn_fcode":"PPL",
    "gn:gn_pop":0,
    "iso:country":"PT",
    "name:cat_x_preferred":[
        "Povoa\u00e7\u00e3o"
    ],
    "name:ceb_x_preferred":[
        "Povoa\u00e7\u00e3o"
    ],
    "name:deu_x_preferred":[
        "Povoa\u00e7\u00e3o"
    ],
    "name:eng_x_preferred":[
        "Povoa\u00e7\u00e3o"
    ],
    "name:fra_x_preferred":[
        "Povoa\u00e7\u00e3o"
    ],
    "name:ita_x_preferred":[
        "Povoa\u00e7\u00e3o"
    ],
    "name:kor_x_preferred":[
        "\ud3ec\ubcf4\uc544\uc0c1"
    ],
    "name:nan_x_preferred":[
        "Povoa\u00e7\u00e3o"
    ],
    "name:nld_x_preferred":[
        "Povoa\u00e7\u00e3o"
    ],
    "name:pol_x_preferred":[
        "Povoa\u00e7\u00e3o"
    ],
    "name:por_x_preferred":[
        "Povoa\u00e7\u00e3o"
    ],
    "name:ron_x_preferred":[
        "Povoa\u00e7\u00e3o"
    ],
    "name:rus_x_preferred":[
        "\u041f\u043e\u0432\u043e\u0430\u0441\u0430\u043d"
    ],
    "name:spa_x_preferred":[
        "Povoa\u00e7\u00e3o"
    ],
    "name:tur_x_preferred":[
        "Povoa\u00e7\u00e3o"
    ],
    "name:ukr_x_preferred":[
        "\u0412\u0456\u043b\u0430-\u0434\u0430-\u041f\u043e\u0432\u0443\u0430\u0441\u0430\u043d"
    ],
    "name:unk_x_variant":[
        "Povoacao do Campo"
    ],
    "name:vie_x_preferred":[
        "Povoa\u00e7\u00e3o"
    ],
    "name:zho_x_preferred":[
        "\u6ce2\u74e6\u6851"
    ],
    "qs_pg:aaroncc":"PT",
    "qs_pg:gn_country":"PT",
    "qs_pg:gn_fcode":"PPL",
    "qs_pg:gn_pop":0,
    "qs_pg:name":"Povoa\u00e7\u00e3o",
    "qs_pg:name_adm0":"Portugal",
    "qs_pg:name_adm1":"Azores",
    "qs_pg:photos":184,
    "qs_pg:photos_1k":37,
    "qs_pg:photos_9k":1,
    "qs_pg:photos_9r":4,
    "qs_pg:photos_all":184,
    "qs_pg:photos_sr":4,
    "qs_pg:pop_sr":0,
    "qs_pg:qs_pg_placetype":"locality",
    "qs_pg:qs_pg_placetype_gp":"Town",
    "qs_pg:woe_adm0":23424925,
    "woe:adm0_id":23424925,
    "woe:name_adm0":"Portugal",
    "woe:name_adm1":"Azores",
    "woe:placetype":"Town",
    "wof:name":"Povoa\u00e7\u00e3o",
    "wof:placetype":"locality"
},
  "geometry": {"coordinates":[-25.25,37.75],"type":"Point"}
}