{
  "type": "Feature",
  "properties": {
    "gn:admin1_code":"4.0",
    "gn:admin2_code":"0304",
    "gn:admin3_code":"30401.0",
    "gn:asciiname":"Abadim",
    "gn:country_code":"PT",
    "gn:dem":589,
    "gn:feature_class":"P",
    "gn:feature_code":"PPL",
    "gn:name":"Abadim",
    "gn:population":0,
    "gn:timezone":"Europe/Lisbon",
    "iso:country":"PT",
    "wof:name":"Abadim",
    "wof:placetype":"locality"
},
  "geometry": {"coordinates":[-7.99155,41.54189],"type":"Point"}
}