{
  "type": "Feature",
  "properties": {
    "gn:admin1_code":"05",
    "gn:admin2_code":"0401",
    "gn:admin3_code":"40114.0",
    "gn:asciiname":"Soeima",
    "gn:country_code":"PT",
    "gn:dem":888,
    "gn:feature_class":"P",
    "gn:feature_code":"PPL",
    "gn:name":"Soeima",
    "gn:population":0,
    "gn:timezone":"Europe/Lisbon",
    "iso:country":"PT",
    "wof:name":"Soeima",
    "wof:placetype":"locality"
},
  "geometry": {"coordinates":[-6.96552,41.43315],"type":"Point"}
}