{
  "type": "Feature",
  "properties": {
    "gn:admin1_code":"5.0",
    "gn:admin2_code":"0402",
    "gn:admin3_code":"40243.0",
    "gn:asciiname":"Palacios",
    "gn:country_code":"PT",
    "gn:dem":833,
    "gn:feature_class":"P",
    "gn:feature_code":"PPL",
    "gn:name":"Pal\u00e1cios",
    "gn:population":0,
    "gn:timezone":"Europe/Lisbon",
    "iso:country":"PT",
    "name:cat_x_preferred":[
        "Palacios"
    ],
    "name:ceb_x_preferred":[
        "Palacios"
    ],
    "name:ces_x_preferred":[
        "Palacios"
    ],
    "name:deu_x_preferred":[
        "Palacios"
    ],
    "name:fra_x_preferred":[
        "Palacios"
    ],
    "name:ita_x_preferred":[
        "Palacios"
    ],
    "name:jpn_x_preferred":[
        "\u30d1\u30e9\u30b7\u30aa\u30b9"
    ],
    "name:nds_x_preferred":[
        "Palacios"
    ],
    "name:rus_x_preferred":[
        "\u041f\u0430\u043b\u0430\u0441\u0438\u043e\u0441"
    ],
    "name:slv_x_preferred":[
        "Palacios"
    ],
    "name:spa_x_preferred":[
        "Palacios"
    ],
    "name:swe_x_preferred":[
        "Palacios"
    ],
    "name:ukr_x_preferred":[
        "\u041f\u0430\u043b\u0430\u0441\u0456\u043e\u0441"
    ],
    "wof:name":"Palacios",
    "wof:placetype":"locality"
},
  "geometry": {"coordinates":[-6.61923,41.81961],"type":"Point"}
}