{
  "type": "Feature",
  "properties": {
    "gn:admin1_code":"4.0",
    "gn:admin2_code":"0302",
    "gn:admin3_code":"30206.0",
    "gn:asciiname":"Penedo do Monte",
    "gn:country_code":"PT",
    "gn:dem":111,
    "gn:feature_class":"P",
    "gn:feature_code":"PPL",
    "gn:name":"Penedo do Monte",
    "gn:population":0,
    "gn:timezone":"Europe/Lisbon",
    "iso:country":"PT",
    "wof:name":"Penedo do Monte",
    "wof:placetype":"locality"
},
  "geometry": {"coordinates":[-8.70446,41.60475],"type":"Point"}
}