{
  "type": "Feature",
  "properties": {
    "gn:admin1_code":"20.0",
    "gn:admin2_code":"1601",
    "gn:admin3_code":"160130.0",
    "gn:asciiname":"Enxerto",
    "gn:country_code":"PT",
    "gn:dem":247,
    "gn:feature_class":"P",
    "gn:feature_code":"PPL",
    "gn:name":"Enxerto",
    "gn:population":0,
    "gn:timezone":"Europe/Lisbon",
    "iso:country":"PT",
    "wof:name":"Enxerto",
    "wof:placetype":"locality"
},
  "geometry": {"coordinates":[-8.45784,41.86381],"type":"Point"}
}