{
  "type": "Feature",
  "properties": {
    "gn:admin1_code":"5.0",
    "gn:admin2_code":"0411",
    "gn:admin3_code":"41104.0",
    "gn:asciiname":"Avelanoso",
    "gn:country_code":"PT",
    "gn:dem":714,
    "gn:feature_class":"P",
    "gn:feature_code":"PPL",
    "gn:name":"Avelanoso",
    "gn:population":0,
    "gn:timezone":"Europe/Lisbon",
    "iso:country":"PT",
    "wof:name":"Avelanoso",
    "wof:placetype":"locality"
},
  "geometry": {"coordinates":[-6.42546,41.65531],"type":"Point"}
}