{
  "type": "Feature",
  "properties": {
    "gn:admin1_code":"04",
    "gn:admin2_code":"0304",
    "gn:admin3_code":"30403.0",
    "gn:asciiname":"Serra",
    "gn:country_code":"PT",
    "gn:dem":203,
    "gn:feature_class":"P",
    "gn:feature_code":"PPL",
    "gn:name":"Serra",
    "gn:population":0,
    "gn:timezone":"Europe/Lisbon",
    "iso:country":"PT",
    "wof:name":"Serra",
    "wof:placetype":"locality"
},
  "geometry": {"coordinates":[-7.96315,41.48986],"type":"Point"}
}