{
  "type": "Feature",
  "properties": {
    "gn:admin1_code":"13",
    "gn:admin2_code":"1015",
    "gn:admin3_code":"101509.0",
    "gn:asciiname":"Melga",
    "gn:country_code":"PT",
    "gn:dem":82,
    "gn:feature_class":"P",
    "gn:feature_code":"PPL",
    "gn:name":"Melga",
    "gn:population":0,
    "gn:timezone":"Europe/Lisbon",
    "iso:country":"PT",
    "name:msa_x_preferred":[
        "Melga"
    ],
    "wof:name":"Melga",
    "wof:placetype":"locality"
},
  "geometry": {"coordinates":[-8.62973,39.88892],"type":"Point"}
}