{
  "type": "Feature",
  "properties": {
    "gn:admin1_code":"09",
    "gn:admin2_code":"0812",
    "gn:admin3_code":"81201.0",
    "gn:asciiname":"Cabeca do Velho",
    "gn:country_code":"PT",
    "gn:dem":422,
    "gn:feature_class":"P",
    "gn:feature_code":"PPL",
    "gn:name":"Cabe\u00e7a do Velho",
    "gn:population":0,
    "gn:timezone":"Europe/Lisbon",
    "iso:country":"PT",
    "wof:name":"Cabeca do Velho",
    "wof:placetype":"locality"
},
  "geometry": {"coordinates":[-7.83069,37.25138],"type":"Point"}
}