{
  "type": "Feature",
  "properties": {
    "gn:admin1_code":"22",
    "gn:admin2_code":"1808",
    "gn:admin3_code":"180807.0",
    "gn:asciiname":"Vila Pouca",
    "gn:country_code":"PT",
    "gn:dem":223,
    "gn:feature_class":"P",
    "gn:feature_code":"PPL",
    "gn:name":"Vila Pouca",
    "gn:population":0,
    "gn:timezone":"Europe/Lisbon",
    "iso:country":"PT",
    "name:deu_x_preferred":[
        "Vila Pouca"
    ],
    "name:nld_x_preferred":[
        "Vila Pouca"
    ],
    "name:por_x_preferred":[
        "Vila Pouca"
    ],
    "name:spa_x_preferred":[
        "Vila Pouca"
    ],
    "wof:name":"Vila Pouca",
    "wof:placetype":"locality"
},
  "geometry": {"coordinates":[-8.27167,40.44629000000001],"type":"Point"}
}