{
  "type": "Feature",
  "properties": {
    "iso:country":"PT",
    "qs:a0":"Portugal",
    "qs:a1":"*Lisboa",
    "qs:a1r":"0",
    "qs:adm0":"Portugal",
    "qs:la_lc":"*",
    "qs:level":"locality",
    "qs:loc":"Bairro do Grilo",
    "qs:loc_alt":"Bairro do Grilo",
    "qs:pop":0,
    "qs:type":"buffered point",
    "wof:name":"Bairro do Grilo",
    "wof:placetype":"locality"
},
  "geometry": {"coordinates":[-9.1497,38.806994],"type":"Point"}
}