{
  "type": "Feature",
  "properties": {
    "gn:admin1_code":"08",
    "gn:admin2_code":"0701",
    "gn:admin3_code":"70101.0",
    "gn:asciiname":"Pipeira",
    "gn:country_code":"PT",
    "gn:dem":349,
    "gn:feature_class":"P",
    "gn:feature_code":"PPL",
    "gn:name":"Pipeira",
    "gn:population":0,
    "gn:timezone":"Europe/Lisbon",
    "iso:country":"PT",
    "wof:name":"Pipeira",
    "wof:placetype":"locality"
},
  "geometry": {"coordinates":[-7.38786,38.69035],"type":"Point"}
}