{
  "type": "Feature",
  "properties": {
    "gn:admin1_code":"22.0",
    "gn:admin2_code":"1817",
    "gn:admin3_code":"181706.0",
    "gn:asciiname":"Mea",
    "gn:country_code":"PT",
    "gn:dem":665,
    "gn:feature_class":"P",
    "gn:feature_code":"PPL",
    "gn:name":"Me\u00e3",
    "gn:population":0,
    "gn:timezone":"Europe/Lisbon",
    "iso:country":"PT",
    "wof:name":"Mea",
    "wof:placetype":"locality"
},
  "geometry": {"coordinates":[-7.71157,40.75151],"type":"Point"}
}