{
  "type": "Feature",
  "properties": {
    "gn:country":"PT",
    "gn:fcode":"PPL",
    "gn:population":17011,
    "iso:country":"PT",
    "name:ast_x_preferred":[
        "S\u00e3o Pedro da Cova"
    ],
    "name:ceb_x_preferred":[
        "S\u00e3o Pedro da Cova"
    ],
    "name:dan_x_preferred":[
        "S\u00e3o Pedro da Cova"
    ],
    "name:deu_x_preferred":[
        "S\u00e3o Pedro da Cova"
    ],
    "name:eng_x_preferred":[
        "S\u00e3o Pedro da Cova"
    ],
    "name:fra_x_preferred":[
        "S\u00e3o Pedro da Cova"
    ],
    "name:jpn_x_preferred":[
        "\u30b5\u30f3\u30fb\u30da\u30c9\u30ed\u30fb\u30c0\u30fb\u30b3\u30fc\u30f4\u30a1"
    ],
    "name:kaz_x_preferred":[
        "\u0421\u0430\u043d-\u041f\u0435\u0434\u0440\u0443-\u0434\u0430-\u041a\u043e\u0432\u0430"
    ],
    "name:ltz_x_preferred":[
        "S\u00e3o Pedro da Cova"
    ],
    "name:nld_x_preferred":[
        "S\u00e3o Pedro da Cova"
    ],
    "name:por_x_preferred":[
        "S\u00e3o Pedro da Cova"
    ],
    "name:rus_x_preferred":[
        "\u0421\u0430\u043d-\u041f\u0435\u0434\u0440\u0443-\u0434\u0430-\u041a\u043e\u0432\u0430"
    ],
    "name:spa_x_preferred":[
        "S\u00e3o Pedro da Cova"
    ],
    "name:tur_x_preferred":[
        "S\u00e3o Pedro da Cova"
    ],
    "name:zho_x_preferred":[
        "\u5723\u4f69\u5fb7\u7f57-\u8fbe\u79d1\u74e6"
    ],
    "qs_pg:aaroncc":"PT",
    "qs_pg:gn_country":"PT",
    "qs_pg:gn_fcode":"PPL",
    "qs_pg:gn_pop":17011,
    "qs_pg:name":"S\u00e3o Pedro da Cova",
    "qs_pg:name_adm0":"Portugal",
    "qs_pg:name_adm1":"Porto",
    "qs_pg:photos_9k":1,
    "qs_pg:photos_9r":4,
    "qs_pg:photos_all":185,
    "qs_pg:photos_sr":0,
    "qs_pg:pop_sr":6,
    "qs_pg:qs_pg_placetype":"locality",
    "qs_pg:qs_pg_placetype_gp":"Town",
    "qs_pg:woe_adm0":23424925,
    "woe:adm0_id":23424925,
    "woe:name_adm0":"Portugal",
    "woe:name_adm1":"Porto",
    "woe:placetype":"Town",
    "wof:name":"S\u00e3o Pedro da Cova",
    "wof:placetype":"locality",
    "wof:population":17011
},
  "geometry": {"coordinates":[-8.50412,41.15508],"type":"Point"}
}