{
  "type": "Feature",
  "properties": {
    "gn:admin1_code":"17.0",
    "gn:admin2_code":"1306",
    "gn:admin3_code":"130611.0",
    "gn:asciiname":"Castelo do Maia",
    "gn:country_code":"PT",
    "gn:dem":111,
    "gn:feature_class":"P",
    "gn:feature_code":"PPL",
    "gn:name":"Castelo do Maia",
    "gn:population":0,
    "gn:timezone":"Europe/Lisbon",
    "iso:country":"PT",
    "wof:name":"Castelo do Maia",
    "wof:placetype":"locality"
},
  "geometry": {"coordinates":[-8.61667,41.26071],"type":"Point"}
}