{
  "type": "Feature",
  "properties": {
    "gn:admin1_code":"4.0",
    "gn:admin2_code":"0311",
    "gn:admin3_code":"31113.0",
    "gn:asciiname":"Agra",
    "gn:country_code":"PT",
    "gn:dem":668,
    "gn:feature_class":"P",
    "gn:feature_code":"PPL",
    "gn:name":"Agra",
    "gn:population":0,
    "gn:timezone":"Europe/Lisbon",
    "iso:country":"PT",
    "wof:name":"Agra",
    "wof:placetype":"locality"
},
  "geometry": {"coordinates":[-8.04789,41.59574],"type":"Point"}
}