{
  "type": "Feature",
  "properties": {
    "gn:admin1_code":"2.0",
    "gn:admin2_code":"0105",
    "gn:admin3_code":"10504.0",
    "gn:asciiname":"Logoela",
    "gn:country_code":"PT",
    "gn:dem":16,
    "gn:feature_class":"P",
    "gn:feature_code":"PPL",
    "gn:name":"Logoela",
    "gn:population":0,
    "gn:timezone":"Europe/Lisbon",
    "iso:country":"PT",
    "wof:name":"Logoela",
    "wof:placetype":"locality"
},
  "geometry": {"coordinates":[-8.57379,40.63121],"type":"Point"}
}