{
  "type": "Feature",
  "properties": {
    "iso:country":"PT",
    "qs_pg:aaroncc":"PT",
    "qs_pg:name":"Sr. Do Ros\u00e1rio",
    "qs_pg:name_adm0":"Portugal",
    "qs_pg:name_adm1":"Madeira",
    "qs_pg:photos":10,
    "qs_pg:photos_1k":2,
    "qs_pg:photos_9k":1,
    "qs_pg:photos_9r":1,
    "qs_pg:photos_all":10,
    "qs_pg:photos_sr":1,
    "qs_pg:pop_sr":0,
    "qs_pg:qs_pg_placetype":"locality",
    "qs_pg:qs_pg_placetype_gp":"Town",
    "qs_pg:woe_adm0":23424925,
    "woe:adm0_id":23424925,
    "woe:name_adm0":"Portugal",
    "woe:name_adm1":"Madeira",
    "woe:placetype":"Town",
    "wof:name":"Sr. Do Ros\u00e1rio",
    "wof:placetype":"locality"
},
  "geometry": {"coordinates":[-17.031469,32.778182],"type":"Point"}
}