{
  "type": "Feature",
  "properties": {
    "gn:admin1_code":"17.0",
    "gn:admin2_code":"1313",
    "gn:admin3_code":"131307.0",
    "gn:asciiname":"Pedrinha",
    "gn:country_code":"PT",
    "gn:dem":26,
    "gn:feature_class":"P",
    "gn:feature_code":"PPL",
    "gn:name":"Pedrinha",
    "gn:population":0,
    "gn:timezone":"Europe/Lisbon",
    "iso:country":"PT",
    "wof:name":"Pedrinha",
    "wof:placetype":"locality"
},
  "geometry": {"coordinates":[-8.7536,41.43955],"type":"Point"}
}