{
  "type": "Feature",
  "properties": {
    "gn:admin1_code":"5.0",
    "gn:admin2_code":"0405",
    "gn:admin3_code":"40517.0",
    "gn:asciiname":"Lamalonga",
    "gn:country_code":"PT",
    "gn:dem":544,
    "gn:feature_class":"P",
    "gn:feature_code":"PPL",
    "gn:name":"Lamalonga",
    "gn:population":0,
    "gn:timezone":"Europe/Lisbon",
    "iso:country":"PT",
    "wof:name":"Lamalonga",
    "wof:placetype":"locality"
},
  "geometry": {"coordinates":[-7.07958,41.67837],"type":"Point"}
}