{
  "type": "Feature",
  "properties": {
    "gn:admin1_code":"22.0",
    "gn:admin2_code":"1810",
    "gn:admin3_code":"181012.0",
    "gn:asciiname":"Bezerreira",
    "gn:country_code":"PT",
    "gn:dem":913,
    "gn:feature_class":"P",
    "gn:feature_code":"PPL",
    "gn:name":"Bezerreira",
    "gn:population":0,
    "gn:timezone":"Europe/Lisbon",
    "iso:country":"PT",
    "wof:name":"Bezerreira",
    "wof:placetype":"locality"
},
  "geometry": {"coordinates":[-8.19898,40.57214000000001],"type":"Point"}
}