{
  "type": "Feature",
  "properties": {
    "gn:admin1_code":"13",
    "gn:admin2_code":"1006",
    "gn:admin3_code":"100604.0",
    "gn:asciiname":"Mestras",
    "gn:country_code":"PT",
    "gn:dem":101,
    "gn:feature_class":"P",
    "gn:feature_code":"PPL",
    "gn:name":"Mestras",
    "gn:population":0,
    "gn:timezone":"Europe/Lisbon",
    "iso:country":"PT",
    "wof:name":"Mestras",
    "wof:placetype":"locality"
},
  "geometry": {"coordinates":[-9.05902,39.46499],"type":"Point"}
}