{
  "type": "Feature",
  "properties": {
    "gn:admin1_code":"2.0",
    "gn:admin2_code":"0106",
    "gn:admin3_code":"10603.0",
    "gn:asciiname":"Almansor",
    "gn:country_code":"PT",
    "gn:dem":152,
    "gn:feature_class":"P",
    "gn:feature_code":"PPL",
    "gn:name":"Almansor",
    "gn:population":0,
    "gn:timezone":"Europe/Lisbon",
    "iso:country":"PT",
    "wof:name":"Almansor",
    "wof:placetype":"locality"
},
  "geometry": {"coordinates":[-8.33726,40.99049],"type":"Point"}
}