{
  "type": "Feature",
  "properties": {
    "gn:admin1_code":"13",
    "gn:admin2_code":"1012",
    "gn:admin3_code":"101203.0",
    "gn:asciiname":"Rego Travesso",
    "gn:country_code":"PT",
    "gn:dem":15,
    "gn:feature_class":"P",
    "gn:feature_code":"PPL",
    "gn:name":"Rego Travesso",
    "gn:population":0,
    "gn:timezone":"Europe/Lisbon",
    "iso:country":"PT",
    "wof:name":"Rego Travesso",
    "wof:placetype":"locality"
},
  "geometry": {"coordinates":[-9.20575,39.33368],"type":"Point"}
}