{
  "type": "Feature",
  "properties": {
    "gn:admin1_code":"18",
    "gn:admin2_code":"1416",
    "gn:admin3_code":"141601.0",
    "gn:asciiname":"Casais da Aroeira",
    "gn:country_code":"PT",
    "gn:dem":123,
    "gn:feature_class":"P",
    "gn:feature_code":"PPL",
    "gn:name":"Casais da Aroeira",
    "gn:population":0,
    "gn:timezone":"Europe/Lisbon",
    "iso:country":"PT",
    "wof:name":"Casais da Aroeira",
    "wof:placetype":"locality"
},
  "geometry": {"coordinates":[-8.7622,39.30268],"type":"Point"}
}