{
  "type": "Feature",
  "properties": {
    "gn:admin1_code":"09",
    "gn:admin2_code":"0812",
    "gn:admin3_code":"81201.0",
    "gn:asciiname":"Corotelo",
    "gn:country_code":"PT",
    "gn:dem":250,
    "gn:feature_class":"P",
    "gn:feature_code":"PPL",
    "gn:name":"Corotelo",
    "gn:population":0,
    "gn:timezone":"Europe/Lisbon",
    "iso:country":"PT",
    "wof:name":"Corotelo",
    "wof:placetype":"locality"
},
  "geometry": {"coordinates":[-7.92476,37.14709000000001],"type":"Point"}
}