{
  "type": "Feature",
  "properties": {
    "gn:admin1_code":"09",
    "gn:admin2_code":"0808",
    "gn:admin3_code":"80806.0",
    "gn:asciiname":"Pombal",
    "gn:country_code":"PT",
    "gn:dem":212,
    "gn:feature_class":"P",
    "gn:feature_code":"PPL",
    "gn:name":"Pombal",
    "gn:population":0,
    "gn:timezone":"Europe/Lisbon",
    "iso:country":"PT",
    "name:ceb_x_preferred":[
        "Pombal"
    ],
    "name:deu_x_preferred":[
        "Pombal"
    ],
    "name:fra_x_preferred":[
        "Pombal"
    ],
    "name:glg_x_preferred":[
        "Pombal"
    ],
    "name:ita_x_preferred":[
        "Pombal"
    ],
    "name:nld_x_preferred":[
        "Pombal"
    ],
    "name:nor_x_preferred":[
        "Pombal"
    ],
    "name:por_x_preferred":[
        "Pombal"
    ],
    "name:rus_x_preferred":[
        "\u041f\u043e\u043c\u0431\u0430\u043b"
    ],
    "name:swe_x_preferred":[
        "Pombal"
    ],
    "name:ukr_x_preferred":[
        "\u041f\u043e\u043c\u0431\u0430\u043b"
    ],
    "name:vie_x_preferred":[
        "Pombal"
    ],
    "name:vol_x_preferred":[
        "Pombal"
    ],
    "wof:name":"Pombal",
    "wof:placetype":"locality"
},
  "geometry": {"coordinates":[-7.99199,37.20423],"type":"Point"}
}