{
  "type": "Feature",
  "properties": {
    "gn:admin1_code":"09",
    "gn:admin2_code":"0808",
    "gn:admin3_code":"80806.0",
    "gn:asciiname":"Pombal",
    "gn:country_code":"PT",
    "gn:dem":212,
    "gn:feature_class":"P",
    "gn:feature_code":"PPL",
    "gn:name":"Pombal",
    "gn:population":0,
    "gn:timezone":"Europe/Lisbon",
    "iso:country":"PT",
    "wof:name":"Pombal",
    "wof:placetype":"locality"
},
  "geometry": {"coordinates":[-7.99199,37.20423],"type":"Point"}
}