{
  "type": "Feature",
  "properties": {
    "gn:admin1_code":"05",
    "gn:admin2_code":"0401",
    "gn:admin3_code":"40112.0",
    "gn:asciiname":"Sendim da Ribeira",
    "gn:country_code":"PT",
    "gn:dem":349,
    "gn:feature_class":"P",
    "gn:feature_code":"PPL",
    "gn:name":"Sendim da Ribeira",
    "gn:population":0,
    "gn:timezone":"Europe/Lisbon",
    "iso:country":"PT",
    "wof:name":"Sendim da Ribeira",
    "wof:placetype":"locality"
},
  "geometry": {"coordinates":[-6.90554,41.31039000000001],"type":"Point"}
}