{
  "type": "Feature",
  "properties": {
    "gn:admin1_code":"16",
    "gn:admin2_code":"1203",
    "gn:admin3_code":"120301.0",
    "gn:asciiname":"Marcolos",
    "gn:country_code":"PT",
    "gn:dem":167,
    "gn:feature_class":"P",
    "gn:feature_code":"PPL",
    "gn:name":"Marcolos",
    "gn:population":0,
    "gn:timezone":"Europe/Lisbon",
    "iso:country":"PT",
    "wof:name":"Marcolos",
    "wof:placetype":"locality"
},
  "geometry": {"coordinates":[-7.9627,39.04379],"type":"Point"}
}