{
  "type": "Feature",
  "properties": {
    "gn:admin1_code":"07",
    "gn:admin2_code":"0611",
    "gn:admin3_code":"61119.0",
    "gn:asciiname":"Vendas de Gavinhos",
    "gn:country_code":"PT",
    "gn:dem":437,
    "gn:feature_class":"P",
    "gn:feature_code":"PPL",
    "gn:name":"Vendas de Gavinhos",
    "gn:population":0,
    "gn:timezone":"Europe/Lisbon",
    "iso:country":"PT",
    "wof:name":"Vendas de Gavinhos",
    "wof:placetype":"locality"
},
  "geometry": {"coordinates":[-7.86583,40.37419000000001],"type":"Point"}
}