{
  "type": "Feature",
  "properties": {
    "gn:admin1_code":"06",
    "gn:admin2_code":"0502",
    "gn:admin3_code":"50202.0",
    "gn:asciiname":"Rochas de Cima",
    "gn:country_code":"PT",
    "gn:dem":657,
    "gn:feature_class":"P",
    "gn:feature_code":"PPL",
    "gn:name":"Rochas de Cima",
    "gn:population":0,
    "gn:timezone":"Europe/Lisbon",
    "iso:country":"PT",
    "wof:name":"Rochas de Cima",
    "wof:placetype":"locality"
},
  "geometry": {"coordinates":[-7.66667,40.05],"type":"Point"}
}