{
  "type": "Feature",
  "properties": {
    "gn:admin1_code":"22.0",
    "gn:admin2_code":"1821",
    "gn:admin3_code":"182105.0",
    "gn:asciiname":"Muceres",
    "gn:country_code":"PT",
    "gn:dem":248,
    "gn:feature_class":"P",
    "gn:feature_code":"PPL",
    "gn:name":"M\u00faceres",
    "gn:population":0,
    "gn:timezone":"Europe/Lisbon",
    "iso:country":"PT",
    "wof:name":"Muceres",
    "wof:placetype":"locality"
},
  "geometry": {"coordinates":[-8.16244,40.53877],"type":"Point"}
}