{
  "type": "Feature",
  "properties": {
    "gn:admin1_code":"18",
    "gn:admin2_code":"1416",
    "gn:admin3_code":"141623.0",
    "gn:asciiname":"Larosa",
    "gn:country_code":"PT",
    "gn:dem":143,
    "gn:feature_class":"P",
    "gn:feature_code":"PPL",
    "gn:name":"Larosa",
    "gn:population":0,
    "gn:timezone":"Europe/Lisbon",
    "iso:country":"PT",
    "wof:name":"Larosa",
    "wof:placetype":"locality"
},
  "geometry": {"coordinates":[-8.75782,39.33989],"type":"Point"}
}