{
  "type": "Feature",
  "properties": {
    "gn:admin1_code":"23.0",
    "gn:admin2_code":"4301",
    "gn:admin3_code":"430109.0",
    "gn:asciiname":"Ribeira do Testo",
    "gn:country_code":"PT",
    "gn:dem":44,
    "gn:feature_class":"P",
    "gn:feature_code":"PPL",
    "gn:name":"Ribeira do Testo",
    "gn:population":0,
    "gn:timezone":"Atlantic/Azores",
    "iso:country":"PT",
    "wof:name":"Ribeira do Testo",
    "wof:placetype":"locality"
},
  "geometry": {"coordinates":[-27.13824,38.6506],"type":"Point"}
}