{
  "type": "Feature",
  "properties": {
    "gn:admin1_code":"18",
    "gn:admin2_code":"1401",
    "gn:admin3_code":"140101.0",
    "gn:asciiname":"Medroa",
    "gn:country_code":"PT",
    "gn:dem":209,
    "gn:feature_class":"P",
    "gn:feature_code":"PPL",
    "gn:name":"Medroa",
    "gn:population":0,
    "gn:timezone":"Europe/Lisbon",
    "iso:country":"PT",
    "wof:name":"Medroa",
    "wof:placetype":"locality"
},
  "geometry": {"coordinates":[-8.28333,39.53333],"type":"Point"}
}