{
  "type": "Feature",
  "properties": {
    "gn:admin1_code":"4.0",
    "gn:admin2_code":"0313",
    "gn:admin3_code":"31301.0",
    "gn:asciiname":"Sa",
    "gn:country_code":"PT",
    "gn:dem":485,
    "gn:feature_class":"P",
    "gn:feature_code":"PPL",
    "gn:name":"S\u00e1",
    "gn:population":0,
    "gn:timezone":"Europe/Lisbon",
    "iso:country":"PT",
    "wof:name":"Sa",
    "wof:placetype":"locality"
},
  "geometry": {"coordinates":[-8.39471,41.73555],"type":"Point"}
}