{
  "type": "Feature",
  "properties": {
    "gn:admin1_code":"09",
    "gn:asciiname":"Cachopos",
    "gn:country_code":"PT",
    "gn:dem":8,
    "gn:feature_class":"P",
    "gn:feature_code":"PPL",
    "gn:name":"Cachopos",
    "gn:population":0,
    "gn:timezone":"Europe/Lisbon",
    "iso:country":"PT",
    "wof:name":"Cachopos",
    "wof:placetype":"locality"
},
  "geometry": {"coordinates":[-8.65617,38.39582],"type":"Point"}
}