{
  "type": "Feature",
  "properties": {
    "gn:admin1_code":"2.0",
    "gn:admin2_code":"0109",
    "gn:admin3_code":"10930.0",
    "gn:asciiname":"Costa Ma",
    "gn:country_code":"PT",
    "gn:dem":243,
    "gn:feature_class":"P",
    "gn:feature_code":"PPL",
    "gn:name":"Costa M\u00e1",
    "gn:population":0,
    "gn:timezone":"Europe/Lisbon",
    "iso:country":"PT",
    "wof:name":"Costa Ma",
    "wof:placetype":"locality"
},
  "geometry": {"coordinates":[-8.44533,40.98282],"type":"Point"}
}