{
  "type": "Feature",
  "properties": {
    "gn:admin1_code":"05",
    "gn:admin2_code":"0412",
    "gn:admin3_code":"41234.0",
    "gn:asciiname":"Vilar Seco da Lomba",
    "gn:country_code":"PT",
    "gn:dem":752,
    "gn:feature_class":"P",
    "gn:feature_code":"PPL",
    "gn:name":"Vilar Seco da Lomba",
    "gn:population":0,
    "gn:timezone":"Europe/Lisbon",
    "iso:country":"PT",
    "wof:name":"Vilar Seco da Lomba",
    "wof:placetype":"locality"
},
  "geometry": {"coordinates":[-7.17321,41.87943],"type":"Point"}
}