{
  "type": "Feature",
  "properties": {
    "gn:admin1_code":"17",
    "gn:admin2_code":"1307",
    "gn:admin3_code":"130714.0",
    "gn:asciiname":"Viadores",
    "gn:country_code":"PT",
    "gn:dem":366,
    "gn:feature_class":"P",
    "gn:feature_code":"PPL",
    "gn:name":"Viadores",
    "gn:population":0,
    "gn:timezone":"Europe/Lisbon",
    "iso:country":"PT",
    "wof:name":"Viadores",
    "wof:placetype":"locality"
},
  "geometry": {"coordinates":[-8.12106,41.12898],"type":"Point"}
}