{
  "type": "Feature",
  "properties": {
    "gn:admin1_code":"21",
    "gn:admin2_code":"1713",
    "gn:admin3_code":"171312.0",
    "gn:asciiname":"Vales",
    "gn:country_code":"PT",
    "gn:dem":674,
    "gn:feature_class":"P",
    "gn:feature_code":"PPL",
    "gn:name":"Vales",
    "gn:population":0,
    "gn:timezone":"Europe/Lisbon",
    "iso:country":"PT",
    "wof:name":"Vales",
    "wof:placetype":"locality"
},
  "geometry": {"coordinates":[-7.51824,41.46202],"type":"Point"}
}