{
  "type": "Feature",
  "properties": {
    "gn:admin1_code":"21",
    "gn:admin2_code":"1714",
    "gn:admin3_code":"171404.0",
    "gn:asciiname":"Torneiros",
    "gn:country_code":"PT",
    "gn:dem":468,
    "gn:feature_class":"P",
    "gn:feature_code":"PPL",
    "gn:name":"Torneiros",
    "gn:population":0,
    "gn:timezone":"Europe/Lisbon",
    "iso:country":"PT",
    "wof:name":"Torneiros",
    "wof:placetype":"locality"
},
  "geometry": {"coordinates":[-7.71652,41.28834000000001],"type":"Point"}
}