{
  "type": "Feature",
  "properties": {
    "gn:admin1_code":"2.0",
    "gn:admin2_code":"0109",
    "gn:admin3_code":"10903.0",
    "gn:asciiname":"Mosteiro",
    "gn:country_code":"PT",
    "gn:dem":135,
    "gn:feature_class":"P",
    "gn:feature_code":"PPL",
    "gn:name":"Mosteir\u00f4",
    "gn:population":0,
    "gn:timezone":"Europe/Lisbon",
    "iso:country":"PT",
    "wof:name":"Mosteiro",
    "wof:placetype":"locality"
},
  "geometry": {"coordinates":[-8.44706,41.03942],"type":"Point"}
}