{
  "type": "Feature",
  "properties": {
    "gn:admin1_code":"18",
    "gn:admin2_code":"1401",
    "gn:admin3_code":"140106.0",
    "gn:asciiname":"Casal da Igreja",
    "gn:country_code":"PT",
    "gn:dem":179,
    "gn:feature_class":"P",
    "gn:feature_code":"PPL",
    "gn:name":"Casal da Igreja",
    "gn:population":0,
    "gn:timezone":"Europe/Lisbon",
    "iso:country":"PT",
    "wof:name":"Casal da Igreja",
    "wof:placetype":"locality"
},
  "geometry": {"coordinates":[-8.09416,39.50359],"type":"Point"}
}