{
  "type": "Feature",
  "properties": {
    "gn:admin1_code":"19",
    "gn:admin2_code":"1509",
    "gn:admin3_code":"150903.0",
    "gn:asciiname":"Geralda",
    "gn:country_code":"PT",
    "gn:dem":188,
    "gn:feature_class":"P",
    "gn:feature_code":"PPL",
    "gn:name":"Geralda",
    "gn:population":0,
    "gn:timezone":"Europe/Lisbon",
    "iso:country":"PT",
    "wof:name":"Geralda",
    "wof:placetype":"locality"
},
  "geometry": {"coordinates":[-8.68755,37.80006],"type":"Point"}
}