{
  "type": "Feature",
  "properties": {
    "gn:gn_country":"PT",
    "gn:gn_fcode":"ADM3",
    "gn:gn_pop":389,
    "gn:population":389,
    "iso:country":"PT",
    "name:ast_x_preferred":[
        "Seda"
    ],
    "name:cat_x_preferred":[
        "Seda"
    ],
    "name:ceb_x_preferred":[
        "Seda"
    ],
    "name:ces_x_preferred":[
        "Seda"
    ],
    "name:deu_x_preferred":[
        "Seda"
    ],
    "name:fra_x_preferred":[
        "Seda"
    ],
    "name:glg_x_preferred":[
        "Seda"
    ],
    "name:kaz_x_preferred":[
        "\u0421\u0435\u0434\u0430"
    ],
    "name:lav_x_preferred":[
        "Seda"
    ],
    "name:lit_x_preferred":[
        "Seda"
    ],
    "name:por_x_preferred":[
        "Seda"
    ],
    "name:rus_x_preferred":[
        "\u0421\u0435\u0434\u0430"
    ],
    "name:spa_x_preferred":[
        "Seda"
    ],
    "name:swe_x_preferred":[
        "Seda"
    ],
    "name:ukr_x_preferred":[
        "\u0421\u0435\u0434\u0430"
    ],
    "qs_pg:aaroncc":"PT",
    "qs_pg:gn_country":"PT",
    "qs_pg:gn_fcode":"ADM3",
    "qs_pg:gn_pop":389,
    "qs_pg:name":"Seda",
    "qs_pg:photos_9r":0,
    "qs_pg:photos_sr":0,
    "qs_pg:pop_sr":2,
    "qs_pg:qs_pg_placetype":"localadmin",
    "wof:name":"Seda",
    "wof:placetype":"localadmin",
    "wof:population":389
},
  "geometry": {"coordinates":[-7.75853,39.17712],"type":"Point"}
}