{
  "type": "Feature",
  "properties": {
    "gn:admin1_code":"09",
    "gn:admin2_code":"0815",
    "gn:admin3_code":"81505.0",
    "gn:asciiname":"Granja",
    "gn:country_code":"PT",
    "gn:dem":69,
    "gn:feature_class":"P",
    "gn:feature_code":"PPL",
    "gn:name":"Granja",
    "gn:population":0,
    "gn:timezone":"Europe/Lisbon",
    "iso:country":"PT",
    "wof:name":"Granja",
    "wof:placetype":"locality"
},
  "geometry": {"coordinates":[-8.9275,37.06438],"type":"Point"}
}