{
  "type": "Feature",
  "properties": {
    "gn:country":"PT",
    "gn:fcode":"PPL",
    "gn:population":0,
    "iso:country":"PT",
    "name:ceb_x_preferred":[
        "Tua"
    ],
    "name:deu_x_preferred":[
        "Tua"
    ],
    "name:nno_x_preferred":[
        "Tua"
    ],
    "name:nor_x_preferred":[
        "Tua"
    ],
    "name:por_x_preferred":[
        "Tua"
    ],
    "name:swe_x_preferred":[
        "Tua"
    ],
    "qs_pg:aaroncc":"PT",
    "qs_pg:gn_country":"PT",
    "qs_pg:gn_fcode":"PPL",
    "qs_pg:gn_pop":0,
    "qs_pg:name":"Tua",
    "qs_pg:name_adm0":"Portugal",
    "qs_pg:name_adm1":"Bragan\u00e7a",
    "qs_pg:photos":82,
    "qs_pg:photos_1k":17,
    "qs_pg:photos_9k":1,
    "qs_pg:photos_9r":3,
    "qs_pg:photos_all":82,
    "qs_pg:photos_sr":3,
    "qs_pg:pop_sr":0,
    "qs_pg:qs_pg_placetype":"locality",
    "qs_pg:qs_pg_placetype_gp":"Town",
    "qs_pg:woe_adm0":23424925,
    "woe:adm0_id":23424925,
    "woe:name_adm0":"Portugal",
    "woe:name_adm1":"Bragan\u00e7a",
    "woe:placetype":"Town",
    "wof:name":"Tua",
    "wof:placetype":"locality"
},
  "geometry": {"coordinates":[-7.42216,41.20778],"type":"Point"}
}