{
  "type": "Feature",
  "properties": {
    "gn:admin1_code":"23.0",
    "gn:admin2_code":"4602",
    "gn:admin3_code":"460201.0",
    "gn:asciiname":"Laje",
    "gn:country_code":"PT",
    "gn:dem":110,
    "gn:feature_class":"P",
    "gn:feature_code":"PPL",
    "gn:name":"Laje",
    "gn:population":0,
    "gn:timezone":"Atlantic/Azores",
    "iso:country":"PT",
    "wof:name":"Laje",
    "wof:placetype":"locality"
},
  "geometry": {"coordinates":[-28.44607,38.54275],"type":"Point"}
}