{
  "type": "Feature",
  "properties": {
    "gn:admin1_code":"04",
    "gn:admin2_code":"0313",
    "gn:admin3_code":"31350.0",
    "gn:asciiname":"Prado",
    "gn:country_code":"PT",
    "gn:dem":292,
    "gn:feature_class":"P",
    "gn:feature_code":"PPL",
    "gn:name":"Prado",
    "gn:population":0,
    "gn:timezone":"Europe/Lisbon",
    "iso:country":"PT",
    "wof:name":"Prado",
    "wof:placetype":"locality"
},
  "geometry": {"coordinates":[-8.44316,41.69814],"type":"Point"}
}