{
  "type": "Feature",
  "properties": {
    "gn:admin1_code":"23.0",
    "gn:admin2_code":"4401",
    "gn:admin3_code":"440104.0",
    "gn:asciiname":"Santa Cruz da Graciosa",
    "gn:country_code":"PT",
    "gn:dem":7,
    "gn:feature_class":"P",
    "gn:feature_code":"PPL",
    "gn:name":"Santa Cruz da Graciosa",
    "gn:population":1776,
    "gn:timezone":"Atlantic/Azores",
    "iso:country":"PT",
    "name:cat_x_preferred":[
        "Santa Cruz da Graciosa"
    ],
    "name:ceb_x_preferred":[
        "Santa Cruz da Graciosa"
    ],
    "name:deu_x_preferred":[
        "Santa Cruz da Graciosa"
    ],
    "name:fra_x_preferred":[
        "Santa Cruz da Graciosa"
    ],
    "name:ita_x_preferred":[
        "Santa Cruz da Graciosa"
    ],
    "name:kor_x_preferred":[
        "\uc0b0\ud0c0\ud06c\ub8e8\uc2a4\ub2e4\uadf8\ub77c\uc2dc\uc624\uc790"
    ],
    "name:lit_x_preferred":[
        "Santa Kruz da Grasioza"
    ],
    "name:msa_x_preferred":[
        "Santa Cruz da Graciosa"
    ],
    "name:nld_x_preferred":[
        "Santa Cruz da Graciosa"
    ],
    "name:pol_x_preferred":[
        "Santa Cruz da Graciosa"
    ],
    "name:por_x_preferred":[
        "Santa Cruz da Graciosa"
    ],
    "name:rus_x_preferred":[
        "\u0421\u0430\u043d\u0442\u0430-\u041a\u0440\u0443\u0448-\u0434\u0430-\u0413\u0440\u0430\u0441\u0438\u043e\u0437\u0430"
    ],
    "name:spa_x_preferred":[
        "Santa Cruz da Graciosa"
    ],
    "name:tur_x_preferred":[
        "Santa Cruz da Graciosa"
    ],
    "name:und_x_variant":[
        "Santa Cruz"
    ],
    "name:vie_x_preferred":[
        "Santa Cruz da Graciosa"
    ],
    "name:vol_x_preferred":[
        "Santa Cruz da Graciosa"
    ],
    "name:war_x_preferred":[
        "Santa Cruz da Graciosa"
    ],
    "name:zho_x_preferred":[
        "\u8056\u514b\u9b6f\u4ec0\u9054\u683c\u62c9\u897f\u5967\u85a9"
    ],
    "wof:name":"Santa Cruz da Graciosa",
    "wof:placetype":"locality",
    "wof:population":1776
},
  "geometry": {"coordinates":[-28.0058,39.08577],"type":"Point"}
}