{
  "type": "Feature",
  "properties": {
    "gn:admin1_code":"22.0",
    "gn:admin2_code":"1817",
    "gn:admin3_code":"181704.0",
    "gn:asciiname":"Duas Igrejas",
    "gn:country_code":"PT",
    "gn:dem":663,
    "gn:feature_class":"P",
    "gn:feature_code":"PPL",
    "gn:name":"Duas Igrejas",
    "gn:population":0,
    "gn:timezone":"Europe/Lisbon",
    "iso:country":"PT",
    "name:ceb_x_preferred":[
        "Duas Igrejas"
    ],
    "name:deu_x_preferred":[
        "Duas Igrejas"
    ],
    "name:fra_x_preferred":[
        "Duas Igrejas"
    ],
    "name:nld_x_preferred":[
        "Duas Igrejas"
    ],
    "name:por_x_preferred":[
        "Duas Igrejas"
    ],
    "name:rus_x_preferred":[
        "\u0414\u0443\u0430\u0437-\u0418\u0433\u0440\u0435\u0436\u0430\u0448"
    ],
    "name:ukr_x_preferred":[
        "\u0414\u0443\u0430\u0437-\u0406\u0433\u0440\u0435\u0436\u0430\u0448"
    ],
    "wof:name":"Duas Igrejas",
    "wof:placetype":"locality"
},
  "geometry": {"coordinates":[-7.70781,40.79934],"type":"Point"}
}