{
  "type": "Feature",
  "properties": {
    "gn:admin1_code":"14",
    "gn:admin2_code":"1111",
    "gn:admin3_code":"111105.0",
    "gn:asciiname":"Atalaia de Cima",
    "gn:country_code":"PT",
    "gn:dem":217,
    "gn:feature_class":"P",
    "gn:feature_code":"PPL",
    "gn:name":"Atalaia de Cima",
    "gn:population":0,
    "gn:timezone":"Europe/Lisbon",
    "iso:country":"PT",
    "wof:name":"Atalaia de Cima",
    "wof:placetype":"locality"
},
  "geometry": {"coordinates":[-9.48153,38.77656],"type":"Point"}
}