{
  "type": "Feature",
  "properties": {
    "gn:admin1_code":"18",
    "gn:admin2_code":"1417",
    "gn:admin3_code":"141701.0",
    "gn:asciiname":"Saramaga",
    "gn:country_code":"PT",
    "gn:dem":230,
    "gn:feature_class":"P",
    "gn:feature_code":"PPL",
    "gn:name":"Saramaga",
    "gn:population":0,
    "gn:timezone":"Europe/Lisbon",
    "iso:country":"PT",
    "wof:name":"Saramaga",
    "wof:placetype":"locality"
},
  "geometry": {"coordinates":[-8.09039,39.55823],"type":"Point"}
}