{
  "type": "Feature",
  "properties": {
    "gn:admin1_code":"22.0",
    "gn:admin2_code":"1816",
    "gn:admin3_code":"181616.0",
    "gn:asciiname":"Leirados",
    "gn:country_code":"PT",
    "gn:dem":444,
    "gn:feature_class":"P",
    "gn:feature_code":"PPL",
    "gn:name":"Leirados",
    "gn:population":0,
    "gn:timezone":"Europe/Lisbon",
    "iso:country":"PT",
    "wof:name":"Leirados",
    "wof:placetype":"locality"
},
  "geometry": {"coordinates":[-8.05815,40.8499],"type":"Point"}
}