{
  "type": "Feature",
  "properties": {
    "gn:admin1_code":"21.0",
    "gn:admin2_code":"1712",
    "gn:admin3_code":"171201.0",
    "gn:asciiname":"Crasto",
    "gn:country_code":"PT",
    "gn:dem":282,
    "gn:feature_class":"P",
    "gn:feature_code":"PPL",
    "gn:name":"Crasto",
    "gn:population":0,
    "gn:timezone":"Europe/Lisbon",
    "iso:country":"PT",
    "wof:name":"Crasto",
    "wof:placetype":"locality"
},
  "geometry": {"coordinates":[-7.32526,41.56204],"type":"Point"}
}