{
  "type": "Feature",
  "properties": {
    "gn:admin1_code":"06",
    "gn:admin2_code":"0508",
    "gn:admin3_code":"50806.0",
    "gn:asciiname":"Giesteiras Cimeiras",
    "gn:country_code":"PT",
    "gn:dem":354,
    "gn:feature_class":"P",
    "gn:feature_code":"PPL",
    "gn:name":"Giesteiras Cimeiras",
    "gn:population":0,
    "gn:timezone":"Europe/Lisbon",
    "iso:country":"PT",
    "wof:name":"Giesteiras Cimeiras",
    "wof:placetype":"locality"
},
  "geometry": {"coordinates":[-7.83226,39.74995],"type":"Point"}
}