{
  "type": "Feature",
  "properties": {
    "gn:admin1_code":"17",
    "gn:admin2_code":"1307",
    "gn:admin3_code":"130716.0",
    "gn:asciiname":"Rio de Galinhas",
    "gn:country_code":"PT",
    "gn:dem":124,
    "gn:feature_class":"P",
    "gn:feature_code":"PPL",
    "gn:name":"Rio de Galinhas",
    "gn:population":0,
    "gn:timezone":"Europe/Lisbon",
    "iso:country":"PT",
    "wof:name":"Rio de Galinhas",
    "wof:placetype":"locality"
},
  "geometry": {"coordinates":[-8.13657,41.17884],"type":"Point"}
}