{
  "type": "Feature",
  "properties": {
    "gn:gn_country":"PT",
    "gn:gn_fcode":"PPL",
    "gn:gn_pop":0,
    "iso:country":"PT",
    "name:deu_x_preferred":[
        "S\u00e3o Bartolomeu do Outeiro"
    ],
    "name:eng_x_preferred":[
        "S\u00e3o Bartolomeu do Outeiro"
    ],
    "name:fra_x_preferred":[
        "S\u00e3o Bartolomeu do Outeiro"
    ],
    "name:kaz_x_preferred":[
        "\u0421\u0430\u043d-\u0411\u0430\u0440\u0442\u043e\u043b\u043e\u043c\u0435\u0443-\u0434\u0443-\u041e\u0442\u0435\u0439\u0440\u0443"
    ],
    "name:nld_x_preferred":[
        "S\u00e3o Bartolomeu do Outeiro"
    ],
    "name:por_x_preferred":[
        "S\u00e3o Bartolomeu do Outeiro"
    ],
    "name:rus_x_preferred":[
        "\u0421\u0430\u043d-\u0411\u0430\u0440\u0442\u043e\u043b\u043e\u043c\u0435\u0443-\u0434\u0443-\u041e\u0442\u0435\u0439\u0440\u0443"
    ],
    "name:spa_x_preferred":[
        "S\u00e3o Bartolomeu do Outeiro"
    ],
    "qs_pg:aaroncc":"PT",
    "qs_pg:gn_country":"PT",
    "qs_pg:gn_fcode":"PPL",
    "qs_pg:gn_pop":0,
    "qs_pg:name":"S\u00e3o Bartolomeu do Outeiro",
    "qs_pg:name_adm0":"Portugal",
    "qs_pg:name_adm1":"Evora",
    "qs_pg:photos":20,
    "qs_pg:photos_1k":4,
    "qs_pg:photos_9k":1,
    "qs_pg:photos_9r":1,
    "qs_pg:photos_all":20,
    "qs_pg:photos_sr":1,
    "qs_pg:pop_sr":0,
    "qs_pg:qs_pg_placetype":"locality",
    "qs_pg:qs_pg_placetype_gp":"Town",
    "qs_pg:woe_adm0":23424925,
    "woe:adm0_id":23424925,
    "woe:name_adm0":"Portugal",
    "woe:name_adm1":"Evora",
    "woe:placetype":"Town",
    "wof:name":"S\u00e3o Bartolomeu do Outeiro",
    "wof:placetype":"locality"
},
  "geometry": {"coordinates":[-7.9084,38.3542],"type":"Point"}
}