{
  "type": "Feature",
  "properties": {
    "iso:country":"PT",
    "name:por_x_preferred":[
        "Silva Escura"
    ],
    "qs:a0":"Portugal",
    "qs:a1":"*Porto",
    "qs:a1r":"0",
    "qs:adm0":"Portugal",
    "qs:la_lc":"*",
    "qs:level":"locality",
    "qs:loc":"Silva Escura",
    "qs:loc_alt":"Silva Escura",
    "qs:pop":0,
    "qs:type":"buffered point",
    "wof:lang":[
        "por"
    ],
    "wof:name":"Silva Escura",
    "wof:placetype":"locality"
},
  "geometry": {"coordinates":[-8.583042,41.256955],"type":"Point"}
}