{
  "type": "Feature",
  "properties": {
    "gn:admin1_code":"21.0",
    "gn:admin2_code":"1703",
    "gn:admin3_code":"170313.0",
    "gn:asciiname":"Faioes",
    "gn:country_code":"PT",
    "gn:dem":390,
    "gn:feature_class":"P",
    "gn:feature_code":"PPL",
    "gn:name":"Fai\u00f5es",
    "gn:population":0,
    "gn:timezone":"Europe/Lisbon",
    "iso:country":"PT",
    "wof:name":"Faioes",
    "wof:placetype":"locality"
},
  "geometry": {"coordinates":[-7.42448,41.75248],"type":"Point"}
}