{
  "type": "Feature",
  "properties": {
    "gn:admin1_code":"4.0",
    "gn:admin2_code":"0308",
    "gn:admin3_code":"30855.0",
    "gn:asciiname":"Burgo",
    "gn:country_code":"PT",
    "gn:dem":158,
    "gn:feature_class":"P",
    "gn:feature_code":"PPL",
    "gn:name":"Burgo",
    "gn:population":0,
    "gn:timezone":"Europe/Lisbon",
    "iso:country":"PT",
    "name:ceb_x_preferred":[
        "Burgo"
    ],
    "name:fra_x_preferred":[
        "Burgo"
    ],
    "name:glg_x_preferred":[
        "Burgo"
    ],
    "name:ita_x_preferred":[
        "Burgo"
    ],
    "name:nld_x_preferred":[
        "Burgo"
    ],
    "name:por_x_preferred":[
        "Burgo"
    ],
    "name:rus_x_preferred":[
        "\u0411\u0443\u0440\u0433\u043e"
    ],
    "name:spa_x_preferred":[
        "Burgo"
    ],
    "wof:name":"Burgo",
    "wof:placetype":"locality"
},
  "geometry": {"coordinates":[-8.36082,41.50666],"type":"Point"}
}