{
  "type": "Feature",
  "properties": {
    "gn:admin1_code":"7.0",
    "gn:admin2_code":"0616",
    "gn:admin3_code":"61610.0",
    "gn:asciiname":"Bogalhas",
    "gn:country_code":"PT",
    "gn:dem":270,
    "gn:feature_class":"P",
    "gn:feature_code":"PPL",
    "gn:name":"Bogalhas",
    "gn:population":0,
    "gn:timezone":"Europe/Lisbon",
    "iso:country":"PT",
    "wof:name":"Bogalhas",
    "wof:placetype":"locality"
},
  "geometry": {"coordinates":[-8.00789,40.29381],"type":"Point"}
}