{
  "type": "Feature",
  "properties": {
    "gn:admin1_code":"7.0",
    "gn:admin2_code":"0609",
    "gn:admin3_code":"60902.0",
    "gn:asciiname":"Fraldeu",
    "gn:country_code":"PT",
    "gn:dem":155,
    "gn:feature_class":"P",
    "gn:feature_code":"PPL",
    "gn:name":"Fraldeu",
    "gn:population":0,
    "gn:timezone":"Europe/Lisbon",
    "iso:country":"PT",
    "wof:name":"Fraldeu",
    "wof:placetype":"locality"
},
  "geometry": {"coordinates":[-8.35558,40.06733],"type":"Point"}
}