{
  "type": "Feature",
  "properties": {
    "gn:admin1_code":"2.0",
    "gn:admin2_code":"0114",
    "gn:admin3_code":"11401.0",
    "gn:asciiname":"Picada",
    "gn:country_code":"PT",
    "gn:dem":66,
    "gn:feature_class":"P",
    "gn:feature_code":"PPL",
    "gn:name":"Picada",
    "gn:population":0,
    "gn:timezone":"Europe/Lisbon",
    "iso:country":"PT",
    "name:cat_x_preferred":[
        "Picada"
    ],
    "name:ces_x_preferred":[
        "Picada"
    ],
    "name:fra_x_preferred":[
        "Picada"
    ],
    "name:ita_x_preferred":[
        "Picada"
    ],
    "name:spa_x_preferred":[
        "Picada"
    ],
    "wof:name":"Picada",
    "wof:placetype":"locality"
},
  "geometry": {"coordinates":[-8.59382,40.50279000000001],"type":"Point"}
}