{
  "type": "Feature",
  "properties": {
    "gn:admin1_code":"22",
    "gn:admin2_code":"1816",
    "gn:admin3_code":"181616.0",
    "gn:asciiname":"Sul",
    "gn:country_code":"PT",
    "gn:dem":256,
    "gn:feature_class":"P",
    "gn:feature_code":"PPL",
    "gn:name":"Sul",
    "gn:population":0,
    "gn:timezone":"Europe/Lisbon",
    "iso:country":"PT",
    "wof:name":"Sul",
    "wof:placetype":"locality"
},
  "geometry": {"coordinates":[-8.04413,40.8368],"type":"Point"}
}