{
  "type": "Feature",
  "properties": {
    "gn:admin1_code":"02",
    "gn:admin2_code":"0101",
    "gn:admin3_code":"10117.0",
    "gn:asciiname":"Travasso",
    "gn:country_code":"PT",
    "gn:dem":64,
    "gn:feature_class":"P",
    "gn:feature_code":"PPL",
    "gn:name":"Travass\u00f4",
    "gn:population":0,
    "gn:timezone":"Europe/Lisbon",
    "iso:country":"PT",
    "wof:name":"Travasso",
    "wof:placetype":"locality"
},
  "geometry": {"coordinates":[-8.50568,40.59652],"type":"Point"}
}