{
  "type": "Feature",
  "properties": {
    "gn:admin1_code":"16",
    "gn:admin2_code":"1212",
    "gn:admin3_code":"121208.0",
    "gn:asciiname":"Monte Claro",
    "gn:country_code":"PT",
    "gn:dem":264,
    "gn:feature_class":"P",
    "gn:feature_code":"PPL",
    "gn:name":"Monte Claro",
    "gn:population":0,
    "gn:timezone":"Europe/Lisbon",
    "iso:country":"PT",
    "wof:name":"Monte Claro",
    "wof:placetype":"locality"
},
  "geometry": {"coordinates":[-7.71858,39.53045],"type":"Point"}
}