{
  "type": "Feature",
  "properties": {
    "gn:admin1_code":"09",
    "gn:admin2_code":"0807",
    "gn:admin3_code":"80701.0",
    "gn:asciiname":"Pedregosa",
    "gn:country_code":"PT",
    "gn:dem":57,
    "gn:feature_class":"P",
    "gn:feature_code":"PPL",
    "gn:name":"Pedregosa",
    "gn:population":0,
    "gn:timezone":"Europe/Lisbon",
    "iso:country":"PT",
    "wof:name":"Pedregosa",
    "wof:placetype":"locality"
},
  "geometry": {"coordinates":[-8.75741,37.13018],"type":"Point"}
}