{
  "type": "Feature",
  "properties": {
    "gn:admin1_code":"22.0",
    "gn:admin2_code":"1801",
    "gn:admin3_code":"180105.0",
    "gn:asciiname":"Coura",
    "gn:country_code":"PT",
    "gn:dem":668,
    "gn:feature_class":"P",
    "gn:feature_code":"PPL",
    "gn:name":"Coura",
    "gn:population":0,
    "gn:timezone":"Europe/Lisbon",
    "iso:country":"PT",
    "wof:name":"Coura",
    "wof:placetype":"locality"
},
  "geometry": {"coordinates":[-7.6549,41.11205],"type":"Point"}
}