{
  "type": "Feature",
  "properties": {
    "gn:country":"PT",
    "gn:fcode":"PPL",
    "gn:population":0,
    "iso:country":"PT",
    "name:ast_x_preferred":[
        "Sernancelhe"
    ],
    "name:ceb_x_preferred":[
        "Sernancelhe"
    ],
    "name:che_x_preferred":[
        "\u0421\u0435\u0440\u043d\u0430\u043d\u0441\u0435\u043b\u044c\u0438"
    ],
    "name:eng_x_preferred":[
        "Sernancelhe"
    ],
    "name:fra_x_preferred":[
        "Sernancelhe"
    ],
    "name:nan_x_preferred":[
        "Sernancelhe"
    ],
    "name:nld_x_preferred":[
        "Sernancelhe"
    ],
    "name:pol_x_preferred":[
        "Sernancelhe"
    ],
    "name:por_x_preferred":[
        "Sernancelhe"
    ],
    "name:rus_x_preferred":[
        "\u0421\u0435\u0440\u043d\u0430\u043d\u0441\u0435\u043b\u044c\u0435"
    ],
    "name:spa_x_preferred":[
        "Sernancelhe"
    ],
    "name:tat_x_preferred":[
        "\u0421\u0435\u0440\u043d\u0430\u043d\u0441\u0435\u043b\u044c\u0438"
    ],
    "name:tur_x_preferred":[
        "Sernancelhe"
    ],
    "qs_pg:aaroncc":"PT",
    "qs_pg:gn_country":"PT",
    "qs_pg:gn_fcode":"PPL",
    "qs_pg:gn_pop":0,
    "qs_pg:name":"Sernancelhe",
    "qs_pg:name_adm0":"Portugal",
    "qs_pg:name_adm1":"Viseu",
    "qs_pg:photos":159,
    "qs_pg:photos_1k":32,
    "qs_pg:photos_9k":1,
    "qs_pg:photos_9r":4,
    "qs_pg:photos_all":159,
    "qs_pg:photos_sr":4,
    "qs_pg:pop_sr":0,
    "qs_pg:qs_pg_placetype":"locality",
    "qs_pg:qs_pg_placetype_gp":"Town",
    "qs_pg:woe_adm0":23424925,
    "woe:adm0_id":23424925,
    "woe:name_adm0":"Portugal",
    "woe:name_adm1":"Viseu",
    "woe:placetype":"Town",
    "wof:name":"Sernancelhe",
    "wof:placetype":"locality"
},
  "geometry": {"coordinates":[-7.49342,40.89871],"type":"Point"}
}