{
  "type": "Feature",
  "properties": {
    "gn:admin1_code":"7.0",
    "gn:admin2_code":"0603",
    "gn:admin3_code":"60301.0",
    "gn:asciiname":"Anagueis",
    "gn:country_code":"PT",
    "gn:dem":168,
    "gn:feature_class":"P",
    "gn:feature_code":"PPL",
    "gn:name":"Anagueis",
    "gn:population":0,
    "gn:timezone":"Europe/Lisbon",
    "iso:country":"PT",
    "wof:name":"Anagueis",
    "wof:placetype":"locality"
},
  "geometry": {"coordinates":[-8.39079,40.14518],"type":"Point"}
}