{
  "type": "Feature",
  "properties": {
    "gn:admin1_code":"2.0",
    "gn:admin2_code":"0101",
    "gn:admin3_code":"10116.0",
    "gn:asciiname":"Fontinha",
    "gn:country_code":"PT",
    "gn:dem":29,
    "gn:feature_class":"P",
    "gn:feature_code":"PPL",
    "gn:name":"Fontinha",
    "gn:population":0,
    "gn:timezone":"Europe/Lisbon",
    "iso:country":"PT",
    "wof:name":"Fontinha",
    "wof:placetype":"locality"
},
  "geometry": {"coordinates":[-8.49957,40.60532],"type":"Point"}
}