{
  "type": "Feature",
  "properties": {
    "gn:admin1_code":"7.0",
    "gn:admin2_code":"0616",
    "gn:admin3_code":"61614.0",
    "gn:asciiname":"Boico",
    "gn:country_code":"PT",
    "gn:dem":205,
    "gn:feature_class":"P",
    "gn:feature_code":"PPL",
    "gn:name":"Boi\u00e7o",
    "gn:population":0,
    "gn:timezone":"Europe/Lisbon",
    "iso:country":"PT",
    "wof:name":"Boico",
    "wof:placetype":"locality"
},
  "geometry": {"coordinates":[-8.051,40.36237],"type":"Point"}
}