{
  "type": "Feature",
  "properties": {
    "gn:admin1_code":"21.0",
    "gn:admin2_code":"1712",
    "gn:admin3_code":"171208.0",
    "gn:asciiname":"Curros",
    "gn:country_code":"PT",
    "gn:dem":544,
    "gn:feature_class":"P",
    "gn:feature_code":"PPL",
    "gn:name":"Curros",
    "gn:population":0,
    "gn:timezone":"Europe/Lisbon",
    "iso:country":"PT",
    "wof:name":"Curros",
    "wof:placetype":"locality"
},
  "geometry": {"coordinates":[-7.45913,41.50758],"type":"Point"}
}