{
  "type": "Feature",
  "properties": {
    "gn:admin1_code":"4.0",
    "gn:admin2_code":"0309",
    "gn:admin3_code":"30918.0",
    "gn:asciiname":"Moure",
    "gn:country_code":"PT",
    "gn:dem":141,
    "gn:feature_class":"P",
    "gn:feature_code":"PPL",
    "gn:name":"Moure",
    "gn:population":0,
    "gn:timezone":"Europe/Lisbon",
    "iso:country":"PT",
    "wof:name":"Moure",
    "wof:placetype":"locality"
},
  "geometry": {"coordinates":[-8.33417,41.60774],"type":"Point"}
}