{
  "type": "Feature",
  "properties": {
    "gn:admin1_code":"17",
    "gn:admin2_code":"1301",
    "gn:admin3_code":"130128.0",
    "gn:asciiname":"Rebordelo",
    "gn:country_code":"PT",
    "gn:dem":262,
    "gn:feature_class":"P",
    "gn:feature_code":"PPL",
    "gn:name":"Rebordelo",
    "gn:population":0,
    "gn:timezone":"Europe/Lisbon",
    "iso:country":"PT",
    "wof:name":"Rebordelo",
    "wof:placetype":"locality"
},
  "geometry": {"coordinates":[-7.98536,41.34408],"type":"Point"}
}