{
  "type": "Feature",
  "properties": {
    "gn:admin1_code":"14",
    "gn:admin2_code":"1101",
    "gn:admin3_code":"110110.0",
    "gn:asciiname":"Soeiro Cunhado",
    "gn:country_code":"PT",
    "gn:dem":152,
    "gn:feature_class":"P",
    "gn:feature_code":"PPL",
    "gn:name":"Soeiro Cunhado",
    "gn:population":0,
    "gn:timezone":"Europe/Lisbon",
    "iso:country":"PT",
    "wof:name":"Soeiro Cunhado",
    "wof:placetype":"locality"
},
  "geometry": {"coordinates":[-9.11667,39.05],"type":"Point"}
}