{
  "type": "Feature",
  "properties": {
    "gn:admin1_code":"20.0",
    "gn:admin2_code":"1602",
    "gn:admin3_code":"160216.0",
    "gn:asciiname":"Cruzinho",
    "gn:country_code":"PT",
    "gn:dem":29,
    "gn:feature_class":"P",
    "gn:feature_code":"PPL",
    "gn:name":"Cruzinho",
    "gn:population":0,
    "gn:timezone":"Europe/Lisbon",
    "iso:country":"PT",
    "wof:name":"Cruzinho",
    "wof:placetype":"locality"
},
  "geometry": {"coordinates":[-8.80705,41.85818],"type":"Point"}
}