{
  "type": "Feature",
  "properties": {
    "gn:admin1_code":"22",
    "gn:admin2_code":"1802",
    "gn:admin3_code":"180206.0",
    "gn:asciiname":"Povoa de Santo Amaro",
    "gn:country_code":"PT",
    "gn:dem":283,
    "gn:feature_class":"P",
    "gn:feature_code":"PPL",
    "gn:name":"P\u00f3voa de Santo Amaro",
    "gn:population":0,
    "gn:timezone":"Europe/Lisbon",
    "iso:country":"PT",
    "wof:name":"Povoa de Santo Amaro",
    "wof:placetype":"locality"
},
  "geometry": {"coordinates":[-8.03545,40.41008],"type":"Point"}
}