{
  "type": "Feature",
  "properties": {
    "gn:admin1_code":"21.0",
    "gn:admin2_code":"1706",
    "gn:admin3_code":"170625.0",
    "gn:asciiname":"Ladrugais",
    "gn:country_code":"PT",
    "gn:dem":802,
    "gn:feature_class":"P",
    "gn:feature_code":"PPL",
    "gn:name":"Ladrugais",
    "gn:population":0,
    "gn:timezone":"Europe/Lisbon",
    "iso:country":"PT",
    "wof:name":"Ladrugais",
    "wof:placetype":"locality"
},
  "geometry": {"coordinates":[-7.91908,41.72116],"type":"Point"}
}