{
  "type": "Feature",
  "properties": {
    "gn:admin1_code":"18",
    "gn:admin2_code":"1403",
    "gn:admin3_code":"140304.0",
    "gn:asciiname":"Besteiros",
    "gn:country_code":"PT",
    "gn:dem":89,
    "gn:feature_class":"P",
    "gn:feature_code":"PPL",
    "gn:name":"Besteiros",
    "gn:population":0,
    "gn:timezone":"Europe/Lisbon",
    "iso:country":"PT",
    "name:ceb_x_preferred":[
        "Besteiros"
    ],
    "name:deu_x_preferred":[
        "Besteiros"
    ],
    "name:fra_x_preferred":[
        "Besteiros"
    ],
    "name:glg_x_preferred":[
        "Besteiros"
    ],
    "name:nld_x_preferred":[
        "Besteiros"
    ],
    "name:por_x_preferred":[
        "Besteiros"
    ],
    "name:rus_x_preferred":[
        "\u0411\u0435\u0448\u0442\u0435\u0439\u0440\u0443\u0448"
    ],
    "name:ukr_x_preferred":[
        "\u0411\u0435\u0448\u0442\u0435\u0439\u0440\u0443\u0448"
    ],
    "wof:name":"Besteiros",
    "wof:placetype":"locality"
},
  "geometry": {"coordinates":[-8.4756,39.15277],"type":"Point"}
}