{
  "type": "Feature",
  "properties": {
    "gn:admin1_code":"4.0",
    "gn:admin2_code":"0302",
    "gn:admin3_code":"30238.0",
    "gn:asciiname":"Pedra Furada",
    "gn:country_code":"PT",
    "gn:dem":86,
    "gn:feature_class":"P",
    "gn:feature_code":"PPL",
    "gn:name":"Pedra Furada",
    "gn:population":0,
    "gn:timezone":"Europe/Lisbon",
    "iso:country":"PT",
    "name:fra_x_preferred":[
        "Pedra Furada"
    ],
    "name:ind_x_preferred":[
        "Pedra Furada"
    ],
    "name:ita_x_preferred":[
        "Pedra Furada"
    ],
    "name:por_x_preferred":[
        "Pedra Furada"
    ],
    "name:spa_x_preferred":[
        "Pedra Furada"
    ],
    "wof:name":"Pedra Furada",
    "wof:placetype":"locality"
},
  "geometry": {"coordinates":[-8.62619,41.46932],"type":"Point"}
}