{
  "type": "Feature",
  "properties": {
    "gn:admin1_code":"02",
    "gn:admin2_code":"0104",
    "gn:admin3_code":"10402.0",
    "gn:asciiname":"Vila Nova",
    "gn:country_code":"PT",
    "gn:dem":517,
    "gn:feature_class":"P",
    "gn:feature_code":"PPL",
    "gn:name":"Vila Nova",
    "gn:population":0,
    "gn:timezone":"Europe/Lisbon",
    "iso:country":"PT",
    "wof:name":"Vila Nova",
    "wof:placetype":"locality"
},
  "geometry": {"coordinates":[-8.1395,40.96441],"type":"Point"}
}