{
  "type": "Feature",
  "properties": {
    "gn:admin1_code":"20",
    "gn:admin2_code":"1604",
    "gn:admin3_code":"160412.0",
    "gn:asciiname":"Souto de Baixo",
    "gn:country_code":"PT",
    "gn:dem":349,
    "gn:feature_class":"P",
    "gn:feature_code":"PPL",
    "gn:name":"Souto de Baixo",
    "gn:population":0,
    "gn:timezone":"Europe/Lisbon",
    "iso:country":"PT",
    "wof:name":"Souto de Baixo",
    "wof:placetype":"locality"
},
  "geometry": {"coordinates":[-8.44666,42.01779000000001],"type":"Point"}
}