{
  "type": "Feature",
  "properties": {
    "gn:admin1_code":"17",
    "gn:admin2_code":"1303",
    "gn:admin3_code":"130332.0",
    "gn:asciiname":"Vila Fria",
    "gn:country_code":"PT",
    "gn:dem":187,
    "gn:feature_class":"P",
    "gn:feature_code":"PPL",
    "gn:name":"Vila Fria",
    "gn:population":0,
    "gn:timezone":"Europe/Lisbon",
    "iso:country":"PT",
    "wof:name":"Vila Fria",
    "wof:placetype":"locality"
},
  "geometry": {"coordinates":[-8.24332,41.38772],"type":"Point"}
}