{
  "type": "Feature",
  "properties": {
    "gn:admin1_code":"14",
    "gn:admin2_code":"1113",
    "gn:admin3_code":"111306.0",
    "gn:asciiname":"Concelhos",
    "gn:country_code":"PT",
    "gn:dem":79,
    "gn:feature_class":"P",
    "gn:feature_code":"PPL",
    "gn:name":"Concelhos",
    "gn:population":0,
    "gn:timezone":"Europe/Lisbon",
    "iso:country":"PT",
    "wof:name":"Concelhos",
    "wof:placetype":"locality"
},
  "geometry": {"coordinates":[-9.32103,39.03264],"type":"Point"}
}