{
  "type": "Feature",
  "properties": {
    "gn:admin1_code":"20.0",
    "gn:admin2_code":"1607",
    "gn:admin3_code":"160703.0",
    "gn:asciiname":"Fojo",
    "gn:country_code":"PT",
    "gn:dem":69,
    "gn:feature_class":"P",
    "gn:feature_code":"PPL",
    "gn:name":"Fojo",
    "gn:population":0,
    "gn:timezone":"Europe/Lisbon",
    "iso:country":"PT",
    "wof:name":"Fojo",
    "wof:placetype":"locality"
},
  "geometry": {"coordinates":[-8.65848,41.76671],"type":"Point"}
}