{
  "type": "Feature",
  "properties": {
    "gn:admin1_code":"14",
    "gn:admin2_code":"1109",
    "gn:admin3_code":"110909.0",
    "gn:asciiname":"Almada",
    "gn:country_code":"PT",
    "gn:dem":156,
    "gn:feature_class":"P",
    "gn:feature_code":"PPL",
    "gn:name":"Almada",
    "gn:population":0,
    "gn:timezone":"Europe/Lisbon",
    "iso:country":"PT",
    "name:ara_x_preferred":[
        "\u0623\u0644\u0645\u0627\u062f\u0627"
    ],
    "name:arg_x_preferred":[
        "Almada"
    ],
    "name:bel_x_preferred":[
        "\u0410\u043b\u043c\u0430\u0434\u0430"
    ],
    "name:cat_x_preferred":[
        "Almada"
    ],
    "name:ceb_x_preferred":[
        "Almada"
    ],
    "name:ces_x_preferred":[
        "Almada"
    ],
    "name:deu_x_preferred":[
        "Almada"
    ],
    "name:ell_x_preferred":[
        "\u0391\u03bb\u03bc\u03ac\u03b4\u03b1"
    ],
    "name:epo_x_preferred":[
        "Almada"
    ],
    "name:eus_x_preferred":[
        "Almada"
    ],
    "name:fas_x_preferred":[
        "\u0622\u0644\u0645\u0627\u062f\u0627"
    ],
    "name:fin_x_preferred":[
        "Almada"
    ],
    "name:fra_x_preferred":[
        "Almada"
    ],
    "name:glg_x_preferred":[
        "Almada"
    ],
    "name:hun_x_preferred":[
        "Almada"
    ],
    "name:hye_x_preferred":[
        "\u0531\u056c\u0574\u0561\u0564\u0561"
    ],
    "name:ind_x_preferred":[
        "Almada"
    ],
    "name:ita_x_preferred":[
        "Almada"
    ],
    "name:jpn_x_preferred":[
        "\u30a2\u30eb\u30de\u30c0"
    ],
    "name:kat_x_preferred":[
        "\u10d0\u10da\u10db\u10d0\u10d3\u10d0"
    ],
    "name:kor_x_preferred":[
        "\uc54c\ub9c8\ub2e4"
    ],
    "name:lit_x_preferred":[
        "Almada"
    ],
    "name:msa_x_preferred":[
        "Almada"
    ],
    "name:mzn_x_preferred":[
        "\u0622\u0644\u0645\u0627\u062f\u0627"
    ],
    "name:nld_x_preferred":[
        "Almada"
    ],
    "name:oci_x_preferred":[
        "Almada"
    ],
    "name:pnb_x_preferred":[
        "\u0627\u0644\u0645\u0627\u062f\u0627"
    ],
    "name:pol_x_preferred":[
        "Almada"
    ],
    "name:por_x_preferred":[
        "Almada"
    ],
    "name:ron_x_preferred":[
        "Almada"
    ],
    "name:rus_x_preferred":[
        "\u0410\u043b\u043c\u0430\u0434\u0430"
    ],
    "name:spa_x_preferred":[
        "Almada"
    ],
    "name:srp_x_preferred":[
        "\u0410\u043b\u043c\u0430\u0434\u0430"
    ],
    "name:swa_x_preferred":[
        "Almada"
    ],
    "name:tat_x_preferred":[
        "\u0410\u043b\u043c\u0430\u0434\u0430"
    ],
    "name:tha_x_preferred":[
        "\u0e2d\u0e31\u0e25\u0e21\u0e32\u0e14\u0e32"
    ],
    "name:tur_x_preferred":[
        "Almada"
    ],
    "name:ukr_x_preferred":[
        "\u0410\u043b\u043c\u0430\u0434\u0430"
    ],
    "name:vie_x_preferred":[
        "Almada"
    ],
    "name:vol_x_preferred":[
        "Almada"
    ],
    "name:war_x_preferred":[
        "Almada"
    ],
    "name:zho_x_preferred":[
        "\u963f\u723e\u99ac\u9054"
    ],
    "wof:name":"Almada",
    "wof:placetype":"locality"
},
  "geometry": {"coordinates":[-9.3448,38.93057],"type":"Point"}
}