{
  "type": "Feature",
  "properties": {
    "gn:admin1_code":"17.0",
    "gn:admin2_code":"1305",
    "gn:admin3_code":"130523.0",
    "gn:asciiname":"Cancela Nova",
    "gn:country_code":"PT",
    "gn:dem":323,
    "gn:feature_class":"P",
    "gn:feature_code":"PPL",
    "gn:name":"Cancela Nova",
    "gn:population":0,
    "gn:timezone":"Europe/Lisbon",
    "iso:country":"PT",
    "wof:name":"Cancela Nova",
    "wof:placetype":"locality"
},
  "geometry": {"coordinates":[-8.28207,41.29347],"type":"Point"}
}