{
  "type": "Feature",
  "properties": {
    "gn:admin1_code":"17",
    "gn:admin2_code":"1302",
    "gn:admin3_code":"130211.0",
    "gn:asciiname":"Vilarelho",
    "gn:country_code":"PT",
    "gn:dem":558,
    "gn:feature_class":"P",
    "gn:feature_code":"PPL",
    "gn:name":"Vilarelho",
    "gn:population":0,
    "gn:timezone":"Europe/Lisbon",
    "iso:country":"PT",
    "wof:name":"Vilarelho",
    "wof:placetype":"locality"
},
  "geometry": {"coordinates":[-8.01366,41.18362],"type":"Point"}
}