{
  "type": "Feature",
  "properties": {
    "gn:admin1_code":"14",
    "gn:admin2_code":"1111",
    "gn:admin3_code":"111110.0",
    "gn:asciiname":"A da Longa",
    "gn:country_code":"PT",
    "gn:dem":120,
    "gn:feature_class":"P",
    "gn:feature_code":"PPL",
    "gn:name":"A da Longa",
    "gn:population":0,
    "gn:timezone":"Europe/Lisbon",
    "iso:country":"PT",
    "name:und_x_variant":[
        "A do Longo",
        "A da Longa"
    ],
    "wof:name":"A da Longa",
    "wof:placetype":"locality"
},
  "geometry": {"coordinates":[-9.39651,38.8831],"type":"Point"}
}