{
  "type": "Feature",
  "properties": {
    "gn:admin1_code":"7.0",
    "gn:admin2_code":"0616",
    "gn:admin3_code":"61614.0",
    "gn:asciiname":"Barras",
    "gn:country_code":"PT",
    "gn:dem":317,
    "gn:feature_class":"P",
    "gn:feature_code":"PPL",
    "gn:name":"Barras",
    "gn:population":0,
    "gn:timezone":"Europe/Lisbon",
    "iso:country":"PT",
    "wof:name":"Barras",
    "wof:placetype":"locality"
},
  "geometry": {"coordinates":[-7.99454,40.35498],"type":"Point"}
}