{
  "type": "Feature",
  "properties": {
    "gn:admin1_code":"06",
    "gn:admin2_code":"0511",
    "gn:admin3_code":"51101.0",
    "gn:asciiname":"Perdigao",
    "gn:country_code":"PT",
    "gn:dem":267,
    "gn:feature_class":"P",
    "gn:feature_code":"PPL",
    "gn:name":"Perdig\u00e3o",
    "gn:population":0,
    "gn:timezone":"Europe/Lisbon",
    "iso:country":"PT",
    "wof:name":"Perdigao",
    "wof:placetype":"locality"
},
  "geometry": {"coordinates":[-7.73366,39.68527],"type":"Point"}
}