{
  "type": "Feature",
  "properties": {
    "gn:admin1_code":"4.0",
    "gn:admin2_code":"0304",
    "gn:admin3_code":"30406.0",
    "gn:asciiname":"Casa",
    "gn:country_code":"PT",
    "gn:dem":468,
    "gn:feature_class":"P",
    "gn:feature_code":"PPL",
    "gn:name":"Casa",
    "gn:population":0,
    "gn:timezone":"Europe/Lisbon",
    "iso:country":"PT",
    "wof:name":"Casa",
    "wof:placetype":"locality"
},
  "geometry": {"coordinates":[-8.02165,41.54106],"type":"Point"}
}