{
  "type": "Feature",
  "properties": {
    "gn:admin1_code":"05",
    "gn:admin2_code":"0403",
    "gn:admin3_code":"40317.0",
    "gn:asciiname":"Selores",
    "gn:country_code":"PT",
    "gn:dem":617,
    "gn:feature_class":"P",
    "gn:feature_code":"PPL",
    "gn:name":"Selores",
    "gn:population":0,
    "gn:timezone":"Europe/Lisbon",
    "iso:country":"PT",
    "wof:name":"Selores",
    "wof:placetype":"locality"
},
  "geometry": {"coordinates":[-7.29265,41.20448],"type":"Point"}
}