{
  "type": "Feature",
  "properties": {
    "gn:admin1_code":"22.0",
    "gn:admin2_code":"1803",
    "gn:admin3_code":"180309.0",
    "gn:asciiname":"Codecal",
    "gn:country_code":"PT",
    "gn:dem":1008,
    "gn:feature_class":"P",
    "gn:feature_code":"PPL",
    "gn:name":"Code\u00e7al",
    "gn:population":0,
    "gn:timezone":"Europe/Lisbon",
    "iso:country":"PT",
    "wof:name":"Codecal",
    "wof:placetype":"locality"
},
  "geometry": {"coordinates":[-7.91135,41.00569],"type":"Point"}
}