{
  "type": "Feature",
  "properties": {
    "gn:admin1_code":"20",
    "gn:admin2_code":"1604",
    "gn:admin3_code":"160417.0",
    "gn:asciiname":"Rodas",
    "gn:country_code":"PT",
    "gn:dem":110,
    "gn:feature_class":"P",
    "gn:feature_code":"PPL",
    "gn:name":"Rodas",
    "gn:population":0,
    "gn:timezone":"Europe/Lisbon",
    "iso:country":"PT",
    "name:ell_x_preferred":[
        "\u03a1\u03bf\u03b4\u03ac\u03c2"
    ],
    "name:fra_x_preferred":[
        "Rodas"
    ],
    "name:ita_x_preferred":[
        "Rodas"
    ],
    "name:kat_x_preferred":[
        "\u10e0\u10dd\u10d3\u10d0\u10e1\u10d8"
    ],
    "name:pol_x_preferred":[
        "Rodas"
    ],
    "name:por_x_preferred":[
        "Rodas"
    ],
    "name:sco_x_preferred":[
        "Rodas"
    ],
    "name:spa_x_preferred":[
        "Rodas"
    ],
    "name:vie_x_preferred":[
        "Rodas"
    ],
    "name:zho_x_preferred":[
        "\u7f85\u9054\u65af"
    ],
    "wof:name":"Rodas",
    "wof:placetype":"locality"
},
  "geometry": {"coordinates":[-8.47725,42.0645],"type":"Point"}
}