{
  "type": "Feature",
  "properties": {
    "gn:country":"PT",
    "gn:fcode":"PPL",
    "gn:population":5724,
    "iso:country":"PT",
    "name:cat_x_preferred":[
        "Caldelas"
    ],
    "name:ceb_x_preferred":[
        "Caldelas"
    ],
    "name:deu_x_preferred":[
        "Caldelas"
    ],
    "name:fra_x_preferred":[
        "Caldelas"
    ],
    "name:glg_x_preferred":[
        "Caldelas"
    ],
    "name:ita_x_preferred":[
        "Caldelas"
    ],
    "name:por_x_preferred":[
        "Caldelas"
    ],
    "name:rus_x_preferred":[
        "\u041a\u0430\u043b\u0434\u0435\u043b\u0430\u0448"
    ],
    "name:spa_x_preferred":[
        "Caldelas"
    ],
    "name:ukr_x_preferred":[
        "\u041a\u0430\u043b\u0434\u0435\u043b\u0430\u0448"
    ],
    "qs_pg:aaroncc":"PT",
    "qs_pg:gn_country":"PT",
    "qs_pg:gn_fcode":"PPL",
    "qs_pg:gn_pop":5724,
    "qs_pg:name":"Caldelas",
    "qs_pg:name_adm0":"Portugal",
    "qs_pg:name_adm1":"Braga",
    "qs_pg:photos_9k":1,
    "qs_pg:photos_9r":1,
    "qs_pg:photos_all":13,
    "qs_pg:photos_sr":0,
    "qs_pg:pop_sr":5,
    "qs_pg:qs_pg_placetype":"locality",
    "qs_pg:qs_pg_placetype_gp":"Town",
    "qs_pg:woe_adm0":23424925,
    "woe:adm0_id":23424925,
    "woe:name_adm0":"Portugal",
    "woe:name_adm1":"Braga",
    "woe:placetype":"Town",
    "wof:name":"Caldelas",
    "wof:placetype":"locality",
    "wof:population":5724
},
  "geometry": {"coordinates":[-8.38148,41.67101],"type":"Point"}
}