{
  "type": "Feature",
  "properties": {
    "gn:country":"PT",
    "gn:fcode":"PPL",
    "gn:population":0,
    "iso:country":"PT",
    "name:ceb_x_preferred":[
        "Canelas"
    ],
    "name:deu_x_preferred":[
        "Canelas"
    ],
    "name:fra_x_preferred":[
        "Canelas"
    ],
    "name:glg_x_preferred":[
        "Canelas"
    ],
    "name:nld_x_preferred":[
        "Canelas"
    ],
    "name:por_x_preferred":[
        "Canelas"
    ],
    "name:rus_x_preferred":[
        "\u041a\u0430\u043d\u0435\u043b\u0430\u0448"
    ],
    "name:spa_x_preferred":[
        "Canelas"
    ],
    "name:swe_x_preferred":[
        "Canelas"
    ],
    "name:tur_x_preferred":[
        "Canelas"
    ],
    "name:vie_x_preferred":[
        "Canelas"
    ],
    "qs_pg:aaroncc":"PT",
    "qs_pg:gn_country":"PT",
    "qs_pg:gn_fcode":"PPL",
    "qs_pg:gn_pop":0,
    "qs_pg:name":"Canelas",
    "qs_pg:name_adm0":"Portugal",
    "qs_pg:name_adm1":"Aveiro",
    "qs_pg:photos_9k":1,
    "qs_pg:photos_9r":1,
    "qs_pg:photos_all":6,
    "qs_pg:photos_sr":0,
    "qs_pg:pop_sr":0,
    "qs_pg:qs_pg_placetype":"locality",
    "qs_pg:qs_pg_placetype_gp":"Town",
    "qs_pg:woe_adm0":23424925,
    "woe:adm0_id":23424925,
    "woe:name_adm0":"Portugal",
    "woe:name_adm1":"Aveiro",
    "woe:placetype":"Town",
    "wof:name":"Canelas",
    "wof:placetype":"locality"
},
  "geometry": {"coordinates":[-8.20279,40.97294],"type":"Point"}
}