{
  "type": "Feature",
  "properties": {
    "gn:admin1_code":"5.0",
    "gn:admin2_code":"0402",
    "gn:admin3_code":"40209.0",
    "gn:asciiname":"Fontes",
    "gn:country_code":"PT",
    "gn:dem":894,
    "gn:feature_class":"P",
    "gn:feature_code":"PPL",
    "gn:name":"Fontes",
    "gn:population":0,
    "gn:timezone":"Europe/Lisbon",
    "iso:country":"PT",
    "name:ukr_x_preferred":[
        "\u0424\u043e\u043d\u0442\u0435\u0448"
    ],
    "wof:name":"Fontes",
    "wof:placetype":"locality"
},
  "geometry": {"coordinates":[-6.84436,41.80834],"type":"Point"}
}