{
  "type": "Feature",
  "properties": {
    "gn:admin1_code":"4.0",
    "gn:admin2_code":"0303",
    "gn:admin3_code":"30361.0",
    "gn:asciiname":"Macada",
    "gn:country_code":"PT",
    "gn:dem":177,
    "gn:feature_class":"P",
    "gn:feature_code":"PPL",
    "gn:name":"Macada",
    "gn:population":0,
    "gn:timezone":"Europe/Lisbon",
    "iso:country":"PT",
    "wof:name":"Macada",
    "wof:placetype":"locality"
},
  "geometry": {"coordinates":[-8.46621,41.49659000000001],"type":"Point"}
}