{
  "type": "Feature",
  "properties": {
    "iso:country":"PT",
    "qs_pg:aaroncc":"PT",
    "qs_pg:name":"Restauradores",
    "qs_pg:name_adm0":"Portugal",
    "qs_pg:name_adm1":"Lisboa",
    "qs_pg:photos":261,
    "qs_pg:photos_1k":53,
    "qs_pg:photos_9k":1,
    "qs_pg:photos_9r":4,
    "qs_pg:photos_all":261,
    "qs_pg:photos_sr":5,
    "qs_pg:pop_sr":0,
    "qs_pg:qs_pg_placetype":"locality",
    "qs_pg:qs_pg_placetype_gp":"Town",
    "qs_pg:woe_adm0":23424925,
    "woe:adm0_id":23424925,
    "woe:name_adm0":"Portugal",
    "woe:name_adm1":"Lisboa",
    "woe:placetype":"Town",
    "wof:name":"Restauradores",
    "wof:placetype":"locality"
},
  "geometry": {"coordinates":[-9.140882,38.715786],"type":"Point"}
}