{
  "type": "Feature",
  "properties": {
    "gn:admin1_code":"02",
    "gn:admin2_code":"0109",
    "gn:admin3_code":"10903.0",
    "gn:asciiname":"Povoas",
    "gn:country_code":"PT",
    "gn:dem":174,
    "gn:feature_class":"P",
    "gn:feature_code":"PPL",
    "gn:name":"P\u00f3voas",
    "gn:population":0,
    "gn:timezone":"Europe/Lisbon",
    "iso:country":"PT",
    "wof:name":"Povoas",
    "wof:placetype":"locality"
},
  "geometry": {"coordinates":[-8.46897,41.01422],"type":"Point"}
}