{
  "type": "Feature",
  "properties": {
    "gn:admin1_code":"7.0",
    "gn:admin2_code":"0611",
    "gn:admin3_code":"61111.0",
    "gn:asciiname":"Galizes",
    "gn:country_code":"PT",
    "gn:dem":489,
    "gn:feature_class":"P",
    "gn:feature_code":"PPL",
    "gn:name":"Galizes",
    "gn:population":0,
    "gn:timezone":"Europe/Lisbon",
    "iso:country":"PT",
    "wof:name":"Galizes",
    "wof:placetype":"locality"
},
  "geometry": {"coordinates":[-7.8937,40.31887],"type":"Point"}
}