{
  "type": "Feature",
  "properties": {
    "gn:admin1_code":"18",
    "gn:admin2_code":"1421",
    "gn:admin3_code":"142114.0",
    "gn:asciiname":"Resouro",
    "gn:country_code":"PT",
    "gn:dem":217,
    "gn:feature_class":"P",
    "gn:feature_code":"PPL",
    "gn:name":"Resouro",
    "gn:population":0,
    "gn:timezone":"Europe/Lisbon",
    "iso:country":"PT",
    "wof:name":"Resouro",
    "wof:placetype":"locality"
},
  "geometry": {"coordinates":[-8.59259,39.75513],"type":"Point"}
}