{
  "type": "Feature",
  "properties": {
    "gn:admin1_code":"18",
    "gn:admin2_code":"1407",
    "gn:admin3_code":"140705.0",
    "gn:asciiname":"Vale da Lama",
    "gn:country_code":"PT",
    "gn:dem":61,
    "gn:feature_class":"P",
    "gn:feature_code":"PPL",
    "gn:name":"Vale da Lama",
    "gn:population":0,
    "gn:timezone":"Europe/Lisbon",
    "iso:country":"PT",
    "wof:name":"Vale da Lama",
    "wof:placetype":"locality"
},
  "geometry": {"coordinates":[-8.49088,39.21826],"type":"Point"}
}