{
  "type": "Feature",
  "properties": {
    "gn:admin1_code":"06",
    "gn:admin2_code":"0510",
    "gn:admin3_code":"51003.0",
    "gn:asciiname":"Boa Farinha",
    "gn:country_code":"PT",
    "gn:dem":357,
    "gn:feature_class":"P",
    "gn:feature_code":"PPL",
    "gn:name":"Boa Farinha",
    "gn:population":0,
    "gn:timezone":"Europe/Lisbon",
    "iso:country":"PT",
    "wof:name":"Boa Farinha",
    "wof:placetype":"locality"
},
  "geometry": {"coordinates":[-8.10913,39.68566],"type":"Point"}
}