{
  "type": "Feature",
  "properties": {
    "gn:admin1_code":"19",
    "gn:admin2_code":"1512",
    "gn:admin3_code":"151201.0",
    "gn:asciiname":"Outao",
    "gn:cc2":"PT",
    "gn:country_code":"PT",
    "gn:dem":17,
    "gn:feature_class":"P",
    "gn:feature_code":"PPL",
    "gn:name":"Out\u00e3o",
    "gn:population":0,
    "gn:timezone":"Europe/Lisbon",
    "iso:country":"PT",
    "name:und_x_variant":[
        "Oit\u00e3o"
    ],
    "wof:name":"Outao",
    "wof:placetype":"locality"
},
  "geometry": {"coordinates":[-8.93407,38.48867],"type":"Point"}
}