{
  "type": "Feature",
  "properties": {
    "gn:country":"PT",
    "gn:fcode":"PPL",
    "gn:population":0,
    "iso:country":"PT",
    "name:deu_x_preferred":[
        "Parada de Tib\u00e3es"
    ],
    "name:eng_x_preferred":[
        "Parada de Tib\u00e3es"
    ],
    "name:fra_x_preferred":[
        "Parada de Tib\u00e3es"
    ],
    "name:kaz_x_preferred":[
        "\u041f\u0430\u0440\u0430\u0434\u0430-\u0434\u0435-\u0422\u0438\u0431\u0430\u0439\u043d\u0448"
    ],
    "name:nld_x_preferred":[
        "Parada de Tib\u00e3es"
    ],
    "name:por_x_preferred":[
        "Parada de Tib\u00e3es"
    ],
    "name:rus_x_preferred":[
        "\u041f\u0430\u0440\u0430\u0434\u0430-\u0434\u0435-\u0422\u0438\u0431\u0430\u0439\u043d\u0448"
    ],
    "name:spa_x_preferred":[
        "Parada de Tib\u00e3es"
    ],
    "name:ukr_x_preferred":[
        "\u041f\u0430\u0440\u0430\u0434\u0430-\u0434\u0435-\u0422\u0456\u0431\u0430\u0439\u043d\u0448"
    ],
    "name:und_x_variant":[
        "Tib\u00e3es"
    ],
    "qs_pg:aaroncc":"PT",
    "qs_pg:gn_country":"PT",
    "qs_pg:gn_fcode":"PPL",
    "qs_pg:gn_pop":0,
    "qs_pg:name":"Parada de Tib\u00e3es",
    "qs_pg:name_adm0":"Portugal",
    "qs_pg:name_adm1":"Braga",
    "qs_pg:photos":6,
    "qs_pg:photos_1k":1,
    "qs_pg:photos_9k":1,
    "qs_pg:photos_9r":1,
    "qs_pg:photos_all":6,
    "qs_pg:photos_sr":1,
    "qs_pg:pop_sr":0,
    "qs_pg:qs_pg_placetype":"locality",
    "qs_pg:qs_pg_placetype_gp":"Town",
    "qs_pg:woe_adm0":23424925,
    "woe:adm0_id":23424925,
    "woe:name_adm0":"Portugal",
    "woe:name_adm1":"Braga",
    "woe:placetype":"Town",
    "wof:name":"Parada de Tib\u00e3es",
    "wof:placetype":"locality"
},
  "geometry": {"coordinates":[-8.47282,41.55954],"type":"Point"}
}