{
  "type": "Feature",
  "properties": {
    "gn:admin1_code":"2.0",
    "gn:admin2_code":"0101",
    "gn:admin3_code":"10106.0",
    "gn:asciiname":"Alvarim",
    "gn:country_code":"PT",
    "gn:dem":66,
    "gn:feature_class":"P",
    "gn:feature_code":"PPL",
    "gn:name":"Alvarim",
    "gn:population":0,
    "gn:timezone":"Europe/Lisbon",
    "iso:country":"PT",
    "wof:name":"Alvarim",
    "wof:placetype":"locality"
},
  "geometry": {"coordinates":[-8.38575,40.54004000000001],"type":"Point"}
}