{
  "type": "Feature",
  "properties": {
    "gn:admin1_code":"20.0",
    "gn:admin2_code":"1607",
    "gn:admin3_code":"160723.0",
    "gn:asciiname":"Gaiao",
    "gn:country_code":"PT",
    "gn:dem":193,
    "gn:feature_class":"P",
    "gn:feature_code":"PPL",
    "gn:name":"Gai\u00e3o",
    "gn:population":0,
    "gn:timezone":"Europe/Lisbon",
    "iso:country":"PT",
    "wof:name":"Gaiao",
    "wof:placetype":"locality"
},
  "geometry": {"coordinates":[-8.58755,41.66127],"type":"Point"}
}