{
  "type": "Feature",
  "properties": {
    "gn:gn_country":"PT",
    "gn:gn_fcode":"PPL",
    "gn:gn_pop":0,
    "iso:country":"PT",
    "name:ast_x_preferred":[
        "Lever"
    ],
    "name:ceb_x_preferred":[
        "Lever"
    ],
    "name:deu_x_preferred":[
        "Lever"
    ],
    "name:eng_x_preferred":[
        "Lever"
    ],
    "name:fra_x_preferred":[
        "Lever"
    ],
    "name:kaz_x_preferred":[
        "\u041b\u0435\u0432\u0435\u0440"
    ],
    "name:msa_x_preferred":[
        "Lever"
    ],
    "name:nan_x_preferred":[
        "Lever"
    ],
    "name:nld_x_preferred":[
        "Lever"
    ],
    "name:por_x_preferred":[
        "Lever"
    ],
    "name:rus_x_preferred":[
        "\u041b\u0435\u0432\u0435\u0440"
    ],
    "name:spa_x_preferred":[
        "Lever"
    ],
    "name:tur_x_preferred":[
        "Lever"
    ],
    "name:zho_x_preferred":[
        "Lever"
    ],
    "qs_pg:aaroncc":"PT",
    "qs_pg:gn_country":"PT",
    "qs_pg:gn_fcode":"PPL",
    "qs_pg:gn_pop":0,
    "qs_pg:name":"Lever",
    "qs_pg:name_adm0":"Portugal",
    "qs_pg:name_adm1":"Porto",
    "qs_pg:photos_9k":1,
    "qs_pg:photos_9r":1,
    "qs_pg:photos_all":2,
    "qs_pg:photos_sr":0,
    "qs_pg:pop_sr":0,
    "qs_pg:qs_pg_placetype":"locality",
    "qs_pg:qs_pg_placetype_gp":"Town",
    "qs_pg:woe_adm0":23424925,
    "woe:adm0_id":23424925,
    "woe:name_adm0":"Portugal",
    "woe:name_adm1":"Porto",
    "woe:placetype":"Town",
    "wof:name":"Lever",
    "wof:placetype":"locality"
},
  "geometry": {"coordinates":[-8.47575,41.06681],"type":"Point"}
}