{
  "type": "Feature",
  "properties": {
    "gn:admin1_code":"19",
    "gn:admin2_code":"1505",
    "gn:admin3_code":"150502.0",
    "gn:asciiname":"Brejo da Silha do Centeio",
    "gn:country_code":"PT",
    "gn:dem":88,
    "gn:feature_class":"P",
    "gn:feature_code":"PPL",
    "gn:name":"Brejo da Silha do Centeio",
    "gn:population":0,
    "gn:timezone":"Europe/Lisbon",
    "iso:country":"PT",
    "wof:name":"Brejo da Silha do Centeio",
    "wof:placetype":"locality"
},
  "geometry": {"coordinates":[-8.46667,38.18333],"type":"Point"}
}