{
  "type": "Feature",
  "properties": {
    "gn:admin1_code":"13",
    "gn:admin2_code":"1001",
    "gn:admin3_code":"100103.0",
    "gn:asciiname":"Ferraria",
    "gn:country_code":"PT",
    "gn:dem":51,
    "gn:feature_class":"P",
    "gn:feature_code":"PPL",
    "gn:name":"Ferraria",
    "gn:population":0,
    "gn:timezone":"Europe/Lisbon",
    "iso:country":"PT",
    "wof:name":"Ferraria",
    "wof:placetype":"locality"
},
  "geometry": {"coordinates":[-8.95874,39.63673],"type":"Point"}
}