{
  "type": "Feature",
  "properties": {
    "gn:admin1_code":"11.0",
    "gn:admin2_code":"0901",
    "gn:admin3_code":"90106.0",
    "gn:asciiname":"Carregais",
    "gn:country_code":"PT",
    "gn:dem":742,
    "gn:feature_class":"P",
    "gn:feature_code":"PPL",
    "gn:name":"Carregais",
    "gn:population":0,
    "gn:timezone":"Europe/Lisbon",
    "iso:country":"PT",
    "wof:name":"Carregais",
    "wof:placetype":"locality"
},
  "geometry": {"coordinates":[-7.48634,40.78731],"type":"Point"}
}