{
  "type": "Feature",
  "properties": {
    "gn:admin1_code":"16",
    "gn:admin2_code":"1213",
    "gn:admin3_code":"121301.0",
    "gn:asciiname":"Horta da Cordeira",
    "gn:country_code":"PT",
    "gn:dem":140,
    "gn:feature_class":"P",
    "gn:feature_code":"PPL",
    "gn:name":"Horta da Cordeira",
    "gn:population":0,
    "gn:timezone":"Europe/Lisbon",
    "iso:country":"PT",
    "wof:name":"Horta da Cordeira",
    "wof:placetype":"locality"
},
  "geometry": {"coordinates":[-7.99218,39.20391],"type":"Point"}
}