{
  "type": "Feature",
  "properties": {
    "gn:admin1_code":"06",
    "gn:admin2_code":"0502",
    "gn:admin3_code":"50209.0",
    "gn:asciiname":"Freixial do Campo",
    "gn:country_code":"PT",
    "gn:dem":359,
    "gn:feature_class":"P",
    "gn:feature_code":"PPL",
    "gn:name":"Freixial do Campo",
    "gn:population":0,
    "gn:timezone":"Europe/Lisbon",
    "iso:country":"PT",
    "wof:name":"Freixial do Campo",
    "wof:placetype":"locality"
},
  "geometry": {"coordinates":[-7.55671,39.92412],"type":"Point"}
}