{
  "type": "Feature",
  "properties": {
    "gn:admin1_code":"7.0",
    "gn:admin2_code":"0603",
    "gn:admin3_code":"60301.0",
    "gn:asciiname":"Cestas",
    "gn:country_code":"PT",
    "gn:dem":143,
    "gn:feature_class":"P",
    "gn:feature_code":"PPL",
    "gn:name":"Cestas",
    "gn:population":0,
    "gn:timezone":"Europe/Lisbon",
    "iso:country":"PT",
    "name:bug_x_preferred":[
        "Cestas"
    ],
    "name:cat_x_preferred":[
        "Cest\u00e0s"
    ],
    "name:ceb_x_preferred":[
        "Cestas"
    ],
    "name:deu_x_preferred":[
        "Cestas"
    ],
    "name:eus_x_preferred":[
        "Cest\u00e0s"
    ],
    "name:fin_x_preferred":[
        "Cestas"
    ],
    "name:fra_x_preferred":[
        "Cestas"
    ],
    "name:hun_x_preferred":[
        "Cestas"
    ],
    "name:ind_x_preferred":[
        "Cestas"
    ],
    "name:ita_x_preferred":[
        "Cestas"
    ],
    "name:kaz_x_preferred":[
        "\u0421\u0435\u0441\u0442\u0430\u0441"
    ],
    "name:lat_x_preferred":[
        "Cestas"
    ],
    "name:mlg_x_preferred":[
        "Cestas"
    ],
    "name:msa_x_preferred":[
        "Cestas"
    ],
    "name:nld_x_preferred":[
        "Cestas"
    ],
    "name:oci_x_preferred":[
        "Cest\u00e0s"
    ],
    "name:pam_x_preferred":[
        "Cestas"
    ],
    "name:pms_x_preferred":[
        "Cestas"
    ],
    "name:pol_x_preferred":[
        "Cestas"
    ],
    "name:por_x_preferred":[
        "Cestas"
    ],
    "name:ron_x_preferred":[
        "Cestas"
    ],
    "name:slk_x_preferred":[
        "Cestas"
    ],
    "name:spa_x_preferred":[
        "Cestas"
    ],
    "name:srp_x_preferred":[
        "\u0421\u0435\u0441\u0442\u0430"
    ],
    "name:swe_x_preferred":[
        "Cestas"
    ],
    "name:ukr_x_preferred":[
        "\u0421\u0435\u0441\u0442\u0430\u0441"
    ],
    "name:uzb_x_preferred":[
        "Cestas"
    ],
    "name:vie_x_preferred":[
        "Cestas"
    ],
    "name:vol_x_preferred":[
        "Cestas"
    ],
    "name:war_x_preferred":[
        "Cestas"
    ],
    "name:zho_x_preferred":[
        "\u585e\u65af\u5854"
    ],
    "wof:name":"Cestas",
    "wof:placetype":"locality"
},
  "geometry": {"coordinates":[-8.40786,40.14277],"type":"Point"}
}