{
  "type": "Feature",
  "properties": {
    "gn:admin1_code":"4.0",
    "gn:admin2_code":"0311",
    "gn:admin3_code":"31110.0",
    "gn:asciiname":"Figueiro",
    "gn:country_code":"PT",
    "gn:dem":390,
    "gn:feature_class":"P",
    "gn:feature_code":"PPL",
    "gn:name":"Figueir\u00f3",
    "gn:population":0,
    "gn:timezone":"Europe/Lisbon",
    "iso:country":"PT",
    "wof:name":"Figueiro",
    "wof:placetype":"locality"
},
  "geometry": {"coordinates":[-8.126,41.60239],"type":"Point"}
}