{
  "type": "Feature",
  "properties": {
    "gn:admin1_code":"04",
    "gn:admin2_code":"0313",
    "gn:admin3_code":"31345.0",
    "gn:asciiname":"Vales",
    "gn:country_code":"PT",
    "gn:dem":105,
    "gn:feature_class":"P",
    "gn:feature_code":"PPL",
    "gn:name":"Vales",
    "gn:population":0,
    "gn:timezone":"Europe/Lisbon",
    "iso:country":"PT",
    "wof:name":"Vales",
    "wof:placetype":"locality"
},
  "geometry": {"coordinates":[-8.52816,41.63723],"type":"Point"}
}