{
  "type": "Feature",
  "properties": {
    "gn:admin1_code":"11",
    "gn:admin2_code":"0913",
    "gn:admin3_code":"91315.0",
    "gn:asciiname":"Reboleiro",
    "gn:country_code":"PT",
    "gn:dem":666,
    "gn:feature_class":"P",
    "gn:feature_code":"PPL",
    "gn:name":"Reboleiro",
    "gn:population":0,
    "gn:timezone":"Europe/Lisbon",
    "iso:country":"PT",
    "wof:name":"Reboleiro",
    "wof:placetype":"locality"
},
  "geometry": {"coordinates":[-7.41992,40.83469],"type":"Point"}
}