{
  "type": "Feature",
  "properties": {
    "gn:admin1_code":"05",
    "gn:admin2_code":"0405",
    "gn:admin3_code":"40535.0",
    "gn:asciiname":"Vilar do Monte",
    "gn:country_code":"PT",
    "gn:dem":600,
    "gn:feature_class":"P",
    "gn:feature_code":"PPL",
    "gn:name":"Vilar do Monte",
    "gn:population":0,
    "gn:timezone":"Europe/Lisbon",
    "iso:country":"PT",
    "wof:name":"Vilar do Monte",
    "wof:placetype":"locality"
},
  "geometry": {"coordinates":[-6.94889,41.50441],"type":"Point"}
}