{
  "type": "Feature",
  "properties": {
    "gn:admin1_code":"05",
    "gn:admin2_code":"0405",
    "gn:admin3_code":"40535.0",
    "gn:asciiname":"Vilar do Monte",
    "gn:country_code":"PT",
    "gn:dem":600,
    "gn:feature_class":"P",
    "gn:feature_code":"PPL",
    "gn:name":"Vilar do Monte",
    "gn:population":0,
    "gn:timezone":"Europe/Lisbon",
    "iso:country":"PT",
    "name:rus_x_preferred":[
        "\u0412\u0438\u043b\u0430\u0440-\u0434\u0443-\u041c\u043e\u043d\u0442\u0438"
    ],
    "name:ukr_x_preferred":[
        "\u0412\u0456\u043b\u0430\u0440-\u0434\u0443-\u041c\u043e\u043d\u0442\u0435"
    ],
    "wof:name":"Vilar do Monte",
    "wof:placetype":"locality"
},
  "geometry": {"coordinates":[-6.94889,41.50441],"type":"Point"}
}