{
  "type": "Feature",
  "properties": {
    "gn:admin1_code":"21.0",
    "gn:admin2_code":"1708",
    "gn:admin3_code":"170811.0",
    "gn:asciiname":"Ferraria",
    "gn:country_code":"PT",
    "gn:dem":585,
    "gn:feature_class":"P",
    "gn:feature_code":"PPL",
    "gn:name":"Ferraria",
    "gn:population":0,
    "gn:timezone":"Europe/Lisbon",
    "iso:country":"PT",
    "name:ceb_x_preferred":[
        "Ferraria"
    ],
    "name:pol_x_preferred":[
        "Ferraria"
    ],
    "name:por_x_preferred":[
        "Ferraria"
    ],
    "name:rus_x_preferred":[
        "\u0424\u0435\u0440\u0440\u0430\u0440\u0438\u044f"
    ],
    "name:spa_x_preferred":[
        "Ferraria"
    ],
    "name:swe_x_preferred":[
        "Ferraria"
    ],
    "name:war_x_preferred":[
        "Ferraria"
    ],
    "wof:name":"Ferraria",
    "wof:placetype":"locality"
},
  "geometry": {"coordinates":[-7.85366,41.22203],"type":"Point"}
}