{
  "type": "Feature",
  "properties": {
    "gn:gn_country":"PT",
    "gn:gn_fcode":"PPL",
    "gn:gn_pop":3768,
    "gn:population":3768,
    "iso:country":"PT",
    "name:ast_x_preferred":[
        "Alhadas"
    ],
    "name:ceb_x_preferred":[
        "Alhadas"
    ],
    "name:deu_x_preferred":[
        "Alhadas"
    ],
    "name:eng_x_preferred":[
        "Alhadas"
    ],
    "name:fra_x_preferred":[
        "Alhadas"
    ],
    "name:kaz_x_preferred":[
        "\u0410\u043b\u044c\u044f\u0434\u0430\u0448"
    ],
    "name:msa_x_preferred":[
        "Alhadas"
    ],
    "name:nan_x_preferred":[
        "Alhadas"
    ],
    "name:nld_x_preferred":[
        "Alhadas"
    ],
    "name:por_x_preferred":[
        "Alhadas"
    ],
    "name:rus_x_preferred":[
        "\u0410\u043b\u044c\u044f\u0434\u0430\u0448"
    ],
    "name:spa_x_preferred":[
        "Alhadas"
    ],
    "qs_pg:aaroncc":"PT",
    "qs_pg:gn_country":"PT",
    "qs_pg:gn_fcode":"PPL",
    "qs_pg:gn_pop":3768,
    "qs_pg:name":"Alhadas",
    "qs_pg:name_adm0":"Portugal",
    "qs_pg:name_adm1":"Coimbra",
    "qs_pg:photos_9k":1,
    "qs_pg:photos_9r":1,
    "qs_pg:photos_all":1,
    "qs_pg:photos_sr":0,
    "qs_pg:pop_sr":4,
    "qs_pg:qs_pg_placetype":"locality",
    "qs_pg:qs_pg_placetype_gp":"Town",
    "qs_pg:woe_adm0":23424925,
    "woe:adm0_id":23424925,
    "woe:name_adm0":"Portugal",
    "woe:name_adm1":"Coimbra",
    "woe:placetype":"Town",
    "wof:name":"Alhadas",
    "wof:placetype":"locality",
    "wof:population":3768
},
  "geometry": {"coordinates":[-8.79057,40.18607],"type":"Point"}
}