{
  "type": "Feature",
  "properties": {
    "gn:admin1_code":"11.0",
    "gn:admin2_code":"0911",
    "gn:admin3_code":"91122.0",
    "gn:asciiname":"Lameiras de Cima",
    "gn:country_code":"PT",
    "gn:dem":854,
    "gn:feature_class":"P",
    "gn:feature_code":"PPL",
    "gn:name":"Lameiras de Cima",
    "gn:population":0,
    "gn:timezone":"Europe/Lisbon",
    "iso:country":"PT",
    "wof:name":"Lameiras de Cima",
    "wof:placetype":"locality"
},
  "geometry": {"coordinates":[-7.1972,40.42657],"type":"Point"}
}