{
  "type": "Feature",
  "properties": {
    "gn:admin1_code":"7.0",
    "gn:admin2_code":"0613",
    "gn:admin3_code":"61303.0",
    "gn:asciiname":"Miro",
    "gn:country_code":"PT",
    "gn:dem":142,
    "gn:feature_class":"P",
    "gn:feature_code":"PPL",
    "gn:name":"Miro",
    "gn:population":0,
    "gn:timezone":"Europe/Lisbon",
    "iso:country":"PT",
    "wof:name":"Miro",
    "wof:placetype":"locality"
},
  "geometry": {"coordinates":[-8.24363,40.28483],"type":"Point"}
}