{
  "type": "Feature",
  "properties": {
    "gn:admin1_code":"17",
    "gn:admin2_code":"1317",
    "gn:admin3_code":"131711.0",
    "gn:asciiname":"Sao Miguel",
    "gn:country_code":"PT",
    "gn:dem":224,
    "gn:feature_class":"P",
    "gn:feature_code":"PPL",
    "gn:name":"S\u00e3o Miguel",
    "gn:population":0,
    "gn:timezone":"Europe/Lisbon",
    "iso:country":"PT",
    "wof:name":"Sao Miguel",
    "wof:placetype":"locality"
},
  "geometry": {"coordinates":[-8.52284,41.04786],"type":"Point"}
}