{
  "type": "Feature",
  "properties": {
    "gn:admin1_code":"17.0",
    "gn:admin2_code":"1303",
    "gn:admin3_code":"130307.0",
    "gn:asciiname":"Jugueiros",
    "gn:country_code":"PT",
    "gn:dem":166,
    "gn:feature_class":"P",
    "gn:feature_code":"PPL",
    "gn:name":"Jugueiros",
    "gn:population":0,
    "gn:timezone":"Europe/Lisbon",
    "iso:country":"PT",
    "wof:name":"Jugueiros",
    "wof:placetype":"locality"
},
  "geometry": {"coordinates":[-8.21969,41.40127],"type":"Point"}
}