{
  "type": "Feature",
  "properties": {
    "gn:admin1_code":"4.0",
    "gn:admin2_code":"0304",
    "gn:admin3_code":"30407.0",
    "gn:asciiname":"Moimenta",
    "gn:country_code":"PT",
    "gn:dem":300,
    "gn:feature_class":"P",
    "gn:feature_code":"PPL",
    "gn:name":"Moimenta",
    "gn:population":0,
    "gn:timezone":"Europe/Lisbon",
    "iso:country":"PT",
    "wof:name":"Moimenta",
    "wof:placetype":"locality"
},
  "geometry": {"coordinates":[-7.88883,41.52391],"type":"Point"}
}