{
  "type": "Feature",
  "properties": {
    "gn:admin1_code":"4.0",
    "gn:admin2_code":"0304",
    "gn:admin3_code":"30407.0",
    "gn:asciiname":"Moimenta",
    "gn:country_code":"PT",
    "gn:dem":300,
    "gn:feature_class":"P",
    "gn:feature_code":"PPL",
    "gn:name":"Moimenta",
    "gn:population":0,
    "gn:timezone":"Europe/Lisbon",
    "iso:country":"PT",
    "name:ceb_x_preferred":[
        "Moimenta"
    ],
    "name:deu_x_preferred":[
        "Moimenta"
    ],
    "name:fra_x_preferred":[
        "Moimenta"
    ],
    "name:glg_x_preferred":[
        "Moimenta"
    ],
    "name:nld_x_preferred":[
        "Moimenta"
    ],
    "name:por_x_preferred":[
        "Moimenta"
    ],
    "name:rus_x_preferred":[
        "\u041c\u043e\u0439\u043c\u0435\u043d\u0442\u0430"
    ],
    "name:tur_x_preferred":[
        "Moimenta"
    ],
    "name:ukr_x_preferred":[
        "\u041c\u043e\u0439\u043c\u0435\u043d\u0442\u0430"
    ],
    "wof:name":"Moimenta",
    "wof:placetype":"locality"
},
  "geometry": {"coordinates":[-7.88883,41.52391],"type":"Point"}
}