{
  "type": "Feature",
  "properties": {
    "gn:admin1_code":"07",
    "gn:admin2_code":"0614",
    "gn:admin3_code":"61405.0",
    "gn:asciiname":"Ferrarias",
    "gn:country_code":"PT",
    "gn:dem":225,
    "gn:feature_class":"P",
    "gn:feature_code":"PPL",
    "gn:name":"Ferrarias",
    "gn:population":0,
    "gn:timezone":"Europe/Lisbon",
    "iso:country":"PT",
    "wof:name":"Ferrarias",
    "wof:placetype":"locality"
},
  "geometry": {"coordinates":[-8.38426,39.98714],"type":"Point"}
}