{
  "type": "Feature",
  "properties": {
    "gn:country":"PT",
    "gn:fcode":"ADM3",
    "gn:population":0,
    "iso:country":"PT",
    "name:bpy_x_preferred":[
        "\u09ac\u09cb\u09a8\u09ab\u09bf\u09ae"
    ],
    "name:bre_x_preferred":[
        "Bonfim"
    ],
    "name:ceb_x_preferred":[
        "Bonfim"
    ],
    "name:deu_x_preferred":[
        "Bonfim"
    ],
    "name:fra_x_preferred":[
        "Bonfim"
    ],
    "name:ita_x_preferred":[
        "Bonfim"
    ],
    "name:nld_x_preferred":[
        "Bonfim"
    ],
    "name:nor_x_preferred":[
        "Bonfim"
    ],
    "name:pol_x_preferred":[
        "Bonfim"
    ],
    "name:por_x_preferred":[
        "Bonfim"
    ],
    "name:sco_x_preferred":[
        "Bonfim"
    ],
    "name:spa_x_preferred":[
        "Bonfim"
    ],
    "name:swe_x_preferred":[
        "Bonfim"
    ],
    "name:vol_x_preferred":[
        "Bonfim"
    ],
    "name:war_x_preferred":[
        "Bonfim"
    ],
    "qs_pg:aaroncc":"PT",
    "qs_pg:gn_country":"PT",
    "qs_pg:gn_fcode":"ADM3",
    "qs_pg:gn_pop":0,
    "qs_pg:name":"Bonfim",
    "qs_pg:photos_9r":0,
    "qs_pg:photos_sr":0,
    "qs_pg:pop_sr":0,
    "qs_pg:qs_pg_placetype":"localadmin",
    "wof:name":"Bonfim",
    "wof:placetype":"localadmin"
},
  "geometry": {"coordinates":[-8.59555,41.15277],"type":"Point"}
}