{
  "type": "Feature",
  "properties": {
    "gn:admin1_code":"17.0",
    "gn:admin2_code":"1311",
    "gn:admin3_code":"131102.0",
    "gn:asciiname":"Boelhe",
    "gn:country_code":"PT",
    "gn:dem":296,
    "gn:feature_class":"P",
    "gn:feature_code":"PPL",
    "gn:name":"Boelhe",
    "gn:population":0,
    "gn:timezone":"Europe/Lisbon",
    "iso:country":"PT",
    "wof:name":"Boelhe",
    "wof:placetype":"locality"
},
  "geometry": {"coordinates":[-8.24475,41.13647],"type":"Point"}
}