{
  "type": "Feature",
  "properties": {
    "gn:admin1_code":"13",
    "gn:admin2_code":"1006",
    "gn:admin3_code":"100609.0",
    "gn:asciiname":"Trabalhia",
    "gn:country_code":"PT",
    "gn:dem":39,
    "gn:feature_class":"P",
    "gn:feature_code":"PPL",
    "gn:name":"Trabalhia",
    "gn:population":0,
    "gn:timezone":"Europe/Lisbon",
    "iso:country":"PT",
    "wof:name":"Trabalhia",
    "wof:placetype":"locality"
},
  "geometry": {"coordinates":[-9.07754,39.43038],"type":"Point"}
}