{
  "type": "Feature",
  "properties": {
    "gn:admin1_code":"23.0",
    "gn:admin2_code":"4603",
    "gn:admin3_code":"460303.0",
    "gn:asciiname":"Canto da Areia",
    "gn:country_code":"PT",
    "gn:dem":20,
    "gn:feature_class":"P",
    "gn:feature_code":"PPL",
    "gn:name":"Canto da Areia",
    "gn:population":0,
    "gn:timezone":"Atlantic/Azores",
    "iso:country":"PT",
    "wof:name":"Canto da Areia",
    "wof:placetype":"locality"
},
  "geometry": {"coordinates":[-28.19182,38.46075],"type":"Point"}
}