{
  "type": "Feature",
  "properties": {
    "gn:admin1_code":"13",
    "gn:admin2_code":"1009",
    "gn:admin3_code":"100905.0",
    "gn:asciiname":"Moura",
    "gn:country_code":"PT",
    "gn:dem":81,
    "gn:feature_class":"P",
    "gn:feature_code":"PPL",
    "gn:name":"Moura",
    "gn:population":0,
    "gn:timezone":"Europe/Lisbon",
    "iso:country":"PT",
    "name:ceb_x_preferred":[
        "Moura"
    ],
    "name:deu_x_preferred":[
        "Moura"
    ],
    "name:fra_x_preferred":[
        "Moura"
    ],
    "name:glg_x_preferred":[
        "Moura"
    ],
    "name:jpn_x_preferred":[
        "\u30e2\u30a6\u30e9"
    ],
    "name:por_x_preferred":[
        "Moura"
    ],
    "name:rus_x_preferred":[
        "\u041c\u043e\u0443\u0440\u0430"
    ],
    "wof:name":"Moura",
    "wof:placetype":"locality"
},
  "geometry": {"coordinates":[-8.8155,39.71957],"type":"Point"}
}