{
  "type": "Feature",
  "properties": {
    "gn:admin1_code":"5.0",
    "gn:admin2_code":"0401",
    "gn:admin3_code":"40120.0",
    "gn:asciiname":"Colmeais",
    "gn:country_code":"PT",
    "gn:dem":734,
    "gn:feature_class":"P",
    "gn:feature_code":"PPL",
    "gn:name":"Colmeais",
    "gn:population":0,
    "gn:timezone":"Europe/Lisbon",
    "iso:country":"PT",
    "wof:name":"Colmeais",
    "wof:placetype":"locality"
},
  "geometry": {"coordinates":[-7.02773,41.40901],"type":"Point"}
}