{
  "type": "Feature",
  "properties": {
    "gn:admin1_code":"4.0",
    "gn:admin2_code":"0311",
    "gn:admin3_code":"31101.0",
    "gn:asciiname":"Anisso",
    "gn:country_code":"PT",
    "gn:dem":505,
    "gn:feature_class":"P",
    "gn:feature_code":"PPL",
    "gn:name":"Aniss\u00f3",
    "gn:population":0,
    "gn:timezone":"Europe/Lisbon",
    "iso:country":"PT",
    "wof:name":"Anisso",
    "wof:placetype":"locality"
},
  "geometry": {"coordinates":[-8.17177,41.60358],"type":"Point"}
}