{
  "type": "Feature",
  "properties": {
    "gn:admin1_code":"17.0",
    "gn:admin2_code":"1310",
    "gn:admin3_code":"131006.0",
    "gn:asciiname":"Bitaraes",
    "gn:country_code":"PT",
    "gn:dem":208,
    "gn:feature_class":"P",
    "gn:feature_code":"PPL",
    "gn:name":"Bitar\u00e3es",
    "gn:population":0,
    "gn:timezone":"Europe/Lisbon",
    "iso:country":"PT",
    "wof:name":"Bitaraes",
    "wof:placetype":"locality"
},
  "geometry": {"coordinates":[-8.32344,41.22645],"type":"Point"}
}