{
  "type": "Feature",
  "properties": {
    "gn:admin1_code":"14",
    "gn:admin2_code":"1113",
    "gn:admin3_code":"111318.0",
    "gn:asciiname":"Macafaneira",
    "gn:country_code":"PT",
    "gn:dem":65,
    "gn:feature_class":"P",
    "gn:feature_code":"PPL",
    "gn:name":"Ma\u00e7afaneira",
    "gn:population":0,
    "gn:timezone":"Europe/Lisbon",
    "iso:country":"PT",
    "wof:name":"Macafaneira",
    "wof:placetype":"locality"
},
  "geometry": {"coordinates":[-9.31213,39.06701],"type":"Point"}
}