{
  "type": "Feature",
  "properties": {
    "gn:admin1_code":"06",
    "gn:admin2_code":"0509",
    "gn:admin3_code":"50914.0",
    "gn:asciiname":"Povoa",
    "gn:country_code":"PT",
    "gn:dem":413,
    "gn:feature_class":"P",
    "gn:feature_code":"PPL",
    "gn:name":"P\u00f3voa",
    "gn:population":0,
    "gn:timezone":"Europe/Lisbon",
    "iso:country":"PT",
    "wof:name":"Povoa",
    "wof:placetype":"locality"
},
  "geometry": {"coordinates":[-8.03445,39.79083],"type":"Point"}
}