{
  "type": "Feature",
  "properties": {
    "gn:admin1_code":"20.0",
    "gn:admin2_code":"1603",
    "gn:admin3_code":"160310.0",
    "gn:asciiname":"Pacos",
    "gn:country_code":"PT",
    "gn:dem":201,
    "gn:feature_class":"P",
    "gn:feature_code":"PPL",
    "gn:name":"Pa\u00e7os",
    "gn:population":0,
    "gn:timezone":"Europe/Lisbon",
    "iso:country":"PT",
    "name:cat_x_preferred":[
        "Pa\u00e7os"
    ],
    "name:deu_x_preferred":[
        "Pa\u00e7os"
    ],
    "name:kaz_x_preferred":[
        "\u041f\u0430\u0441\u0443\u0448"
    ],
    "name:nld_x_preferred":[
        "Pa\u00e7os"
    ],
    "name:por_x_preferred":[
        "Pa\u00e7os"
    ],
    "name:rus_x_preferred":[
        "\u041f\u0430\u0441\u0443\u0448"
    ],
    "name:spa_x_preferred":[
        "Pa\u00e7os"
    ],
    "name:und_x_variant":[
        "Pa\u00e7os"
    ],
    "wof:name":"Pacos",
    "wof:placetype":"locality"
},
  "geometry": {"coordinates":[-8.20675,42.13504],"type":"Point"}
}