{
  "type": "Feature",
  "properties": {
    "gn:admin1_code":"07",
    "gn:admin2_code":"0604",
    "gn:admin3_code":"60401.0",
    "gn:asciiname":"Rodao",
    "gn:country_code":"PT",
    "gn:dem":31,
    "gn:feature_class":"P",
    "gn:feature_code":"PPL",
    "gn:name":"Rod\u00e3o",
    "gn:population":0,
    "gn:timezone":"Europe/Lisbon",
    "iso:country":"PT",
    "wof:name":"Rodao",
    "wof:placetype":"locality"
},
  "geometry": {"coordinates":[-8.51541,40.14303],"type":"Point"}
}