{
  "type": "Feature",
  "properties": {
    "gn:admin1_code":"21",
    "gn:admin2_code":"1712",
    "gn:admin3_code":"171217.0",
    "gn:asciiname":"Rio Torto",
    "gn:country_code":"PT",
    "gn:dem":274,
    "gn:feature_class":"P",
    "gn:feature_code":"PPL",
    "gn:name":"Rio Torto",
    "gn:population":0,
    "gn:timezone":"Europe/Lisbon",
    "iso:country":"PT",
    "wof:name":"Rio Torto",
    "wof:placetype":"locality"
},
  "geometry": {"coordinates":[-7.28698,41.55909000000001],"type":"Point"}
}