{
  "type": "Feature",
  "properties": {
    "gn:admin1_code":"07",
    "gn:admin2_code":"0613",
    "gn:admin3_code":"61308.0",
    "gn:asciiname":"Sao Paio",
    "gn:country_code":"PT",
    "gn:dem":218,
    "gn:feature_class":"P",
    "gn:feature_code":"PPL",
    "gn:name":"S\u00e3o Paio",
    "gn:population":0,
    "gn:timezone":"Europe/Lisbon",
    "iso:country":"PT",
    "wof:name":"Sao Paio",
    "wof:placetype":"locality"
},
  "geometry": {"coordinates":[-8.12829,40.31263],"type":"Point"}
}