{
  "type": "Feature",
  "properties": {
    "gn:admin1_code":"14",
    "gn:admin2_code":"1109",
    "gn:admin3_code":"110911.0",
    "gn:asciiname":"Castelo Picao",
    "gn:country_code":"PT",
    "gn:dem":221,
    "gn:feature_class":"P",
    "gn:feature_code":"PPL",
    "gn:name":"Castelo Pic\u00e3o",
    "gn:population":0,
    "gn:timezone":"Europe/Lisbon",
    "iso:country":"PT",
    "wof:name":"Castelo Picao",
    "wof:placetype":"locality"
},
  "geometry": {"coordinates":[-9.1983,38.93909],"type":"Point"}
}