{
  "type": "Feature",
  "properties": {
    "gn:admin1_code":"20.0",
    "gn:admin2_code":"1609",
    "gn:admin3_code":"160921.0",
    "gn:asciiname":"Moreira de Geraz do Lima",
    "gn:country_code":"PT",
    "gn:dem":14,
    "gn:feature_class":"P",
    "gn:feature_code":"PPL",
    "gn:name":"Moreira de Geraz do Lima",
    "gn:population":0,
    "gn:timezone":"Europe/Lisbon",
    "iso:country":"PT",
    "wof:name":"Moreira de Geraz do Lima",
    "wof:placetype":"locality"
},
  "geometry": {"coordinates":[-8.68667,41.71313],"type":"Point"}
}