{
  "type": "Feature",
  "properties": {
    "gn:admin1_code":"09",
    "gn:admin2_code":"0807",
    "gn:admin3_code":"80704.0",
    "gn:asciiname":"Monte Ruivo",
    "gn:country_code":"PT",
    "gn:dem":70,
    "gn:feature_class":"P",
    "gn:feature_code":"PPL",
    "gn:name":"Monte Ruivo",
    "gn:population":0,
    "gn:timezone":"Europe/Lisbon",
    "iso:country":"PT",
    "wof:name":"Monte Ruivo",
    "wof:placetype":"locality"
},
  "geometry": {"coordinates":[-8.67827,37.17517],"type":"Point"}
}