{
  "type": "Feature",
  "properties": {
    "gn:admin1_code":"5.0",
    "gn:admin2_code":"0405",
    "gn:admin3_code":"40522.0",
    "gn:asciiname":"Murcos",
    "gn:country_code":"PT",
    "gn:dem":707,
    "gn:feature_class":"P",
    "gn:feature_code":"PPL",
    "gn:name":"Mur\u00e7\u00f3s",
    "gn:population":0,
    "gn:timezone":"Europe/Lisbon",
    "iso:country":"PT",
    "wof:name":"Murcos",
    "wof:placetype":"locality"
},
  "geometry": {"coordinates":[-6.98122,41.68047],"type":"Point"}
}