{
  "type": "Feature",
  "properties": {
    "gn:admin1_code":"09",
    "gn:admin2_code":"0805",
    "gn:admin3_code":"80501.0",
    "gn:asciiname":"Ferradeira",
    "gn:country_code":"PT",
    "gn:dem":50,
    "gn:feature_class":"P",
    "gn:feature_code":"PPL",
    "gn:name":"Ferradeira",
    "gn:population":0,
    "gn:timezone":"Europe/Lisbon",
    "iso:country":"PT",
    "wof:name":"Ferradeira",
    "wof:placetype":"locality"
},
  "geometry": {"coordinates":[-7.88943,37.0501],"type":"Point"}
}