{
  "type": "Feature",
  "properties": {
    "gn:admin1_code":"5.0",
    "gn:admin2_code":"0407",
    "gn:admin3_code":"40704.0",
    "gn:asciiname":"Lamas de Cavalo",
    "gn:country_code":"PT",
    "gn:dem":545,
    "gn:feature_class":"P",
    "gn:feature_code":"PPL",
    "gn:name":"Lamas de Cavalo",
    "gn:population":0,
    "gn:timezone":"Europe/Lisbon",
    "iso:country":"PT",
    "wof:name":"Lamas de Cavalo",
    "wof:placetype":"locality"
},
  "geometry": {"coordinates":[-7.10522,41.5719],"type":"Point"}
}