{
  "type": "Feature",
  "properties": {
    "gn:admin1_code":"2.0",
    "gn:admin2_code":"0103",
    "gn:admin3_code":"10311.0",
    "gn:asciiname":"Horta",
    "gn:country_code":"PT",
    "gn:dem":93,
    "gn:feature_class":"P",
    "gn:feature_code":"PPL",
    "gn:name":"Horta",
    "gn:population":0,
    "gn:timezone":"Europe/Lisbon",
    "iso:country":"PT",
    "wof:name":"Horta",
    "wof:placetype":"locality"
},
  "geometry": {"coordinates":[-8.48967,40.42062],"type":"Point"}
}