{
  "type": "Feature",
  "properties": {
    "gn:admin1_code":"2.0",
    "gn:admin2_code":"0103",
    "gn:admin3_code":"10311.0",
    "gn:asciiname":"Horta",
    "gn:country_code":"PT",
    "gn:dem":93,
    "gn:feature_class":"P",
    "gn:feature_code":"PPL",
    "gn:name":"Horta",
    "gn:population":0,
    "gn:timezone":"Europe/Lisbon",
    "iso:country":"PT",
    "name:cat_x_preferred":[
        "Horta"
    ],
    "name:ceb_x_preferred":[
        "Horta"
    ],
    "name:deu_x_preferred":[
        "Horta"
    ],
    "name:epo_x_preferred":[
        "Horta"
    ],
    "name:fin_x_preferred":[
        "Horta"
    ],
    "name:fra_x_preferred":[
        "Horta"
    ],
    "name:glg_x_preferred":[
        "Horta"
    ],
    "name:ita_x_preferred":[
        "Horta"
    ],
    "name:lat_x_preferred":[
        "Horta"
    ],
    "name:nld_x_preferred":[
        "Horta"
    ],
    "name:pol_x_preferred":[
        "Horta"
    ],
    "name:por_x_preferred":[
        "Horta"
    ],
    "name:spa_x_preferred":[
        "Horta"
    ],
    "name:swe_x_preferred":[
        "Horta"
    ],
    "name:tur_x_preferred":[
        "Horta"
    ],
    "wof:name":"Horta",
    "wof:placetype":"locality"
},
  "geometry": {"coordinates":[-8.48967,40.42062],"type":"Point"}
}