{
  "type": "Feature",
  "properties": {
    "gn:admin1_code":"09",
    "gn:admin2_code":"0808",
    "gn:admin3_code":"80803.0",
    "gn:asciiname":"Cerro dos Vermelhos",
    "gn:country_code":"PT",
    "gn:dem":401,
    "gn:feature_class":"P",
    "gn:feature_code":"PPL",
    "gn:name":"Cerro dos Vermelhos",
    "gn:population":0,
    "gn:timezone":"Europe/Lisbon",
    "iso:country":"PT",
    "wof:name":"Cerro dos Vermelhos",
    "wof:placetype":"locality"
},
  "geometry": {"coordinates":[-8.02473,37.34624],"type":"Point"}
}