{
  "type": "Feature",
  "properties": {
    "gn:gn_country":"PT",
    "gn:gn_fcode":"PPL",
    "gn:gn_pop":0,
    "iso:country":"PT",
    "name:deu_x_preferred":[
        "Marialva"
    ],
    "name:eng_x_preferred":[
        "Marialva"
    ],
    "name:fra_x_preferred":[
        "Marialva"
    ],
    "name:nan_x_preferred":[
        "Marialva"
    ],
    "name:por_x_preferred":[
        "Marialva"
    ],
    "name:rus_x_preferred":[
        "\u041c\u0430\u0440\u044c\u044f\u043b\u0432\u0430"
    ],
    "name:spa_x_preferred":[
        "Marialva"
    ],
    "name:unk_x_variant":[
        "Aravi"
    ],
    "qs_pg:aaroncc":"PT",
    "qs_pg:gn_country":"PT",
    "qs_pg:gn_fcode":"PPL",
    "qs_pg:gn_pop":0,
    "qs_pg:name":"Marialva",
    "qs_pg:name_adm0":"Portugal",
    "qs_pg:name_adm1":"Guarda",
    "qs_pg:photos":78,
    "qs_pg:photos_1k":16,
    "qs_pg:photos_9k":1,
    "qs_pg:photos_9r":3,
    "qs_pg:photos_all":78,
    "qs_pg:photos_sr":3,
    "qs_pg:pop_sr":0,
    "qs_pg:qs_pg_placetype":"locality",
    "qs_pg:qs_pg_placetype_gp":"Town",
    "qs_pg:woe_adm0":23424925,
    "woe:adm0_id":23424925,
    "woe:name_adm0":"Portugal",
    "woe:name_adm1":"Guarda",
    "woe:placetype":"Town",
    "wof:name":"Marialva",
    "wof:placetype":"locality"
},
  "geometry": {"coordinates":[-7.23246,40.91501],"type":"Point"}
}