{
  "type": "Feature",
  "properties": {
    "gn:admin1_code":"11.0",
    "gn:admin2_code":"0910",
    "gn:admin3_code":"91003.0",
    "gn:asciiname":"Azevo",
    "gn:country_code":"PT",
    "gn:dem":541,
    "gn:feature_class":"P",
    "gn:feature_code":"PPL",
    "gn:name":"Azevo",
    "gn:population":0,
    "gn:timezone":"Europe/Lisbon",
    "iso:country":"PT",
    "wof:name":"Azevo",
    "wof:placetype":"locality"
},
  "geometry": {"coordinates":[-7.13149,40.85415],"type":"Point"}
}