{
  "type": "Feature",
  "properties": {
    "gn:admin1_code":"03",
    "gn:admin2_code":"0211",
    "gn:admin3_code":"21106.0",
    "gn:asciiname":"Atabueira",
    "gn:country_code":"PT",
    "gn:dem":126,
    "gn:feature_class":"P",
    "gn:feature_code":"PPL",
    "gn:name":"Atabueira",
    "gn:population":0,
    "gn:timezone":"Europe/Lisbon",
    "iso:country":"PT",
    "wof:name":"Atabueira",
    "wof:placetype":"locality"
},
  "geometry": {"coordinates":[-8.6462,37.68531],"type":"Point"}
}