{
  "type": "Feature",
  "properties": {
    "gn:admin1_code":"20.0",
    "gn:admin2_code":"1603",
    "gn:admin3_code":"160302.0",
    "gn:asciiname":"Teso",
    "gn:country_code":"PT",
    "gn:dem":1090,
    "gn:feature_class":"P",
    "gn:feature_code":"PPL",
    "gn:name":"Teso",
    "gn:population":0,
    "gn:timezone":"Europe/Lisbon",
    "iso:country":"PT",
    "name:ceb_x_preferred":[
        "Teso"
    ],
    "name:fra_x_preferred":[
        "Teso"
    ],
    "name:ita_x_preferred":[
        "Teso"
    ],
    "name:nld_x_preferred":[
        "Teso"
    ],
    "name:por_x_preferred":[
        "Teso"
    ],
    "name:swe_x_preferred":[
        "Teso"
    ],
    "wof:name":"Teso",
    "wof:placetype":"locality"
},
  "geometry": {"coordinates":[-8.13932,42.03651],"type":"Point"}
}