{
  "type": "Feature",
  "properties": {
    "gn:gn_country":"PT",
    "gn:gn_fcode":"ADM3",
    "gn:gn_pop":0,
    "iso:country":"PT",
    "name:ceb_x_preferred":[
        "S\u00e3o Br\u00e1s"
    ],
    "name:deu_x_preferred":[
        "S\u00e3o Br\u00e1s"
    ],
    "name:fra_x_preferred":[
        "S\u00e3o Br\u00e1s"
    ],
    "name:nld_x_preferred":[
        "S\u00e3o Br\u00e1s"
    ],
    "name:por_x_preferred":[
        "S\u00e3o Br\u00e1s"
    ],
    "name:rus_x_preferred":[
        "\u0421\u0430\u043d-\u0411\u0440\u0430\u0448"
    ],
    "name:sco_x_preferred":[
        "S\u00e3o Br\u00e1s"
    ],
    "name:swe_x_preferred":[
        "S\u00e3o Br\u00e1s"
    ],
    "qs_pg:aaroncc":"PT",
    "qs_pg:gn_country":"PT",
    "qs_pg:gn_fcode":"ADM3",
    "qs_pg:gn_pop":0,
    "qs_pg:name":"S\u00e3o Br\u00e1s",
    "qs_pg:photos_9r":0,
    "qs_pg:photos_sr":0,
    "qs_pg:pop_sr":0,
    "qs_pg:qs_pg_placetype":"localadmin",
    "wof:name":"S\u00e3o Br\u00e1s",
    "wof:placetype":"localadmin"
},
  "geometry": {"coordinates":[-9.23325,38.78065],"type":"Point"}
}