{
  "type": "Feature",
  "properties": {
    "gn:admin1_code":"19",
    "gn:admin2_code":"1508",
    "gn:admin3_code":"150801.0",
    "gn:asciiname":"Monte do Caria",
    "gn:country_code":"PT",
    "gn:dem":59,
    "gn:feature_class":"P",
    "gn:feature_code":"PPL",
    "gn:name":"Monte do Caria",
    "gn:population":0,
    "gn:timezone":"Europe/Lisbon",
    "iso:country":"PT",
    "wof:name":"Monte do Caria",
    "wof:placetype":"locality"
},
  "geometry": {"coordinates":[-8.68186,38.65561],"type":"Point"}
}