{
  "type": "Feature",
  "properties": {
    "gn:admin1_code":"09",
    "gn:admin2_code":"0813",
    "gn:admin3_code":"81305.0",
    "gn:asciiname":"Gaviao de Cima",
    "gn:country_code":"PT",
    "gn:dem":146,
    "gn:feature_class":"P",
    "gn:feature_code":"PPL",
    "gn:name":"Gavi\u00e3o de Cima",
    "gn:population":0,
    "gn:timezone":"Europe/Lisbon",
    "iso:country":"PT",
    "wof:name":"Gaviao de Cima",
    "wof:placetype":"locality"
},
  "geometry": {"coordinates":[-8.25307,37.29141],"type":"Point"}
}