{
  "type": "Feature",
  "properties": {
    "gn:admin1_code":"21",
    "gn:admin2_code":"1712",
    "gn:admin3_code":"171222.0",
    "gn:asciiname":"Sobrado",
    "gn:country_code":"PT",
    "gn:dem":822,
    "gn:feature_class":"P",
    "gn:feature_code":"PPL",
    "gn:name":"Sobrado",
    "gn:population":0,
    "gn:timezone":"Europe/Lisbon",
    "iso:country":"PT",
    "name:arg_x_preferred":[
        "Sobrado"
    ],
    "name:bre_x_preferred":[
        "Sobrado"
    ],
    "name:cat_x_preferred":[
        "Sobrado"
    ],
    "name:ceb_x_preferred":[
        "Sobrado"
    ],
    "name:deu_x_preferred":[
        "Sobrado"
    ],
    "name:eus_x_preferred":[
        "Sobrado"
    ],
    "name:fra_x_preferred":[
        "Sobrado"
    ],
    "name:glg_x_preferred":[
        "Sobrado"
    ],
    "name:hun_x_preferred":[
        "Sobrado"
    ],
    "name:ita_x_preferred":[
        "Sobrado"
    ],
    "name:jpn_x_preferred":[
        "\u30bd\u30d6\u30e9\u30fc\u30c9"
    ],
    "name:msa_x_preferred":[
        "Sobrado"
    ],
    "name:nld_x_preferred":[
        "Sobrado"
    ],
    "name:oci_x_preferred":[
        "Sobrado"
    ],
    "name:pol_x_preferred":[
        "Sobrado"
    ],
    "name:por_x_preferred":[
        "Sobrado"
    ],
    "name:rus_x_preferred":[
        "\u0421\u043e\u0431\u0440\u0430\u0434\u0443"
    ],
    "name:spa_x_preferred":[
        "Sobrado"
    ],
    "name:swe_x_preferred":[
        "Sobrado"
    ],
    "name:ukr_x_preferred":[
        "\u0421\u043e\u0431\u0440\u0430\u0434\u0443"
    ],
    "name:vie_x_preferred":[
        "Sobrado"
    ],
    "name:war_x_preferred":[
        "Sobrado"
    ],
    "wof:name":"Sobrado",
    "wof:placetype":"locality"
},
  "geometry": {"coordinates":[-7.46982,41.57361],"type":"Point"}
}