{
  "type": "Feature",
  "properties": {
    "gn:admin1_code":"20.0",
    "gn:admin2_code":"1608",
    "gn:admin3_code":"160803.0",
    "gn:asciiname":"Bade",
    "gn:country_code":"PT",
    "gn:dem":110,
    "gn:feature_class":"P",
    "gn:feature_code":"PPL",
    "gn:name":"Bade",
    "gn:population":0,
    "gn:timezone":"Europe/Lisbon",
    "iso:country":"PT",
    "wof:name":"Bade",
    "wof:placetype":"locality"
},
  "geometry": {"coordinates":[-8.60404,41.97781],"type":"Point"}
}