{
  "type": "Feature",
  "properties": {
    "gn:admin1_code":"20.0",
    "gn:admin2_code":"1608",
    "gn:admin3_code":"160803.0",
    "gn:asciiname":"Bade",
    "gn:country_code":"PT",
    "gn:dem":110,
    "gn:feature_class":"P",
    "gn:feature_code":"PPL",
    "gn:name":"Bade",
    "gn:population":0,
    "gn:timezone":"Europe/Lisbon",
    "iso:country":"PT",
    "name:ceb_x_preferred":[
        "Bade"
    ],
    "name:deu_x_preferred":[
        "Bade"
    ],
    "name:fra_x_preferred":[
        "Bade"
    ],
    "name:glg_x_preferred":[
        "Bade"
    ],
    "name:ita_x_preferred":[
        "Bade"
    ],
    "name:kat_x_preferred":[
        "\u10d1\u10d0\u10d3\u10d4"
    ],
    "name:nld_x_preferred":[
        "Bade"
    ],
    "name:rus_x_preferred":[
        "\u0411\u0430\u0434\u0435"
    ],
    "name:swe_x_preferred":[
        "Bade"
    ],
    "wof:name":"Bade",
    "wof:placetype":"locality"
},
  "geometry": {"coordinates":[-8.60404,41.97781],"type":"Point"}
}