{
  "type": "Feature",
  "properties": {
    "gn:admin1_code":"22.0",
    "gn:admin2_code":"1808",
    "gn:admin3_code":"180802.0",
    "gn:asciiname":"Galhardo",
    "gn:country_code":"PT",
    "gn:dem":157,
    "gn:feature_class":"P",
    "gn:feature_code":"PPL",
    "gn:name":"Galhardo",
    "gn:population":0,
    "gn:timezone":"Europe/Lisbon",
    "iso:country":"PT",
    "wof:name":"Galhardo",
    "wof:placetype":"locality"
},
  "geometry": {"coordinates":[-8.26987,40.3478],"type":"Point"}
}