{
  "type": "Feature",
  "properties": {
    "gn:admin1_code":"4.0",
    "gn:admin2_code":"0307",
    "gn:admin3_code":"30720.0",
    "gn:asciiname":"Pedraido",
    "gn:country_code":"PT",
    "gn:dem":633,
    "gn:feature_class":"P",
    "gn:feature_code":"PPL",
    "gn:name":"Pedra\u00eddo",
    "gn:population":0,
    "gn:timezone":"Europe/Lisbon",
    "iso:country":"PT",
    "wof:name":"Pedraido",
    "wof:placetype":"locality"
},
  "geometry": {"coordinates":[-8.12021,41.51031],"type":"Point"}
}