{
  "type": "Feature",
  "properties": {
    "gn:admin1_code":"11.0",
    "gn:admin2_code":"0911",
    "gn:admin3_code":"91132.0",
    "gn:asciiname":"Perofico",
    "gn:country_code":"PT",
    "gn:dem":744,
    "gn:feature_class":"P",
    "gn:feature_code":"PPL",
    "gn:name":"Perofico",
    "gn:population":0,
    "gn:timezone":"Europe/Lisbon",
    "iso:country":"PT",
    "wof:name":"Perofico",
    "wof:placetype":"locality"
},
  "geometry": {"coordinates":[-7.04121,40.48225],"type":"Point"}
}