{
  "type": "Feature",
  "properties": {
    "gn:admin1_code":"06",
    "gn:admin2_code":"0509",
    "gn:admin3_code":"50914.0",
    "gn:asciiname":"Beirao",
    "gn:country_code":"PT",
    "gn:dem":570,
    "gn:feature_class":"P",
    "gn:feature_code":"PPL",
    "gn:name":"Beir\u00e3o",
    "gn:population":0,
    "gn:timezone":"Europe/Lisbon",
    "iso:country":"PT",
    "wof:name":"Beirao",
    "wof:placetype":"locality"
},
  "geometry": {"coordinates":[-7.98399,39.80176],"type":"Point"}
}