{
  "type": "Feature",
  "properties": {
    "gn:admin1_code":"03",
    "gn:admin2_code":"0208",
    "gn:admin3_code":"20802.0",
    "gn:asciiname":"Quinta da Amia",
    "gn:country_code":"PT",
    "gn:dem":104,
    "gn:feature_class":"P",
    "gn:feature_code":"PPL",
    "gn:name":"Quinta da \u00c2mia",
    "gn:population":0,
    "gn:timezone":"Europe/Lisbon",
    "iso:country":"PT",
    "wof:name":"Quinta da Amia",
    "wof:placetype":"locality"
},
  "geometry": {"coordinates":[-8.14275,38.04992],"type":"Point"}
}