{
  "type": "Feature",
  "properties": {
    "gn:admin1_code":"18",
    "gn:admin2_code":"1418",
    "gn:admin3_code":"141806.0",
    "gn:asciiname":"Fonte de Dom Joao",
    "gn:country_code":"PT",
    "gn:dem":244,
    "gn:feature_class":"P",
    "gn:feature_code":"PPL",
    "gn:name":"Fonte de Dom Jo\u00e3o",
    "gn:population":0,
    "gn:timezone":"Europe/Lisbon",
    "iso:country":"PT",
    "wof:name":"Fonte de Dom Joao",
    "wof:placetype":"locality"
},
  "geometry": {"coordinates":[-8.33368,39.62397],"type":"Point"}
}