{
  "type": "Feature",
  "properties": {
    "gn:admin1_code":"14",
    "gn:admin2_code":"1104",
    "gn:admin3_code":"110406.0",
    "gn:asciiname":"Boica",
    "gn:country_code":"PT",
    "gn:dem":99,
    "gn:feature_class":"P",
    "gn:feature_code":"PPL",
    "gn:name":"Boi\u00e7a",
    "gn:population":0,
    "gn:timezone":"Europe/Lisbon",
    "iso:country":"PT",
    "wof:name":"Boica",
    "wof:placetype":"locality"
},
  "geometry": {"coordinates":[-9.03751,39.29532],"type":"Point"}
}