{
  "type": "Feature",
  "properties": {
    "gn:admin1_code":"18",
    "gn:admin2_code":"1419",
    "gn:admin3_code":"141902.0",
    "gn:asciiname":"Outeiro Grande",
    "gn:country_code":"PT",
    "gn:dem":133,
    "gn:feature_class":"P",
    "gn:feature_code":"PPL",
    "gn:name":"Outeiro Grande",
    "gn:population":0,
    "gn:timezone":"Europe/Lisbon",
    "iso:country":"PT",
    "wof:name":"Outeiro Grande",
    "wof:placetype":"locality"
},
  "geometry": {"coordinates":[-8.51517,39.56142],"type":"Point"}
}