{
  "type": "Feature",
  "properties": {
    "gn:admin1_code":"22.0",
    "gn:admin2_code":"1823",
    "gn:admin3_code":"182324.0",
    "gn:asciiname":"Gumirais",
    "gn:country_code":"PT",
    "gn:dem":456,
    "gn:feature_class":"P",
    "gn:feature_code":"PPL",
    "gn:name":"Gumir\u00e3is",
    "gn:population":0,
    "gn:timezone":"Europe/Lisbon",
    "iso:country":"PT",
    "wof:name":"Gumirais",
    "wof:placetype":"locality"
},
  "geometry": {"coordinates":[-7.89404,40.6653],"type":"Point"}
}