{
  "type": "Feature",
  "properties": {
    "gn:admin1_code":"22.0",
    "gn:admin2_code":"1803",
    "gn:admin3_code":"180319.0",
    "gn:asciiname":"Cetos",
    "gn:country_code":"PT",
    "gn:dem":786,
    "gn:feature_class":"P",
    "gn:feature_code":"PPL",
    "gn:name":"Cetos",
    "gn:population":0,
    "gn:timezone":"Europe/Lisbon",
    "iso:country":"PT",
    "wof:name":"Cetos",
    "wof:placetype":"locality"
},
  "geometry": {"coordinates":[-7.97217,40.93838],"type":"Point"}
}