{
  "type": "Feature",
  "properties": {
    "gn:admin1_code":"7.0",
    "gn:admin2_code":"0603",
    "gn:admin3_code":"60301.0",
    "gn:asciiname":"Monforte",
    "gn:country_code":"PT",
    "gn:dem":201,
    "gn:feature_class":"P",
    "gn:feature_code":"PPL",
    "gn:name":"Monforte",
    "gn:population":0,
    "gn:timezone":"Europe/Lisbon",
    "iso:country":"PT",
    "name:arg_x_preferred":[
        "Monforte"
    ],
    "name:bar_x_preferred":[
        "Monforte"
    ],
    "name:cat_x_preferred":[
        "Monforte"
    ],
    "name:ceb_x_preferred":[
        "Monforte"
    ],
    "name:deu_x_preferred":[
        "Monforte"
    ],
    "name:fra_x_preferred":[
        "Monforte"
    ],
    "name:glg_x_preferred":[
        "Monforte"
    ],
    "name:ita_x_preferred":[
        "Monforte"
    ],
    "name:nld_x_preferred":[
        "Monforte"
    ],
    "name:por_x_preferred":[
        "Monforte"
    ],
    "name:spa_x_preferred":[
        "Monforte"
    ],
    "name:swe_x_preferred":[
        "Monforte"
    ],
    "name:ukr_x_preferred":[
        "\u041c\u043e\u043d\u0444\u043e\u0440\u0442\u0435"
    ],
    "wof:name":"Monforte",
    "wof:placetype":"locality"
},
  "geometry": {"coordinates":[-8.38688,40.10785],"type":"Point"}
}