{
  "type": "Feature",
  "properties": {
    "gn:admin1_code":"19",
    "gn:admin2_code":"1503",
    "gn:admin3_code":"150310.0",
    "gn:asciiname":"Barrocas",
    "gn:country_code":"PT",
    "gn:dem":1,
    "gn:feature_class":"P",
    "gn:feature_code":"PPL",
    "gn:name":"Barrocas",
    "gn:population":0,
    "gn:timezone":"Europe/Lisbon",
    "iso:country":"PT",
    "name:ceb_x_preferred":[
        "Barrocas"
    ],
    "name:epo_x_preferred":[
        "Barrocas"
    ],
    "name:eus_x_preferred":[
        "Barrocas"
    ],
    "name:fra_x_preferred":[
        "Barrocas"
    ],
    "name:hye_x_preferred":[
        "\u0532\u0561\u057c\u0578\u056f\u0561\u057d"
    ],
    "name:ita_x_preferred":[
        "Barrocas"
    ],
    "name:kat_x_preferred":[
        "\u10d1\u10d0\u10e0\u10dd\u10d9\u10d0\u10e1\u10d8"
    ],
    "name:kaz_x_preferred":[
        "\u0411\u0430\u0440\u0440\u043e\u043a\u0430\u0441"
    ],
    "name:mlg_x_preferred":[
        "Barrocas"
    ],
    "name:nld_x_preferred":[
        "Barrocas"
    ],
    "name:nor_x_preferred":[
        "Barrocas"
    ],
    "name:pol_x_preferred":[
        "Barrocas"
    ],
    "name:por_x_preferred":[
        "Barrocas"
    ],
    "name:ron_x_preferred":[
        "Barrocas"
    ],
    "name:rus_x_preferred":[
        "\u0411\u0430\u0440\u0440\u043e\u043a\u0430\u0441"
    ],
    "name:swe_x_preferred":[
        "Barrocas"
    ],
    "name:vie_x_preferred":[
        "Barrocas"
    ],
    "name:vol_x_preferred":[
        "Barrocas"
    ],
    "name:war_x_preferred":[
        "Barrocas"
    ],
    "name:zho_x_preferred":[
        "\u5df4\u7f57\u5361\u65af"
    ],
    "wof:name":"Barrocas",
    "wof:placetype":"locality"
},
  "geometry": {"coordinates":[-9.15732,38.66712],"type":"Point"}
}