{
  "type": "Feature",
  "properties": {
    "gn:admin1_code":"19",
    "gn:admin2_code":"1503",
    "gn:admin3_code":"150310.0",
    "gn:asciiname":"Barrocas",
    "gn:country_code":"PT",
    "gn:dem":1,
    "gn:feature_class":"P",
    "gn:feature_code":"PPL",
    "gn:name":"Barrocas",
    "gn:population":0,
    "gn:timezone":"Europe/Lisbon",
    "iso:country":"PT",
    "wof:name":"Barrocas",
    "wof:placetype":"locality"
},
  "geometry": {"coordinates":[-9.15732,38.66712],"type":"Point"}
}