{
  "type": "Feature",
  "properties": {
    "gn:admin1_code":"4.0",
    "gn:admin2_code":"0312",
    "gn:admin3_code":"31221.0",
    "gn:asciiname":"Landim",
    "gn:country_code":"PT",
    "gn:dem":96,
    "gn:feature_class":"P",
    "gn:feature_code":"PPL",
    "gn:name":"Landim",
    "gn:population":0,
    "gn:timezone":"Europe/Lisbon",
    "iso:country":"PT",
    "wof:name":"Landim",
    "wof:placetype":"locality"
},
  "geometry": {"coordinates":[-8.4685,41.38335],"type":"Point"}
}