{
  "type": "Feature",
  "properties": {
    "gn:admin1_code":"2.0",
    "gn:admin2_code":"0109",
    "gn:admin3_code":"10922.0",
    "gn:asciiname":"Mouquim",
    "gn:country_code":"PT",
    "gn:dem":257,
    "gn:feature_class":"P",
    "gn:feature_code":"PPL",
    "gn:name":"Mouquim",
    "gn:population":0,
    "gn:timezone":"Europe/Lisbon",
    "iso:country":"PT",
    "wof:name":"Mouquim",
    "wof:placetype":"locality"
},
  "geometry": {"coordinates":[-8.46054,40.93271],"type":"Point"}
}