{
  "type": "Feature",
  "properties": {
    "gn:admin1_code":"16",
    "gn:admin2_code":"1205",
    "gn:admin3_code":"120502.0",
    "gn:asciiname":"Bom Jesus",
    "gn:country_code":"PT",
    "gn:dem":477,
    "gn:feature_class":"P",
    "gn:feature_code":"PPL",
    "gn:name":"Bom Jesus",
    "gn:population":0,
    "gn:timezone":"Europe/Lisbon",
    "iso:country":"PT",
    "wof:name":"Bom Jesus",
    "wof:placetype":"locality"
},
  "geometry": {"coordinates":[-7.45163,39.42121],"type":"Point"}
}