{
  "type": "Feature",
  "properties": {
    "gn:admin1_code":"11",
    "gn:admin2_code":"0910",
    "gn:admin3_code":"91027.0",
    "gn:asciiname":"Vascoveiro",
    "gn:country_code":"PT",
    "gn:dem":598,
    "gn:feature_class":"P",
    "gn:feature_code":"PPL",
    "gn:name":"Vascoveiro",
    "gn:population":0,
    "gn:timezone":"Europe/Lisbon",
    "iso:country":"PT",
    "wof:name":"Vascoveiro",
    "wof:placetype":"locality"
},
  "geometry": {"coordinates":[-7.06995,40.73466],"type":"Point"}
}