{
  "type": "Feature",
  "properties": {
    "gn:country":"PT",
    "gn:fcode":"PPL",
    "gn:population":0,
    "iso:country":"PT",
    "name:cat_x_preferred":[
        "Granja"
    ],
    "name:ceb_x_preferred":[
        "Granja"
    ],
    "name:deu_x_preferred":[
        "Granja"
    ],
    "name:fra_x_preferred":[
        "Granja"
    ],
    "name:ita_x_preferred":[
        "Granja"
    ],
    "name:mlg_x_preferred":[
        "Granja"
    ],
    "name:nld_x_preferred":[
        "Granja"
    ],
    "name:por_x_preferred":[
        "Granja"
    ],
    "name:rus_x_preferred":[
        "\u0413\u0440\u0430\u043d\u0436\u0430"
    ],
    "name:spa_x_preferred":[
        "Granja"
    ],
    "name:swe_x_preferred":[
        "Granja"
    ],
    "name:tur_x_preferred":[
        "Granja"
    ],
    "name:vie_x_preferred":[
        "Granja"
    ],
    "qs_pg:aaroncc":"PT",
    "qs_pg:gn_country":"PT",
    "qs_pg:gn_fcode":"PPL",
    "qs_pg:gn_pop":0,
    "qs_pg:name":"Granja",
    "qs_pg:name_adm0":"Portugal",
    "qs_pg:name_adm1":"Vila Real",
    "qs_pg:photos":11,
    "qs_pg:photos_1k":2,
    "qs_pg:photos_9k":1,
    "qs_pg:photos_9r":1,
    "qs_pg:photos_all":11,
    "qs_pg:photos_sr":1,
    "qs_pg:pop_sr":0,
    "qs_pg:qs_pg_placetype":"locality",
    "qs_pg:qs_pg_placetype_gp":"Town",
    "qs_pg:woe_adm0":23424925,
    "woe:adm0_id":23424925,
    "woe:name_adm0":"Portugal",
    "woe:name_adm1":"Vila Real",
    "woe:placetype":"Town",
    "wof:name":"Granja",
    "wof:placetype":"locality"
},
  "geometry": {"coordinates":[-7.64953,41.6947],"type":"Point"}
}