{
  "type": "Feature",
  "properties": {
    "gn:admin1_code":"2.0",
    "gn:admin2_code":"0102",
    "gn:admin3_code":"10201.0",
    "gn:asciiname":"Assilho",
    "gn:country_code":"PT",
    "gn:dem":112,
    "gn:feature_class":"P",
    "gn:feature_code":"PPL",
    "gn:name":"Assilh\u00f3",
    "gn:population":0,
    "gn:timezone":"Europe/Lisbon",
    "iso:country":"PT",
    "wof:name":"Assilho",
    "wof:placetype":"locality"
},
  "geometry": {"coordinates":[-8.47994,40.6866],"type":"Point"}
}