{
  "type": "Feature",
  "properties": {
    "gn:admin1_code":"17",
    "gn:admin2_code":"1302",
    "gn:admin3_code":"130213.0",
    "gn:asciiname":"Sao Salvador",
    "gn:country_code":"PT",
    "gn:dem":297,
    "gn:feature_class":"P",
    "gn:feature_code":"PPL",
    "gn:name":"S\u00e3o Salvador",
    "gn:population":0,
    "gn:timezone":"Europe/Lisbon",
    "iso:country":"PT",
    "wof:name":"Sao Salvador",
    "wof:placetype":"locality"
},
  "geometry": {"coordinates":[-8.00794,41.11721],"type":"Point"}
}