{
  "type": "Feature",
  "properties": {
    "gn:admin1_code":"4.0",
    "gn:admin2_code":"0305",
    "gn:admin3_code":"30507.0",
    "gn:asciiname":"Carvalho",
    "gn:country_code":"PT",
    "gn:dem":526,
    "gn:feature_class":"P",
    "gn:feature_code":"PPL",
    "gn:name":"Carvalho",
    "gn:population":0,
    "gn:timezone":"Europe/Lisbon",
    "iso:country":"PT",
    "name:deu_x_preferred":[
        "Carvalho"
    ],
    "name:por_x_preferred":[
        "Carvalho"
    ],
    "wof:name":"Carvalho",
    "wof:placetype":"locality"
},
  "geometry": {"coordinates":[-8.0666,41.37873],"type":"Point"}
}