{
  "type": "Feature",
  "properties": {
    "gn:admin1_code":"22.0",
    "gn:admin2_code":"1823",
    "gn:admin3_code":"182322.0",
    "gn:asciiname":"Gomiei",
    "gn:country_code":"PT",
    "gn:dem":447,
    "gn:feature_class":"P",
    "gn:feature_code":"PPL",
    "gn:name":"Gomiei",
    "gn:population":0,
    "gn:timezone":"Europe/Lisbon",
    "iso:country":"PT",
    "wof:name":"Gomiei",
    "wof:placetype":"locality"
},
  "geometry": {"coordinates":[-8.00406,40.74713],"type":"Point"}
}