{
  "type": "Feature",
  "properties": {
    "gn:admin1_code":"21",
    "gn:admin2_code":"1705",
    "gn:admin3_code":"170508.0",
    "gn:asciiname":"Vila Cha",
    "gn:country_code":"PT",
    "gn:dem":549,
    "gn:feature_class":"P",
    "gn:feature_code":"PPL",
    "gn:name":"Vila Ch\u00e3",
    "gn:population":0,
    "gn:timezone":"Europe/Lisbon",
    "iso:country":"PT",
    "wof:name":"Vila Cha",
    "wof:placetype":"locality"
},
  "geometry": {"coordinates":[-7.86887,41.39487],"type":"Point"}
}