{
  "type": "Feature",
  "properties": {
    "gn:admin1_code":"22",
    "gn:admin2_code":"1802",
    "gn:admin3_code":"180206.0",
    "gn:asciiname":"Povoa das Forcadas",
    "gn:country_code":"PT",
    "gn:dem":290,
    "gn:feature_class":"P",
    "gn:feature_code":"PPL",
    "gn:name":"P\u00f3voa das Forcadas",
    "gn:population":0,
    "gn:timezone":"Europe/Lisbon",
    "iso:country":"PT",
    "wof:name":"Povoa das Forcadas",
    "wof:placetype":"locality"
},
  "geometry": {"coordinates":[-8.03137,40.41535],"type":"Point"}
}