{
  "type": "Feature",
  "properties": {
    "gn:admin1_code":"4.0",
    "gn:admin2_code":"0303",
    "gn:admin3_code":"30343.0",
    "gn:asciiname":"Passos",
    "gn:country_code":"PT",
    "gn:dem":138,
    "gn:feature_class":"P",
    "gn:feature_code":"PPL",
    "gn:name":"Passos",
    "gn:population":0,
    "gn:timezone":"Europe/Lisbon",
    "iso:country":"PT",
    "name:ceb_x_preferred":[
        "Passos"
    ],
    "name:deu_x_preferred":[
        "Passos"
    ],
    "name:fra_x_preferred":[
        "Passos"
    ],
    "name:nld_x_preferred":[
        "Passos"
    ],
    "name:pol_x_preferred":[
        "Passos"
    ],
    "name:por_x_preferred":[
        "Passos"
    ],
    "name:rus_x_preferred":[
        "\u041f\u0430\u0441\u0441\u0443\u0448"
    ],
    "name:swe_x_preferred":[
        "Passos"
    ],
    "name:ukr_x_preferred":[
        "\u041f\u0430\u0441\u0441\u0443\u0448"
    ],
    "wof:name":"Passos",
    "wof:placetype":"locality"
},
  "geometry": {"coordinates":[-8.49914,41.52907],"type":"Point"}
}