{
  "type": "Feature",
  "properties": {
    "gn:admin1_code":"07",
    "gn:admin2_code":"0601",
    "gn:admin3_code":"60105.0",
    "gn:asciiname":"Sequeiros",
    "gn:country_code":"PT",
    "gn:dem":241,
    "gn:feature_class":"P",
    "gn:feature_code":"PPL",
    "gn:name":"Sequeiros",
    "gn:population":0,
    "gn:timezone":"Europe/Lisbon",
    "iso:country":"PT",
    "wof:name":"Sequeiros",
    "wof:placetype":"locality"
},
  "geometry": {"coordinates":[-8.07672,40.18162],"type":"Point"}
}