{
  "type": "Feature",
  "properties": {
    "gn:admin1_code":"21.0",
    "gn:admin2_code":"1703",
    "gn:admin3_code":"170318.0",
    "gn:asciiname":"Alanhosa",
    "gn:country_code":"PT",
    "gn:dem":826,
    "gn:feature_class":"P",
    "gn:feature_code":"PPL",
    "gn:name":"Alanhosa",
    "gn:population":0,
    "gn:timezone":"Europe/Lisbon",
    "iso:country":"PT",
    "wof:name":"Alanhosa",
    "wof:placetype":"locality"
},
  "geometry": {"coordinates":[-7.44481,41.67041],"type":"Point"}
}