{
  "type": "Feature",
  "properties": {
    "gn:admin1_code":"22.0",
    "gn:admin2_code":"1806",
    "gn:admin3_code":"180610.0",
    "gn:asciiname":"Caes de Baixo",
    "gn:country_code":"PT",
    "gn:dem":441,
    "gn:feature_class":"P",
    "gn:feature_code":"PPL",
    "gn:name":"C\u00e3es de Baixo",
    "gn:population":0,
    "gn:timezone":"Europe/Lisbon",
    "iso:country":"PT",
    "wof:name":"Caes de Baixo",
    "wof:placetype":"locality"
},
  "geometry": {"coordinates":[-7.78333,40.58333],"type":"Point"}
}