{
  "type": "Feature",
  "properties": {
    "gn:admin1_code":"7.0",
    "gn:admin2_code":"0616",
    "gn:admin3_code":"61606.0",
    "gn:asciiname":"Espariz",
    "gn:country_code":"PT",
    "gn:dem":308,
    "gn:feature_class":"P",
    "gn:feature_code":"PPL",
    "gn:name":"Espariz",
    "gn:population":0,
    "gn:timezone":"Europe/Lisbon",
    "iso:country":"PT",
    "wof:name":"Espariz",
    "wof:placetype":"locality"
},
  "geometry": {"coordinates":[-8.03178,40.31324],"type":"Point"}
}