{
  "type": "Feature",
  "properties": {
    "gn:admin1_code":"7.0",
    "gn:admin2_code":"0601",
    "gn:admin3_code":"60108.0",
    "gn:asciiname":"Esculca",
    "gn:country_code":"PT",
    "gn:dem":500,
    "gn:feature_class":"P",
    "gn:feature_code":"PPL",
    "gn:name":"Esculca",
    "gn:population":0,
    "gn:timezone":"Europe/Lisbon",
    "iso:country":"PT",
    "wof:name":"Esculca",
    "wof:placetype":"locality"
},
  "geometry": {"coordinates":[-7.96867,40.2394],"type":"Point"}
}