{
  "type": "Feature",
  "properties": {
    "gn:admin1_code":"18",
    "gn:admin2_code":"1415",
    "gn:admin3_code":"141503.0",
    "gn:asciiname":"Malhada dos Porcos",
    "gn:country_code":"PT",
    "gn:dem":20,
    "gn:feature_class":"P",
    "gn:feature_code":"PPL",
    "gn:name":"Malhada dos Porcos",
    "gn:population":0,
    "gn:timezone":"Europe/Lisbon",
    "iso:country":"PT",
    "wof:name":"Malhada dos Porcos",
    "wof:placetype":"locality"
},
  "geometry": {"coordinates":[-8.67512,39.10132],"type":"Point"}
}