{
  "type": "Feature",
  "properties": {
    "gn:admin1_code":"2.0",
    "gn:admin2_code":"0108",
    "gn:admin3_code":"10801.0",
    "gn:asciiname":"Falcao",
    "gn:country_code":"PT",
    "gn:dem":41,
    "gn:feature_class":"P",
    "gn:feature_code":"PPL",
    "gn:name":"Falc\u00e3o",
    "gn:population":0,
    "gn:timezone":"Europe/Lisbon",
    "iso:country":"PT",
    "wof:name":"Falcao",
    "wof:placetype":"locality"
},
  "geometry": {"coordinates":[-8.56679,40.79052],"type":"Point"}
}