{
  "type": "Feature",
  "properties": {
    "gn:country":"PT",
    "gn:fcode":"PPL",
    "gn:population":0,
    "iso:country":"PT",
    "name:ceb_x_preferred":[
        "Odeleite"
    ],
    "name:deu_x_preferred":[
        "Odeleite"
    ],
    "name:kaz_x_preferred":[
        "\u041e\u0434\u0435\u043b\u0435\u0439\u0442\u0435"
    ],
    "name:nld_x_preferred":[
        "Odeleite"
    ],
    "name:por_x_preferred":[
        "Odeleite"
    ],
    "name:rus_x_preferred":[
        "\u041e\u0434\u0435\u043b\u0435\u0439\u0442\u0435"
    ],
    "name:spa_x_preferred":[
        "Odeleite"
    ],
    "qs_pg:aaroncc":"PT",
    "qs_pg:gn_country":"PT",
    "qs_pg:gn_fcode":"PPL",
    "qs_pg:gn_pop":0,
    "qs_pg:name":"Odeleite",
    "qs_pg:name_adm0":"Portugal",
    "qs_pg:name_adm1":"Faro",
    "qs_pg:photos":85,
    "qs_pg:photos_1k":17,
    "qs_pg:photos_9k":1,
    "qs_pg:photos_9r":3,
    "qs_pg:photos_all":85,
    "qs_pg:photos_sr":3,
    "qs_pg:pop_sr":0,
    "qs_pg:qs_pg_placetype":"locality",
    "qs_pg:qs_pg_placetype_gp":"Town",
    "qs_pg:woe_adm0":23424925,
    "woe:adm0_id":23424925,
    "woe:name_adm0":"Portugal",
    "woe:name_adm1":"Faro",
    "woe:placetype":"Town",
    "wof:name":"Odeleite",
    "wof:placetype":"locality"
},
  "geometry": {"coordinates":[-7.48728,37.33372],"type":"Point"}
}