{
  "type": "Feature",
  "properties": {
    "gn:admin1_code":"7.0",
    "gn:admin2_code":"0615",
    "gn:admin3_code":"61510.0",
    "gn:asciiname":"Carpinteiras",
    "gn:country_code":"PT",
    "gn:dem":119,
    "gn:feature_class":"P",
    "gn:feature_code":"PPL",
    "gn:name":"Carpinteiras",
    "gn:population":0,
    "gn:timezone":"Europe/Lisbon",
    "iso:country":"PT",
    "wof:name":"Carpinteiras",
    "wof:placetype":"locality"
},
  "geometry": {"coordinates":[-8.53168,40.03775],"type":"Point"}
}