{
  "type": "Feature",
  "properties": {
    "gn:admin1_code":"02",
    "gn:admin2_code":"0109",
    "gn:admin3_code":"10930.0",
    "gn:asciiname":"Serralva",
    "gn:country_code":"PT",
    "gn:dem":165,
    "gn:feature_class":"P",
    "gn:feature_code":"PPL",
    "gn:name":"Serralva",
    "gn:population":0,
    "gn:timezone":"Europe/Lisbon",
    "iso:country":"PT",
    "wof:name":"Serralva",
    "wof:placetype":"locality"
},
  "geometry": {"coordinates":[-8.43146,41.00512],"type":"Point"}
}