{
  "type": "Feature",
  "properties": {
    "gn:admin1_code":"09",
    "gn:admin2_code":"0804",
    "gn:admin3_code":"80403.0",
    "gn:asciiname":"Alcaria",
    "gn:country_code":"PT",
    "gn:dem":91,
    "gn:feature_class":"P",
    "gn:feature_code":"PPL",
    "gn:name":"Alcaria",
    "gn:population":0,
    "gn:timezone":"Europe/Lisbon",
    "iso:country":"PT",
    "wof:name":"Alcaria",
    "wof:placetype":"locality"
},
  "geometry": {"coordinates":[-7.46705,37.33749],"type":"Point"}
}