{
  "type": "Feature",
  "properties": {
    "gn:admin1_code":"18",
    "gn:admin2_code":"1403",
    "gn:admin3_code":"140301.0",
    "gn:asciiname":"Quinta do Casal Branco",
    "gn:country_code":"PT",
    "gn:dem":14,
    "gn:feature_class":"P",
    "gn:feature_code":"PPL",
    "gn:name":"Quinta do Casal Branco",
    "gn:population":0,
    "gn:timezone":"Europe/Lisbon",
    "iso:country":"PT",
    "wof:name":"Quinta do Casal Branco",
    "wof:placetype":"locality"
},
  "geometry": {"coordinates":[-8.65977,39.16981],"type":"Point"}
}