{
  "type": "Feature",
  "properties": {
    "gn:admin1_code":"18",
    "gn:admin2_code":"1407",
    "gn:admin3_code":"140706.0",
    "gn:asciiname":"Cantarinhos de Cima",
    "gn:country_code":"PT",
    "gn:dem":103,
    "gn:feature_class":"P",
    "gn:feature_code":"PPL",
    "gn:name":"Cantarinhos de Cima",
    "gn:population":0,
    "gn:timezone":"Europe/Lisbon",
    "iso:country":"PT",
    "wof:name":"Cantarinhos de Cima",
    "wof:placetype":"locality"
},
  "geometry": {"coordinates":[-8.42805,39.14745],"type":"Point"}
}