{
  "type": "Feature",
  "properties": {
    "gn:admin1_code":"21",
    "gn:admin2_code":"1702",
    "gn:admin3_code":"170210.0",
    "gn:asciiname":"Vila Pequena",
    "gn:country_code":"PT",
    "gn:dem":737,
    "gn:feature_class":"P",
    "gn:feature_code":"PPL",
    "gn:name":"Vila Pequena",
    "gn:population":0,
    "gn:timezone":"Europe/Lisbon",
    "iso:country":"PT",
    "wof:name":"Vila Pequena",
    "wof:placetype":"locality"
},
  "geometry": {"coordinates":[-7.8423,41.65219],"type":"Point"}
}