{
  "type": "Feature",
  "properties": {
    "gn:admin1_code":"18",
    "gn:admin2_code":"1413",
    "gn:admin3_code":"141302.0",
    "gn:asciiname":"Aldeia de Eiras",
    "gn:country_code":"PT",
    "gn:dem":309,
    "gn:feature_class":"P",
    "gn:feature_code":"PPL",
    "gn:name":"Aldeia de Eiras",
    "gn:population":0,
    "gn:timezone":"Europe/Lisbon",
    "iso:country":"PT",
    "wof:name":"Aldeia de Eiras",
    "wof:placetype":"locality"
},
  "geometry": {"coordinates":[-8.01258,39.63024],"type":"Point"}
}