{
  "type": "Feature",
  "properties": {
    "gn:admin1_code":"2.0",
    "gn:admin2_code":"0109",
    "gn:admin3_code":"10915.0",
    "gn:asciiname":"Agoncida",
    "gn:country_code":"PT",
    "gn:dem":165,
    "gn:feature_class":"P",
    "gn:feature_code":"PPL",
    "gn:name":"Agoncida",
    "gn:population":0,
    "gn:timezone":"Europe/Lisbon",
    "iso:country":"PT",
    "wof:name":"Agoncida",
    "wof:placetype":"locality"
},
  "geometry": {"coordinates":[-8.53302,40.89563],"type":"Point"}
}