{
  "type": "Feature",
  "properties": {
    "gn:admin1_code":"7.0",
    "gn:admin2_code":"0610",
    "gn:admin3_code":"61011.0",
    "gn:asciiname":"Murraca",
    "gn:country_code":"PT",
    "gn:dem":75,
    "gn:feature_class":"P",
    "gn:feature_code":"PPL",
    "gn:name":"Murra\u00e7\u00e3",
    "gn:population":0,
    "gn:timezone":"Europe/Lisbon",
    "iso:country":"PT",
    "wof:name":"Murraca",
    "wof:placetype":"locality"
},
  "geometry": {"coordinates":[-8.6211,40.24374],"type":"Point"}
}