{
  "type": "Feature",
  "properties": {
    "gn:admin1_code":"18",
    "gn:admin2_code":"1403",
    "gn:admin3_code":"140303.0",
    "gn:asciiname":"Pacos Velhos",
    "gn:country_code":"PT",
    "gn:dem":40,
    "gn:feature_class":"P",
    "gn:feature_code":"PPL",
    "gn:name":"Pa\u00e7os Velhos",
    "gn:population":0,
    "gn:timezone":"Europe/Lisbon",
    "iso:country":"PT",
    "wof:name":"Pacos Velhos",
    "wof:placetype":"locality"
},
  "geometry": {"coordinates":[-8.52564,39.14236],"type":"Point"}
}