{
  "type": "Feature",
  "properties": {
    "gn:admin1_code":"02",
    "gn:admin2_code":"0117",
    "gn:admin3_code":"11707.0",
    "gn:asciiname":"Prezas",
    "gn:country_code":"PT",
    "gn:dem":475,
    "gn:feature_class":"P",
    "gn:feature_code":"PPL",
    "gn:name":"Prezas",
    "gn:population":0,
    "gn:timezone":"Europe/Lisbon",
    "iso:country":"PT",
    "wof:name":"Prezas",
    "wof:placetype":"locality"
},
  "geometry": {"coordinates":[-8.37474,40.76949000000001],"type":"Point"}
}