{
  "type": "Feature",
  "properties": {
    "gn:admin1_code":"06",
    "gn:admin2_code":"0509",
    "gn:admin3_code":"50907.0",
    "gn:asciiname":"Sorvel Fundeiro",
    "gn:country_code":"PT",
    "gn:dem":508,
    "gn:feature_class":"P",
    "gn:feature_code":"PPL",
    "gn:name":"Sorvel Fundeiro",
    "gn:population":0,
    "gn:timezone":"Europe/Lisbon",
    "iso:country":"PT",
    "wof:name":"Sorvel Fundeiro",
    "wof:placetype":"locality"
},
  "geometry": {"coordinates":[-7.99762,39.83045],"type":"Point"}
}