{
  "type": "Feature",
  "properties": {
    "gn:admin1_code":"7.0",
    "gn:admin2_code":"0601",
    "gn:admin3_code":"60102.0",
    "gn:asciiname":"Casal de Sao Jose",
    "gn:country_code":"PT",
    "gn:dem":286,
    "gn:feature_class":"P",
    "gn:feature_code":"PPL",
    "gn:name":"Casal de S\u00e3o Jos\u00e9",
    "gn:population":0,
    "gn:timezone":"Europe/Lisbon",
    "iso:country":"PT",
    "wof:name":"Casal de Sao Jose",
    "wof:placetype":"locality"
},
  "geometry": {"coordinates":[-8.05236,40.20552],"type":"Point"}
}