{
  "type": "Feature",
  "properties": {
    "gn:admin1_code":"04",
    "gn:admin2_code":"0306",
    "gn:admin3_code":"30601.0",
    "gn:asciiname":"Sao Paio de Cima",
    "gn:country_code":"PT",
    "gn:dem":128,
    "gn:feature_class":"P",
    "gn:feature_code":"PPL",
    "gn:name":"S\u00e3o Paio de Cima",
    "gn:population":0,
    "gn:timezone":"Europe/Lisbon",
    "iso:country":"PT",
    "wof:name":"Sao Paio de Cima",
    "wof:placetype":"locality"
},
  "geometry": {"coordinates":[-8.76111,41.59633],"type":"Point"}
}