{
  "type": "Feature",
  "properties": {
    "gn:admin1_code":"08",
    "gn:admin2_code":"0702",
    "gn:admin3_code":"70202.0",
    "gn:asciiname":"Cortical de Baixo",
    "gn:country_code":"PT",
    "gn:dem":282,
    "gn:feature_class":"P",
    "gn:feature_code":"PPL",
    "gn:name":"Corti\u00e7al de Baixo",
    "gn:population":0,
    "gn:timezone":"Europe/Lisbon",
    "iso:country":"PT",
    "wof:name":"Cortical de Baixo",
    "wof:placetype":"locality"
},
  "geometry": {"coordinates":[-7.86161,38.71352],"type":"Point"}
}