{
  "type": "Feature",
  "properties": {
    "gn:admin1_code":"13",
    "gn:admin2_code":"1003",
    "gn:admin3_code":"100307.0",
    "gn:asciiname":"Mogadouro de Baixo",
    "gn:country_code":"PT",
    "gn:dem":219,
    "gn:feature_class":"P",
    "gn:feature_code":"PPL",
    "gn:name":"Mogadouro de Baixo",
    "gn:population":0,
    "gn:timezone":"Europe/Lisbon",
    "iso:country":"PT",
    "wof:name":"Mogadouro de Baixo",
    "wof:placetype":"locality"
},
  "geometry": {"coordinates":[-8.47891,39.90504],"type":"Point"}
}