{
  "type": "Feature",
  "properties": {
    "gn:admin1_code":"2.0",
    "gn:admin2_code":"0104",
    "gn:admin3_code":"10402.0",
    "gn:asciiname":"Lubrem",
    "gn:country_code":"PT",
    "gn:dem":419,
    "gn:feature_class":"P",
    "gn:feature_code":"PPL",
    "gn:name":"Lubr\u00e9m",
    "gn:population":0,
    "gn:timezone":"Europe/Lisbon",
    "iso:country":"PT",
    "wof:name":"Lubrem",
    "wof:placetype":"locality"
},
  "geometry": {"coordinates":[-8.15,40.96667],"type":"Point"}
}