{
  "type": "Feature",
  "properties": {
    "gn:admin1_code":"17",
    "gn:admin2_code":"1313",
    "gn:admin3_code":"131310.0",
    "gn:asciiname":"Vila Velha",
    "gn:country_code":"PT",
    "gn:dem":10,
    "gn:feature_class":"P",
    "gn:feature_code":"PPL",
    "gn:name":"Vila Velha",
    "gn:population":0,
    "gn:timezone":"Europe/Lisbon",
    "iso:country":"PT",
    "wof:name":"Vila Velha",
    "wof:placetype":"locality"
},
  "geometry": {"coordinates":[-8.76667,41.38333],"type":"Point"}
}