{
  "type": "Feature",
  "properties": {
    "gn:admin1_code":"17",
    "gn:admin2_code":"1313",
    "gn:admin3_code":"131310.0",
    "gn:asciiname":"Vila Velha",
    "gn:country_code":"PT",
    "gn:dem":10,
    "gn:feature_class":"P",
    "gn:feature_code":"PPL",
    "gn:name":"Vila Velha",
    "gn:population":0,
    "gn:timezone":"Europe/Lisbon",
    "iso:country":"PT",
    "name:ara_x_preferred":[
        "\u0641\u064a\u0644\u0627 \u0641\u0627\u0644\u064a\u0627"
    ],
    "name:bpy_x_preferred":[
        "\u09ad\u09bf\u09b2\u09be \u09ad\u09c7\u09b2\u09b9\u09be"
    ],
    "name:bul_x_preferred":[
        "\u0412\u0438\u043b\u0430 \u0412\u0435\u043b\u044f"
    ],
    "name:ceb_x_preferred":[
        "Vila Velha"
    ],
    "name:deu_x_preferred":[
        "Vila Velha"
    ],
    "name:ell_x_preferred":[
        "\u0392\u03af\u03bb\u03b1 \u0392\u03ad\u03bb\u03b9\u03b1"
    ],
    "name:eml_x_preferred":[
        "Vila Velha"
    ],
    "name:epo_x_preferred":[
        "Vila Velha"
    ],
    "name:eus_x_preferred":[
        "Vila Velha"
    ],
    "name:fra_x_preferred":[
        "Vila Velha"
    ],
    "name:heb_x_preferred":[
        "\u05d5\u05d9\u05dc\u05d4 \u05d5\u05dc\u05d9\u05d4"
    ],
    "name:hrv_x_preferred":[
        "Vila Velha"
    ],
    "name:hun_x_preferred":[
        "Vila Velha"
    ],
    "name:hye_x_preferred":[
        "\u054e\u056b\u056c\u0561 \u054e\u0565\u056c\u056b\u0561"
    ],
    "name:ido_x_preferred":[
        "Vila Velha"
    ],
    "name:ita_x_preferred":[
        "Vila Velha"
    ],
    "name:jpn_x_preferred":[
        "\u30f4\u30a3\u30e9\u30fb\u30f4\u30a7\u30fc\u30ea\u30e3"
    ],
    "name:kat_x_preferred":[
        "\u10d5\u10d8\u10da\u10d0-\u10d5\u10d4\u10da\u10d8\u10d0"
    ],
    "name:kaz_x_preferred":[
        "\u0412\u0438\u043b\u0430-\u0412\u0435\u043b\u044c\u044f"
    ],
    "name:kor_x_preferred":[
        "\ube4c\ub77c \ubca8\ud558"
    ],
    "name:kor_x_variant":[
        "\ube4c\ub77c\ubca8\ub7b4"
    ],
    "name:lit_x_preferred":[
        "Vila Velja"
    ],
    "name:mlg_x_preferred":[
        "Vila Velha"
    ],
    "name:nld_x_preferred":[
        "Vila Velha"
    ],
    "name:nor_x_preferred":[
        "Vila Velha"
    ],
    "name:pol_x_preferred":[
        "Vila Velha"
    ],
    "name:por_x_preferred":[
        "Vila Velha"
    ],
    "name:ron_x_preferred":[
        "Vila Velha"
    ],
    "name:rus_x_preferred":[
        "\u0412\u0438\u043b\u0430-\u0412\u0435\u043b\u044c\u044f"
    ],
    "name:spa_x_preferred":[
        "Vila Velha"
    ],
    "name:srp_x_preferred":[
        "\u0412\u0438\u043b\u0430 \u0412\u0435\u0459\u0430"
    ],
    "name:swe_x_preferred":[
        "Vila Velha"
    ],
    "name:tat_x_preferred":[
        "\u0412\u0438\u043b\u0430-\u0412\u0435\u043b\u044c\u044f"
    ],
    "name:tur_x_preferred":[
        "Vila Velha"
    ],
    "name:ukr_x_preferred":[
        "\u0412\u0456\u043b\u0430-\u0412\u0435\u043b\u044c\u044f"
    ],
    "name:urd_x_preferred":[
        "\u0648\u0644\u0627 \u0648\u06cc\u0644\u06c1\u0627"
    ],
    "name:vie_x_preferred":[
        "Vila Velha"
    ],
    "name:vol_x_preferred":[
        "Vila Velha"
    ],
    "name:war_x_preferred":[
        "Vila Velha"
    ],
    "name:zho_cn_x_preferred":[
        "\u97e6\u5229\u4e9a\u9547"
    ],
    "name:zho_tw_x_preferred":[
        "\u97cb\u5229\u4e9e\u93ae"
    ],
    "name:zho_x_preferred":[
        "\u97e6\u5229\u4e9a\u9547"
    ],
    "wof:name":"Vila Velha",
    "wof:placetype":"locality"
},
  "geometry": {"coordinates":[-8.76667,41.38333],"type":"Point"}
}