{
  "type": "Feature",
  "properties": {
    "gn:admin1_code":"13",
    "gn:admin2_code":"1008",
    "gn:admin3_code":"100801.0",
    "gn:asciiname":"Moninhos Fundeiros",
    "gn:country_code":"PT",
    "gn:dem":362,
    "gn:feature_class":"P",
    "gn:feature_code":"PPL",
    "gn:name":"Moninhos Fundeiros",
    "gn:population":0,
    "gn:timezone":"Europe/Lisbon",
    "iso:country":"PT",
    "wof:name":"Moninhos Fundeiros",
    "wof:placetype":"locality"
},
  "geometry": {"coordinates":[-8.29743,39.9467],"type":"Point"}
}