{
  "type": "Feature",
  "properties": {
    "gn:country":"PT",
    "gn:fcode":"PPL",
    "gn:population":4686,
    "iso:country":"PT",
    "name:ast_x_preferred":[
        "Lustosa"
    ],
    "name:ceb_x_preferred":[
        "Lustosa"
    ],
    "name:che_x_preferred":[
        "\u041b\u0443\u0448\u0442\u043e\u0437\u0430"
    ],
    "name:deu_x_preferred":[
        "Lustosa"
    ],
    "name:eng_x_preferred":[
        "Lustosa"
    ],
    "name:fra_x_preferred":[
        "Lustosa"
    ],
    "name:kaz_x_preferred":[
        "\u041b\u0443\u0448\u0442\u043e\u0437\u0430"
    ],
    "name:nan_x_preferred":[
        "Lustosa"
    ],
    "name:nld_x_preferred":[
        "Lustosa"
    ],
    "name:por_x_preferred":[
        "Lustosa"
    ],
    "name:rus_x_preferred":[
        "\u041b\u0443\u0448\u0442\u043e\u0437\u0430"
    ],
    "name:spa_x_preferred":[
        "Lustosa"
    ],
    "name:tat_x_preferred":[
        "\u041b\u0443\u0448\u0442\u043e\u0437\u0430"
    ],
    "name:zho_x_preferred":[
        "Lustosa"
    ],
    "qs_pg:aaroncc":"PT",
    "qs_pg:gn_country":"PT",
    "qs_pg:gn_fcode":"PPL",
    "qs_pg:gn_pop":4686,
    "qs_pg:name":"Lustosa",
    "qs_pg:name_adm0":"Portugal",
    "qs_pg:name_adm1":"Porto",
    "qs_pg:photos":14,
    "qs_pg:photos_1k":3,
    "qs_pg:photos_9k":1,
    "qs_pg:photos_9r":1,
    "qs_pg:photos_all":14,
    "qs_pg:photos_sr":1,
    "qs_pg:pop_sr":4,
    "qs_pg:qs_pg_placetype":"locality",
    "qs_pg:qs_pg_placetype_gp":"Town",
    "qs_pg:woe_adm0":23424925,
    "woe:adm0_id":23424925,
    "woe:name_adm0":"Portugal",
    "woe:name_adm1":"Porto",
    "woe:placetype":"Town",
    "wof:name":"Lustosa",
    "wof:placetype":"locality",
    "wof:population":4686
},
  "geometry": {"coordinates":[-8.31715,41.34082],"type":"Point"}
}