{
  "type": "Feature",
  "properties": {
    "gn:admin1_code":"6.0",
    "gn:admin2_code":"0504",
    "gn:admin3_code":"50414.0",
    "gn:asciiname":"Chaos",
    "gn:country_code":"PT",
    "gn:dem":465,
    "gn:feature_class":"P",
    "gn:feature_code":"PPL",
    "gn:name":"Ch\u00e3os",
    "gn:population":0,
    "gn:timezone":"Europe/Lisbon",
    "iso:country":"PT",
    "wof:name":"Chaos",
    "wof:placetype":"locality"
},
  "geometry": {"coordinates":[-7.45944,40.13615],"type":"Point"}
}