{
  "type": "Feature",
  "properties": {
    "gn:admin1_code":"2.0",
    "gn:admin2_code":"0103",
    "gn:admin3_code":"10305.0",
    "gn:asciiname":"Figueira",
    "gn:country_code":"PT",
    "gn:dem":112,
    "gn:feature_class":"P",
    "gn:feature_code":"PPL",
    "gn:name":"Figueira",
    "gn:population":0,
    "gn:timezone":"Europe/Lisbon",
    "iso:country":"PT",
    "name:ceb_x_preferred":[
        "Figueira"
    ],
    "name:deu_x_preferred":[
        "Figueira"
    ],
    "name:fra_x_preferred":[
        "Figueira"
    ],
    "name:glg_x_preferred":[
        "Figueira"
    ],
    "name:nld_x_preferred":[
        "Figueira"
    ],
    "name:por_x_preferred":[
        "Figueira"
    ],
    "name:rus_x_preferred":[
        "\u0424\u0438\u0433\u0435\u0439\u0440\u0430"
    ],
    "name:swe_x_preferred":[
        "Figueira"
    ],
    "name:ukr_x_preferred":[
        "\u0424\u0456\u0433\u0435\u0439\u0440\u0430"
    ],
    "wof:name":"Figueira",
    "wof:placetype":"locality"
},
  "geometry": {"coordinates":[-8.38373,40.4884],"type":"Point"}
}