{
  "type": "Feature",
  "properties": {
    "gn:admin1_code":"2.0",
    "gn:admin2_code":"0103",
    "gn:admin3_code":"10305.0",
    "gn:asciiname":"Figueira",
    "gn:country_code":"PT",
    "gn:dem":112,
    "gn:feature_class":"P",
    "gn:feature_code":"PPL",
    "gn:name":"Figueira",
    "gn:population":0,
    "gn:timezone":"Europe/Lisbon",
    "iso:country":"PT",
    "wof:name":"Figueira",
    "wof:placetype":"locality"
},
  "geometry": {"coordinates":[-8.38373,40.4884],"type":"Point"}
}