{
  "type": "Feature",
  "properties": {
    "gn:admin1_code":"13",
    "gn:admin2_code":"1015",
    "gn:admin3_code":"101502.0",
    "gn:asciiname":"Castelo da Graciera",
    "gn:country_code":"PT",
    "gn:dem":244,
    "gn:feature_class":"P",
    "gn:feature_code":"PPL",
    "gn:name":"Castelo da Graciera",
    "gn:population":0,
    "gn:timezone":"Europe/Lisbon",
    "iso:country":"PT",
    "wof:name":"Castelo da Graciera",
    "wof:placetype":"locality"
},
  "geometry": {"coordinates":[-8.60492,39.812],"type":"Point"}
}