{
  "type": "Feature",
  "properties": {
    "gn:admin1_code":"7.0",
    "gn:admin2_code":"0614",
    "gn:admin3_code":"61406.0",
    "gn:asciiname":"Chainca",
    "gn:country_code":"PT",
    "gn:dem":287,
    "gn:feature_class":"P",
    "gn:feature_code":"PPL",
    "gn:name":"Chain\u00e7a",
    "gn:population":0,
    "gn:timezone":"Europe/Lisbon",
    "iso:country":"PT",
    "wof:name":"Chainca",
    "wof:placetype":"locality"
},
  "geometry": {"coordinates":[-8.41923,40.04259],"type":"Point"}
}