{
  "type": "Feature",
  "properties": {
    "gn:admin1_code":"20.0",
    "gn:admin2_code":"1604",
    "gn:admin3_code":"160418.0",
    "gn:asciiname":"Moreira",
    "gn:country_code":"PT",
    "gn:dem":89,
    "gn:feature_class":"P",
    "gn:feature_code":"PPL",
    "gn:name":"Moreira",
    "gn:population":0,
    "gn:timezone":"Europe/Lisbon",
    "iso:country":"PT",
    "wof:name":"Moreira",
    "wof:placetype":"locality"
},
  "geometry": {"coordinates":[-8.48749,42.02258],"type":"Point"}
}