{
  "type": "Feature",
  "properties": {
    "gn:admin1_code":"20.0",
    "gn:admin2_code":"1607",
    "gn:admin3_code":"160737.0",
    "gn:asciiname":"Lapa",
    "gn:country_code":"PT",
    "gn:dem":562,
    "gn:feature_class":"P",
    "gn:feature_code":"PPL",
    "gn:name":"Lapa",
    "gn:population":0,
    "gn:timezone":"Europe/Lisbon",
    "iso:country":"PT",
    "wof:name":"Lapa",
    "wof:placetype":"locality"
},
  "geometry": {"coordinates":[-8.52342,41.82086],"type":"Point"}
}