{
  "type": "Feature",
  "properties": {
    "gn:admin1_code":"20.0",
    "gn:admin2_code":"1607",
    "gn:admin3_code":"160737.0",
    "gn:asciiname":"Lapa",
    "gn:country_code":"PT",
    "gn:dem":562,
    "gn:feature_class":"P",
    "gn:feature_code":"PPL",
    "gn:name":"Lapa",
    "gn:population":0,
    "gn:timezone":"Europe/Lisbon",
    "iso:country":"PT",
    "name:ben_x_preferred":[
        "\u09b2\u09be\u09aa\u09be"
    ],
    "name:bpy_x_preferred":[
        "\u09b2\u09be\u09aa\u09be"
    ],
    "name:ceb_x_preferred":[
        "Lapa"
    ],
    "name:deu_x_preferred":[
        "Lapa"
    ],
    "name:ell_x_preferred":[
        "\u039b\u03ac\u03c0\u03b1"
    ],
    "name:eus_x_preferred":[
        "Lapa"
    ],
    "name:fas_x_preferred":[
        "\u0644\u0627\u067e\u0627"
    ],
    "name:fin_x_preferred":[
        "Lapa"
    ],
    "name:fra_x_preferred":[
        "Lapa"
    ],
    "name:glg_x_preferred":[
        "Lapa"
    ],
    "name:heb_x_preferred":[
        "\u05dc\u05d0\u05e4\u05d4"
    ],
    "name:hin_x_preferred":[
        "\u0932\u093e\u092a\u093e"
    ],
    "name:ind_x_preferred":[
        "Lapa"
    ],
    "name:ita_x_preferred":[
        "Lapa"
    ],
    "name:jpn_x_preferred":[
        "\u30e9\u30d1"
    ],
    "name:kor_x_preferred":[
        "\ub77c\ud30c"
    ],
    "name:lav_x_preferred":[
        "Lapa"
    ],
    "name:nld_x_preferred":[
        "Lapa"
    ],
    "name:por_x_preferred":[
        "Lapa"
    ],
    "name:scn_x_preferred":[
        "Lapa"
    ],
    "name:spa_x_preferred":[
        "Lapa"
    ],
    "name:swe_x_preferred":[
        "Lapa"
    ],
    "name:tur_x_preferred":[
        "Lapa"
    ],
    "name:ukr_x_preferred":[
        "\u041b\u0430\u043f\u0430"
    ],
    "name:zho_cn_x_preferred":[
        "\u62c9\u5e15"
    ],
    "name:zho_tw_x_preferred":[
        "\u62c9\u5e15"
    ],
    "wof:name":"Lapa",
    "wof:placetype":"locality"
},
  "geometry": {"coordinates":[-8.52342,41.82086],"type":"Point"}
}