{
  "type": "Feature",
  "properties": {
    "gn:admin1_code":"16",
    "gn:admin2_code":"1214",
    "gn:admin3_code":"121406.0",
    "gn:asciiname":"Vargem",
    "gn:country_code":"PT",
    "gn:dem":436,
    "gn:feature_class":"P",
    "gn:feature_code":"PPL",
    "gn:name":"Vargem",
    "gn:population":0,
    "gn:timezone":"Europe/Lisbon",
    "iso:country":"PT",
    "wof:name":"Vargem",
    "wof:placetype":"locality"
},
  "geometry": {"coordinates":[-7.44506,39.33019],"type":"Point"}
}