{
  "type": "Feature",
  "properties": {
    "gn:admin1_code":"7.0",
    "gn:admin2_code":"0607",
    "gn:admin3_code":"60704.0",
    "gn:asciiname":"Avessada",
    "gn:country_code":"PT",
    "gn:dem":198,
    "gn:feature_class":"P",
    "gn:feature_code":"PPL",
    "gn:name":"Avessada",
    "gn:population":0,
    "gn:timezone":"Europe/Lisbon",
    "iso:country":"PT",
    "wof:name":"Avessada",
    "wof:placetype":"locality"
},
  "geometry": {"coordinates":[-8.1732,40.14083],"type":"Point"}
}