{
  "type": "Feature",
  "properties": {
    "gn:admin1_code":"13",
    "gn:admin2_code":"1016",
    "gn:admin3_code":"101610.0",
    "gn:asciiname":"Vale Florido",
    "gn:country_code":"PT",
    "gn:dem":252,
    "gn:feature_class":"P",
    "gn:feature_code":"PPL",
    "gn:name":"Vale Florido",
    "gn:population":0,
    "gn:timezone":"Europe/Lisbon",
    "iso:country":"PT",
    "wof:name":"Vale Florido",
    "wof:placetype":"locality"
},
  "geometry": {"coordinates":[-8.7647,39.47857],"type":"Point"}
}