{
  "type": "Feature",
  "properties": {
    "gn:admin1_code":"4.0",
    "gn:admin2_code":"0313",
    "gn:admin3_code":"31323.0",
    "gn:asciiname":"Goja",
    "gn:country_code":"PT",
    "gn:dem":64,
    "gn:feature_class":"P",
    "gn:feature_code":"PPL",
    "gn:name":"Goja",
    "gn:population":0,
    "gn:timezone":"Europe/Lisbon",
    "iso:country":"PT",
    "wof:name":"Goja",
    "wof:placetype":"locality"
},
  "geometry": {"coordinates":[-8.48001,41.61973],"type":"Point"}
}