{
  "type": "Feature",
  "properties": {
    "gn:admin1_code":"20.0",
    "gn:admin2_code":"1604",
    "gn:admin3_code":"160424.0",
    "gn:asciiname":"Branda de Santo Antonio",
    "gn:country_code":"PT",
    "gn:dem":1000,
    "gn:feature_class":"P",
    "gn:feature_code":"PPL",
    "gn:name":"Branda de Santo Ant\u00f3nio",
    "gn:population":0,
    "gn:timezone":"Europe/Lisbon",
    "iso:country":"PT",
    "wof:name":"Branda de Santo Antonio",
    "wof:placetype":"locality"
},
  "geometry": {"coordinates":[-8.29466,41.99857],"type":"Point"}
}