{
  "type": "Feature",
  "properties": {
    "gn:admin1_code":"21.0",
    "gn:admin2_code":"1707",
    "gn:admin3_code":"170703.0",
    "gn:asciiname":"Cadaval",
    "gn:country_code":"PT",
    "gn:dem":663,
    "gn:feature_class":"P",
    "gn:feature_code":"PPL",
    "gn:name":"Cadaval",
    "gn:population":0,
    "gn:timezone":"Europe/Lisbon",
    "iso:country":"PT",
    "name:ceb_x_preferred":[
        "Cadaval"
    ],
    "name:por_x_preferred":[
        "Cadaval"
    ],
    "wof:name":"Cadaval",
    "wof:placetype":"locality"
},
  "geometry": {"coordinates":[-7.48337,41.39567],"type":"Point"}
}