{
  "type": "Feature",
  "properties": {
    "gn:admin1_code":"19",
    "gn:admin2_code":"1501",
    "gn:admin3_code":"150103.0",
    "gn:asciiname":"Sesmaria dos Pretos",
    "gn:country_code":"PT",
    "gn:dem":109,
    "gn:feature_class":"P",
    "gn:feature_code":"PPL",
    "gn:name":"Sesmaria dos Pretos",
    "gn:population":0,
    "gn:timezone":"Europe/Lisbon",
    "iso:country":"PT",
    "wof:name":"Sesmaria dos Pretos",
    "wof:placetype":"locality"
},
  "geometry": {"coordinates":[-8.37922,38.39554],"type":"Point"}
}