{
  "type": "Feature",
  "properties": {
    "gn:admin1_code":"14",
    "gn:admin2_code":"1111",
    "gn:admin3_code":"111111.0",
    "gn:asciiname":"Nafarros",
    "gn:country_code":"PT",
    "gn:dem":101,
    "gn:feature_class":"P",
    "gn:feature_code":"PPL",
    "gn:name":"Nafarros",
    "gn:population":0,
    "gn:timezone":"Europe/Lisbon",
    "iso:country":"PT",
    "wof:name":"Nafarros",
    "wof:placetype":"locality"
},
  "geometry": {"coordinates":[-9.42336,38.81521],"type":"Point"}
}