{
  "type": "Feature",
  "properties": {
    "gn:admin1_code":"20",
    "gn:admin2_code":"1601",
    "gn:admin3_code":"160140.0",
    "gn:asciiname":"Senra",
    "gn:country_code":"PT",
    "gn:dem":34,
    "gn:feature_class":"P",
    "gn:feature_code":"PPL",
    "gn:name":"Senra",
    "gn:population":0,
    "gn:timezone":"Europe/Lisbon",
    "iso:country":"PT",
    "name:nld_x_preferred":[
        "Senra"
    ],
    "name:por_x_preferred":[
        "Senra"
    ],
    "name:spa_x_preferred":[
        "Senra"
    ],
    "wof:name":"Senra",
    "wof:placetype":"locality"
},
  "geometry": {"coordinates":[-8.37804,41.81531],"type":"Point"}
}