{
  "type": "Feature",
  "properties": {
    "gn:admin1_code":"09",
    "gn:admin2_code":"0802",
    "gn:admin3_code":"80202.0",
    "gn:asciiname":"Alcaria Alta",
    "gn:country_code":"PT",
    "gn:dem":284,
    "gn:feature_class":"P",
    "gn:feature_code":"PPL",
    "gn:name":"Alcaria Alta",
    "gn:population":0,
    "gn:timezone":"Europe/Lisbon",
    "iso:country":"PT",
    "wof:name":"Alcaria Alta",
    "wof:placetype":"locality"
},
  "geometry": {"coordinates":[-7.68481,37.44046],"type":"Point"}
}