{
  "type": "Feature",
  "properties": {
    "gn:admin1_code":"11.0",
    "gn:admin2_code":"0906",
    "gn:admin3_code":"90607.0",
    "gn:asciiname":"Novelaes",
    "gn:country_code":"PT",
    "gn:dem":503,
    "gn:feature_class":"P",
    "gn:feature_code":"PPL",
    "gn:name":"Novel\u00e3es",
    "gn:population":0,
    "gn:timezone":"Europe/Lisbon",
    "iso:country":"PT",
    "wof:name":"Novelaes",
    "wof:placetype":"locality"
},
  "geometry": {"coordinates":[-7.68499,40.49332],"type":"Point"}
}