{
  "type": "Feature",
  "properties": {
    "gn:admin1_code":"2.0",
    "gn:admin2_code":"0119",
    "gn:admin3_code":"11907.0",
    "gn:asciiname":"Funcao",
    "gn:country_code":"PT",
    "gn:dem":569,
    "gn:feature_class":"P",
    "gn:feature_code":"PPL",
    "gn:name":"Fun\u00e7\u00e3o",
    "gn:population":0,
    "gn:timezone":"Europe/Lisbon",
    "iso:country":"PT",
    "wof:name":"Funcao",
    "wof:placetype":"locality"
},
  "geometry": {"coordinates":[-8.33187,40.85415],"type":"Point"}
}