{
  "type": "Feature",
  "properties": {
    "gn:admin1_code":"2.0",
    "gn:admin2_code":"0114",
    "gn:admin3_code":"11403.0",
    "gn:asciiname":"Aguas Boas",
    "gn:country_code":"PT",
    "gn:dem":53,
    "gn:feature_class":"P",
    "gn:feature_code":"PPL",
    "gn:name":"\u00c1guas Boas",
    "gn:population":0,
    "gn:timezone":"Europe/Lisbon",
    "iso:country":"PT",
    "wof:name":"Aguas Boas",
    "wof:placetype":"locality"
},
  "geometry": {"coordinates":[-8.56299,40.53644],"type":"Point"}
}