{
  "type": "Feature",
  "properties": {
    "gn:admin1_code":"13",
    "gn:admin2_code":"1009",
    "gn:admin3_code":"100915.0",
    "gn:asciiname":"Casal da Quinta",
    "gn:country_code":"PT",
    "gn:dem":152,
    "gn:feature_class":"P",
    "gn:feature_code":"PPL",
    "gn:name":"Casal da Quinta",
    "gn:population":0,
    "gn:timezone":"Europe/Lisbon",
    "iso:country":"PT",
    "wof:name":"Casal da Quinta",
    "wof:placetype":"locality"
},
  "geometry": {"coordinates":[-8.75046,39.81496],"type":"Point"}
}