{
  "type": "Feature",
  "properties": {
    "gn:admin1_code":"03",
    "gn:admin2_code":"0209",
    "gn:admin3_code":"20908.0",
    "gn:asciiname":"Casa Velha",
    "gn:country_code":"PT",
    "gn:dem":252,
    "gn:feature_class":"P",
    "gn:feature_code":"PPL",
    "gn:name":"Casa Velha",
    "gn:population":0,
    "gn:timezone":"Europe/Lisbon",
    "iso:country":"PT",
    "wof:name":"Casa Velha",
    "wof:placetype":"locality"
},
  "geometry": {"coordinates":[-7.8845,37.51979],"type":"Point"}
}