{
  "type": "Feature",
  "properties": {
    "gn:admin1_code":"21",
    "gn:admin2_code":"1706",
    "gn:admin3_code":"170601.0",
    "gn:asciiname":"Xertelo",
    "gn:country_code":"PT",
    "gn:dem":735,
    "gn:feature_class":"P",
    "gn:feature_code":"PPL",
    "gn:name":"Xertelo",
    "gn:population":0,
    "gn:timezone":"Europe/Lisbon",
    "iso:country":"PT",
    "wof:name":"Xertelo",
    "wof:placetype":"locality"
},
  "geometry": {"coordinates":[-8.01137,41.73583],"type":"Point"}
}