{
  "type": "Feature",
  "properties": {
    "iso:country":"PT",
    "name:deu_x_preferred":[
        "Faj\u00e3 de Cima"
    ],
    "name:msa_x_preferred":[
        "Faj\u00e3 de Cima"
    ],
    "name:por_x_colloquial":[
        "Faja de Cima"
    ],
    "name:por_x_preferred":[
        "Faj\u00e3 de Cima"
    ],
    "name:rus_x_preferred":[
        "\u0424\u0430\u0436\u0430\u043d-\u0434\u0438-\u0421\u0438\u043c\u0430"
    ],
    "name:rus_x_variant":[
        "\u0424\u0430\u0436\u0430\u043d-\u0434\u0435-\u0421\u0438\u043c\u0430"
    ],
    "name:spa_x_preferred":[
        "Faj\u00e3 de Cima"
    ],
    "qs:a0":"Portugal",
    "qs:a1":"*Regi\u00e3o Aut\u00f3noma dos A\u00e7ores",
    "qs:a1r":"0",
    "qs:adm0":"Portugal",
    "qs:la_lc":"*",
    "qs:level":"locality",
    "qs:loc":"Faj\u00e3 de Cima",
    "qs:loc_alt":"Faja de Cima",
    "qs:pop":0,
    "qs:type":"buffered point",
    "wd:wordcount":364,
    "wof:lang":[
        "por"
    ],
    "wof:name":"Faj\u00e3 de Cima",
    "wof:placetype":"locality"
},
  "geometry": {"coordinates":[-25.660673,37.771397],"type":"Point"}
}