{
  "type": "Feature",
  "properties": {
    "gn:admin1_code":"22.0",
    "gn:admin2_code":"1818",
    "gn:admin3_code":"181805.0",
    "gn:asciiname":"Escurquela",
    "gn:country_code":"PT",
    "gn:dem":633,
    "gn:feature_class":"P",
    "gn:feature_code":"PPL",
    "gn:name":"Escurquela",
    "gn:population":0,
    "gn:timezone":"Europe/Lisbon",
    "iso:country":"PT",
    "wof:name":"Escurquela",
    "wof:placetype":"locality"
},
  "geometry": {"coordinates":[-7.52134,41.00503],"type":"Point"}
}