{
  "type": "Feature",
  "properties": {
    "gn:admin1_code":"7.0",
    "gn:admin2_code":"0601",
    "gn:admin3_code":"60111.0",
    "gn:asciiname":"Malhada Cha",
    "gn:country_code":"PT",
    "gn:dem":863,
    "gn:feature_class":"P",
    "gn:feature_code":"PPL",
    "gn:name":"Malhada Ch\u00e3",
    "gn:population":0,
    "gn:timezone":"Europe/Lisbon",
    "iso:country":"PT",
    "wof:name":"Malhada Cha",
    "wof:placetype":"locality"
},
  "geometry": {"coordinates":[-7.80622,40.205],"type":"Point"}
}