{
  "type": "Feature",
  "properties": {
    "gn:admin1_code":"20.0",
    "gn:admin2_code":"1607",
    "gn:admin3_code":"160716.0",
    "gn:asciiname":"Anta",
    "gn:country_code":"PT",
    "gn:dem":12,
    "gn:feature_class":"P",
    "gn:feature_code":"PPL",
    "gn:name":"Anta",
    "gn:population":0,
    "gn:timezone":"Europe/Lisbon",
    "iso:country":"PT",
    "name:ceb_x_preferred":[
        "Anta"
    ],
    "name:deu_x_preferred":[
        "Anta"
    ],
    "name:eus_x_preferred":[
        "Anta"
    ],
    "name:fra_x_preferred":[
        "Anta"
    ],
    "name:glg_x_preferred":[
        "Anta"
    ],
    "name:ita_x_preferred":[
        "Anta"
    ],
    "name:nld_x_preferred":[
        "Anta"
    ],
    "name:pol_x_preferred":[
        "Anta"
    ],
    "name:por_x_preferred":[
        "Anta"
    ],
    "name:rus_x_preferred":[
        "\u0410\u043d\u0442\u0430"
    ],
    "name:spa_x_preferred":[
        "Anta"
    ],
    "name:swe_x_preferred":[
        "Anta"
    ],
    "name:ukr_x_preferred":[
        "\u0410\u043d\u0442\u0430"
    ],
    "wof:name":"Anta",
    "wof:placetype":"locality"
},
  "geometry": {"coordinates":[-8.61897,41.74301],"type":"Point"}
}