{
  "type": "Feature",
  "properties": {
    "gn:admin1_code":"20.0",
    "gn:admin2_code":"1607",
    "gn:admin3_code":"160716.0",
    "gn:asciiname":"Anta",
    "gn:country_code":"PT",
    "gn:dem":12,
    "gn:feature_class":"P",
    "gn:feature_code":"PPL",
    "gn:name":"Anta",
    "gn:population":0,
    "gn:timezone":"Europe/Lisbon",
    "iso:country":"PT",
    "wof:name":"Anta",
    "wof:placetype":"locality"
},
  "geometry": {"coordinates":[-8.61897,41.74301],"type":"Point"}
}