{
  "type": "Feature",
  "properties": {
    "gn:admin1_code":"02",
    "gn:admin2_code":"0102",
    "gn:admin3_code":"10206.0",
    "gn:asciiname":"Telhadela",
    "gn:country_code":"PT",
    "gn:dem":142,
    "gn:feature_class":"P",
    "gn:feature_code":"PPL",
    "gn:name":"Telhadela",
    "gn:population":0,
    "gn:timezone":"Europe/Lisbon",
    "iso:country":"PT",
    "wof:name":"Telhadela",
    "wof:placetype":"locality"
},
  "geometry": {"coordinates":[-8.44884,40.76389],"type":"Point"}
}