{
  "type": "Feature",
  "properties": {
    "gn:admin1_code":"5.0",
    "gn:admin2_code":"0405",
    "gn:admin3_code":"40513.0",
    "gn:asciiname":"Bousende",
    "gn:country_code":"PT",
    "gn:dem":1050,
    "gn:feature_class":"P",
    "gn:feature_code":"PPL",
    "gn:name":"Bousende",
    "gn:population":0,
    "gn:timezone":"Europe/Lisbon",
    "iso:country":"PT",
    "wof:name":"Bousende",
    "wof:placetype":"locality"
},
  "geometry": {"coordinates":[-6.91871,41.65263],"type":"Point"}
}