{
  "type": "Feature",
  "properties": {
    "gn:admin1_code":"02",
    "gn:admin2_code":"0109",
    "gn:admin3_code":"10923.0",
    "gn:asciiname":"Sanfins",
    "gn:country_code":"PT",
    "gn:dem":167,
    "gn:feature_class":"P",
    "gn:feature_code":"PPL",
    "gn:name":"Sanfins",
    "gn:population":1970,
    "gn:timezone":"Europe/Lisbon",
    "iso:country":"PT",
    "name:deu_x_preferred":[
        "Sanfins"
    ],
    "name:kaz_x_preferred":[
        "\u0421\u0430\u043d\u0444\u0438\u043d\u0448"
    ],
    "name:nld_x_preferred":[
        "Sanfins"
    ],
    "name:por_x_preferred":[
        "Sanfins"
    ],
    "name:rus_x_preferred":[
        "\u0421\u0430\u043d\u0444\u0438\u043d\u0448"
    ],
    "name:spa_x_preferred":[
        "Sanfins"
    ],
    "name:tur_x_preferred":[
        "Sanfins"
    ],
    "name:ukr_x_preferred":[
        "\u0421\u0430\u043d\u0444\u0456\u043d\u0448"
    ],
    "name:zho_x_preferred":[
        "\u6851\u82ac\u4ec0"
    ],
    "wof:name":"Sanfins",
    "wof:placetype":"locality",
    "wof:population":1970
},
  "geometry": {"coordinates":[-8.52563,40.92979],"type":"Point"}
}