{
  "type": "Feature",
  "properties": {
    "gn:admin1_code":"21.0",
    "gn:admin2_code":"1707",
    "gn:admin3_code":"170703.0",
    "gn:asciiname":"Fiolhoso",
    "gn:country_code":"PT",
    "gn:dem":732,
    "gn:feature_class":"P",
    "gn:feature_code":"PPL",
    "gn:name":"Fiolhoso",
    "gn:population":0,
    "gn:timezone":"Europe/Lisbon",
    "iso:country":"PT",
    "wof:name":"Fiolhoso",
    "wof:placetype":"locality"
},
  "geometry": {"coordinates":[-7.50429,41.40949000000001],"type":"Point"}
}