{
  "type": "Feature",
  "properties": {
    "gn:admin1_code":"13",
    "gn:admin2_code":"1016",
    "gn:admin3_code":"101610.0",
    "gn:asciiname":"Moliana",
    "gn:country_code":"PT",
    "gn:dem":452,
    "gn:feature_class":"P",
    "gn:feature_code":"PPL",
    "gn:name":"Moliana",
    "gn:population":0,
    "gn:timezone":"Europe/Lisbon",
    "iso:country":"PT",
    "wof:name":"Moliana",
    "wof:placetype":"locality"
},
  "geometry": {"coordinates":[-8.77788,39.50349],"type":"Point"}
}