{
  "type": "Feature",
  "properties": {
    "gn:admin1_code":"23.0",
    "gn:admin2_code":"4203",
    "gn:admin3_code":"420317.0",
    "gn:asciiname":"Gloria",
    "gn:country_code":"PT",
    "gn:dem":1,
    "gn:feature_class":"P",
    "gn:feature_code":"PPL",
    "gn:name":"Gl\u00f3ria",
    "gn:population":0,
    "gn:timezone":"Atlantic/Azores",
    "iso:country":"PT",
    "wof:name":"Gloria",
    "wof:placetype":"locality"
},
  "geometry": {"coordinates":[-25.61402,37.75124],"type":"Point"}
}