{
  "type": "Feature",
  "properties": {
    "gn:admin1_code":"08",
    "gn:admin2_code":"0706",
    "gn:admin3_code":"70608.0",
    "gn:asciiname":"Sesmaria da Ameira",
    "gn:country_code":"PT",
    "gn:dem":84,
    "gn:feature_class":"P",
    "gn:feature_code":"PPL",
    "gn:name":"Sesmaria da Ameira",
    "gn:population":0,
    "gn:timezone":"Europe/Lisbon",
    "iso:country":"PT",
    "wof:name":"Sesmaria da Ameira",
    "wof:placetype":"locality"
},
  "geometry": {"coordinates":[-8.42918,38.72558],"type":"Point"}
}