{
  "type": "Feature",
  "properties": {
    "gn:admin1_code":"14",
    "gn:admin2_code":"1109",
    "gn:admin3_code":"110905.0",
    "gn:asciiname":"Sao Sebastiao",
    "gn:country_code":"PT",
    "gn:dem":134,
    "gn:feature_class":"P",
    "gn:feature_code":"PPL",
    "gn:name":"S\u00e3o Sebasti\u00e3o",
    "gn:population":0,
    "gn:timezone":"Europe/Lisbon",
    "iso:country":"PT",
    "wof:name":"Sao Sebastiao",
    "wof:placetype":"locality"
},
  "geometry": {"coordinates":[-9.22783,39.00578],"type":"Point"}
}