{
  "type": "Feature",
  "properties": {
    "gn:admin1_code":"2.0",
    "gn:admin2_code":"0101",
    "gn:admin3_code":"10101.0",
    "gn:asciiname":"Bertufo",
    "gn:country_code":"PT",
    "gn:dem":227,
    "gn:feature_class":"P",
    "gn:feature_code":"PPL",
    "gn:name":"Bertufo",
    "gn:population":0,
    "gn:timezone":"Europe/Lisbon",
    "iso:country":"PT",
    "wof:name":"Bertufo",
    "wof:placetype":"locality"
},
  "geometry": {"coordinates":[-8.3093,40.57974],"type":"Point"}
}