{
  "type": "Feature",
  "properties": {
    "gn:admin1_code":"21",
    "gn:admin2_code":"1706",
    "gn:admin3_code":"170618.0",
    "gn:asciiname":"Vilarinho de Negroes",
    "gn:country_code":"PT",
    "gn:dem":874,
    "gn:feature_class":"P",
    "gn:feature_code":"PPL",
    "gn:name":"Vilarinho de Negr\u00f5es",
    "gn:population":0,
    "gn:timezone":"Europe/Lisbon",
    "iso:country":"PT",
    "wof:name":"Vilarinho de Negroes",
    "wof:placetype":"locality"
},
  "geometry": {"coordinates":[-7.80171,41.73759],"type":"Point"}
}