{
  "type": "Feature",
  "properties": {
    "gn:admin1_code":"7.0",
    "gn:admin2_code":"0610",
    "gn:admin3_code":"61006.0",
    "gn:asciiname":"Meas do Campo",
    "gn:country_code":"PT",
    "gn:dem":36,
    "gn:feature_class":"P",
    "gn:feature_code":"PPL",
    "gn:name":"Me\u00e3s do Campo",
    "gn:population":0,
    "gn:timezone":"Europe/Lisbon",
    "iso:country":"PT",
    "wof:name":"Meas do Campo",
    "wof:placetype":"locality"
},
  "geometry": {"coordinates":[-8.63147,40.21294],"type":"Point"}
}