{
  "type": "Feature",
  "properties": {
    "gn:admin1_code":"7.0",
    "gn:admin2_code":"0611",
    "gn:admin3_code":"61118.0",
    "gn:asciiname":"Felgueira",
    "gn:country_code":"PT",
    "gn:dem":184,
    "gn:feature_class":"P",
    "gn:feature_code":"PPL",
    "gn:name":"Felgueira",
    "gn:population":0,
    "gn:timezone":"Europe/Lisbon",
    "iso:country":"PT",
    "wof:name":"Felgueira",
    "wof:placetype":"locality"
},
  "geometry": {"coordinates":[-7.84477,40.49184],"type":"Point"}
}