{
  "type": "Feature",
  "properties": {
    "gn:admin1_code":"20",
    "gn:admin2_code":"1606",
    "gn:admin3_code":"160605.0",
    "gn:asciiname":"Porto Bom",
    "gn:country_code":"PT",
    "gn:dem":531,
    "gn:feature_class":"P",
    "gn:feature_code":"PPL",
    "gn:name":"Porto Bom",
    "gn:population":0,
    "gn:timezone":"Europe/Lisbon",
    "iso:country":"PT",
    "wof:name":"Porto Bom",
    "wof:placetype":"locality"
},
  "geometry": {"coordinates":[-8.46871,41.74515],"type":"Point"}
}