{
  "type": "Feature",
  "properties": {
    "gn:admin1_code":"03",
    "gn:admin2_code":"0211",
    "gn:admin3_code":"21102.0",
    "gn:asciiname":"Reliquias",
    "gn:country_code":"PT",
    "gn:dem":243,
    "gn:feature_class":"P",
    "gn:feature_code":"PPL",
    "gn:name":"Rel\u00edquias",
    "gn:population":0,
    "gn:timezone":"Europe/Lisbon",
    "iso:country":"PT",
    "name:ceb_x_preferred":[
        "Rel\u00edquias"
    ],
    "name:deu_x_preferred":[
        "Rel\u00edquias"
    ],
    "name:kaz_x_preferred":[
        "\u0420\u0435\u043b\u0438\u043a\u044c\u044f\u0448"
    ],
    "name:nld_x_preferred":[
        "Rel\u00edquias"
    ],
    "name:por_x_preferred":[
        "Rel\u00edquias"
    ],
    "name:rus_x_preferred":[
        "\u0420\u0435\u043b\u0438\u043a\u0438\u0430\u0448"
    ],
    "name:spa_x_preferred":[
        "Rel\u00edquias"
    ],
    "name:ukr_x_preferred":[
        "\u0420\u0435\u043b\u0456\u043a\u0456\u0430\u0448"
    ],
    "name:und_x_variant":[
        "Rel\u00edquias"
    ],
    "name:zho_x_preferred":[
        "\u96f7\u5229\u57fa\u4e9a\u4ec0"
    ],
    "wof:name":"Reliquias",
    "wof:placetype":"locality"
},
  "geometry": {"coordinates":[-8.48509,37.70126],"type":"Point"}
}