{
  "type": "Feature",
  "properties": {
    "gn:admin1_code":"04",
    "gn:admin2_code":"0302",
    "gn:admin3_code":"30282.0",
    "gn:asciiname":"Ucha",
    "gn:country_code":"PT",
    "gn:dem":58,
    "gn:feature_class":"P",
    "gn:feature_code":"PPL",
    "gn:name":"Ucha",
    "gn:population":0,
    "gn:timezone":"Europe/Lisbon",
    "iso:country":"PT",
    "wof:name":"Ucha",
    "wof:placetype":"locality"
},
  "geometry": {"coordinates":[-8.51955,41.5785],"type":"Point"}
}