{
  "type": "Feature",
  "properties": {
    "gn:admin1_code":"11",
    "gn:admin2_code":"0914",
    "gn:admin3_code":"91416.0",
    "gn:asciiname":"Quinta das Alminhas",
    "gn:country_code":"PT",
    "gn:dem":624,
    "gn:feature_class":"P",
    "gn:feature_code":"PPL",
    "gn:name":"Quinta das Alminhas",
    "gn:population":0,
    "gn:timezone":"Europe/Lisbon",
    "iso:country":"PT",
    "wof:name":"Quinta das Alminhas",
    "wof:placetype":"locality"
},
  "geometry": {"coordinates":[-7.23674,41.04297],"type":"Point"}
}