{
  "type": "Feature",
  "properties": {
    "gn:admin1_code":"7.0",
    "gn:admin2_code":"0615",
    "gn:admin3_code":"61509.0",
    "gn:asciiname":"Portela",
    "gn:country_code":"PT",
    "gn:dem":51,
    "gn:feature_class":"P",
    "gn:feature_code":"PPL",
    "gn:name":"Portela",
    "gn:population":0,
    "gn:timezone":"Europe/Lisbon",
    "iso:country":"PT",
    "name:ceb_x_preferred":[
        "Portela"
    ],
    "name:deu_x_preferred":[
        "Portela"
    ],
    "name:fra_x_preferred":[
        "Portela"
    ],
    "name:glg_x_preferred":[
        "Portela"
    ],
    "name:kaz_x_preferred":[
        "\u041f\u043e\u0440\u0442\u0435\u043b\u0430"
    ],
    "name:nld_x_preferred":[
        "Portela"
    ],
    "name:por_x_preferred":[
        "Portela"
    ],
    "name:rus_x_preferred":[
        "\u041f\u043e\u0440\u0442\u0435\u043b\u0430"
    ],
    "name:spa_x_preferred":[
        "Portela"
    ],
    "name:srp_x_preferred":[
        "Portela"
    ],
    "name:ukr_x_preferred":[
        "\u041f\u043e\u0440\u0442\u0435\u043b\u0430"
    ],
    "wof:name":"Portela",
    "wof:placetype":"locality"
},
  "geometry": {"coordinates":[-8.59978,40.07769],"type":"Point"}
}