{
  "type": "Feature",
  "properties": {
    "gn:admin1_code":"05",
    "gn:admin2_code":"0402",
    "gn:admin3_code":"40240.0",
    "gn:asciiname":"Sao Lourenco",
    "gn:country_code":"PT",
    "gn:dem":740,
    "gn:feature_class":"P",
    "gn:feature_code":"PPL",
    "gn:name":"S\u00e3o Louren\u00e7o",
    "gn:population":0,
    "gn:timezone":"Europe/Lisbon",
    "iso:country":"PT",
    "wof:name":"Sao Lourenco",
    "wof:placetype":"locality"
},
  "geometry": {"coordinates":[-6.7823,41.77771],"type":"Point"}
}