{
  "type": "Feature",
  "properties": {
    "gn:admin1_code":"14",
    "gn:admin2_code":"1101",
    "gn:admin3_code":"110109.0",
    "gn:asciiname":"Pacos",
    "gn:country_code":"PT",
    "gn:dem":28,
    "gn:feature_class":"P",
    "gn:feature_code":"PPL",
    "gn:name":"Pa\u00e7os",
    "gn:population":0,
    "gn:timezone":"Europe/Lisbon",
    "iso:country":"PT",
    "wof:name":"Pacos",
    "wof:placetype":"locality"
},
  "geometry": {"coordinates":[-8.98183,39.10869],"type":"Point"}
}