{
  "type": "Feature",
  "properties": {
    "gn:admin1_code":"10",
    "gn:admin2_code":"3201",
    "gn:admin3_code":"320101.0",
    "gn:asciiname":"Areias",
    "gn:country_code":"PT",
    "gn:dem":101,
    "gn:feature_class":"P",
    "gn:feature_code":"PPL",
    "gn:name":"Areias",
    "gn:population":0,
    "gn:timezone":"Atlantic/Madeira",
    "iso:country":"PT",
    "name:bpy_x_preferred":[
        "\u0986\u09b0\u09c7\u0987\u09af\u09bc\u09be\u09b8"
    ],
    "name:ceb_x_preferred":[
        "Areias"
    ],
    "name:deu_x_preferred":[
        "Areias"
    ],
    "name:fra_x_preferred":[
        "Areias"
    ],
    "name:kaz_x_preferred":[
        "\u0410\u0440\u0435\u044f\u0448"
    ],
    "name:nld_x_preferred":[
        "Areias"
    ],
    "name:pol_x_preferred":[
        "Areias"
    ],
    "name:por_x_preferred":[
        "Areias"
    ],
    "name:rus_x_preferred":[
        "\u0410\u0440\u0435\u044f\u0448"
    ],
    "name:spa_x_preferred":[
        "Areias"
    ],
    "name:swe_x_preferred":[
        "Areias"
    ],
    "name:ukr_x_preferred":[
        "\u0410\u0440\u0435\u0439\u044f\u0448"
    ],
    "name:vie_x_preferred":[
        "Areias"
    ],
    "wof:name":"Areias",
    "wof:placetype":"locality"
},
  "geometry": {"coordinates":[-16.35,33.08333],"type":"Point"}
}