{
  "type": "Feature",
  "properties": {
    "gn:admin1_code":"20.0",
    "gn:admin2_code":"1606",
    "gn:admin3_code":"160614.0",
    "gn:asciiname":"Fundo de Oleiros",
    "gn:country_code":"PT",
    "gn:dem":96,
    "gn:feature_class":"P",
    "gn:feature_code":"PPL",
    "gn:name":"Fundo de Oleiros",
    "gn:population":0,
    "gn:timezone":"Europe/Lisbon",
    "iso:country":"PT",
    "wof:name":"Fundo de Oleiros",
    "wof:placetype":"locality"
},
  "geometry": {"coordinates":[-8.43551,41.79933],"type":"Point"}
}