{
  "type": "Feature",
  "properties": {
    "gn:admin1_code":"14",
    "gn:admin2_code":"1109",
    "gn:admin3_code":"110909.0",
    "gn:asciiname":"Grossinhos",
    "gn:country_code":"PT",
    "gn:dem":185,
    "gn:feature_class":"P",
    "gn:feature_code":"PPL",
    "gn:name":"Grossinhos",
    "gn:population":0,
    "gn:timezone":"Europe/Lisbon",
    "iso:country":"PT",
    "wof:name":"Grossinhos",
    "wof:placetype":"locality"
},
  "geometry": {"coordinates":[-9.35123,38.94022],"type":"Point"}
}