{
  "type": "Feature",
  "properties": {
    "gn:admin1_code":"13",
    "gn:admin2_code":"1001",
    "gn:admin3_code":"100118.0",
    "gn:asciiname":"Martinganca",
    "gn:country_code":"PT",
    "gn:dem":156,
    "gn:feature_class":"P",
    "gn:feature_code":"PPL",
    "gn:name":"Martingan\u00e7a",
    "gn:population":0,
    "gn:timezone":"Europe/Lisbon",
    "iso:country":"PT",
    "wof:name":"Martinganca",
    "wof:placetype":"locality"
},
  "geometry": {"coordinates":[-8.95,39.68333],"type":"Point"}
}