{
  "type": "Feature",
  "properties": {
    "gn:admin1_code":"20.0",
    "gn:admin2_code":"1601",
    "gn:admin3_code":"160115.0",
    "gn:asciiname":"Mundao",
    "gn:country_code":"PT",
    "gn:dem":177,
    "gn:feature_class":"P",
    "gn:feature_code":"PPL",
    "gn:name":"Mund\u00e3o",
    "gn:population":0,
    "gn:timezone":"Europe/Lisbon",
    "iso:country":"PT",
    "wof:name":"Mundao",
    "wof:placetype":"locality"
},
  "geometry": {"coordinates":[-8.40944,41.88836],"type":"Point"}
}