{
  "type": "Feature",
  "properties": {
    "gn:admin1_code":"4.0",
    "gn:admin2_code":"0307",
    "gn:admin3_code":"30718.0",
    "gn:asciiname":"Marinhao",
    "gn:country_code":"PT",
    "gn:dem":424,
    "gn:feature_class":"P",
    "gn:feature_code":"PPL",
    "gn:name":"Marinh\u00e3o",
    "gn:population":0,
    "gn:timezone":"Europe/Lisbon",
    "iso:country":"PT",
    "wof:name":"Marinhao",
    "wof:placetype":"locality"
},
  "geometry": {"coordinates":[-8.12662,41.46579000000001],"type":"Point"}
}