{
  "type": "Feature",
  "properties": {
    "gn:admin1_code":"11",
    "gn:admin2_code":"0912",
    "gn:admin3_code":"91213.0",
    "gn:asciiname":"Vila Cha de Cima",
    "gn:country_code":"PT",
    "gn:dem":450,
    "gn:feature_class":"P",
    "gn:feature_code":"PPL",
    "gn:name":"Vila Ch\u00e3 de Cima",
    "gn:population":0,
    "gn:timezone":"Europe/Lisbon",
    "iso:country":"PT",
    "wof:name":"Vila Cha de Cima",
    "wof:placetype":"locality"
},
  "geometry": {"coordinates":[-7.73333,40.45],"type":"Point"}
}