{
  "type": "Feature",
  "properties": {
    "gn:admin1_code":"04",
    "gn:admin2_code":"0303",
    "gn:admin3_code":"30324.0",
    "gn:asciiname":"Soito Chao",
    "gn:country_code":"PT",
    "gn:dem":142,
    "gn:feature_class":"P",
    "gn:feature_code":"PPL",
    "gn:name":"Soito Ch\u00e3o",
    "gn:population":0,
    "gn:timezone":"Europe/Lisbon",
    "iso:country":"PT",
    "wof:name":"Soito Chao",
    "wof:placetype":"locality"
},
  "geometry": {"coordinates":[-8.43816,41.54665],"type":"Point"}
}