{
  "type": "Feature",
  "properties": {
    "gn:admin1_code":"20.0",
    "gn:admin2_code":"1604",
    "gn:admin3_code":"160419.0",
    "gn:asciiname":"Parada",
    "gn:country_code":"PT",
    "gn:dem":229,
    "gn:feature_class":"P",
    "gn:feature_code":"PPL",
    "gn:name":"Parada",
    "gn:population":0,
    "gn:timezone":"Europe/Lisbon",
    "iso:country":"PT",
    "wof:name":"Parada",
    "wof:placetype":"locality"
},
  "geometry": {"coordinates":[-8.46509,42.0204],"type":"Point"}
}