{
  "type": "Feature",
  "properties": {
    "gn:admin1_code":"18",
    "gn:admin2_code":"1419",
    "gn:admin3_code":"141902.0",
    "gn:asciiname":"Casais de Igreja",
    "gn:country_code":"PT",
    "gn:dem":134,
    "gn:feature_class":"P",
    "gn:feature_code":"PPL",
    "gn:name":"Casais de Igreja",
    "gn:population":0,
    "gn:timezone":"Europe/Lisbon",
    "iso:country":"PT",
    "wof:name":"Casais de Igreja",
    "wof:placetype":"locality"
},
  "geometry": {"coordinates":[-8.52439,39.58747],"type":"Point"}
}