{
  "type": "Feature",
  "properties": {
    "gn:admin1_code":"11.0",
    "gn:admin2_code":"0912",
    "gn:admin3_code":"91222.0",
    "gn:asciiname":"Catraia",
    "gn:country_code":"PT",
    "gn:dem":562,
    "gn:feature_class":"P",
    "gn:feature_code":"PPL",
    "gn:name":"Catraia",
    "gn:population":0,
    "gn:timezone":"Europe/Lisbon",
    "iso:country":"PT",
    "wof:name":"Catraia",
    "wof:placetype":"locality"
},
  "geometry": {"coordinates":[-7.76104,40.38606],"type":"Point"}
}