{
  "type": "Feature",
  "properties": {
    "gn:admin1_code":"5.0",
    "gn:admin2_code":"0402",
    "gn:admin3_code":"40228.0",
    "gn:asciiname":"Paradinha Nova",
    "gn:country_code":"PT",
    "gn:dem":623,
    "gn:feature_class":"P",
    "gn:feature_code":"PPL",
    "gn:name":"Paradinha Nova",
    "gn:population":0,
    "gn:timezone":"Europe/Lisbon",
    "iso:country":"PT",
    "wof:name":"Paradinha Nova",
    "wof:placetype":"locality"
},
  "geometry": {"coordinates":[-6.66514,41.61393],"type":"Point"}
}