{
  "type": "Feature",
  "properties": {
    "gn:admin1_code":"5.0",
    "gn:admin2_code":"0402",
    "gn:admin3_code":"40228.0",
    "gn:asciiname":"Paradinha Nova",
    "gn:country_code":"PT",
    "gn:dem":623,
    "gn:feature_class":"P",
    "gn:feature_code":"PPL",
    "gn:name":"Paradinha Nova",
    "gn:population":0,
    "gn:timezone":"Europe/Lisbon",
    "iso:country":"PT",
    "name:deu_x_preferred":[
        "Paradinha Nova"
    ],
    "name:fra_x_preferred":[
        "Paradinha Nova"
    ],
    "name:kaz_x_preferred":[
        "\u041f\u0430\u0440\u0430\u0434\u0438\u043d\u044c\u044f-\u041d\u043e\u0432\u0430"
    ],
    "name:nld_x_preferred":[
        "Paradinha Nova"
    ],
    "name:por_x_preferred":[
        "Paradinha Nova"
    ],
    "name:rus_x_preferred":[
        "\u041f\u0430\u0440\u0430\u0434\u0438\u043d\u044c\u044f-\u041d\u043e\u0432\u0430"
    ],
    "name:spa_x_preferred":[
        "Paradinha Nova"
    ],
    "name:zho_x_preferred":[
        "\u65b0\u5e15\u62c9\u8fea\u5c3c\u4e9a"
    ],
    "wof:name":"Paradinha Nova",
    "wof:placetype":"locality"
},
  "geometry": {"coordinates":[-6.66514,41.61393],"type":"Point"}
}