{
  "type": "Feature",
  "properties": {
    "iso:country":"PT",
    "name:por_x_colloquial":[
        "Seixo"
    ],
    "name:por_x_preferred":[
        "Seixo"
    ],
    "name:unk_x_variant":[
        "Seixo"
    ],
    "qs:gn_adm0_cc":"PT",
    "qs:gn_fcode":"PPL",
    "qs:gn_local":8010584,
    "qs:gn_nam_loc":"Matosinhos, Porto, PT",
    "qs:gn_namadm1":"17",
    "qs:gn_name":"Seixo",
    "qs:local_max":3813,
    "qs:local_sum":4288,
    "qs:localhoods":3,
    "qs:name":"Seixo",
    "qs:name_adm0":"Portugal",
    "qs:name_adm1":"Porto",
    "qs:name_adm2":"Matosinhos",
    "qs:name_local":"Matosinhos",
    "qs:photo_max":23,
    "qs:photo_sum":58,
    "qs:placetype":"Suburb",
    "qs:quad_count":11,
    "qs:woe_adm0":23424925,
    "qs:woe_adm1":2346575,
    "qs:woe_adm2":12596524,
    "qs:woe_lau":0,
    "qs:woe_local":12596524,
    "qs:woe_ver":"7.10.0",
    "wof:lang":[
        "por"
    ],
    "wof:name":"Seixo",
    "wof:placetype":"neighbourhood"
},
  "geometry": {"coordinates":[-8.626541,41.204454],"type":"Point"}
}