{
  "type": "Feature",
  "properties": {
    "gn:admin1_code":"16",
    "gn:admin2_code":"1215",
    "gn:admin3_code":"121504.0",
    "gn:asciiname":"Monte da Cegarrega",
    "gn:country_code":"PT",
    "gn:dem":221,
    "gn:feature_class":"P",
    "gn:feature_code":"PPL",
    "gn:name":"Monte da Cegarrega",
    "gn:population":0,
    "gn:timezone":"Europe/Lisbon",
    "iso:country":"PT",
    "wof:name":"Monte da Cegarrega",
    "wof:placetype":"locality"
},
  "geometry": {"coordinates":[-7.67202,38.99157],"type":"Point"}
}