{
  "type": "Feature",
  "properties": {
    "gn:admin1_code":"22.0",
    "gn:admin2_code":"1824",
    "gn:admin3_code":"182404.0",
    "gn:asciiname":"Carvalhal de Vermilhas",
    "gn:country_code":"PT",
    "gn:dem":744,
    "gn:feature_class":"P",
    "gn:feature_code":"PPL",
    "gn:name":"Carvalhal de Vermilhas",
    "gn:population":0,
    "gn:timezone":"Europe/Lisbon",
    "iso:country":"PT",
    "wof:name":"Carvalhal de Vermilhas",
    "wof:placetype":"locality"
},
  "geometry": {"coordinates":[-8.15447,40.65488],"type":"Point"}
}