{
  "type": "Feature",
  "properties": {
    "gn:admin1_code":"06",
    "gn:admin2_code":"0506",
    "gn:admin3_code":"50608.0",
    "gn:asciiname":"Vale das Ovelhas",
    "gn:country_code":"PT",
    "gn:dem":624,
    "gn:feature_class":"P",
    "gn:feature_code":"PPL",
    "gn:name":"Vale das Ovelhas",
    "gn:population":0,
    "gn:timezone":"Europe/Lisbon",
    "iso:country":"PT",
    "wof:name":"Vale das Ovelhas",
    "wof:placetype":"locality"
},
  "geometry": {"coordinates":[-7.87343,39.96908],"type":"Point"}
}