{
  "type": "Feature",
  "properties": {
    "gn:admin1_code":"4.0",
    "gn:admin2_code":"0311",
    "gn:admin3_code":"31121.0",
    "gn:asciiname":"Laje",
    "gn:country_code":"PT",
    "gn:dem":591,
    "gn:feature_class":"P",
    "gn:feature_code":"PPL",
    "gn:name":"Laje",
    "gn:population":0,
    "gn:timezone":"Europe/Lisbon",
    "iso:country":"PT",
    "name:bpy_x_preferred":[
        "\u09b2\u09be\u099c\u09c7"
    ],
    "name:epo_x_preferred":[
        "Laje"
    ],
    "name:eus_x_preferred":[
        "Laje"
    ],
    "name:fra_x_preferred":[
        "Laje"
    ],
    "name:hye_x_preferred":[
        "\u053c\u0561\u056a\u056b"
    ],
    "name:ita_x_preferred":[
        "Laje"
    ],
    "name:kat_x_preferred":[
        "\u10da\u10d0\u10df\u10d8"
    ],
    "name:kaz_x_preferred":[
        "\u041b\u0430\u0436\u0438"
    ],
    "name:mlg_x_preferred":[
        "Laje"
    ],
    "name:nld_x_preferred":[
        "Laje"
    ],
    "name:nor_x_preferred":[
        "Laje"
    ],
    "name:pol_x_preferred":[
        "Laje"
    ],
    "name:por_x_preferred":[
        "Laje"
    ],
    "name:ron_x_preferred":[
        "Laje"
    ],
    "name:rus_x_preferred":[
        "\u041b\u0430\u0436\u0438"
    ],
    "name:urd_x_preferred":[
        "\u0644\u0627\u062e\u06cc"
    ],
    "name:vie_x_preferred":[
        "Laje"
    ],
    "name:vol_x_preferred":[
        "Laje"
    ],
    "name:war_x_preferred":[
        "Laje"
    ],
    "wof:name":"Laje",
    "wof:placetype":"locality"
},
  "geometry": {"coordinates":[-8.09191,41.6155],"type":"Point"}
}