{
  "type": "Feature",
  "properties": {
    "gn:admin1_code":"18",
    "gn:admin2_code":"1414",
    "gn:admin3_code":"141411.0",
    "gn:asciiname":"Dourada",
    "gn:country_code":"PT",
    "gn:dem":124,
    "gn:feature_class":"P",
    "gn:feature_code":"PPL",
    "gn:name":"Dourada",
    "gn:population":0,
    "gn:timezone":"Europe/Lisbon",
    "iso:country":"PT",
    "wof:name":"Dourada",
    "wof:placetype":"locality"
},
  "geometry": {"coordinates":[-8.89672,39.36435],"type":"Point"}
}