{
  "type": "Feature",
  "properties": {
    "gn:admin1_code":"22.0",
    "gn:admin2_code":"1823",
    "gn:admin3_code":"182319.0",
    "gn:asciiname":"Orgens",
    "gn:country_code":"PT",
    "gn:dem":478,
    "gn:feature_class":"P",
    "gn:feature_code":"PPL",
    "gn:name":"Orgens",
    "gn:population":0,
    "gn:timezone":"Europe/Lisbon",
    "iso:country":"PT",
    "wof:name":"Orgens",
    "wof:placetype":"locality"
},
  "geometry": {"coordinates":[-7.93633,40.66644],"type":"Point"}
}