{
  "type": "Feature",
  "properties": {
    "gn:admin1_code":"09",
    "gn:admin2_code":"0802",
    "gn:admin3_code":"80204.0",
    "gn:asciiname":"Soudes",
    "gn:country_code":"PT",
    "gn:dem":206,
    "gn:feature_class":"P",
    "gn:feature_code":"PPL",
    "gn:name":"Soudes",
    "gn:population":0,
    "gn:timezone":"Europe/Lisbon",
    "iso:country":"PT",
    "wof:name":"Soudes",
    "wof:placetype":"locality"
},
  "geometry": {"coordinates":[-7.61817,37.38607],"type":"Point"}
}