{
  "type": "Feature",
  "properties": {
    "gn:admin1_code":"20.0",
    "gn:admin2_code":"1607",
    "gn:admin3_code":"160751.0",
    "gn:asciiname":"Grajal",
    "gn:country_code":"PT",
    "gn:dem":192,
    "gn:feature_class":"P",
    "gn:feature_code":"PPL",
    "gn:name":"Grajal",
    "gn:population":0,
    "gn:timezone":"Europe/Lisbon",
    "iso:country":"PT",
    "wof:name":"Grajal",
    "wof:placetype":"locality"
},
  "geometry": {"coordinates":[-8.62824,41.68068],"type":"Point"}
}