{
  "type": "Feature",
  "properties": {
    "gn:admin1_code":"20.0",
    "gn:admin2_code":"1601",
    "gn:admin3_code":"160102.0",
    "gn:asciiname":"Bouca Soeiro",
    "gn:country_code":"PT",
    "gn:dem":163,
    "gn:feature_class":"P",
    "gn:feature_code":"PPL",
    "gn:name":"Bou\u00e7a Soeiro",
    "gn:population":0,
    "gn:timezone":"Europe/Lisbon",
    "iso:country":"PT",
    "wof:name":"Bouca Soeiro",
    "wof:placetype":"locality"
},
  "geometry": {"coordinates":[-8.44228,41.88107],"type":"Point"}
}