{
  "type": "Feature",
  "properties": {
    "gn:admin1_code":"17.0",
    "gn:admin2_code":"1308",
    "gn:admin3_code":"130801.0",
    "gn:asciiname":"Gondivinho",
    "gn:country_code":"PT",
    "gn:dem":54,
    "gn:feature_class":"P",
    "gn:feature_code":"PPL",
    "gn:name":"Gondivinho",
    "gn:population":0,
    "gn:timezone":"Europe/Lisbon",
    "iso:country":"PT",
    "wof:name":"Gondivinho",
    "wof:placetype":"locality"
},
  "geometry": {"coordinates":[-8.64424,41.21387],"type":"Point"}
}