{
  "type": "Feature",
  "properties": {
    "gn:country":"PT",
    "gn:fcode":"PPL",
    "gn:population":0,
    "iso:country":"PT",
    "name:ast_x_preferred":[
        "Rogil"
    ],
    "name:bul_x_preferred":[
        "\u0420\u043e\u0433\u0438\u043b"
    ],
    "name:ceb_x_preferred":[
        "Rogil"
    ],
    "name:deu_x_preferred":[
        "Rogil"
    ],
    "name:eng_x_preferred":[
        "Rogil"
    ],
    "name:fra_x_preferred":[
        "Rogil"
    ],
    "name:kaz_x_preferred":[
        "\u0420\u043e\u0436\u0438\u043b"
    ],
    "name:nan_x_preferred":[
        "Rogil"
    ],
    "name:nld_x_preferred":[
        "Rogil"
    ],
    "name:por_x_preferred":[
        "Rogil"
    ],
    "name:rus_x_preferred":[
        "\u0420\u043e\u0436\u0438\u043b"
    ],
    "name:spa_x_preferred":[
        "Rogil"
    ],
    "qs_pg:aaroncc":"PT",
    "qs_pg:gn_country":"PT",
    "qs_pg:gn_fcode":"PPL",
    "qs_pg:gn_pop":0,
    "qs_pg:name":"Rogil",
    "qs_pg:name_adm0":"Portugal",
    "qs_pg:name_adm1":"Faro",
    "qs_pg:photos":47,
    "qs_pg:photos_1k":10,
    "qs_pg:photos_9k":1,
    "qs_pg:photos_9r":2,
    "qs_pg:photos_all":47,
    "qs_pg:photos_sr":2,
    "qs_pg:pop_sr":0,
    "qs_pg:qs_pg_placetype":"locality",
    "qs_pg:qs_pg_placetype_gp":"Town",
    "qs_pg:woe_adm0":23424925,
    "woe:adm0_id":23424925,
    "woe:name_adm0":"Portugal",
    "woe:name_adm1":"Faro",
    "woe:placetype":"Town",
    "wof:name":"Rogil",
    "wof:placetype":"locality"
},
  "geometry": {"coordinates":[-8.79982,37.37474],"type":"Point"}
}