{
  "type": "Feature",
  "properties": {
    "gn:admin1_code":"17.0",
    "gn:admin2_code":"1307",
    "gn:admin3_code":"130729.0",
    "gn:asciiname":"Pinheiro",
    "gn:country_code":"PT",
    "gn:dem":343,
    "gn:feature_class":"P",
    "gn:feature_code":"PPL",
    "gn:name":"Pinheiro",
    "gn:population":0,
    "gn:timezone":"Europe/Lisbon",
    "iso:country":"PT",
    "wof:name":"Pinheiro",
    "wof:placetype":"locality"
},
  "geometry": {"coordinates":[-8.08932,41.20075],"type":"Point"}
}