{
  "type": "Feature",
  "properties": {
    "gn:admin1_code":"05",
    "gn:admin2_code":"0402",
    "gn:admin3_code":"40245.0",
    "gn:asciiname":"Santa Apolonia",
    "gn:country_code":"PT",
    "gn:dem":704,
    "gn:feature_class":"P",
    "gn:feature_code":"PPL",
    "gn:name":"Santa Apol\u00f3nia",
    "gn:population":0,
    "gn:timezone":"Europe/Lisbon",
    "iso:country":"PT",
    "name:ceb_x_preferred":[
        "Santa Apolonia"
    ],
    "name:fra_x_preferred":[
        "Santa Apolonia"
    ],
    "name:swe_x_preferred":[
        "Santa Apolonia"
    ],
    "wof:name":"Santa Apolonia",
    "wof:placetype":"locality"
},
  "geometry": {"coordinates":[-6.76793,41.80266],"type":"Point"}
}