{
  "type": "Feature",
  "properties": {
    "gn:admin1_code":"18",
    "gn:admin2_code":"1421",
    "gn:admin3_code":"142115.0",
    "gn:asciiname":"Penigardos",
    "gn:country_code":"PT",
    "gn:dem":163,
    "gn:feature_class":"P",
    "gn:feature_code":"PPL",
    "gn:name":"Penigardos",
    "gn:population":0,
    "gn:timezone":"Europe/Lisbon",
    "iso:country":"PT",
    "wof:name":"Penigardos",
    "wof:placetype":"locality"
},
  "geometry": {"coordinates":[-8.56517,39.66101],"type":"Point"}
}