{
  "type": "Feature",
  "properties": {
    "gn:admin1_code":"05",
    "gn:admin2_code":"0407",
    "gn:admin3_code":"40733.0",
    "gn:asciiname":"Vale de Salgueiro",
    "gn:country_code":"PT",
    "gn:dem":346,
    "gn:feature_class":"P",
    "gn:feature_code":"PPL",
    "gn:name":"Vale de Salgueiro",
    "gn:population":0,
    "gn:timezone":"Europe/Lisbon",
    "iso:country":"PT",
    "wof:name":"Vale de Salgueiro",
    "wof:placetype":"locality"
},
  "geometry": {"coordinates":[-7.23513,41.58996],"type":"Point"}
}