{
  "type": "Feature",
  "properties": {
    "gn:admin1_code":"2.0",
    "gn:admin2_code":"0103",
    "gn:admin3_code":"10309.0",
    "gn:asciiname":"Candeeira",
    "gn:country_code":"PT",
    "gn:dem":33,
    "gn:feature_class":"P",
    "gn:feature_code":"PPL",
    "gn:name":"Candeeira",
    "gn:population":0,
    "gn:timezone":"Europe/Lisbon",
    "iso:country":"PT",
    "wof:name":"Candeeira",
    "wof:placetype":"locality"
},
  "geometry": {"coordinates":[-8.48333,40.48333],"type":"Point"}
}