{
  "type": "Feature",
  "properties": {
    "gn:admin1_code":"13",
    "gn:admin2_code":"1008",
    "gn:admin3_code":"100801.0",
    "gn:asciiname":"Lomba da Casa",
    "gn:country_code":"PT",
    "gn:dem":464,
    "gn:feature_class":"P",
    "gn:feature_code":"PPL",
    "gn:name":"Lomba da Casa",
    "gn:population":0,
    "gn:timezone":"Europe/Lisbon",
    "iso:country":"PT",
    "wof:name":"Lomba da Casa",
    "wof:placetype":"locality"
},
  "geometry": {"coordinates":[-8.32346,39.9448],"type":"Point"}
}