{
  "type": "Feature",
  "properties": {
    "gn:admin1_code":"20",
    "gn:admin2_code":"1609",
    "gn:admin3_code":"160928.0",
    "gn:asciiname":"Rome",
    "gn:country_code":"PT",
    "gn:dem":57,
    "gn:feature_class":"P",
    "gn:feature_code":"PPL",
    "gn:name":"Rom\u00e9",
    "gn:population":0,
    "gn:timezone":"Europe/Lisbon",
    "iso:country":"PT",
    "wof:name":"Rome",
    "wof:placetype":"locality"
},
  "geometry": {"coordinates":[-8.76479,41.7108],"type":"Point"}
}