{
  "type": "Feature",
  "properties": {
    "gn:admin1_code":"6.0",
    "gn:admin2_code":"0503",
    "gn:admin3_code":"50329.0",
    "gn:asciiname":"Coutada",
    "gn:country_code":"PT",
    "gn:dem":444,
    "gn:feature_class":"P",
    "gn:feature_code":"PPL",
    "gn:name":"Coutada",
    "gn:population":0,
    "gn:timezone":"Europe/Lisbon",
    "iso:country":"PT",
    "wof:name":"Coutada",
    "wof:placetype":"locality"
},
  "geometry": {"coordinates":[-7.58859,40.19204000000001],"type":"Point"}
}