{
  "type": "Feature",
  "properties": {
    "gn:admin1_code":"4.0",
    "gn:admin2_code":"0313",
    "gn:admin3_code":"31309.0",
    "gn:asciiname":"Bom Despacho",
    "gn:country_code":"PT",
    "gn:dem":185,
    "gn:feature_class":"P",
    "gn:feature_code":"PPL",
    "gn:name":"Bom Despacho",
    "gn:population":0,
    "gn:timezone":"Europe/Lisbon",
    "iso:country":"PT",
    "name:ceb_x_preferred":[
        "Bom Despacho"
    ],
    "name:nld_x_preferred":[
        "Bom Despacho"
    ],
    "name:rus_x_preferred":[
        "\u0411\u043e\u043d-\u0414\u0435\u0441\u043f\u0430\u0448\u0443"
    ],
    "name:swe_x_preferred":[
        "Bom Despacho"
    ],
    "wof:name":"Bom Despacho",
    "wof:placetype":"locality"
},
  "geometry": {"coordinates":[-8.541,41.6001],"type":"Point"}
}