{
  "type": "Feature",
  "properties": {
    "gn:admin1_code":"9.0",
    "gn:admin2_code":"0801",
    "gn:admin3_code":"80105.0",
    "gn:asciiname":"Praia Maria Luisa",
    "gn:country_code":"PT",
    "gn:dem":36,
    "gn:feature_class":"P",
    "gn:feature_code":"PPL",
    "gn:name":"Praia Maria Luisa",
    "gn:population":0,
    "gn:timezone":"Europe/Lisbon",
    "iso:country":"PT",
    "wof:name":"Praia Maria Luisa",
    "wof:placetype":"locality"
},
  "geometry": {"coordinates":[-8.20696,37.09092],"type":"Point"}
}