{
  "type": "Feature",
  "properties": {
    "gn:admin1_code":"06",
    "gn:admin2_code":"0508",
    "gn:admin3_code":"50803.0",
    "gn:asciiname":"Vale da Mua",
    "gn:country_code":"PT",
    "gn:dem":261,
    "gn:feature_class":"P",
    "gn:feature_code":"PPL",
    "gn:name":"Vale da Mua",
    "gn:population":0,
    "gn:timezone":"Europe/Lisbon",
    "iso:country":"PT",
    "wof:name":"Vale da Mua",
    "wof:placetype":"locality"
},
  "geometry": {"coordinates":[-7.79025,39.69821],"type":"Point"}
}