{
  "type": "Feature",
  "properties": {
    "gn:admin1_code":"14",
    "gn:admin2_code":"1109",
    "gn:admin3_code":"110904.0",
    "gn:asciiname":"Sao Lourenco",
    "gn:country_code":"PT",
    "gn:dem":25,
    "gn:feature_class":"P",
    "gn:feature_code":"PPL",
    "gn:name":"S\u00e3o Louren\u00e7o",
    "gn:population":0,
    "gn:timezone":"Europe/Lisbon",
    "iso:country":"PT",
    "wof:name":"Sao Lourenco",
    "wof:placetype":"locality"
},
  "geometry": {"coordinates":[-9.41861,39.01358],"type":"Point"}
}