{
  "type": "Feature",
  "properties": {
    "gn:admin1_code":"04",
    "gn:admin2_code":"0306",
    "gn:admin3_code":"30613.0",
    "gn:asciiname":"Terroso",
    "gn:country_code":"PT",
    "gn:dem":77,
    "gn:feature_class":"P",
    "gn:feature_code":"PPL",
    "gn:name":"Terroso",
    "gn:population":0,
    "gn:timezone":"Europe/Lisbon",
    "iso:country":"PT",
    "name:ceb_x_preferred":[
        "Terroso"
    ],
    "name:deu_x_preferred":[
        "Terroso"
    ],
    "name:kaz_x_preferred":[
        "\u0422\u0435\u0440\u0440\u043e\u0437\u0443"
    ],
    "name:nld_x_preferred":[
        "Terroso"
    ],
    "name:por_x_preferred":[
        "Terroso"
    ],
    "name:rus_x_preferred":[
        "\u0422\u0435\u0440\u0440\u043e\u0437\u0443"
    ],
    "name:spa_x_preferred":[
        "Terroso"
    ],
    "name:tur_x_preferred":[
        "Terroso"
    ],
    "name:zho_x_preferred":[
        "\u7279\u7f57\u82cf"
    ],
    "wof:name":"Terroso",
    "wof:placetype":"locality"
},
  "geometry": {"coordinates":[-8.73198,41.54436],"type":"Point"}
}