{
  "type": "Feature",
  "properties": {
    "gn:admin1_code":"4.0",
    "gn:admin2_code":"0308",
    "gn:admin3_code":"30821.0",
    "gn:asciiname":"Ponta do Campo",
    "gn:country_code":"PT",
    "gn:dem":138,
    "gn:feature_class":"P",
    "gn:feature_code":"PPL",
    "gn:name":"Ponta do Campo",
    "gn:population":0,
    "gn:timezone":"Europe/Lisbon",
    "iso:country":"PT",
    "wof:name":"Ponta do Campo",
    "wof:placetype":"locality"
},
  "geometry": {"coordinates":[-8.3686,41.42519],"type":"Point"}
}