{
  "type": "Feature",
  "properties": {
    "gn:admin1_code":"22.0",
    "gn:admin2_code":"1817",
    "gn:admin3_code":"181709.0",
    "gn:asciiname":"Ladario",
    "gn:country_code":"PT",
    "gn:dem":475,
    "gn:feature_class":"P",
    "gn:feature_code":"PPL",
    "gn:name":"Lad\u00e1rio",
    "gn:population":0,
    "gn:timezone":"Europe/Lisbon",
    "iso:country":"PT",
    "wof:name":"Ladario",
    "wof:placetype":"locality"
},
  "geometry": {"coordinates":[-7.73685,40.69778],"type":"Point"}
}