{
  "type": "Feature",
  "properties": {
    "gn:admin1_code":"13",
    "gn:admin2_code":"1007",
    "gn:admin3_code":"100701.0",
    "gn:asciiname":"Rapos",
    "gn:country_code":"PT",
    "gn:dem":447,
    "gn:feature_class":"P",
    "gn:feature_code":"PPL",
    "gn:name":"Rapos",
    "gn:population":0,
    "gn:timezone":"Europe/Lisbon",
    "iso:country":"PT",
    "wof:name":"Rapos",
    "wof:placetype":"locality"
},
  "geometry": {"coordinates":[-8.19855,39.98869000000001],"type":"Point"}
}