{
  "type": "Feature",
  "properties": {
    "gn:admin1_code":"21.0",
    "gn:admin2_code":"1706",
    "gn:admin3_code":"170610.0",
    "gn:asciiname":"Fervidelas",
    "gn:country_code":"PT",
    "gn:dem":940,
    "gn:feature_class":"P",
    "gn:feature_code":"PPL",
    "gn:name":"Fervidelas",
    "gn:population":0,
    "gn:timezone":"Europe/Lisbon",
    "iso:country":"PT",
    "wof:name":"Fervidelas",
    "wof:placetype":"locality"
},
  "geometry": {"coordinates":[-7.89961,41.75488],"type":"Point"}
}