{
  "type": "Feature",
  "properties": {
    "gn:admin1_code":"23.0",
    "gn:admin2_code":"4101",
    "gn:admin3_code":"410105.0",
    "gn:asciiname":"Flor da Rosa",
    "gn:country_code":"PT",
    "gn:dem":120,
    "gn:feature_class":"P",
    "gn:feature_code":"PPL",
    "gn:name":"Flor da Rosa",
    "gn:population":0,
    "gn:timezone":"Atlantic/Azores",
    "iso:country":"PT",
    "wof:name":"Flor da Rosa",
    "wof:placetype":"locality"
},
  "geometry": {"coordinates":[-25.15,36.96667],"type":"Point"}
}