{
  "type": "Feature",
  "properties": {
    "gn:admin1_code":"22.0",
    "gn:admin2_code":"1824",
    "gn:admin3_code":"182408.0",
    "gn:asciiname":"Pacos",
    "gn:country_code":"PT",
    "gn:dem":471,
    "gn:feature_class":"P",
    "gn:feature_code":"PPL",
    "gn:name":"Pa\u00e7os",
    "gn:population":0,
    "gn:timezone":"Europe/Lisbon",
    "iso:country":"PT",
    "wof:name":"Pacos",
    "wof:placetype":"locality"
},
  "geometry": {"coordinates":[-8.136,40.7043],"type":"Point"}
}