{
  "type": "Feature",
  "properties": {
    "gn:admin1_code":"7.0",
    "gn:admin2_code":"0612",
    "gn:admin3_code":"61204.0",
    "gn:asciiname":"Esteiro",
    "gn:country_code":"PT",
    "gn:dem":371,
    "gn:feature_class":"P",
    "gn:feature_code":"PPL",
    "gn:name":"Esteiro",
    "gn:population":0,
    "gn:timezone":"Europe/Lisbon",
    "iso:country":"PT",
    "wof:name":"Esteiro",
    "wof:placetype":"locality"
},
  "geometry": {"coordinates":[-7.80893,40.08143],"type":"Point"}
}