{
  "type": "Feature",
  "properties": {
    "gn:admin1_code":"13",
    "gn:admin2_code":"1008",
    "gn:admin3_code":"100805.0",
    "gn:asciiname":"Aldeia Cimeira",
    "gn:country_code":"PT",
    "gn:dem":374,
    "gn:feature_class":"P",
    "gn:feature_code":"PPL",
    "gn:name":"Aldeia Cimeira",
    "gn:population":0,
    "gn:timezone":"Europe/Lisbon",
    "iso:country":"PT",
    "wof:name":"Aldeia Cimeira",
    "wof:placetype":"locality"
},
  "geometry": {"coordinates":[-8.24405,39.87217],"type":"Point"}
}