{
  "type": "Feature",
  "properties": {
    "gn:admin1_code":"21.0",
    "gn:admin2_code":"1713",
    "gn:admin3_code":"171316.0",
    "gn:asciiname":"Cerdeira",
    "gn:country_code":"PT",
    "gn:dem":842,
    "gn:feature_class":"P",
    "gn:feature_code":"PPL",
    "gn:name":"Cerdeira",
    "gn:population":0,
    "gn:timezone":"Europe/Lisbon",
    "iso:country":"PT",
    "wof:name":"Cerdeira",
    "wof:placetype":"locality"
},
  "geometry": {"coordinates":[-7.59586,41.44777],"type":"Point"}
}