{
  "type": "Feature",
  "properties": {
    "gn:admin1_code":"7.0",
    "gn:admin2_code":"0610",
    "gn:admin3_code":"61008.0",
    "gn:asciiname":"Casais Velhos",
    "gn:country_code":"PT",
    "gn:dem":19,
    "gn:feature_class":"P",
    "gn:feature_code":"PPL",
    "gn:name":"Casais Velhos",
    "gn:population":0,
    "gn:timezone":"Europe/Lisbon",
    "iso:country":"PT",
    "wof:name":"Casais Velhos",
    "wof:placetype":"locality"
},
  "geometry": {"coordinates":[-8.56376,40.15076],"type":"Point"}
}