{
  "type": "Feature",
  "properties": {
    "gn:admin1_code":"18",
    "gn:admin2_code":"1418",
    "gn:admin3_code":"141805.0",
    "gn:asciiname":"Calvinos",
    "gn:country_code":"PT",
    "gn:dem":210,
    "gn:feature_class":"P",
    "gn:feature_code":"PPL",
    "gn:name":"Calvinos",
    "gn:population":0,
    "gn:timezone":"Europe/Lisbon",
    "iso:country":"PT",
    "wof:name":"Calvinos",
    "wof:placetype":"locality"
},
  "geometry": {"coordinates":[-8.37691,39.67602],"type":"Point"}
}