{
  "type": "Feature",
  "properties": {
    "gn:admin1_code":"7.0",
    "gn:admin2_code":"0615",
    "gn:admin3_code":"61505.0",
    "gn:asciiname":"Gesteira",
    "gn:country_code":"PT",
    "gn:dem":15,
    "gn:feature_class":"P",
    "gn:feature_code":"PPL",
    "gn:name":"Gesteira",
    "gn:population":0,
    "gn:timezone":"Europe/Lisbon",
    "iso:country":"PT",
    "wof:name":"Gesteira",
    "wof:placetype":"locality"
},
  "geometry": {"coordinates":[-8.65594,40.08379],"type":"Point"}
}