{
  "type": "Feature",
  "properties": {
    "gn:admin1_code":"4.0",
    "gn:admin2_code":"0302",
    "gn:admin3_code":"30288.0",
    "gn:asciiname":"Aldeia",
    "gn:country_code":"PT",
    "gn:dem":96,
    "gn:feature_class":"P",
    "gn:feature_code":"PPL",
    "gn:name":"Aldeia",
    "gn:population":0,
    "gn:timezone":"Europe/Lisbon",
    "iso:country":"PT",
    "wof:name":"Aldeia",
    "wof:placetype":"locality"
},
  "geometry": {"coordinates":[-8.65677,41.47633],"type":"Point"}
}