{
  "type": "Feature",
  "properties": {
    "gn:admin1_code":"14",
    "gn:admin2_code":"1113",
    "gn:admin3_code":"111307.0",
    "gn:asciiname":"Sevilheira",
    "gn:country_code":"PT",
    "gn:dem":120,
    "gn:feature_class":"P",
    "gn:feature_code":"PPL",
    "gn:name":"Sevilheira",
    "gn:population":0,
    "gn:timezone":"Europe/Lisbon",
    "iso:country":"PT",
    "wof:name":"Sevilheira",
    "wof:placetype":"locality"
},
  "geometry": {"coordinates":[-9.18372,39.09864],"type":"Point"}
}