{
  "type": "Feature",
  "properties": {
    "gn:admin1_code":"2.0",
    "gn:admin2_code":"0103",
    "gn:admin3_code":"10311.0",
    "gn:asciiname":"Espinhal",
    "gn:country_code":"PT",
    "gn:dem":39,
    "gn:feature_class":"P",
    "gn:feature_code":"PPL",
    "gn:name":"Espinhal",
    "gn:population":0,
    "gn:timezone":"Europe/Lisbon",
    "iso:country":"PT",
    "name:ceb_x_preferred":[
        "Espinhal"
    ],
    "name:deu_x_preferred":[
        "Espinhal"
    ],
    "name:kaz_x_preferred":[
        "\u042d\u0448\u043f\u0438\u043d\u044c\u044f\u043b"
    ],
    "name:msa_x_preferred":[
        "Espinhal"
    ],
    "name:por_x_preferred":[
        "Espinhal"
    ],
    "name:rus_x_preferred":[
        "\u042d\u0448\u043f\u0438\u043d\u044c\u044f\u043b"
    ],
    "name:spa_x_preferred":[
        "Espinhal"
    ],
    "wof:name":"Espinhal",
    "wof:placetype":"locality"
},
  "geometry": {"coordinates":[-8.46361,40.42184],"type":"Point"}
}