{
  "type": "Feature",
  "properties": {
    "gn:admin1_code":"6.0",
    "gn:admin2_code":"0507",
    "gn:admin3_code":"50701.0",
    "gn:asciiname":"Aguas",
    "gn:country_code":"PT",
    "gn:dem":402,
    "gn:feature_class":"P",
    "gn:feature_code":"PPL",
    "gn:name":"\u00c1guas",
    "gn:population":0,
    "gn:timezone":"Europe/Lisbon",
    "iso:country":"PT",
    "wof:name":"Aguas",
    "wof:placetype":"locality"
},
  "geometry": {"coordinates":[-7.20697,40.11262],"type":"Point"}
}