{
  "type": "Feature",
  "properties": {
    "gn:admin1_code":"22",
    "gn:admin2_code":"1823",
    "gn:admin3_code":"182319.0",
    "gn:asciiname":"Travassos",
    "gn:country_code":"PT",
    "gn:dem":409,
    "gn:feature_class":"P",
    "gn:feature_code":"PPL",
    "gn:name":"Travass\u00f3s",
    "gn:population":0,
    "gn:timezone":"Europe/Lisbon",
    "iso:country":"PT",
    "wof:name":"Travassos",
    "wof:placetype":"locality"
},
  "geometry": {"coordinates":[-7.95673,40.66575],"type":"Point"}
}