{
  "type": "Feature",
  "properties": {
    "gn:admin1_code":"04",
    "gn:admin2_code":"0307",
    "gn:admin3_code":"30733.0",
    "gn:asciiname":"Vilar",
    "gn:country_code":"PT",
    "gn:dem":349,
    "gn:feature_class":"P",
    "gn:feature_code":"PPL",
    "gn:name":"Vilar",
    "gn:population":0,
    "gn:timezone":"Europe/Lisbon",
    "iso:country":"PT",
    "wof:name":"Vilar",
    "wof:placetype":"locality"
},
  "geometry": {"coordinates":[-8.19159,41.49132],"type":"Point"}
}