{
  "type": "Feature",
  "properties": {
    "gn:admin1_code":"18",
    "gn:admin2_code":"1401",
    "gn:admin3_code":"140110.0",
    "gn:asciiname":"Barrada",
    "gn:country_code":"PT",
    "gn:dem":179,
    "gn:feature_class":"P",
    "gn:feature_code":"PPL",
    "gn:name":"Barrada",
    "gn:population":0,
    "gn:timezone":"Europe/Lisbon",
    "iso:country":"PT",
    "wof:name":"Barrada",
    "wof:placetype":"locality"
},
  "geometry": {"coordinates":[-8.06598,39.41771],"type":"Point"}
}