{
  "type": "Feature",
  "properties": {
    "gn:admin1_code":"14",
    "gn:admin2_code":"1111",
    "gn:admin3_code":"111103.0",
    "gn:asciiname":"Alveijar",
    "gn:country_code":"PT",
    "gn:dem":257,
    "gn:feature_class":"P",
    "gn:feature_code":"PPL",
    "gn:name":"Alveijar",
    "gn:population":0,
    "gn:timezone":"Europe/Lisbon",
    "iso:country":"PT",
    "wof:name":"Alveijar",
    "wof:placetype":"locality"
},
  "geometry": {"coordinates":[-9.25,38.83333],"type":"Point"}
}