{
  "type": "Feature",
  "properties": {
    "gn:admin1_code":"7.0",
    "gn:admin2_code":"0614",
    "gn:admin3_code":"61403.0",
    "gn:asciiname":"Podentes",
    "gn:country_code":"PT",
    "gn:dem":188,
    "gn:feature_class":"P",
    "gn:feature_code":"PPL",
    "gn:name":"Podentes",
    "gn:population":0,
    "gn:timezone":"Europe/Lisbon",
    "iso:country":"PT",
    "wof:name":"Podentes",
    "wof:placetype":"locality"
},
  "geometry": {"coordinates":[-8.39269,40.0588],"type":"Point"}
}