{
  "type": "Feature",
  "properties": {
    "gn:admin1_code":"22.0",
    "gn:admin2_code":"1810",
    "gn:admin3_code":"181006.0",
    "gn:asciiname":"Entre Aguas",
    "gn:country_code":"PT",
    "gn:dem":420,
    "gn:feature_class":"P",
    "gn:feature_code":"PPL",
    "gn:name":"Entre \u00c1guas",
    "gn:population":0,
    "gn:timezone":"Europe/Lisbon",
    "iso:country":"PT",
    "wof:name":"Entre Aguas",
    "wof:placetype":"locality"
},
  "geometry": {"coordinates":[-8.24938,40.69206],"type":"Point"}
}