{
  "type": "Feature",
  "properties": {
    "gn:admin1_code":"13",
    "gn:admin2_code":"1006",
    "gn:admin3_code":"100604.0",
    "gn:asciiname":"Cabeca Alta",
    "gn:country_code":"PT",
    "gn:dem":167,
    "gn:feature_class":"P",
    "gn:feature_code":"PPL",
    "gn:name":"Cabe\u00e7a Alta",
    "gn:population":0,
    "gn:timezone":"Europe/Lisbon",
    "iso:country":"PT",
    "wof:name":"Cabeca Alta",
    "wof:placetype":"locality"
},
  "geometry": {"coordinates":[-9.05028,39.43547],"type":"Point"}
}