{
  "type": "Feature",
  "properties": {
    "gn:admin1_code":"09",
    "gn:admin2_code":"0814",
    "gn:admin3_code":"81404.0",
    "gn:asciiname":"Casas Altas",
    "gn:country_code":"PT",
    "gn:dem":214,
    "gn:feature_class":"P",
    "gn:feature_code":"PPL",
    "gn:name":"Casas Altas",
    "gn:population":0,
    "gn:timezone":"Europe/Lisbon",
    "iso:country":"PT",
    "name:arg_x_preferred":[
        "Casas Altas"
    ],
    "name:ast_x_preferred":[
        "Casas Altas"
    ],
    "name:cat_x_preferred":[
        "Cases Altes"
    ],
    "name:ceb_x_preferred":[
        "Casas Altas"
    ],
    "name:eus_x_preferred":[
        "Casas Altas"
    ],
    "name:fra_x_preferred":[
        "Casas Altas"
    ],
    "name:hun_x_preferred":[
        "Casas Altas"
    ],
    "name:ita_x_preferred":[
        "Casas Altas"
    ],
    "name:msa_x_preferred":[
        "Casas Altas"
    ],
    "name:nld_x_preferred":[
        "Casas Altas"
    ],
    "name:oci_x_preferred":[
        "Casas Altas"
    ],
    "name:pol_x_preferred":[
        "Casas Altas"
    ],
    "name:por_x_preferred":[
        "Casas Altas"
    ],
    "name:rus_x_preferred":[
        "\u041a\u0430\u0441\u0430\u0441-\u0410\u043b\u044c\u0442\u0430\u0441"
    ],
    "name:spa_x_preferred":[
        "Casas Altas"
    ],
    "name:sqi_x_preferred":[
        "Casas Altas"
    ],
    "name:swe_x_preferred":[
        "Casas Altas"
    ],
    "name:ukr_x_preferred":[
        "\u041a\u0430\u0441\u0430\u0441-\u0410\u043b\u044c\u0442\u0430\u0441"
    ],
    "name:vie_x_preferred":[
        "Casas Altas"
    ],
    "name:war_x_preferred":[
        "Casas Altas"
    ],
    "name:zho_x_preferred":[
        "\u5361\u8428\u8428\u5c14\u5854\u65af"
    ],
    "wof:name":"Casas Altas",
    "wof:placetype":"locality"
},
  "geometry": {"coordinates":[-7.72451,37.22016],"type":"Point"}
}