{
  "type": "Feature",
  "properties": {
    "gn:admin1_code":"5.0",
    "gn:admin2_code":"0412",
    "gn:admin3_code":"41212.0",
    "gn:asciiname":"Carvalhas",
    "gn:country_code":"PT",
    "gn:dem":956,
    "gn:feature_class":"P",
    "gn:feature_code":"PPL",
    "gn:name":"Carvalhas",
    "gn:population":0,
    "gn:timezone":"Europe/Lisbon",
    "iso:country":"PT",
    "wof:name":"Carvalhas",
    "wof:placetype":"locality"
},
  "geometry": {"coordinates":[-7.00023,41.94372],"type":"Point"}
}