{
  "type": "Feature",
  "properties": {
    "gn:admin1_code":"5.0",
    "gn:admin2_code":"0412",
    "gn:admin3_code":"41212.0",
    "gn:asciiname":"Carvalhas",
    "gn:country_code":"PT",
    "gn:dem":956,
    "gn:feature_class":"P",
    "gn:feature_code":"PPL",
    "gn:name":"Carvalhas",
    "gn:population":0,
    "gn:timezone":"Europe/Lisbon",
    "iso:country":"PT",
    "name:bpy_x_preferred":[
        "\u0995\u09be\u09b0\u09cd\u09ad\u09be\u09b2\u09b9\u09cb\u09b8"
    ],
    "name:ceb_x_preferred":[
        "Carvalhos"
    ],
    "name:deu_x_preferred":[
        "Carvalhas"
    ],
    "name:kaz_x_preferred":[
        "\u041a\u0430\u0440\u0432\u0430\u043b\u044c\u044f\u0448"
    ],
    "name:msa_x_preferred":[
        "Carvalhos"
    ],
    "name:por_x_preferred":[
        "Carvalhas"
    ],
    "name:rus_x_preferred":[
        "\u041a\u0430\u0440\u0432\u0430\u043b\u044c\u044f\u0448"
    ],
    "name:spa_x_preferred":[
        "Carvalhas"
    ],
    "name:ukr_x_preferred":[
        "\u041a\u0430\u0440\u0432\u0430\u043b\u044f\u0448"
    ],
    "name:zho_x_preferred":[
        "\u5361\u74e6\u5229\u4e9a\u65af"
    ],
    "wof:name":"Carvalhas",
    "wof:placetype":"locality"
},
  "geometry": {"coordinates":[-7.00023,41.94372],"type":"Point"}
}