{
  "type": "Feature",
  "properties": {
    "gn:admin1_code":"20.0",
    "gn:admin2_code":"1609",
    "gn:admin3_code":"160904.0",
    "gn:asciiname":"Monte",
    "gn:country_code":"PT",
    "gn:dem":56,
    "gn:feature_class":"P",
    "gn:feature_code":"PPL",
    "gn:name":"Monte",
    "gn:population":0,
    "gn:timezone":"Europe/Lisbon",
    "iso:country":"PT",
    "wof:name":"Monte",
    "wof:placetype":"locality"
},
  "geometry": {"coordinates":[-8.78454,41.66748],"type":"Point"}
}