{
  "type": "Feature",
  "properties": {
    "gn:admin1_code":"09",
    "gn:admin2_code":"0801",
    "gn:admin3_code":"80104.0",
    "gn:asciiname":"Fontainhas",
    "gn:country_code":"PT",
    "gn:dem":98,
    "gn:feature_class":"P",
    "gn:feature_code":"PPL",
    "gn:name":"Fontainhas",
    "gn:population":0,
    "gn:timezone":"Europe/Lisbon",
    "iso:country":"PT",
    "name:cat_x_preferred":[
        "Fontainhas"
    ],
    "name:fra_x_preferred":[
        "Fontainhas"
    ],
    "name:por_x_preferred":[
        "Fontainhas"
    ],
    "name:ron_x_preferred":[
        "Fontainhas"
    ],
    "wof:name":"Fontainhas",
    "wof:placetype":"locality"
},
  "geometry": {"coordinates":[-8.21864,37.12749],"type":"Point"}
}