{
  "type": "Feature",
  "properties": {
    "gn:admin1_code":"14",
    "gn:admin2_code":"1109",
    "gn:admin3_code":"110902.0",
    "gn:asciiname":"Baleia",
    "gn:country_code":"PT",
    "gn:dem":102,
    "gn:feature_class":"P",
    "gn:feature_code":"PPL",
    "gn:name":"Baleia",
    "gn:population":0,
    "gn:timezone":"Europe/Lisbon",
    "iso:country":"PT",
    "name:por_x_preferred":[
        "Baleia"
    ],
    "name:ron_x_preferred":[
        "Baleia"
    ],
    "wof:name":"Baleia",
    "wof:placetype":"locality"
},
  "geometry": {"coordinates":[-9.40132,38.93522],"type":"Point"}
}