{
  "type": "Feature",
  "properties": {
    "gn:admin1_code":"06",
    "gn:admin2_code":"0510",
    "gn:admin3_code":"51001.0",
    "gn:asciiname":"Lagoa Cimeira",
    "gn:country_code":"PT",
    "gn:dem":301,
    "gn:feature_class":"P",
    "gn:feature_code":"PPL",
    "gn:name":"Lagoa Cimeira",
    "gn:population":0,
    "gn:timezone":"Europe/Lisbon",
    "iso:country":"PT",
    "wof:name":"Lagoa Cimeira",
    "wof:placetype":"locality"
},
  "geometry": {"coordinates":[-8.15646,39.73179],"type":"Point"}
}