{
  "type": "Feature",
  "properties": {
    "gn:admin1_code":"13",
    "gn:admin2_code":"1003",
    "gn:admin3_code":"100304.0",
    "gn:asciiname":"Tojeira",
    "gn:country_code":"PT",
    "gn:dem":248,
    "gn:feature_class":"P",
    "gn:feature_code":"PPL",
    "gn:name":"Tojeira",
    "gn:population":0,
    "gn:timezone":"Europe/Lisbon",
    "iso:country":"PT",
    "wof:name":"Tojeira",
    "wof:placetype":"locality"
},
  "geometry": {"coordinates":[-8.37153,39.92285],"type":"Point"}
}