{
  "type": "Feature",
  "properties": {
    "gn:admin1_code":"22.0",
    "gn:admin2_code":"1811",
    "gn:admin3_code":"181109.0",
    "gn:asciiname":"Pindo",
    "gn:country_code":"PT",
    "gn:dem":490,
    "gn:feature_class":"P",
    "gn:feature_code":"PPL",
    "gn:name":"Pindo",
    "gn:population":0,
    "gn:timezone":"Europe/Lisbon",
    "iso:country":"PT",
    "wof:name":"Pindo",
    "wof:placetype":"locality"
},
  "geometry": {"coordinates":[-7.76085,40.67084000000001],"type":"Point"}
}