{
  "type": "Feature",
  "properties": {
    "gn:admin1_code":"05",
    "gn:admin2_code":"0407",
    "gn:admin3_code":"40704.0",
    "gn:asciiname":"Vale da Lagoa",
    "gn:country_code":"PT",
    "gn:dem":491,
    "gn:feature_class":"P",
    "gn:feature_code":"PPL",
    "gn:name":"Vale da Lagoa",
    "gn:population":0,
    "gn:timezone":"Europe/Lisbon",
    "iso:country":"PT",
    "wof:name":"Vale da Lagoa",
    "wof:placetype":"locality"
},
  "geometry": {"coordinates":[-7.05409,41.57167000000001],"type":"Point"}
}