{
  "type": "Feature",
  "properties": {
    "gn:country":"PT",
    "gn:fcode":"PPL",
    "gn:population":13495,
    "iso:country":"PT",
    "name:ceb_x_preferred":[
        "Arcozelo"
    ],
    "name:deu_x_preferred":[
        "Arcozelo"
    ],
    "name:fra_x_preferred":[
        "Arcozelo"
    ],
    "name:ita_x_preferred":[
        "Arcozelo"
    ],
    "name:nld_x_preferred":[
        "Arcozelo"
    ],
    "name:por_x_preferred":[
        "Arcozelo"
    ],
    "name:rus_x_preferred":[
        "\u0410\u0440\u043a\u043e\u0437\u0435\u043b\u0443"
    ],
    "name:swe_x_preferred":[
        "Arcozelo"
    ],
    "name:tur_x_preferred":[
        "Arcozelo"
    ],
    "name:ukr_x_preferred":[
        "\u0410\u0440\u043a\u043e\u0437\u0435\u043b\u0443"
    ],
    "qs_pg:aaroncc":"PT",
    "qs_pg:gn_country":"PT",
    "qs_pg:gn_fcode":"PPL",
    "qs_pg:gn_pop":13495,
    "qs_pg:name":"Arcozelo",
    "qs_pg:name_adm0":"Portugal",
    "qs_pg:name_adm1":"Porto",
    "qs_pg:photos":31,
    "qs_pg:photos_1k":6,
    "qs_pg:photos_9k":1,
    "qs_pg:photos_9r":2,
    "qs_pg:photos_all":31,
    "qs_pg:photos_sr":2,
    "qs_pg:pop_sr":6,
    "qs_pg:qs_pg_placetype":"locality",
    "qs_pg:qs_pg_placetype_gp":"Town",
    "qs_pg:woe_adm0":23424925,
    "woe:adm0_id":23424925,
    "woe:name_adm0":"Portugal",
    "woe:name_adm1":"Porto",
    "woe:placetype":"Town",
    "wof:name":"Arcozelo",
    "wof:placetype":"locality",
    "wof:population":13495
},
  "geometry": {"coordinates":[-8.64326,41.05328],"type":"Point"}
}