{
  "type": "Feature",
  "properties": {
    "gn:admin1_code":"2.0",
    "gn:admin2_code":"0117",
    "gn:admin3_code":"11701.0",
    "gn:asciiname":"Carrazedo",
    "gn:country_code":"PT",
    "gn:dem":301,
    "gn:feature_class":"P",
    "gn:feature_code":"PPL",
    "gn:name":"Carrazedo",
    "gn:population":0,
    "gn:timezone":"Europe/Lisbon",
    "iso:country":"PT",
    "wof:name":"Carrazedo",
    "wof:placetype":"locality"
},
  "geometry": {"coordinates":[-8.33238,40.69237],"type":"Point"}
}