{
  "type": "Feature",
  "properties": {
    "gn:admin1_code":"20.0",
    "gn:admin2_code":"1601",
    "gn:admin3_code":"160124.0",
    "gn:asciiname":"Paco",
    "gn:country_code":"PT",
    "gn:dem":75,
    "gn:feature_class":"P",
    "gn:feature_code":"PPL",
    "gn:name":"Pa\u00e7\u00f4",
    "gn:population":0,
    "gn:timezone":"Europe/Lisbon",
    "iso:country":"PT",
    "name:ita_x_preferred":[
        "Paco"
    ],
    "wof:name":"Paco",
    "wof:placetype":"locality"
},
  "geometry": {"coordinates":[-8.41244,41.83625],"type":"Point"}
}