{
  "type": "Feature",
  "properties": {
    "gn:admin1_code":"11.0",
    "gn:admin2_code":"0912",
    "gn:admin3_code":"91215.0",
    "gn:asciiname":"Eiro",
    "gn:country_code":"PT",
    "gn:dem":591,
    "gn:feature_class":"P",
    "gn:feature_code":"PPL",
    "gn:name":"Eir\u00f4",
    "gn:population":0,
    "gn:timezone":"Europe/Lisbon",
    "iso:country":"PT",
    "wof:name":"Eiro",
    "wof:placetype":"locality"
},
  "geometry": {"coordinates":[-7.64948,40.45534],"type":"Point"}
}