{
  "type": "Feature",
  "properties": {
    "gn:admin1_code":"18",
    "gn:admin2_code":"1419",
    "gn:admin3_code":"141902.0",
    "gn:asciiname":"Paialvo",
    "gn:country_code":"PT",
    "gn:dem":98,
    "gn:feature_class":"P",
    "gn:feature_code":"PPL",
    "gn:name":"Paialvo",
    "gn:population":2599,
    "gn:timezone":"Europe/Lisbon",
    "iso:country":"PT",
    "name:ceb_x_preferred":[
        "Paialvo"
    ],
    "name:deu_x_preferred":[
        "Paialvo"
    ],
    "name:fra_x_preferred":[
        "Paialvo"
    ],
    "name:kaz_x_preferred":[
        "\u041f\u0430\u0439\u0430\u043b\u0432\u0443"
    ],
    "name:nld_x_preferred":[
        "Paialvo"
    ],
    "name:por_x_preferred":[
        "Paialvo"
    ],
    "name:rus_x_preferred":[
        "\u041f\u0430\u044f\u043b\u0432\u0443"
    ],
    "name:spa_x_preferred":[
        "Paialvo"
    ],
    "name:tur_x_preferred":[
        "Paialvo"
    ],
    "wof:name":"Paialvo",
    "wof:placetype":"locality",
    "wof:population":2599
},
  "geometry": {"coordinates":[-8.46835,39.56399],"type":"Point"}
}