{
  "type": "Feature",
  "properties": {
    "gn:admin1_code":"18",
    "gn:admin2_code":"1419",
    "gn:admin3_code":"141902.0",
    "gn:asciiname":"Paialvo",
    "gn:country_code":"PT",
    "gn:dem":98,
    "gn:feature_class":"P",
    "gn:feature_code":"PPL",
    "gn:name":"Paialvo",
    "gn:population":2599,
    "gn:timezone":"Europe/Lisbon",
    "iso:country":"PT",
    "wof:name":"Paialvo",
    "wof:placetype":"locality",
    "wof:population":2599
},
  "geometry": {"coordinates":[-8.46835,39.56399],"type":"Point"}
}