{
  "type": "Feature",
  "properties": {
    "gn:admin1_code":"03",
    "gn:admin2_code":"0209",
    "gn:admin3_code":"20904.0",
    "gn:asciiname":"Amendoeira",
    "gn:country_code":"PT",
    "gn:dem":162,
    "gn:feature_class":"P",
    "gn:feature_code":"PPL",
    "gn:name":"Amendoeira",
    "gn:population":0,
    "gn:timezone":"Europe/Lisbon",
    "iso:country":"PT",
    "wof:name":"Amendoeira",
    "wof:placetype":"locality"
},
  "geometry": {"coordinates":[-7.69174,37.79145],"type":"Point"}
}