{
  "type": "Feature",
  "properties": {
    "gn:admin1_code":"10",
    "gn:admin2_code":"3101",
    "gn:admin3_code":"310102.0",
    "gn:asciiname":"Ribeira do Raposo",
    "gn:country_code":"PT",
    "gn:dem":376,
    "gn:feature_class":"P",
    "gn:feature_code":"PPL",
    "gn:name":"Ribeira do Raposo",
    "gn:population":0,
    "gn:timezone":"Atlantic/Madeira",
    "iso:country":"PT",
    "wof:name":"Ribeira do Raposo",
    "wof:placetype":"locality"
},
  "geometry": {"coordinates":[-17.16667,32.73333],"type":"Point"}
}