{
  "type": "Feature",
  "properties": {
    "gn:admin1_code":"17.0",
    "gn:admin2_code":"1313",
    "gn:admin3_code":"131302.0",
    "gn:asciiname":"Aldeia",
    "gn:country_code":"PT",
    "gn:dem":-9999,
    "gn:feature_class":"P",
    "gn:feature_code":"PPL",
    "gn:name":"Aldeia",
    "gn:population":0,
    "gn:timezone":"Europe/Lisbon",
    "iso:country":"PT",
    "wof:name":"Aldeia",
    "wof:placetype":"locality"
},
  "geometry": {"coordinates":[-8.78314,41.42908],"type":"Point"}
}