{
  "type": "Feature",
  "properties": {
    "gn:admin1_code":"03",
    "gn:admin2_code":"0201",
    "gn:admin3_code":"20104.0",
    "gn:asciiname":"Aldeia Nova",
    "gn:country_code":"PT",
    "gn:dem":101,
    "gn:feature_class":"P",
    "gn:feature_code":"PPL",
    "gn:name":"Aldeia Nova",
    "gn:population":0,
    "gn:timezone":"Europe/Lisbon",
    "iso:country":"PT",
    "wof:name":"Aldeia Nova",
    "wof:placetype":"locality"
},
  "geometry": {"coordinates":[-8.18669,37.95153],"type":"Point"}
}