{
  "type": "Feature",
  "properties": {
    "gn:admin1_code":"7.0",
    "gn:admin2_code":"0601",
    "gn:admin3_code":"60113.0",
    "gn:asciiname":"Chapinheira",
    "gn:country_code":"PT",
    "gn:dem":323,
    "gn:feature_class":"P",
    "gn:feature_code":"PPL",
    "gn:name":"Chapinheira",
    "gn:population":0,
    "gn:timezone":"Europe/Lisbon",
    "iso:country":"PT",
    "wof:name":"Chapinheira",
    "wof:placetype":"locality"
},
  "geometry": {"coordinates":[-8.17311,40.20572],"type":"Point"}
}