{
  "type": "Feature",
  "properties": {
    "gn:population":5932,
    "iso:country":"PT",
    "name:arg_x_preferred":[
        "Ribeira Brava"
    ],
    "name:arm_x_preferred":[
        "\u054c\u056b\u0562\u0565\u0575\u0580\u0561 \u0532\u0580\u0561\u057e\u0561"
    ],
    "name:baq_x_preferred":[
        "Ribeira Brava"
    ],
    "name:cat_x_preferred":[
        "Ribeira Brava"
    ],
    "name:chi_x_preferred":[
        "\u91cc\u97cb\u62c9\u5e03\u62c9\u74e6"
    ],
    "name:cze_x_preferred":[
        "Ribeira Brava"
    ],
    "name:deu_x_preferred":[
        "Ribeira Brava"
    ],
    "name:dut_x_preferred":[
        "Ribeira Brava"
    ],
    "name:ell_x_preferred":[
        "\u03a1\u03b9\u03b2\u03ad\u03b9\u03c1\u03b1 \u039c\u03c0\u03c1\u03ac\u03b2\u03b1"
    ],
    "name:eng_x_preferred":[
        "Ribeira Brava"
    ],
    "name:fin_x_preferred":[
        "Ribeira Brava"
    ],
    "name:fra_x_preferred":[
        "Ribeira Brava"
    ],
    "name:fre_x_preferred":[
        "Ribeira Brava"
    ],
    "name:ger_x_preferred":[
        "Ribeira Brava"
    ],
    "name:hun_x_preferred":[
        "Ribeira Brava"
    ],
    "name:ita_x_preferred":[
        "Ribeira Brava"
    ],
    "name:kor_x_preferred":[
        "\ud788\ubca0\uc774\ub77c\ube0c\ub77c\ubc14"
    ],
    "name:lit_x_preferred":[
        "Ribeira Brava"
    ],
    "name:may_x_preferred":[
        "Ribeira Brava"
    ],
    "name:nan_x_preferred":[
        "Ribeira Brava"
    ],
    "name:nld_x_preferred":[
        "Ribeira Brava"
    ],
    "name:nob_x_preferred":[
        "Ribeira Brava"
    ],
    "name:pol_x_preferred":[
        "Ribeira Brava"
    ],
    "name:por_x_preferred":[
        "Ribeira Brava"
    ],
    "name:rus_x_preferred":[
        "\u0420\u0438\u0431\u0435\u0439\u0440\u0430-\u0411\u0440\u0430\u0432\u0430"
    ],
    "name:spa_x_preferred":[
        "Ribeira Brava"
    ],
    "name:tur_x_preferred":[
        "Ribeira Brava"
    ],
    "name:ukr_x_preferred":[
        "\u0420\u0456\u0431\u0435\u0439\u0440\u0430-\u0411\u0440\u0430\u0432\u0430"
    ],
    "name:vie_x_preferred":[
        "Ribeira Brava"
    ],
    "name:vol_x_preferred":[
        "Ribeira Brava"
    ],
    "name:war_x_preferred":[
        "Ribeira Brava"
    ],
    "qs:a0":"Portugal",
    "qs:a1":"*Regi\u00e3o Aut\u00f3noma da Madeira",
    "qs:a1r":"0",
    "qs:adm0":"Portugal",
    "qs:la_lc":"*",
    "qs:level":"locality",
    "qs:loc":"Ribeira Brava",
    "qs:loc_alt":"Ribeira Brava",
    "qs:pop":0,
    "qs:type":"buffered point",
    "wd:wordcount":45,
    "wof:lang":[
        "por"
    ],
    "wof:name":"Ribeira Brava",
    "wof:placetype":"locality",
    "wof:population":5932
},
  "geometry": {"coordinates":[-17.062596,32.669522],"type":"Point"}
}