{
  "type": "Feature",
  "properties": {
    "gn:admin1_code":"18",
    "gn:admin2_code":"1409",
    "gn:admin3_code":"140901.0",
    "gn:asciiname":"Monte dos Alhos",
    "gn:country_code":"PT",
    "gn:dem":22,
    "gn:feature_class":"P",
    "gn:feature_code":"PPL",
    "gn:name":"Monte dos Alhos",
    "gn:population":0,
    "gn:timezone":"Europe/Lisbon",
    "iso:country":"PT",
    "wof:name":"Monte dos Alhos",
    "wof:placetype":"locality"
},
  "geometry": {"coordinates":[-8.48896,38.95401],"type":"Point"}
}