{
  "type": "Feature",
  "properties": {
    "gn:admin1_code":"22.0",
    "gn:admin2_code":"1803",
    "gn:admin3_code":"180304.0",
    "gn:asciiname":"Costilhao",
    "gn:country_code":"PT",
    "gn:dem":752,
    "gn:feature_class":"P",
    "gn:feature_code":"PPL",
    "gn:name":"Costilh\u00e3o",
    "gn:population":0,
    "gn:timezone":"Europe/Lisbon",
    "iso:country":"PT",
    "wof:name":"Costilhao",
    "wof:placetype":"locality"
},
  "geometry": {"coordinates":[-7.90489,40.92608],"type":"Point"}
}