{
  "type": "Feature",
  "properties": {
    "gn:admin1_code":"20.0",
    "gn:admin2_code":"1607",
    "gn:admin3_code":"160701.0",
    "gn:asciiname":"Anais",
    "gn:country_code":"PT",
    "gn:dem":282,
    "gn:feature_class":"P",
    "gn:feature_code":"PPL",
    "gn:name":"Anais",
    "gn:population":0,
    "gn:timezone":"Europe/Lisbon",
    "iso:country":"PT",
    "wof:name":"Anais",
    "wof:placetype":"locality"
},
  "geometry": {"coordinates":[-8.52401,41.69901],"type":"Point"}
}