{
  "type": "Feature",
  "properties": {
    "gn:admin1_code":"17.0",
    "gn:admin2_code":"1307",
    "gn:admin3_code":"130706.0",
    "gn:asciiname":"Favoes",
    "gn:country_code":"PT",
    "gn:dem":199,
    "gn:feature_class":"P",
    "gn:feature_code":"PPL",
    "gn:name":"Fav\u00f5es",
    "gn:population":0,
    "gn:timezone":"Europe/Lisbon",
    "iso:country":"PT",
    "wof:name":"Favoes",
    "wof:placetype":"locality"
},
  "geometry": {"coordinates":[-8.23107,41.1151],"type":"Point"}
}