{
  "type": "Feature",
  "properties": {
    "gn:admin1_code":"17",
    "gn:admin2_code":"1302",
    "gn:admin3_code":"130208.0",
    "gn:asciiname":"Taloes",
    "gn:country_code":"PT",
    "gn:dem":613,
    "gn:feature_class":"P",
    "gn:feature_code":"PPL",
    "gn:name":"Tal\u00f5es",
    "gn:population":0,
    "gn:timezone":"Europe/Lisbon",
    "iso:country":"PT",
    "wof:name":"Taloes",
    "wof:placetype":"locality"
},
  "geometry": {"coordinates":[-7.98163,41.21314],"type":"Point"}
}