{
  "type": "Feature",
  "properties": {
    "gn:admin1_code":"20.0",
    "gn:asciiname":"Calvario",
    "gn:country_code":"PT",
    "gn:dem":18,
    "gn:feature_class":"P",
    "gn:feature_code":"PPL",
    "gn:name":"Calv\u00e1rio",
    "gn:population":0,
    "gn:timezone":"Europe/Madrid",
    "iso:country":"PT",
    "wof:name":"Calvario",
    "wof:placetype":"locality"
},
  "geometry": {"coordinates":[-8.56749,42.05609000000001],"type":"Point"}
}