{
  "type": "Feature",
  "properties": {
    "gn:admin1_code":"22",
    "gn:admin2_code":"1805",
    "gn:admin3_code":"180516.0",
    "gn:asciiname":"Sao Giao",
    "gn:country_code":"PT",
    "gn:dem":290,
    "gn:feature_class":"P",
    "gn:feature_code":"PPL",
    "gn:name":"S\u00e3o Gi\u00e3o",
    "gn:population":0,
    "gn:timezone":"Europe/Lisbon",
    "iso:country":"PT",
    "wof:name":"Sao Giao",
    "wof:placetype":"locality"
},
  "geometry": {"coordinates":[-7.8366,41.1462],"type":"Point"}
}