{
  "type": "Feature",
  "properties": {
    "gn:admin1_code":"14",
    "gn:admin2_code":"1111",
    "gn:admin3_code":"111110.0",
    "gn:asciiname":"Peroleite",
    "gn:country_code":"PT",
    "gn:dem":129,
    "gn:feature_class":"P",
    "gn:feature_code":"PPL",
    "gn:name":"Peroleite",
    "gn:population":0,
    "gn:timezone":"Europe/Lisbon",
    "iso:country":"PT",
    "wof:name":"Peroleite",
    "wof:placetype":"locality"
},
  "geometry": {"coordinates":[-9.38805,38.91057],"type":"Point"}
}