{
  "type": "Feature",
  "properties": {
    "gn:admin1_code":"13",
    "gn:admin2_code":"1001",
    "gn:admin3_code":"100108.0",
    "gn:asciiname":"Corticada",
    "gn:country_code":"PT",
    "gn:dem":103,
    "gn:feature_class":"P",
    "gn:feature_code":"PPL",
    "gn:name":"Corti\u00e7ada",
    "gn:population":0,
    "gn:timezone":"Europe/Lisbon",
    "iso:country":"PT",
    "wof:name":"Corticada",
    "wof:placetype":"locality"
},
  "geometry": {"coordinates":[-8.97118,39.50232000000001],"type":"Point"}
}