{
  "type": "Feature",
  "properties": {
    "gn:admin1_code":"22.0",
    "gn:admin2_code":"1813",
    "gn:admin3_code":"181312.0",
    "gn:asciiname":"Cuvelinhas",
    "gn:country_code":"PT",
    "gn:dem":591,
    "gn:feature_class":"P",
    "gn:feature_code":"PPL",
    "gn:name":"Cuvelinhas",
    "gn:population":0,
    "gn:timezone":"Europe/Lisbon",
    "iso:country":"PT",
    "wof:name":"Cuvelinhas",
    "wof:placetype":"locality"
},
  "geometry": {"coordinates":[-7.98201,41.05428],"type":"Point"}
}