{
  "type": "Feature",
  "properties": {
    "gn:admin1_code":"03",
    "gn:admin2_code":"0202",
    "gn:admin3_code":"20202.0",
    "gn:asciiname":"Monte das Figueiras",
    "gn:country_code":"PT",
    "gn:dem":239,
    "gn:feature_class":"P",
    "gn:feature_code":"PPL",
    "gn:name":"Monte das Figueiras",
    "gn:population":0,
    "gn:timezone":"Europe/Lisbon",
    "iso:country":"PT",
    "wof:name":"Monte das Figueiras",
    "wof:placetype":"locality"
},
  "geometry": {"coordinates":[-8.23816,37.52556],"type":"Point"}
}