{
  "type": "Feature",
  "properties": {
    "gn:admin1_code":"18",
    "gn:admin2_code":"1401",
    "gn:admin3_code":"140110.0",
    "gn:asciiname":"Courelas",
    "gn:country_code":"PT",
    "gn:dem":106,
    "gn:feature_class":"P",
    "gn:feature_code":"PPL",
    "gn:name":"Courelas",
    "gn:population":0,
    "gn:timezone":"Europe/Lisbon",
    "iso:country":"PT",
    "wof:name":"Courelas",
    "wof:placetype":"locality"
},
  "geometry": {"coordinates":[-8.1211,39.34601],"type":"Point"}
}