{
  "type": "Feature",
  "properties": {
    "gn:admin1_code":"23.0",
    "gn:admin2_code":"4202",
    "gn:admin3_code":"420201.0",
    "gn:asciiname":"Feteira Pequena",
    "gn:country_code":"PT",
    "gn:dem":200,
    "gn:feature_class":"P",
    "gn:feature_code":"PPL",
    "gn:name":"Feteira Pequena",
    "gn:population":0,
    "gn:timezone":"Atlantic/Azores",
    "iso:country":"PT",
    "wof:name":"Feteira Pequena",
    "wof:placetype":"locality"
},
  "geometry": {"coordinates":[-25.26667,37.85],"type":"Point"}
}