{
  "type": "Feature",
  "properties": {
    "gn:admin1_code":"23.0",
    "gn:admin2_code":"4602",
    "gn:admin3_code":"460205.0",
    "gn:asciiname":"Prainha do Galeao",
    "gn:country_code":"PT",
    "gn:dem":133,
    "gn:feature_class":"P",
    "gn:feature_code":"PPL",
    "gn:name":"Prainha do Gale\u00e3o",
    "gn:population":0,
    "gn:timezone":"Atlantic/Azores",
    "iso:country":"PT",
    "wof:name":"Prainha do Galeao",
    "wof:placetype":"locality"
},
  "geometry": {"coordinates":[-28.43333,38.43333],"type":"Point"}
}