{
  "type": "Feature",
  "properties": {
    "gn:admin1_code":"16",
    "gn:admin2_code":"1207",
    "gn:admin3_code":"120701.0",
    "gn:asciiname":"Monte do Freixial",
    "gn:country_code":"PT",
    "gn:dem":182,
    "gn:feature_class":"P",
    "gn:feature_code":"PPL",
    "gn:name":"Monte do Freixial",
    "gn:population":0,
    "gn:timezone":"Europe/Lisbon",
    "iso:country":"PT",
    "wof:name":"Monte do Freixial",
    "wof:placetype":"locality"
},
  "geometry": {"coordinates":[-7.16632,38.79457],"type":"Point"}
}