{
  "type": "Feature",
  "properties": {
    "gn:admin1_code":"18",
    "gn:admin2_code":"1421",
    "gn:admin3_code":"142108.0",
    "gn:asciiname":"Junqueira",
    "gn:country_code":"PT",
    "gn:dem":173,
    "gn:feature_class":"P",
    "gn:feature_code":"PPL",
    "gn:name":"Junqueira",
    "gn:population":0,
    "gn:timezone":"Europe/Lisbon",
    "iso:country":"PT",
    "wof:name":"Junqueira",
    "wof:placetype":"locality"
},
  "geometry": {"coordinates":[-8.47819,39.80068],"type":"Point"}
}