{
  "type": "Feature",
  "properties": {
    "gn:admin1_code":"18",
    "gn:admin2_code":"1421",
    "gn:admin3_code":"142108.0",
    "gn:asciiname":"Junqueira",
    "gn:country_code":"PT",
    "gn:dem":173,
    "gn:feature_class":"P",
    "gn:feature_code":"PPL",
    "gn:name":"Junqueira",
    "gn:population":0,
    "gn:timezone":"Europe/Lisbon",
    "iso:country":"PT",
    "name:ceb_x_preferred":[
        "Junqueira"
    ],
    "name:deu_x_preferred":[
        "Junqueira"
    ],
    "name:fra_x_preferred":[
        "Junqueira"
    ],
    "name:nld_x_preferred":[
        "Junqueira"
    ],
    "name:por_x_preferred":[
        "Junqueira"
    ],
    "name:rus_x_preferred":[
        "\u0416\u0443\u043d\u043a\u0435\u0439\u0440\u0430"
    ],
    "name:tur_x_preferred":[
        "Junqueira"
    ],
    "name:ukr_x_preferred":[
        "\u0416\u0443\u043d\u043a\u0435\u0439\u0440\u0430"
    ],
    "wof:name":"Junqueira",
    "wof:placetype":"locality"
},
  "geometry": {"coordinates":[-8.47819,39.80068],"type":"Point"}
}