{
  "type": "Feature",
  "properties": {
    "gn:admin1_code":"09",
    "gn:admin2_code":"0809",
    "gn:admin3_code":"80903.0",
    "gn:asciiname":"Peso",
    "gn:country_code":"PT",
    "gn:dem":487,
    "gn:feature_class":"P",
    "gn:feature_code":"PPL",
    "gn:name":"Peso",
    "gn:population":0,
    "gn:timezone":"Europe/Lisbon",
    "iso:country":"PT",
    "wof:name":"Peso",
    "wof:placetype":"locality"
},
  "geometry": {"coordinates":[-8.56667,37.33333],"type":"Point"}
}