{
  "type": "Feature",
  "properties": {
    "gn:admin1_code":"09",
    "gn:admin2_code":"0809",
    "gn:admin3_code":"80903.0",
    "gn:asciiname":"Peso",
    "gn:country_code":"PT",
    "gn:dem":487,
    "gn:feature_class":"P",
    "gn:feature_code":"PPL",
    "gn:name":"Peso",
    "gn:population":0,
    "gn:timezone":"Europe/Lisbon",
    "iso:country":"PT",
    "name:bel_x_preferred":[
        "\u041f\u0435\u0441\u0430"
    ],
    "name:bod_x_preferred":[
        "\u0f54\u0f7a\u0f0b\u0f66\u0f7c\u0f0d"
    ],
    "name:bre_x_preferred":[
        "Peso"
    ],
    "name:bul_x_preferred":[
        "\u041f\u0435\u0441\u043e"
    ],
    "name:cat_x_preferred":[
        "Peso"
    ],
    "name:ces_x_preferred":[
        "Peso"
    ],
    "name:dan_x_preferred":[
        "Peso"
    ],
    "name:deu_x_preferred":[
        "Peso"
    ],
    "name:epo_x_preferred":[
        "Peso"
    ],
    "name:eus_x_preferred":[
        "Peso"
    ],
    "name:fas_x_preferred":[
        "\u067e\u0632\u0648"
    ],
    "name:fin_x_preferred":[
        "Peso"
    ],
    "name:fra_x_preferred":[
        "Peso"
    ],
    "name:glg_x_preferred":[
        "Peso"
    ],
    "name:hat_x_preferred":[
        "Peso"
    ],
    "name:heb_x_preferred":[
        "\u05e4\u05e1\u05d5"
    ],
    "name:hrv_x_preferred":[
        "Pezo"
    ],
    "name:hun_x_preferred":[
        "Peso"
    ],
    "name:ind_x_preferred":[
        "Peso"
    ],
    "name:ita_x_preferred":[
        "Peso"
    ],
    "name:kat_x_preferred":[
        "\u10de\u10d4\u10e1\u10dd"
    ],
    "name:kir_x_preferred":[
        "\u041f\u0435\u0441\u043e"
    ],
    "name:lav_x_preferred":[
        "Peso"
    ],
    "name:mar_x_preferred":[
        "\u092a\u0947\u0938\u094b"
    ],
    "name:mkd_x_preferred":[
        "\u041a\u0430\u0442\u0435\u0433\u043e\u0440\u0438\u0458\u0430:\u041f\u0435\u0437\u043e\u0441"
    ],
    "name:msa_x_preferred":[
        "Peso"
    ],
    "name:nld_x_preferred":[
        "Peso"
    ],
    "name:nor_x_preferred":[
        "Peso"
    ],
    "name:oci_x_preferred":[
        "Peso"
    ],
    "name:pol_x_preferred":[
        "Peso"
    ],
    "name:por_x_preferred":[
        "Peso"
    ],
    "name:rus_x_preferred":[
        "\u041f\u0435\u0441\u043e"
    ],
    "name:sah_x_preferred":[
        "\u041f\u0435\u0441\u043e"
    ],
    "name:slv_x_preferred":[
        "Peso"
    ],
    "name:spa_x_preferred":[
        "Peso"
    ],
    "name:swe_x_preferred":[
        "Peso"
    ],
    "name:tgl_x_preferred":[
        "Piso"
    ],
    "name:tha_x_preferred":[
        "\u0e40\u0e1b\u0e42\u0e0b"
    ],
    "name:tur_x_preferred":[
        "Peso"
    ],
    "name:ukr_x_preferred":[
        "\u041f\u0435\u0441\u043e"
    ],
    "name:uzb_x_preferred":[
        "Peso"
    ],
    "name:zho_x_preferred":[
        "\u6bd4\u7d22"
    ],
    "wof:name":"Peso",
    "wof:placetype":"locality"
},
  "geometry": {"coordinates":[-8.56667,37.33333],"type":"Point"}
}