{
  "type": "Feature",
  "properties": {
    "gn:admin1_code":"18",
    "gn:admin2_code":"1413",
    "gn:admin3_code":"141303.0",
    "gn:asciiname":"Cardigos",
    "gn:country_code":"PT",
    "gn:dem":433,
    "gn:feature_class":"P",
    "gn:feature_code":"PPL",
    "gn:name":"Cardigos",
    "gn:population":0,
    "gn:timezone":"Europe/Lisbon",
    "iso:country":"PT",
    "wof:name":"Cardigos",
    "wof:placetype":"locality"
},
  "geometry": {"coordinates":[-8.02144,39.69506],"type":"Point"}
}