{
  "type": "Feature",
  "properties": {
    "gn:admin1_code":"09",
    "gn:admin2_code":"0802",
    "gn:admin3_code":"80203.0",
    "gn:asciiname":"Pessegueiro",
    "gn:country_code":"PT",
    "gn:dem":239,
    "gn:feature_class":"P",
    "gn:feature_code":"PPL",
    "gn:name":"Pessegueiro",
    "gn:population":0,
    "gn:timezone":"Europe/Lisbon",
    "iso:country":"PT",
    "wof:name":"Pessegueiro",
    "wof:placetype":"locality"
},
  "geometry": {"coordinates":[-7.84508,37.43055],"type":"Point"}
}