{
  "type": "Feature",
  "properties": {
    "gn:admin1_code":"4.0",
    "gn:admin2_code":"0302",
    "gn:admin3_code":"30247.0",
    "gn:asciiname":"Martim",
    "gn:country_code":"PT",
    "gn:dem":91,
    "gn:feature_class":"P",
    "gn:feature_code":"PPL",
    "gn:name":"Martim",
    "gn:population":0,
    "gn:timezone":"Europe/Lisbon",
    "iso:country":"PT",
    "name:ceb_x_preferred":[
        "Martim"
    ],
    "name:deu_x_preferred":[
        "Martim"
    ],
    "name:kaz_x_preferred":[
        "\u041c\u0430\u0440\u0442\u0438\u043d"
    ],
    "name:nld_x_preferred":[
        "Martim"
    ],
    "name:por_x_preferred":[
        "Martim"
    ],
    "name:rus_x_preferred":[
        "\u041c\u0430\u0440\u0442\u0438\u043d"
    ],
    "name:spa_x_preferred":[
        "Martim"
    ],
    "name:ukr_x_preferred":[
        "\u041c\u0430\u0440\u0442\u0456\u043d"
    ],
    "wof:name":"Martim",
    "wof:placetype":"locality"
},
  "geometry": {"coordinates":[-8.51916,41.53419],"type":"Point"}
}