{
  "type": "Feature",
  "properties": {
    "gn:admin1_code":"4.0",
    "gn:admin2_code":"0302",
    "gn:admin3_code":"30247.0",
    "gn:asciiname":"Martim",
    "gn:country_code":"PT",
    "gn:dem":91,
    "gn:feature_class":"P",
    "gn:feature_code":"PPL",
    "gn:name":"Martim",
    "gn:population":0,
    "gn:timezone":"Europe/Lisbon",
    "iso:country":"PT",
    "wof:name":"Martim",
    "wof:placetype":"locality"
},
  "geometry": {"coordinates":[-8.51916,41.53419],"type":"Point"}
}