{
  "type": "Feature",
  "properties": {
    "gn:admin1_code":"16",
    "gn:admin2_code":"1207",
    "gn:admin3_code":"120708.0",
    "gn:asciiname":"Sao Vicente",
    "gn:country_code":"PT",
    "gn:dem":357,
    "gn:feature_class":"P",
    "gn:feature_code":"PPL",
    "gn:name":"S\u00e3o Vicente",
    "gn:population":0,
    "gn:timezone":"Europe/Lisbon",
    "iso:country":"PT",
    "wof:name":"Sao Vicente",
    "wof:placetype":"locality"
},
  "geometry": {"coordinates":[-7.2127,38.95498],"type":"Point"}
}