{
  "type": "Feature",
  "properties": {
    "gn:admin1_code":"4.0",
    "gn:admin2_code":"0308",
    "gn:admin3_code":"30802.0",
    "gn:asciiname":"Arosa",
    "gn:country_code":"PT",
    "gn:dem":189,
    "gn:feature_class":"P",
    "gn:feature_code":"PPL",
    "gn:name":"Arosa",
    "gn:population":0,
    "gn:timezone":"Europe/Lisbon",
    "iso:country":"PT",
    "name:als_x_preferred":[
        "Arosa"
    ],
    "name:bul_x_preferred":[
        "\u0410\u0440\u043e\u0437\u0430"
    ],
    "name:cat_x_preferred":[
        "Arosa"
    ],
    "name:ces_x_preferred":[
        "Arosa"
    ],
    "name:dan_x_preferred":[
        "Arosa"
    ],
    "name:deu_x_preferred":[
        "Arosa"
    ],
    "name:epo_x_preferred":[
        "Arosa"
    ],
    "name:eus_x_preferred":[
        "Arosa"
    ],
    "name:fas_x_preferred":[
        "\u0627\u0631\u0648\u0632\u0627"
    ],
    "name:fin_x_preferred":[
        "Arosa"
    ],
    "name:fra_x_preferred":[
        "Arosa"
    ],
    "name:heb_x_preferred":[
        "\u05d0\u05e8\u05d5\u05d6\u05d4"
    ],
    "name:hrv_x_preferred":[
        "Arosa"
    ],
    "name:hun_x_preferred":[
        "Arosa"
    ],
    "name:ind_x_preferred":[
        "Arosa"
    ],
    "name:ita_x_preferred":[
        "Arosa"
    ],
    "name:jpn_x_preferred":[
        "\u30a2\u30ed\u30fc\u30b6"
    ],
    "name:kaz_x_preferred":[
        "\u0410\u0440\u043e\u0437\u0430"
    ],
    "name:kor_x_preferred":[
        "\uc544\ub85c\uc790"
    ],
    "name:lat_x_preferred":[
        "Araus"
    ],
    "name:lit_x_preferred":[
        "Aroza"
    ],
    "name:lmo_x_preferred":[
        "Arosa"
    ],
    "name:msa_x_preferred":[
        "Arosa"
    ],
    "name:nld_x_preferred":[
        "Arosa"
    ],
    "name:nno_x_preferred":[
        "Arosa"
    ],
    "name:pms_x_preferred":[
        "Arosa"
    ],
    "name:pol_x_preferred":[
        "Arosa"
    ],
    "name:por_x_preferred":[
        "Arosa"
    ],
    "name:roh_x_preferred":[
        "Arosa"
    ],
    "name:ron_x_preferred":[
        "Arosa"
    ],
    "name:rus_x_preferred":[
        "\u0410\u0440\u043e\u0437\u0430"
    ],
    "name:spa_x_preferred":[
        "Arosa"
    ],
    "name:sqi_x_preferred":[
        "Arosa"
    ],
    "name:swe_x_preferred":[
        "Arosa"
    ],
    "name:ukr_x_preferred":[
        "\u0410\u0440\u043e\u0437\u0430"
    ],
    "name:uzb_x_preferred":[
        "Arosa"
    ],
    "name:vol_x_preferred":[
        "Arosa"
    ],
    "name:war_x_preferred":[
        "Arosa"
    ],
    "name:zho_x_preferred":[
        "\u963f\u7f85\u85a9"
    ],
    "wof:name":"Arosa",
    "wof:placetype":"locality"
},
  "geometry": {"coordinates":[-8.21885,41.55178],"type":"Point"}
}