{
  "type": "Feature",
  "properties": {
    "gn:admin1_code":"10",
    "gn:admin2_code":"3110",
    "gn:admin3_code":"311001.0",
    "gn:asciiname":"Feiteiras",
    "gn:country_code":"PT",
    "gn:dem":429,
    "gn:feature_class":"P",
    "gn:feature_code":"PPL",
    "gn:name":"Feiteiras",
    "gn:population":0,
    "gn:timezone":"Atlantic/Madeira",
    "iso:country":"PT",
    "wof:name":"Feiteiras",
    "wof:placetype":"locality"
},
  "geometry": {"coordinates":[-16.98333,32.81667],"type":"Point"}
}