{
  "type": "Feature",
  "properties": {
    "gn:admin1_code":"16",
    "gn:admin2_code":"1206",
    "gn:admin3_code":"120602.0",
    "gn:asciiname":"Montes Novos",
    "gn:country_code":"PT",
    "gn:dem":261,
    "gn:feature_class":"P",
    "gn:feature_code":"PPL",
    "gn:name":"Montes Novos",
    "gn:population":0,
    "gn:timezone":"Europe/Lisbon",
    "iso:country":"PT",
    "wof:name":"Montes Novos",
    "wof:placetype":"locality"
},
  "geometry": {"coordinates":[-7.59506,39.22679],"type":"Point"}
}