{
  "type": "Feature",
  "properties": {
    "gn:admin1_code":"7.0",
    "gn:admin2_code":"0613",
    "gn:admin3_code":"61304.0",
    "gn:asciiname":"Paradela",
    "gn:country_code":"PT",
    "gn:dem":385,
    "gn:feature_class":"P",
    "gn:feature_code":"PPL",
    "gn:name":"Paradela",
    "gn:population":0,
    "gn:timezone":"Europe/Lisbon",
    "iso:country":"PT",
    "name:ceb_x_preferred":[
        "Paradela"
    ],
    "name:deu_x_preferred":[
        "Paradela"
    ],
    "name:glg_x_preferred":[
        "Paradela"
    ],
    "name:nld_x_preferred":[
        "Paradela"
    ],
    "name:pol_x_preferred":[
        "Paradela"
    ],
    "name:por_x_preferred":[
        "Paradela"
    ],
    "name:rus_x_preferred":[
        "\u041f\u0430\u0440\u0430\u0434\u0435\u043b\u0430"
    ],
    "name:spa_x_preferred":[
        "Paradela"
    ],
    "name:swe_x_preferred":[
        "Paradela"
    ],
    "name:tur_x_preferred":[
        "Paradela"
    ],
    "name:ukr_x_preferred":[
        "\u041f\u0430\u0440\u0430\u0434\u0435\u043b\u0430"
    ],
    "wof:name":"Paradela",
    "wof:placetype":"locality"
},
  "geometry": {"coordinates":[-8.33109,40.26665],"type":"Point"}
}