{
  "type": "Feature",
  "properties": {
    "gn:admin1_code":"06",
    "gn:admin2_code":"0509",
    "gn:admin3_code":"50910.0",
    "gn:asciiname":"Cardal Grande",
    "gn:country_code":"PT",
    "gn:dem":234,
    "gn:feature_class":"P",
    "gn:feature_code":"PPL",
    "gn:name":"Cardal Grande",
    "gn:population":0,
    "gn:timezone":"Europe/Lisbon",
    "iso:country":"PT",
    "wof:name":"Cardal Grande",
    "wof:placetype":"locality"
},
  "geometry": {"coordinates":[-8.2207,39.74927],"type":"Point"}
}