{
  "type": "Feature",
  "properties": {
    "gn:admin1_code":"14",
    "gn:admin2_code":"1108",
    "gn:admin3_code":"110801.0",
    "gn:asciiname":"Seixal",
    "gn:country_code":"PT",
    "gn:dem":34,
    "gn:feature_class":"P",
    "gn:feature_code":"PPL",
    "gn:name":"Seixal",
    "gn:population":0,
    "gn:timezone":"Europe/Lisbon",
    "iso:country":"PT",
    "wof:name":"Seixal",
    "wof:placetype":"locality"
},
  "geometry": {"coordinates":[-9.32318,39.26026],"type":"Point"}
}