{
  "type": "Feature",
  "properties": {
    "gn:admin1_code":"14",
    "gn:admin2_code":"1108",
    "gn:admin3_code":"110801.0",
    "gn:asciiname":"Seixal",
    "gn:country_code":"PT",
    "gn:dem":34,
    "gn:feature_class":"P",
    "gn:feature_code":"PPL",
    "gn:name":"Seixal",
    "gn:population":0,
    "gn:timezone":"Europe/Lisbon",
    "iso:country":"PT",
    "name:ara_x_preferred":[
        "\u0633\u064a\u0643\u0633\u0627\u0644"
    ],
    "name:cat_x_preferred":[
        "Seixal"
    ],
    "name:ceb_x_preferred":[
        "Seixal"
    ],
    "name:deu_x_preferred":[
        "Seixal"
    ],
    "name:epo_x_preferred":[
        "Seixal"
    ],
    "name:eus_x_preferred":[
        "Seixal"
    ],
    "name:fas_x_preferred":[
        "\u0633\u0626\u06cc\u0634\u0627\u0644"
    ],
    "name:fin_x_preferred":[
        "Seixal"
    ],
    "name:fra_x_preferred":[
        "Seixal"
    ],
    "name:glg_x_preferred":[
        "Seixal"
    ],
    "name:hye_x_preferred":[
        "\u054d\u0565\u0575\u0577\u0561\u056c"
    ],
    "name:ita_x_preferred":[
        "Seixal"
    ],
    "name:kat_x_preferred":[
        "\u10e1\u10d4\u10d8\u10e8\u10d0\u10da\u10d8"
    ],
    "name:lit_x_preferred":[
        "Sei\u0161alis"
    ],
    "name:mwl_x_preferred":[
        "Seixal"
    ],
    "name:mzn_x_preferred":[
        "\u0633\u0626\u06cc\u0634\u0627\u0644"
    ],
    "name:nld_x_preferred":[
        "Seixal"
    ],
    "name:oci_x_preferred":[
        "Seixal"
    ],
    "name:pol_x_preferred":[
        "Seixal"
    ],
    "name:por_x_preferred":[
        "Seixal"
    ],
    "name:ron_x_preferred":[
        "Seixal"
    ],
    "name:rus_x_preferred":[
        "\u0421\u0435\u0439\u0448\u0430\u043b"
    ],
    "name:spa_x_preferred":[
        "Seixal"
    ],
    "name:tur_x_preferred":[
        "Seixal"
    ],
    "name:ukr_x_preferred":[
        "\u0421\u0435\u0439\u0448\u0430\u043b"
    ],
    "name:vie_x_preferred":[
        "Seixal"
    ],
    "name:vol_x_preferred":[
        "Seixal"
    ],
    "name:war_x_preferred":[
        "Seixal"
    ],
    "name:zho_x_preferred":[
        "\u585e\u6c99\u723e"
    ],
    "wof:name":"Seixal",
    "wof:placetype":"locality"
},
  "geometry": {"coordinates":[-9.32318,39.26026],"type":"Point"}
}