{
  "type": "Feature",
  "properties": {
    "gn:admin1_code":"23.0",
    "gn:admin2_code":"4205",
    "gn:admin3_code":"420502.0",
    "gn:asciiname":"Criacao",
    "gn:cc2":"PT",
    "gn:country_code":"PT",
    "gn:dem":328,
    "gn:feature_class":"P",
    "gn:feature_code":"PPL",
    "gn:name":"Cria\u00e7\u00e3o",
    "gn:population":0,
    "gn:timezone":"Atlantic/Azores",
    "iso:country":"PT",
    "name:und_x_variant":[
        "Crea\u00e7\u00e3o",
        "Cria\u00e7\u00e3o"
    ],
    "wof:name":"Criacao",
    "wof:placetype":"locality"
},
  "geometry": {"coordinates":[-25.33333,37.83333],"type":"Point"}
}