{
  "type": "Feature",
  "properties": {
    "gn:admin1_code":"22.0",
    "gn:admin2_code":"1804",
    "gn:admin3_code":"180410.0",
    "gn:asciiname":"Fundoais",
    "gn:country_code":"PT",
    "gn:dem":320,
    "gn:feature_class":"P",
    "gn:feature_code":"PPL",
    "gn:name":"Fundoais",
    "gn:population":0,
    "gn:timezone":"Europe/Lisbon",
    "iso:country":"PT",
    "wof:name":"Fundoais",
    "wof:placetype":"locality"
},
  "geometry": {"coordinates":[-8.05961,41.07068],"type":"Point"}
}