{
  "type": "Feature",
  "properties": {
    "gn:admin1_code":"20",
    "gn:admin2_code":"1605",
    "gn:admin3_code":"160518.0",
    "gn:asciiname":"Resende",
    "gn:country_code":"PT",
    "gn:dem":477,
    "gn:feature_class":"P",
    "gn:feature_code":"PPL",
    "gn:name":"Resende",
    "gn:population":0,
    "gn:timezone":"Europe/Lisbon",
    "iso:country":"PT",
    "wof:name":"Resende",
    "wof:placetype":"locality"
},
  "geometry": {"coordinates":[-8.55747,41.90386],"type":"Point"}
}