{
  "type": "Feature",
  "properties": {
    "gn:admin1_code":"20",
    "gn:admin2_code":"1605",
    "gn:admin3_code":"160518.0",
    "gn:asciiname":"Resende",
    "gn:country_code":"PT",
    "gn:dem":477,
    "gn:feature_class":"P",
    "gn:feature_code":"PPL",
    "gn:name":"Resende",
    "gn:population":0,
    "gn:timezone":"Europe/Lisbon",
    "iso:country":"PT",
    "name:bpy_x_preferred":[
        "\u09b0\u09c7\u09b8\u09c7\u09a8\u09cd\u09a1\u09c7"
    ],
    "name:bre_x_preferred":[
        "Resende"
    ],
    "name:ceb_x_preferred":[
        "Resende"
    ],
    "name:deu_x_preferred":[
        "Resende"
    ],
    "name:fra_x_preferred":[
        "Resende"
    ],
    "name:ita_x_preferred":[
        "Resende"
    ],
    "name:mlg_x_preferred":[
        "Resende"
    ],
    "name:nld_x_preferred":[
        "Resende"
    ],
    "name:nor_x_preferred":[
        "Resende"
    ],
    "name:pol_x_preferred":[
        "Resende"
    ],
    "name:por_x_preferred":[
        "Resende"
    ],
    "name:rus_x_preferred":[
        "\u0420\u0435\u0437\u0435\u043d\u0434\u0435"
    ],
    "name:sco_x_preferred":[
        "Resende"
    ],
    "name:spa_x_preferred":[
        "Resende"
    ],
    "name:swe_x_preferred":[
        "Resende"
    ],
    "name:ukr_x_preferred":[
        "\u0420\u0435\u0437\u0435\u043d\u0434\u0435"
    ],
    "name:vie_x_preferred":[
        "Resende"
    ],
    "name:vol_x_preferred":[
        "Resende"
    ],
    "wof:name":"Resende",
    "wof:placetype":"locality"
},
  "geometry": {"coordinates":[-8.55747,41.90386],"type":"Point"}
}