{
  "type": "Feature",
  "properties": {
    "gn:admin1_code":"17.0",
    "gn:admin2_code":"1310",
    "gn:admin3_code":"131008.0",
    "gn:asciiname":"Barreiro",
    "gn:country_code":"PT",
    "gn:dem":177,
    "gn:feature_class":"P",
    "gn:feature_code":"PPL",
    "gn:name":"Barreiro",
    "gn:population":0,
    "gn:timezone":"Europe/Lisbon",
    "iso:country":"PT",
    "wof:name":"Barreiro",
    "wof:placetype":"locality"
},
  "geometry": {"coordinates":[-8.36008,41.1791],"type":"Point"}
}