{
  "type": "Feature",
  "properties": {
    "gn:admin1_code":"11.0",
    "gn:admin2_code":"0911",
    "gn:admin3_code":"91133.0",
    "gn:asciiname":"Caldeirinhas",
    "gn:country_code":"PT",
    "gn:dem":528,
    "gn:feature_class":"P",
    "gn:feature_code":"PPL",
    "gn:name":"Caldeirinhas",
    "gn:population":0,
    "gn:timezone":"Europe/Lisbon",
    "iso:country":"PT",
    "wof:name":"Caldeirinhas",
    "wof:placetype":"locality"
},
  "geometry": {"coordinates":[-7.2172,40.35467],"type":"Point"}
}