{
  "type": "Feature",
  "properties": {
    "gn:admin1_code":"4.0",
    "gn:admin2_code":"0309",
    "gn:admin3_code":"30927.0",
    "gn:asciiname":"Bustelos",
    "gn:country_code":"PT",
    "gn:dem":263,
    "gn:feature_class":"P",
    "gn:feature_code":"PPL",
    "gn:name":"Bustelos",
    "gn:population":0,
    "gn:timezone":"Europe/Lisbon",
    "iso:country":"PT",
    "wof:name":"Bustelos",
    "wof:placetype":"locality"
},
  "geometry": {"coordinates":[-8.20592,41.57389000000001],"type":"Point"}
}