{
  "type": "Feature",
  "properties": {
    "gn:admin1_code":"04",
    "gn:admin2_code":"0301",
    "gn:admin3_code":"30122.0",
    "gn:asciiname":"Seramil",
    "gn:country_code":"PT",
    "gn:dem":346,
    "gn:feature_class":"P",
    "gn:feature_code":"PPL",
    "gn:name":"Seramil",
    "gn:population":0,
    "gn:timezone":"Europe/Lisbon",
    "iso:country":"PT",
    "wof:name":"Seramil",
    "wof:placetype":"locality"
},
  "geometry": {"coordinates":[-8.31278,41.67216],"type":"Point"}
}