{
  "type": "Feature",
  "properties": {
    "gn:admin1_code":"19.0",
    "gn:admin2_code":"1511",
    "gn:admin3_code":"151101.0",
    "gn:asciiname":"Aiana de Cima",
    "gn:country_code":"PT",
    "gn:dem":102,
    "gn:feature_class":"P",
    "gn:feature_code":"PPL",
    "gn:name":"Aiana de Cima",
    "gn:population":0,
    "gn:timezone":"Europe/Lisbon",
    "iso:country":"PT",
    "wof:name":"Aiana de Cima",
    "wof:placetype":"locality"
},
  "geometry": {"coordinates":[-9.1426,38.47022],"type":"Point"}
}