{
  "type": "Feature",
  "properties": {
    "gn:admin1_code":"20.0",
    "gn:admin2_code":"1610",
    "gn:admin3_code":"161013.0",
    "gn:asciiname":"Cima de Vila",
    "gn:country_code":"PT",
    "gn:dem":278,
    "gn:feature_class":"P",
    "gn:feature_code":"PPL",
    "gn:name":"Cima de Vila",
    "gn:population":0,
    "gn:timezone":"Europe/Lisbon",
    "iso:country":"PT",
    "wof:name":"Cima de Vila",
    "wof:placetype":"locality"
},
  "geometry": {"coordinates":[-8.73351,41.90869],"type":"Point"}
}