{
  "type": "Feature",
  "properties": {
    "gn:admin1_code":"4.0",
    "gn:admin2_code":"0314",
    "gn:admin3_code":"31403.0",
    "gn:asciiname":"Cromil",
    "gn:country_code":"PT",
    "gn:dem":165,
    "gn:feature_class":"P",
    "gn:feature_code":"PPL",
    "gn:name":"Cromil",
    "gn:population":0,
    "gn:timezone":"Europe/Lisbon",
    "iso:country":"PT",
    "wof:name":"Cromil",
    "wof:placetype":"locality"
},
  "geometry": {"coordinates":[-8.31667,41.38333],"type":"Point"}
}