{
  "type": "Feature",
  "properties": {
    "gn:admin1_code":"07",
    "gn:admin2_code":"0601",
    "gn:admin3_code":"60110.0",
    "gn:asciiname":"Relva Velha",
    "gn:country_code":"PT",
    "gn:dem":751,
    "gn:feature_class":"P",
    "gn:feature_code":"PPL",
    "gn:name":"Relva Velha",
    "gn:population":0,
    "gn:timezone":"Europe/Lisbon",
    "iso:country":"PT",
    "wof:name":"Relva Velha",
    "wof:placetype":"locality"
},
  "geometry": {"coordinates":[-7.90578,40.2174],"type":"Point"}
}