{
  "type": "Feature",
  "properties": {
    "gn:admin1_code":"08",
    "gn:admin2_code":"0702",
    "gn:admin3_code":"70201.0",
    "gn:asciiname":"Santana do Campo",
    "gn:country_code":"PT",
    "gn:dem":255,
    "gn:feature_class":"P",
    "gn:feature_code":"PPL",
    "gn:name":"Santana do Campo",
    "gn:population":0,
    "gn:timezone":"Europe/Lisbon",
    "iso:country":"PT",
    "wof:name":"Santana do Campo",
    "wof:placetype":"locality"
},
  "geometry": {"coordinates":[-8.03192,38.76737],"type":"Point"}
}