{
  "type": "Feature",
  "properties": {
    "gn:admin1_code":"14",
    "gn:admin2_code":"1101",
    "gn:admin3_code":"110107.0",
    "gn:asciiname":"Findal",
    "gn:country_code":"PT",
    "gn:dem":182,
    "gn:feature_class":"P",
    "gn:feature_code":"PPL",
    "gn:name":"Findal",
    "gn:population":0,
    "gn:timezone":"Europe/Lisbon",
    "iso:country":"PT",
    "wof:name":"Findal",
    "wof:placetype":"locality"
},
  "geometry": {"coordinates":[-9.02463,39.08722],"type":"Point"}
}