{
  "type": "Feature",
  "properties": {
    "gn:admin1_code":"17",
    "gn:admin2_code":"1302",
    "gn:admin3_code":"130219.0",
    "gn:asciiname":"Urgueira",
    "gn:country_code":"PT",
    "gn:dem":563,
    "gn:feature_class":"P",
    "gn:feature_code":"PPL",
    "gn:name":"Urgueira",
    "gn:population":0,
    "gn:timezone":"Europe/Lisbon",
    "iso:country":"PT",
    "wof:name":"Urgueira",
    "wof:placetype":"locality"
},
  "geometry": {"coordinates":[-7.96167,41.14919],"type":"Point"}
}