{
  "type": "Feature",
  "properties": {
    "gn:admin1_code":"2.0",
    "gn:admin2_code":"0108",
    "gn:admin3_code":"10801.0",
    "gn:asciiname":"Paredes",
    "gn:country_code":"PT",
    "gn:dem":19,
    "gn:feature_class":"P",
    "gn:feature_code":"PPL",
    "gn:name":"Paredes",
    "gn:population":0,
    "gn:timezone":"Europe/Lisbon",
    "iso:country":"PT",
    "wof:name":"Paredes",
    "wof:placetype":"locality"
},
  "geometry": {"coordinates":[-8.58334,40.80831],"type":"Point"}
}