{
  "type": "Feature",
  "properties": {
    "gn:admin1_code":"19",
    "gn:admin2_code":"1507",
    "gn:admin3_code":"150701.0",
    "gn:asciiname":"Escatelar",
    "gn:country_code":"PT",
    "gn:dem":60,
    "gn:feature_class":"P",
    "gn:feature_code":"PPL",
    "gn:name":"Escatelar",
    "gn:population":0,
    "gn:timezone":"Europe/Lisbon",
    "iso:country":"PT",
    "wof:name":"Escatelar",
    "wof:placetype":"locality"
},
  "geometry": {"coordinates":[-8.58325,38.75345],"type":"Point"}
}