{
  "type": "Feature",
  "properties": {
    "gn:admin1_code":"04",
    "gn:admin2_code":"0307",
    "gn:admin3_code":"30719.0",
    "gn:asciiname":"Sao Vicente de Passos",
    "gn:country_code":"PT",
    "gn:dem":410,
    "gn:feature_class":"P",
    "gn:feature_code":"PPL",
    "gn:name":"S\u00e3o Vicente de Passos",
    "gn:population":0,
    "gn:timezone":"Europe/Lisbon",
    "iso:country":"PT",
    "wof:name":"Sao Vicente de Passos",
    "wof:placetype":"locality"
},
  "geometry": {"coordinates":[-8.19843,41.48029],"type":"Point"}
}