{
  "type": "Feature",
  "properties": {
    "gn:admin1_code":"20",
    "gn:admin2_code":"1603",
    "gn:admin3_code":"160310.0",
    "gn:asciiname":"Vinhas",
    "gn:country_code":"PT",
    "gn:dem":177,
    "gn:feature_class":"P",
    "gn:feature_code":"PPL",
    "gn:name":"Vinhas",
    "gn:population":0,
    "gn:timezone":"Europe/Lisbon",
    "iso:country":"PT",
    "wof:name":"Vinhas",
    "wof:placetype":"locality"
},
  "geometry": {"coordinates":[-8.22387,42.12919],"type":"Point"}
}