{
  "type": "Feature",
  "properties": {
    "gn:admin1_code":"07",
    "gn:admin2_code":"0615",
    "gn:admin3_code":"61507.0",
    "gn:asciiname":"Cotas",
    "gn:country_code":"PT",
    "gn:dem":347,
    "gn:feature_class":"P",
    "gn:feature_code":"PPL",
    "gn:name":"Cotas",
    "gn:population":0,
    "gn:timezone":"Europe/Lisbon",
    "iso:country":"PT",
    "wof:name":"Cotas",
    "wof:placetype":"locality"
},
  "geometry": {"coordinates":[-8.48686,40.00574],"type":"Point"}
}