{
  "type": "Feature",
  "properties": {
    "gn:admin1_code":"07",
    "gn:admin2_code":"0617",
    "gn:admin3_code":"61701.0",
    "gn:asciiname":"Terreiros de Alem",
    "gn:country_code":"PT",
    "gn:dem":391,
    "gn:feature_class":"P",
    "gn:feature_code":"PPL",
    "gn:name":"Terreiros de Al\u00e9m",
    "gn:population":0,
    "gn:timezone":"Europe/Lisbon",
    "iso:country":"PT",
    "wof:name":"Terreiros de Alem",
    "wof:placetype":"locality"
},
  "geometry": {"coordinates":[-8.31454,40.21452],"type":"Point"}
}