{
  "type": "Feature",
  "properties": {
    "gn:admin1_code":"16",
    "gn:admin2_code":"1214",
    "gn:admin3_code":"121402.0",
    "gn:asciiname":"Vale de Monteiro",
    "gn:country_code":"PT",
    "gn:dem":457,
    "gn:feature_class":"P",
    "gn:feature_code":"PPL",
    "gn:name":"Vale de Monteiro",
    "gn:population":0,
    "gn:timezone":"Europe/Lisbon",
    "iso:country":"PT",
    "wof:name":"Vale de Monteiro",
    "wof:placetype":"locality"
},
  "geometry": {"coordinates":[-7.30465,39.20569],"type":"Point"}
}