{
  "type": "Feature",
  "properties": {
    "gn:admin1_code":"03",
    "gn:admin2_code":"0209",
    "gn:admin3_code":"20907.0",
    "gn:asciiname":"Alcaria Longa",
    "gn:country_code":"PT",
    "gn:dem":185,
    "gn:feature_class":"P",
    "gn:feature_code":"PPL",
    "gn:name":"Alcaria Longa",
    "gn:population":0,
    "gn:timezone":"Europe/Lisbon",
    "iso:country":"PT",
    "wof:name":"Alcaria Longa",
    "wof:placetype":"locality"
},
  "geometry": {"coordinates":[-7.86171,37.56053],"type":"Point"}
}