{
  "type": "Feature",
  "properties": {
    "gn:admin1_code":"18",
    "gn:admin2_code":"1409",
    "gn:admin3_code":"140903.0",
    "gn:asciiname":"Pissilgais",
    "gn:country_code":"PT",
    "gn:dem":148,
    "gn:feature_class":"P",
    "gn:feature_code":"PPL",
    "gn:name":"Pissilgais",
    "gn:population":0,
    "gn:timezone":"Europe/Lisbon",
    "iso:country":"PT",
    "wof:name":"Pissilgais",
    "wof:placetype":"locality"
},
  "geometry": {"coordinates":[-8.41893,39.09906],"type":"Point"}
}