{
  "type": "Feature",
  "properties": {
    "gn:admin1_code":"17",
    "gn:admin2_code":"1317",
    "gn:admin3_code":"131722.0",
    "gn:asciiname":"Tartomil",
    "gn:country_code":"PT",
    "gn:dem":43,
    "gn:feature_class":"P",
    "gn:feature_code":"PPL",
    "gn:name":"Tartomil",
    "gn:population":0,
    "gn:timezone":"Europe/Lisbon",
    "iso:country":"PT",
    "wof:name":"Tartomil",
    "wof:placetype":"locality"
},
  "geometry": {"coordinates":[-8.64235,41.09347],"type":"Point"}
}