{
  "type": "Feature",
  "properties": {
    "gn:admin1_code":"20.0",
    "gn:admin2_code":"1603",
    "gn:admin3_code":"160307.0",
    "gn:asciiname":"Aldeia",
    "gn:country_code":"PT",
    "gn:dem":545,
    "gn:feature_class":"P",
    "gn:feature_code":"PPL",
    "gn:name":"Aldeia",
    "gn:population":0,
    "gn:timezone":"Europe/Lisbon",
    "iso:country":"PT",
    "wof:name":"Aldeia",
    "wof:placetype":"locality"
},
  "geometry": {"coordinates":[-8.19532,42.10847],"type":"Point"}
}