{
  "type": "Feature",
  "properties": {
    "gn:admin1_code":"03",
    "gn:admin2_code":"0212",
    "gn:admin3_code":"21201.0",
    "gn:asciiname":"Alcarias",
    "gn:country_code":"PT",
    "gn:dem":200,
    "gn:feature_class":"P",
    "gn:feature_code":"PPL",
    "gn:name":"Alcarias",
    "gn:population":0,
    "gn:timezone":"Europe/Lisbon",
    "iso:country":"PT",
    "wof:name":"Alcarias",
    "wof:placetype":"locality"
},
  "geometry": {"coordinates":[-8.22518,37.77873],"type":"Point"}
}