{
  "type": "Feature",
  "properties": {
    "gn:admin1_code":"20.0",
    "gn:admin2_code":"1602",
    "gn:admin3_code":"160205.0",
    "gn:asciiname":"Colarinha",
    "gn:country_code":"PT",
    "gn:dem":20,
    "gn:feature_class":"P",
    "gn:feature_code":"PPL",
    "gn:name":"Colarinha",
    "gn:population":0,
    "gn:timezone":"Europe/Lisbon",
    "iso:country":"PT",
    "wof:name":"Colarinha",
    "wof:placetype":"locality"
},
  "geometry": {"coordinates":[-8.79389,41.86305],"type":"Point"}
}