{
  "type": "Feature",
  "properties": {
    "gn:country":"PT",
    "gn:fcode":"PPL",
    "gn:population":0,
    "iso:country":"PT",
    "name:ast_x_preferred":[
        "Constantim"
    ],
    "name:ceb_x_preferred":[
        "Constantim"
    ],
    "name:deu_x_preferred":[
        "Constantim"
    ],
    "name:eng_x_preferred":[
        "Constantim"
    ],
    "name:fra_x_preferred":[
        "Constantim"
    ],
    "name:kaz_x_preferred":[
        "\u041a\u043e\u043d\u0448\u0442\u0430\u043d\u0442\u0438\u043d"
    ],
    "name:mwl_x_preferred":[
        "Custantin"
    ],
    "name:nan_x_preferred":[
        "Constantim"
    ],
    "name:nld_x_preferred":[
        "Constantim"
    ],
    "name:por_x_preferred":[
        "Constantim"
    ],
    "name:rus_x_preferred":[
        "\u041a\u043e\u043d\u0448\u0442\u0430\u043d\u0442\u0438\u043d"
    ],
    "name:spa_x_preferred":[
        "Constantim"
    ],
    "name:ukr_x_preferred":[
        "\u041a\u043e\u043d\u0448\u0442\u0430\u043d\u0442\u0456\u043d"
    ],
    "name:zho_x_preferred":[
        "\u5eb7\u65af\u5766\u4e01"
    ],
    "qs_pg:aaroncc":"PT",
    "qs_pg:gn_country":"PT",
    "qs_pg:gn_fcode":"PPL",
    "qs_pg:gn_pop":0,
    "qs_pg:name":"Constantim",
    "qs_pg:name_adm0":"Portugal",
    "qs_pg:name_adm1":"Bragan\u00e7a",
    "qs_pg:photos":19,
    "qs_pg:photos_1k":4,
    "qs_pg:photos_9k":1,
    "qs_pg:photos_9r":1,
    "qs_pg:photos_all":19,
    "qs_pg:photos_sr":1,
    "qs_pg:pop_sr":0,
    "qs_pg:qs_pg_placetype":"locality",
    "qs_pg:qs_pg_placetype_gp":"Town",
    "qs_pg:woe_adm0":23424925,
    "woe:adm0_id":23424925,
    "woe:name_adm0":"Portugal",
    "woe:name_adm1":"Bragan\u00e7a",
    "woe:placetype":"Town",
    "wof:name":"Constantim",
    "wof:placetype":"locality"
},
  "geometry": {"coordinates":[-6.27492,41.62254],"type":"Point"}
}