{
  "type": "Feature",
  "properties": {
    "gn:country":"PT",
    "gn:fcode":"PPL",
    "gn:population":7870,
    "iso:country":"PT",
    "name:ceb_x_preferred":[
        "Ferreiros"
    ],
    "name:deu_x_preferred":[
        "Ferreiros"
    ],
    "name:fra_x_preferred":[
        "Ferreiros"
    ],
    "name:glg_x_preferred":[
        "Ferreiros"
    ],
    "name:nld_x_preferred":[
        "Ferreiros"
    ],
    "name:por_x_preferred":[
        "Ferreiros"
    ],
    "name:rus_x_preferred":[
        "\u0424\u0435\u0440\u0440\u0435\u0439\u0440\u0443\u0448"
    ],
    "name:spa_x_preferred":[
        "Ferreiros"
    ],
    "name:swe_x_preferred":[
        "Ferreiros"
    ],
    "name:ukr_x_preferred":[
        "\u0424\u0435\u0440\u0440\u0435\u0439\u0440\u0443\u0448"
    ],
    "qs_pg:aaroncc":"PT",
    "qs_pg:gn_country":"PT",
    "qs_pg:gn_fcode":"PPL",
    "qs_pg:gn_pop":7870,
    "qs_pg:name":"Ferreiros",
    "qs_pg:name_adm0":"Portugal",
    "qs_pg:name_adm1":"Porto",
    "qs_pg:photos_9r":0,
    "qs_pg:photos_sr":0,
    "qs_pg:pop_sr":5,
    "qs_pg:qs_pg_placetype":"locality",
    "qs_pg:qs_pg_placetype_gp":"Town",
    "qs_pg:woe_adm0":23424925,
    "woe:adm0_id":23424925,
    "woe:name_adm0":"Portugal",
    "woe:name_adm1":"Porto",
    "woe:placetype":"Town",
    "wof:name":"Ferreiros",
    "wof:placetype":"locality",
    "wof:population":7870
},
  "geometry": {"coordinates":[-8.55,41.35],"type":"Point"}
}