{
  "type": "Feature",
  "properties": {
    "gn:admin1_code":"19",
    "gn:admin2_code":"1509",
    "gn:admin3_code":"150903.0",
    "gn:asciiname":"Pontao",
    "gn:country_code":"PT",
    "gn:dem":156,
    "gn:feature_class":"P",
    "gn:feature_code":"PPL",
    "gn:name":"Pont\u00e3o",
    "gn:population":0,
    "gn:timezone":"Europe/Lisbon",
    "iso:country":"PT",
    "wof:name":"Pontao",
    "wof:placetype":"locality"
},
  "geometry": {"coordinates":[-8.68089,37.80537],"type":"Point"}
}