{
  "type": "Feature",
  "properties": {
    "gn:admin1_code":"21.0",
    "gn:admin2_code":"1703",
    "gn:admin3_code":"170305.0",
    "gn:asciiname":"Bustelo",
    "gn:country_code":"PT",
    "gn:dem":466,
    "gn:feature_class":"P",
    "gn:feature_code":"PPL",
    "gn:name":"Bustelo",
    "gn:population":0,
    "gn:timezone":"Europe/Lisbon",
    "iso:country":"PT",
    "name:ceb_x_preferred":[
        "Bustelo"
    ],
    "name:deu_x_preferred":[
        "Bustelo"
    ],
    "name:fra_x_preferred":[
        "Bustelo"
    ],
    "name:glg_x_preferred":[
        "Bustelo"
    ],
    "name:nld_x_preferred":[
        "Bustelo"
    ],
    "name:por_x_preferred":[
        "Bustelo"
    ],
    "wof:name":"Bustelo",
    "wof:placetype":"locality"
},
  "geometry": {"coordinates":[-7.49088,41.78926],"type":"Point"}
}