{
  "type": "Feature",
  "properties": {
    "iso:country":"PT",
    "qs_pg:aaroncc":"PT",
    "qs_pg:name":"Quinta Das Salinas",
    "qs_pg:name_adm0":"Portugal",
    "qs_pg:name_adm1":"Faro",
    "qs_pg:photos":287,
    "qs_pg:photos_1k":58,
    "qs_pg:photos_9k":1,
    "qs_pg:photos_9r":4,
    "qs_pg:photos_all":287,
    "qs_pg:photos_sr":5,
    "qs_pg:pop_sr":0,
    "qs_pg:qs_pg_placetype":"locality",
    "qs_pg:qs_pg_placetype_gp":"Town",
    "qs_pg:woe_adm0":23424925,
    "woe:adm0_id":23424925,
    "woe:name_adm0":"Portugal",
    "woe:name_adm1":"Faro",
    "woe:placetype":"Town",
    "wof:name":"Quinta Das Salinas",
    "wof:placetype":"locality"
},
  "geometry": {"coordinates":[-8.039578,37.034419],"type":"Point"}
}