{
  "type": "Feature",
  "properties": {
    "gn:admin1_code":"18",
    "gn:admin2_code":"1411",
    "gn:admin3_code":"141102.0",
    "gn:asciiname":"Vila Verde",
    "gn:country_code":"PT",
    "gn:dem":225,
    "gn:feature_class":"P",
    "gn:feature_code":"PPL",
    "gn:name":"Vila Verde",
    "gn:population":0,
    "gn:timezone":"Europe/Lisbon",
    "iso:country":"PT",
    "wof:name":"Vila Verde",
    "wof:placetype":"locality"
},
  "geometry": {"coordinates":[-8.36266,39.73545],"type":"Point"}
}