{
  "type": "Feature",
  "properties": {
    "gn:admin1_code":"18",
    "gn:admin2_code":"1407",
    "gn:admin3_code":"140702.0",
    "gn:asciiname":"Chouto",
    "gn:country_code":"PT",
    "gn:dem":120,
    "gn:feature_class":"P",
    "gn:feature_code":"PPL",
    "gn:name":"Chouto",
    "gn:population":0,
    "gn:timezone":"Europe/Lisbon",
    "iso:country":"PT",
    "wof:name":"Chouto",
    "wof:placetype":"locality"
},
  "geometry": {"coordinates":[-8.35038,39.27072],"type":"Point"}
}