{
  "type": "Feature",
  "properties": {
    "gn:admin1_code":"16",
    "gn:admin2_code":"1211",
    "gn:admin3_code":"121102.0",
    "gn:asciiname":"Senhora dos Prazeres",
    "gn:country_code":"PT",
    "gn:dem":273,
    "gn:feature_class":"P",
    "gn:feature_code":"PPL",
    "gn:name":"Senhora dos Prazeres",
    "gn:population":0,
    "gn:timezone":"Europe/Lisbon",
    "iso:country":"PT",
    "wof:name":"Senhora dos Prazeres",
    "wof:placetype":"locality"
},
  "geometry": {"coordinates":[-7.42064,38.98483],"type":"Point"}
}