{
  "type": "Feature",
  "properties": {
    "gn:admin1_code":"22.0",
    "gn:admin2_code":"1805",
    "gn:admin3_code":"180521.0",
    "gn:asciiname":"Balsemao",
    "gn:country_code":"PT",
    "gn:dem":287,
    "gn:feature_class":"P",
    "gn:feature_code":"PPL",
    "gn:name":"Balsem\u00e3o",
    "gn:population":0,
    "gn:timezone":"Europe/Lisbon",
    "iso:country":"PT",
    "wof:name":"Balsemao",
    "wof:placetype":"locality"
},
  "geometry": {"coordinates":[-7.78313,41.1069],"type":"Point"}
}