{
  "type": "Feature",
  "properties": {
    "gn:admin1_code":"03",
    "gn:admin2_code":"0206",
    "gn:admin3_code":"20603.0",
    "gn:asciiname":"Entradas",
    "gn:country_code":"PT",
    "gn:dem":174,
    "gn:feature_class":"P",
    "gn:feature_code":"PPL",
    "gn:name":"Entradas",
    "gn:population":0,
    "gn:timezone":"Europe/Lisbon",
    "iso:country":"PT",
    "name:ceb_x_preferred":[
        "Entradas"
    ],
    "name:deu_x_preferred":[
        "Entradas"
    ],
    "name:kaz_x_preferred":[
        "\u042d\u043d\u0442\u0440\u0430\u0434\u0430\u0448"
    ],
    "name:nld_x_preferred":[
        "Entradas"
    ],
    "name:por_x_preferred":[
        "Entradas"
    ],
    "name:rus_x_preferred":[
        "\u042d\u043d\u0442\u0440\u0430\u0434\u0430\u0448"
    ],
    "name:spa_x_preferred":[
        "Entradas"
    ],
    "name:ukr_x_preferred":[
        "\u0415\u043d\u0442\u0440\u0430\u0434\u0430\u0448"
    ],
    "name:zho_x_preferred":[
        "\u6069\u7279\u62c9\u8fbe\u4ec0"
    ],
    "wof:name":"Entradas",
    "wof:placetype":"locality"
},
  "geometry": {"coordinates":[-8.0141,37.77443],"type":"Point"}
}