{
  "type": "Feature",
  "properties": {
    "gn:admin1_code":"21.0",
    "gn:admin2_code":"1702",
    "gn:admin3_code":"170214.0",
    "gn:asciiname":"Agrelos",
    "gn:country_code":"PT",
    "gn:dem":785,
    "gn:feature_class":"P",
    "gn:feature_code":"PPL",
    "gn:name":"Agrelos",
    "gn:population":0,
    "gn:timezone":"Europe/Lisbon",
    "iso:country":"PT",
    "wof:name":"Agrelos",
    "wof:placetype":"locality"
},
  "geometry": {"coordinates":[-7.80752,41.65837],"type":"Point"}
}