{
  "type": "Feature",
  "properties": {
    "gn:admin1_code":"16",
    "gn:admin2_code":"1211",
    "gn:admin3_code":"121104.0",
    "gn:asciiname":"Quinta de Santo Antonio",
    "gn:country_code":"PT",
    "gn:dem":295,
    "gn:feature_class":"P",
    "gn:feature_code":"PPL",
    "gn:name":"Quinta de Santo Ant\u00f3nio",
    "gn:population":0,
    "gn:timezone":"Europe/Lisbon",
    "iso:country":"PT",
    "wof:name":"Quinta de Santo Antonio",
    "wof:placetype":"locality"
},
  "geometry": {"coordinates":[-7.46773,39.08453],"type":"Point"}
}