{
  "type": "Feature",
  "properties": {
    "gn:admin1_code":"18",
    "gn:admin2_code":"1421",
    "gn:admin3_code":"142110.0",
    "gn:asciiname":"Casais dos Montes",
    "gn:country_code":"PT",
    "gn:dem":241,
    "gn:feature_class":"P",
    "gn:feature_code":"PPL",
    "gn:name":"Casais dos Montes",
    "gn:population":0,
    "gn:timezone":"Europe/Lisbon",
    "iso:country":"PT",
    "wof:name":"Casais dos Montes",
    "wof:placetype":"locality"
},
  "geometry": {"coordinates":[-8.59243,39.71708],"type":"Point"}
}