{
  "type": "Feature",
  "properties": {
    "gn:admin1_code":"10",
    "gn:admin2_code":"3108",
    "gn:admin3_code":"310805.0",
    "gn:asciiname":"Sao Pedro",
    "gn:country_code":"PT",
    "gn:dem":337,
    "gn:feature_class":"P",
    "gn:feature_code":"PPL",
    "gn:name":"S\u00e3o Pedro",
    "gn:population":0,
    "gn:timezone":"Atlantic/Madeira",
    "iso:country":"PT",
    "name:und_x_variant":[
        "S\u00e3o Pedro"
    ],
    "wof:name":"Sao Pedro",
    "wof:placetype":"locality"
},
  "geometry": {"coordinates":[-16.80373,32.6847],"type":"Point"}
}