{
  "type": "Feature",
  "properties": {
    "gn:admin1_code":"10",
    "gn:admin2_code":"3108",
    "gn:admin3_code":"310805.0",
    "gn:asciiname":"Sao Pedro",
    "gn:country_code":"PT",
    "gn:dem":337,
    "gn:feature_class":"P",
    "gn:feature_code":"PPL",
    "gn:name":"S\u00e3o Pedro",
    "gn:population":0,
    "gn:timezone":"Atlantic/Madeira",
    "iso:country":"PT",
    "name:deu_x_preferred":[
        "S\u00e3o Pedro"
    ],
    "name:fra_x_preferred":[
        "S\u00e3o Pedro"
    ],
    "name:kaz_x_preferred":[
        "\u0421\u0430\u043d-\u041f\u0435\u0434\u0440\u0443"
    ],
    "name:nld_x_preferred":[
        "S\u00e3o Pedro"
    ],
    "name:por_x_preferred":[
        "S\u00e3o Pedro"
    ],
    "name:rus_x_preferred":[
        "\u0421\u0430\u043d-\u041f\u0435\u0434\u0440\u0443"
    ],
    "wof:name":"Sao Pedro",
    "wof:placetype":"locality"
},
  "geometry": {"coordinates":[-16.80373,32.6847],"type":"Point"}
}