{
  "type": "Feature",
  "properties": {
    "gn:admin1_code":"07",
    "gn:admin2_code":"0610",
    "gn:admin3_code":"61001.0",
    "gn:asciiname":"Presalves",
    "gn:country_code":"PT",
    "gn:dem":70,
    "gn:feature_class":"P",
    "gn:feature_code":"PPL",
    "gn:name":"Presalves",
    "gn:population":0,
    "gn:timezone":"Europe/Lisbon",
    "iso:country":"PT",
    "wof:name":"Presalves",
    "wof:placetype":"locality"
},
  "geometry": {"coordinates":[-8.7333,40.1412],"type":"Point"}
}