{
  "type": "Feature",
  "properties": {
    "gn:admin1_code":"04",
    "gn:admin2_code":"0307",
    "gn:admin3_code":"30732.0",
    "gn:asciiname":"Vilarelhe",
    "gn:country_code":"PT",
    "gn:dem":362,
    "gn:feature_class":"P",
    "gn:feature_code":"PPL",
    "gn:name":"Vilarelhe",
    "gn:population":0,
    "gn:timezone":"Europe/Lisbon",
    "iso:country":"PT",
    "wof:name":"Vilarelhe",
    "wof:placetype":"locality"
},
  "geometry": {"coordinates":[-8.18995,41.53182],"type":"Point"}
}