{
  "type": "Feature",
  "properties": {
    "gn:admin1_code":"07",
    "gn:admin2_code":"0611",
    "gn:admin3_code":"61105.0",
    "gn:asciiname":"Povoa de Sao Cosme",
    "gn:country_code":"PT",
    "gn:dem":350,
    "gn:feature_class":"P",
    "gn:feature_code":"PPL",
    "gn:name":"P\u00f3voa de S\u00e3o Cosme",
    "gn:population":0,
    "gn:timezone":"Europe/Lisbon",
    "iso:country":"PT",
    "wof:name":"Povoa de Sao Cosme",
    "wof:placetype":"locality"
},
  "geometry": {"coordinates":[-7.90284,40.43963],"type":"Point"}
}