{
  "type": "Feature",
  "properties": {
    "gn:admin1_code":"20",
    "gn:admin2_code":"1605",
    "gn:admin3_code":"160519.0",
    "gn:asciiname":"Veiga do Monte",
    "gn:country_code":"PT",
    "gn:dem":281,
    "gn:feature_class":"P",
    "gn:feature_code":"PPL",
    "gn:name":"Veiga do Monte",
    "gn:population":0,
    "gn:timezone":"Europe/Lisbon",
    "iso:country":"PT",
    "wof:name":"Veiga do Monte",
    "wof:placetype":"locality"
},
  "geometry": {"coordinates":[-8.62429,41.85258],"type":"Point"}
}