{
  "type": "Feature",
  "properties": {
    "gn:admin1_code":"7.0",
    "gn:admin2_code":"0605",
    "gn:admin3_code":"60517.0",
    "gn:asciiname":"Atouguia",
    "gn:country_code":"PT",
    "gn:dem":21,
    "gn:feature_class":"P",
    "gn:feature_code":"PPL",
    "gn:name":"Atouguia",
    "gn:population":0,
    "gn:timezone":"Europe/Lisbon",
    "iso:country":"PT",
    "wof:name":"Atouguia",
    "wof:placetype":"locality"
},
  "geometry": {"coordinates":[-8.74795,40.05543],"type":"Point"}
}