{
  "type": "Feature",
  "properties": {
    "gn:admin1_code":"02",
    "gn:admin2_code":"0109",
    "gn:admin3_code":"10921.0",
    "gn:asciiname":"Santo Antonio",
    "gn:country_code":"PT",
    "gn:dem":112,
    "gn:feature_class":"P",
    "gn:feature_code":"PPL",
    "gn:name":"Santo Ant\u00f3nio",
    "gn:population":0,
    "gn:timezone":"Europe/Lisbon",
    "iso:country":"PT",
    "wof:name":"Santo Antonio",
    "wof:placetype":"locality"
},
  "geometry": {"coordinates":[-8.58544,40.96005],"type":"Point"}
}