{
  "type": "Feature",
  "properties": {
    "gn:admin1_code":"07",
    "gn:admin2_code":"0601",
    "gn:admin3_code":"60110.0",
    "gn:asciiname":"Valadinho",
    "gn:country_code":"PT",
    "gn:dem":529,
    "gn:feature_class":"P",
    "gn:feature_code":"PPL",
    "gn:name":"Valadinho",
    "gn:population":0,
    "gn:timezone":"Europe/Lisbon",
    "iso:country":"PT",
    "wof:name":"Valadinho",
    "wof:placetype":"locality"
},
  "geometry": {"coordinates":[-7.9056,40.24484],"type":"Point"}
}