{
  "type": "Feature",
  "properties": {
    "gn:admin1_code":"4.0",
    "gn:admin2_code":"0305",
    "gn:admin3_code":"30503.0",
    "gn:asciiname":"Cabanelas",
    "gn:country_code":"PT",
    "gn:dem":603,
    "gn:feature_class":"P",
    "gn:feature_code":"PPL",
    "gn:name":"Cabanelas",
    "gn:population":0,
    "gn:timezone":"Europe/Lisbon",
    "iso:country":"PT",
    "wof:name":"Cabanelas",
    "wof:placetype":"locality"
},
  "geometry": {"coordinates":[-8.10318,41.3861],"type":"Point"}
}