{
  "type": "Feature",
  "properties": {
    "gn:admin1_code":"16",
    "gn:admin2_code":"1207",
    "gn:admin3_code":"120708.0",
    "gn:asciiname":"Monte do Mestre",
    "gn:country_code":"PT",
    "gn:dem":377,
    "gn:feature_class":"P",
    "gn:feature_code":"PPL",
    "gn:name":"Monte do Mestre",
    "gn:population":0,
    "gn:timezone":"Europe/Lisbon",
    "iso:country":"PT",
    "wof:name":"Monte do Mestre",
    "wof:placetype":"locality"
},
  "geometry": {"coordinates":[-7.21667,38.95],"type":"Point"}
}