{
  "type": "Feature",
  "properties": {
    "gn:admin1_code":"20.0",
    "gn:admin2_code":"1603",
    "gn:admin3_code":"160302.0",
    "gn:asciiname":"Vila",
    "gn:country_code":"PT",
    "gn:dem":945,
    "gn:feature_class":"P",
    "gn:feature_code":"PPLA3",
    "gn:name":"Vila",
    "gn:population":0,
    "gn:timezone":"Europe/Lisbon",
    "iso:country":"PT",
    "name:bre_x_preferred":[
        "Vila"
    ],
    "name:cat_x_preferred":[
        "Vila"
    ],
    "name:ceb_x_preferred":[
        "Vila"
    ],
    "name:ces_x_preferred":[
        "Villa"
    ],
    "name:deu_x_preferred":[
        "Vila"
    ],
    "name:est_x_preferred":[
        "Vila"
    ],
    "name:fin_x_preferred":[
        "Vila"
    ],
    "name:fra_x_preferred":[
        "Vila"
    ],
    "name:glg_x_preferred":[
        "Vila"
    ],
    "name:hun_x_preferred":[
        "Vila"
    ],
    "name:hye_x_preferred":[
        "\u054e\u056b\u056c\u0561"
    ],
    "name:ita_x_preferred":[
        "Vila"
    ],
    "name:nld_x_preferred":[
        "Vila"
    ],
    "name:por_x_preferred":[
        "Vila"
    ],
    "name:slk_x_preferred":[
        "Vila"
    ],
    "name:spa_x_preferred":[
        "Vila"
    ],
    "name:swe_x_preferred":[
        "Vila"
    ],
    "name:ukr_x_preferred":[
        "\u0412\u0456\u043b\u0430"
    ],
    "wof:name":"Vila",
    "wof:placetype":"locality"
},
  "geometry": {"coordinates":[-8.1588,42.0304],"type":"Point"}
}