{
  "type": "Feature",
  "properties": {
    "gn:admin1_code":"4.0",
    "gn:admin2_code":"0313",
    "gn:admin3_code":"31336.0",
    "gn:asciiname":"Pico",
    "gn:country_code":"PT",
    "gn:dem":150,
    "gn:feature_class":"P",
    "gn:feature_code":"PPL",
    "gn:name":"Pico",
    "gn:population":0,
    "gn:timezone":"Europe/Lisbon",
    "iso:country":"PT",
    "name:und_x_variant":[
        "S\u00e3o Paio",
        "Pico"
    ],
    "wof:name":"Pico",
    "wof:placetype":"locality"
},
  "geometry": {"coordinates":[-8.43078,41.68762],"type":"Point"}
}