{
  "type": "Feature",
  "properties": {
    "gn:admin1_code":"13.0",
    "gn:admin2_code":"1007",
    "gn:admin3_code":"100701.0",
    "gn:asciiname":"Amial",
    "gn:country_code":"PT",
    "gn:dem":512,
    "gn:feature_class":"P",
    "gn:feature_code":"PPL",
    "gn:name":"Amial",
    "gn:population":0,
    "gn:timezone":"Europe/Lisbon",
    "iso:country":"PT",
    "wof:name":"Amial",
    "wof:placetype":"locality"
},
  "geometry": {"coordinates":[-8.21585,40.01427],"type":"Point"}
}