{
  "type": "Feature",
  "properties": {
    "gn:admin1_code":"22.0",
    "gn:admin2_code":"1806",
    "gn:admin3_code":"180608.0",
    "gn:asciiname":"Freixiosa",
    "gn:country_code":"PT",
    "gn:dem":542,
    "gn:feature_class":"P",
    "gn:feature_code":"PPL",
    "gn:name":"Freixiosa",
    "gn:population":0,
    "gn:timezone":"Europe/Lisbon",
    "iso:country":"PT",
    "name:ceb_x_preferred":[
        "Freixiosa"
    ],
    "name:deu_x_preferred":[
        "Freixiosa"
    ],
    "name:kaz_x_preferred":[
        "\u0424\u0440\u0435\u0439\u0448\u0438\u043e\u0437\u0430"
    ],
    "name:nld_x_preferred":[
        "Freixiosa"
    ],
    "name:por_x_preferred":[
        "Freixiosa"
    ],
    "name:rus_x_preferred":[
        "\u0424\u0440\u0435\u0439\u0448\u0438\u043e\u0437\u0430"
    ],
    "name:spa_x_preferred":[
        "Freixiosa"
    ],
    "wof:name":"Freixiosa",
    "wof:placetype":"locality"
},
  "geometry": {"coordinates":[-7.67583,40.61212],"type":"Point"}
}