{
  "type": "Feature",
  "properties": {
    "gn:admin1_code":"22.0",
    "gn:admin2_code":"1806",
    "gn:admin3_code":"180608.0",
    "gn:asciiname":"Freixiosa",
    "gn:country_code":"PT",
    "gn:dem":542,
    "gn:feature_class":"P",
    "gn:feature_code":"PPL",
    "gn:name":"Freixiosa",
    "gn:population":0,
    "gn:timezone":"Europe/Lisbon",
    "iso:country":"PT",
    "wof:name":"Freixiosa",
    "wof:placetype":"locality"
},
  "geometry": {"coordinates":[-7.67583,40.61212],"type":"Point"}
}