{
  "type": "Feature",
  "properties": {
    "gn:admin1_code":"09",
    "gn:admin2_code":"0805",
    "gn:admin3_code":"80505.0",
    "gn:asciiname":"Ilha da Culatra",
    "gn:country_code":"PT",
    "gn:dem":-9999,
    "gn:feature_class":"P",
    "gn:feature_code":"PPL",
    "gn:name":"Ilha da Culatra",
    "gn:population":0,
    "gn:timezone":"Europe/Lisbon",
    "iso:country":"PT",
    "wof:name":"Ilha da Culatra",
    "wof:placetype":"locality"
},
  "geometry": {"coordinates":[-7.83926,36.99364],"type":"Point"}
}