{
  "type": "Feature",
  "properties": {
    "gn:admin1_code":"02",
    "gn:admin2_code":"0114",
    "gn:admin3_code":"11403.0",
    "gn:asciiname":"Regatinha",
    "gn:country_code":"PT",
    "gn:dem":47,
    "gn:feature_class":"P",
    "gn:feature_code":"PPL",
    "gn:name":"Regatinha",
    "gn:population":0,
    "gn:timezone":"Europe/Lisbon",
    "iso:country":"PT",
    "wof:name":"Regatinha",
    "wof:placetype":"locality"
},
  "geometry": {"coordinates":[-8.54034,40.53842],"type":"Point"}
}