{
  "type": "Feature",
  "properties": {
    "gn:admin1_code":"04",
    "gn:admin2_code":"0307",
    "gn:admin3_code":"30718.0",
    "gn:asciiname":"Vilela",
    "gn:country_code":"PT",
    "gn:dem":530,
    "gn:feature_class":"P",
    "gn:feature_code":"PPL",
    "gn:name":"Vilela",
    "gn:population":0,
    "gn:timezone":"Europe/Lisbon",
    "iso:country":"PT",
    "wof:name":"Vilela",
    "wof:placetype":"locality"
},
  "geometry": {"coordinates":[-8.09689,41.49056],"type":"Point"}
}