{
  "type": "Feature",
  "properties": {
    "gn:admin1_code":"09",
    "gn:admin2_code":"0805",
    "gn:admin3_code":"80503.0",
    "gn:asciiname":"Laranjeira",
    "gn:country_code":"PT",
    "gn:dem":198,
    "gn:feature_class":"P",
    "gn:feature_code":"PPL",
    "gn:name":"Laranjeira",
    "gn:population":0,
    "gn:timezone":"Europe/Lisbon",
    "iso:country":"PT",
    "name:und_x_variant":[
        "Larangeira",
        "Laranjeira"
    ],
    "wof:name":"Laranjeira",
    "wof:placetype":"locality"
},
  "geometry": {"coordinates":[-7.9599,37.11089000000001],"type":"Point"}
}