{
  "type": "Feature",
  "properties": {
    "gn:admin1_code":"22.0",
    "gn:admin2_code":"1823",
    "gn:admin3_code":"182305.0",
    "gn:asciiname":"Calde",
    "gn:country_code":"PT",
    "gn:dem":561,
    "gn:feature_class":"P",
    "gn:feature_code":"PPL",
    "gn:name":"Calde",
    "gn:population":0,
    "gn:timezone":"Europe/Lisbon",
    "iso:country":"PT",
    "wof:name":"Calde",
    "wof:placetype":"locality"
},
  "geometry": {"coordinates":[-7.91153,40.78209],"type":"Point"}
}