{
  "type": "Feature",
  "properties": {
    "gn:admin1_code":"7.0",
    "gn:admin2_code":"0606",
    "gn:admin3_code":"60601.0",
    "gn:asciiname":"Ladeira",
    "gn:country_code":"PT",
    "gn:dem":323,
    "gn:feature_class":"P",
    "gn:feature_code":"PPL",
    "gn:name":"Ladeira",
    "gn:population":0,
    "gn:timezone":"Europe/Lisbon",
    "iso:country":"PT",
    "wof:name":"Ladeira",
    "wof:placetype":"locality"
},
  "geometry": {"coordinates":[-8.09708,40.01766],"type":"Point"}
}