{
  "type": "Feature",
  "properties": {
    "gn:admin1_code":"10",
    "gn:admin2_code":"3105",
    "gn:admin3_code":"310502.0",
    "gn:asciiname":"Cova do Moirao",
    "gn:country_code":"PT",
    "gn:dem":329,
    "gn:feature_class":"P",
    "gn:feature_code":"PPL",
    "gn:name":"Cova do Moir\u00e3o",
    "gn:population":0,
    "gn:timezone":"Atlantic/Madeira",
    "iso:country":"PT",
    "wof:name":"Cova do Moirao",
    "wof:placetype":"locality"
},
  "geometry": {"coordinates":[-17.13332999999999,32.71667],"type":"Point"}
}