{
  "type": "Feature",
  "properties": {
    "gn:admin1_code":"20",
    "gn:admin2_code":"1607",
    "gn:admin3_code":"160728.0",
    "gn:asciiname":"Valinhos",
    "gn:country_code":"PT",
    "gn:dem":229,
    "gn:feature_class":"P",
    "gn:feature_code":"PPL",
    "gn:name":"Valinhos",
    "gn:population":0,
    "gn:timezone":"Europe/Lisbon",
    "iso:country":"PT",
    "wof:name":"Valinhos",
    "wof:placetype":"locality"
},
  "geometry": {"coordinates":[-8.51527,41.75988],"type":"Point"}
}