{
  "type": "Feature",
  "properties": {
    "gn:admin1_code":"20",
    "gn:admin2_code":"1607",
    "gn:admin3_code":"160728.0",
    "gn:asciiname":"Valinhos",
    "gn:country_code":"PT",
    "gn:dem":229,
    "gn:feature_class":"P",
    "gn:feature_code":"PPL",
    "gn:name":"Valinhos",
    "gn:population":0,
    "gn:timezone":"Europe/Lisbon",
    "iso:country":"PT",
    "name:ara_x_preferred":[
        "\u0641\u0627\u0644\u064a\u0646\u0647\u0648\u0633"
    ],
    "name:bpy_x_preferred":[
        "\u09ad\u09be\u09b2\u0987\u09a8\u09b9\u09cb\u09b8"
    ],
    "name:cat_x_preferred":[
        "Valinhos"
    ],
    "name:ceb_x_preferred":[
        "Valinhos"
    ],
    "name:deu_x_preferred":[
        "Valinhos"
    ],
    "name:epo_x_preferred":[
        "Valinhos"
    ],
    "name:eus_x_preferred":[
        "Valinhos"
    ],
    "name:fra_x_preferred":[
        "Valinhos"
    ],
    "name:ita_x_preferred":[
        "Valinhos"
    ],
    "name:kaz_x_preferred":[
        "\u0412\u0430\u043b\u0438\u043d\u044c\u044e\u0441"
    ],
    "name:mlg_x_preferred":[
        "Valinhos"
    ],
    "name:nld_x_preferred":[
        "Valinhos"
    ],
    "name:nor_x_preferred":[
        "Valinhos"
    ],
    "name:pol_x_preferred":[
        "Valinhos"
    ],
    "name:por_x_preferred":[
        "Valinhos"
    ],
    "name:ron_x_preferred":[
        "Valinhos"
    ],
    "name:rus_x_preferred":[
        "\u0412\u0430\u043b\u0438\u043d\u044c\u044e\u0441"
    ],
    "name:spa_x_preferred":[
        "Valinhos"
    ],
    "name:swe_x_preferred":[
        "Valinhos"
    ],
    "name:tat_x_preferred":[
        "\u0412\u0430\u043b\u0438\u043d\u044c\u044e\u0441"
    ],
    "name:ukr_x_preferred":[
        "\u0412\u0430\u043b\u0456\u043d\u044c\u044e\u0441"
    ],
    "name:vol_x_preferred":[
        "Valinhos"
    ],
    "name:war_x_preferred":[
        "Valinhos"
    ],
    "name:zho_x_preferred":[
        "\u74e6\u5229\u5c3c\u4e4c\u65af"
    ],
    "wof:name":"Valinhos",
    "wof:placetype":"locality"
},
  "geometry": {"coordinates":[-8.51527,41.75988],"type":"Point"}
}