{
  "type": "Feature",
  "properties": {
    "gn:admin1_code":"06",
    "gn:admin2_code":"0511",
    "gn:admin3_code":"51104.0",
    "gn:asciiname":"Vale do Cobrao",
    "gn:country_code":"PT",
    "gn:dem":300,
    "gn:feature_class":"P",
    "gn:feature_code":"PPL",
    "gn:name":"Vale do Cobr\u00e3o",
    "gn:population":0,
    "gn:timezone":"Europe/Lisbon",
    "iso:country":"PT",
    "wof:name":"Vale do Cobrao",
    "wof:placetype":"locality"
},
  "geometry": {"coordinates":[-7.73756,39.71316],"type":"Point"}
}