{
  "type": "Feature",
  "properties": {
    "gn:admin1_code":"18",
    "gn:admin2_code":"1405",
    "gn:admin3_code":"140504.0",
    "gn:asciiname":"Sao Bras",
    "gn:country_code":"PT",
    "gn:dem":21,
    "gn:feature_class":"P",
    "gn:feature_code":"PPL",
    "gn:name":"S\u00e3o Br\u00e1s",
    "gn:population":0,
    "gn:timezone":"Europe/Lisbon",
    "iso:country":"PT",
    "wof:name":"Sao Bras",
    "wof:placetype":"locality"
},
  "geometry": {"coordinates":[-8.7289,38.95535],"type":"Point"}
}