{
  "type": "Feature",
  "properties": {
    "gn:admin1_code":"17.0",
    "gn:admin2_code":"1311",
    "gn:admin3_code":"131117.0",
    "gn:asciiname":"Luzim",
    "gn:country_code":"PT",
    "gn:dem":281,
    "gn:feature_class":"P",
    "gn:feature_code":"PPL",
    "gn:name":"Luzim",
    "gn:population":0,
    "gn:timezone":"Europe/Lisbon",
    "iso:country":"PT",
    "wof:name":"Luzim",
    "wof:placetype":"locality"
},
  "geometry": {"coordinates":[-8.2451,41.1528],"type":"Point"}
}