{
  "type": "Feature",
  "properties": {
    "gn:admin1_code":"11.0",
    "gn:admin2_code":"0912",
    "gn:admin3_code":"91224.0",
    "gn:asciiname":"Casal",
    "gn:country_code":"PT",
    "gn:dem":424,
    "gn:feature_class":"P",
    "gn:feature_code":"PPL",
    "gn:name":"Casal",
    "gn:population":0,
    "gn:timezone":"Europe/Lisbon",
    "iso:country":"PT",
    "name:nld_x_preferred":[
        "Casal"
    ],
    "name:swe_x_preferred":[
        "Casal"
    ],
    "wof:name":"Casal",
    "wof:placetype":"locality"
},
  "geometry": {"coordinates":[-7.81823,40.41443],"type":"Point"}
}