{
  "type": "Feature",
  "properties": {
    "gn:admin1_code":"5.0",
    "gn:admin2_code":"0405",
    "gn:admin3_code":"40523.0",
    "gn:asciiname":"Malta",
    "gn:country_code":"PT",
    "gn:dem":648,
    "gn:feature_class":"P",
    "gn:feature_code":"PPL",
    "gn:name":"Malta",
    "gn:population":0,
    "gn:timezone":"Europe/Lisbon",
    "iso:country":"PT",
    "wof:name":"Malta",
    "wof:placetype":"locality"
},
  "geometry": {"coordinates":[-6.91362,41.48282],"type":"Point"}
}