{
  "type": "Feature",
  "properties": {
    "iso:country":"PT",
    "name:cat_x_preferred":[
        "Neves"
    ],
    "name:ceb_x_preferred":[
        "Neves"
    ],
    "name:deu_x_preferred":[
        "Neves"
    ],
    "name:fra_x_preferred":[
        "Neves"
    ],
    "name:ita_x_preferred":[
        "Neves"
    ],
    "name:por_x_preferred":[
        "Neves"
    ],
    "name:rus_x_preferred":[
        "\u041d\u0435\u0432\u0438\u0448"
    ],
    "name:spa_x_preferred":[
        "Neves"
    ],
    "name:swe_x_preferred":[
        "Neves"
    ],
    "qs_pg:aaroncc":"PT",
    "qs_pg:name":"Neves",
    "qs_pg:name_adm0":"Portugal",
    "qs_pg:name_adm1":"Madeira",
    "qs_pg:photos":40,
    "qs_pg:photos_1k":8,
    "qs_pg:photos_9k":1,
    "qs_pg:photos_9r":2,
    "qs_pg:photos_all":40,
    "qs_pg:photos_sr":2,
    "qs_pg:pop_sr":0,
    "qs_pg:qs_pg_placetype":"locality",
    "qs_pg:qs_pg_placetype_gp":"Town",
    "qs_pg:woe_adm0":23424925,
    "woe:adm0_id":23424925,
    "woe:name_adm0":"Portugal",
    "woe:name_adm1":"Madeira",
    "woe:placetype":"Town",
    "wof:name":"Neves",
    "wof:placetype":"locality"
},
  "geometry": {"coordinates":[-16.87045,32.652239],"type":"Point"}
}