{
  "type": "Feature",
  "properties": {
    "gn:admin1_code":"09",
    "gn:admin2_code":"0816",
    "gn:admin3_code":"81601.0",
    "gn:asciiname":"Pocinho",
    "gn:country_code":"PT",
    "gn:dem":72,
    "gn:feature_class":"P",
    "gn:feature_code":"PPL",
    "gn:name":"Pocinho",
    "gn:population":0,
    "gn:timezone":"Europe/Lisbon",
    "iso:country":"PT",
    "wof:name":"Pocinho",
    "wof:placetype":"locality"
},
  "geometry": {"coordinates":[-7.54188,37.19236],"type":"Point"}
}