{
  "type": "Feature",
  "properties": {
    "gn:admin1_code":"20.0",
    "gn:admin2_code":"1605",
    "gn:admin3_code":"160511.0",
    "gn:asciiname":"Agrela",
    "gn:country_code":"PT",
    "gn:dem":481,
    "gn:feature_class":"P",
    "gn:feature_code":"PPL",
    "gn:name":"Agrela",
    "gn:population":0,
    "gn:timezone":"Europe/Lisbon",
    "iso:country":"PT",
    "name:ceb_x_preferred":[
        "Agrela"
    ],
    "name:deu_x_preferred":[
        "Agrela"
    ],
    "name:fra_x_preferred":[
        "Agrela"
    ],
    "name:glg_x_preferred":[
        "Agrela"
    ],
    "name:nld_x_preferred":[
        "Agrela"
    ],
    "name:por_x_preferred":[
        "Agrela"
    ],
    "name:spa_x_preferred":[
        "Agrela"
    ],
    "name:ukr_x_preferred":[
        "\u0410\u0433\u0440\u0435\u043b\u0430"
    ],
    "name:zho_x_preferred":[
        "\u963f\u683c\u96f7\u62c9"
    ],
    "wof:name":"Agrela",
    "wof:placetype":"locality"
},
  "geometry": {"coordinates":[-8.52748,41.95085],"type":"Point"}
}