{
  "type": "Feature",
  "properties": {
    "gn:admin1_code":"16",
    "gn:admin2_code":"1210",
    "gn:admin3_code":"121003.0",
    "gn:asciiname":"Arranjinho",
    "gn:country_code":"PT",
    "gn:dem":479,
    "gn:feature_class":"P",
    "gn:feature_code":"PPL",
    "gn:name":"Arranjinho",
    "gn:population":0,
    "gn:timezone":"Europe/Lisbon",
    "iso:country":"PT",
    "wof:name":"Arranjinho",
    "wof:placetype":"locality"
},
  "geometry": {"coordinates":[-7.35,39.41667],"type":"Point"}
}