{
  "type": "Feature",
  "properties": {
    "gn:admin1_code":"14",
    "gn:admin2_code":"1104",
    "gn:admin3_code":"110405.0",
    "gn:asciiname":"Rumeleira",
    "gn:country_code":"PT",
    "gn:dem":155,
    "gn:feature_class":"P",
    "gn:feature_code":"PPL",
    "gn:name":"Rumeleira",
    "gn:population":0,
    "gn:timezone":"Europe/Lisbon",
    "iso:country":"PT",
    "wof:name":"Rumeleira",
    "wof:placetype":"locality"
},
  "geometry": {"coordinates":[-9.06667,39.20598],"type":"Point"}
}