{
  "type": "Feature",
  "properties": {
    "gn:admin1_code":"19",
    "gn:admin2_code":"1509",
    "gn:admin3_code":"150902.0",
    "gn:asciiname":"Roxo",
    "gn:country_code":"PT",
    "gn:dem":44,
    "gn:feature_class":"P",
    "gn:feature_code":"PPL",
    "gn:name":"Roxo",
    "gn:population":0,
    "gn:timezone":"Europe/Lisbon",
    "iso:country":"PT",
    "wof:name":"Roxo",
    "wof:placetype":"locality"
},
  "geometry": {"coordinates":[-8.38759,37.98785],"type":"Point"}
}