{
  "type": "Feature",
  "properties": {
    "gn:admin1_code":"22.0",
    "gn:admin2_code":"1819",
    "gn:admin3_code":"181906.0",
    "gn:asciiname":"Granja do Tedo",
    "gn:country_code":"PT",
    "gn:dem":352,
    "gn:feature_class":"P",
    "gn:feature_code":"PPL",
    "gn:name":"Granja do Tedo",
    "gn:population":0,
    "gn:timezone":"Europe/Lisbon",
    "iso:country":"PT",
    "wof:name":"Granja do Tedo",
    "wof:placetype":"locality"
},
  "geometry": {"coordinates":[-7.61387,41.06733],"type":"Point"}
}