{
  "type": "Feature",
  "properties": {
    "gn:admin1_code":"20.0",
    "gn:admin2_code":"1606",
    "gn:admin3_code":"160615.0",
    "gn:asciiname":"Paco Vedro de Magalhaes",
    "gn:country_code":"PT",
    "gn:dem":111,
    "gn:feature_class":"P",
    "gn:feature_code":"PPL",
    "gn:name":"Pa\u00e7o Vedro de Magalh\u00e3es",
    "gn:population":0,
    "gn:timezone":"Europe/Lisbon",
    "iso:country":"PT",
    "wof:name":"Paco Vedro de Magalhaes",
    "wof:placetype":"locality"
},
  "geometry": {"coordinates":[-8.40365,41.79467],"type":"Point"}
}