{
  "type": "Feature",
  "properties": {
    "gn:admin1_code":"04",
    "gn:admin2_code":"0307",
    "gn:admin3_code":"30705.0",
    "gn:asciiname":"Retorta",
    "gn:country_code":"PT",
    "gn:dem":392,
    "gn:feature_class":"P",
    "gn:feature_code":"PPL",
    "gn:name":"Retorta",
    "gn:population":0,
    "gn:timezone":"Europe/Lisbon",
    "iso:country":"PT",
    "wof:name":"Retorta",
    "wof:placetype":"locality"
},
  "geometry": {"coordinates":[-8.18333,41.41667],"type":"Point"}
}