{
  "type": "Feature",
  "properties": {
    "gn:admin1_code":"06",
    "gn:admin2_code":"0507",
    "gn:admin3_code":"50710.0",
    "gn:asciiname":"Quinta do Prado",
    "gn:country_code":"PT",
    "gn:dem":433,
    "gn:feature_class":"P",
    "gn:feature_code":"PPL",
    "gn:name":"Quinta do Prado",
    "gn:population":0,
    "gn:timezone":"Europe/Lisbon",
    "iso:country":"PT",
    "wof:name":"Quinta do Prado",
    "wof:placetype":"locality"
},
  "geometry": {"coordinates":[-7.20472,40.1598],"type":"Point"}
}