{
  "type": "Feature",
  "properties": {
    "gn:admin1_code":"22",
    "gn:admin2_code":"1815",
    "gn:admin3_code":"181502.0",
    "gn:asciiname":"Sarzedinho",
    "gn:country_code":"PT",
    "gn:dem":207,
    "gn:feature_class":"P",
    "gn:feature_code":"PPL",
    "gn:name":"Sarzedinho",
    "gn:population":0,
    "gn:timezone":"Europe/Lisbon",
    "iso:country":"PT",
    "wof:name":"Sarzedinho",
    "wof:placetype":"locality"
},
  "geometry": {"coordinates":[-7.52428,41.15767],"type":"Point"}
}