{
  "type": "Feature",
  "properties": {
    "gn:admin1_code":"14",
    "gn:admin2_code":"1114",
    "gn:admin3_code":"111402.0",
    "gn:asciiname":"Quinta da Verdelha",
    "gn:country_code":"PT",
    "gn:dem":17,
    "gn:feature_class":"P",
    "gn:feature_code":"PPL",
    "gn:name":"Quinta da Verdelha",
    "gn:population":0,
    "gn:timezone":"Europe/Lisbon",
    "iso:country":"PT",
    "wof:name":"Quinta da Verdelha",
    "wof:placetype":"locality"
},
  "geometry": {"coordinates":[-9.04893,38.88635],"type":"Point"}
}