{
  "type": "Feature",
  "properties": {
    "gn:admin1_code":"4.0",
    "gn:admin2_code":"0308",
    "gn:admin3_code":"30843.0",
    "gn:asciiname":"Briteiros",
    "gn:country_code":"PT",
    "gn:dem":262,
    "gn:feature_class":"P",
    "gn:feature_code":"PPL",
    "gn:name":"Briteiros",
    "gn:population":0,
    "gn:timezone":"Europe/Lisbon",
    "iso:country":"PT",
    "name:und_x_variant":[
        "Santa Leoc\u00e1dia",
        "Briteiros"
    ],
    "wof:name":"Briteiros",
    "wof:placetype":"locality"
},
  "geometry": {"coordinates":[-8.34356,41.52724],"type":"Point"}
}