{
  "type": "Feature",
  "properties": {
    "gn:admin1_code":"17",
    "gn:admin2_code":"1302",
    "gn:admin3_code":"130213.0",
    "gn:asciiname":"Santa Cruz do Douro",
    "gn:country_code":"PT",
    "gn:dem":313,
    "gn:feature_class":"P",
    "gn:feature_code":"PPL",
    "gn:name":"Santa Cruz do Douro",
    "gn:population":0,
    "gn:timezone":"Europe/Lisbon",
    "iso:country":"PT",
    "wof:name":"Santa Cruz do Douro",
    "wof:placetype":"locality"
},
  "geometry": {"coordinates":[-8.01156,41.11917],"type":"Point"}
}