{
  "type": "Feature",
  "properties": {
    "gn:admin1_code":"13",
    "gn:admin2_code":"1015",
    "gn:admin3_code":"101511.0",
    "gn:asciiname":"Infesta",
    "gn:country_code":"PT",
    "gn:dem":211,
    "gn:feature_class":"P",
    "gn:feature_code":"PPL",
    "gn:name":"Infesta",
    "gn:population":0,
    "gn:timezone":"Europe/Lisbon",
    "iso:country":"PT",
    "name:ceb_x_preferred":[
        "Infesta"
    ],
    "name:deu_x_preferred":[
        "Infesta"
    ],
    "name:fra_x_preferred":[
        "Infesta"
    ],
    "name:glg_x_preferred":[
        "Infesta"
    ],
    "name:nld_x_preferred":[
        "Infesta"
    ],
    "name:por_x_preferred":[
        "Infesta"
    ],
    "name:rus_x_preferred":[
        "\u0418\u043d\u0444\u0435\u0448\u0442\u0430"
    ],
    "name:ukr_x_preferred":[
        "\u0406\u043d\u0444\u0435\u0448\u0442\u0430"
    ],
    "wof:name":"Infesta",
    "wof:placetype":"locality"
},
  "geometry": {"coordinates":[-8.5759,39.84863],"type":"Point"}
}