{
  "type": "Feature",
  "properties": {
    "gn:admin1_code":"11.0",
    "gn:admin2_code":"0903",
    "gn:admin3_code":"90304.0",
    "gn:asciiname":"Carrapichana",
    "gn:country_code":"PT",
    "gn:dem":557,
    "gn:feature_class":"P",
    "gn:feature_code":"PPL",
    "gn:name":"Carrapichana",
    "gn:population":0,
    "gn:timezone":"Europe/Lisbon",
    "iso:country":"PT",
    "wof:name":"Carrapichana",
    "wof:placetype":"locality"
},
  "geometry": {"coordinates":[-7.48606,40.56235],"type":"Point"}
}