{
  "type": "Feature",
  "properties": {
    "gn:admin1_code":"09",
    "gn:admin2_code":"0809",
    "gn:admin3_code":"80902.0",
    "gn:asciiname":"Vale da Horta",
    "gn:country_code":"PT",
    "gn:dem":123,
    "gn:feature_class":"P",
    "gn:feature_code":"PPL",
    "gn:name":"Vale da Horta",
    "gn:population":0,
    "gn:timezone":"Europe/Lisbon",
    "iso:country":"PT",
    "wof:name":"Vale da Horta",
    "wof:placetype":"locality"
},
  "geometry": {"coordinates":[-8.67414,37.24666],"type":"Point"}
}