{
  "type": "Feature",
  "properties": {
    "iso:country":"PT",
    "qs_pg:aaroncc":"PT",
    "qs_pg:name":"Barragem de Belver",
    "qs_pg:name_adm0":"Portugal",
    "qs_pg:name_adm1":"Santar\u00e9m",
    "qs_pg:photos":57,
    "qs_pg:photos_1k":12,
    "qs_pg:photos_9k":1,
    "qs_pg:photos_9r":2,
    "qs_pg:photos_all":57,
    "qs_pg:photos_sr":2,
    "qs_pg:pop_sr":0,
    "qs_pg:qs_pg_placetype":"locality",
    "qs_pg:qs_pg_placetype_gp":"Town",
    "qs_pg:woe_adm0":23424925,
    "woe:adm0_id":23424925,
    "woe:name_adm0":"Portugal",
    "woe:name_adm1":"Santar\u00e9m",
    "woe:placetype":"Town",
    "wof:name":"Barragem de Belver",
    "wof:placetype":"locality"
},
  "geometry": {"coordinates":[-7.969379,39.487623],"type":"Point"}
}