{
  "type": "Feature",
  "properties": {
    "gn:admin1_code":"13",
    "gn:admin2_code":"1016",
    "gn:admin3_code":"101605.0",
    "gn:asciiname":"Vale de Agua",
    "gn:country_code":"PT",
    "gn:dem":141,
    "gn:feature_class":"P",
    "gn:feature_code":"PPL",
    "gn:name":"Vale de \u00c1gua",
    "gn:population":0,
    "gn:timezone":"Europe/Lisbon",
    "iso:country":"PT",
    "wof:name":"Vale de Agua",
    "wof:placetype":"locality"
},
  "geometry": {"coordinates":[-8.87523,39.6253],"type":"Point"}
}