{
  "type": "Feature",
  "properties": {
    "gn:admin1_code":"22.0",
    "gn:admin2_code":"1809",
    "gn:admin3_code":"180903.0",
    "gn:asciiname":"Algeraz",
    "gn:country_code":"PT",
    "gn:dem":439,
    "gn:feature_class":"P",
    "gn:feature_code":"PPL",
    "gn:name":"Algeraz",
    "gn:population":0,
    "gn:timezone":"Europe/Lisbon",
    "iso:country":"PT",
    "wof:name":"Algeraz",
    "wof:placetype":"locality"
},
  "geometry": {"coordinates":[-7.86081,40.54247],"type":"Point"}
}