{
  "type": "Feature",
  "properties": {
    "gn:admin1_code":"02",
    "gn:admin2_code":"0105",
    "gn:admin3_code":"10505.0",
    "gn:asciiname":"Quinta do Loureiro",
    "gn:country_code":"PT",
    "gn:dem":28,
    "gn:feature_class":"P",
    "gn:feature_code":"PPL",
    "gn:name":"Quint\u00e3 do Loureiro",
    "gn:population":0,
    "gn:timezone":"Europe/Lisbon",
    "iso:country":"PT",
    "wof:name":"Quinta do Loureiro",
    "wof:placetype":"locality"
},
  "geometry": {"coordinates":[-8.58913,40.65284000000001],"type":"Point"}
}