{
  "type": "Feature",
  "properties": {
    "gn:admin1_code":"2.0",
    "gn:admin2_code":"0104",
    "gn:admin3_code":"10418.0",
    "gn:asciiname":"Penaceira",
    "gn:country_code":"PT",
    "gn:dem":215,
    "gn:feature_class":"P",
    "gn:feature_code":"PPL",
    "gn:name":"Penaceira",
    "gn:population":0,
    "gn:timezone":"Europe/Lisbon",
    "iso:country":"PT",
    "wof:name":"Penaceira",
    "wof:placetype":"locality"
},
  "geometry": {"coordinates":[-8.33695,40.93256],"type":"Point"}
}