{
  "type": "Feature",
  "properties": {
    "gn:admin1_code":"11.0",
    "gn:admin2_code":"0901",
    "gn:admin3_code":"90108.0",
    "gn:asciiname":"Mocoes",
    "gn:country_code":"PT",
    "gn:dem":910,
    "gn:feature_class":"P",
    "gn:feature_code":"PPL",
    "gn:name":"Mo\u00e7\u00f5es",
    "gn:population":0,
    "gn:timezone":"Europe/Lisbon",
    "iso:country":"PT",
    "wof:name":"Mocoes",
    "wof:placetype":"locality"
},
  "geometry": {"coordinates":[-7.55901,40.87053],"type":"Point"}
}