{
  "type": "Feature",
  "properties": {
    "gn:admin1_code":"14",
    "gn:admin2_code":"1101",
    "gn:admin3_code":"110106.0",
    "gn:asciiname":"Antas",
    "gn:country_code":"PT",
    "gn:dem":211,
    "gn:feature_class":"P",
    "gn:feature_code":"PPL",
    "gn:name":"Antas",
    "gn:population":0,
    "gn:timezone":"Europe/Lisbon",
    "iso:country":"PT",
    "wof:name":"Antas",
    "wof:placetype":"locality"
},
  "geometry": {"coordinates":[-9.05596,39.0433],"type":"Point"}
}