{
  "type": "Feature",
  "properties": {
    "gn:admin1_code":"03",
    "gn:admin2_code":"0211",
    "gn:admin3_code":"21105.0",
    "gn:asciiname":"Pomar",
    "gn:country_code":"PT",
    "gn:dem":103,
    "gn:feature_class":"P",
    "gn:feature_code":"PPL",
    "gn:name":"Pomar",
    "gn:population":0,
    "gn:timezone":"Europe/Lisbon",
    "iso:country":"PT",
    "name:cat_x_preferred":[
        "Pomar"
    ],
    "name:deu_x_preferred":[
        "Pomar"
    ],
    "name:fra_x_preferred":[
        "Pomar"
    ],
    "name:glg_x_preferred":[
        "Pomar"
    ],
    "name:spa_x_preferred":[
        "Pomar"
    ],
    "wof:name":"Pomar",
    "wof:placetype":"locality"
},
  "geometry": {"coordinates":[-8.57624,37.60688],"type":"Point"}
}