{
  "type": "Feature",
  "properties": {
    "gn:admin1_code":"07",
    "gn:admin2_code":"0610",
    "gn:admin3_code":"61003.0",
    "gn:asciiname":"Sao Giraldo",
    "gn:country_code":"PT",
    "gn:dem":62,
    "gn:feature_class":"P",
    "gn:feature_code":"PPL",
    "gn:name":"S\u00e3o Giraldo",
    "gn:population":0,
    "gn:timezone":"Europe/Lisbon",
    "iso:country":"PT",
    "wof:name":"Sao Giraldo",
    "wof:placetype":"locality"
},
  "geometry": {"coordinates":[-8.65,40.21667],"type":"Point"}
}