{
  "type": "Feature",
  "properties": {
    "gn:admin1_code":"4.0",
    "gn:admin2_code":"0309",
    "gn:admin3_code":"30924.0",
    "gn:asciiname":"Bezerral",
    "gn:country_code":"PT",
    "gn:dem":543,
    "gn:feature_class":"P",
    "gn:feature_code":"PPL",
    "gn:name":"Bezerral",
    "gn:population":0,
    "gn:timezone":"Europe/Lisbon",
    "iso:country":"PT",
    "wof:name":"Bezerral",
    "wof:placetype":"locality"
},
  "geometry": {"coordinates":[-8.214,41.62815],"type":"Point"}
}