{
  "type": "Feature",
  "properties": {
    "gn:admin1_code":"4.0",
    "gn:admin2_code":"0302",
    "gn:admin3_code":"30213.0",
    "gn:asciiname":"Areal de Cima",
    "gn:country_code":"PT",
    "gn:dem":53,
    "gn:feature_class":"P",
    "gn:feature_code":"PPL",
    "gn:name":"Areal de Cima",
    "gn:population":0,
    "gn:timezone":"Europe/Lisbon",
    "iso:country":"PT",
    "wof:name":"Areal de Cima",
    "wof:placetype":"locality"
},
  "geometry": {"coordinates":[-8.62003,41.5218],"type":"Point"}
}