{
  "type": "Feature",
  "properties": {
    "gn:admin1_code":"06",
    "gn:admin2_code":"0502",
    "gn:admin3_code":"50221.0",
    "gn:asciiname":"Vale Chiqueiro",
    "gn:country_code":"PT",
    "gn:dem":284,
    "gn:feature_class":"P",
    "gn:feature_code":"PPL",
    "gn:name":"Vale Chiqueiro",
    "gn:population":0,
    "gn:timezone":"Europe/Lisbon",
    "iso:country":"PT",
    "wof:name":"Vale Chiqueiro",
    "wof:placetype":"locality"
},
  "geometry": {"coordinates":[-7.73159,39.82366],"type":"Point"}
}