{
  "type": "Feature",
  "properties": {
    "gn:admin1_code":"23.0",
    "gn:admin2_code":"4201",
    "gn:admin3_code":"420102.0",
    "gn:asciiname":"Rego d'Agua",
    "gn:country_code":"PT",
    "gn:dem":242,
    "gn:feature_class":"P",
    "gn:feature_code":"PPL",
    "gn:name":"Rego d\u2019\u00c1gua",
    "gn:population":0,
    "gn:timezone":"Atlantic/Azores",
    "iso:country":"PT",
    "wof:name":"Rego d'Agua",
    "wof:placetype":"locality"
},
  "geometry": {"coordinates":[-25.55,37.76667],"type":"Point"}
}