{
  "type": "Feature",
  "properties": {
    "gn:admin1_code":"4.0",
    "gn:admin2_code":"0307",
    "gn:admin3_code":"30721.0",
    "gn:asciiname":"Meixedos",
    "gn:country_code":"PT",
    "gn:dem":516,
    "gn:feature_class":"P",
    "gn:feature_code":"PPL",
    "gn:name":"Meixedos",
    "gn:population":0,
    "gn:timezone":"Europe/Lisbon",
    "iso:country":"PT",
    "wof:name":"Meixedos",
    "wof:placetype":"locality"
},
  "geometry": {"coordinates":[-8.13731,41.51143],"type":"Point"}
}