{
  "type": "Feature",
  "properties": {
    "gn:admin1_code":"13",
    "gn:admin2_code":"1004",
    "gn:admin3_code":"100401.0",
    "gn:asciiname":"Rebolaria",
    "gn:country_code":"PT",
    "gn:dem":124,
    "gn:feature_class":"P",
    "gn:feature_code":"PPL",
    "gn:name":"Rebolaria",
    "gn:population":0,
    "gn:timezone":"Europe/Lisbon",
    "iso:country":"PT",
    "wof:name":"Rebolaria",
    "wof:placetype":"locality"
},
  "geometry": {"coordinates":[-8.81446,39.66605],"type":"Point"}
}