{
  "type": "Feature",
  "properties": {
    "gn:admin1_code":"17.0",
    "gn:admin2_code":"1302",
    "gn:admin3_code":"130206.0",
    "gn:asciiname":"Pedreda",
    "gn:country_code":"PT",
    "gn:dem":470,
    "gn:feature_class":"P",
    "gn:feature_code":"PPL",
    "gn:name":"Pedreda",
    "gn:population":0,
    "gn:timezone":"Europe/Lisbon",
    "iso:country":"PT",
    "wof:name":"Pedreda",
    "wof:placetype":"locality"
},
  "geometry": {"coordinates":[-8.06232,41.13068],"type":"Point"}
}