{
  "type": "Feature",
  "properties": {
    "gn:admin1_code":"11.0",
    "gn:admin2_code":"0910",
    "gn:admin3_code":"91008.0",
    "gn:asciiname":"Ervas Tenras",
    "gn:country_code":"PT",
    "gn:dem":624,
    "gn:feature_class":"P",
    "gn:feature_code":"PPL",
    "gn:name":"Ervas Tenras",
    "gn:population":0,
    "gn:timezone":"Europe/Lisbon",
    "iso:country":"PT",
    "wof:name":"Ervas Tenras",
    "wof:placetype":"locality"
},
  "geometry": {"coordinates":[-7.18517,40.74067],"type":"Point"}
}