{
  "type": "Feature",
  "properties": {
    "gn:admin1_code":"22",
    "gn:admin2_code":"1811",
    "gn:admin3_code":"181112.0",
    "gn:asciiname":"Trancozelos",
    "gn:country_code":"PT",
    "gn:dem":442,
    "gn:feature_class":"P",
    "gn:feature_code":"PPL",
    "gn:name":"Trancozelos",
    "gn:population":0,
    "gn:timezone":"Europe/Lisbon",
    "iso:country":"PT",
    "wof:name":"Trancozelos",
    "wof:placetype":"locality"
},
  "geometry": {"coordinates":[-7.70377,40.65338],"type":"Point"}
}