{
  "type": "Feature",
  "properties": {
    "gn:admin1_code":"03",
    "gn:admin2_code":"0202",
    "gn:admin3_code":"20206.0",
    "gn:asciiname":"Pampilhais de Baixo",
    "gn:country_code":"PT",
    "gn:dem":401,
    "gn:feature_class":"P",
    "gn:feature_code":"PPL",
    "gn:name":"Pampilhais de Baixo",
    "gn:population":0,
    "gn:timezone":"Europe/Lisbon",
    "iso:country":"PT",
    "wof:name":"Pampilhais de Baixo",
    "wof:placetype":"locality"
},
  "geometry": {"coordinates":[-8.15336,37.40551],"type":"Point"}
}