{
  "type": "Feature",
  "properties": {
    "gn:admin1_code":"17.0",
    "gn:admin2_code":"1313",
    "gn:admin3_code":"131306.0",
    "gn:asciiname":"Beiriz",
    "gn:country_code":"PT",
    "gn:dem":62,
    "gn:feature_class":"P",
    "gn:feature_code":"PPL",
    "gn:name":"Beiriz",
    "gn:population":0,
    "gn:timezone":"Europe/Lisbon",
    "iso:country":"PT",
    "name:ceb_x_preferred":[
        "Beiriz"
    ],
    "name:deu_x_preferred":[
        "Beiriz"
    ],
    "name:kaz_x_preferred":[
        "\u0411\u0435\u0439\u0440\u0438\u0448"
    ],
    "name:nld_x_preferred":[
        "Beiriz"
    ],
    "name:por_x_preferred":[
        "Beiriz"
    ],
    "name:rus_x_preferred":[
        "\u0411\u0435\u0439\u0440\u0438\u0448"
    ],
    "name:spa_x_preferred":[
        "Beiriz"
    ],
    "name:tur_x_preferred":[
        "Beiriz"
    ],
    "name:zho_x_preferred":[
        "\u8d1d\u91cc\u5179"
    ],
    "wof:name":"Beiriz",
    "wof:placetype":"locality"
},
  "geometry": {"coordinates":[-8.71706,41.39954],"type":"Point"}
}