{
  "type": "Feature",
  "properties": {
    "gn:admin1_code":"4.0",
    "gn:admin2_code":"0311",
    "gn:admin3_code":"31106.0",
    "gn:asciiname":"Cova",
    "gn:country_code":"PT",
    "gn:dem":420,
    "gn:feature_class":"P",
    "gn:feature_code":"PPL",
    "gn:name":"Cova",
    "gn:population":0,
    "gn:timezone":"Europe/Lisbon",
    "iso:country":"PT",
    "name:ceb_x_preferred":[
        "\u041a\u043e\u0432\u0430"
    ],
    "name:deu_x_preferred":[
        "Cova"
    ],
    "name:glg_x_preferred":[
        "Cova"
    ],
    "name:ita_x_preferred":[
        "Cova"
    ],
    "name:jpn_x_preferred":[
        "\u30b3\u30f4\u30a1"
    ],
    "name:por_x_preferred":[
        "Cova"
    ],
    "name:rus_x_preferred":[
        "\u041a\u043e\u0432\u0430"
    ],
    "name:ukr_x_preferred":[
        "\u041a\u043e\u0432\u0430"
    ],
    "wof:name":"Cova",
    "wof:placetype":"locality"
},
  "geometry": {"coordinates":[-8.16271,41.6711],"type":"Point"}
}