{
  "type": "Feature",
  "properties": {
    "gn:admin1_code":"4.0",
    "gn:admin2_code":"0311",
    "gn:admin3_code":"31106.0",
    "gn:asciiname":"Cova",
    "gn:country_code":"PT",
    "gn:dem":420,
    "gn:feature_class":"P",
    "gn:feature_code":"PPL",
    "gn:name":"Cova",
    "gn:population":0,
    "gn:timezone":"Europe/Lisbon",
    "iso:country":"PT",
    "wof:name":"Cova",
    "wof:placetype":"locality"
},
  "geometry": {"coordinates":[-8.16271,41.6711],"type":"Point"}
}