{
  "type": "Feature",
  "properties": {
    "gn:admin1_code":"21.0",
    "gn:admin2_code":"1703",
    "gn:admin3_code":"170334.0",
    "gn:asciiname":"Aveleda",
    "gn:country_code":"PT",
    "gn:dem":509,
    "gn:feature_class":"P",
    "gn:feature_code":"PPL",
    "gn:name":"Aveleda",
    "gn:population":0,
    "gn:timezone":"Europe/Lisbon",
    "iso:country":"PT",
    "wof:name":"Aveleda",
    "wof:placetype":"locality"
},
  "geometry": {"coordinates":[-7.23404,41.84956],"type":"Point"}
}