{
  "type": "Feature",
  "properties": {
    "gn:admin1_code":"21.0",
    "gn:admin2_code":"1706",
    "gn:admin3_code":"170609.0",
    "gn:asciiname":"Nogueiro",
    "gn:country_code":"PT",
    "gn:dem":802,
    "gn:feature_class":"P",
    "gn:feature_code":"PPL",
    "gn:name":"Nogueir\u00f3",
    "gn:population":0,
    "gn:timezone":"Europe/Lisbon",
    "iso:country":"PT",
    "wof:name":"Nogueiro",
    "wof:placetype":"locality"
},
  "geometry": {"coordinates":[-7.97585,41.69794],"type":"Point"}
}