{
  "type": "Feature",
  "properties": {
    "gn:admin1_code":"18",
    "gn:admin2_code":"1407",
    "gn:admin3_code":"140702.0",
    "gn:asciiname":"Casais do Anafe do Meio",
    "gn:country_code":"PT",
    "gn:dem":133,
    "gn:feature_class":"P",
    "gn:feature_code":"PPL",
    "gn:name":"Casais do Anafe do Meio",
    "gn:population":0,
    "gn:timezone":"Europe/Lisbon",
    "iso:country":"PT",
    "wof:name":"Casais do Anafe do Meio",
    "wof:placetype":"locality"
},
  "geometry": {"coordinates":[-8.34037,39.28182],"type":"Point"}
}