{
  "type": "Feature",
  "properties": {
    "gn:admin1_code":"14",
    "gn:admin2_code":"1109",
    "gn:admin3_code":"110911.0",
    "gn:asciiname":"Cartaxaria",
    "gn:country_code":"PT",
    "gn:dem":158,
    "gn:feature_class":"P",
    "gn:feature_code":"PPL",
    "gn:name":"Cartaxaria",
    "gn:population":0,
    "gn:timezone":"Europe/Lisbon",
    "iso:country":"PT",
    "wof:name":"Cartaxaria",
    "wof:placetype":"locality"
},
  "geometry": {"coordinates":[-9.16969,38.93144],"type":"Point"}
}