{
  "type": "Feature",
  "properties": {
    "gn:admin1_code":"16",
    "gn:admin2_code":"1214",
    "gn:admin3_code":"121406.0",
    "gn:asciiname":"Varandas",
    "gn:country_code":"PT",
    "gn:dem":660,
    "gn:feature_class":"P",
    "gn:feature_code":"PPL",
    "gn:name":"Varandas",
    "gn:population":0,
    "gn:timezone":"Europe/Lisbon",
    "iso:country":"PT",
    "wof:name":"Varandas",
    "wof:placetype":"locality"
},
  "geometry": {"coordinates":[-7.39653,39.31543],"type":"Point"}
}