{
  "type": "Feature",
  "properties": {
    "gn:admin1_code":"22.0",
    "gn:admin2_code":"1824",
    "gn:admin3_code":"182402.0",
    "gn:asciiname":"Confulcos",
    "gn:country_code":"PT",
    "gn:dem":542,
    "gn:feature_class":"P",
    "gn:feature_code":"PPL",
    "gn:name":"Confulcos",
    "gn:population":0,
    "gn:timezone":"Europe/Lisbon",
    "iso:country":"PT",
    "wof:name":"Confulcos",
    "wof:placetype":"locality"
},
  "geometry": {"coordinates":[-8.14425,40.68872],"type":"Point"}
}