{
  "type": "Feature",
  "properties": {
    "gn:admin1_code":"21.0",
    "gn:admin2_code":"1707",
    "gn:admin3_code":"170702.0",
    "gn:asciiname":"Carva",
    "gn:country_code":"PT",
    "gn:dem":774,
    "gn:feature_class":"P",
    "gn:feature_code":"PPL",
    "gn:name":"Carva",
    "gn:population":0,
    "gn:timezone":"Europe/Lisbon",
    "iso:country":"PT",
    "wof:name":"Carva",
    "wof:placetype":"locality"
},
  "geometry": {"coordinates":[-7.55787,41.41339],"type":"Point"}
}