{
  "type": "Feature",
  "properties": {
    "gn:admin1_code":"20.0",
    "gn:admin2_code":"1601",
    "gn:admin3_code":"160146.0",
    "gn:asciiname":"Cunhas",
    "gn:country_code":"PT",
    "gn:dem":463,
    "gn:feature_class":"P",
    "gn:feature_code":"PPL",
    "gn:name":"Cunhas",
    "gn:population":0,
    "gn:timezone":"Europe/Lisbon",
    "iso:country":"PT",
    "wof:name":"Cunhas",
    "wof:placetype":"locality"
},
  "geometry": {"coordinates":[-8.23914,41.87674000000001],"type":"Point"}
}