{
  "type": "Feature",
  "properties": {
    "gn:admin1_code":"22",
    "gn:admin2_code":"1808",
    "gn:admin3_code":"180810.0",
    "gn:asciiname":"Vale de Remigio",
    "gn:country_code":"PT",
    "gn:dem":145,
    "gn:feature_class":"P",
    "gn:feature_code":"PPL",
    "gn:name":"Vale de Rem\u00edgio",
    "gn:population":0,
    "gn:timezone":"Europe/Lisbon",
    "iso:country":"PT",
    "wof:name":"Vale de Remigio",
    "wof:placetype":"locality"
},
  "geometry": {"coordinates":[-8.26608,40.40206],"type":"Point"}
}