{
  "type": "Feature",
  "properties": {
    "gn:admin1_code":"22",
    "gn:admin2_code":"1804",
    "gn:admin3_code":"180405.0",
    "gn:asciiname":"Rebolfo",
    "gn:country_code":"PT",
    "gn:dem":592,
    "gn:feature_class":"P",
    "gn:feature_code":"PPL",
    "gn:name":"Rebolfo",
    "gn:population":0,
    "gn:timezone":"Europe/Lisbon",
    "iso:country":"PT",
    "wof:name":"Rebolfo",
    "wof:placetype":"locality"
},
  "geometry": {"coordinates":[-8.03678,41.0357],"type":"Point"}
}