{
  "type": "Feature",
  "properties": {
    "gn:admin1_code":"2.0",
    "gn:admin2_code":"0104",
    "gn:admin3_code":"10411.0",
    "gn:asciiname":"Cela",
    "gn:country_code":"PT",
    "gn:dem":149,
    "gn:feature_class":"P",
    "gn:feature_code":"PPL",
    "gn:name":"Cela",
    "gn:population":0,
    "gn:timezone":"Europe/Lisbon",
    "iso:country":"PT",
    "wof:name":"Cela",
    "wof:placetype":"locality"
},
  "geometry": {"coordinates":[-8.35031,40.98806],"type":"Point"}
}