{
  "type": "Feature",
  "properties": {
    "gn:admin1_code":"2.0",
    "gn:admin2_code":"0104",
    "gn:admin3_code":"10411.0",
    "gn:asciiname":"Cela",
    "gn:country_code":"PT",
    "gn:dem":149,
    "gn:feature_class":"P",
    "gn:feature_code":"PPL",
    "gn:name":"Cela",
    "gn:population":0,
    "gn:timezone":"Europe/Lisbon",
    "iso:country":"PT",
    "name:ceb_x_preferred":[
        "Cela"
    ],
    "name:ces_x_preferred":[
        "Cela"
    ],
    "name:deu_x_preferred":[
        "Cela"
    ],
    "name:fra_x_preferred":[
        "Cela"
    ],
    "name:glg_x_preferred":[
        "Cela"
    ],
    "name:heb_x_preferred":[
        "\u05e1\u05dc\u05d4"
    ],
    "name:hrv_x_preferred":[
        "Cela"
    ],
    "name:nld_x_preferred":[
        "Cela"
    ],
    "name:pol_x_preferred":[
        "Cela"
    ],
    "name:por_x_preferred":[
        "Cela"
    ],
    "name:slk_x_preferred":[
        "Cela"
    ],
    "name:spa_x_preferred":[
        "Cela"
    ],
    "name:swe_x_preferred":[
        "Cela"
    ],
    "wof:name":"Cela",
    "wof:placetype":"locality"
},
  "geometry": {"coordinates":[-8.35031,40.98806],"type":"Point"}
}