{
  "type": "Feature",
  "properties": {
    "gn:admin1_code":"6.0",
    "gn:admin2_code":"0507",
    "gn:admin3_code":"50710.0",
    "gn:asciiname":"Estalagem",
    "gn:country_code":"PT",
    "gn:dem":552,
    "gn:feature_class":"P",
    "gn:feature_code":"PPL",
    "gn:name":"Estalagem",
    "gn:population":0,
    "gn:timezone":"Europe/Lisbon",
    "iso:country":"PT",
    "wof:name":"Estalagem",
    "wof:placetype":"locality"
},
  "geometry": {"coordinates":[-7.13997,40.19995],"type":"Point"}
}