{
  "type": "Feature",
  "properties": {
    "gn:admin1_code":"4.0",
    "gn:admin2_code":"0312",
    "gn:admin3_code":"31223.0",
    "gn:asciiname":"Armental",
    "gn:country_code":"PT",
    "gn:dem":99,
    "gn:feature_class":"P",
    "gn:feature_code":"PPL",
    "gn:name":"Armental",
    "gn:population":0,
    "gn:timezone":"Europe/Lisbon",
    "iso:country":"PT",
    "wof:name":"Armental",
    "wof:placetype":"locality"
},
  "geometry": {"coordinates":[-8.53951,41.43619],"type":"Point"}
}