{
  "type": "Feature",
  "properties": {
    "gn:admin1_code":"13",
    "gn:admin2_code":"1015",
    "gn:admin3_code":"101514.0",
    "gn:asciiname":"Castelo",
    "gn:country_code":"PT",
    "gn:dem":279,
    "gn:feature_class":"P",
    "gn:feature_code":"PPL",
    "gn:name":"Castelo",
    "gn:population":0,
    "gn:timezone":"Europe/Lisbon",
    "iso:country":"PT",
    "wof:name":"Castelo",
    "wof:placetype":"locality"
},
  "geometry": {"coordinates":[-8.54804,39.89409000000001],"type":"Point"}
}