{
  "type": "Feature",
  "properties": {
    "gn:admin1_code":"17.0",
    "gn:admin2_code":"1307",
    "gn:admin3_code":"130713.0",
    "gn:asciiname":"Pacos de Gaiolo",
    "gn:country_code":"PT",
    "gn:dem":201,
    "gn:feature_class":"P",
    "gn:feature_code":"PPL",
    "gn:name":"Pa\u00e7os de Gaiolo",
    "gn:population":0,
    "gn:timezone":"Europe/Lisbon",
    "iso:country":"PT",
    "wof:name":"Pacos de Gaiolo",
    "wof:placetype":"locality"
},
  "geometry": {"coordinates":[-8.1124,41.10252],"type":"Point"}
}