{
  "type": "Feature",
  "properties": {
    "gn:admin1_code":"22.0",
    "gn:admin2_code":"1804",
    "gn:admin3_code":"180416.0",
    "gn:asciiname":"Fermentaos",
    "gn:country_code":"PT",
    "gn:dem":724,
    "gn:feature_class":"P",
    "gn:feature_code":"PPL",
    "gn:name":"Ferment\u00e3os",
    "gn:population":0,
    "gn:timezone":"Europe/Lisbon",
    "iso:country":"PT",
    "wof:name":"Fermentaos",
    "wof:placetype":"locality"
},
  "geometry": {"coordinates":[-8.04951,41.00983],"type":"Point"}
}