{
  "type": "Feature",
  "properties": {
    "gn:admin1_code":"22.0",
    "gn:admin2_code":"1823",
    "gn:admin3_code":"182318.0",
    "gn:asciiname":"Mundao",
    "gn:country_code":"PT",
    "gn:dem":562,
    "gn:feature_class":"P",
    "gn:feature_code":"PPL",
    "gn:name":"Mund\u00e3o",
    "gn:population":0,
    "gn:timezone":"Europe/Lisbon",
    "iso:country":"PT",
    "wof:name":"Mundao",
    "wof:placetype":"locality"
},
  "geometry": {"coordinates":[-7.86654,40.69418],"type":"Point"}
}