{
  "type": "Feature",
  "properties": {
    "gn:admin1_code":"08",
    "gn:admin2_code":"0706",
    "gn:admin3_code":"70608.0",
    "gn:asciiname":"Petamarica de Baixo",
    "gn:country_code":"PT",
    "gn:dem":101,
    "gn:feature_class":"P",
    "gn:feature_code":"PPL",
    "gn:name":"Petamari\u00e7a de Baixo",
    "gn:population":0,
    "gn:timezone":"Europe/Lisbon",
    "iso:country":"PT",
    "wof:name":"Petamarica de Baixo",
    "wof:placetype":"locality"
},
  "geometry": {"coordinates":[-8.41808,38.75926],"type":"Point"}
}