{
  "type": "Feature",
  "properties": {
    "gn:admin1_code":"13",
    "gn:admin2_code":"1016",
    "gn:admin3_code":"101611.0",
    "gn:asciiname":"Fonte do Oleiro",
    "gn:country_code":"PT",
    "gn:dem":159,
    "gn:feature_class":"P",
    "gn:feature_code":"PPL",
    "gn:name":"Fonte do Oleiro",
    "gn:population":0,
    "gn:timezone":"Europe/Lisbon",
    "iso:country":"PT",
    "wof:name":"Fonte do Oleiro",
    "wof:placetype":"locality"
},
  "geometry": {"coordinates":[-8.8105,39.62494],"type":"Point"}
}