{
  "type": "Feature",
  "properties": {
    "gn:admin1_code":"18",
    "gn:admin2_code":"1418",
    "gn:admin3_code":"141805.0",
    "gn:asciiname":"Algaz",
    "gn:country_code":"PT",
    "gn:dem":114,
    "gn:feature_class":"P",
    "gn:feature_code":"PPL",
    "gn:name":"Algaz",
    "gn:population":0,
    "gn:timezone":"Europe/Lisbon",
    "iso:country":"PT",
    "wof:name":"Algaz",
    "wof:placetype":"locality"
},
  "geometry": {"coordinates":[-8.36248,39.62413],"type":"Point"}
}