{
  "type": "Feature",
  "properties": {
    "gn:admin1_code":"4.0",
    "gn:admin2_code":"0306",
    "gn:admin3_code":"30602.0",
    "gn:asciiname":"Cedo Bem",
    "gn:country_code":"PT",
    "gn:dem":-9999,
    "gn:feature_class":"P",
    "gn:feature_code":"PPL",
    "gn:name":"Cedo Bem",
    "gn:population":0,
    "gn:timezone":"Europe/Lisbon",
    "iso:country":"PT",
    "wof:name":"Cedo Bem",
    "wof:placetype":"locality"
},
  "geometry": {"coordinates":[-8.78396,41.49701],"type":"Point"}
}