{
  "type": "Feature",
  "properties": {
    "gn:gn_country":"PT",
    "gn:gn_fcode":"PPL",
    "gn:gn_pop":11336,
    "gn:population":11336,
    "iso:country":"PT",
    "name:deu_x_preferred":[
        "Moreira"
    ],
    "name:eng_x_preferred":[
        "Moreira"
    ],
    "name:fra_x_preferred":[
        "Moreira"
    ],
    "name:glg_x_preferred":[
        "Moreira"
    ],
    "name:kaz_x_preferred":[
        "\u041c\u043e\u0440\u0435\u0439\u0440\u0430"
    ],
    "name:msa_x_preferred":[
        "Moreira"
    ],
    "name:nld_x_preferred":[
        "Moreira"
    ],
    "name:por_x_preferred":[
        "Moreira"
    ],
    "name:rus_x_preferred":[
        "\u041c\u043e\u0440\u0435\u0439\u0440\u0430"
    ],
    "name:spa_x_preferred":[
        "Moreira"
    ],
    "name:zho_x_preferred":[
        "Moreira"
    ],
    "qs_pg:aaroncc":"PT",
    "qs_pg:gn_country":"PT",
    "qs_pg:gn_fcode":"PPL",
    "qs_pg:gn_pop":11336,
    "qs_pg:name":"Moreira",
    "qs_pg:name_adm0":"Portugal",
    "qs_pg:name_adm1":"Porto",
    "qs_pg:photos_9r":0,
    "qs_pg:photos_sr":0,
    "qs_pg:pop_sr":6,
    "qs_pg:qs_pg_placetype":"locality",
    "qs_pg:qs_pg_placetype_gp":"Town",
    "qs_pg:woe_adm0":23424925,
    "woe:adm0_id":23424925,
    "woe:name_adm0":"Portugal",
    "woe:name_adm1":"Porto",
    "woe:placetype":"Town",
    "wof:name":"Moreira",
    "wof:placetype":"locality",
    "wof:population":11336
},
  "geometry": {"coordinates":[-8.38939,41.056],"type":"Point"}
}