{
  "type": "Feature",
  "properties": {
    "iso:country":"PT",
    "qs_pg:aaroncc":"PT",
    "qs_pg:name":"Alto de S\u00e3o Jo\u00e3o",
    "qs_pg:name_adm0":"Portugal",
    "qs_pg:name_adm1":"Coimbra",
    "qs_pg:photos":19,
    "qs_pg:photos_1k":4,
    "qs_pg:photos_9k":1,
    "qs_pg:photos_9r":1,
    "qs_pg:photos_all":19,
    "qs_pg:photos_sr":1,
    "qs_pg:pop_sr":0,
    "qs_pg:qs_pg_placetype":"locality",
    "qs_pg:qs_pg_placetype_gp":"Town",
    "qs_pg:woe_adm0":23424925,
    "woe:adm0_id":23424925,
    "woe:name_adm0":"Portugal",
    "woe:name_adm1":"Coimbra",
    "woe:placetype":"Town",
    "wof:name":"Alto de S\u00e3o Jo\u00e3o",
    "wof:placetype":"locality"
},
  "geometry": {"coordinates":[-8.406322,40.193233],"type":"Point"}
}