{
  "type": "Feature",
  "properties": {
    "gn:admin1_code":"4.0",
    "gn:admin2_code":"0304",
    "gn:admin3_code":"30403.0",
    "gn:asciiname":"Gaiteiras",
    "gn:country_code":"PT",
    "gn:dem":226,
    "gn:feature_class":"P",
    "gn:feature_code":"PPL",
    "gn:name":"Gaiteiras",
    "gn:population":0,
    "gn:timezone":"Europe/Lisbon",
    "iso:country":"PT",
    "wof:name":"Gaiteiras",
    "wof:placetype":"locality"
},
  "geometry": {"coordinates":[-7.95164,41.48155],"type":"Point"}
}