{
  "type": "Feature",
  "properties": {
    "gn:admin1_code":"18",
    "gn:admin2_code":"1416",
    "gn:admin3_code":"141603.0",
    "gn:asciiname":"Dom Fernando",
    "gn:country_code":"PT",
    "gn:dem":124,
    "gn:feature_class":"P",
    "gn:feature_code":"PPL",
    "gn:name":"Dom Fernando",
    "gn:population":0,
    "gn:timezone":"Europe/Lisbon",
    "iso:country":"PT",
    "wof:name":"Dom Fernando",
    "wof:placetype":"locality"
},
  "geometry": {"coordinates":[-8.69363,39.34307],"type":"Point"}
}