{
  "type": "Feature",
  "properties": {
    "gn:admin1_code":"4.0",
    "gn:admin2_code":"0303",
    "gn:admin3_code":"30362.0",
    "gn:asciiname":"Chascas",
    "gn:country_code":"PT",
    "gn:dem":152,
    "gn:feature_class":"P",
    "gn:feature_code":"PPL",
    "gn:name":"Chascas",
    "gn:population":0,
    "gn:timezone":"Europe/Lisbon",
    "iso:country":"PT",
    "wof:name":"Chascas",
    "wof:placetype":"locality"
},
  "geometry": {"coordinates":[-8.47463,41.50602],"type":"Point"}
}