{
  "type": "Feature",
  "properties": {
    "gn:admin1_code":"04",
    "gn:admin2_code":"0303",
    "gn:admin3_code":"30315.0",
    "gn:asciiname":"Sao Miguel",
    "gn:country_code":"PT",
    "gn:dem":172,
    "gn:feature_class":"P",
    "gn:feature_code":"PPL",
    "gn:name":"S\u00e3o Miguel",
    "gn:population":0,
    "gn:timezone":"Europe/Lisbon",
    "iso:country":"PT",
    "wof:name":"Sao Miguel",
    "wof:placetype":"locality"
},
  "geometry": {"coordinates":[-8.43721,41.50816],"type":"Point"}
}