{
  "type": "Feature",
  "properties": {
    "gn:country":"PT",
    "gn:fcode":"PPL",
    "gn:population":0,
    "iso:country":"PT",
    "name:ast_x_preferred":[
        "Ancede"
    ],
    "name:ceb_x_preferred":[
        "Ancede"
    ],
    "name:che_x_preferred":[
        "\u0410\u043d\u0441\u0435\u0434\u0435"
    ],
    "name:deu_x_preferred":[
        "Ancede"
    ],
    "name:eng_x_preferred":[
        "Ancede"
    ],
    "name:fra_x_preferred":[
        "Ancede"
    ],
    "name:kaz_x_preferred":[
        "\u0410\u043d\u0441\u0435\u0434\u0435"
    ],
    "name:nld_x_preferred":[
        "Ancede"
    ],
    "name:por_x_preferred":[
        "Ancede"
    ],
    "name:rus_x_preferred":[
        "\u0410\u043d\u0441\u0435\u0434\u0435"
    ],
    "name:spa_x_preferred":[
        "Ancede"
    ],
    "name:tat_x_preferred":[
        "\u0410\u043d\u0441\u0435\u0434\u0435"
    ],
    "name:zho_x_preferred":[
        "\u5b89\u585e\u8fea"
    ],
    "qs_pg:aaroncc":"PT",
    "qs_pg:gn_country":"PT",
    "qs_pg:gn_fcode":"PPL",
    "qs_pg:gn_pop":0,
    "qs_pg:name":"Ancede",
    "qs_pg:name_adm0":"Portugal",
    "qs_pg:name_adm1":"Braga",
    "qs_pg:photos_9r":0,
    "qs_pg:photos_sr":0,
    "qs_pg:pop_sr":0,
    "qs_pg:qs_pg_placetype":"locality",
    "qs_pg:qs_pg_placetype_gp":"Town",
    "qs_pg:woe_adm0":23424925,
    "woe:adm0_id":23424925,
    "woe:name_adm0":"Portugal",
    "woe:name_adm1":"Braga",
    "woe:placetype":"Town",
    "wof:name":"Ancede",
    "wof:placetype":"locality"
},
  "geometry": {"coordinates":[-8.05691,41.10199],"type":"Point"}
}