{
  "type": "Feature",
  "properties": {
    "gn:admin1_code":"4.0",
    "gn:admin2_code":"0302",
    "gn:admin3_code":"30247.0",
    "gn:asciiname":"Martim de Alem",
    "gn:country_code":"PT",
    "gn:dem":82,
    "gn:feature_class":"P",
    "gn:feature_code":"PPL",
    "gn:name":"Martim de Al\u00e9m",
    "gn:population":0,
    "gn:timezone":"Europe/Lisbon",
    "iso:country":"PT",
    "wof:name":"Martim de Alem",
    "wof:placetype":"locality"
},
  "geometry": {"coordinates":[-8.50487,41.5366],"type":"Point"}
}