{
  "type": "Feature",
  "properties": {
    "gn:admin1_code":"4.0",
    "gn:admin2_code":"0313",
    "gn:admin3_code":"31317.0",
    "gn:asciiname":"Pacos",
    "gn:country_code":"PT",
    "gn:dem":72,
    "gn:feature_class":"P",
    "gn:feature_code":"PPL",
    "gn:name":"Pa\u00e7os",
    "gn:population":0,
    "gn:timezone":"Europe/Lisbon",
    "iso:country":"PT",
    "wof:name":"Pacos",
    "wof:placetype":"locality"
},
  "geometry": {"coordinates":[-8.42508,41.6652],"type":"Point"}
}