{
  "type": "Feature",
  "properties": {
    "gn:admin1_code":"20.0",
    "gn:admin2_code":"1608",
    "gn:admin3_code":"160808.0",
    "gn:asciiname":"Azenhas",
    "gn:country_code":"PT",
    "gn:dem":142,
    "gn:feature_class":"P",
    "gn:feature_code":"PPL",
    "gn:name":"Azenhas",
    "gn:population":0,
    "gn:timezone":"Europe/Lisbon",
    "iso:country":"PT",
    "wof:name":"Azenhas",
    "wof:placetype":"locality"
},
  "geometry": {"coordinates":[-8.6178,42.03013],"type":"Point"}
}