{
  "type": "Feature",
  "properties": {
    "gn:admin1_code":"02",
    "gn:admin2_code":"0104",
    "gn:admin3_code":"10416.0",
    "gn:asciiname":"Sao Mamede",
    "gn:country_code":"PT",
    "gn:dem":313,
    "gn:feature_class":"P",
    "gn:feature_code":"PPL",
    "gn:name":"S\u00e3o Mamede",
    "gn:population":0,
    "gn:timezone":"Europe/Lisbon",
    "iso:country":"PT",
    "wof:name":"Sao Mamede",
    "wof:placetype":"locality"
},
  "geometry": {"coordinates":[-8.29092,40.95465],"type":"Point"}
}