{
  "type": "Feature",
  "properties": {
    "gn:admin1_code":"2.0",
    "gn:admin2_code":"0109",
    "gn:admin3_code":"10927.0",
    "gn:asciiname":"Casal do Ido",
    "gn:country_code":"PT",
    "gn:dem":171,
    "gn:feature_class":"P",
    "gn:feature_code":"PPL",
    "gn:name":"Casal do Ido",
    "gn:population":0,
    "gn:timezone":"Europe/Lisbon",
    "iso:country":"PT",
    "wof:name":"Casal do Ido",
    "wof:placetype":"locality"
},
  "geometry": {"coordinates":[-8.5095,40.97375],"type":"Point"}
}