{
  "type": "Feature",
  "properties": {
    "gn:admin1_code":"17.0",
    "gn:admin2_code":"1317",
    "gn:admin3_code":"131703.0",
    "gn:asciiname":"Curro",
    "gn:country_code":"PT",
    "gn:dem":112,
    "gn:feature_class":"P",
    "gn:feature_code":"PPL",
    "gn:name":"Curro",
    "gn:population":0,
    "gn:timezone":"Europe/Lisbon",
    "iso:country":"PT",
    "wof:name":"Curro",
    "wof:placetype":"locality"
},
  "geometry": {"coordinates":[-8.59951,41.07523],"type":"Point"}
}