{
  "type": "Feature",
  "properties": {
    "gn:admin1_code":"7.0",
    "gn:admin2_code":"0613",
    "gn:admin3_code":"61309.0",
    "gn:asciiname":"Beco",
    "gn:country_code":"PT",
    "gn:dem":141,
    "gn:feature_class":"P",
    "gn:feature_code":"PPL",
    "gn:name":"Beco",
    "gn:population":0,
    "gn:timezone":"Europe/Lisbon",
    "iso:country":"PT",
    "wof:name":"Beco",
    "wof:placetype":"locality"
},
  "geometry": {"coordinates":[-8.21893,40.29348],"type":"Point"}
}