{
  "type": "Feature",
  "properties": {
    "gn:admin1_code":"14",
    "gn:admin2_code":"1101",
    "gn:admin3_code":"110103.0",
    "gn:asciiname":"Aldeia Gavinha",
    "gn:country_code":"PT",
    "gn:dem":115,
    "gn:feature_class":"P",
    "gn:feature_code":"PPL",
    "gn:name":"Aldeia Gavinha",
    "gn:population":0,
    "gn:timezone":"Europe/Lisbon",
    "iso:country":"PT",
    "name:und_x_variant":[
        "Aldegavinha",
        "Aldeia Gavinha"
    ],
    "wof:name":"Aldeia Gavinha",
    "wof:placetype":"locality"
},
  "geometry": {"coordinates":[-9.09534,39.08377],"type":"Point"}
}