{
  "type": "Feature",
  "properties": {
    "gn:admin1_code":"14",
    "gn:admin2_code":"1101",
    "gn:admin3_code":"110103.0",
    "gn:asciiname":"Aldeia Gavinha",
    "gn:country_code":"PT",
    "gn:dem":115,
    "gn:feature_class":"P",
    "gn:feature_code":"PPL",
    "gn:name":"Aldeia Gavinha",
    "gn:population":0,
    "gn:timezone":"Europe/Lisbon",
    "iso:country":"PT",
    "name:ceb_x_preferred":[
        "Aldeia Gavinha"
    ],
    "name:deu_x_preferred":[
        "Aldeia Gavinha"
    ],
    "name:fas_x_preferred":[
        "\u0627\u0644\u062f\u06cc\u0627 \u06af\u0627\u0648\u06cc\u0646\u0647\u0627"
    ],
    "name:kaz_x_preferred":[
        "\u0410\u043b\u0434\u0435\u0439\u044f-\u0413\u0430\u0432\u0438\u043d\u044c\u044f"
    ],
    "name:nld_x_preferred":[
        "Aldeia Gavinha"
    ],
    "name:pol_x_preferred":[
        "Aldeia Gavinha"
    ],
    "name:por_x_preferred":[
        "Aldeia Gavinha"
    ],
    "name:rus_x_preferred":[
        "\u0410\u043b\u0434\u0435\u044f-\u0413\u0430\u0432\u0438\u043d\u044c\u044f"
    ],
    "name:spa_x_preferred":[
        "Aldeia Gavinha"
    ],
    "name:ukr_x_preferred":[
        "\u0410\u043b\u0434\u0435\u0439\u044f-\u0413\u0430\u0432\u0456\u043d\u044f"
    ],
    "name:und_x_variant":[
        "Aldegavinha"
    ],
    "wof:name":"Aldeia Gavinha",
    "wof:placetype":"locality"
},
  "geometry": {"coordinates":[-9.09534,39.08377],"type":"Point"}
}