{
  "type": "Feature",
  "properties": {
    "gn:admin1_code":"7.0",
    "gn:admin2_code":"0616",
    "gn:admin3_code":"61601.0",
    "gn:asciiname":"Azere",
    "gn:country_code":"PT",
    "gn:dem":213,
    "gn:feature_class":"P",
    "gn:feature_code":"PPL",
    "gn:name":"\u00c1zere",
    "gn:population":0,
    "gn:timezone":"Europe/Lisbon",
    "iso:country":"PT",
    "wof:name":"Azere",
    "wof:placetype":"locality"
},
  "geometry": {"coordinates":[-8.09091,40.34889],"type":"Point"}
}