{
  "type": "Feature",
  "properties": {
    "gn:admin1_code":"17.0",
    "gn:admin2_code":"1301",
    "gn:admin3_code":"130116.0",
    "gn:asciiname":"Gatao",
    "gn:country_code":"PT",
    "gn:dem":135,
    "gn:feature_class":"P",
    "gn:feature_code":"PPL",
    "gn:name":"Gat\u00e3o",
    "gn:population":0,
    "gn:timezone":"Europe/Lisbon",
    "iso:country":"PT",
    "wof:name":"Gatao",
    "wof:placetype":"locality"
},
  "geometry": {"coordinates":[-8.06047,41.29496],"type":"Point"}
}