{
  "type": "Feature",
  "properties": {
    "gn:admin1_code":"18",
    "gn:admin2_code":"1401",
    "gn:admin3_code":"140118.0",
    "gn:asciiname":"Carrapatoso",
    "gn:country_code":"PT",
    "gn:dem":197,
    "gn:feature_class":"P",
    "gn:feature_code":"PPL",
    "gn:name":"Carrapatoso",
    "gn:population":0,
    "gn:timezone":"Europe/Lisbon",
    "iso:country":"PT",
    "wof:name":"Carrapatoso",
    "wof:placetype":"locality"
},
  "geometry": {"coordinates":[-8.23488,39.59025],"type":"Point"}
}