{
  "type": "Feature",
  "properties": {
    "gn:admin1_code":"18",
    "gn:admin2_code":"1421",
    "gn:admin3_code":"142111.0",
    "gn:asciiname":"Bairro",
    "gn:country_code":"PT",
    "gn:dem":304,
    "gn:feature_class":"P",
    "gn:feature_code":"PPL",
    "gn:name":"Bairro",
    "gn:population":0,
    "gn:timezone":"Europe/Lisbon",
    "iso:country":"PT",
    "name:ast_x_preferred":[
        "Barriu"
    ],
    "name:cat_x_preferred":[
        "Barri"
    ],
    "name:glg_x_preferred":[
        "Barrio"
    ],
    "name:por_x_preferred":[
        "Bairro"
    ],
    "name:tur_x_preferred":[
        "Bairro"
    ],
    "wof:name":"Bairro",
    "wof:placetype":"locality"
},
  "geometry": {"coordinates":[-8.59209,39.57718],"type":"Point"}
}