{
  "type": "Feature",
  "properties": {
    "gn:admin1_code":"20",
    "gn:admin2_code":"1608",
    "gn:admin3_code":"160810.0",
    "gn:asciiname":"Soutelo",
    "gn:country_code":"PT",
    "gn:dem":193,
    "gn:feature_class":"P",
    "gn:feature_code":"PPL",
    "gn:name":"Soutelo",
    "gn:population":0,
    "gn:timezone":"Europe/Lisbon",
    "iso:country":"PT",
    "name:ceb_x_preferred":[
        "Soutelo"
    ],
    "name:deu_x_preferred":[
        "Soutelo"
    ],
    "name:glg_x_preferred":[
        "Soutelo"
    ],
    "name:nld_x_preferred":[
        "Soutelo"
    ],
    "name:por_x_preferred":[
        "Soutelo"
    ],
    "name:rus_x_preferred":[
        "\u0421\u043e\u0442\u0435\u043b\u0443"
    ],
    "name:spa_x_preferred":[
        "Soutelo"
    ],
    "name:ukr_x_preferred":[
        "\u0421\u043e\u0442\u0435\u043b\u0443"
    ],
    "wof:name":"Soutelo",
    "wof:placetype":"locality"
},
  "geometry": {"coordinates":[-8.57052,42.02238],"type":"Point"}
}