{
  "type": "Feature",
  "properties": {
    "gn:admin1_code":"06",
    "gn:admin2_code":"0502",
    "gn:admin3_code":"50222.0",
    "gn:asciiname":"Violeiro",
    "gn:country_code":"PT",
    "gn:dem":504,
    "gn:feature_class":"P",
    "gn:feature_code":"PPL",
    "gn:name":"Violeiro",
    "gn:population":0,
    "gn:timezone":"Europe/Lisbon",
    "iso:country":"PT",
    "wof:name":"Violeiro",
    "wof:placetype":"locality"
},
  "geometry": {"coordinates":[-7.65287,40.03132],"type":"Point"}
}