{
  "type": "Feature",
  "properties": {
    "gn:admin1_code":"13",
    "gn:admin2_code":"1001",
    "gn:admin3_code":"100114.0",
    "gn:asciiname":"Moita do Poco",
    "gn:country_code":"PT",
    "gn:dem":208,
    "gn:feature_class":"P",
    "gn:feature_code":"PPL",
    "gn:name":"Moita do Po\u00e7o",
    "gn:population":0,
    "gn:timezone":"Europe/Lisbon",
    "iso:country":"PT",
    "wof:name":"Moita do Poco",
    "wof:placetype":"locality"
},
  "geometry": {"coordinates":[-8.94321,39.44216],"type":"Point"}
}