{
  "type": "Feature",
  "properties": {
    "gn:admin1_code":"04",
    "gn:admin2_code":"0313",
    "gn:admin3_code":"31304.0",
    "gn:asciiname":"Vila Seca",
    "gn:country_code":"PT",
    "gn:dem":72,
    "gn:feature_class":"P",
    "gn:feature_code":"PPL",
    "gn:name":"Vila Seca",
    "gn:population":0,
    "gn:timezone":"Europe/Lisbon",
    "iso:country":"PT",
    "name:ceb_x_preferred":[
        "Vila Seca"
    ],
    "name:deu_x_preferred":[
        "Vila Seca"
    ],
    "name:fra_x_preferred":[
        "Vila Seca"
    ],
    "name:kaz_x_preferred":[
        "\u0412\u0438\u043b\u0430-\u0421\u0435\u043a\u0430"
    ],
    "name:nld_x_preferred":[
        "Vila Seca"
    ],
    "name:por_x_preferred":[
        "Vila Seca"
    ],
    "name:rus_x_preferred":[
        "\u0412\u0438\u043b\u0430-\u0421\u0435\u043a\u0430"
    ],
    "name:spa_x_preferred":[
        "Vila Seca"
    ],
    "name:ukr_x_preferred":[
        "\u0412\u0456\u043b\u0430-\u0421\u0435\u043a\u0430"
    ],
    "wof:name":"Vila Seca",
    "wof:placetype":"locality"
},
  "geometry": {"coordinates":[-8.48784,41.63442],"type":"Point"}
}