{
  "type": "Feature",
  "properties": {
    "gn:admin1_code":"06",
    "gn:admin2_code":"0509",
    "gn:admin3_code":"50910.0",
    "gn:asciiname":"Palhais",
    "gn:country_code":"PT",
    "gn:dem":261,
    "gn:feature_class":"P",
    "gn:feature_code":"PPL",
    "gn:name":"Palhais",
    "gn:population":0,
    "gn:timezone":"Europe/Lisbon",
    "iso:country":"PT",
    "wof:name":"Palhais",
    "wof:placetype":"locality"
},
  "geometry": {"coordinates":[-8.19916,39.76439],"type":"Point"}
}