{
  "type": "Feature",
  "properties": {
    "gn:admin1_code":"22",
    "gn:admin2_code":"1803",
    "gn:admin3_code":"180314.0",
    "gn:asciiname":"Relva",
    "gn:country_code":"PT",
    "gn:dem":929,
    "gn:feature_class":"P",
    "gn:feature_code":"PPL",
    "gn:name":"Relva",
    "gn:population":0,
    "gn:timezone":"Europe/Lisbon",
    "iso:country":"PT",
    "name:ceb_x_preferred":[
        "Relva"
    ],
    "name:deu_x_preferred":[
        "Relva"
    ],
    "name:msa_x_preferred":[
        "Relva"
    ],
    "name:por_x_preferred":[
        "Relva"
    ],
    "name:rus_x_preferred":[
        "\u0420\u0435\u043b\u0432\u0430"
    ],
    "name:spa_x_preferred":[
        "Relva"
    ],
    "wof:name":"Relva",
    "wof:placetype":"locality"
},
  "geometry": {"coordinates":[-7.85664,40.95696],"type":"Point"}
}