{
  "type": "Feature",
  "properties": {
    "gn:admin1_code":"09",
    "gn:admin2_code":"0808",
    "gn:admin3_code":"80808.0",
    "gn:asciiname":"Cerro do Mocho",
    "gn:country_code":"PT",
    "gn:dem":106,
    "gn:feature_class":"P",
    "gn:feature_code":"PPL",
    "gn:name":"Cerro do Mocho",
    "gn:population":0,
    "gn:timezone":"Europe/Lisbon",
    "iso:country":"PT",
    "wof:name":"Cerro do Mocho",
    "wof:placetype":"locality"
},
  "geometry": {"coordinates":[-8.03644,37.11131],"type":"Point"}
}