{
  "type": "Feature",
  "properties": {
    "gn:admin1_code":"08",
    "gn:admin2_code":"0704",
    "gn:admin3_code":"70404.0",
    "gn:asciiname":"Junceira",
    "gn:country_code":"PT",
    "gn:dem":290,
    "gn:feature_class":"P",
    "gn:feature_code":"PPL",
    "gn:name":"Junceira",
    "gn:population":0,
    "gn:timezone":"Europe/Lisbon",
    "iso:country":"PT",
    "wof:name":"Junceira",
    "wof:placetype":"locality"
},
  "geometry": {"coordinates":[-7.67144,38.7734],"type":"Point"}
}