{
  "type": "Feature",
  "properties": {
    "gn:admin1_code":"7.0",
    "gn:admin2_code":"0615",
    "gn:admin3_code":"61509.0",
    "gn:asciiname":"Louzoes",
    "gn:country_code":"PT",
    "gn:dem":57,
    "gn:feature_class":"P",
    "gn:feature_code":"PPL",
    "gn:name":"Louz\u00f5es",
    "gn:population":0,
    "gn:timezone":"Europe/Lisbon",
    "iso:country":"PT",
    "wof:name":"Louzoes",
    "wof:placetype":"locality"
},
  "geometry": {"coordinates":[-8.65447,40.06829000000001],"type":"Point"}
}