{
  "type": "Feature",
  "properties": {
    "gn:admin1_code":"13",
    "gn:admin2_code":"1013",
    "gn:admin3_code":"101301.0",
    "gn:asciiname":"Casal da Francisca",
    "gn:country_code":"PT",
    "gn:dem":342,
    "gn:feature_class":"P",
    "gn:feature_code":"PPL",
    "gn:name":"Casal da Francisca",
    "gn:population":0,
    "gn:timezone":"Europe/Lisbon",
    "iso:country":"PT",
    "wof:name":"Casal da Francisca",
    "wof:placetype":"locality"
},
  "geometry": {"coordinates":[-8.21206,39.88397],"type":"Point"}
}