{
  "type": "Feature",
  "properties": {
    "gn:admin1_code":"13",
    "gn:admin2_code":"1008",
    "gn:admin3_code":"100805.0",
    "gn:asciiname":"Casal da Fonte",
    "gn:country_code":"PT",
    "gn:dem":370,
    "gn:feature_class":"P",
    "gn:feature_code":"PPL",
    "gn:name":"Casal da Fonte",
    "gn:population":0,
    "gn:timezone":"Europe/Lisbon",
    "iso:country":"PT",
    "wof:name":"Casal da Fonte",
    "wof:placetype":"locality"
},
  "geometry": {"coordinates":[-8.24518,39.86948],"type":"Point"}
}