{
  "type": "Feature",
  "properties": {
    "gn:gn_country":"PT",
    "gn:gn_fcode":"PPL",
    "gn:gn_pop":6540,
    "gn:population":6540,
    "iso:country":"PT",
    "name:ast_x_preferred":[
        "Avanca"
    ],
    "name:ceb_x_preferred":[
        "Avanca"
    ],
    "name:dan_x_preferred":[
        "Avanca"
    ],
    "name:deu_x_preferred":[
        "Avanca"
    ],
    "name:eng_x_preferred":[
        "Avanca"
    ],
    "name:fra_x_preferred":[
        "Avanca"
    ],
    "name:jpn_x_preferred":[
        "\u30a2\u30f4\u30a1\u30f3\u30ab"
    ],
    "name:kaz_x_preferred":[
        "\u0410\u0432\u0430\u043d\u043a\u0430"
    ],
    "name:msa_x_preferred":[
        "Avanca"
    ],
    "name:nan_x_preferred":[
        "Avanca"
    ],
    "name:nld_x_preferred":[
        "Avanca"
    ],
    "name:por_x_preferred":[
        "Avanca"
    ],
    "name:rus_x_preferred":[
        "\u0410\u0432\u0430\u043d\u043a\u0430"
    ],
    "name:spa_x_preferred":[
        "Avanca"
    ],
    "name:swe_x_preferred":[
        "Avanca"
    ],
    "name:ukr_x_preferred":[
        "\u0410\u0432\u0430\u043d\u043a\u0430"
    ],
    "name:zho_x_preferred":[
        "\u963f\u4e07\u5361"
    ],
    "qs_pg:aaroncc":"PT",
    "qs_pg:gn_country":"PT",
    "qs_pg:gn_fcode":"PPL",
    "qs_pg:gn_pop":6540,
    "qs_pg:name":"Avanca",
    "qs_pg:name_adm0":"Portugal",
    "qs_pg:name_adm1":"Aveiro",
    "qs_pg:photos_9k":1,
    "qs_pg:photos_9r":1,
    "qs_pg:photos_all":2,
    "qs_pg:photos_sr":0,
    "qs_pg:pop_sr":5,
    "qs_pg:qs_pg_placetype":"locality",
    "qs_pg:qs_pg_placetype_gp":"Town",
    "qs_pg:woe_adm0":23424925,
    "woe:adm0_id":23424925,
    "woe:name_adm0":"Portugal",
    "woe:name_adm1":"Aveiro",
    "woe:placetype":"Town",
    "wof:name":"Avanca",
    "wof:placetype":"locality",
    "wof:population":6540
},
  "geometry": {"coordinates":[-8.5722,40.80771],"type":"Point"}
}