{
  "type": "Feature",
  "properties": {
    "gn:admin1_code":"11",
    "gn:admin2_code":"0911",
    "gn:admin3_code":"91126.0",
    "gn:asciiname":"Rebolosa",
    "gn:country_code":"PT",
    "gn:dem":799,
    "gn:feature_class":"P",
    "gn:feature_code":"PPL",
    "gn:name":"Rebolosa",
    "gn:population":0,
    "gn:timezone":"Europe/Lisbon",
    "iso:country":"PT",
    "wof:name":"Rebolosa",
    "wof:placetype":"locality"
},
  "geometry": {"coordinates":[-6.91075,40.42206],"type":"Point"}
}