{
  "type": "Feature",
  "properties": {
    "gn:admin1_code":"04",
    "gn:admin2_code":"0309",
    "gn:admin3_code":"30925.0",
    "gn:asciiname":"Vilarinho de Baixo",
    "gn:country_code":"PT",
    "gn:dem":387,
    "gn:feature_class":"P",
    "gn:feature_code":"PPL",
    "gn:name":"Vilarinho de Baixo",
    "gn:population":0,
    "gn:timezone":"Europe/Lisbon",
    "iso:country":"PT",
    "wof:name":"Vilarinho de Baixo",
    "wof:placetype":"locality"
},
  "geometry": {"coordinates":[-8.19011,41.55635],"type":"Point"}
}