{
  "type": "Feature",
  "properties": {
    "gn:country":"PT",
    "gn:fcode":"ADM3",
    "gn:population":0,
    "iso:country":"PT",
    "name:deu_x_preferred":[
        "Le\u00e7a do Balio"
    ],
    "name:eng_x_preferred":[
        "Le\u00e7a do Balio"
    ],
    "name:fra_x_preferred":[
        "Le\u00e7a do Balio"
    ],
    "name:kaz_x_preferred":[
        "\u041b\u0435\u0441\u0430-\u0434\u0443-\u0411\u0430\u043b\u0438\u0443"
    ],
    "name:msa_x_preferred":[
        "Le\u00e7a do Balio"
    ],
    "name:por_x_preferred":[
        "Le\u00e7a do Balio"
    ],
    "name:rus_x_preferred":[
        "\u041b\u0435\u0441\u0430-\u0434\u0443-\u0411\u0430\u043b\u0438\u0443"
    ],
    "name:spa_x_preferred":[
        "Le\u00e7a do Balio"
    ],
    "name:tur_x_preferred":[
        "Le\u00e7a do Balio"
    ],
    "name:zho_x_preferred":[
        "Le\u00e7a do Balio"
    ],
    "qs_pg:aaroncc":"PT",
    "qs_pg:gn_country":"PT",
    "qs_pg:gn_fcode":"ADM3",
    "qs_pg:gn_pop":0,
    "qs_pg:name":"Le\u00e7a do Balio",
    "qs_pg:name_adm0":"Portugal",
    "qs_pg:name_adm1":"Porto",
    "qs_pg:photos":39,
    "qs_pg:photos_1k":8,
    "qs_pg:photos_9k":1,
    "qs_pg:photos_9r":2,
    "qs_pg:photos_all":39,
    "qs_pg:photos_sr":2,
    "qs_pg:pop_sr":0,
    "qs_pg:qs_pg_placetype":"locality",
    "qs_pg:qs_pg_placetype_gp":"Town",
    "qs_pg:woe_adm0":23424925,
    "woe:adm0_id":23424925,
    "woe:name_adm0":"Portugal",
    "woe:name_adm1":"Porto",
    "woe:placetype":"Town",
    "wof:name":"Le\u00e7a do Balio",
    "wof:placetype":"locality"
},
  "geometry": {"coordinates":[-8.63182,41.21236],"type":"Point"}
}