{
  "type": "Feature",
  "properties": {
    "gn:admin1_code":"08",
    "gn:admin2_code":"0706",
    "gn:admin3_code":"70601.0",
    "gn:asciiname":"Monte Retorta",
    "gn:country_code":"PT",
    "gn:dem":62,
    "gn:feature_class":"P",
    "gn:feature_code":"PPL",
    "gn:name":"Monte Retorta",
    "gn:population":0,
    "gn:timezone":"Europe/Lisbon",
    "iso:country":"PT",
    "wof:name":"Monte Retorta",
    "wof:placetype":"locality"
},
  "geometry": {"coordinates":[-8.51689,38.59053],"type":"Point"}
}