{
  "type": "Feature",
  "properties": {
    "gn:admin1_code":"5.0",
    "gn:admin2_code":"0410",
    "gn:admin3_code":"41017.0",
    "gn:asciiname":"Arco",
    "gn:country_code":"PT",
    "gn:dem":510,
    "gn:feature_class":"P",
    "gn:feature_code":"PPL",
    "gn:name":"Arco",
    "gn:population":0,
    "gn:timezone":"Europe/Lisbon",
    "iso:country":"PT",
    "wof:name":"Arco",
    "wof:placetype":"locality"
},
  "geometry": {"coordinates":[-7.16256,41.27947],"type":"Point"}
}