{
  "type": "Feature",
  "properties": {
    "gn:admin1_code":"5.0",
    "gn:admin2_code":"0410",
    "gn:admin3_code":"41017.0",
    "gn:asciiname":"Arco",
    "gn:country_code":"PT",
    "gn:dem":510,
    "gn:feature_class":"P",
    "gn:feature_code":"PPL",
    "gn:name":"Arco",
    "gn:population":0,
    "gn:timezone":"Europe/Lisbon",
    "iso:country":"PT",
    "name:arg_x_preferred":[
        "Arco"
    ],
    "name:bre_x_preferred":[
        "Arco"
    ],
    "name:ceb_x_preferred":[
        "Arco"
    ],
    "name:deu_x_preferred":[
        "Arco"
    ],
    "name:epo_x_preferred":[
        "Arko"
    ],
    "name:eus_x_preferred":[
        "Arco"
    ],
    "name:fra_x_preferred":[
        "Arco"
    ],
    "name:glg_x_preferred":[
        "Arco"
    ],
    "name:hun_x_preferred":[
        "Arco"
    ],
    "name:ina_x_preferred":[
        "Arco"
    ],
    "name:ita_x_preferred":[
        "Arco"
    ],
    "name:jpn_x_preferred":[
        "\u30a2\u30eb\u30b3"
    ],
    "name:nld_x_preferred":[
        "Arco"
    ],
    "name:pol_x_preferred":[
        "Arco"
    ],
    "name:por_x_preferred":[
        "Arco"
    ],
    "name:rus_x_preferred":[
        "\u0410\u0440\u043a\u043e"
    ],
    "name:spa_x_preferred":[
        "Arco"
    ],
    "name:srp_x_preferred":[
        "\u0410\u0440\u043a\u043e"
    ],
    "name:swe_x_preferred":[
        "Arco"
    ],
    "name:ukr_x_preferred":[
        "\u0410\u0440\u043a\u043e"
    ],
    "name:vol_x_preferred":[
        "Arco"
    ],
    "wof:name":"Arco",
    "wof:placetype":"locality"
},
  "geometry": {"coordinates":[-7.16256,41.27947],"type":"Point"}
}