{
  "type": "Feature",
  "properties": {
    "gn:admin1_code":"22.0",
    "gn:admin2_code":"1821",
    "gn:admin3_code":"182115.0",
    "gn:asciiname":"Nandufe",
    "gn:country_code":"PT",
    "gn:dem":305,
    "gn:feature_class":"P",
    "gn:feature_code":"PPL",
    "gn:name":"Nandufe",
    "gn:population":0,
    "gn:timezone":"Europe/Lisbon",
    "iso:country":"PT",
    "wof:name":"Nandufe",
    "wof:placetype":"locality"
},
  "geometry": {"coordinates":[-8.07664,40.54288],"type":"Point"}
}