{
  "type": "Feature",
  "properties": {
    "gn:admin1_code":"08",
    "gn:admin2_code":"0704",
    "gn:admin3_code":"70413.0",
    "gn:asciiname":"Comendadeira",
    "gn:country_code":"PT",
    "gn:dem":256,
    "gn:feature_class":"P",
    "gn:feature_code":"PPL",
    "gn:name":"Comendadeira",
    "gn:population":0,
    "gn:timezone":"Europe/Lisbon",
    "iso:country":"PT",
    "wof:name":"Comendadeira",
    "wof:placetype":"locality"
},
  "geometry": {"coordinates":[-7.53333,38.96667],"type":"Point"}
}