{
  "type": "Feature",
  "properties": {
    "gn:admin1_code":"17.0",
    "gn:admin2_code":"1316",
    "gn:admin3_code":"131628.0",
    "gn:asciiname":"Bairro Piscatorio",
    "gn:country_code":"PT",
    "gn:dem":-9999,
    "gn:feature_class":"P",
    "gn:feature_code":"PPL",
    "gn:name":"Bairro Piscat\u00f3rio",
    "gn:population":0,
    "gn:timezone":"Europe/Lisbon",
    "iso:country":"PT",
    "wof:name":"Bairro Piscatorio",
    "wof:placetype":"locality"
},
  "geometry": {"coordinates":[-8.75391,41.3581],"type":"Point"}
}