{
  "type": "Feature",
  "properties": {
    "gn:admin1_code":"07",
    "gn:admin2_code":"0613",
    "gn:admin3_code":"61307.0",
    "gn:asciiname":"Ribela",
    "gn:country_code":"PT",
    "gn:dem":205,
    "gn:feature_class":"P",
    "gn:feature_code":"PPL",
    "gn:name":"Ribela",
    "gn:population":0,
    "gn:timezone":"Europe/Lisbon",
    "iso:country":"PT",
    "wof:name":"Ribela",
    "wof:placetype":"locality"
},
  "geometry": {"coordinates":[-8.31115,40.29216],"type":"Point"}
}