{
  "type": "Feature",
  "properties": {
    "gn:admin1_code":"4.0",
    "gn:admin2_code":"0304",
    "gn:admin3_code":"30406.0",
    "gn:asciiname":"Gondarem",
    "gn:country_code":"PT",
    "gn:dem":559,
    "gn:feature_class":"P",
    "gn:feature_code":"PPL",
    "gn:name":"Gondar\u00e9m",
    "gn:population":0,
    "gn:timezone":"Europe/Lisbon",
    "iso:country":"PT",
    "wof:name":"Gondarem",
    "wof:placetype":"locality"
},
  "geometry": {"coordinates":[-8.02042,41.5566],"type":"Point"}
}