{
  "type": "Feature",
  "properties": {
    "gn:admin1_code":"4.0",
    "gn:admin2_code":"0303",
    "gn:admin3_code":"30335.0",
    "gn:asciiname":"Lajes",
    "gn:country_code":"PT",
    "gn:dem":99,
    "gn:feature_class":"P",
    "gn:feature_code":"PPL",
    "gn:name":"Lajes",
    "gn:population":0,
    "gn:timezone":"Europe/Lisbon",
    "iso:country":"PT",
    "name:bpy_x_preferred":[
        "\u09b2\u09be\u099c\u09c7\u09b8"
    ],
    "name:ceb_x_preferred":[
        "Lajes"
    ],
    "name:deu_x_preferred":[
        "Lajes"
    ],
    "name:fra_x_preferred":[
        "Lajes"
    ],
    "name:nld_x_preferred":[
        "Lajes"
    ],
    "name:pol_x_preferred":[
        "Lajes"
    ],
    "name:por_x_preferred":[
        "Lajes"
    ],
    "name:rus_x_preferred":[
        "\u041b\u0430\u0436\u0438\u0448"
    ],
    "name:swe_x_preferred":[
        "Lajes"
    ],
    "name:ukr_x_preferred":[
        "\u041b\u0430\u0436\u0435\u0448"
    ],
    "wof:name":"Lajes",
    "wof:placetype":"locality"
},
  "geometry": {"coordinates":[-8.34973,41.60699],"type":"Point"}
}