{
  "type": "Feature",
  "properties": {
    "iso:country":"PT",
    "name:cat_x_preferred":[
        "Vila do Porto"
    ],
    "name:deu_x_preferred":[
        "Vila do Porto"
    ],
    "name:eng_x_preferred":[
        "Vila do Porto"
    ],
    "name:fra_x_preferred":[
        "Vila do Porto"
    ],
    "name:ita_x_preferred":[
        "Vila do Porto"
    ],
    "name:kor_x_preferred":[
        "\ube4c\ub77c\ub450\ud3ec\ub974\ud22c"
    ],
    "name:lit_x_preferred":[
        "Vila do Portas"
    ],
    "name:msa_x_preferred":[
        "Vila do Porto"
    ],
    "name:nld_x_preferred":[
        "Vila do Porto"
    ],
    "name:pol_x_preferred":[
        "Vila do Porto"
    ],
    "name:por_x_preferred":[
        "Vila do Porto"
    ],
    "name:ron_x_preferred":[
        "Vila do Porto"
    ],
    "name:rus_x_preferred":[
        "\u0412\u0438\u043b\u0430-\u0434\u0443-\u041f\u043e\u0440\u0442\u0443"
    ],
    "name:spa_x_preferred":[
        "Vila do Porto"
    ],
    "name:tur_x_preferred":[
        "Vila do Porto"
    ],
    "name:vie_x_preferred":[
        "Vila do Porto"
    ],
    "name:vol_x_preferred":[
        "Vila do Porto"
    ],
    "name:war_x_preferred":[
        "Vila do Porto"
    ],
    "name:zho_min_nan_x_preferred":[
        "Vila do Porto"
    ],
    "name:zho_x_preferred":[
        "\u6ce2\u723e\u5716\u93ae"
    ],
    "qs:a0":"Portugal",
    "qs:a1":"*Regi\u00e3o Aut\u00f3noma dos A\u00e7ores",
    "qs:a1r":"0",
    "qs:adm0":"Portugal",
    "qs:la_lc":"*",
    "qs:level":"locality",
    "qs:loc":"Vila do Porto",
    "qs:loc_alt":"Vila do Porto",
    "qs:pop":0,
    "qs:type":"buffered point",
    "wd:wordcount":1357,
    "wof:lang":[
        "por"
    ],
    "wof:name":"Vila do Porto",
    "wof:placetype":"locality"
},
  "geometry": {"coordinates":[-25.142737,36.957252],"type":"Point"}
}