{
  "type": "Feature",
  "properties": {
    "gn:admin1_code":"13",
    "gn:admin2_code":"1002",
    "gn:admin3_code":"100205.0",
    "gn:asciiname":"Pelma",
    "gn:country_code":"PT",
    "gn:dem":145,
    "gn:feature_class":"P",
    "gn:feature_code":"PPL",
    "gn:name":"Pelm\u00e1",
    "gn:population":0,
    "gn:timezone":"Europe/Lisbon",
    "iso:country":"PT",
    "wof:name":"Pelma",
    "wof:placetype":"locality"
},
  "geometry": {"coordinates":[-8.45073,39.77136],"type":"Point"}
}