{
  "type": "Feature",
  "properties": {
    "gn:admin1_code":"22.0",
    "gn:admin2_code":"1808",
    "gn:admin3_code":"180808.0",
    "gn:asciiname":"Calvos",
    "gn:country_code":"PT",
    "gn:dem":370,
    "gn:feature_class":"P",
    "gn:feature_code":"PPL",
    "gn:name":"Calvos",
    "gn:population":0,
    "gn:timezone":"Europe/Lisbon",
    "iso:country":"PT",
    "wof:name":"Calvos",
    "wof:placetype":"locality"
},
  "geometry": {"coordinates":[-8.22604,40.47982],"type":"Point"}
}