{
  "type": "Feature",
  "properties": {
    "gn:admin1_code":"7.0",
    "gn:admin2_code":"0613",
    "gn:admin3_code":"61307.0",
    "gn:asciiname":"Carvalhal de Mansores",
    "gn:country_code":"PT",
    "gn:dem":168,
    "gn:feature_class":"P",
    "gn:feature_code":"PPL",
    "gn:name":"Carvalhal de Mansores",
    "gn:population":0,
    "gn:timezone":"Europe/Lisbon",
    "iso:country":"PT",
    "wof:name":"Carvalhal de Mansores",
    "wof:placetype":"locality"
},
  "geometry": {"coordinates":[-8.26844,40.29397],"type":"Point"}
}