{
  "type": "Feature",
  "properties": {
    "gn:admin1_code":"5.0",
    "gn:admin2_code":"0403",
    "gn:admin3_code":"40301.0",
    "gn:asciiname":"Areias",
    "gn:country_code":"PT",
    "gn:dem":663,
    "gn:feature_class":"P",
    "gn:feature_code":"PPL",
    "gn:name":"Areias",
    "gn:population":0,
    "gn:timezone":"Europe/Lisbon",
    "iso:country":"PT",
    "wof:name":"Areias",
    "wof:placetype":"locality"
},
  "geometry": {"coordinates":[-7.32461,41.27693],"type":"Point"}
}