{
  "type": "Feature",
  "properties": {
    "gn:admin1_code":"18",
    "gn:admin2_code":"1401",
    "gn:admin3_code":"140104.0",
    "gn:asciiname":"Brunheirinho",
    "gn:country_code":"PT",
    "gn:dem":140,
    "gn:feature_class":"P",
    "gn:feature_code":"PPL",
    "gn:name":"Brunheirinho",
    "gn:population":0,
    "gn:timezone":"Europe/Lisbon",
    "iso:country":"PT",
    "wof:name":"Brunheirinho",
    "wof:placetype":"locality"
},
  "geometry": {"coordinates":[-8.08186,39.33038],"type":"Point"}
}