{
  "type": "Feature",
  "properties": {
    "gn:admin1_code":"18",
    "gn:admin2_code":"1413",
    "gn:admin3_code":"141302.0",
    "gn:asciiname":"Amendoa",
    "gn:country_code":"PT",
    "gn:dem":416,
    "gn:feature_class":"P",
    "gn:feature_code":"PPL",
    "gn:name":"Am\u00eandoa",
    "gn:population":0,
    "gn:timezone":"Europe/Lisbon",
    "iso:country":"PT",
    "wof:name":"Amendoa",
    "wof:placetype":"locality"
},
  "geometry": {"coordinates":[-8.067,39.65823],"type":"Point"}
}