{
  "type": "Feature",
  "properties": {
    "gn:admin1_code":"18",
    "gn:admin2_code":"1405",
    "gn:admin3_code":"140501.0",
    "gn:asciiname":"Vale de Junco",
    "gn:country_code":"PT",
    "gn:dem":2,
    "gn:feature_class":"P",
    "gn:feature_code":"PPL",
    "gn:name":"Vale de Junco",
    "gn:population":0,
    "gn:timezone":"Europe/Lisbon",
    "iso:country":"PT",
    "wof:name":"Vale de Junco",
    "wof:placetype":"locality"
},
  "geometry": {"coordinates":[-8.76667,38.96667],"type":"Point"}
}