{
  "type": "Feature",
  "properties": {
    "gn:admin1_code":"22.0",
    "gn:admin2_code":"1803",
    "gn:admin3_code":"180316.0",
    "gn:asciiname":"Parada de Ester",
    "gn:country_code":"PT",
    "gn:dem":356,
    "gn:feature_class":"P",
    "gn:feature_code":"PPL",
    "gn:name":"Parada de Ester",
    "gn:population":0,
    "gn:timezone":"Europe/Lisbon",
    "iso:country":"PT",
    "wof:name":"Parada de Ester",
    "wof:placetype":"locality"
},
  "geometry": {"coordinates":[-8.05932,40.93177],"type":"Point"}
}