{
  "type": "Feature",
  "properties": {
    "gn:admin1_code":"17.0",
    "gn:admin2_code":"1306",
    "gn:admin3_code":"130601.0",
    "gn:asciiname":"Parada",
    "gn:country_code":"PT",
    "gn:dem":81,
    "gn:feature_class":"P",
    "gn:feature_code":"PPL",
    "gn:name":"Parada",
    "gn:population":0,
    "gn:timezone":"Europe/Lisbon",
    "iso:country":"PT",
    "wof:name":"Parada",
    "wof:placetype":"locality"
},
  "geometry": {"coordinates":[-8.59225,41.20468],"type":"Point"}
}