{
  "type": "Feature",
  "properties": {
    "gn:admin1_code":"21.0",
    "gn:admin2_code":"1704",
    "gn:admin3_code":"170407.0",
    "gn:asciiname":"Granjao",
    "gn:country_code":"PT",
    "gn:dem":71,
    "gn:feature_class":"P",
    "gn:feature_code":"PPL",
    "gn:name":"Granj\u00e3o",
    "gn:population":0,
    "gn:timezone":"Europe/Lisbon",
    "iso:country":"PT",
    "wof:name":"Granjao",
    "wof:placetype":"locality"
},
  "geometry": {"coordinates":[-7.84567,41.15682],"type":"Point"}
}