{
  "type": "Feature",
  "properties": {
    "gn:admin1_code":"09",
    "gn:admin2_code":"0813",
    "gn:admin3_code":"81305.0",
    "gn:asciiname":"Monte Boi",
    "gn:country_code":"PT",
    "gn:dem":215,
    "gn:feature_class":"P",
    "gn:feature_code":"PPL",
    "gn:name":"Monte Boi",
    "gn:population":0,
    "gn:timezone":"Europe/Lisbon",
    "iso:country":"PT",
    "wof:name":"Monte Boi",
    "wof:placetype":"locality"
},
  "geometry": {"coordinates":[-8.3043,37.25225],"type":"Point"}
}