{
  "type": "Feature",
  "properties": {
    "gn:admin1_code":"08",
    "gn:admin2_code":"0707",
    "gn:admin3_code":"70701.0",
    "gn:asciiname":"Monte das Aguias",
    "gn:country_code":"PT",
    "gn:dem":99,
    "gn:feature_class":"P",
    "gn:feature_code":"PPL",
    "gn:name":"Monte das \u00c1guias",
    "gn:population":0,
    "gn:timezone":"Europe/Lisbon",
    "iso:country":"PT",
    "wof:name":"Monte das Aguias",
    "wof:placetype":"locality"
},
  "geometry": {"coordinates":[-8.12446,38.87466],"type":"Point"}
}