{
  "type": "Feature",
  "properties": {
    "gn:admin1_code":"20.0",
    "gn:admin2_code":"1602",
    "gn:admin3_code":"160218.0",
    "gn:asciiname":"Barreiros",
    "gn:country_code":"PT",
    "gn:dem":44,
    "gn:feature_class":"P",
    "gn:feature_code":"PPL",
    "gn:name":"Barreiros",
    "gn:population":0,
    "gn:timezone":"Europe/Lisbon",
    "iso:country":"PT",
    "name:bpy_x_preferred":[
        "\u09ac\u09be\u09b0\u09cd\u09b0\u09c7\u0987\u09b0\u09cb\u09b8"
    ],
    "name:ceb_x_preferred":[
        "Barreiros"
    ],
    "name:deu_x_preferred":[
        "Barreiros"
    ],
    "name:fra_x_preferred":[
        "Barreiros"
    ],
    "name:glg_x_preferred":[
        "Barreiros"
    ],
    "name:ita_x_preferred":[
        "Barreiros"
    ],
    "name:mlg_x_preferred":[
        "Barreiros"
    ],
    "name:nld_x_preferred":[
        "Barreiros"
    ],
    "name:pol_x_preferred":[
        "Barreiros"
    ],
    "name:por_x_preferred":[
        "Barreiros"
    ],
    "name:rus_x_preferred":[
        "\u0411\u0430\u0440\u0440\u0435\u0439\u0440\u043e\u0441"
    ],
    "name:spa_x_preferred":[
        "Barreiros"
    ],
    "name:swe_x_preferred":[
        "Barreiros"
    ],
    "name:ukr_x_preferred":[
        "\u0411\u0430\u0440\u0440\u0435\u0439\u0440\u0443\u0448"
    ],
    "name:vie_x_preferred":[
        "Barreiros"
    ],
    "name:war_x_preferred":[
        "Barreiros"
    ],
    "wof:name":"Barreiros",
    "wof:placetype":"locality"
},
  "geometry": {"coordinates":[-8.79872,41.89203],"type":"Point"}
}