{
  "type": "Feature",
  "properties": {
    "gn:admin1_code":"20.0",
    "gn:admin2_code":"1602",
    "gn:admin3_code":"160218.0",
    "gn:asciiname":"Barreiros",
    "gn:country_code":"PT",
    "gn:dem":44,
    "gn:feature_class":"P",
    "gn:feature_code":"PPL",
    "gn:name":"Barreiros",
    "gn:population":0,
    "gn:timezone":"Europe/Lisbon",
    "iso:country":"PT",
    "wof:name":"Barreiros",
    "wof:placetype":"locality"
},
  "geometry": {"coordinates":[-8.79872,41.89203],"type":"Point"}
}