{
  "type": "Feature",
  "properties": {
    "gn:admin1_code":"2.0",
    "gn:admin2_code":"0106",
    "gn:admin3_code":"10605.0",
    "gn:asciiname":"Folgoso",
    "gn:country_code":"PT",
    "gn:dem":168,
    "gn:feature_class":"P",
    "gn:feature_code":"PPL",
    "gn:name":"Folgoso",
    "gn:population":0,
    "gn:timezone":"Europe/Lisbon",
    "iso:country":"PT",
    "wof:name":"Folgoso",
    "wof:placetype":"locality"
},
  "geometry": {"coordinates":[-8.34832,41.01988],"type":"Point"}
}