{
  "type": "Feature",
  "properties": {
    "gn:admin1_code":"22",
    "gn:admin2_code":"1816",
    "gn:admin3_code":"181617.0",
    "gn:asciiname":"Preguinho",
    "gn:country_code":"PT",
    "gn:dem":472,
    "gn:feature_class":"P",
    "gn:feature_code":"PPL",
    "gn:name":"Preguinho",
    "gn:population":0,
    "gn:timezone":"Europe/Lisbon",
    "iso:country":"PT",
    "wof:name":"Preguinho",
    "wof:placetype":"locality"
},
  "geometry": {"coordinates":[-8.21427,40.78152],"type":"Point"}
}