{
  "type": "Feature",
  "properties": {
    "gn:admin1_code":"22",
    "gn:admin2_code":"1816",
    "gn:admin3_code":"181617.0",
    "gn:asciiname":"Preguinho",
    "gn:country_code":"PT",
    "gn:dem":472,
    "gn:feature_class":"P",
    "gn:feature_code":"PPL",
    "gn:name":"Preguinho",
    "gn:population":0,
    "gn:timezone":"Europe/Lisbon",
    "iso:country":"PT",
    "name:ara_x_preferred":[
        "\u0628\u0631\u064a\u063a\u064a\u0646\u064a\u0648"
    ],
    "name:deu_x_preferred":[
        "Preguinho"
    ],
    "name:fas_x_preferred":[
        "\u067e\u0631\u06af\u06cc\u0646\u06cc\u0648"
    ],
    "name:fin_x_preferred":[
        "Preguinho"
    ],
    "name:fra_x_preferred":[
        "Preguinho"
    ],
    "name:hun_x_preferred":[
        "Preguinho"
    ],
    "name:ita_x_preferred":[
        "Preguinho"
    ],
    "name:jpn_x_preferred":[
        "\u30b8\u30e7\u30a2\u30f3\u30fb\u30b3\u30a8\u30fc\u30ea\u30e7\u30fb\u30cd\u30c8"
    ],
    "name:kor_x_preferred":[
        "\ud504\ub808\uae30\ub274"
    ],
    "name:mkd_x_preferred":[
        "\u041f\u0440\u0435\u0433\u0443\u045a\u043e"
    ],
    "name:mlt_x_preferred":[
        "Preguinho"
    ],
    "name:nld_x_preferred":[
        "Preguinho"
    ],
    "name:pol_x_preferred":[
        "Preguinho"
    ],
    "name:por_x_preferred":[
        "Preguinho"
    ],
    "name:rus_x_preferred":[
        "\u041a\u043e\u044d\u043b\u044c\u044e \u041d\u0435\u0442\u0443"
    ],
    "name:swe_x_preferred":[
        "Preguinho"
    ],
    "name:tgk_x_preferred":[
        "\u041f\u0440\u0435\u0433\u0443\u0438\u043d\u044e"
    ],
    "wof:name":"Preguinho",
    "wof:placetype":"locality"
},
  "geometry": {"coordinates":[-8.21427,40.78152],"type":"Point"}
}