{
  "type": "Feature",
  "properties": {
    "gn:admin1_code":"11.0",
    "gn:admin2_code":"0909",
    "gn:admin3_code":"90910.0",
    "gn:asciiname":"Ariola",
    "gn:country_code":"PT",
    "gn:dem":621,
    "gn:feature_class":"P",
    "gn:feature_code":"PPL",
    "gn:name":"Ariola",
    "gn:population":0,
    "gn:timezone":"Europe/Lisbon",
    "iso:country":"PT",
    "wof:name":"Ariola",
    "wof:placetype":"locality"
},
  "geometry": {"coordinates":[-7.29805,40.97294],"type":"Point"}
}