{
  "type": "Feature",
  "properties": {
    "gn:country":"PT",
    "gn:fcode":"PPL",
    "gn:population":0,
    "iso:country":"PT",
    "name:ben_x_preferred":[
        "\u09aa\u09be\u09b2\u09be"
    ],
    "name:cat_x_preferred":[
        "Pala"
    ],
    "name:ceb_x_preferred":[
        "Pala"
    ],
    "name:ces_x_preferred":[
        "Pala"
    ],
    "name:deu_x_preferred":[
        "Pala"
    ],
    "name:ell_x_preferred":[
        "\u03a0\u03ac\u03bb\u03b1"
    ],
    "name:est_x_preferred":[
        "Pala"
    ],
    "name:eus_x_preferred":[
        "Pala"
    ],
    "name:fra_x_preferred":[
        "Pala"
    ],
    "name:glg_x_preferred":[
        "Pala"
    ],
    "name:heb_x_preferred":[
        "\u05e4\u05dc\u05d4"
    ],
    "name:hrv_x_preferred":[
        "Pala"
    ],
    "name:hun_x_preferred":[
        "Pala"
    ],
    "name:ita_x_preferred":[
        "Pala"
    ],
    "name:kor_x_preferred":[
        "\ud314\ub77c"
    ],
    "name:lit_x_preferred":[
        "Pala"
    ],
    "name:mal_x_preferred":[
        "\u0d2a\u0d3e\u0d32"
    ],
    "name:nld_x_preferred":[
        "Pala"
    ],
    "name:pol_x_preferred":[
        "Pala"
    ],
    "name:por_x_preferred":[
        "Pala"
    ],
    "name:ron_x_preferred":[
        "Pala"
    ],
    "name:rus_x_preferred":[
        "\u041f\u0430\u043b\u0430"
    ],
    "name:slk_x_preferred":[
        "Pala"
    ],
    "name:spa_x_preferred":[
        "Pala"
    ],
    "name:srp_x_preferred":[
        "\u041f\u0430\u043b\u0430"
    ],
    "name:swe_x_preferred":[
        "Pala"
    ],
    "name:tgl_x_preferred":[
        "Pala"
    ],
    "name:tur_x_preferred":[
        "Pala"
    ],
    "name:ukr_x_preferred":[
        "\u041f\u0430\u043b\u0430"
    ],
    "name:vie_x_preferred":[
        "Pala"
    ],
    "name:vol_x_preferred":[
        "Pala"
    ],
    "qs_pg:aaroncc":"PT",
    "qs_pg:gn_country":"PT",
    "qs_pg:gn_fcode":"PPL",
    "qs_pg:gn_pop":0,
    "qs_pg:name":"Pala",
    "qs_pg:name_adm0":"Portugal",
    "qs_pg:name_adm1":"Porto",
    "qs_pg:photos":16,
    "qs_pg:photos_1k":3,
    "qs_pg:photos_9k":1,
    "qs_pg:photos_9r":1,
    "qs_pg:photos_all":16,
    "qs_pg:photos_sr":1,
    "qs_pg:pop_sr":0,
    "qs_pg:qs_pg_placetype":"locality",
    "qs_pg:qs_pg_placetype_gp":"Town",
    "qs_pg:woe_adm0":23424925,
    "woe:adm0_id":23424925,
    "woe:name_adm0":"Portugal",
    "woe:name_adm1":"Porto",
    "woe:placetype":"Town",
    "wof:name":"Pala",
    "wof:placetype":"locality"
},
  "geometry": {"coordinates":[-8.08752,41.10022],"type":"Point"}
}