{
  "type": "Feature",
  "properties": {
    "gn:admin1_code":"17",
    "gn:admin2_code":"1301",
    "gn:admin3_code":"130129.0",
    "gn:asciiname":"Salvador do Monte",
    "gn:country_code":"PT",
    "gn:dem":322,
    "gn:feature_class":"P",
    "gn:feature_code":"PPL",
    "gn:name":"Salvador do Monte",
    "gn:population":0,
    "gn:timezone":"Europe/Lisbon",
    "iso:country":"PT",
    "wof:name":"Salvador do Monte",
    "wof:placetype":"locality"
},
  "geometry": {"coordinates":[-8.08773,41.24019000000001],"type":"Point"}
}