{
  "type": "Feature",
  "properties": {
    "gn:admin1_code":"21.0",
    "gn:admin2_code":"1712",
    "gn:admin3_code":"171206.0",
    "gn:asciiname":"Canaveses",
    "gn:country_code":"PT",
    "gn:dem":379,
    "gn:feature_class":"P",
    "gn:feature_code":"PPL",
    "gn:name":"Canaveses",
    "gn:population":0,
    "gn:timezone":"Europe/Lisbon",
    "iso:country":"PT",
    "wof:name":"Canaveses",
    "wof:placetype":"locality"
},
  "geometry": {"coordinates":[-7.36277,41.50473],"type":"Point"}
}