{
  "type": "Feature",
  "properties": {
    "gn:country":"PT",
    "gn:fcode":"PPL",
    "gn:population":0,
    "iso:country":"PT",
    "name:ast_x_preferred":[
        "Lardosa"
    ],
    "name:ceb_x_preferred":[
        "Lardosa"
    ],
    "name:deu_x_preferred":[
        "Lardosa"
    ],
    "name:eng_x_preferred":[
        "Lardosa"
    ],
    "name:fra_x_preferred":[
        "Lardosa"
    ],
    "name:kaz_x_preferred":[
        "\u041b\u0430\u0440\u0434\u043e\u0437\u0430"
    ],
    "name:nan_x_preferred":[
        "Lardosa"
    ],
    "name:nld_x_preferred":[
        "Lardosa"
    ],
    "name:por_x_preferred":[
        "Lardosa"
    ],
    "name:rus_x_preferred":[
        "\u041b\u0430\u0440\u0434\u043e\u0437\u0430"
    ],
    "name:spa_x_preferred":[
        "Lardosa"
    ],
    "name:ukr_x_preferred":[
        "\u041b\u0430\u0440\u0434\u043e\u0437\u0430"
    ],
    "qs_pg:aaroncc":"PT",
    "qs_pg:gn_country":"PT",
    "qs_pg:gn_fcode":"PPL",
    "qs_pg:gn_pop":0,
    "qs_pg:name":"Lardosa",
    "qs_pg:name_adm0":"Portugal",
    "qs_pg:name_adm1":"Castelo Branco",
    "qs_pg:photos":92,
    "qs_pg:photos_1k":19,
    "qs_pg:photos_9k":1,
    "qs_pg:photos_9r":3,
    "qs_pg:photos_all":92,
    "qs_pg:photos_sr":3,
    "qs_pg:pop_sr":0,
    "qs_pg:qs_pg_placetype":"locality",
    "qs_pg:qs_pg_placetype_gp":"Town",
    "qs_pg:woe_adm0":23424925,
    "woe:adm0_id":23424925,
    "woe:name_adm0":"Portugal",
    "woe:name_adm1":"Castelo Branco",
    "woe:placetype":"Town",
    "wof:name":"Lardosa",
    "wof:placetype":"locality"
},
  "geometry": {"coordinates":[-7.44557,39.98898],"type":"Point"}
}