{
  "type": "Feature",
  "properties": {
    "gn:admin1_code":"11.0",
    "gn:admin2_code":"0907",
    "gn:admin3_code":"90734.0",
    "gn:asciiname":"Minga Feia",
    "gn:country_code":"PT",
    "gn:dem":877,
    "gn:feature_class":"P",
    "gn:feature_code":"PPL",
    "gn:name":"Minga Feia",
    "gn:population":0,
    "gn:timezone":"Europe/Lisbon",
    "iso:country":"PT",
    "wof:name":"Minga Feia",
    "wof:placetype":"locality"
},
  "geometry": {"coordinates":[-7.26578,40.47147],"type":"Point"}
}