{
  "type": "Feature",
  "properties": {
    "gn:admin1_code":"22",
    "gn:admin2_code":"1820",
    "gn:admin3_code":"182010.0",
    "gn:asciiname":"Vila Cha de Cangueiros",
    "gn:country_code":"PT",
    "gn:dem":839,
    "gn:feature_class":"P",
    "gn:feature_code":"PPL",
    "gn:name":"Vila Ch\u00e3 de Cangueiros",
    "gn:population":0,
    "gn:timezone":"Europe/Lisbon",
    "iso:country":"PT",
    "wof:name":"Vila Cha de Cangueiros",
    "wof:placetype":"locality"
},
  "geometry": {"coordinates":[-7.68784,41.03145],"type":"Point"}
}