{
  "type": "Feature",
  "properties": {
    "gn:admin1_code":"14",
    "gn:admin2_code":"1115",
    "gn:admin3_code":"111506.0",
    "gn:asciiname":"Olival",
    "gn:country_code":"PT",
    "gn:dem":159,
    "gn:feature_class":"P",
    "gn:feature_code":"PPL",
    "gn:name":"Olival",
    "gn:population":0,
    "gn:timezone":"Europe/Lisbon",
    "iso:country":"PT",
    "name:ceb_x_preferred":[
        "Olival"
    ],
    "name:deu_x_preferred":[
        "Olival"
    ],
    "name:fra_x_preferred":[
        "Olival"
    ],
    "name:nld_x_preferred":[
        "Olival"
    ],
    "name:por_x_preferred":[
        "Olival"
    ],
    "name:rus_x_preferred":[
        "\u041e\u043b\u0438\u0432\u0430\u043b"
    ],
    "name:tur_x_preferred":[
        "Olival"
    ],
    "wof:name":"Olival",
    "wof:placetype":"locality"
},
  "geometry": {"coordinates":[-9.25015,38.77079000000001],"type":"Point"}
}