{
  "type": "Feature",
  "properties": {
    "gn:admin1_code":"18",
    "gn:admin2_code":"1418",
    "gn:admin3_code":"141805.0",
    "gn:asciiname":"Assamaca",
    "gn:country_code":"PT",
    "gn:dem":204,
    "gn:feature_class":"P",
    "gn:feature_code":"PPL",
    "gn:name":"Assama\u00e7a",
    "gn:population":0,
    "gn:timezone":"Europe/Lisbon",
    "iso:country":"PT",
    "wof:name":"Assamaca",
    "wof:placetype":"locality"
},
  "geometry": {"coordinates":[-8.35302,39.66825],"type":"Point"}
}