{
  "type": "Feature",
  "properties": {
    "gn:admin1_code":"21.0",
    "gn:admin2_code":"1713",
    "gn:admin3_code":"171302.0",
    "gn:asciiname":"Cidadelha de Jales",
    "gn:country_code":"PT",
    "gn:dem":789,
    "gn:feature_class":"P",
    "gn:feature_code":"PPL",
    "gn:name":"Cidadelha de Jales",
    "gn:population":0,
    "gn:timezone":"Europe/Lisbon",
    "iso:country":"PT",
    "wof:name":"Cidadelha de Jales",
    "wof:placetype":"locality"
},
  "geometry": {"coordinates":[-7.56846,41.46271],"type":"Point"}
}