{
  "type": "Feature",
  "properties": {
    "gn:admin1_code":"20",
    "gn:admin2_code":"1604",
    "gn:admin3_code":"160424.0",
    "gn:asciiname":"Riba de Mouro",
    "gn:country_code":"PT",
    "gn:dem":270,
    "gn:feature_class":"P",
    "gn:feature_code":"PPL",
    "gn:name":"Riba de Mouro",
    "gn:population":0,
    "gn:timezone":"Europe/Lisbon",
    "iso:country":"PT",
    "wof:name":"Riba de Mouro",
    "wof:placetype":"locality"
},
  "geometry": {"coordinates":[-8.33449,42.03596],"type":"Point"}
}