{
  "type": "Feature",
  "properties": {
    "gn:admin1_code":"21.0",
    "gn:admin2_code":"1703",
    "gn:admin3_code":"170323.0",
    "gn:asciiname":"Fernandinho",
    "gn:country_code":"PT",
    "gn:dem":749,
    "gn:feature_class":"P",
    "gn:feature_code":"PPL",
    "gn:name":"Fernandinho",
    "gn:population":0,
    "gn:timezone":"Europe/Lisbon",
    "iso:country":"PT",
    "wof:name":"Fernandinho",
    "wof:placetype":"locality"
},
  "geometry": {"coordinates":[-7.49243,41.61255],"type":"Point"}
}