{
  "type": "Feature",
  "properties": {
    "gn:admin1_code":"21.0",
    "gn:admin2_code":"1703",
    "gn:admin3_code":"170323.0",
    "gn:asciiname":"Fernandinho",
    "gn:country_code":"PT",
    "gn:dem":749,
    "gn:feature_class":"P",
    "gn:feature_code":"PPL",
    "gn:name":"Fernandinho",
    "gn:population":0,
    "gn:timezone":"Europe/Lisbon",
    "iso:country":"PT",
    "name:ces_x_preferred":[
        "Fernandinho"
    ],
    "name:deu_x_preferred":[
        "Fernandinho"
    ],
    "name:fin_x_preferred":[
        "Fernandinho"
    ],
    "name:ita_x_preferred":[
        "Fernandinho"
    ],
    "name:jpn_x_preferred":[
        "\u30d5\u30a7\u30eb\u30ca\u30f3\u30b8\u30fc\u30cb\u30e7"
    ],
    "name:ltz_x_preferred":[
        "Fernandinho"
    ],
    "name:por_x_preferred":[
        "Fernandinho"
    ],
    "name:ron_x_preferred":[
        "Fernandinho"
    ],
    "name:rus_x_preferred":[
        "\u0424\u0435\u0440\u043d\u0430\u043d\u0434\u0438\u043d\u044c\u043e"
    ],
    "wof:name":"Fernandinho",
    "wof:placetype":"locality"
},
  "geometry": {"coordinates":[-7.49243,41.61255],"type":"Point"}
}