{
  "type": "Feature",
  "properties": {
    "gn:admin1_code":"06",
    "gn:admin2_code":"0509",
    "gn:admin3_code":"50901.0",
    "gn:asciiname":"Lameira da Alagoa",
    "gn:country_code":"PT",
    "gn:dem":342,
    "gn:feature_class":"P",
    "gn:feature_code":"PPL",
    "gn:name":"Lameira da Alagoa",
    "gn:population":0,
    "gn:timezone":"Europe/Lisbon",
    "iso:country":"PT",
    "wof:name":"Lameira da Alagoa",
    "wof:placetype":"locality"
},
  "geometry": {"coordinates":[-8.1432,39.8158],"type":"Point"}
}