{
  "type": "Feature",
  "properties": {
    "gn:admin1_code":"7.0",
    "gn:admin2_code":"0614",
    "gn:admin3_code":"61403.0",
    "gn:asciiname":"Alfafar",
    "gn:country_code":"PT",
    "gn:dem":210,
    "gn:feature_class":"P",
    "gn:feature_code":"PPL",
    "gn:name":"Alfafar",
    "gn:population":0,
    "gn:timezone":"Europe/Lisbon",
    "iso:country":"PT",
    "name:arg_x_preferred":[
        "Alfafar"
    ],
    "name:azb_x_preferred":[
        "\u0622\u0644\u0641\u0627\u0641\u0627\u0631"
    ],
    "name:cat_x_preferred":[
        "Alfafar"
    ],
    "name:ceb_x_preferred":[
        "Alfafar"
    ],
    "name:eus_x_preferred":[
        "Alfafar"
    ],
    "name:fas_x_preferred":[
        "\u0622\u0644\u0641\u0627\u0641\u0627\u0631"
    ],
    "name:fra_x_preferred":[
        "Alfafar"
    ],
    "name:glg_x_preferred":[
        "Alfafar"
    ],
    "name:hun_x_preferred":[
        "Alfafar"
    ],
    "name:ita_x_preferred":[
        "Alfafar"
    ],
    "name:msa_x_preferred":[
        "Alfafar"
    ],
    "name:nld_x_preferred":[
        "Alfafar"
    ],
    "name:oci_x_preferred":[
        "Alfafar"
    ],
    "name:pol_x_preferred":[
        "Alfafar"
    ],
    "name:por_x_preferred":[
        "Alfafar"
    ],
    "name:rus_x_preferred":[
        "\u0410\u043b\u044c\u0444\u0430\u0444\u0430\u0440"
    ],
    "name:spa_x_preferred":[
        "Alfafar"
    ],
    "name:sqi_x_preferred":[
        "Alfafar"
    ],
    "name:srp_x_preferred":[
        "\u0410\u043b\u0444\u0430\u0444\u0430\u0440"
    ],
    "name:swe_x_preferred":[
        "Alfafar"
    ],
    "name:ukr_x_preferred":[
        "\u0410\u043b\u0444\u0430\u0444\u0430\u0440"
    ],
    "name:vie_x_preferred":[
        "Alfafar"
    ],
    "name:war_x_preferred":[
        "Alfafar"
    ],
    "name:zho_x_preferred":[
        "\u963f\u5c14\u6cd5\u6cd5\u5c14"
    ],
    "wof:name":"Alfafar",
    "wof:placetype":"locality"
},
  "geometry": {"coordinates":[-8.43239,40.06564],"type":"Point"}
}