{
  "type": "Feature",
  "properties": {
    "gn:admin1_code":"7.0",
    "gn:admin2_code":"0614",
    "gn:admin3_code":"61403.0",
    "gn:asciiname":"Alfafar",
    "gn:country_code":"PT",
    "gn:dem":210,
    "gn:feature_class":"P",
    "gn:feature_code":"PPL",
    "gn:name":"Alfafar",
    "gn:population":0,
    "gn:timezone":"Europe/Lisbon",
    "iso:country":"PT",
    "wof:name":"Alfafar",
    "wof:placetype":"locality"
},
  "geometry": {"coordinates":[-8.43239,40.06564],"type":"Point"}
}