{
  "type": "Feature",
  "properties": {
    "gn:admin1_code":"22.0",
    "gn:admin2_code":"1817",
    "gn:admin3_code":"181704.0",
    "gn:asciiname":"Carvalhal",
    "gn:country_code":"PT",
    "gn:dem":674,
    "gn:feature_class":"P",
    "gn:feature_code":"PPL",
    "gn:name":"Carvalhal",
    "gn:population":0,
    "gn:timezone":"Europe/Lisbon",
    "iso:country":"PT",
    "wof:name":"Carvalhal",
    "wof:placetype":"locality"
},
  "geometry": {"coordinates":[-7.70273,40.81259],"type":"Point"}
}