{
  "type": "Feature",
  "properties": {
    "gn:admin1_code":"06",
    "gn:admin2_code":"0510",
    "gn:admin3_code":"51003.0",
    "gn:asciiname":"Vila de Rei",
    "gn:country_code":"PT",
    "gn:dem":444,
    "gn:feature_class":"P",
    "gn:feature_code":"PPLA2",
    "gn:name":"Vila de Rei",
    "gn:population":3452,
    "gn:timezone":"Europe/Lisbon",
    "iso:country":"PT",
    "name:rus_x_preferred":[
        "\u0412\u0438\u043b\u0430-\u0434\u0438-\u0420\u0435\u0439"
    ],
    "name:ukr_x_preferred":[
        "\u0412\u0456\u043b\u0430-\u0434\u0435-\u0420\u0435\u0439"
    ],
    "name:und_x_variant":[
        "Vila do Rei",
        "Vila de Rei"
    ],
    "wof:name":"Vila de Rei",
    "wof:placetype":"locality",
    "wof:population":3452
},
  "geometry": {"coordinates":[-8.14577,39.67604],"type":"Point"}
}