{
  "type": "Feature",
  "properties": {
    "gn:admin1_code":"18",
    "gn:admin2_code":"1421",
    "gn:admin3_code":"142112.0",
    "gn:asciiname":"Sandoeira",
    "gn:country_code":"PT",
    "gn:dem":109,
    "gn:feature_class":"P",
    "gn:feature_code":"PPL",
    "gn:name":"Sandoeira",
    "gn:population":0,
    "gn:timezone":"Europe/Lisbon",
    "iso:country":"PT",
    "wof:name":"Sandoeira",
    "wof:placetype":"locality"
},
  "geometry": {"coordinates":[-8.47693,39.7214],"type":"Point"}
}