{
  "type": "Feature",
  "properties": {
    "gn:admin1_code":"16",
    "gn:admin2_code":"1207",
    "gn:admin3_code":"120708.0",
    "gn:asciiname":"Chacim",
    "gn:country_code":"PT",
    "gn:dem":250,
    "gn:feature_class":"P",
    "gn:feature_code":"PPL",
    "gn:name":"Chacim",
    "gn:population":0,
    "gn:timezone":"Europe/Lisbon",
    "iso:country":"PT",
    "wof:name":"Chacim",
    "wof:placetype":"locality"
},
  "geometry": {"coordinates":[-7.1596,38.98309],"type":"Point"}
}