{
  "type": "Feature",
  "properties": {
    "gn:admin1_code":"17.0",
    "gn:admin2_code":"1307",
    "gn:admin3_code":"130712.0",
    "gn:asciiname":"Maureles",
    "gn:country_code":"PT",
    "gn:dem":176,
    "gn:feature_class":"P",
    "gn:feature_code":"PPL",
    "gn:name":"Maureles",
    "gn:population":0,
    "gn:timezone":"Europe/Lisbon",
    "iso:country":"PT",
    "wof:name":"Maureles",
    "wof:placetype":"locality"
},
  "geometry": {"coordinates":[-8.19165,41.18117],"type":"Point"}
}