{
  "type": "Feature",
  "properties": {
    "gn:admin1_code":"14",
    "gn:admin2_code":"1111",
    "gn:admin3_code":"111105.0",
    "gn:asciiname":"Pe da Serra",
    "gn:country_code":"PT",
    "gn:dem":223,
    "gn:feature_class":"P",
    "gn:feature_code":"PPL",
    "gn:name":"P\u00e9 da Serra",
    "gn:population":0,
    "gn:timezone":"Europe/Lisbon",
    "iso:country":"PT",
    "wof:name":"Pe da Serra",
    "wof:placetype":"locality"
},
  "geometry": {"coordinates":[-9.46133,38.78911],"type":"Point"}
}