{
  "type": "Feature",
  "properties": {
    "gn:country":"PT",
    "gn:fcode":"ADM3",
    "gn:population":0,
    "iso:country":"PT",
    "name:ara_x_preferred":[
        "\u0623\u0631\u0627\u064a\u0648\u0644\u0648\u0633"
    ],
    "name:cat_x_preferred":[
        "Arraiolos"
    ],
    "name:ceb_x_preferred":[
        "Arraiolos"
    ],
    "name:deu_x_preferred":[
        "Arraiolos"
    ],
    "name:epo_x_preferred":[
        "Arraiolos"
    ],
    "name:eus_x_preferred":[
        "Arraiolos"
    ],
    "name:fra_x_preferred":[
        "Arraiolos"
    ],
    "name:hun_x_preferred":[
        "Arraiolos"
    ],
    "name:ita_x_preferred":[
        "Arraiolos"
    ],
    "name:msa_x_preferred":[
        "Arraiolos"
    ],
    "name:nld_x_preferred":[
        "Arraiolos"
    ],
    "name:pol_x_preferred":[
        "Arraiolos"
    ],
    "name:por_x_preferred":[
        "Arraiolos"
    ],
    "name:rus_x_preferred":[
        "\u0410\u0440\u0440\u0430\u0439\u043e\u043b\u0443\u0448"
    ],
    "name:spa_x_preferred":[
        "Arraiolos"
    ],
    "name:tur_x_preferred":[
        "Arraiolos"
    ],
    "name:ukr_x_preferred":[
        "\u0410\u0440\u0440\u0430\u0439\u043e\u043b\u0443\u0448"
    ],
    "name:vie_x_preferred":[
        "Arraiolos"
    ],
    "name:vol_x_preferred":[
        "Arraiolos"
    ],
    "name:war_x_preferred":[
        "Arraiolos"
    ],
    "name:zho_x_preferred":[
        "\u963f\u62c9\u7d04\u6d1b\u65af"
    ],
    "qs_pg:aaroncc":"PT",
    "qs_pg:gn_country":"PT",
    "qs_pg:gn_fcode":"ADM3",
    "qs_pg:gn_pop":0,
    "qs_pg:name":"Arraiolos",
    "qs_pg:photos_9r":0,
    "qs_pg:photos_sr":0,
    "qs_pg:pop_sr":0,
    "qs_pg:qs_pg_placetype":"localadmin",
    "wof:name":"Arraiolos",
    "wof:placetype":"localadmin"
},
  "geometry": {"coordinates":[-8.02166,38.76084],"type":"Point"}
}