{
  "type": "Feature",
  "properties": {
    "gn:admin1_code":"22.0",
    "gn:admin2_code":"1808",
    "gn:admin3_code":"180804.0",
    "gn:asciiname":"Pomares",
    "gn:country_code":"PT",
    "gn:dem":250,
    "gn:feature_class":"P",
    "gn:feature_code":"PPL",
    "gn:name":"Pomares",
    "gn:population":0,
    "gn:timezone":"Europe/Lisbon",
    "iso:country":"PT",
    "wof:name":"Pomares",
    "wof:placetype":"locality"
},
  "geometry": {"coordinates":[-8.29137,40.40036],"type":"Point"}
}