{
  "type": "Feature",
  "properties": {
    "gn:admin1_code":"04",
    "gn:admin2_code":"0303",
    "gn:admin3_code":"30301.0",
    "gn:asciiname":"Ribeira",
    "gn:country_code":"PT",
    "gn:dem":69,
    "gn:feature_class":"P",
    "gn:feature_code":"PPL",
    "gn:name":"Ribeira",
    "gn:population":0,
    "gn:timezone":"Europe/Lisbon",
    "iso:country":"PT",
    "wof:name":"Ribeira",
    "wof:placetype":"locality"
},
  "geometry": {"coordinates":[-8.40221,41.60155],"type":"Point"}
}