{
  "type": "Feature",
  "properties": {
    "gn:admin1_code":"18",
    "gn:admin2_code":"1402",
    "gn:admin3_code":"140209.0",
    "gn:asciiname":"Carvalheiras",
    "gn:country_code":"PT",
    "gn:dem":425,
    "gn:feature_class":"P",
    "gn:feature_code":"PPL",
    "gn:name":"Carvalheiras",
    "gn:population":0,
    "gn:timezone":"Europe/Lisbon",
    "iso:country":"PT",
    "wof:name":"Carvalheiras",
    "wof:placetype":"locality"
},
  "geometry": {"coordinates":[-8.73102,39.52167],"type":"Point"}
}