{
  "type": "Feature",
  "properties": {
    "iso:country":"PT",
    "qs_pg:aaroncc":"PT",
    "qs_pg:name":"Passil",
    "qs_pg:name_adm0":"Portugal",
    "qs_pg:name_adm1":"Set\u00fabal",
    "qs_pg:photos":14,
    "qs_pg:photos_1k":3,
    "qs_pg:photos_9k":1,
    "qs_pg:photos_9r":1,
    "qs_pg:photos_all":14,
    "qs_pg:photos_sr":1,
    "qs_pg:pop_sr":0,
    "qs_pg:qs_pg_placetype":"locality",
    "qs_pg:qs_pg_placetype_gp":"Town",
    "qs_pg:woe_adm0":23424925,
    "woe:adm0_id":23424925,
    "woe:name_adm0":"Portugal",
    "woe:name_adm1":"Set\u00fabal",
    "woe:placetype":"Town",
    "wof:name":"Passil",
    "wof:placetype":"locality"
},
  "geometry": {"coordinates":[-8.895975,38.709692],"type":"Point"}
}