{
  "type": "Feature",
  "properties": {
    "gn:admin1_code":"4.0",
    "gn:admin2_code":"0305",
    "gn:admin3_code":"30520.0",
    "gn:asciiname":"Basto",
    "gn:country_code":"PT",
    "gn:dem":553,
    "gn:feature_class":"P",
    "gn:feature_code":"PPL",
    "gn:name":"Basto",
    "gn:population":0,
    "gn:timezone":"Europe/Lisbon",
    "iso:country":"PT",
    "name:ara_x_preferred":[
        "\u0628\u0627\u0633\u062a\u0648"
    ],
    "name:deu_x_preferred":[
        "Basto"
    ],
    "name:ell_x_preferred":[
        "Basto"
    ],
    "name:fin_x_preferred":[
        "Basto"
    ],
    "name:fra_x_preferred":[
        "Basto"
    ],
    "name:ita_x_preferred":[
        "Basto"
    ],
    "name:nld_x_preferred":[
        "Basto"
    ],
    "name:pol_x_preferred":[
        "Basto"
    ],
    "name:ron_x_preferred":[
        "Basto"
    ],
    "name:spa_x_preferred":[
        "Basto"
    ],
    "name:und_x_variant":[
        "S\u00e3o Clemente"
    ],
    "wof:name":"Basto",
    "wof:placetype":"locality"
},
  "geometry": {"coordinates":[-8.04571,41.47171],"type":"Point"}
}