{
  "type": "Feature",
  "properties": {
    "gn:admin1_code":"4.0",
    "gn:admin2_code":"0305",
    "gn:admin3_code":"30520.0",
    "gn:asciiname":"Basto",
    "gn:country_code":"PT",
    "gn:dem":553,
    "gn:feature_class":"P",
    "gn:feature_code":"PPL",
    "gn:name":"Basto",
    "gn:population":0,
    "gn:timezone":"Europe/Lisbon",
    "iso:country":"PT",
    "name:und_x_variant":[
        "S\u00e3o Clemente",
        "Basto"
    ],
    "wof:name":"Basto",
    "wof:placetype":"locality"
},
  "geometry": {"coordinates":[-8.04571,41.47171],"type":"Point"}
}