{
  "type": "Feature",
  "properties": {
    "gn:gn_country":"PT",
    "gn:gn_fcode":"PPL",
    "gn:gn_pop":0,
    "iso:country":"PT",
    "name:unk_x_variant":[
        "Mina de S\u00e3o Domingos"
    ],
    "qs_pg:aaroncc":"PT",
    "qs_pg:gn_country":"PT",
    "qs_pg:gn_fcode":"PPL",
    "qs_pg:gn_pop":0,
    "qs_pg:name":"Minas de S\u00e3o Domingos",
    "qs_pg:name_adm0":"Portugal",
    "qs_pg:name_adm1":"Beja",
    "qs_pg:photos":356,
    "qs_pg:photos_1k":72,
    "qs_pg:photos_9k":2,
    "qs_pg:photos_9r":5,
    "qs_pg:photos_all":356,
    "qs_pg:photos_sr":6,
    "qs_pg:pop_sr":3,
    "qs_pg:qs_pg_placetype":"locality",
    "qs_pg:qs_pg_placetype_gp":"Town",
    "qs_pg:woe_adm0":23424925,
    "woe:adm0_id":23424925,
    "woe:name_adm0":"Portugal",
    "woe:name_adm1":"Beja",
    "woe:placetype":"Town",
    "wof:name":"Minas de S\u00e3o Domingos",
    "wof:placetype":"locality"
},
  "geometry": {"coordinates":[-7.49034,37.67434],"type":"Point"}
}