{
  "type": "Feature",
  "properties": {
    "gn:admin1_code":"21",
    "gn:admin2_code":"1712",
    "gn:admin3_code":"171212.0",
    "gn:asciiname":"Vilaranda Boa",
    "gn:country_code":"PT",
    "gn:dem":778,
    "gn:feature_class":"P",
    "gn:feature_code":"PPL",
    "gn:name":"Vilaranda Boa",
    "gn:population":0,
    "gn:timezone":"Europe/Lisbon",
    "iso:country":"PT",
    "wof:name":"Vilaranda Boa",
    "wof:placetype":"locality"
},
  "geometry": {"coordinates":[-7.41703,41.65351],"type":"Point"}
}