{
  "type": "Feature",
  "properties": {
    "gn:admin1_code":"18",
    "gn:admin2_code":"1414",
    "gn:admin3_code":"141401.0",
    "gn:asciiname":"Alqueidao",
    "gn:country_code":"PT",
    "gn:dem":128,
    "gn:feature_class":"P",
    "gn:feature_code":"PPL",
    "gn:name":"Alqueid\u00e3o",
    "gn:population":0,
    "gn:timezone":"Europe/Lisbon",
    "iso:country":"PT",
    "wof:name":"Alqueidao",
    "wof:placetype":"locality"
},
  "geometry": {"coordinates":[-8.89935,39.41979],"type":"Point"}
}