{
  "type": "Feature",
  "properties": {
    "gn:admin1_code":"7.0",
    "gn:admin2_code":"0617",
    "gn:admin3_code":"61702.0",
    "gn:asciiname":"Moura Morta",
    "gn:country_code":"PT",
    "gn:dem":114,
    "gn:feature_class":"P",
    "gn:feature_code":"PPL",
    "gn:name":"Moura Morta",
    "gn:population":0,
    "gn:timezone":"Europe/Lisbon",
    "iso:country":"PT",
    "wof:name":"Moura Morta",
    "wof:placetype":"locality"
},
  "geometry": {"coordinates":[-8.18924,40.24453],"type":"Point"}
}