{
  "type": "Feature",
  "properties": {
    "gn:admin1_code":"22",
    "gn:admin2_code":"1824",
    "gn:admin3_code":"182402.0",
    "gn:asciiname":"Santa Comba",
    "gn:country_code":"PT",
    "gn:dem":612,
    "gn:feature_class":"P",
    "gn:feature_code":"PPL",
    "gn:name":"Santa Comba",
    "gn:population":0,
    "gn:timezone":"Europe/Lisbon",
    "iso:country":"PT",
    "name:ceb_x_preferred":[
        "Santa Comba"
    ],
    "name:deu_x_preferred":[
        "Santa Comba"
    ],
    "name:fra_x_preferred":[
        "Santa Comba"
    ],
    "name:glg_x_preferred":[
        "Santa Comba"
    ],
    "name:lmo_x_preferred":[
        "Santa Comba"
    ],
    "name:nld_x_preferred":[
        "Santa Comba"
    ],
    "name:por_x_preferred":[
        "Santa Comba"
    ],
    "name:rus_x_preferred":[
        "\u0421\u0430\u043d\u0442\u0430-\u041a\u043e\u043c\u0431\u0430"
    ],
    "name:swe_x_preferred":[
        "Santa Comba"
    ],
    "name:ukr_x_preferred":[
        "\u0421\u0430\u043d\u0442\u0430-\u041a\u043e\u043c\u0431\u0430"
    ],
    "wof:name":"Santa Comba",
    "wof:placetype":"locality"
},
  "geometry": {"coordinates":[-8.15484,40.67241],"type":"Point"}
}