{
  "type": "Feature",
  "properties": {
    "gn:admin1_code":"22",
    "gn:admin2_code":"1816",
    "gn:admin3_code":"181618.0",
    "gn:asciiname":"Varzea",
    "gn:country_code":"PT",
    "gn:dem":154,
    "gn:feature_class":"P",
    "gn:feature_code":"PPL",
    "gn:name":"V\u00e1rzea",
    "gn:population":0,
    "gn:timezone":"Europe/Lisbon",
    "iso:country":"PT",
    "wof:name":"Varzea",
    "wof:placetype":"locality"
},
  "geometry": {"coordinates":[-8.09169,40.74088],"type":"Point"}
}