{
  "type": "Feature",
  "properties": {
    "gn:admin1_code":"14",
    "gn:admin2_code":"1111",
    "gn:admin3_code":"111108.0",
    "gn:asciiname":"Serradas",
    "gn:country_code":"PT",
    "gn:dem":147,
    "gn:feature_class":"P",
    "gn:feature_code":"PPL",
    "gn:name":"Serradas",
    "gn:population":0,
    "gn:timezone":"Europe/Lisbon",
    "iso:country":"PT",
    "wof:name":"Serradas",
    "wof:placetype":"locality"
},
  "geometry": {"coordinates":[-9.33633,38.76936],"type":"Point"}
}