{
  "type": "Feature",
  "properties": {
    "gn:admin1_code":"21.0",
    "gn:admin2_code":"1706",
    "gn:admin3_code":"170622.0",
    "gn:asciiname":"Ponteira",
    "gn:country_code":"PT",
    "gn:dem":909,
    "gn:feature_class":"P",
    "gn:feature_code":"PPL",
    "gn:name":"Ponteira",
    "gn:population":0,
    "gn:timezone":"Europe/Lisbon",
    "iso:country":"PT",
    "wof:name":"Ponteira",
    "wof:placetype":"locality"
},
  "geometry": {"coordinates":[-7.96378,41.74298],"type":"Point"}
}