{
  "type": "Feature",
  "properties": {
    "gn:admin1_code":"2.0",
    "gn:asciiname":"Balazeima",
    "gn:country_code":"PT",
    "gn:dem":478,
    "gn:feature_class":"P",
    "gn:feature_code":"PPL",
    "gn:name":"Balazeima",
    "gn:population":0,
    "gn:timezone":"Europe/Lisbon",
    "iso:country":"PT",
    "wof:name":"Balazeima",
    "wof:placetype":"locality"
},
  "geometry": {"coordinates":[-8.25866,40.60033],"type":"Point"}
}