{
  "type": "Feature",
  "properties": {
    "gn:admin1_code":"08",
    "gn:admin2_code":"0704",
    "gn:admin3_code":"70401.0",
    "gn:asciiname":"Marta Ruiva",
    "gn:country_code":"PT",
    "gn:dem":435,
    "gn:feature_class":"P",
    "gn:feature_code":"PPL",
    "gn:name":"Marta Ruiva",
    "gn:population":0,
    "gn:timezone":"Europe/Lisbon",
    "iso:country":"PT",
    "wof:name":"Marta Ruiva",
    "wof:placetype":"locality"
},
  "geometry": {"coordinates":[-7.48834,38.82018],"type":"Point"}
}