{
  "type": "Feature",
  "properties": {
    "gn:admin1_code":"20.0",
    "gn:admin2_code":"1601",
    "gn:admin3_code":"160119.0",
    "gn:asciiname":"Jolda",
    "gn:country_code":"PT",
    "gn:dem":127,
    "gn:feature_class":"P",
    "gn:feature_code":"PPL",
    "gn:name":"Jolda",
    "gn:population":0,
    "gn:timezone":"Europe/Lisbon",
    "iso:country":"PT",
    "name:und_x_variant":[
        "Santa Maria Madalena",
        "Madalena",
        "Jolda"
    ],
    "wof:name":"Jolda",
    "wof:placetype":"locality"
},
  "geometry": {"coordinates":[-8.50254,41.80302],"type":"Point"}
}