{
  "type": "Feature",
  "properties": {
    "gn:country":"PT",
    "gn:fcode":"STNB",
    "gn:population":200,
    "iso:country":"PT",
    "name:por_x_preferred":[
        "INL"
    ],
    "name:por_x_variant":[
        "Laborat\u00f3rio Ib\u00e9rico Internacional de Nanotecnologia"
    ],
    "name:spa_x_preferred":[
        "Laboratorio Ib\u00e9rico Internacional de Nanotecnolog\u00eda"
    ],
    "qs_pg:aaroncc":"PT",
    "qs_pg:gn_country":"PT",
    "qs_pg:gn_fcode":"STNB",
    "qs_pg:gn_pop":200,
    "qs_pg:name":"International Iberian Nanotechnology Laboratory",
    "qs_pg:photos_9r":0,
    "qs_pg:photos_sr":0,
    "qs_pg:pop_sr":1,
    "qs_pg:qs_pg_placetype":"locality",
    "wof:name":"International Iberian Nanotechnology Laboratory",
    "wof:placetype":"locality",
    "wof:population":200
},
  "geometry": {"coordinates":[-8.39848,41.55526],"type":"Point"}
}