{
  "type": "Feature",
  "properties": {
    "gn:admin1_code":"21.0",
    "gn:admin2_code":"1714",
    "gn:admin3_code":"171427.0",
    "gn:asciiname":"Carvas",
    "gn:country_code":"PT",
    "gn:dem":715,
    "gn:feature_class":"P",
    "gn:feature_code":"PPL",
    "gn:name":"Carvas",
    "gn:population":0,
    "gn:timezone":"Europe/Lisbon",
    "iso:country":"PT",
    "wof:name":"Carvas",
    "wof:placetype":"locality"
},
  "geometry": {"coordinates":[-7.66819,41.3053],"type":"Point"}
}