{
  "type": "Feature",
  "properties": {
    "gn:admin1_code":"07",
    "gn:admin2_code":"0606",
    "gn:admin3_code":"60602.0",
    "gn:asciiname":"Sandinha",
    "gn:country_code":"PT",
    "gn:dem":360,
    "gn:feature_class":"P",
    "gn:feature_code":"PPL",
    "gn:name":"Sandinha",
    "gn:population":0,
    "gn:timezone":"Europe/Lisbon",
    "iso:country":"PT",
    "wof:name":"Sandinha",
    "wof:placetype":"locality"
},
  "geometry": {"coordinates":[-8.05163,40.14491],"type":"Point"}
}