{
  "type": "Feature",
  "properties": {
    "gn:admin1_code":"21.0",
    "gn:admin2_code":"1706",
    "gn:admin3_code":"170626.0",
    "gn:asciiname":"Carvalho",
    "gn:country_code":"PT",
    "gn:dem":970,
    "gn:feature_class":"P",
    "gn:feature_code":"PPL",
    "gn:name":"Carvalho",
    "gn:population":0,
    "gn:timezone":"Europe/Lisbon",
    "iso:country":"PT",
    "name:deu_x_preferred":[
        "Carvalho"
    ],
    "name:por_x_preferred":[
        "Carvalho"
    ],
    "wof:name":"Carvalho",
    "wof:placetype":"locality"
},
  "geometry": {"coordinates":[-7.92256,41.61165],"type":"Point"}
}