{
  "type": "Feature",
  "properties": {
    "gn:admin1_code":"14",
    "gn:admin2_code":"1112",
    "gn:admin3_code":"111202.0",
    "gn:asciiname":"Serreira",
    "gn:country_code":"PT",
    "gn:dem":187,
    "gn:feature_class":"P",
    "gn:feature_code":"PPL",
    "gn:name":"Serreira",
    "gn:population":0,
    "gn:timezone":"Europe/Lisbon",
    "iso:country":"PT",
    "wof:name":"Serreira",
    "wof:placetype":"locality"
},
  "geometry": {"coordinates":[-9.22049,38.96285],"type":"Point"}
}