{
  "type": "Feature",
  "properties": {
    "gn:admin1_code":"21.0",
    "gn:admin2_code":"1714",
    "gn:admin3_code":"171416.0",
    "gn:asciiname":"Mondroes",
    "gn:country_code":"PT",
    "gn:dem":498,
    "gn:feature_class":"P",
    "gn:feature_code":"PPL",
    "gn:name":"Mondr\u00f5es",
    "gn:population":0,
    "gn:timezone":"Europe/Lisbon",
    "iso:country":"PT",
    "wof:name":"Mondroes",
    "wof:placetype":"locality"
},
  "geometry": {"coordinates":[-7.78944,41.29243],"type":"Point"}
}