{
  "type": "Feature",
  "properties": {
    "gn:admin1_code":"18",
    "gn:admin2_code":"1421",
    "gn:admin3_code":"142104.0",
    "gn:asciiname":"Carvoeira",
    "gn:country_code":"PT",
    "gn:dem":146,
    "gn:feature_class":"P",
    "gn:feature_code":"PPL",
    "gn:name":"Carvoeira",
    "gn:population":0,
    "gn:timezone":"Europe/Lisbon",
    "iso:country":"PT",
    "wof:name":"Carvoeira",
    "wof:placetype":"locality"
},
  "geometry": {"coordinates":[-8.54475,39.71561],"type":"Point"}
}