{
  "type": "Feature",
  "properties": {
    "gn:admin1_code":"06",
    "gn:admin2_code":"0502",
    "gn:admin3_code":"50216.0",
    "gn:asciiname":"Caldeirinhas",
    "gn:country_code":"PT",
    "gn:dem":203,
    "gn:feature_class":"P",
    "gn:feature_code":"PPL",
    "gn:name":"Caldeirinhas",
    "gn:population":0,
    "gn:timezone":"Europe/Lisbon",
    "iso:country":"PT",
    "wof:name":"Caldeirinhas",
    "wof:placetype":"locality"
},
  "geometry": {"coordinates":[-7.22112,39.78106],"type":"Point"}
}