{
  "type": "Feature",
  "properties": {
    "gn:admin1_code":"4.0",
    "gn:admin2_code":"0302",
    "gn:admin3_code":"30234.0",
    "gn:asciiname":"Gilmonde",
    "gn:country_code":"PT",
    "gn:dem":53,
    "gn:feature_class":"P",
    "gn:feature_code":"PPL",
    "gn:name":"Gilmonde",
    "gn:population":0,
    "gn:timezone":"Europe/Lisbon",
    "iso:country":"PT",
    "wof:name":"Gilmonde",
    "wof:placetype":"locality"
},
  "geometry": {"coordinates":[-8.67455,41.51227],"type":"Point"}
}