{
  "type": "Feature",
  "properties": {
    "gn:admin1_code":"4.0",
    "gn:admin2_code":"0302",
    "gn:admin3_code":"30234.0",
    "gn:asciiname":"Gilmonde",
    "gn:country_code":"PT",
    "gn:dem":53,
    "gn:feature_class":"P",
    "gn:feature_code":"PPL",
    "gn:name":"Gilmonde",
    "gn:population":0,
    "gn:timezone":"Europe/Lisbon",
    "iso:country":"PT",
    "name:ceb_x_preferred":[
        "Gilmonde"
    ],
    "name:deu_x_preferred":[
        "Gilmonde"
    ],
    "name:kaz_x_preferred":[
        "\u0416\u0438\u043b\u043c\u043e\u043d\u0434\u0438"
    ],
    "name:nld_x_preferred":[
        "Gilmonde"
    ],
    "name:por_x_preferred":[
        "Gilmonde"
    ],
    "name:rus_x_preferred":[
        "\u0416\u0438\u043b\u043c\u043e\u043d\u0434\u0438"
    ],
    "name:spa_x_preferred":[
        "Gilmonde"
    ],
    "name:ukr_x_preferred":[
        "\u0416\u0456\u043b\u043c\u043e\u043d\u0434\u0435"
    ],
    "wof:name":"Gilmonde",
    "wof:placetype":"locality"
},
  "geometry": {"coordinates":[-8.67455,41.51227],"type":"Point"}
}