{
  "type": "Feature",
  "properties": {
    "gn:admin1_code":"4.0",
    "gn:admin2_code":"0313",
    "gn:admin3_code":"31312.0",
    "gn:asciiname":"Covas",
    "gn:country_code":"PT",
    "gn:dem":253,
    "gn:feature_class":"P",
    "gn:feature_code":"PPL",
    "gn:name":"Covas",
    "gn:population":0,
    "gn:timezone":"Europe/Lisbon",
    "iso:country":"PT",
    "wof:name":"Covas",
    "wof:placetype":"locality"
},
  "geometry": {"coordinates":[-8.41657,41.74162000000001],"type":"Point"}
}