{
  "type": "Feature",
  "properties": {
    "gn:admin1_code":"14",
    "gn:admin2_code":"1113",
    "gn:admin3_code":"111316.0",
    "gn:asciiname":"Areias",
    "gn:country_code":"PT",
    "gn:dem":36,
    "gn:feature_class":"P",
    "gn:feature_code":"PPL",
    "gn:name":"Areias",
    "gn:population":0,
    "gn:timezone":"Europe/Lisbon",
    "iso:country":"PT",
    "name:und_x_variant":[
        "Quinta da Areia",
        "Areias"
    ],
    "wof:name":"Areias",
    "wof:placetype":"locality"
},
  "geometry": {"coordinates":[-9.38505,39.11075],"type":"Point"}
}