{
  "type": "Feature",
  "properties": {
    "gn:admin1_code":"14",
    "gn:admin2_code":"1113",
    "gn:admin3_code":"111316.0",
    "gn:asciiname":"Areias",
    "gn:country_code":"PT",
    "gn:dem":36,
    "gn:feature_class":"P",
    "gn:feature_code":"PPL",
    "gn:name":"Areias",
    "gn:population":0,
    "gn:timezone":"Europe/Lisbon",
    "iso:country":"PT",
    "name:bpy_x_preferred":[
        "\u0986\u09b0\u09c7\u0987\u09af\u09bc\u09be\u09b8"
    ],
    "name:ceb_x_preferred":[
        "Areias"
    ],
    "name:deu_x_preferred":[
        "Areias"
    ],
    "name:fra_x_preferred":[
        "Areias"
    ],
    "name:kaz_x_preferred":[
        "\u0410\u0440\u0435\u044f\u0448"
    ],
    "name:nld_x_preferred":[
        "Areias"
    ],
    "name:pol_x_preferred":[
        "Areias"
    ],
    "name:por_x_preferred":[
        "Areias"
    ],
    "name:rus_x_preferred":[
        "\u0410\u0440\u0435\u044f\u0448"
    ],
    "name:spa_x_preferred":[
        "Areias"
    ],
    "name:swe_x_preferred":[
        "Areias"
    ],
    "name:ukr_x_preferred":[
        "\u0410\u0440\u0435\u0439\u044f\u0448"
    ],
    "name:und_x_variant":[
        "Quinta da Areia"
    ],
    "name:vie_x_preferred":[
        "Areias"
    ],
    "wof:name":"Areias",
    "wof:placetype":"locality"
},
  "geometry": {"coordinates":[-9.38505,39.11075],"type":"Point"}
}