{
  "type": "Feature",
  "properties": {
    "gn:admin1_code":"13",
    "gn:admin2_code":"1007",
    "gn:admin3_code":"100701.0",
    "gn:asciiname":"Sarzedas do Vasco",
    "gn:country_code":"PT",
    "gn:dem":411,
    "gn:feature_class":"P",
    "gn:feature_code":"PPL",
    "gn:name":"Sarzedas do Vasco",
    "gn:population":0,
    "gn:timezone":"Europe/Lisbon",
    "iso:country":"PT",
    "wof:name":"Sarzedas do Vasco",
    "wof:placetype":"locality"
},
  "geometry": {"coordinates":[-8.21663,39.95273],"type":"Point"}
}