{
  "type": "Feature",
  "properties": {
    "gn:admin1_code":"2.0",
    "gn:admin2_code":"0112",
    "gn:admin3_code":"11201.0",
    "gn:asciiname":"Bunheiro",
    "gn:country_code":"PT",
    "gn:dem":8,
    "gn:feature_class":"P",
    "gn:feature_code":"PPL",
    "gn:name":"Bunheiro",
    "gn:population":0,
    "gn:timezone":"Europe/Lisbon",
    "iso:country":"PT",
    "wof:name":"Bunheiro",
    "wof:placetype":"locality"
},
  "geometry": {"coordinates":[-8.64172,40.77837],"type":"Point"}
}