{
  "type": "Feature",
  "properties": {
    "gn:admin1_code":"13.0",
    "gn:admin2_code":"1015",
    "gn:admin3_code":"101510.0",
    "gn:asciiname":"Carramanha",
    "gn:country_code":"PT",
    "gn:dem":33,
    "gn:feature_class":"P",
    "gn:feature_code":"PPL",
    "gn:name":"Carramanha",
    "gn:population":0,
    "gn:timezone":"Europe/Lisbon",
    "iso:country":"PT",
    "wof:name":"Carramanha",
    "wof:placetype":"locality"
},
  "geometry": {"coordinates":[-8.59108,40.01795],"type":"Point"}
}