{
  "type": "Feature",
  "properties": {
    "gn:admin1_code":"09",
    "gn:admin2_code":"0808",
    "gn:admin3_code":"80805.0",
    "gn:asciiname":"Barros da Fonte Santa",
    "gn:country_code":"PT",
    "gn:dem":37,
    "gn:feature_class":"P",
    "gn:feature_code":"PPL",
    "gn:name":"Barros da Fonte Santa",
    "gn:population":0,
    "gn:timezone":"Europe/Lisbon",
    "iso:country":"PT",
    "wof:name":"Barros da Fonte Santa",
    "wof:placetype":"locality"
},
  "geometry": {"coordinates":[-8.07205,37.08478],"type":"Point"}
}