{
  "type": "Feature",
  "properties": {
    "gn:admin1_code":"2.0",
    "gn:admin2_code":"0118",
    "gn:admin3_code":"11801.0",
    "gn:asciiname":"Choca do Mar",
    "gn:country_code":"PT",
    "gn:dem":33,
    "gn:feature_class":"P",
    "gn:feature_code":"PPL",
    "gn:name":"Choca do Mar",
    "gn:population":0,
    "gn:timezone":"Europe/Lisbon",
    "iso:country":"PT",
    "wof:name":"Choca do Mar",
    "wof:placetype":"locality"
},
  "geometry": {"coordinates":[-8.69743,40.48844],"type":"Point"}
}