{
  "type": "Feature",
  "properties": {
    "gn:admin1_code":"04",
    "gn:admin2_code":"0309",
    "gn:admin3_code":"30926.0",
    "gn:asciiname":"Quintela",
    "gn:country_code":"PT",
    "gn:dem":156,
    "gn:feature_class":"P",
    "gn:feature_code":"PPL",
    "gn:name":"Quintela",
    "gn:population":0,
    "gn:timezone":"Europe/Lisbon",
    "iso:country":"PT",
    "name:ceb_x_preferred":[
        "Quintela"
    ],
    "name:deu_x_preferred":[
        "Quintela"
    ],
    "name:glg_x_preferred":[
        "Quintela"
    ],
    "name:kaz_x_preferred":[
        "\u041a\u0438\u043d\u0442\u0435\u043b\u0430"
    ],
    "name:nld_x_preferred":[
        "Quintela"
    ],
    "name:por_x_preferred":[
        "Quintela"
    ],
    "name:rus_x_preferred":[
        "\u041a\u0438\u043d\u0442\u0435\u043b\u0430"
    ],
    "name:spa_x_preferred":[
        "Quintela"
    ],
    "name:tur_x_preferred":[
        "Quintela"
    ],
    "wof:name":"Quintela",
    "wof:placetype":"locality"
},
  "geometry": {"coordinates":[-8.24803,41.5478],"type":"Point"}
}