{
  "type": "Feature",
  "properties": {
    "gn:admin1_code":"04",
    "gn:admin2_code":"0309",
    "gn:admin3_code":"30926.0",
    "gn:asciiname":"Quintela",
    "gn:country_code":"PT",
    "gn:dem":156,
    "gn:feature_class":"P",
    "gn:feature_code":"PPL",
    "gn:name":"Quintela",
    "gn:population":0,
    "gn:timezone":"Europe/Lisbon",
    "iso:country":"PT",
    "wof:name":"Quintela",
    "wof:placetype":"locality"
},
  "geometry": {"coordinates":[-8.24803,41.5478],"type":"Point"}
}