{
  "type": "Feature",
  "properties": {
    "gn:admin1_code":"08",
    "gn:admin2_code":"0701",
    "gn:admin3_code":"70106.0",
    "gn:asciiname":"Monte Alegre",
    "gn:country_code":"PT",
    "gn:dem":235,
    "gn:feature_class":"P",
    "gn:feature_code":"PPL",
    "gn:name":"Monte Alegre",
    "gn:population":0,
    "gn:timezone":"Europe/Lisbon",
    "iso:country":"PT",
    "name:bpy_x_preferred":[
        "\u09ae\u09cb\u09a8\u09cd\u099f\u09c7 \u0986\u09b2\u09c7\u0997\u09cd\u09b0\u09c7"
    ],
    "name:ceb_x_preferred":[
        "Monte Alegre"
    ],
    "name:deu_x_preferred":[
        "Monte Alegre"
    ],
    "name:fra_x_preferred":[
        "Monte Alegre"
    ],
    "name:ita_x_preferred":[
        "Monte Alegre"
    ],
    "name:nld_x_preferred":[
        "Monte Alegre"
    ],
    "name:nor_x_preferred":[
        "Monte Alegre"
    ],
    "name:por_x_preferred":[
        "Monte Alegre"
    ],
    "name:srp_x_preferred":[
        "\u041c\u043e\u043d\u0442\u0435 \u0410\u043b\u0435\u0433\u0440\u0435"
    ],
    "name:swe_x_preferred":[
        "Monte Alegre"
    ],
    "name:vie_x_preferred":[
        "Monte Alegre"
    ],
    "name:vol_x_preferred":[
        "Monte Alegre"
    ],
    "wof:name":"Monte Alegre",
    "wof:placetype":"locality"
},
  "geometry": {"coordinates":[-7.31667,38.68333],"type":"Point"}
}