{
  "type": "Feature",
  "properties": {
    "gn:admin1_code":"20",
    "gn:admin2_code":"1604",
    "gn:admin3_code":"160431.0",
    "gn:asciiname":"Trute",
    "gn:country_code":"PT",
    "gn:dem":240,
    "gn:feature_class":"P",
    "gn:feature_code":"PPL",
    "gn:name":"Trute",
    "gn:population":0,
    "gn:timezone":"Europe/Lisbon",
    "iso:country":"PT",
    "name:pol_x_preferred":[
        "Trute"
    ],
    "name:urd_x_preferred":[
        "\u062a\u0631\u0648\u062a\u06d2"
    ],
    "wof:name":"Trute",
    "wof:placetype":"locality"
},
  "geometry": {"coordinates":[-8.46974,42.01297],"type":"Point"}
}