{
  "type": "Feature",
  "properties": {
    "gn:admin1_code":"18",
    "gn:admin2_code":"1417",
    "gn:admin3_code":"141702.0",
    "gn:asciiname":"Lameiras",
    "gn:country_code":"PT",
    "gn:dem":252,
    "gn:feature_class":"P",
    "gn:feature_code":"PPL",
    "gn:name":"Lameiras",
    "gn:population":0,
    "gn:timezone":"Europe/Lisbon",
    "iso:country":"PT",
    "wof:name":"Lameiras",
    "wof:placetype":"locality"
},
  "geometry": {"coordinates":[-8.16451,39.58753],"type":"Point"}
}