{
  "type": "Feature",
  "properties": {
    "gn:admin1_code":"22",
    "gn:admin2_code":"1823",
    "gn:admin3_code":"182311.0",
    "gn:asciiname":"Salgueiral",
    "gn:country_code":"PT",
    "gn:dem":529,
    "gn:feature_class":"P",
    "gn:feature_code":"PPL",
    "gn:name":"Salgueiral",
    "gn:population":0,
    "gn:timezone":"Europe/Lisbon",
    "iso:country":"PT",
    "wof:name":"Salgueiral",
    "wof:placetype":"locality"
},
  "geometry": {"coordinates":[-8.04124,40.66603],"type":"Point"}
}