{
  "type": "Feature",
  "properties": {
    "gn:admin1_code":"17",
    "gn:admin2_code":"1304",
    "gn:admin3_code":"130407.0",
    "gn:asciiname":"Sobrido",
    "gn:country_code":"PT",
    "gn:dem":113,
    "gn:feature_class":"P",
    "gn:feature_code":"PPL",
    "gn:name":"Sobrido",
    "gn:population":0,
    "gn:timezone":"Europe/Lisbon",
    "iso:country":"PT",
    "wof:name":"Sobrido",
    "wof:placetype":"locality"
},
  "geometry": {"coordinates":[-8.42207,41.0747],"type":"Point"}
}