{
  "type": "Feature",
  "properties": {
    "gn:admin1_code":"17",
    "gn:admin2_code":"1307",
    "gn:admin3_code":"130718.0",
    "gn:asciiname":"Sardoeira",
    "gn:country_code":"PT",
    "gn:dem":209,
    "gn:feature_class":"P",
    "gn:feature_code":"PPL",
    "gn:name":"Sardoeira",
    "gn:population":0,
    "gn:timezone":"Europe/Lisbon",
    "iso:country":"PT",
    "wof:name":"Sardoeira",
    "wof:placetype":"locality"
},
  "geometry": {"coordinates":[-8.17209,41.09666],"type":"Point"}
}