{
  "type": "Feature",
  "properties": {
    "gn:admin1_code":"21.0",
    "gn:admin2_code":"1708",
    "gn:admin3_code":"170810.0",
    "gn:asciiname":"Alvacoes do Tanha",
    "gn:country_code":"PT",
    "gn:dem":204,
    "gn:feature_class":"P",
    "gn:feature_code":"PPL",
    "gn:name":"Alva\u00e7\u00f5es do Tanha",
    "gn:population":0,
    "gn:timezone":"Europe/Lisbon",
    "iso:country":"PT",
    "wof:name":"Alvacoes do Tanha",
    "wof:placetype":"locality"
},
  "geometry": {"coordinates":[-7.74355,41.19162],"type":"Point"}
}