{
  "type": "Feature",
  "properties": {
    "gn:admin1_code":"20.0",
    "gn:admin2_code":"1601",
    "gn:admin3_code":"160149.0",
    "gn:asciiname":"Paredes do Vale",
    "gn:country_code":"PT",
    "gn:dem":408,
    "gn:feature_class":"P",
    "gn:feature_code":"PPL",
    "gn:name":"Paredes do Vale",
    "gn:population":0,
    "gn:timezone":"Europe/Lisbon",
    "iso:country":"PT",
    "wof:name":"Paredes do Vale",
    "wof:placetype":"locality"
},
  "geometry": {"coordinates":[-8.35,41.85],"type":"Point"}
}