{
  "type": "Feature",
  "properties": {
    "gn:admin1_code":"4.0",
    "gn:admin2_code":"0311",
    "gn:admin3_code":"31110.0",
    "gn:asciiname":"Magos",
    "gn:country_code":"PT",
    "gn:dem":383,
    "gn:feature_class":"P",
    "gn:feature_code":"PPL",
    "gn:name":"Magos",
    "gn:population":0,
    "gn:timezone":"Europe/Lisbon",
    "iso:country":"PT",
    "wof:name":"Magos",
    "wof:placetype":"locality"
},
  "geometry": {"coordinates":[-8.11656,41.60709],"type":"Point"}
}