{
  "type": "Feature",
  "properties": {
    "gn:admin1_code":"22.0",
    "gn:admin2_code":"1822",
    "gn:admin3_code":"182201.0",
    "gn:asciiname":"Alhais",
    "gn:country_code":"PT",
    "gn:dem":775,
    "gn:feature_class":"P",
    "gn:feature_code":"PPL",
    "gn:name":"Alhais",
    "gn:population":0,
    "gn:timezone":"Europe/Lisbon",
    "iso:country":"PT",
    "wof:name":"Alhais",
    "wof:placetype":"locality"
},
  "geometry": {"coordinates":[-7.70549,40.86315],"type":"Point"}
}