{
  "type": "Feature",
  "properties": {
    "gn:admin1_code":"20.0",
    "gn:admin2_code":"1607",
    "gn:admin3_code":"160715.0",
    "gn:asciiname":"Cepoes",
    "gn:country_code":"PT",
    "gn:dem":111,
    "gn:feature_class":"P",
    "gn:feature_code":"PPL",
    "gn:name":"Cep\u00f5es",
    "gn:population":0,
    "gn:timezone":"Europe/Lisbon",
    "iso:country":"PT",
    "wof:name":"Cepoes",
    "wof:placetype":"locality"
},
  "geometry": {"coordinates":[-8.58795,41.82657],"type":"Point"}
}