{
  "type": "Feature",
  "properties": {
    "gn:admin1_code":"20",
    "gn:admin2_code":"1604",
    "gn:admin3_code":"160428.0",
    "gn:asciiname":"Vilar",
    "gn:country_code":"PT",
    "gn:dem":320,
    "gn:feature_class":"P",
    "gn:feature_code":"PPL",
    "gn:name":"Vilar",
    "gn:population":0,
    "gn:timezone":"Europe/Lisbon",
    "iso:country":"PT",
    "wof:name":"Vilar",
    "wof:placetype":"locality"
},
  "geometry": {"coordinates":[-8.34841,42.01808],"type":"Point"}
}