{
  "type": "Feature",
  "properties": {
    "gn:admin1_code":"22",
    "gn:admin2_code":"1814",
    "gn:admin3_code":"181405.0",
    "gn:asciiname":"Sao Joaninho",
    "gn:country_code":"PT",
    "gn:dem":316,
    "gn:feature_class":"P",
    "gn:feature_code":"PPL",
    "gn:name":"S\u00e3o Joaninho",
    "gn:population":0,
    "gn:timezone":"Europe/Lisbon",
    "iso:country":"PT",
    "name:und_x_variant":[
        "San Joaninho",
        "S\u00e3o Joaninho"
    ],
    "wof:name":"Sao Joaninho",
    "wof:placetype":"locality"
},
  "geometry": {"coordinates":[-8.1245,40.44929000000001],"type":"Point"}
}