{
  "type": "Feature",
  "properties": {
    "gn:admin1_code":"22",
    "gn:admin2_code":"1821",
    "gn:admin3_code":"182119.0",
    "gn:asciiname":"Teixo",
    "gn:country_code":"PT",
    "gn:dem":695,
    "gn:feature_class":"P",
    "gn:feature_code":"PPL",
    "gn:name":"Teixo",
    "gn:population":0,
    "gn:timezone":"Europe/Lisbon",
    "iso:country":"PT",
    "wof:name":"Teixo",
    "wof:placetype":"locality"
},
  "geometry": {"coordinates":[-8.23499,40.5532],"type":"Point"}
}