{
  "type": "Feature",
  "properties": {
    "gn:admin1_code":"22.0",
    "gn:admin2_code":"1821",
    "gn:admin3_code":"182111.0",
    "gn:asciiname":"Pedra da Vista",
    "gn:country_code":"PT",
    "gn:dem":299,
    "gn:feature_class":"P",
    "gn:feature_code":"PPL",
    "gn:name":"Pedra da Vista",
    "gn:population":0,
    "gn:timezone":"Europe/Lisbon",
    "iso:country":"PT",
    "wof:name":"Pedra da Vista",
    "wof:placetype":"locality"
},
  "geometry": {"coordinates":[-8.10537,40.53503],"type":"Point"}
}