{
  "type": "Feature",
  "properties": {
    "gn:admin1_code":"11.0",
    "gn:admin2_code":"0914",
    "gn:admin3_code":"91411.0",
    "gn:asciiname":"Numao",
    "gn:country_code":"PT",
    "gn:dem":624,
    "gn:feature_class":"P",
    "gn:feature_code":"PPL",
    "gn:name":"Num\u00e3o",
    "gn:population":0,
    "gn:timezone":"Europe/Lisbon",
    "iso:country":"PT",
    "wof:name":"Numao",
    "wof:placetype":"locality"
},
  "geometry": {"coordinates":[-7.2918,41.09572],"type":"Point"}
}