{
  "type": "Feature",
  "properties": {
    "gn:admin1_code":"13",
    "gn:admin2_code":"1001",
    "gn:admin3_code":"100106.0",
    "gn:asciiname":"Bica",
    "gn:country_code":"PT",
    "gn:dem":180,
    "gn:feature_class":"P",
    "gn:feature_code":"PPL",
    "gn:name":"Bica",
    "gn:population":0,
    "gn:timezone":"Europe/Lisbon",
    "iso:country":"PT",
    "name:deu_x_preferred":[
        "Bica"
    ],
    "name:por_x_preferred":[
        "Bica"
    ],
    "wof:name":"Bica",
    "wof:placetype":"locality"
},
  "geometry": {"coordinates":[-9.05925,39.5263],"type":"Point"}
}