{
  "type": "Feature",
  "properties": {
    "gn:admin1_code":"2.0",
    "gn:admin2_code":"0101",
    "gn:admin3_code":"10104.0",
    "gn:asciiname":"Bicha Moura",
    "gn:country_code":"PT",
    "gn:dem":18,
    "gn:feature_class":"P",
    "gn:feature_code":"PPL",
    "gn:name":"Bicha Moura",
    "gn:population":0,
    "gn:timezone":"Europe/Lisbon",
    "iso:country":"PT",
    "wof:name":"Bicha Moura",
    "wof:placetype":"locality"
},
  "geometry": {"coordinates":[-8.43333,40.56667],"type":"Point"}
}