{
  "type": "Feature",
  "properties": {
    "gn:admin1_code":"11.0",
    "gn:admin2_code":"0907",
    "gn:admin3_code":"90724.0",
    "gn:asciiname":"Penedo da Se",
    "gn:country_code":"PT",
    "gn:dem":794,
    "gn:feature_class":"P",
    "gn:feature_code":"PPL",
    "gn:name":"Penedo da S\u00e9",
    "gn:population":0,
    "gn:timezone":"Europe/Lisbon",
    "iso:country":"PT",
    "wof:name":"Penedo da Se",
    "wof:placetype":"locality"
},
  "geometry": {"coordinates":[-7.07159,40.4826],"type":"Point"}
}