{
  "type": "Feature",
  "properties": {
    "gn:admin1_code":"18",
    "gn:admin2_code":"1418",
    "gn:admin3_code":"141815.0",
    "gn:asciiname":"Barreira Grande",
    "gn:country_code":"PT",
    "gn:dem":194,
    "gn:feature_class":"P",
    "gn:feature_code":"PPL",
    "gn:name":"Barreira Grande",
    "gn:population":0,
    "gn:timezone":"Europe/Lisbon",
    "iso:country":"PT",
    "wof:name":"Barreira Grande",
    "wof:placetype":"locality"
},
  "geometry": {"coordinates":[-8.28954,39.60896],"type":"Point"}
}