{
  "type": "Feature",
  "properties": {
    "gn:admin1_code":"22.0",
    "gn:admin2_code":"1804",
    "gn:admin3_code":"180413.0",
    "gn:asciiname":"Peso",
    "gn:country_code":"PT",
    "gn:dem":643,
    "gn:feature_class":"P",
    "gn:feature_code":"PPL",
    "gn:name":"Peso",
    "gn:population":0,
    "gn:timezone":"Europe/Lisbon",
    "iso:country":"PT",
    "wof:name":"Peso",
    "wof:placetype":"locality"
},
  "geometry": {"coordinates":[-8.1095,41.05528],"type":"Point"}
}