{
  "type": "Feature",
  "properties": {
    "gn:admin1_code":"13",
    "gn:admin2_code":"1001",
    "gn:admin3_code":"100105.0",
    "gn:asciiname":"Riba Fria",
    "gn:country_code":"PT",
    "gn:dem":237,
    "gn:feature_class":"P",
    "gn:feature_code":"PPL",
    "gn:name":"Riba Fria",
    "gn:population":0,
    "gn:timezone":"Europe/Lisbon",
    "iso:country":"PT",
    "wof:name":"Riba Fria",
    "wof:placetype":"locality"
},
  "geometry": {"coordinates":[-8.9936,39.41694],"type":"Point"}
}