{
  "type": "Feature",
  "properties": {
    "gn:admin1_code":"22.0",
    "gn:admin2_code":"1824",
    "gn:admin3_code":"182405.0",
    "gn:asciiname":"Bandavizes",
    "gn:country_code":"PT",
    "gn:dem":261,
    "gn:feature_class":"P",
    "gn:feature_code":"PPL",
    "gn:name":"Bandavizes",
    "gn:population":0,
    "gn:timezone":"Europe/Lisbon",
    "iso:country":"PT",
    "wof:name":"Bandavizes",
    "wof:placetype":"locality"
},
  "geometry": {"coordinates":[-8.0737,40.7314],"type":"Point"}
}