{
  "type": "Feature",
  "properties": {
    "gn:admin1_code":"22.0",
    "gn:admin2_code":"1821",
    "gn:admin3_code":"182111.0",
    "gn:asciiname":"Botulho",
    "gn:country_code":"PT",
    "gn:dem":278,
    "gn:feature_class":"P",
    "gn:feature_code":"PPL",
    "gn:name":"Botulho",
    "gn:population":0,
    "gn:timezone":"Europe/Lisbon",
    "iso:country":"PT",
    "wof:name":"Botulho",
    "wof:placetype":"locality"
},
  "geometry": {"coordinates":[-8.09954,40.51959],"type":"Point"}
}