{
  "type": "Feature",
  "properties": {
    "gn:admin1_code":"09",
    "gn:admin2_code":"0808",
    "gn:admin3_code":"80808.0",
    "gn:asciiname":"Pedragosa",
    "gn:country_code":"PT",
    "gn:dem":250,
    "gn:feature_class":"P",
    "gn:feature_code":"PPL",
    "gn:name":"Pedragosa",
    "gn:population":0,
    "gn:timezone":"Europe/Lisbon",
    "iso:country":"PT",
    "wof:name":"Pedragosa",
    "wof:placetype":"locality"
},
  "geometry": {"coordinates":[-7.99235,37.14211],"type":"Point"}
}