{
  "type": "Feature",
  "properties": {
    "gn:admin1_code":"08",
    "gn:admin2_code":"0701",
    "gn:admin3_code":"70103.0",
    "gn:asciiname":"Aldeia dos Marmelos",
    "gn:country_code":"PT",
    "gn:dem":316,
    "gn:feature_class":"P",
    "gn:feature_code":"PPL",
    "gn:name":"Aldeia dos Marmelos",
    "gn:population":0,
    "gn:timezone":"Europe/Lisbon",
    "iso:country":"PT",
    "wof:name":"Aldeia dos Marmelos",
    "wof:placetype":"locality"
},
  "geometry": {"coordinates":[-7.47248,38.56178],"type":"Point"}
}