{
  "type": "Feature",
  "properties": {
    "gn:admin1_code":"04",
    "gn:admin2_code":"0301",
    "gn:admin3_code":"30104.0",
    "gn:asciiname":"Sao Vicente do Bico",
    "gn:country_code":"PT",
    "gn:dem":79,
    "gn:feature_class":"P",
    "gn:feature_code":"PPL",
    "gn:name":"S\u00e3o Vicente do Bico",
    "gn:population":0,
    "gn:timezone":"Europe/Lisbon",
    "iso:country":"PT",
    "wof:name":"Sao Vicente do Bico",
    "wof:placetype":"locality"
},
  "geometry": {"coordinates":[-8.40927,41.64176],"type":"Point"}
}