{
  "type": "Feature",
  "properties": {
    "gn:admin1_code":"20.0",
    "gn:admin2_code":"1606",
    "gn:admin3_code":"160604.0",
    "gn:asciiname":"Britelo",
    "gn:country_code":"PT",
    "gn:dem":91,
    "gn:feature_class":"P",
    "gn:feature_code":"PPL",
    "gn:name":"Britelo",
    "gn:population":0,
    "gn:timezone":"Europe/Lisbon",
    "iso:country":"PT",
    "wof:name":"Britelo",
    "wof:placetype":"locality"
},
  "geometry": {"coordinates":[-8.29219,41.84019],"type":"Point"}
}