{
  "type": "Feature",
  "properties": {
    "gn:admin1_code":"22.0",
    "gn:admin2_code":"1816",
    "gn:admin3_code":"181606.0",
    "gn:asciiname":"Figueiredo de Alva",
    "gn:country_code":"PT",
    "gn:dem":472,
    "gn:feature_class":"P",
    "gn:feature_code":"PPL",
    "gn:name":"Figueiredo de Alva",
    "gn:population":0,
    "gn:timezone":"Europe/Lisbon",
    "iso:country":"PT",
    "wof:name":"Figueiredo de Alva",
    "wof:placetype":"locality"
},
  "geometry": {"coordinates":[-7.98375,40.82787],"type":"Point"}
}