{
  "type": "Feature",
  "properties": {
    "gn:admin1_code":"03",
    "gn:admin2_code":"0213",
    "gn:admin3_code":"21301.0",
    "gn:asciiname":"A do Pinto",
    "gn:country_code":"PT",
    "gn:dem":196,
    "gn:feature_class":"P",
    "gn:feature_code":"PPL",
    "gn:name":"A do Pinto",
    "gn:population":0,
    "gn:timezone":"Europe/Lisbon",
    "iso:country":"PT",
    "name:und_x_variant":[
        "Aldeia do Pinto",
        "A do Pinto"
    ],
    "wof:name":"A do Pinto",
    "wof:placetype":"locality"
},
  "geometry": {"coordinates":[-7.47955,37.91837],"type":"Point"}
}