{
  "type": "Feature",
  "properties": {
    "gn:admin1_code":"19",
    "gn:admin2_code":"1501",
    "gn:admin3_code":"150101.0",
    "gn:asciiname":"Monte Novo",
    "gn:country_code":"PT",
    "gn:dem":20,
    "gn:feature_class":"P",
    "gn:feature_code":"PPL",
    "gn:name":"Monte Novo",
    "gn:population":0,
    "gn:timezone":"Europe/Lisbon",
    "iso:country":"PT",
    "wof:name":"Monte Novo",
    "wof:placetype":"locality"
},
  "geometry": {"coordinates":[-8.6304,38.44529],"type":"Point"}
}