{
  "type": "Feature",
  "properties": {
    "gn:admin1_code":"08",
    "gn:admin2_code":"0702",
    "gn:admin3_code":"70204.0",
    "gn:asciiname":"Mendo Marques de Cima",
    "gn:country_code":"PT",
    "gn:dem":251,
    "gn:feature_class":"P",
    "gn:feature_code":"PPL",
    "gn:name":"Mendo Marques de Cima",
    "gn:population":0,
    "gn:timezone":"Europe/Lisbon",
    "iso:country":"PT",
    "wof:name":"Mendo Marques de Cima",
    "wof:placetype":"locality"
},
  "geometry": {"coordinates":[-7.90151,38.77218],"type":"Point"}
}