{
  "type": "Feature",
  "properties": {
    "gn:admin1_code":"17.0",
    "gn:admin2_code":"1304",
    "gn:admin3_code":"130405.0",
    "gn:asciiname":"Areja",
    "gn:country_code":"PT",
    "gn:dem":25,
    "gn:feature_class":"P",
    "gn:feature_code":"PPL",
    "gn:name":"Areja",
    "gn:population":0,
    "gn:timezone":"Europe/Lisbon",
    "iso:country":"PT",
    "wof:name":"Areja",
    "wof:placetype":"locality"
},
  "geometry": {"coordinates":[-8.40125,41.05103],"type":"Point"}
}