{
  "type": "Feature",
  "properties": {
    "gn:admin1_code":"21.0",
    "gn:admin2_code":"1701",
    "gn:admin3_code":"170117.0",
    "gn:asciiname":"Parafita",
    "gn:country_code":"PT",
    "gn:dem":736,
    "gn:feature_class":"P",
    "gn:feature_code":"PPL",
    "gn:name":"Parafita",
    "gn:population":0,
    "gn:timezone":"Europe/Lisbon",
    "iso:country":"PT",
    "wof:name":"Parafita",
    "wof:placetype":"locality"
},
  "geometry": {"coordinates":[-7.54372,41.38824],"type":"Point"}
}