{
  "type": "Feature",
  "properties": {
    "gn:admin1_code":"18",
    "gn:admin2_code":"1411",
    "gn:admin3_code":"141106.0",
    "gn:asciiname":"Castanheira",
    "gn:country_code":"PT",
    "gn:dem":157,
    "gn:feature_class":"P",
    "gn:feature_code":"PPL",
    "gn:name":"Castanheira",
    "gn:population":0,
    "gn:timezone":"Europe/Lisbon",
    "iso:country":"PT",
    "wof:name":"Castanheira",
    "wof:placetype":"locality"
},
  "geometry": {"coordinates":[-8.23333,39.66667],"type":"Point"}
}