{
  "type": "Feature",
  "properties": {
    "gn:admin1_code":"7.0",
    "gn:admin2_code":"0608",
    "gn:admin3_code":"60801.0",
    "gn:asciiname":"Colmeal",
    "gn:country_code":"PT",
    "gn:dem":47,
    "gn:feature_class":"P",
    "gn:feature_code":"PPL",
    "gn:name":"Colmeal",
    "gn:population":0,
    "gn:timezone":"Europe/Lisbon",
    "iso:country":"PT",
    "wof:name":"Colmeal",
    "wof:placetype":"locality"
},
  "geometry": {"coordinates":[-8.70829,40.3877],"type":"Point"}
}