{
  "type": "Feature",
  "properties": {
    "gn:admin1_code":"11.0",
    "gn:admin2_code":"0907",
    "gn:admin3_code":"90720.0",
    "gn:asciiname":"Goncalo",
    "gn:country_code":"PT",
    "gn:dem":602,
    "gn:feature_class":"P",
    "gn:feature_code":"PPL",
    "gn:name":"Gon\u00e7alo",
    "gn:population":0,
    "gn:timezone":"Europe/Lisbon",
    "iso:country":"PT",
    "wof:name":"Goncalo",
    "wof:placetype":"locality"
},
  "geometry": {"coordinates":[-7.34837,40.42016],"type":"Point"}
}