{
  "type": "Feature",
  "properties": {
    "gn:admin1_code":"23.0",
    "gn:admin2_code":"4101",
    "gn:admin3_code":"410105.0",
    "gn:asciiname":"Paul de Cima",
    "gn:country_code":"PT",
    "gn:dem":107,
    "gn:feature_class":"P",
    "gn:feature_code":"PPL",
    "gn:name":"Paul de Cima",
    "gn:population":0,
    "gn:timezone":"Atlantic/Azores",
    "iso:country":"PT",
    "wof:name":"Paul de Cima",
    "wof:placetype":"locality"
},
  "geometry": {"coordinates":[-25.15,36.98333],"type":"Point"}
}