{
  "type": "Feature",
  "properties": {
    "gn:admin1_code":"20",
    "gn:admin2_code":"1607",
    "gn:admin3_code":"160747.0",
    "gn:asciiname":"Rebordoes",
    "gn:country_code":"PT",
    "gn:dem":96,
    "gn:feature_class":"P",
    "gn:feature_code":"PPL",
    "gn:name":"Rebord\u00f5es",
    "gn:population":0,
    "gn:timezone":"Europe/Lisbon",
    "iso:country":"PT",
    "name:und_x_variant":[
        "Divino Salvador",
        "Souto",
        "Rebord\u00f5es"
    ],
    "wof:name":"Rebordoes",
    "wof:placetype":"locality"
},
  "geometry": {"coordinates":[-8.55261,41.72166],"type":"Point"}
}