{
  "type": "Feature",
  "properties": {
    "gn:admin1_code":"22",
    "gn:admin2_code":"1811",
    "gn:admin3_code":"181109.0",
    "gn:asciiname":"Roriz",
    "gn:country_code":"PT",
    "gn:dem":421,
    "gn:feature_class":"P",
    "gn:feature_code":"PPL",
    "gn:name":"Roriz",
    "gn:population":0,
    "gn:timezone":"Europe/Lisbon",
    "iso:country":"PT",
    "name:ceb_x_preferred":[
        "Roriz"
    ],
    "name:deu_x_preferred":[
        "Roriz"
    ],
    "name:fra_x_preferred":[
        "Roriz"
    ],
    "name:nld_x_preferred":[
        "Roriz"
    ],
    "name:por_x_preferred":[
        "Roriz"
    ],
    "name:rus_x_preferred":[
        "\u0420\u043e\u0440\u0438\u0448"
    ],
    "name:spa_x_preferred":[
        "Roriz"
    ],
    "wof:name":"Roriz",
    "wof:placetype":"locality"
},
  "geometry": {"coordinates":[-7.74076,40.67501],"type":"Point"}
}