{
  "type": "Feature",
  "properties": {
    "gn:admin1_code":"21",
    "gn:admin2_code":"1706",
    "gn:admin3_code":"170635.0",
    "gn:asciiname":"Vila da Ponte",
    "gn:country_code":"PT",
    "gn:dem":742,
    "gn:feature_class":"P",
    "gn:feature_code":"PPL",
    "gn:name":"Vila da Ponte",
    "gn:population":0,
    "gn:timezone":"Europe/Lisbon",
    "iso:country":"PT",
    "wof:name":"Vila da Ponte",
    "wof:placetype":"locality"
},
  "geometry": {"coordinates":[-7.89612,41.71984000000001],"type":"Point"}
}