{
  "type": "Feature",
  "properties": {
    "gn:country":"PT",
    "gn:fcode":"PPL",
    "gn:population":7789,
    "iso:country":"PT",
    "name:ceb_x_preferred":[
        "Sande"
    ],
    "name:dan_x_preferred":[
        "Sande"
    ],
    "name:deu_x_preferred":[
        "Sande"
    ],
    "name:epo_x_preferred":[
        "Sande"
    ],
    "name:est_x_preferred":[
        "Sande"
    ],
    "name:eus_x_preferred":[
        "Sande"
    ],
    "name:fin_x_preferred":[
        "Sande"
    ],
    "name:fra_x_preferred":[
        "Sande"
    ],
    "name:glg_x_preferred":[
        "Sande"
    ],
    "name:hrv_x_preferred":[
        "Sande"
    ],
    "name:ita_x_preferred":[
        "Sande"
    ],
    "name:lim_x_preferred":[
        "Sande"
    ],
    "name:nld_x_preferred":[
        "Sande"
    ],
    "name:nno_x_preferred":[
        "Sande"
    ],
    "name:nor_x_preferred":[
        "Sande"
    ],
    "name:pol_x_preferred":[
        "Sande"
    ],
    "name:por_x_preferred":[
        "Sande"
    ],
    "name:ron_x_preferred":[
        "Sande"
    ],
    "name:rus_x_preferred":[
        "\u0421\u0430\u043d\u0434\u0435"
    ],
    "name:sme_x_preferred":[
        "Sande"
    ],
    "name:swe_x_preferred":[
        "Sande"
    ],
    "qs_pg:aaroncc":"PT",
    "qs_pg:gn_country":"PT",
    "qs_pg:gn_fcode":"PPL",
    "qs_pg:gn_pop":7789,
    "qs_pg:name":"Sande",
    "qs_pg:name_adm0":"Portugal",
    "qs_pg:name_adm1":"Braga",
    "qs_pg:photos_9r":0,
    "qs_pg:photos_sr":0,
    "qs_pg:pop_sr":5,
    "qs_pg:qs_pg_placetype":"locality",
    "qs_pg:qs_pg_placetype_gp":"Town",
    "qs_pg:woe_adm0":23424925,
    "woe:adm0_id":23424925,
    "woe:name_adm0":"Portugal",
    "woe:name_adm1":"Braga",
    "woe:placetype":"Town",
    "wof:name":"Sande",
    "wof:placetype":"locality",
    "wof:population":7789
},
  "geometry": {"coordinates":[-8.39246,41.7019],"type":"Point"}
}