{
  "type": "Feature",
  "properties": {
    "gn:gn_country":"PT",
    "gn:gn_fcode":"PPL",
    "gn:gn_pop":7789,
    "gn:population":7789,
    "iso:country":"PT",
    "qs_pg:aaroncc":"PT",
    "qs_pg:gn_country":"PT",
    "qs_pg:gn_fcode":"PPL",
    "qs_pg:gn_pop":7789,
    "qs_pg:name":"Sande",
    "qs_pg:name_adm0":"Portugal",
    "qs_pg:name_adm1":"Braga",
    "qs_pg:photos_9r":0,
    "qs_pg:photos_sr":0,
    "qs_pg:pop_sr":5,
    "qs_pg:qs_pg_placetype":"locality",
    "qs_pg:qs_pg_placetype_gp":"Town",
    "qs_pg:woe_adm0":23424925,
    "woe:adm0_id":23424925,
    "woe:name_adm0":"Portugal",
    "woe:name_adm1":"Braga",
    "woe:placetype":"Town",
    "wof:name":"Sande",
    "wof:placetype":"locality",
    "wof:population":7789
},
  "geometry": {"coordinates":[-8.39246,41.7019],"type":"Point"}
}