{
  "type": "Feature",
  "properties": {
    "gn:admin1_code":"20.0",
    "gn:admin2_code":"1601",
    "gn:admin3_code":"160149.0",
    "gn:asciiname":"Gontariz",
    "gn:country_code":"PT",
    "gn:dem":274,
    "gn:feature_class":"P",
    "gn:feature_code":"PPL",
    "gn:name":"Gontariz",
    "gn:population":0,
    "gn:timezone":"Europe/Lisbon",
    "iso:country":"PT",
    "wof:name":"Gontariz",
    "wof:placetype":"locality"
},
  "geometry": {"coordinates":[-8.38333,41.85],"type":"Point"}
}