{
  "type": "Feature",
  "properties": {
    "gn:admin1_code":"08",
    "gn:admin2_code":"0704",
    "gn:admin3_code":"70408.0",
    "gn:asciiname":"Ameixial",
    "gn:country_code":"PT",
    "gn:dem":301,
    "gn:feature_class":"P",
    "gn:feature_code":"PPL",
    "gn:name":"Ameixial",
    "gn:population":0,
    "gn:timezone":"Europe/Lisbon",
    "iso:country":"PT",
    "name:ceb_x_preferred":[
        "Ameixial"
    ],
    "name:deu_x_preferred":[
        "Ameixial"
    ],
    "name:fas_x_preferred":[
        "\u0627\u0645\u06cc\u06a9\u0632\u06cc\u0627\u0644"
    ],
    "name:kaz_x_preferred":[
        "\u0410\u043c\u0435\u0439\u0448\u044c\u044f\u043b"
    ],
    "name:nld_x_preferred":[
        "Ameixial"
    ],
    "name:por_x_preferred":[
        "Ameixial"
    ],
    "name:rus_x_preferred":[
        "\u0410\u043c\u0435\u0439\u0448\u0438\u0430\u043b"
    ],
    "name:spa_x_preferred":[
        "Ameixial"
    ],
    "name:tur_x_preferred":[
        "Ameixial"
    ],
    "name:und_x_variant":[
        "S\u00e3o Bento",
        "S\u00e3o Bento do Ameixial"
    ],
    "wof:name":"Ameixial",
    "wof:placetype":"locality"
},
  "geometry": {"coordinates":[-7.65114,38.84511],"type":"Point"}
}