{
  "type": "Feature",
  "properties": {
    "gn:admin1_code":"08",
    "gn:admin2_code":"0705",
    "gn:admin3_code":"70501.0",
    "gn:asciiname":"Boa Fe",
    "gn:country_code":"PT",
    "gn:dem":262,
    "gn:feature_class":"P",
    "gn:feature_code":"PPL",
    "gn:name":"Boa F\u00e9",
    "gn:population":0,
    "gn:timezone":"Europe/Lisbon",
    "iso:country":"PT",
    "wof:name":"Boa Fe",
    "wof:placetype":"locality"
},
  "geometry": {"coordinates":[-8.09023,38.55236],"type":"Point"}
}