{
  "type": "Feature",
  "properties": {
    "gn:admin1_code":"04",
    "gn:admin2_code":"0302",
    "gn:admin3_code":"30264.0",
    "gn:asciiname":"Quiraz",
    "gn:country_code":"PT",
    "gn:dem":49,
    "gn:feature_class":"P",
    "gn:feature_code":"PPL",
    "gn:name":"Quiraz",
    "gn:population":0,
    "gn:timezone":"Europe/Lisbon",
    "iso:country":"PT",
    "wof:name":"Quiraz",
    "wof:placetype":"locality"
},
  "geometry": {"coordinates":[-8.59817,41.58428],"type":"Point"}
}