{
  "type": "Feature",
  "properties": {
    "gn:country":"PT",
    "gn:fcode":"PPL",
    "gn:population":8322,
    "iso:country":"PT",
    "name:che_x_preferred":[
        "\u041a\u0430\u0448\u0442\u0435\u043b\u043e\u0439\u043d\u0448-\u0434\u0435-\u0421\u0435\u043f\u0435\u0434\u0430"
    ],
    "name:deu_x_preferred":[
        "Castel\u00f5es de Cepeda"
    ],
    "name:eng_x_preferred":[
        "Castel\u00f5es de Cepeda"
    ],
    "name:fra_x_preferred":[
        "Castel\u00f5es de Cepeda"
    ],
    "name:kaz_x_preferred":[
        "\u041a\u0430\u0448\u0442\u0435\u043b\u043e\u0439\u043d\u0448-\u0434\u0435-\u0421\u0435\u043f\u0435\u0434\u0430"
    ],
    "name:nld_x_preferred":[
        "Castel\u00f5es de Cepeda"
    ],
    "name:por_x_preferred":[
        "Castel\u00f5es de Cepeda"
    ],
    "name:rus_x_preferred":[
        "\u041a\u0430\u0448\u0442\u0435\u043b\u043e\u0439\u043d\u0448-\u0434\u0435-\u0421\u0435\u043f\u0435\u0434\u0430"
    ],
    "name:spa_x_preferred":[
        "Castel\u00f5es de Cepeda"
    ],
    "name:tat_x_preferred":[
        "\u041a\u0430\u0448\u0442\u0435\u043b\u043e\u0439\u043d\u0448-\u0434\u0435-\u0421\u0435\u043f\u0435\u0434\u0430"
    ],
    "name:tur_x_preferred":[
        "Castel\u00f5es de Cepeda"
    ],
    "name:zho_x_preferred":[
        "\u5361\u65af\u7279\u9686\u4f0a\u4ec0-\u8fea\u585e\u4f69\u8fbe"
    ],
    "qs_pg:aaroncc":"PT",
    "qs_pg:gn_country":"PT",
    "qs_pg:gn_fcode":"PPL",
    "qs_pg:gn_pop":8322,
    "qs_pg:name":"Castel\u00f5es de Cepeda",
    "qs_pg:name_adm0":"Portugal",
    "qs_pg:name_adm1":"Porto",
    "qs_pg:photos_9k":1,
    "qs_pg:photos_9r":1,
    "qs_pg:photos_all":6,
    "qs_pg:photos_sr":0,
    "qs_pg:pop_sr":5,
    "qs_pg:qs_pg_placetype":"locality",
    "qs_pg:qs_pg_placetype_gp":"Town",
    "qs_pg:woe_adm0":23424925,
    "woe:adm0_id":23424925,
    "woe:name_adm0":"Portugal",
    "woe:name_adm1":"Porto",
    "woe:placetype":"Town",
    "wof:name":"Castel\u00f5es de Cepeda",
    "wof:placetype":"locality",
    "wof:population":8322
},
  "geometry": {"coordinates":[-8.33516,41.20265],"type":"Point"}
}