{
  "type": "Feature",
  "properties": {
    "gn:admin1_code":"2.0",
    "gn:admin2_code":"0101",
    "gn:admin3_code":"10114.0",
    "gn:asciiname":"Barrosa",
    "gn:country_code":"PT",
    "gn:dem":199,
    "gn:feature_class":"P",
    "gn:feature_code":"PPL",
    "gn:name":"Barrosa",
    "gn:population":0,
    "gn:timezone":"Europe/Lisbon",
    "iso:country":"PT",
    "name:ceb_x_preferred":[
        "Barrosa"
    ],
    "name:swe_x_preferred":[
        "Barrosa"
    ],
    "wof:name":"Barrosa",
    "wof:placetype":"locality"
},
  "geometry": {"coordinates":[-8.34051,40.62132],"type":"Point"}
}