{
  "type": "Feature",
  "properties": {
    "gn:admin1_code":"7.0",
    "gn:admin2_code":"0612",
    "gn:admin3_code":"61207.0",
    "gn:asciiname":"Coelhal",
    "gn:country_code":"PT",
    "gn:dem":527,
    "gn:feature_class":"P",
    "gn:feature_code":"PPL",
    "gn:name":"Coelhal",
    "gn:population":0,
    "gn:timezone":"Europe/Lisbon",
    "iso:country":"PT",
    "wof:name":"Coelhal",
    "wof:placetype":"locality"
},
  "geometry": {"coordinates":[-8.02087,40.0343],"type":"Point"}
}