{
  "type": "Feature",
  "properties": {
    "gn:admin1_code":"23.0",
    "gn:admin2_code":"4601",
    "gn:admin3_code":"460102.0",
    "gn:asciiname":"Silveira",
    "gn:country_code":"PT",
    "gn:dem":57,
    "gn:feature_class":"P",
    "gn:feature_code":"PPL",
    "gn:name":"Silveira",
    "gn:population":0,
    "gn:timezone":"Atlantic/Azores",
    "iso:country":"PT",
    "wof:name":"Silveira",
    "wof:placetype":"locality"
},
  "geometry": {"coordinates":[-28.27756,38.41604],"type":"Point"}
}