{
  "type": "Feature",
  "properties": {
    "gn:admin1_code":"20.0",
    "gn:admin2_code":"1601",
    "gn:admin3_code":"160142.0",
    "gn:asciiname":"Algarvia",
    "gn:country_code":"PT",
    "gn:dem":49,
    "gn:feature_class":"P",
    "gn:feature_code":"PPL",
    "gn:name":"Algarvia",
    "gn:population":0,
    "gn:timezone":"Europe/Lisbon",
    "iso:country":"PT",
    "name:ceb_x_preferred":[
        "Algarvia"
    ],
    "name:deu_x_preferred":[
        "Algarvia"
    ],
    "name:msa_x_preferred":[
        "Algarvia"
    ],
    "name:por_x_preferred":[
        "Algarvia"
    ],
    "name:rus_x_preferred":[
        "\u0410\u043b\u0433\u0430\u0440\u0432\u0438\u044f"
    ],
    "name:spa_x_preferred":[
        "Algarvia"
    ],
    "wof:name":"Algarvia",
    "wof:placetype":"locality"
},
  "geometry": {"coordinates":[-8.49214,41.79739],"type":"Point"}
}