{
  "type": "Feature",
  "properties": {
    "gn:admin1_code":"13",
    "gn:admin2_code":"1009",
    "gn:admin3_code":"100921.0",
    "gn:asciiname":"Matoeira",
    "gn:country_code":"PT",
    "gn:dem":59,
    "gn:feature_class":"P",
    "gn:feature_code":"PPL",
    "gn:name":"Matoeira",
    "gn:population":0,
    "gn:timezone":"Europe/Lisbon",
    "iso:country":"PT",
    "wof:name":"Matoeira",
    "wof:placetype":"locality"
},
  "geometry": {"coordinates":[-8.82306,39.80434],"type":"Point"}
}