{
  "type": "Feature",
  "properties": {
    "gn:admin1_code":"18",
    "gn:admin2_code":"1420",
    "gn:admin3_code":"142002.0",
    "gn:asciiname":"Laranjeira",
    "gn:country_code":"PT",
    "gn:dem":121,
    "gn:feature_class":"P",
    "gn:feature_code":"PPL",
    "gn:name":"Laranjeira",
    "gn:population":0,
    "gn:timezone":"Europe/Lisbon",
    "iso:country":"PT",
    "wof:name":"Laranjeira",
    "wof:placetype":"locality"
},
  "geometry": {"coordinates":[-8.36554,39.49033],"type":"Point"}
}