{
  "type": "Feature",
  "properties": {
    "gn:admin1_code":"21.0",
    "gn:admin2_code":"1712",
    "gn:admin3_code":"171229.0",
    "gn:asciiname":"Moncal Vargas",
    "gn:country_code":"PT",
    "gn:dem":541,
    "gn:feature_class":"P",
    "gn:feature_code":"PPL",
    "gn:name":"Moncal Vargas",
    "gn:population":0,
    "gn:timezone":"Europe/Lisbon",
    "iso:country":"PT",
    "wof:name":"Moncal Vargas",
    "wof:placetype":"locality"
},
  "geometry": {"coordinates":[-7.36667,41.63333],"type":"Point"}
}