{
  "type": "Feature",
  "properties": {
    "gn:admin1_code":"19",
    "gn:admin2_code":"1501",
    "gn:admin3_code":"150103.0",
    "gn:asciiname":"Arouca",
    "gn:country_code":"PT",
    "gn:dem":21,
    "gn:feature_class":"P",
    "gn:feature_code":"PPL",
    "gn:name":"Arouca",
    "gn:population":0,
    "gn:timezone":"Europe/Lisbon",
    "iso:country":"PT",
    "name:ceb_x_preferred":[
        "Arouca"
    ],
    "name:deu_x_preferred":[
        "Arouca"
    ],
    "name:fra_x_preferred":[
        "Arouca"
    ],
    "name:nld_x_preferred":[
        "Arouca"
    ],
    "name:pol_x_preferred":[
        "Arouca"
    ],
    "name:por_x_preferred":[
        "Arouca"
    ],
    "name:rus_x_preferred":[
        "\u0410\u0440\u043e\u043a\u0430"
    ],
    "name:ukr_x_preferred":[
        "\u0410\u0440\u043e\u043a\u0430"
    ],
    "wof:name":"Arouca",
    "wof:placetype":"locality"
},
  "geometry": {"coordinates":[-8.46437,38.30328],"type":"Point"}
}