{
  "type": "Feature",
  "properties": {
    "gn:admin1_code":"07",
    "gn:admin2_code":"0606",
    "gn:admin3_code":"60601.0",
    "gn:asciiname":"Roda Cimeira",
    "gn:country_code":"PT",
    "gn:dem":489,
    "gn:feature_class":"P",
    "gn:feature_code":"PPL",
    "gn:name":"Roda Cimeira",
    "gn:population":0,
    "gn:timezone":"Europe/Lisbon",
    "iso:country":"PT",
    "wof:name":"Roda Cimeira",
    "wof:placetype":"locality"
},
  "geometry": {"coordinates":[-8.10035,40.0653],"type":"Point"}
}