{
  "type": "Feature",
  "properties": {
    "gn:admin1_code":"02",
    "gn:admin2_code":"0114",
    "gn:admin3_code":"11404.0",
    "gn:asciiname":"Repolao",
    "gn:country_code":"PT",
    "gn:dem":29,
    "gn:feature_class":"P",
    "gn:feature_code":"PPL",
    "gn:name":"Repol\u00e3o",
    "gn:population":0,
    "gn:timezone":"Europe/Lisbon",
    "iso:country":"PT",
    "wof:name":"Repolao",
    "wof:placetype":"locality"
},
  "geometry": {"coordinates":[-8.48587,40.5229],"type":"Point"}
}