{
  "type": "Feature",
  "properties": {
    "gn:admin1_code":"20.0",
    "gn:admin2_code":"1607",
    "gn:admin3_code":"160718.0",
    "gn:asciiname":"Burgonha",
    "gn:country_code":"PT",
    "gn:dem":129,
    "gn:feature_class":"P",
    "gn:feature_code":"PPL",
    "gn:name":"Burgonha",
    "gn:population":0,
    "gn:timezone":"Europe/Lisbon",
    "iso:country":"PT",
    "wof:name":"Burgonha",
    "wof:placetype":"locality"
},
  "geometry": {"coordinates":[-8.61667,41.71667],"type":"Point"}
}