{
  "type": "Feature",
  "properties": {
    "gn:admin1_code":"22",
    "gn:admin2_code":"1804",
    "gn:admin3_code":"180410.0",
    "gn:asciiname":"Valemelhorado",
    "gn:country_code":"PT",
    "gn:dem":347,
    "gn:feature_class":"P",
    "gn:feature_code":"PPL",
    "gn:name":"Valemelhorado",
    "gn:population":0,
    "gn:timezone":"Europe/Lisbon",
    "iso:country":"PT",
    "wof:name":"Valemelhorado",
    "wof:placetype":"locality"
},
  "geometry": {"coordinates":[-8.05829,41.0727],"type":"Point"}
}