{
  "type": "Feature",
  "properties": {
    "gn:admin1_code":"13",
    "gn:admin2_code":"1014",
    "gn:admin3_code":"101402.0",
    "gn:asciiname":"Bolhos",
    "gn:country_code":"PT",
    "gn:dem":64,
    "gn:feature_class":"P",
    "gn:feature_code":"PPL",
    "gn:name":"Bolhos",
    "gn:population":0,
    "gn:timezone":"Europe/Lisbon",
    "iso:country":"PT",
    "wof:name":"Bolhos",
    "wof:placetype":"locality"
},
  "geometry": {"coordinates":[-9.28534,39.30615],"type":"Point"}
}