{
  "type": "Feature",
  "properties": {
    "gn:admin1_code":"21.0",
    "gn:admin2_code":"1703",
    "gn:admin3_code":"170306.0",
    "gn:asciiname":"Calvao",
    "gn:country_code":"PT",
    "gn:dem":657,
    "gn:feature_class":"P",
    "gn:feature_code":"PPL",
    "gn:name":"Calv\u00e3o",
    "gn:population":0,
    "gn:timezone":"Europe/Lisbon",
    "iso:country":"PT",
    "wof:name":"Calvao",
    "wof:placetype":"locality"
},
  "geometry": {"coordinates":[-7.54502,41.79093],"type":"Point"}
}