{
  "type": "Feature",
  "properties": {
    "gn:admin1_code":"21.0",
    "gn:admin2_code":"1711",
    "gn:admin3_code":"171105.0",
    "gn:asciiname":"Paradela do Monte",
    "gn:country_code":"PT",
    "gn:dem":668,
    "gn:feature_class":"P",
    "gn:feature_code":"PPL",
    "gn:name":"Paradela do Monte",
    "gn:population":0,
    "gn:timezone":"Europe/Lisbon",
    "iso:country":"PT",
    "wof:name":"Paradela do Monte",
    "wof:placetype":"locality"
},
  "geometry": {"coordinates":[-7.84318,41.24869],"type":"Point"}
}