{
  "type": "Feature",
  "properties": {
    "gn:admin1_code":"09",
    "gn:admin2_code":"0808",
    "gn:admin3_code":"80807.0",
    "gn:asciiname":"Pero de Elvas",
    "gn:country_code":"PT",
    "gn:dem":491,
    "gn:feature_class":"P",
    "gn:feature_code":"PPL",
    "gn:name":"Pero de Elvas",
    "gn:population":0,
    "gn:timezone":"Europe/Lisbon",
    "iso:country":"PT",
    "wof:name":"Pero de Elvas",
    "wof:placetype":"locality"
},
  "geometry": {"coordinates":[-7.93003,37.26801],"type":"Point"}
}