{
  "type": "Feature",
  "properties": {
    "iso:country":"PT",
    "name:ast_x_preferred":[
        "Brandoa"
    ],
    "name:bul_x_preferred":[
        "\u0411\u0440\u0430\u043d\u0434\u043e\u0430"
    ],
    "name:ceb_x_preferred":[
        "Brandoa"
    ],
    "name:deu_x_preferred":[
        "Brandoa"
    ],
    "name:eng_x_preferred":[
        "Brandoa"
    ],
    "name:fra_x_preferred":[
        "Brandoa"
    ],
    "name:kaz_x_preferred":[
        "\u0411\u0440\u0430\u043d\u0434\u043e\u0430"
    ],
    "name:nld_x_preferred":[
        "Brandoa"
    ],
    "name:pol_x_preferred":[
        "Brandoa"
    ],
    "name:por_x_preferred":[
        "Brandoa"
    ],
    "name:rus_x_preferred":[
        "\u0411\u0440\u0430\u043d\u0434\u043e\u0430"
    ],
    "name:sco_x_preferred":[
        "Brandoa"
    ],
    "name:spa_x_preferred":[
        "Brandoa"
    ],
    "name:swe_x_preferred":[
        "Brandoa"
    ],
    "name:ukr_x_preferred":[
        "\u0411\u0440\u0430\u043d\u0434\u043e\u0430"
    ],
    "name:zho_x_preferred":[
        "Caram\u00e3o"
    ],
    "qs:gn_adm0_cc":"PT",
    "qs:gn_fcode":"ADM3",
    "qs:gn_local":8010569,
    "qs:gn_nam_loc":"Amadora, Lisboa, PT",
    "qs:gn_namadm1":"14",
    "qs:gn_name":"Brandoa",
    "qs:local_max":284,
    "qs:local_sum":342,
    "qs:localhoods":3,
    "qs:name":"Brandoa",
    "qs:name_adm0":"Portugal",
    "qs:name_adm1":"Lisboa",
    "qs:name_adm2":"Amadora",
    "qs:name_local":"Amadora",
    "qs:photo_max":6,
    "qs:photo_sum":8,
    "qs:placetype":"Suburb",
    "qs:quad_count":3,
    "qs:woe_adm0":23424925,
    "qs:woe_adm1":2346573,
    "qs:woe_adm2":12596416,
    "qs:woe_lau":0,
    "qs:woe_local":12596416,
    "qs:woe_ver":"7.10.0",
    "wd:wordcount":45,
    "wof:lang":[
        "por"
    ],
    "wof:name":"Brandoa",
    "wof:placetype":"neighbourhood"
},
  "geometry": {"coordinates":[-9.210663,38.776035],"type":"Point"}
}