{
  "type": "Feature",
  "properties": {
    "gn:admin1_code":"22.0",
    "gn:admin2_code":"1823",
    "gn:admin3_code":"182329.0",
    "gn:asciiname":"Covelo",
    "gn:country_code":"PT",
    "gn:dem":473,
    "gn:feature_class":"P",
    "gn:feature_code":"PPL",
    "gn:name":"Covelo",
    "gn:population":0,
    "gn:timezone":"Europe/Lisbon",
    "iso:country":"PT",
    "name:ceb_x_preferred":[
        "Covelo"
    ],
    "name:deu_x_preferred":[
        "Covelo"
    ],
    "name:fra_x_preferred":[
        "Covelo"
    ],
    "name:glg_x_preferred":[
        "Covelo"
    ],
    "name:ita_x_preferred":[
        "Covelo"
    ],
    "name:nld_x_preferred":[
        "Covelo"
    ],
    "name:por_x_preferred":[
        "Covelo"
    ],
    "name:srp_x_preferred":[
        "Covelo"
    ],
    "name:swe_x_preferred":[
        "Covelo"
    ],
    "name:tur_x_preferred":[
        "Covelo"
    ],
    "name:ukr_x_preferred":[
        "\u041a\u043e\u0432\u0435\u043b\u0443"
    ],
    "wof:name":"Covelo",
    "wof:placetype":"locality"
},
  "geometry": {"coordinates":[-7.78101,40.70409],"type":"Point"}
}