{
  "type": "Feature",
  "properties": {
    "gn:admin1_code":"22",
    "gn:admin2_code":"1817",
    "gn:admin3_code":"181707.0",
    "gn:asciiname":"Rio de Moinhos",
    "gn:country_code":"PT",
    "gn:dem":498,
    "gn:feature_class":"P",
    "gn:feature_code":"PPL",
    "gn:name":"Rio de Moinhos",
    "gn:population":0,
    "gn:timezone":"Europe/Lisbon",
    "iso:country":"PT",
    "wof:name":"Rio de Moinhos",
    "wof:placetype":"locality"
},
  "geometry": {"coordinates":[-7.70317,40.71283],"type":"Point"}
}