{
  "type": "Feature",
  "properties": {
    "gn:admin1_code":"18",
    "gn:admin2_code":"1413",
    "gn:admin3_code":"141304.0",
    "gn:asciiname":"Maxieira",
    "gn:country_code":"PT",
    "gn:dem":397,
    "gn:feature_class":"P",
    "gn:feature_code":"PPL",
    "gn:name":"Maxieira",
    "gn:population":0,
    "gn:timezone":"Europe/Lisbon",
    "iso:country":"PT",
    "wof:name":"Maxieira",
    "wof:placetype":"locality"
},
  "geometry": {"coordinates":[-7.98011,39.6429],"type":"Point"}
}