{
  "type": "Feature",
  "properties": {
    "gn:admin1_code":"4.0",
    "gn:admin2_code":"0302",
    "gn:admin3_code":"30231.0",
    "gn:asciiname":"Fim de Vila",
    "gn:country_code":"PT",
    "gn:dem":53,
    "gn:feature_class":"P",
    "gn:feature_code":"PPL",
    "gn:name":"Fim de Vila",
    "gn:population":0,
    "gn:timezone":"Europe/Lisbon",
    "iso:country":"PT",
    "wof:name":"Fim de Vila",
    "wof:placetype":"locality"
},
  "geometry": {"coordinates":[-8.67644,41.48199],"type":"Point"}
}