{
  "type": "Feature",
  "properties": {
    "gn:admin1_code":"20",
    "gn:admin2_code":"1601",
    "gn:admin3_code":"160140.0",
    "gn:asciiname":"Sao Jorge",
    "gn:country_code":"PT",
    "gn:dem":86,
    "gn:feature_class":"P",
    "gn:feature_code":"PPL",
    "gn:name":"S\u00e3o Jorge",
    "gn:population":0,
    "gn:timezone":"Europe/Lisbon",
    "iso:country":"PT",
    "wof:name":"Sao Jorge",
    "wof:placetype":"locality"
},
  "geometry": {"coordinates":[-8.37678,41.82214000000001],"type":"Point"}
}