{
  "type": "Feature",
  "properties": {
    "gn:admin1_code":"4.0",
    "gn:admin2_code":"0309",
    "gn:admin3_code":"30914.0",
    "gn:asciiname":"Olival",
    "gn:country_code":"PT",
    "gn:dem":231,
    "gn:feature_class":"P",
    "gn:feature_code":"PPL",
    "gn:name":"Olival",
    "gn:population":0,
    "gn:timezone":"Europe/Lisbon",
    "iso:country":"PT",
    "name:ceb_x_preferred":[
        "Olival"
    ],
    "name:deu_x_preferred":[
        "Olival"
    ],
    "name:fra_x_preferred":[
        "Olival"
    ],
    "name:nld_x_preferred":[
        "Olival"
    ],
    "name:por_x_preferred":[
        "Olival"
    ],
    "name:rus_x_preferred":[
        "\u041e\u043b\u0438\u0432\u0430\u043b"
    ],
    "name:tur_x_preferred":[
        "Olival"
    ],
    "wof:name":"Olival",
    "wof:placetype":"locality"
},
  "geometry": {"coordinates":[-8.28968,41.60357],"type":"Point"}
}