{
  "type": "Feature",
  "properties": {
    "gn:admin1_code":"16",
    "gn:admin2_code":"1203",
    "gn:admin3_code":"120302.0",
    "gn:asciiname":"Vale de Cabecas",
    "gn:country_code":"PT",
    "gn:dem":122,
    "gn:feature_class":"P",
    "gn:feature_code":"PPL",
    "gn:name":"Vale de Cabe\u00e7as",
    "gn:population":0,
    "gn:timezone":"Europe/Lisbon",
    "iso:country":"PT",
    "wof:name":"Vale de Cabecas",
    "wof:placetype":"locality"
},
  "geometry": {"coordinates":[-8.09229,39.05782],"type":"Point"}
}