{
  "type": "Feature",
  "properties": {
    "gn:admin1_code":"16",
    "gn:admin2_code":"1213",
    "gn:admin3_code":"121304.0",
    "gn:asciiname":"Pernancha de Cima",
    "gn:country_code":"PT",
    "gn:dem":155,
    "gn:feature_class":"P",
    "gn:feature_code":"PPL",
    "gn:name":"Pernancha de Cima",
    "gn:population":0,
    "gn:timezone":"Europe/Lisbon",
    "iso:country":"PT",
    "wof:name":"Pernancha de Cima",
    "wof:placetype":"locality"
},
  "geometry": {"coordinates":[-8.22069,39.17573],"type":"Point"}
}