{
  "type": "Feature",
  "properties": {
    "gn:admin1_code":"07",
    "gn:admin2_code":"0616",
    "gn:admin3_code":"61613.0",
    "gn:asciiname":"Sinde",
    "gn:country_code":"PT",
    "gn:dem":264,
    "gn:feature_class":"P",
    "gn:feature_code":"PPL",
    "gn:name":"Sinde",
    "gn:population":0,
    "gn:timezone":"Europe/Lisbon",
    "iso:country":"PT",
    "name:ceb_x_preferred":[
        "Sinde"
    ],
    "name:fra_x_preferred":[
        "Sinde"
    ],
    "name:glg_x_preferred":[
        "Sinde"
    ],
    "name:spa_x_preferred":[
        "Sinde"
    ],
    "name:swe_x_preferred":[
        "Sinde"
    ],
    "wof:name":"Sinde",
    "wof:placetype":"locality"
},
  "geometry": {"coordinates":[-8.05136,40.32259000000001],"type":"Point"}
}