{
  "type": "Feature",
  "properties": {
    "gn:admin1_code":"21",
    "gn:admin2_code":"1706",
    "gn:admin3_code":"170627.0",
    "gn:asciiname":"Santo Andre",
    "gn:country_code":"PT",
    "gn:dem":828,
    "gn:feature_class":"P",
    "gn:feature_code":"PPL",
    "gn:name":"Santo Andr\u00e9",
    "gn:population":0,
    "gn:timezone":"Europe/Lisbon",
    "iso:country":"PT",
    "wof:name":"Santo Andre",
    "wof:placetype":"locality"
},
  "geometry": {"coordinates":[-7.66699,41.86498],"type":"Point"}
}