{
  "type": "Feature",
  "properties": {
    "gn:admin1_code":"5.0",
    "gn:admin2_code":"0403",
    "gn:admin3_code":"40307.0",
    "gn:asciiname":"Lavandeira",
    "gn:country_code":"PT",
    "gn:dem":625,
    "gn:feature_class":"P",
    "gn:feature_code":"PPL",
    "gn:name":"Lavandeira",
    "gn:population":0,
    "gn:timezone":"Europe/Lisbon",
    "iso:country":"PT",
    "name:ceb_x_preferred":[
        "Lavandeira"
    ],
    "name:glg_x_preferred":[
        "Lavandeira"
    ],
    "name:nld_x_preferred":[
        "Lavandeira"
    ],
    "name:por_x_preferred":[
        "Lavandeira"
    ],
    "name:rus_x_preferred":[
        "\u041b\u0430\u0432\u0430\u043d\u0434\u0435\u0439\u0440\u0430"
    ],
    "name:swe_x_preferred":[
        "Lavandeira"
    ],
    "name:ukr_x_preferred":[
        "\u041b\u0430\u0432\u0430\u043d\u0434\u0435\u0439\u0440\u0430"
    ],
    "wof:name":"Lavandeira",
    "wof:placetype":"locality"
},
  "geometry": {"coordinates":[-7.3009,41.19294],"type":"Point"}
}