{
  "type": "Feature",
  "properties": {
    "gn:admin1_code":"18",
    "gn:admin2_code":"1417",
    "gn:admin3_code":"141701.0",
    "gn:asciiname":"Vale Formoso",
    "gn:country_code":"PT",
    "gn:dem":193,
    "gn:feature_class":"P",
    "gn:feature_code":"PPL",
    "gn:name":"Vale Formoso",
    "gn:population":0,
    "gn:timezone":"Europe/Lisbon",
    "iso:country":"PT",
    "name:ceb_x_preferred":[
        "Vale Formoso"
    ],
    "name:deu_x_preferred":[
        "Vale Formoso"
    ],
    "name:kaz_x_preferred":[
        "\u0412\u0430\u043b\u0435-\u0424\u043e\u0440\u043c\u043e\u0437\u0443"
    ],
    "name:nld_x_preferred":[
        "Vale Formoso"
    ],
    "name:por_x_preferred":[
        "Vale Formoso"
    ],
    "name:rus_x_preferred":[
        "\u0412\u0430\u043b\u0435-\u0424\u043e\u0440\u043c\u043e\u0437\u0443"
    ],
    "name:spa_x_preferred":[
        "Vale Formoso"
    ],
    "name:ukr_x_preferred":[
        "\u0412\u0430\u043b\u0435-\u0424\u043e\u0440\u043c\u043e\u0437\u0443"
    ],
    "wof:name":"Vale Formoso",
    "wof:placetype":"locality"
},
  "geometry": {"coordinates":[-8.09941,39.54368],"type":"Point"}
}