{
  "type": "Feature",
  "properties": {
    "gn:admin1_code":"20.0",
    "gn:admin2_code":"1609",
    "gn:admin3_code":"160905.0",
    "gn:asciiname":"Alem do Rio",
    "gn:country_code":"PT",
    "gn:dem":15,
    "gn:feature_class":"P",
    "gn:feature_code":"PPL",
    "gn:name":"Al\u00e9m do Rio",
    "gn:population":0,
    "gn:timezone":"Europe/Lisbon",
    "iso:country":"PT",
    "wof:name":"Alem do Rio",
    "wof:placetype":"locality"
},
  "geometry": {"coordinates":[-8.85712,41.72381],"type":"Point"}
}