{
  "type": "Feature",
  "properties": {
    "gn:admin1_code":"22",
    "gn:admin2_code":"1823",
    "gn:admin3_code":"182327.0",
    "gn:asciiname":"Teivas",
    "gn:country_code":"PT",
    "gn:dem":401,
    "gn:feature_class":"P",
    "gn:feature_code":"PPL",
    "gn:name":"Teivas",
    "gn:population":0,
    "gn:timezone":"Europe/Lisbon",
    "iso:country":"PT",
    "wof:name":"Teivas",
    "wof:placetype":"locality"
},
  "geometry": {"coordinates":[-7.92475,40.61599],"type":"Point"}
}