{
  "type": "Feature",
  "properties": {
    "gn:admin1_code":"07",
    "gn:admin2_code":"0607",
    "gn:admin3_code":"60704.0",
    "gn:asciiname":"Quatro Aguas",
    "gn:country_code":"PT",
    "gn:dem":212,
    "gn:feature_class":"P",
    "gn:feature_code":"PPL",
    "gn:name":"Quatro \u00c1guas",
    "gn:population":0,
    "gn:timezone":"Europe/Lisbon",
    "iso:country":"PT",
    "wof:name":"Quatro Aguas",
    "wof:placetype":"locality"
},
  "geometry": {"coordinates":[-8.17483,40.16749],"type":"Point"}
}