{
  "type": "Feature",
  "properties": {
    "gn:admin1_code":"22.0",
    "gn:admin2_code":"1824",
    "gn:admin3_code":"182407.0",
    "gn:asciiname":"Covas",
    "gn:country_code":"PT",
    "gn:dem":852,
    "gn:feature_class":"P",
    "gn:feature_code":"PPL",
    "gn:name":"Covas",
    "gn:population":0,
    "gn:timezone":"Europe/Lisbon",
    "iso:country":"PT",
    "name:ceb_x_preferred":[
        "Covas"
    ],
    "name:deu_x_preferred":[
        "Covas"
    ],
    "name:fra_x_preferred":[
        "Covas"
    ],
    "name:glg_x_preferred":[
        "Covas"
    ],
    "name:kaz_x_preferred":[
        "\u041a\u043e\u0432\u0430\u0448"
    ],
    "name:nld_x_preferred":[
        "Covas"
    ],
    "name:por_x_preferred":[
        "Covas"
    ],
    "name:rus_x_preferred":[
        "\u041a\u043e\u0432\u0430\u0448"
    ],
    "name:spa_x_preferred":[
        "Covas"
    ],
    "name:tur_x_preferred":[
        "Covas"
    ],
    "name:ukr_x_preferred":[
        "\u041a\u043e\u0432\u0430\u0448"
    ],
    "wof:name":"Covas",
    "wof:placetype":"locality"
},
  "geometry": {"coordinates":[-8.10324,40.66598],"type":"Point"}
}