{
  "type": "Feature",
  "properties": {
    "gn:admin1_code":"4.0",
    "gn:admin2_code":"0304",
    "gn:admin3_code":"30415.0",
    "gn:asciiname":"Fondevila",
    "gn:country_code":"PT",
    "gn:dem":461,
    "gn:feature_class":"P",
    "gn:feature_code":"PPL",
    "gn:name":"Fondevila",
    "gn:population":0,
    "gn:timezone":"Europe/Lisbon",
    "iso:country":"PT",
    "wof:name":"Fondevila",
    "wof:placetype":"locality"
},
  "geometry": {"coordinates":[-7.96914,41.55333],"type":"Point"}
}