{
  "type": "Feature",
  "properties": {
    "gn:admin1_code":"09",
    "gn:admin2_code":"0812",
    "gn:admin3_code":"81201.0",
    "gn:asciiname":"Fonte do Touro",
    "gn:country_code":"PT",
    "gn:dem":256,
    "gn:feature_class":"P",
    "gn:feature_code":"PPL",
    "gn:name":"Fonte do Touro",
    "gn:population":0,
    "gn:timezone":"Europe/Lisbon",
    "iso:country":"PT",
    "wof:name":"Fonte do Touro",
    "wof:placetype":"locality"
},
  "geometry": {"coordinates":[-7.91979,37.15454],"type":"Point"}
}