{
  "type": "Feature",
  "properties": {
    "gn:admin1_code":"13",
    "gn:admin2_code":"1006",
    "gn:admin3_code":"100612.0",
    "gn:asciiname":"Sao Gregorio",
    "gn:country_code":"PT",
    "gn:dem":142,
    "gn:feature_class":"P",
    "gn:feature_code":"PPL",
    "gn:name":"S\u00e3o Greg\u00f3rio",
    "gn:population":0,
    "gn:timezone":"Europe/Lisbon",
    "iso:country":"PT",
    "name:und_x_variant":[
        "S\u00e3o Gregorio da Fanadia",
        "S\u00e3o Greg\u00f3rio"
    ],
    "wof:name":"Sao Gregorio",
    "wof:placetype":"locality"
},
  "geometry": {"coordinates":[-9.05618,39.35258],"type":"Point"}
}