{
  "type": "Feature",
  "properties": {
    "gn:admin1_code":"23.0",
    "gn:admin2_code":"4101",
    "gn:admin3_code":"410103.0",
    "gn:asciiname":"Lombinha",
    "gn:country_code":"PT",
    "gn:dem":256,
    "gn:feature_class":"P",
    "gn:feature_code":"PPL",
    "gn:name":"Lombinha",
    "gn:population":0,
    "gn:timezone":"Atlantic/Azores",
    "iso:country":"PT",
    "wof:name":"Lombinha",
    "wof:placetype":"locality"
},
  "geometry": {"coordinates":[-25.08333,36.95],"type":"Point"}
}