{
  "type": "Feature",
  "properties": {
    "gn:admin1_code":"06",
    "gn:admin2_code":"0508",
    "gn:admin3_code":"50804.0",
    "gn:asciiname":"Cimadas Fundeiras",
    "gn:country_code":"PT",
    "gn:dem":480,
    "gn:feature_class":"P",
    "gn:feature_code":"PPL",
    "gn:name":"Cimadas Fundeiras",
    "gn:population":0,
    "gn:timezone":"Europe/Lisbon",
    "iso:country":"PT",
    "wof:name":"Cimadas Fundeiras",
    "wof:placetype":"locality"
},
  "geometry": {"coordinates":[-7.98181,39.74591],"type":"Point"}
}