{
  "type": "Feature",
  "properties": {
    "gn:admin1_code":"04",
    "gn:admin2_code":"0304",
    "gn:admin3_code":"30415.0",
    "gn:asciiname":"Rio Douro",
    "gn:country_code":"PT",
    "gn:dem":353,
    "gn:feature_class":"P",
    "gn:feature_code":"PPL",
    "gn:name":"Rio Douro",
    "gn:population":0,
    "gn:timezone":"Europe/Lisbon",
    "iso:country":"PT",
    "name:ceb_x_preferred":[
        "Rio Douro"
    ],
    "name:deu_x_preferred":[
        "Rio Douro"
    ],
    "name:por_x_preferred":[
        "Rio Douro"
    ],
    "wof:name":"Rio Douro",
    "wof:placetype":"locality"
},
  "geometry": {"coordinates":[-7.97139,41.5389],"type":"Point"}
}