{
  "type": "Feature",
  "properties": {
    "gn:admin1_code":"4.0",
    "gn:admin2_code":"0303",
    "gn:admin3_code":"30355.0",
    "gn:asciiname":"Pedregal",
    "gn:country_code":"PT",
    "gn:dem":392,
    "gn:feature_class":"P",
    "gn:feature_code":"PPL",
    "gn:name":"Pedregal",
    "gn:population":0,
    "gn:timezone":"Europe/Lisbon",
    "iso:country":"PT",
    "name:ceb_x_preferred":[
        "Pedregal"
    ],
    "name:fra_x_preferred":[
        "Pedregal"
    ],
    "name:ita_x_preferred":[
        "Pedregal"
    ],
    "name:pol_x_preferred":[
        "Pedregal"
    ],
    "name:por_x_preferred":[
        "Pedregal"
    ],
    "name:spa_x_preferred":[
        "Pedregal"
    ],
    "name:srp_x_preferred":[
        "\u041f\u0435\u0434\u0440\u0435\u0433\u0430\u043b"
    ],
    "name:swe_x_preferred":[
        "Pedregal"
    ],
    "wof:name":"Pedregal",
    "wof:placetype":"locality"
},
  "geometry": {"coordinates":[-8.32577,41.54971],"type":"Point"}
}