{
  "type": "Feature",
  "properties": {
    "gn:admin1_code":"23.0",
    "gn:admin2_code":"4601",
    "gn:admin3_code":"460104.0",
    "gn:asciiname":"Arrife",
    "gn:country_code":"PT",
    "gn:dem":168,
    "gn:feature_class":"P",
    "gn:feature_code":"PPL",
    "gn:name":"Arrife",
    "gn:population":0,
    "gn:timezone":"Atlantic/Azores",
    "iso:country":"PT",
    "wof:name":"Arrife",
    "wof:placetype":"locality"
},
  "geometry": {"coordinates":[-28.22139,38.39152],"type":"Point"}
}