{
  "type": "Feature",
  "properties": {
    "gn:admin1_code":"18",
    "gn:admin2_code":"1407",
    "gn:admin3_code":"140704.0",
    "gn:asciiname":"Aranhas de Baixo",
    "gn:country_code":"PT",
    "gn:dem":143,
    "gn:feature_class":"P",
    "gn:feature_code":"PPL",
    "gn:name":"Aranhas de Baixo",
    "gn:population":0,
    "gn:timezone":"Europe/Lisbon",
    "iso:country":"PT",
    "wof:name":"Aranhas de Baixo",
    "wof:placetype":"locality"
},
  "geometry": {"coordinates":[-8.27743,39.31806],"type":"Point"}
}