{
  "type": "Feature",
  "properties": {
    "gn:admin1_code":"5.0",
    "gn:admin2_code":"0403",
    "gn:admin3_code":"40312.0",
    "gn:asciiname":"Pereiros",
    "gn:country_code":"PT",
    "gn:dem":501,
    "gn:feature_class":"P",
    "gn:feature_code":"PPL",
    "gn:name":"Pereiros",
    "gn:population":0,
    "gn:timezone":"Europe/Lisbon",
    "iso:country":"PT",
    "wof:name":"Pereiros",
    "wof:placetype":"locality"
},
  "geometry": {"coordinates":[-7.29737,41.31564],"type":"Point"}
}