{
  "type": "Feature",
  "properties": {
    "gn:admin1_code":"7.0",
    "gn:admin2_code":"0614",
    "gn:admin3_code":"61404.0",
    "gn:asciiname":"Legacao",
    "gn:country_code":"PT",
    "gn:dem":238,
    "gn:feature_class":"P",
    "gn:feature_code":"PPL",
    "gn:name":"Lega\u00e7\u00e3o",
    "gn:population":0,
    "gn:timezone":"Europe/Lisbon",
    "iso:country":"PT",
    "wof:name":"Legacao",
    "wof:placetype":"locality"
},
  "geometry": {"coordinates":[-8.46715,40.03069],"type":"Point"}
}