{
  "type": "Feature",
  "properties": {
    "gn:admin1_code":"16.0",
    "gn:admin2_code":"1214",
    "gn:admin3_code":"121406.0",
    "gn:asciiname":"Ribeira de Nisa",
    "gn:country_code":"PT",
    "gn:dem":514,
    "gn:feature_class":"P",
    "gn:feature_code":"PPLL",
    "gn:name":"Ribeira de Nisa",
    "gn:population":0,
    "gn:timezone":"Europe/Lisbon",
    "iso:country":"PT",
    "wof:name":"Ribeira de Nisa",
    "wof:placetype":"locality"
},
  "geometry": {"coordinates":[-7.41388,39.32553],"type":"Point"}
}