{
  "type": "Feature",
  "properties": {
    "gn:admin1_code":"22.0",
    "gn:admin2_code":"1805",
    "gn:admin3_code":"180523.0",
    "gn:asciiname":"Agra",
    "gn:country_code":"PT",
    "gn:dem":478,
    "gn:feature_class":"P",
    "gn:feature_code":"PPL",
    "gn:name":"Agra",
    "gn:population":0,
    "gn:timezone":"Europe/Lisbon",
    "iso:country":"PT",
    "wof:name":"Agra",
    "wof:placetype":"locality"
},
  "geometry": {"coordinates":[-7.77217,41.08087],"type":"Point"}
}