{
  "type": "Feature",
  "properties": {
    "gn:admin1_code":"4.0",
    "gn:admin2_code":"0308",
    "gn:admin3_code":"30843.0",
    "gn:asciiname":"Eira Velha",
    "gn:country_code":"PT",
    "gn:dem":198,
    "gn:feature_class":"P",
    "gn:feature_code":"PPL",
    "gn:name":"Eira Velha",
    "gn:population":0,
    "gn:timezone":"Europe/Lisbon",
    "iso:country":"PT",
    "wof:name":"Eira Velha",
    "wof:placetype":"locality"
},
  "geometry": {"coordinates":[-8.3412,41.52101],"type":"Point"}
}