{
  "type": "Feature",
  "properties": {
    "gn:admin1_code":"20.0",
    "gn:admin2_code":"1608",
    "gn:admin3_code":"160807.0",
    "gn:asciiname":"Ozao",
    "gn:country_code":"PT",
    "gn:dem":313,
    "gn:feature_class":"P",
    "gn:feature_code":"PPL",
    "gn:name":"Oz\u00e3o",
    "gn:population":0,
    "gn:timezone":"Europe/Lisbon",
    "iso:country":"PT",
    "wof:name":"Ozao",
    "wof:placetype":"locality"
},
  "geometry": {"coordinates":[-8.59696,42.0118],"type":"Point"}
}