{
  "type": "Feature",
  "properties": {
    "gn:admin1_code":"18",
    "gn:admin2_code":"1411",
    "gn:admin3_code":"141106.0",
    "gn:asciiname":"Carvalhais",
    "gn:country_code":"PT",
    "gn:dem":259,
    "gn:feature_class":"P",
    "gn:feature_code":"PPL",
    "gn:name":"Carvalhais",
    "gn:population":0,
    "gn:timezone":"Europe/Lisbon",
    "iso:country":"PT",
    "wof:name":"Carvalhais",
    "wof:placetype":"locality"
},
  "geometry": {"coordinates":[-8.28287,39.6637],"type":"Point"}
}