{
  "type": "Feature",
  "properties": {
    "gn:admin1_code":"22.0",
    "gn:admin2_code":"1803",
    "gn:admin3_code":"180303.0",
    "gn:asciiname":"Cabril",
    "gn:country_code":"PT",
    "gn:dem":481,
    "gn:feature_class":"P",
    "gn:feature_code":"PPL",
    "gn:name":"Cabril",
    "gn:population":0,
    "gn:timezone":"Europe/Lisbon",
    "iso:country":"PT",
    "wof:name":"Cabril",
    "wof:placetype":"locality"
},
  "geometry": {"coordinates":[-8.10093,40.9515],"type":"Point"}
}