{
  "type": "Feature",
  "properties": {
    "gn:admin1_code":"7.0",
    "gn:admin2_code":"0613",
    "gn:admin3_code":"61309.0",
    "gn:asciiname":"Laborins",
    "gn:country_code":"PT",
    "gn:dem":152,
    "gn:feature_class":"P",
    "gn:feature_code":"PPL",
    "gn:name":"Laborins",
    "gn:population":0,
    "gn:timezone":"Europe/Lisbon",
    "iso:country":"PT",
    "wof:name":"Laborins",
    "wof:placetype":"locality"
},
  "geometry": {"coordinates":[-8.21162,40.29581],"type":"Point"}
}