{
  "type": "Feature",
  "properties": {
    "gn:admin1_code":"07",
    "gn:admin2_code":"0617",
    "gn:admin3_code":"61703.0",
    "gn:asciiname":"Segundeira",
    "gn:country_code":"PT",
    "gn:dem":150,
    "gn:feature_class":"P",
    "gn:feature_code":"PPL",
    "gn:name":"Segundeira",
    "gn:population":0,
    "gn:timezone":"Europe/Lisbon",
    "iso:country":"PT",
    "wof:name":"Segundeira",
    "wof:placetype":"locality"
},
  "geometry": {"coordinates":[-8.24053,40.22167],"type":"Point"}
}