{
  "type": "Feature",
  "properties": {
    "gn:country":"PT",
    "gn:fcode":"PPL",
    "gn:population":0,
    "iso:country":"PT",
    "name:ceb_x_preferred":[
        "Cria\u00e7\u00e3o Velha"
    ],
    "name:deu_x_preferred":[
        "Cria\u00e7\u00e3o Velha"
    ],
    "name:por_x_preferred":[
        "Cria\u00e7\u00e3o Velha"
    ],
    "name:rus_x_preferred":[
        "\u041a\u0440\u0438\u0430\u0441\u0430\u043d-\u0412\u0435\u043b\u044c\u044f"
    ],
    "name:spa_x_preferred":[
        "Cria\u00e7\u00e3o Velha"
    ],
    "qs_pg:aaroncc":"PT",
    "qs_pg:gn_country":"PT",
    "qs_pg:gn_fcode":"PPL",
    "qs_pg:gn_pop":0,
    "qs_pg:name":"Cria\u00e7\u00e3o Velha",
    "qs_pg:name_adm0":"Portugal",
    "qs_pg:name_adm1":"Azores",
    "qs_pg:photos":28,
    "qs_pg:photos_1k":6,
    "qs_pg:photos_9k":1,
    "qs_pg:photos_9r":2,
    "qs_pg:photos_all":28,
    "qs_pg:photos_sr":2,
    "qs_pg:pop_sr":0,
    "qs_pg:qs_pg_placetype":"locality",
    "qs_pg:qs_pg_placetype_gp":"Town",
    "qs_pg:woe_adm0":23424925,
    "woe:adm0_id":23424925,
    "woe:name_adm0":"Portugal",
    "woe:name_adm1":"Azores",
    "woe:placetype":"Town",
    "wof:name":"Cria\u00e7\u00e3o Velha",
    "wof:placetype":"locality"
},
  "geometry": {"coordinates":[-28.53333,38.51667],"type":"Point"}
}