{
  "type": "Feature",
  "properties": {
    "gn:admin1_code":"06",
    "gn:admin2_code":"0502",
    "gn:admin3_code":"50223.0",
    "gn:asciiname":"Sobrainho da Ribeira",
    "gn:country_code":"PT",
    "gn:dem":256,
    "gn:feature_class":"P",
    "gn:feature_code":"PPL",
    "gn:name":"Sobrainho da Ribeira",
    "gn:population":0,
    "gn:timezone":"Europe/Lisbon",
    "iso:country":"PT",
    "wof:name":"Sobrainho da Ribeira",
    "wof:placetype":"locality"
},
  "geometry": {"coordinates":[-7.75067,39.82879000000001],"type":"Point"}
}