{
  "type": "Feature",
  "properties": {
    "gn:admin1_code":"18",
    "gn:admin2_code":"1401",
    "gn:admin3_code":"140113.0",
    "gn:asciiname":"Quinta da Viscondessa",
    "gn:country_code":"PT",
    "gn:dem":74,
    "gn:feature_class":"P",
    "gn:feature_code":"PPL",
    "gn:name":"Quinta da Viscondessa",
    "gn:population":0,
    "gn:timezone":"Europe/Lisbon",
    "iso:country":"PT",
    "wof:name":"Quinta da Viscondessa",
    "wof:placetype":"locality"
},
  "geometry": {"coordinates":[-8.21667,39.48333],"type":"Point"}
}