{
  "type": "Feature",
  "properties": {
    "gn:admin1_code":"7.0",
    "gn:admin2_code":"0609",
    "gn:admin3_code":"60904.0",
    "gn:asciiname":"Canas",
    "gn:country_code":"PT",
    "gn:dem":218,
    "gn:feature_class":"P",
    "gn:feature_code":"PPL",
    "gn:name":"Canas",
    "gn:population":0,
    "gn:timezone":"Europe/Lisbon",
    "iso:country":"PT",
    "name:ceb_x_preferred":[
        "Canas"
    ],
    "name:deu_x_preferred":[
        "Canas"
    ],
    "name:nld_x_preferred":[
        "Canas"
    ],
    "name:por_x_preferred":[
        "Canas"
    ],
    "name:ron_x_preferred":[
        "Canas"
    ],
    "name:rus_x_preferred":[
        "\u041a\u0430\u043d\u0430\u0441"
    ],
    "name:swe_x_preferred":[
        "Canas"
    ],
    "wof:name":"Canas",
    "wof:placetype":"locality"
},
  "geometry": {"coordinates":[-8.35049,40.17694],"type":"Point"}
}