{
  "type": "Feature",
  "properties": {
    "gn:admin1_code":"23.0",
    "gn:asciiname":"Terra Cha",
    "gn:country_code":"PT",
    "gn:dem":-9999,
    "gn:feature_class":"P",
    "gn:feature_code":"PPL",
    "gn:name":"Terra Ch\u00e3",
    "gn:population":0,
    "gn:timezone":"Atlantic/Azores",
    "iso:country":"PT",
    "wof:name":"Terra Cha",
    "wof:placetype":"locality"
},
  "geometry": {"coordinates":[-25.15,37.75],"type":"Point"}
}