{
  "type": "Feature",
  "properties": {
    "gn:admin1_code":"21",
    "gn:admin2_code":"1714",
    "gn:admin3_code":"171408.0",
    "gn:asciiname":"Povoacao",
    "gn:country_code":"PT",
    "gn:dem":226,
    "gn:feature_class":"P",
    "gn:feature_code":"PPL",
    "gn:name":"Povoa\u00e7\u00e3o",
    "gn:population":0,
    "gn:timezone":"Europe/Lisbon",
    "iso:country":"PT",
    "wof:name":"Povoacao",
    "wof:placetype":"locality"
},
  "geometry": {"coordinates":[-7.75099,41.2232],"type":"Point"}
}