{
  "type": "Feature",
  "properties": {
    "gn:admin1_code":"08",
    "gn:admin2_code":"0703",
    "gn:admin3_code":"70303.0",
    "gn:asciiname":"Sao Gregorio",
    "gn:country_code":"PT",
    "gn:dem":310,
    "gn:feature_class":"P",
    "gn:feature_code":"PPL",
    "gn:name":"S\u00e3o Greg\u00f3rio",
    "gn:population":0,
    "gn:timezone":"Europe/Lisbon",
    "iso:country":"PT",
    "wof:name":"Sao Gregorio",
    "wof:placetype":"locality"
},
  "geometry": {"coordinates":[-7.50875,38.76154],"type":"Point"}
}