{
  "type": "Feature",
  "properties": {
    "gn:admin1_code":"7.0",
    "gn:admin2_code":"0602",
    "gn:admin3_code":"60205.0",
    "gn:asciiname":"Cordinha",
    "gn:country_code":"PT",
    "gn:dem":110,
    "gn:feature_class":"P",
    "gn:feature_code":"PPL",
    "gn:name":"Cordinh\u00e3",
    "gn:population":0,
    "gn:timezone":"Europe/Lisbon",
    "iso:country":"PT",
    "wof:name":"Cordinha",
    "wof:placetype":"locality"
},
  "geometry": {"coordinates":[-8.53273,40.33537000000001],"type":"Point"}
}