{
  "type": "Feature",
  "properties": {
    "gn:admin1_code":"06",
    "gn:admin2_code":"0502",
    "gn:admin3_code":"50221.0",
    "gn:asciiname":"Vale de Agua",
    "gn:country_code":"PT",
    "gn:dem":285,
    "gn:feature_class":"P",
    "gn:feature_code":"PPL",
    "gn:name":"Vale de \u00c1gua",
    "gn:population":0,
    "gn:timezone":"Europe/Lisbon",
    "iso:country":"PT",
    "wof:name":"Vale de Agua",
    "wof:placetype":"locality"
},
  "geometry": {"coordinates":[-7.71944,39.82737],"type":"Point"}
}