{
  "type": "Feature",
  "properties": {
    "gn:admin1_code":"20.0",
    "gn:admin2_code":"1601",
    "gn:admin3_code":"160145.0",
    "gn:asciiname":"Padrao",
    "gn:country_code":"PT",
    "gn:dem":508,
    "gn:feature_class":"P",
    "gn:feature_code":"PPL",
    "gn:name":"Padr\u00e3o",
    "gn:population":0,
    "gn:timezone":"Europe/Lisbon",
    "iso:country":"PT",
    "wof:name":"Padrao",
    "wof:placetype":"locality"
},
  "geometry": {"coordinates":[-8.35484,41.98042],"type":"Point"}
}