{
  "type": "Feature",
  "properties": {
    "gn:admin1_code":"23.0",
    "gn:admin2_code":"4301",
    "gn:admin3_code":"430116.0",
    "gn:asciiname":"Sao Mateus",
    "gn:country_code":"PT",
    "gn:dem":-9999,
    "gn:feature_class":"P",
    "gn:feature_code":"PPL",
    "gn:name":"S\u00e3o Mateus",
    "gn:population":3757,
    "gn:timezone":"Atlantic/Azores",
    "iso:country":"PT",
    "name:ceb_x_preferred":[
        "S\u00e3o Mateus da Calheta"
    ],
    "name:deu_x_preferred":[
        "S\u00e3o Mateus da Calheta"
    ],
    "name:por_x_preferred":[
        "S\u00e3o Mateus da Calheta"
    ],
    "name:rus_x_preferred":[
        "\u0421\u0430\u043d-\u041c\u0430\u0442\u0435\u0443\u0448-\u0434\u0430-\u041a\u0430\u043b\u044c\u0435\u0442\u0430"
    ],
    "name:spa_x_preferred":[
        "S\u00e3o Mateus da Calheta"
    ],
    "name:und_x_variant":[
        "S\u00e3o Matheus",
        "S\u00e3o Matheus da Calheta",
        "S\u00e3o Mateus"
    ],
    "wof:name":"Sao Mateus",
    "wof:placetype":"locality",
    "wof:population":3757
},
  "geometry": {"coordinates":[-27.26935,38.6563],"type":"Point"}
}