{
  "type": "Feature",
  "properties": {
    "gn:admin1_code":"18",
    "gn:admin2_code":"1416",
    "gn:admin3_code":"141622.0",
    "gn:asciiname":"Valverde",
    "gn:country_code":"PT",
    "gn:dem":39,
    "gn:feature_class":"P",
    "gn:feature_code":"PPL",
    "gn:name":"Valverde",
    "gn:population":0,
    "gn:timezone":"Europe/Lisbon",
    "iso:country":"PT",
    "wof:name":"Valverde",
    "wof:placetype":"locality"
},
  "geometry": {"coordinates":[-8.59946,39.37272],"type":"Point"}
}