{
  "type": "Feature",
  "properties": {
    "gn:country":"PT",
    "gn:fcode":"PPL",
    "gn:population":0,
    "iso:country":"PT",
    "name:bre_x_preferred":[
        "S\u00e3o Pedro"
    ],
    "name:ceb_x_preferred":[
        "S\u00e3o Pedro"
    ],
    "name:deu_x_preferred":[
        "S\u00e3o Pedro"
    ],
    "name:fra_x_preferred":[
        "S\u00e3o Pedro"
    ],
    "name:ita_x_preferred":[
        "S\u00e3o Pedro"
    ],
    "name:nld_x_preferred":[
        "S\u00e3o Pedro"
    ],
    "name:nor_x_preferred":[
        "S\u00e3o Pedro"
    ],
    "name:pol_x_preferred":[
        "S\u00e3o Pedro"
    ],
    "name:por_x_preferred":[
        "S\u00e3o Pedro"
    ],
    "name:rus_x_preferred":[
        "\u0421\u0430\u043d-\u041f\u0435\u0434\u0440\u0443"
    ],
    "name:sco_x_preferred":[
        "S\u00e3o Pedro"
    ],
    "name:spa_x_preferred":[
        "S\u00e3o Pedro"
    ],
    "name:swe_x_preferred":[
        "S\u00e3o Pedro"
    ],
    "name:tur_x_preferred":[
        "S\u00e3o Pedro"
    ],
    "name:ukr_x_preferred":[
        "\u0421\u0430\u043d-\u041f\u0435\u0434\u0440\u0443"
    ],
    "name:vie_x_preferred":[
        "S\u00e3o Pedro"
    ],
    "name:vol_x_preferred":[
        "S\u00e3o Pedro"
    ],
    "qs_pg:aaroncc":"PT",
    "qs_pg:gn_country":"PT",
    "qs_pg:gn_fcode":"PPL",
    "qs_pg:gn_pop":0,
    "qs_pg:name":"S\u00e3o Pedro",
    "qs_pg:name_adm0":"Portugal",
    "qs_pg:name_adm1":"Viana do Castelo",
    "qs_pg:photos":9,
    "qs_pg:photos_1k":2,
    "qs_pg:photos_9k":1,
    "qs_pg:photos_9r":1,
    "qs_pg:photos_all":9,
    "qs_pg:photos_sr":1,
    "qs_pg:pop_sr":0,
    "qs_pg:qs_pg_placetype":"locality",
    "qs_pg:qs_pg_placetype_gp":"Town",
    "qs_pg:woe_adm0":23424925,
    "woe:adm0_id":23424925,
    "woe:name_adm0":"Portugal",
    "woe:name_adm1":"Viana do Castelo",
    "woe:placetype":"Town",
    "wof:name":"S\u00e3o Pedro",
    "wof:placetype":"locality"
},
  "geometry": {"coordinates":[-8.50957,41.75498],"type":"Point"}
}