{
  "type": "Feature",
  "properties": {
    "gn:admin1_code":"16",
    "gn:admin2_code":"1202",
    "gn:admin3_code":"120202.0",
    "gn:asciiname":"Outeiro das Pratas",
    "gn:country_code":"PT",
    "gn:dem":366,
    "gn:feature_class":"P",
    "gn:feature_code":"PPL",
    "gn:name":"Outeiro das Pratas",
    "gn:population":0,
    "gn:timezone":"Europe/Lisbon",
    "iso:country":"PT",
    "wof:name":"Outeiro das Pratas",
    "wof:placetype":"locality"
},
  "geometry": {"coordinates":[-7.19693,39.16356],"type":"Point"}
}