{
  "type": "Feature",
  "properties": {
    "gn:admin1_code":"06",
    "gn:admin2_code":"0506",
    "gn:admin3_code":"50604.0",
    "gn:asciiname":"Estorneiros",
    "gn:country_code":"PT",
    "gn:dem":726,
    "gn:feature_class":"P",
    "gn:feature_code":"PPL",
    "gn:name":"Estorneiros",
    "gn:population":0,
    "gn:timezone":"Europe/Lisbon",
    "iso:country":"PT",
    "wof:name":"Estorneiros",
    "wof:placetype":"locality"
},
  "geometry": {"coordinates":[-7.80307,39.93923],"type":"Point"}
}