{
  "type": "Feature",
  "properties": {
    "gn:country":"PT",
    "gn:fcode":"PPL",
    "gn:population":0,
    "iso:country":"PT",
    "name:ceb_x_preferred":[
        "Penhas da Sa\u00fade"
    ],
    "name:eng_x_preferred":[
        "Penhas da Sa\u00fade"
    ],
    "name:fra_x_preferred":[
        "Penhas da Sa\u00fade"
    ],
    "name:nld_x_preferred":[
        "Penhas da Sa\u00fade"
    ],
    "name:por_x_preferred":[
        "Penhas da Sa\u00fade"
    ],
    "name:spa_x_preferred":[
        "Penhas da Sa\u00fade"
    ],
    "name:zho_x_preferred":[
        "\u4f69\u5c3c\u4e9e\u4ec0\u9054\u7d39\u8fea"
    ],
    "qs_pg:aaroncc":"PT",
    "qs_pg:gn_country":"PT",
    "qs_pg:gn_fcode":"PPL",
    "qs_pg:gn_pop":0,
    "qs_pg:name":"Penhas da Sa\u00fade",
    "qs_pg:name_adm0":"Portugal",
    "qs_pg:name_adm1":"Castelo Branco",
    "qs_pg:photos":930,
    "qs_pg:photos_1k":188,
    "qs_pg:photos_9k":4,
    "qs_pg:photos_9r":6,
    "qs_pg:photos_all":930,
    "qs_pg:photos_sr":10,
    "qs_pg:pop_sr":0,
    "qs_pg:qs_pg_placetype":"locality",
    "qs_pg:qs_pg_placetype_gp":"Town",
    "qs_pg:woe_adm0":23424925,
    "woe:adm0_id":23424925,
    "woe:name_adm0":"Portugal",
    "woe:name_adm1":"Castelo Branco",
    "woe:placetype":"Town",
    "wof:name":"Penhas da Sa\u00fade",
    "wof:placetype":"locality"
},
  "geometry": {"coordinates":[-7.54787,40.30865],"type":"Point"}
}