{
  "type": "Feature",
  "properties": {
    "gn:admin1_code":"13",
    "gn:admin2_code":"1016",
    "gn:admin3_code":"101612.0",
    "gn:asciiname":"Castanheiro",
    "gn:country_code":"PT",
    "gn:dem":175,
    "gn:feature_class":"P",
    "gn:feature_code":"PPL",
    "gn:name":"Castanheiro",
    "gn:population":0,
    "gn:timezone":"Europe/Lisbon",
    "iso:country":"PT",
    "name:por_x_preferred":[
        "Castanheiro"
    ],
    "wof:name":"Castanheiro",
    "wof:placetype":"locality"
},
  "geometry": {"coordinates":[-8.83066,39.62815],"type":"Point"}
}