{
  "type": "Feature",
  "properties": {
    "gn:admin1_code":"22",
    "gn:admin2_code":"1821",
    "gn:admin3_code":"182101.0",
    "gn:asciiname":"Vale",
    "gn:country_code":"PT",
    "gn:dem":238,
    "gn:feature_class":"P",
    "gn:feature_code":"PPL",
    "gn:name":"Vale",
    "gn:population":0,
    "gn:timezone":"Europe/Lisbon",
    "iso:country":"PT",
    "wof:name":"Vale",
    "wof:placetype":"locality"
},
  "geometry": {"coordinates":[-8.17339,40.48201],"type":"Point"}
}