{
  "type": "Feature",
  "properties": {
    "gn:admin1_code":"7.0",
    "gn:admin2_code":"0607",
    "gn:admin3_code":"60702.0",
    "gn:asciiname":"Marmeleira",
    "gn:country_code":"PT",
    "gn:dem":121,
    "gn:feature_class":"P",
    "gn:feature_code":"PPL",
    "gn:name":"Marmeleira",
    "gn:population":0,
    "gn:timezone":"Europe/Lisbon",
    "iso:country":"PT",
    "wof:name":"Marmeleira",
    "wof:placetype":"locality"
},
  "geometry": {"coordinates":[-8.26513,40.17662],"type":"Point"}
}