{
  "type": "Feature",
  "properties": {
    "gn:admin1_code":"23.0",
    "gn:admin2_code":"4206",
    "gn:admin3_code":"420601.0",
    "gn:asciiname":"Trinta Reis",
    "gn:country_code":"PT",
    "gn:dem":53,
    "gn:feature_class":"P",
    "gn:feature_code":"PPL",
    "gn:name":"Trinta Reis",
    "gn:population":0,
    "gn:timezone":"Atlantic/Azores",
    "iso:country":"PT",
    "wof:name":"Trinta Reis",
    "wof:placetype":"locality"
},
  "geometry": {"coordinates":[-25.46667,37.71667],"type":"Point"}
}