{
  "type": "Feature",
  "properties": {
    "gn:admin1_code":"20",
    "gn:admin2_code":"1603",
    "gn:admin3_code":"160302.0",
    "gn:asciiname":"Ribeiro de Baixo",
    "gn:country_code":"PT",
    "gn:dem":626,
    "gn:feature_class":"P",
    "gn:feature_code":"PPL",
    "gn:name":"Ribeiro de Baixo",
    "gn:population":0,
    "gn:timezone":"Europe/Lisbon",
    "iso:country":"PT",
    "wof:name":"Ribeiro de Baixo",
    "wof:placetype":"locality"
},
  "geometry": {"coordinates":[-8.18632,41.95199],"type":"Point"}
}