{
  "type": "Feature",
  "properties": {
    "gn:admin1_code":"22.0",
    "gn:admin2_code":"1806",
    "gn:admin3_code":"180616.0",
    "gn:asciiname":"Pinheiro",
    "gn:country_code":"PT",
    "gn:dem":611,
    "gn:feature_class":"P",
    "gn:feature_code":"PPL",
    "gn:name":"Pinheiro",
    "gn:population":0,
    "gn:timezone":"Europe/Lisbon",
    "iso:country":"PT",
    "wof:name":"Pinheiro",
    "wof:placetype":"locality"
},
  "geometry": {"coordinates":[-7.56785,40.63206],"type":"Point"}
}