{
  "type": "Feature",
  "properties": {
    "gn:admin1_code":"7.0",
    "gn:admin2_code":"0603",
    "gn:admin3_code":"60311.0",
    "gn:asciiname":"Lagoas",
    "gn:country_code":"PT",
    "gn:dem":192,
    "gn:feature_class":"P",
    "gn:feature_code":"PPL",
    "gn:name":"Lagoas",
    "gn:population":0,
    "gn:timezone":"Europe/Lisbon",
    "iso:country":"PT",
    "wof:name":"Lagoas",
    "wof:placetype":"locality"
},
  "geometry": {"coordinates":[-8.37687,40.18041],"type":"Point"}
}