{
  "type": "Feature",
  "properties": {
    "gn:admin1_code":"09",
    "gn:admin2_code":"0802",
    "gn:admin3_code":"80201.0",
    "gn:asciiname":"Montinho das Laranjeiras",
    "gn:country_code":"PT",
    "gn:dem":8,
    "gn:feature_class":"P",
    "gn:feature_code":"PPL",
    "gn:name":"Montinho das Laranjeiras",
    "gn:population":0,
    "gn:timezone":"Europe/Lisbon",
    "iso:country":"PT",
    "wof:name":"Montinho das Laranjeiras",
    "wof:placetype":"locality"
},
  "geometry": {"coordinates":[-7.46314,37.40801],"type":"Point"}
}