{
  "type": "Feature",
  "properties": {
    "gn:admin1_code":"06",
    "gn:admin2_code":"0509",
    "gn:admin3_code":"50904.0",
    "gn:asciiname":"Moinhos da Ribeira",
    "gn:country_code":"PT",
    "gn:dem":193,
    "gn:feature_class":"P",
    "gn:feature_code":"PPL",
    "gn:name":"Moinhos da Ribeira",
    "gn:population":0,
    "gn:timezone":"Europe/Lisbon",
    "iso:country":"PT",
    "wof:name":"Moinhos da Ribeira",
    "wof:placetype":"locality"
},
  "geometry": {"coordinates":[-8.20706,39.77514],"type":"Point"}
}