{
  "type": "Feature",
  "properties": {
    "gn:admin1_code":"22",
    "gn:admin2_code":"1821",
    "gn:admin3_code":"182118.0",
    "gn:asciiname":"Sao Tiago de Besteiros",
    "gn:country_code":"PT",
    "gn:dem":361,
    "gn:feature_class":"P",
    "gn:feature_code":"PPL",
    "gn:name":"S\u00e3o Tiago de Besteiros",
    "gn:population":0,
    "gn:timezone":"Europe/Lisbon",
    "iso:country":"PT",
    "wof:name":"Sao Tiago de Besteiros",
    "wof:placetype":"locality"
},
  "geometry": {"coordinates":[-8.12921,40.58241],"type":"Point"}
}