{
  "type": "Feature",
  "properties": {
    "gn:admin1_code":"11.0",
    "gn:admin2_code":"0907",
    "gn:admin3_code":"90723.0",
    "gn:asciiname":"Pero Soares",
    "gn:country_code":"PT",
    "gn:dem":806,
    "gn:feature_class":"P",
    "gn:feature_code":"PPL",
    "gn:name":"Pero Soares",
    "gn:population":0,
    "gn:timezone":"Europe/Lisbon",
    "iso:country":"PT",
    "wof:name":"Pero Soares",
    "wof:placetype":"locality"
},
  "geometry": {"coordinates":[-7.32064,40.54335],"type":"Point"}
}