{
  "type": "Feature",
  "properties": {
    "gn:country":"PT",
    "gn:fcode":"PPL",
    "gn:population":0,
    "iso:country":"PT",
    "name:bul_x_preferred":[
        "\u041c\u0435\u0439\u0440\u0435\u043b\u0438\u0441"
    ],
    "name:deu_x_preferred":[
        "Meireles"
    ],
    "name:fra_x_preferred":[
        "Meireles"
    ],
    "name:jpn_x_preferred":[
        "\u30e1\u30a4\u30ec\u30ec\u30b9"
    ],
    "qs_pg:aaroncc":"PT",
    "qs_pg:gn_country":"PT",
    "qs_pg:gn_fcode":"PPL",
    "qs_pg:gn_pop":0,
    "qs_pg:name":"Meireles",
    "qs_pg:name_adm0":"Portugal",
    "qs_pg:name_adm1":"Bragan\u00e7a",
    "qs_pg:photos_9r":0,
    "qs_pg:photos_sr":0,
    "qs_pg:pop_sr":0,
    "qs_pg:qs_pg_placetype":"locality",
    "qs_pg:qs_pg_placetype_gp":"Town",
    "qs_pg:woe_adm0":23424925,
    "woe:adm0_id":23424925,
    "woe:name_adm0":"Portugal",
    "woe:name_adm1":"Bragan\u00e7a",
    "woe:placetype":"Town",
    "wof:name":"Meireles",
    "wof:placetype":"locality"
},
  "geometry": {"coordinates":[-7.17112,41.35889],"type":"Point"}
}