{
  "type": "Feature",
  "properties": {
    "gn:admin1_code":"08",
    "gn:admin2_code":"0705",
    "gn:admin3_code":"70506.0",
    "gn:asciiname":"Borrazeiro de Sao Bento",
    "gn:country_code":"PT",
    "gn:dem":279,
    "gn:feature_class":"P",
    "gn:feature_code":"PPL",
    "gn:name":"Borrazeiro de S\u00e3o Bento",
    "gn:population":0,
    "gn:timezone":"Europe/Lisbon",
    "iso:country":"PT",
    "wof:name":"Borrazeiro de Sao Bento",
    "wof:placetype":"locality"
},
  "geometry": {"coordinates":[-7.8422,38.69691],"type":"Point"}
}