{
  "type": "Feature",
  "properties": {
    "gn:admin1_code":"7.0",
    "gn:admin2_code":"0609",
    "gn:admin3_code":"60902.0",
    "gn:asciiname":"Meas",
    "gn:country_code":"PT",
    "gn:dem":137,
    "gn:feature_class":"P",
    "gn:feature_code":"PPL",
    "gn:name":"Me\u00e3s",
    "gn:population":0,
    "gn:timezone":"Europe/Lisbon",
    "iso:country":"PT",
    "wof:name":"Meas",
    "wof:placetype":"locality"
},
  "geometry": {"coordinates":[-8.31636,40.08385],"type":"Point"}
}