{
  "type": "Feature",
  "properties": {
    "gn:admin1_code":"20",
    "gn:admin2_code":"1608",
    "gn:admin3_code":"160810.0",
    "gn:asciiname":"Quebrada",
    "gn:country_code":"PT",
    "gn:dem":322,
    "gn:feature_class":"P",
    "gn:feature_code":"PPL",
    "gn:name":"Quebrada",
    "gn:population":0,
    "gn:timezone":"Europe/Lisbon",
    "iso:country":"PT",
    "name:ceb_x_preferred":[
        "Quebrada"
    ],
    "name:deu_x_preferred":[
        "Quebrada"
    ],
    "name:fra_x_preferred":[
        "Quebrada"
    ],
    "name:nld_x_preferred":[
        "Quebrada"
    ],
    "name:spa_x_preferred":[
        "Quebrada"
    ],
    "name:swe_x_preferred":[
        "Quebrada"
    ],
    "wof:name":"Quebrada",
    "wof:placetype":"locality"
},
  "geometry": {"coordinates":[-8.57877,42.01012],"type":"Point"}
}