{
  "type": "Feature",
  "properties": {
    "gn:admin1_code":"20.0",
    "gn:asciiname":"Podame",
    "gn:country_code":"PT",
    "gn:dem":111,
    "gn:feature_class":"P",
    "gn:feature_code":"PPL",
    "gn:name":"Podame",
    "gn:population":0,
    "gn:timezone":"Europe/Lisbon",
    "iso:country":"PT",
    "wof:name":"Podame",
    "wof:placetype":"locality"
},
  "geometry": {"coordinates":[-8.36667,41.03333],"type":"Point"}
}