{
  "type": "Feature",
  "properties": {
    "gn:admin1_code":"05",
    "gn:admin2_code":"0407",
    "gn:admin3_code":"40736.0",
    "gn:asciiname":"Vila Boa",
    "gn:country_code":"PT",
    "gn:dem":359,
    "gn:feature_class":"P",
    "gn:feature_code":"PPL",
    "gn:name":"Vila Boa",
    "gn:population":0,
    "gn:timezone":"Europe/Lisbon",
    "iso:country":"PT",
    "wof:name":"Vila Boa",
    "wof:placetype":"locality"
},
  "geometry": {"coordinates":[-7.34384,41.39482],"type":"Point"}
}