{
  "type": "Feature",
  "properties": {
    "gn:admin1_code":"4.0",
    "gn:admin2_code":"0303",
    "gn:admin3_code":"30315.0",
    "gn:asciiname":"Figueiredo",
    "gn:country_code":"PT",
    "gn:dem":183,
    "gn:feature_class":"P",
    "gn:feature_code":"PPL",
    "gn:name":"Figueiredo",
    "gn:population":0,
    "gn:timezone":"Europe/Lisbon",
    "iso:country":"PT",
    "name:ceb_x_preferred":[
        "Figueiredo"
    ],
    "name:deu_x_preferred":[
        "Figueiredo"
    ],
    "name:fra_x_preferred":[
        "Figueiredo"
    ],
    "name:glg_x_preferred":[
        "Figueiredo"
    ],
    "name:ita_x_preferred":[
        "Figueiredo"
    ],
    "name:nld_x_preferred":[
        "Figueiredo"
    ],
    "name:por_x_preferred":[
        "Figueiredo"
    ],
    "name:rus_x_preferred":[
        "\u0424\u0438\u0433\u0435\u0439\u0440\u0435\u0434\u0443"
    ],
    "wof:name":"Figueiredo",
    "wof:placetype":"locality"
},
  "geometry": {"coordinates":[-8.44171,41.49962],"type":"Point"}
}