{
  "type": "Feature",
  "properties": {
    "gn:admin1_code":"19",
    "gn:admin2_code":"1501",
    "gn:admin3_code":"150104.0",
    "gn:asciiname":"Parchanas",
    "gn:country_code":"PT",
    "gn:dem":21,
    "gn:feature_class":"P",
    "gn:feature_code":"PPL",
    "gn:name":"Parchanas",
    "gn:population":0,
    "gn:timezone":"Europe/Lisbon",
    "iso:country":"PT",
    "wof:name":"Parchanas",
    "wof:placetype":"locality"
},
  "geometry": {"coordinates":[-8.39954,38.27946],"type":"Point"}
}