{
  "type": "Feature",
  "properties": {
    "gn:admin1_code":"03",
    "gn:admin2_code":"0212",
    "gn:admin3_code":"21205.0",
    "gn:asciiname":"Telheiro",
    "gn:country_code":"PT",
    "gn:dem":200,
    "gn:feature_class":"P",
    "gn:feature_code":"PPL",
    "gn:name":"Telheiro",
    "gn:population":0,
    "gn:timezone":"Europe/Lisbon",
    "iso:country":"PT",
    "wof:name":"Telheiro",
    "wof:placetype":"locality"
},
  "geometry": {"coordinates":[-8.4443,37.70849000000001],"type":"Point"}
}