{
  "type": "Feature",
  "properties": {
    "gn:admin1_code":"4.0",
    "gn:admin2_code":"0313",
    "gn:admin3_code":"31325.0",
    "gn:asciiname":"Loureira",
    "gn:country_code":"PT",
    "gn:dem":59,
    "gn:feature_class":"P",
    "gn:feature_code":"PPL",
    "gn:name":"Loureira",
    "gn:population":0,
    "gn:timezone":"Europe/Lisbon",
    "iso:country":"PT",
    "name:chv_x_preferred":[
        "\u041b\u043e\u0443\u0440\u0435\u0439\u0440\u0443"
    ],
    "name:deu_x_preferred":[
        "Loureiro"
    ],
    "name:glg_x_preferred":[
        "Loureira branca"
    ],
    "name:pol_x_preferred":[
        "Loureiro"
    ],
    "name:por_x_preferred":[
        "Loureiro"
    ],
    "name:spa_x_preferred":[
        "Loureira"
    ],
    "wof:name":"Loureira",
    "wof:placetype":"locality"
},
  "geometry": {"coordinates":[-8.42543,41.63345],"type":"Point"}
}