{
  "type": "Feature",
  "properties": {
    "gn:admin1_code":"23.0",
    "gn:admin2_code":"4301",
    "gn:admin3_code":"430112.0",
    "gn:asciiname":"Ribeirinha",
    "gn:country_code":"PT",
    "gn:dem":213,
    "gn:feature_class":"P",
    "gn:feature_code":"PPL",
    "gn:name":"Ribeirinha",
    "gn:population":2684,
    "gn:timezone":"Atlantic/Azores",
    "iso:country":"PT",
    "name:ceb_x_preferred":[
        "Ribeirinha"
    ],
    "name:deu_x_preferred":[
        "Ribeirinha"
    ],
    "name:fra_x_preferred":[
        "Ribeirinha"
    ],
    "name:nld_x_preferred":[
        "Ribeirinha"
    ],
    "name:por_x_preferred":[
        "Ribeirinha"
    ],
    "name:rus_x_preferred":[
        "\u0420\u0438\u0431\u0435\u0439\u0440\u0438\u043d\u044c\u044f"
    ],
    "wof:name":"Ribeirinha",
    "wof:placetype":"locality",
    "wof:population":2684
},
  "geometry": {"coordinates":[-27.18093,38.66203],"type":"Point"}
}