{
  "type": "Feature",
  "properties": {
    "gn:admin1_code":"23.0",
    "gn:admin2_code":"4301",
    "gn:admin3_code":"430112.0",
    "gn:asciiname":"Ribeirinha",
    "gn:country_code":"PT",
    "gn:dem":213,
    "gn:feature_class":"P",
    "gn:feature_code":"PPL",
    "gn:name":"Ribeirinha",
    "gn:population":2684,
    "gn:timezone":"Atlantic/Azores",
    "iso:country":"PT",
    "wof:name":"Ribeirinha",
    "wof:placetype":"locality",
    "wof:population":2684
},
  "geometry": {"coordinates":[-27.18093,38.66203],"type":"Point"}
}