{
  "type": "Feature",
  "properties": {
    "gn:admin1_code":"21",
    "gn:admin2_code":"1706",
    "gn:admin3_code":"170605.0",
    "gn:asciiname":"Vilaca",
    "gn:country_code":"PT",
    "gn:dem":950,
    "gn:feature_class":"P",
    "gn:feature_code":"PPL",
    "gn:name":"Vila\u00e7a",
    "gn:population":0,
    "gn:timezone":"Europe/Lisbon",
    "iso:country":"PT",
    "wof:name":"Vilaca",
    "wof:placetype":"locality"
},
  "geometry": {"coordinates":[-7.90319,41.78784],"type":"Point"}
}