{
  "type": "Feature",
  "properties": {
    "gn:admin1_code":"17.0",
    "gn:admin2_code":"1308",
    "gn:admin3_code":"130803.0",
    "gn:asciiname":"Avilhoso",
    "gn:country_code":"PT",
    "gn:dem":38,
    "gn:feature_class":"P",
    "gn:feature_code":"PPL",
    "gn:name":"Avilhoso",
    "gn:population":0,
    "gn:timezone":"Europe/Lisbon",
    "iso:country":"PT",
    "wof:name":"Avilhoso",
    "wof:placetype":"locality"
},
  "geometry": {"coordinates":[-8.7023,41.24896],"type":"Point"}
}