{
  "type": "Feature",
  "properties": {
    "gn:admin1_code":"14",
    "gn:admin2_code":"1101",
    "gn:admin3_code":"110108.0",
    "gn:asciiname":"Casais das Sarraipas",
    "gn:country_code":"PT",
    "gn:dem":128,
    "gn:feature_class":"P",
    "gn:feature_code":"PPL",
    "gn:name":"Casais das Sarraipas",
    "gn:population":0,
    "gn:timezone":"Europe/Lisbon",
    "iso:country":"PT",
    "wof:name":"Casais das Sarraipas",
    "wof:placetype":"locality"
},
  "geometry": {"coordinates":[-9.05641,39.11254],"type":"Point"}
}