{
  "type": "Feature",
  "properties": {
    "gn:admin1_code":"2.0",
    "gn:admin2_code":"0104",
    "gn:admin3_code":"10410.0",
    "gn:asciiname":"Cirquidolo",
    "gn:country_code":"PT",
    "gn:dem":510,
    "gn:feature_class":"P",
    "gn:feature_code":"PPL",
    "gn:name":"Cirquidolo",
    "gn:population":0,
    "gn:timezone":"Europe/Lisbon",
    "iso:country":"PT",
    "wof:name":"Cirquidolo",
    "wof:placetype":"locality"
},
  "geometry": {"coordinates":[-8.23617,40.97272],"type":"Point"}
}