{
  "type": "Feature",
  "properties": {
    "gn:admin1_code":"22",
    "gn:admin2_code":"1823",
    "gn:admin3_code":"182329.0",
    "gn:asciiname":"Sao Cristovao",
    "gn:country_code":"PT",
    "gn:dem":443,
    "gn:feature_class":"P",
    "gn:feature_code":"PPL",
    "gn:name":"S\u00e3o Crist\u00f3v\u00e3o",
    "gn:population":0,
    "gn:timezone":"Europe/Lisbon",
    "iso:country":"PT",
    "wof:name":"Sao Cristovao",
    "wof:placetype":"locality"
},
  "geometry": {"coordinates":[-7.7871,40.69144],"type":"Point"}
}