{
  "type": "Feature",
  "properties": {
    "gn:admin1_code":"22.0",
    "gn:admin2_code":"1814",
    "gn:admin3_code":"181402.0",
    "gn:asciiname":"Ovoa",
    "gn:country_code":"PT",
    "gn:dem":210,
    "gn:feature_class":"P",
    "gn:feature_code":"PPL",
    "gn:name":"\u00d3voa",
    "gn:population":0,
    "gn:timezone":"Europe/Lisbon",
    "iso:country":"PT",
    "wof:name":"Ovoa",
    "wof:placetype":"locality"
},
  "geometry": {"coordinates":[-8.13057,40.38008],"type":"Point"}
}