{
  "type": "Feature",
  "properties": {
    "gn:admin1_code":"09",
    "gn:admin2_code":"0808",
    "gn:admin3_code":"80801.0",
    "gn:asciiname":"Barros de Sao Joao",
    "gn:country_code":"PT",
    "gn:dem":37,
    "gn:feature_class":"P",
    "gn:feature_code":"PPL",
    "gn:name":"Barros de S\u00e3o Jo\u00e3o",
    "gn:population":0,
    "gn:timezone":"Europe/Lisbon",
    "iso:country":"PT",
    "wof:name":"Barros de Sao Joao",
    "wof:placetype":"locality"
},
  "geometry": {"coordinates":[-7.98333,37.06667],"type":"Point"}
}