{
  "type": "Feature",
  "properties": {
    "gn:admin1_code":"21.0",
    "gn:admin2_code":"1709",
    "gn:admin3_code":"170903.0",
    "gn:asciiname":"Cabriz",
    "gn:country_code":"PT",
    "gn:dem":433,
    "gn:feature_class":"P",
    "gn:feature_code":"PPL",
    "gn:name":"Cabriz",
    "gn:population":0,
    "gn:timezone":"Europe/Lisbon",
    "iso:country":"PT",
    "wof:name":"Cabriz",
    "wof:placetype":"locality"
},
  "geometry": {"coordinates":[-7.80908,41.46619000000001],"type":"Point"}
}