{
  "type": "Feature",
  "properties": {
    "gn:admin1_code":"23.0",
    "gn:admin2_code":"4204",
    "gn:admin3_code":"420403.0",
    "gn:asciiname":"Lagoa das Furnas",
    "gn:country_code":"PT",
    "gn:dem":299,
    "gn:feature_class":"P",
    "gn:feature_code":"PPL",
    "gn:name":"Lagoa das Furnas",
    "gn:population":0,
    "gn:timezone":"Atlantic/Azores",
    "iso:country":"PT",
    "wof:name":"Lagoa das Furnas",
    "wof:placetype":"locality"
},
  "geometry": {"coordinates":[-25.33333,37.75],"type":"Point"}
}