{
  "type": "Feature",
  "properties": {
    "gn:admin1_code":"07",
    "gn:admin2_code":"0614",
    "gn:admin3_code":"61403.0",
    "gn:asciiname":"Retorta",
    "gn:country_code":"PT",
    "gn:dem":145,
    "gn:feature_class":"P",
    "gn:feature_code":"PPL",
    "gn:name":"Retorta",
    "gn:population":0,
    "gn:timezone":"Europe/Lisbon",
    "iso:country":"PT",
    "wof:name":"Retorta",
    "wof:placetype":"locality"
},
  "geometry": {"coordinates":[-8.36378,40.05738],"type":"Point"}
}