{
  "type": "Feature",
  "properties": {
    "gn:gn_country":"PT",
    "gn:gn_fcode":"PPL",
    "gn:gn_pop":0,
    "iso:country":"PT",
    "name:deu_x_preferred":[
        "Cabanas de Torres"
    ],
    "name:eng_x_preferred":[
        "Cabanas de Torres"
    ],
    "name:fra_x_preferred":[
        "Cabanas de Torres"
    ],
    "name:kaz_x_preferred":[
        "\u041a\u0430\u0431\u0430\u043d\u0430\u0448-\u0434\u0438-\u0422\u043e\u0440\u0440\u0438\u0448"
    ],
    "name:nld_x_preferred":[
        "Cabanas de Torres"
    ],
    "name:pol_x_preferred":[
        "Cabanas de Torres"
    ],
    "name:por_x_preferred":[
        "Cabanas de Torres"
    ],
    "name:rus_x_preferred":[
        "\u041a\u0430\u0431\u0430\u043d\u0430\u0448-\u0434\u0438-\u0422\u043e\u0440\u0440\u0438\u0448"
    ],
    "name:spa_x_preferred":[
        "Cabanas de Torres"
    ],
    "qs_pg:aaroncc":"PT",
    "qs_pg:gn_country":"PT",
    "qs_pg:gn_fcode":"PPL",
    "qs_pg:gn_pop":0,
    "qs_pg:name":"Cabanas de Torres",
    "qs_pg:name_adm0":"Portugal",
    "qs_pg:name_adm1":"Lisboa",
    "qs_pg:photos":16,
    "qs_pg:photos_1k":3,
    "qs_pg:photos_9k":1,
    "qs_pg:photos_9r":1,
    "qs_pg:photos_all":16,
    "qs_pg:photos_sr":1,
    "qs_pg:pop_sr":0,
    "qs_pg:qs_pg_placetype":"locality",
    "qs_pg:qs_pg_placetype_gp":"Town",
    "qs_pg:woe_adm0":23424925,
    "woe:adm0_id":23424925,
    "woe:name_adm0":"Portugal",
    "woe:name_adm1":"Lisboa",
    "woe:placetype":"Town",
    "wof:name":"Cabanas de Torres",
    "wof:placetype":"locality"
},
  "geometry": {"coordinates":[-9.06588,39.15581],"type":"Point"}
}