{
  "type": "Feature",
  "properties": {
    "gn:admin1_code":"06",
    "gn:admin2_code":"0505",
    "gn:admin3_code":"50517.0",
    "gn:asciiname":"Monte Novo do Calacu",
    "gn:country_code":"PT",
    "gn:dem":277,
    "gn:feature_class":"P",
    "gn:feature_code":"PPL",
    "gn:name":"Monte Novo do Calacu",
    "gn:population":0,
    "gn:timezone":"Europe/Lisbon",
    "iso:country":"PT",
    "wof:name":"Monte Novo do Calacu",
    "wof:placetype":"locality"
},
  "geometry": {"coordinates":[-7.06032,39.8142],"type":"Point"}
}