{
  "type": "Feature",
  "properties": {
    "gn:admin1_code":"13",
    "gn:admin2_code":"1015",
    "gn:admin3_code":"101508.0",
    "gn:asciiname":"Meires",
    "gn:country_code":"PT",
    "gn:dem":53,
    "gn:feature_class":"P",
    "gn:feature_code":"PPL",
    "gn:name":"Meires",
    "gn:population":0,
    "gn:timezone":"Europe/Lisbon",
    "iso:country":"PT",
    "wof:name":"Meires",
    "wof:placetype":"locality"
},
  "geometry": {"coordinates":[-8.62832,39.98637],"type":"Point"}
}