{
  "type": "Feature",
  "properties": {
    "gn:admin1_code":"14",
    "gn:admin2_code":"1101",
    "gn:admin3_code":"110113.0",
    "gn:asciiname":"Penafirme",
    "gn:country_code":"PT",
    "gn:dem":183,
    "gn:feature_class":"P",
    "gn:feature_code":"PPL",
    "gn:name":"Penafirme",
    "gn:population":0,
    "gn:timezone":"Europe/Lisbon",
    "iso:country":"PT",
    "wof:name":"Penafirme",
    "wof:placetype":"locality"
},
  "geometry": {"coordinates":[-9.09145,39.13407],"type":"Point"}
}