{
  "type": "Feature",
  "properties": {
    "gn:admin1_code":"14",
    "gn:admin2_code":"1113",
    "gn:admin3_code":"111309.0",
    "gn:asciiname":"Lapas",
    "gn:country_code":"PT",
    "gn:dem":106,
    "gn:feature_class":"P",
    "gn:feature_code":"PPL",
    "gn:name":"Lapas",
    "gn:population":0,
    "gn:timezone":"Europe/Lisbon",
    "iso:country":"PT",
    "wof:name":"Lapas",
    "wof:placetype":"locality"
},
  "geometry": {"coordinates":[-9.20451,39.11078],"type":"Point"}
}