{
  "type": "Feature",
  "properties": {
    "gn:gn_country":"PT",
    "gn:gn_fcode":"PPL",
    "gn:gn_pop":0,
    "iso:country":"PT",
    "name:arg_x_preferred":[
        "Sobrado"
    ],
    "name:bre_x_preferred":[
        "Sobrado"
    ],
    "name:cat_x_preferred":[
        "Sobrado"
    ],
    "name:ceb_x_preferred":[
        "Sobrado"
    ],
    "name:deu_x_preferred":[
        "Sobrado"
    ],
    "name:eus_x_preferred":[
        "Sobrado"
    ],
    "name:fra_x_preferred":[
        "Sobrado"
    ],
    "name:glg_x_preferred":[
        "Sobrado"
    ],
    "name:hun_x_preferred":[
        "Sobrado"
    ],
    "name:ita_x_preferred":[
        "Sobrado"
    ],
    "name:jpn_x_preferred":[
        "\u30bd\u30d6\u30e9\u30fc\u30c9"
    ],
    "name:msa_x_preferred":[
        "Sobrado"
    ],
    "name:nld_x_preferred":[
        "Sobrado"
    ],
    "name:oci_x_preferred":[
        "Sobrado"
    ],
    "name:pol_x_preferred":[
        "Sobrado"
    ],
    "name:por_x_preferred":[
        "Sobrado"
    ],
    "name:rus_x_preferred":[
        "\u0421\u043e\u0431\u0440\u0430\u0434\u0443"
    ],
    "name:spa_x_preferred":[
        "Sobrado"
    ],
    "name:swe_x_preferred":[
        "Sobrado"
    ],
    "name:ukr_x_preferred":[
        "\u0421\u043e\u0431\u0440\u0430\u0434\u0443"
    ],
    "name:unk_x_variant":[
        "Castelo de Paiva"
    ],
    "name:vie_x_preferred":[
        "Sobrado"
    ],
    "name:war_x_preferred":[
        "Sobrado"
    ],
    "qs_pg:aaroncc":"PT",
    "qs_pg:gn_country":"PT",
    "qs_pg:gn_fcode":"PPL",
    "qs_pg:gn_pop":0,
    "qs_pg:name":"Sobrado",
    "qs_pg:name_adm0":"Portugal",
    "qs_pg:name_adm1":"Aveiro",
    "qs_pg:photos":19,
    "qs_pg:photos_1k":4,
    "qs_pg:photos_9k":1,
    "qs_pg:photos_9r":1,
    "qs_pg:photos_all":19,
    "qs_pg:photos_sr":1,
    "qs_pg:pop_sr":0,
    "qs_pg:qs_pg_placetype":"locality",
    "qs_pg:qs_pg_placetype_gp":"Town",
    "qs_pg:woe_adm0":23424925,
    "woe:adm0_id":23424925,
    "woe:name_adm0":"Portugal",
    "woe:name_adm1":"Aveiro",
    "woe:placetype":"Town",
    "wof:name":"Sobrado",
    "wof:placetype":"locality"
},
  "geometry": {"coordinates":[-8.26822,41.04342],"type":"Point"}
}