{
  "type": "Feature",
  "properties": {
    "gn:admin1_code":"08",
    "gn:admin2_code":"0705",
    "gn:admin3_code":"70509.0",
    "gn:asciiname":"Monte do Trambolho",
    "gn:country_code":"PT",
    "gn:dem":254,
    "gn:feature_class":"P",
    "gn:feature_code":"PPL",
    "gn:name":"Monte do Trambolho",
    "gn:population":0,
    "gn:timezone":"Europe/Lisbon",
    "iso:country":"PT",
    "wof:name":"Monte do Trambolho",
    "wof:placetype":"locality"
},
  "geometry": {"coordinates":[-7.80066,38.63839],"type":"Point"}
}