{
  "type": "Feature",
  "properties": {
    "gn:admin1_code":"7.0",
    "gn:admin2_code":"0603",
    "gn:admin3_code":"60317.0",
    "gn:asciiname":"Coselhas",
    "gn:country_code":"PT",
    "gn:dem":24,
    "gn:feature_class":"P",
    "gn:feature_code":"PPL",
    "gn:name":"Coselhas",
    "gn:population":0,
    "gn:timezone":"Europe/Lisbon",
    "iso:country":"PT",
    "wof:name":"Coselhas",
    "wof:placetype":"locality"
},
  "geometry": {"coordinates":[-8.42803,40.22139],"type":"Point"}
}