{
  "type": "Feature",
  "properties": {
    "gn:admin1_code":"11.0",
    "gn:admin2_code":"0910",
    "gn:admin3_code":"91010.0",
    "gn:asciiname":"Espedrada",
    "gn:country_code":"PT",
    "gn:dem":654,
    "gn:feature_class":"P",
    "gn:feature_code":"PPL",
    "gn:name":"Espedrada",
    "gn:population":0,
    "gn:timezone":"Europe/Lisbon",
    "iso:country":"PT",
    "wof:name":"Espedrada",
    "wof:placetype":"locality"
},
  "geometry": {"coordinates":[-7.19252,40.67259],"type":"Point"}
}