{
  "type": "Feature",
  "properties": {
    "iso:country":"PT",
    "name:pol_x_preferred":[
        "S\u00e3o Vicente"
    ],
    "wof:name":"Sao Vicente",
    "wof:placetype":"neighbourhood"
},
  "geometry": {"coordinates":[-9.12499251980642,38.71807798644361],"type":"Point"}
}