{
  "type": "Feature",
  "properties": {
    "gn:country":"PT",
    "gn:fcode":"PPL",
    "gn:population":5157,
    "iso:country":"PT",
    "name:ceb_x_preferred":[
        "Ferreiras"
    ],
    "name:deu_x_preferred":[
        "Ferreiras"
    ],
    "name:kaz_x_preferred":[
        "\u0424\u0435\u0440\u0440\u0435\u0439\u0440\u0430\u0448"
    ],
    "name:nld_x_preferred":[
        "Ferreiras"
    ],
    "name:por_x_preferred":[
        "Ferreiras"
    ],
    "name:rus_x_preferred":[
        "\u0424\u0435\u0440\u0440\u0435\u0439\u0440\u0430\u0448"
    ],
    "name:spa_x_preferred":[
        "Ferreiras"
    ],
    "name:swe_x_preferred":[
        "Ferreiras"
    ],
    "qs_pg:aaroncc":"PT",
    "qs_pg:gn_country":"PT",
    "qs_pg:gn_fcode":"PPL",
    "qs_pg:gn_pop":5157,
    "qs_pg:name":"Ferreiras",
    "qs_pg:name_adm0":"Portugal",
    "qs_pg:name_adm1":"Faro",
    "qs_pg:photos_9k":1,
    "qs_pg:photos_9r":1,
    "qs_pg:photos_all":1,
    "qs_pg:photos_sr":0,
    "qs_pg:pop_sr":5,
    "qs_pg:qs_pg_placetype":"locality",
    "qs_pg:qs_pg_placetype_gp":"Town",
    "qs_pg:woe_adm0":23424925,
    "woe:adm0_id":23424925,
    "woe:name_adm0":"Portugal",
    "woe:name_adm1":"Faro",
    "woe:placetype":"Town",
    "wof:name":"Ferreiras",
    "wof:placetype":"locality",
    "wof:population":5157
},
  "geometry": {"coordinates":[-8.23759,37.12926],"type":"Point"}
}