{
  "type": "Feature",
  "properties": {
    "gn:admin1_code":"22",
    "gn:admin2_code":"1813",
    "gn:admin3_code":"181306.0",
    "gn:asciiname":"Redondo",
    "gn:country_code":"PT",
    "gn:dem":316,
    "gn:feature_class":"P",
    "gn:feature_code":"PPL",
    "gn:name":"Redondo",
    "gn:population":0,
    "gn:timezone":"Europe/Lisbon",
    "iso:country":"PT",
    "name:ceb_x_preferred":[
        "Redondo"
    ],
    "name:deu_x_preferred":[
        "Redondo"
    ],
    "name:eus_x_preferred":[
        "Redondo"
    ],
    "name:fas_x_preferred":[
        "\u0631\u062f\u0648\u0646\u062f\u0648"
    ],
    "name:fra_x_preferred":[
        "Redondo"
    ],
    "name:glg_x_preferred":[
        "Redondo"
    ],
    "name:ita_x_preferred":[
        "Redondo"
    ],
    "name:por_x_preferred":[
        "Redondo"
    ],
    "name:rus_x_preferred":[
        "\u0420\u0435\u0434\u043e\u043d\u0434\u0443"
    ],
    "name:spa_x_preferred":[
        "Redondo"
    ],
    "name:swe_x_preferred":[
        "Redondo"
    ],
    "wof:name":"Redondo",
    "wof:placetype":"locality"
},
  "geometry": {"coordinates":[-8.01667,41.08333],"type":"Point"}
}