{
  "type": "Feature",
  "properties": {
    "gn:admin1_code":"22",
    "gn:admin2_code":"1813",
    "gn:admin3_code":"181306.0",
    "gn:asciiname":"Redondo",
    "gn:country_code":"PT",
    "gn:dem":316,
    "gn:feature_class":"P",
    "gn:feature_code":"PPL",
    "gn:name":"Redondo",
    "gn:population":0,
    "gn:timezone":"Europe/Lisbon",
    "iso:country":"PT",
    "wof:name":"Redondo",
    "wof:placetype":"locality"
},
  "geometry": {"coordinates":[-8.01667,41.08333],"type":"Point"}
}