{
  "type": "Feature",
  "properties": {
    "gn:admin1_code":"08",
    "gn:admin2_code":"0705",
    "gn:admin3_code":"70521.0",
    "gn:asciiname":"Quinta do Galego",
    "gn:country_code":"PT",
    "gn:dem":261,
    "gn:feature_class":"P",
    "gn:feature_code":"PPL",
    "gn:name":"Quinta do Galego",
    "gn:population":0,
    "gn:timezone":"Europe/Lisbon",
    "iso:country":"PT",
    "wof:name":"Quinta do Galego",
    "wof:placetype":"locality"
},
  "geometry": {"coordinates":[-7.88333,38.58333],"type":"Point"}
}