{
  "type": "Feature",
  "properties": {
    "gn:admin1_code":"2.0",
    "gn:admin2_code":"0105",
    "gn:admin3_code":"10502.0",
    "gn:asciiname":"Cabeco",
    "gn:country_code":"PT",
    "gn:dem":11,
    "gn:feature_class":"P",
    "gn:feature_code":"PPL",
    "gn:name":"Cabe\u00e7o",
    "gn:population":0,
    "gn:timezone":"Europe/Lisbon",
    "iso:country":"PT",
    "wof:name":"Cabeco",
    "wof:placetype":"locality"
},
  "geometry": {"coordinates":[-8.6289,40.68068],"type":"Point"}
}