{
  "type": "Feature",
  "properties": {
    "iso:country":"PT",
    "name:cat_x_preferred":[
        "Amares"
    ],
    "name:ceb_x_preferred":[
        "Amares"
    ],
    "name:dan_x_preferred":[
        "Amares"
    ],
    "name:deu_x_preferred":[
        "Amares"
    ],
    "name:eng_x_preferred":[
        "Amares"
    ],
    "name:eus_x_preferred":[
        "Amares"
    ],
    "name:fas_x_preferred":[
        "\u0634\u0647\u0631 \u0627\u0645\u0631\u06cc\u0633"
    ],
    "name:fin_x_preferred":[
        "Amares"
    ],
    "name:fra_x_preferred":[
        "Amares"
    ],
    "name:glg_x_preferred":[
        "Amares"
    ],
    "name:ita_x_preferred":[
        "Amares"
    ],
    "name:msa_x_preferred":[
        "Amares"
    ],
    "name:mwl_x_preferred":[
        "Amares"
    ],
    "name:nan_x_preferred":[
        "Amares"
    ],
    "name:nld_x_preferred":[
        "Amares"
    ],
    "name:nob_x_preferred":[
        "Amares"
    ],
    "name:pol_x_preferred":[
        "Amares"
    ],
    "name:por_x_preferred":[
        "Amares"
    ],
    "name:rup_x_preferred":[
        "Amares"
    ],
    "name:rus_x_preferred":[
        "\u0410\u043c\u0430\u0440\u0438\u0448"
    ],
    "name:spa_x_preferred":[
        "Amares"
    ],
    "name:tur_x_preferred":[
        "Amares"
    ],
    "name:ukr_x_preferred":[
        "\u0410\u043c\u0430\u0440\u0456\u0448"
    ],
    "name:vie_x_preferred":[
        "Amares"
    ],
    "name:vol_x_preferred":[
        "Amares"
    ],
    "name:war_x_preferred":[
        "Amares"
    ],
    "name:zho_min_nan_x_preferred":[
        "Amares"
    ],
    "name:zho_x_preferred":[
        "\u963f\u99ac\u91cc\u4ec0"
    ],
    "qs:a0":"Portugal",
    "qs:a1":"*Braga",
    "qs:a1r":"0",
    "qs:adm0":"Portugal",
    "qs:la_lc":"*",
    "qs:level":"locality",
    "qs:loc":"Amares",
    "qs:loc_alt":"Amares",
    "qs:pop":0,
    "qs:type":"buffered point",
    "wd:wordcount":110,
    "wof:lang":[
        "por"
    ],
    "wof:name":"Amares",
    "wof:placetype":"locality"
},
  "geometry": {"coordinates":[-8.355453,41.636558],"type":"Point"}
}