{
  "type": "Feature",
  "properties": {
    "gn:admin1_code":"22",
    "gn:admin2_code":"1821",
    "gn:admin3_code":"182113.0",
    "gn:asciiname":"Ribeiro",
    "gn:country_code":"PT",
    "gn:dem":336,
    "gn:feature_class":"P",
    "gn:feature_code":"PPL",
    "gn:name":"Ribeiro",
    "gn:population":0,
    "gn:timezone":"Europe/Lisbon",
    "iso:country":"PT",
    "name:bel_x_preferred":[
        "\u0420\u044b\u0431\u0435\u0439\u0440\u0443"
    ],
    "name:ces_x_preferred":[
        "Ribeiro"
    ],
    "name:deu_x_preferred":[
        "Ribeiro"
    ],
    "name:fin_x_preferred":[
        "Ribeiro"
    ],
    "name:fra_x_preferred":[
        "Ribeiro"
    ],
    "name:glg_x_preferred":[
        "Ribeiro"
    ],
    "name:ita_x_preferred":[
        "Ribeiro"
    ],
    "name:kor_x_preferred":[
        "\ud788\ubca0\uc774\ub8e8"
    ],
    "name:lit_x_preferred":[
        "Ribeiro"
    ],
    "name:pol_x_preferred":[
        "Ribeiro"
    ],
    "name:rus_x_preferred":[
        "\u0420\u0438\u0431\u0435\u0439\u0440\u0443"
    ],
    "name:swe_x_preferred":[
        "Ribeiro"
    ],
    "name:ukr_x_preferred":[
        "\u0420\u0456\u0431\u0435\u0439\u0440\u043e"
    ],
    "wof:name":"Ribeiro",
    "wof:placetype":"locality"
},
  "geometry": {"coordinates":[-8.06683,40.57649],"type":"Point"}
}