{
  "type": "Feature",
  "properties": {
    "gn:admin1_code":"22",
    "gn:admin2_code":"1821",
    "gn:admin3_code":"182113.0",
    "gn:asciiname":"Ribeiro",
    "gn:country_code":"PT",
    "gn:dem":336,
    "gn:feature_class":"P",
    "gn:feature_code":"PPL",
    "gn:name":"Ribeiro",
    "gn:population":0,
    "gn:timezone":"Europe/Lisbon",
    "iso:country":"PT",
    "wof:name":"Ribeiro",
    "wof:placetype":"locality"
},
  "geometry": {"coordinates":[-8.06683,40.57649],"type":"Point"}
}