{
  "type": "Feature",
  "properties": {
    "gn:admin1_code":"03",
    "gn:admin2_code":"0211",
    "gn:admin3_code":"21102.0",
    "gn:asciiname":"Barreiros",
    "gn:country_code":"PT",
    "gn:dem":196,
    "gn:feature_class":"P",
    "gn:feature_code":"PPL",
    "gn:name":"Barreiros",
    "gn:population":0,
    "gn:timezone":"Europe/Lisbon",
    "iso:country":"PT",
    "wof:name":"Barreiros",
    "wof:placetype":"locality"
},
  "geometry": {"coordinates":[-8.48572,37.69522],"type":"Point"}
}