{
  "type": "Feature",
  "properties": {
    "gn:admin1_code":"20",
    "gn:admin2_code":"1604",
    "gn:admin3_code":"160425.0",
    "gn:asciiname":"Valadares",
    "gn:country_code":"PT",
    "gn:dem":116,
    "gn:feature_class":"P",
    "gn:feature_code":"PPL",
    "gn:name":"Valadares",
    "gn:population":0,
    "gn:timezone":"Europe/Lisbon",
    "iso:country":"PT",
    "name:ceb_x_preferred":[
        "Valadares"
    ],
    "name:deu_x_preferred":[
        "Valadares"
    ],
    "name:fra_x_preferred":[
        "Valadares"
    ],
    "name:glg_x_preferred":[
        "Valadares"
    ],
    "name:nld_x_preferred":[
        "Valadares"
    ],
    "name:por_x_preferred":[
        "Valadares"
    ],
    "name:rus_x_preferred":[
        "\u0412\u0430\u043b\u0430\u0434\u0430\u0440\u0435\u0448"
    ],
    "name:spa_x_preferred":[
        "Valadares"
    ],
    "name:swe_x_preferred":[
        "Valadares"
    ],
    "name:tur_x_preferred":[
        "Valadares"
    ],
    "wof:name":"Valadares",
    "wof:placetype":"locality"
},
  "geometry": {"coordinates":[-8.35818,42.07297],"type":"Point"}
}