{
  "type": "Feature",
  "properties": {
    "gn:admin1_code":"20",
    "gn:admin2_code":"1604",
    "gn:admin3_code":"160425.0",
    "gn:asciiname":"Valadares",
    "gn:country_code":"PT",
    "gn:dem":116,
    "gn:feature_class":"P",
    "gn:feature_code":"PPL",
    "gn:name":"Valadares",
    "gn:population":0,
    "gn:timezone":"Europe/Lisbon",
    "iso:country":"PT",
    "wof:name":"Valadares",
    "wof:placetype":"locality"
},
  "geometry": {"coordinates":[-8.35818,42.07297],"type":"Point"}
}