{
  "type": "Feature",
  "properties": {
    "gn:admin1_code":"08",
    "gn:admin2_code":"0710",
    "gn:admin3_code":"71002.0",
    "gn:asciiname":"Adaval",
    "gn:country_code":"PT",
    "gn:dem":249,
    "gn:feature_class":"P",
    "gn:feature_code":"PPL",
    "gn:name":"Adaval",
    "gn:population":0,
    "gn:timezone":"Europe/Lisbon",
    "iso:country":"PT",
    "wof:name":"Adaval",
    "wof:placetype":"locality"
},
  "geometry": {"coordinates":[-7.61065,38.61789],"type":"Point"}
}