{
  "type": "Feature",
  "properties": {
    "gn:admin1_code":"22.0",
    "gn:admin2_code":"1813",
    "gn:admin3_code":"181311.0",
    "gn:asciiname":"Pesqueira",
    "gn:country_code":"PT",
    "gn:dem":621,
    "gn:feature_class":"P",
    "gn:feature_code":"PPL",
    "gn:name":"Pesqueira",
    "gn:population":0,
    "gn:timezone":"Europe/Lisbon",
    "iso:country":"PT",
    "name:ceb_x_preferred":[
        "Pesqueira"
    ],
    "name:glg_x_preferred":[
        "Pesqueira"
    ],
    "name:spa_x_preferred":[
        "Pesqueira"
    ],
    "name:swe_x_preferred":[
        "Pesqueira"
    ],
    "wof:name":"Pesqueira",
    "wof:placetype":"locality"
},
  "geometry": {"coordinates":[-7.93517,41.08734000000001],"type":"Point"}
}