{
  "type": "Feature",
  "properties": {
    "gn:admin1_code":"19",
    "gn:admin2_code":"1513",
    "gn:admin3_code":"151301.0",
    "gn:asciiname":"Carocha",
    "gn:country_code":"PT",
    "gn:dem":174,
    "gn:feature_class":"P",
    "gn:feature_code":"PPL",
    "gn:name":"Carocha",
    "gn:population":0,
    "gn:timezone":"Europe/Lisbon",
    "iso:country":"PT",
    "wof:name":"Carocha",
    "wof:placetype":"locality"
},
  "geometry": {"coordinates":[-8.69719,37.89804],"type":"Point"}
}