{
  "type": "Feature",
  "properties": {
    "gn:admin1_code":"21",
    "gn:admin2_code":"1708",
    "gn:admin3_code":"170805.0",
    "gn:asciiname":"Reguengo",
    "gn:country_code":"PT",
    "gn:dem":474,
    "gn:feature_class":"P",
    "gn:feature_code":"PPL",
    "gn:name":"Reguengo",
    "gn:population":0,
    "gn:timezone":"Europe/Lisbon",
    "iso:country":"PT",
    "name:fra_x_preferred":[
        "Reguengo"
    ],
    "name:glg_x_preferred":[
        "Reguengo"
    ],
    "name:por_x_preferred":[
        "Reguengo"
    ],
    "name:spa_x_preferred":[
        "Reguengo"
    ],
    "wof:name":"Reguengo",
    "wof:placetype":"locality"
},
  "geometry": {"coordinates":[-7.81733,41.19505],"type":"Point"}
}