{
  "type": "Feature",
  "properties": {
    "gn:admin1_code":"13",
    "gn:admin2_code":"1016",
    "gn:admin3_code":"101603.0",
    "gn:asciiname":"Orcario",
    "gn:country_code":"PT",
    "gn:dem":262,
    "gn:feature_class":"P",
    "gn:feature_code":"PPL",
    "gn:name":"Or\u00e7\u00e1rio",
    "gn:population":0,
    "gn:timezone":"Europe/Lisbon",
    "iso:country":"PT",
    "wof:name":"Orcario",
    "wof:placetype":"locality"
},
  "geometry": {"coordinates":[-8.76641,39.54284000000001],"type":"Point"}
}