{
  "type": "Feature",
  "properties": {
    "gn:admin1_code":"5.0",
    "gn:admin2_code":"0412",
    "gn:admin3_code":"41235.0",
    "gn:asciiname":"Ermida",
    "gn:country_code":"PT",
    "gn:dem":465,
    "gn:feature_class":"P",
    "gn:feature_code":"PPL",
    "gn:name":"Ermida",
    "gn:population":0,
    "gn:timezone":"Europe/Lisbon",
    "iso:country":"PT",
    "wof:name":"Ermida",
    "wof:placetype":"locality"
},
  "geometry": {"coordinates":[-7.00565,41.80258],"type":"Point"}
}