{
  "type": "Feature",
  "properties": {
    "gn:admin1_code":"14",
    "gn:admin2_code":"1107",
    "gn:admin3_code":"110717.0",
    "gn:asciiname":"Categal",
    "gn:country_code":"PT",
    "gn:dem":82,
    "gn:feature_class":"P",
    "gn:feature_code":"PPL",
    "gn:name":"Categal",
    "gn:population":0,
    "gn:timezone":"Europe/Lisbon",
    "iso:country":"PT",
    "wof:name":"Categal",
    "wof:placetype":"locality"
},
  "geometry": {"coordinates":[-9.11667,38.81667],"type":"Point"}
}