{
  "type": "Feature",
  "properties": {
    "gn:country":"PT",
    "gn:fcode":"PPL",
    "gn:population":0,
    "iso:country":"PT",
    "name:deu_x_preferred":[
        "Campo de Besteiros"
    ],
    "name:eng_x_preferred":[
        "Campo de Besteiros"
    ],
    "name:fra_x_preferred":[
        "Campo de Besteiros"
    ],
    "name:kaz_x_preferred":[
        "\u041a\u0430\u043c\u043f\u0443-\u0434\u0435-\u0411\u0435\u0448\u0442\u0435\u0439\u0440\u0443\u0448"
    ],
    "name:msa_x_preferred":[
        "Campo de Besteiros"
    ],
    "name:nan_x_preferred":[
        "Campo de Besteiros"
    ],
    "name:nld_x_preferred":[
        "Campo de Besteiros"
    ],
    "name:por_x_preferred":[
        "Campo de Besteiros"
    ],
    "name:rus_x_preferred":[
        "\u041a\u0430\u043c\u043f\u0443-\u0434\u0435-\u0411\u0435\u0448\u0442\u0435\u0439\u0440\u0443\u0448"
    ],
    "name:spa_x_preferred":[
        "Campo de Besteiros"
    ],
    "name:tur_x_preferred":[
        "Campo de Besteiros"
    ],
    "qs_pg:aaroncc":"PT",
    "qs_pg:gn_country":"PT",
    "qs_pg:gn_fcode":"PPL",
    "qs_pg:gn_pop":0,
    "qs_pg:name":"Campo de Besteiros",
    "qs_pg:name_adm0":"Portugal",
    "qs_pg:name_adm1":"Viseu",
    "qs_pg:photos_9k":1,
    "qs_pg:photos_9r":1,
    "qs_pg:photos_all":1,
    "qs_pg:photos_sr":0,
    "qs_pg:pop_sr":0,
    "qs_pg:qs_pg_placetype":"locality",
    "qs_pg:qs_pg_placetype_gp":"Town",
    "qs_pg:woe_adm0":23424925,
    "woe:adm0_id":23424925,
    "woe:name_adm0":"Portugal",
    "woe:name_adm1":"Viseu",
    "woe:placetype":"Town",
    "wof:name":"Campo de Besteiros",
    "wof:placetype":"locality"
},
  "geometry": {"coordinates":[-8.1356,40.56015],"type":"Point"}
}