{
  "type": "Feature",
  "properties": {
    "gn:admin1_code":"03",
    "gn:admin2_code":"0209",
    "gn:admin3_code":"20905.0",
    "gn:asciiname":"Monte da Costa",
    "gn:country_code":"PT",
    "gn:dem":155,
    "gn:feature_class":"P",
    "gn:feature_code":"PPL",
    "gn:name":"Monte da Costa",
    "gn:population":0,
    "gn:timezone":"Europe/Lisbon",
    "iso:country":"PT",
    "wof:name":"Monte da Costa",
    "wof:placetype":"locality"
},
  "geometry": {"coordinates":[-7.56685,37.64356],"type":"Point"}
}