{
  "type": "Feature",
  "properties": {
    "gn:admin1_code":"7.0",
    "gn:admin2_code":"0617",
    "gn:admin3_code":"61703.0",
    "gn:asciiname":"Cabecas",
    "gn:country_code":"PT",
    "gn:dem":158,
    "gn:feature_class":"P",
    "gn:feature_code":"PPL",
    "gn:name":"Cabe\u00e7as",
    "gn:population":0,
    "gn:timezone":"Europe/Lisbon",
    "iso:country":"PT",
    "wof:name":"Cabecas",
    "wof:placetype":"locality"
},
  "geometry": {"coordinates":[-8.25825,40.22561],"type":"Point"}
}