{
  "type": "Feature",
  "properties": {
    "gn:admin1_code":"17.0",
    "gn:asciiname":"Cidadelhe",
    "gn:country_code":"PT",
    "gn:dem":328,
    "gn:feature_class":"P",
    "gn:feature_code":"PPL",
    "gn:name":"Cidadelhe",
    "gn:population":0,
    "gn:timezone":"Europe/Lisbon",
    "iso:country":"PT",
    "wof:name":"Cidadelhe",
    "wof:placetype":"locality"
},
  "geometry": {"coordinates":[-7.84367,41.17033],"type":"Point"}
}