{
  "type": "Feature",
  "properties": {
    "gn:admin1_code":"21.0",
    "gn:admin2_code":"1703",
    "gn:admin3_code":"170333.0",
    "gn:asciiname":"Pereira da Veiga",
    "gn:country_code":"PT",
    "gn:dem":376,
    "gn:feature_class":"P",
    "gn:feature_code":"PPL",
    "gn:name":"Pereira da Veiga",
    "gn:population":0,
    "gn:timezone":"Europe/Lisbon",
    "iso:country":"PT",
    "wof:name":"Pereira da Veiga",
    "wof:placetype":"locality"
},
  "geometry": {"coordinates":[-7.47918,41.71253],"type":"Point"}
}