{
  "type": "Feature",
  "properties": {
    "gn:admin1_code":"2.0",
    "gn:admin2_code":"0109",
    "gn:admin3_code":"10912.0",
    "gn:asciiname":"Cimo de Vila",
    "gn:country_code":"PT",
    "gn:dem":255,
    "gn:feature_class":"P",
    "gn:feature_code":"PPL",
    "gn:name":"Cimo de Vila",
    "gn:population":0,
    "gn:timezone":"Europe/Lisbon",
    "iso:country":"PT",
    "wof:name":"Cimo de Vila",
    "wof:placetype":"locality"
},
  "geometry": {"coordinates":[-8.4625,40.96896],"type":"Point"}
}