{
  "type": "Feature",
  "properties": {
    "gn:admin1_code":"20.0",
    "gn:admin2_code":"1610",
    "gn:admin3_code":"161006.0",
    "gn:asciiname":"Gondarem",
    "gn:country_code":"PT",
    "gn:dem":85,
    "gn:feature_class":"P",
    "gn:feature_code":"PPL",
    "gn:name":"Gondar\u00e9m",
    "gn:population":0,
    "gn:timezone":"Europe/Lisbon",
    "iso:country":"PT",
    "wof:name":"Gondarem",
    "wof:placetype":"locality"
},
  "geometry": {"coordinates":[-8.75134,41.91855],"type":"Point"}
}