{
  "type": "Feature",
  "properties": {
    "gn:admin1_code":"20",
    "gn:admin2_code":"1604",
    "gn:admin3_code":"160423.0",
    "gn:asciiname":"Regoufe",
    "gn:country_code":"PT",
    "gn:dem":200,
    "gn:feature_class":"P",
    "gn:feature_code":"PPL",
    "gn:name":"Regoufe",
    "gn:population":0,
    "gn:timezone":"Europe/Lisbon",
    "iso:country":"PT",
    "wof:name":"Regoufe",
    "wof:placetype":"locality"
},
  "geometry": {"coordinates":[-8.49323,41.99112],"type":"Point"}
}