{
  "type": "Feature",
  "properties": {
    "gn:admin1_code":"7.0",
    "gn:admin2_code":"0605",
    "gn:admin3_code":"60518.0",
    "gn:asciiname":"Casal Lourenco",
    "gn:country_code":"PT",
    "gn:dem":53,
    "gn:feature_class":"P",
    "gn:feature_code":"PPL",
    "gn:name":"Casal Louren\u00e7o",
    "gn:population":0,
    "gn:timezone":"Europe/Lisbon",
    "iso:country":"PT",
    "wof:name":"Casal Lourenco",
    "wof:placetype":"locality"
},
  "geometry": {"coordinates":[-8.78333,40.23333],"type":"Point"}
}