{
  "type": "Feature",
  "properties": {
    "gn:admin1_code":"04",
    "gn:admin2_code":"0307",
    "gn:admin3_code":"30733.0",
    "gn:asciiname":"Travassos",
    "gn:country_code":"PT",
    "gn:dem":380,
    "gn:feature_class":"P",
    "gn:feature_code":"PPL",
    "gn:name":"Travass\u00f3s",
    "gn:population":0,
    "gn:timezone":"Europe/Lisbon",
    "iso:country":"PT",
    "name:ceb_x_preferred":[
        "Travassos"
    ],
    "name:deu_x_preferred":[
        "Travassos"
    ],
    "wof:name":"Travassos",
    "wof:placetype":"locality"
},
  "geometry": {"coordinates":[-8.20214,41.49245],"type":"Point"}
}