{
  "type": "Feature",
  "properties": {
    "gn:admin1_code":"02",
    "gn:admin2_code":"0112",
    "gn:admin3_code":"11201.0",
    "gn:asciiname":"Rua do Forno",
    "gn:country_code":"PT",
    "gn:dem":2,
    "gn:feature_class":"P",
    "gn:feature_code":"PPL",
    "gn:name":"Rua do Forno",
    "gn:population":0,
    "gn:timezone":"Europe/Lisbon",
    "iso:country":"PT",
    "wof:name":"Rua do Forno",
    "wof:placetype":"locality"
},
  "geometry": {"coordinates":[-8.65935,40.75792],"type":"Point"}
}