{
  "type": "Feature",
  "properties": {
    "gn:admin1_code":"06",
    "gn:admin2_code":"0509",
    "gn:admin3_code":"50911.0",
    "gn:asciiname":"Roqueiro",
    "gn:country_code":"PT",
    "gn:dem":397,
    "gn:feature_class":"P",
    "gn:feature_code":"PPL",
    "gn:name":"Roqueiro",
    "gn:population":0,
    "gn:timezone":"Europe/Lisbon",
    "iso:country":"PT",
    "wof:name":"Roqueiro",
    "wof:placetype":"locality"
},
  "geometry": {"coordinates":[-8.10622,39.92748],"type":"Point"}
}