{
  "type": "Feature",
  "properties": {
    "gn:admin1_code":"13",
    "gn:admin2_code":"1006",
    "gn:admin3_code":"100607.0",
    "gn:asciiname":"Rostos",
    "gn:country_code":"PT",
    "gn:dem":119,
    "gn:feature_class":"P",
    "gn:feature_code":"PPL",
    "gn:name":"Rostos",
    "gn:population":0,
    "gn:timezone":"Europe/Lisbon",
    "iso:country":"PT",
    "wof:name":"Rostos",
    "wof:placetype":"locality"
},
  "geometry": {"coordinates":[-9.00153,39.30633],"type":"Point"}
}