{
  "type": "Feature",
  "properties": {
    "gn:admin1_code":"13.0",
    "gn:admin2_code":"1015",
    "gn:admin3_code":"101503.0",
    "gn:asciiname":"Carrascos",
    "gn:country_code":"PT",
    "gn:dem":106,
    "gn:feature_class":"P",
    "gn:feature_code":"PPL",
    "gn:name":"Carrascos",
    "gn:population":0,
    "gn:timezone":"Europe/Lisbon",
    "iso:country":"PT",
    "wof:name":"Carrascos",
    "wof:placetype":"locality"
},
  "geometry": {"coordinates":[-8.68622,40.016],"type":"Point"}
}