{
  "type": "Feature",
  "properties": {
    "gn:admin1_code":"03",
    "gn:admin2_code":"0209",
    "gn:admin3_code":"20905.0",
    "gn:asciiname":"Achada do Gamo",
    "gn:country_code":"PT",
    "gn:dem":108,
    "gn:feature_class":"P",
    "gn:feature_code":"PPL",
    "gn:name":"Achada do Gamo",
    "gn:population":0,
    "gn:timezone":"Europe/Lisbon",
    "iso:country":"PT",
    "wof:name":"Achada do Gamo",
    "wof:placetype":"locality"
},
  "geometry": {"coordinates":[-7.5094,37.65251],"type":"Point"}
}