{
  "type": "Feature",
  "properties": {
    "gn:admin1_code":"06",
    "gn:admin2_code":"0506",
    "gn:admin3_code":"50607.0",
    "gn:asciiname":"Mosteiro",
    "gn:country_code":"PT",
    "gn:dem":532,
    "gn:feature_class":"P",
    "gn:feature_code":"PPL",
    "gn:name":"Mosteiro",
    "gn:population":0,
    "gn:timezone":"Europe/Lisbon",
    "iso:country":"PT",
    "name:ceb_x_preferred":[
        "Mosteiro"
    ],
    "name:deu_x_preferred":[
        "Mosteiro"
    ],
    "name:fra_x_preferred":[
        "Mosteiro"
    ],
    "name:glg_x_preferred":[
        "Mosteiro"
    ],
    "name:nld_x_preferred":[
        "Mosteiro"
    ],
    "name:por_x_preferred":[
        "Mosteiro"
    ],
    "name:spa_x_preferred":[
        "Mosteiro"
    ],
    "name:ukr_x_preferred":[
        "\u041c\u043e\u0448\u0442\u0435\u0439\u0440\u0443"
    ],
    "wof:name":"Mosteiro",
    "wof:placetype":"locality"
},
  "geometry": {"coordinates":[-7.96316,39.89529],"type":"Point"}
}