{
  "type": "Feature",
  "properties": {
    "gn:admin1_code":"06",
    "gn:admin2_code":"0506",
    "gn:admin3_code":"50607.0",
    "gn:asciiname":"Mosteiro",
    "gn:country_code":"PT",
    "gn:dem":532,
    "gn:feature_class":"P",
    "gn:feature_code":"PPL",
    "gn:name":"Mosteiro",
    "gn:population":0,
    "gn:timezone":"Europe/Lisbon",
    "iso:country":"PT",
    "wof:name":"Mosteiro",
    "wof:placetype":"locality"
},
  "geometry": {"coordinates":[-7.96316,39.89529],"type":"Point"}
}