{
  "type": "Feature",
  "properties": {
    "gn:admin1_code":"2.0",
    "gn:admin2_code":"0104",
    "gn:admin3_code":"10409.0",
    "gn:asciiname":"Gestosa",
    "gn:country_code":"PT",
    "gn:dem":519,
    "gn:feature_class":"P",
    "gn:feature_code":"PPL",
    "gn:name":"Gestosa",
    "gn:population":0,
    "gn:timezone":"Europe/Lisbon",
    "iso:country":"PT",
    "wof:name":"Gestosa",
    "wof:placetype":"locality"
},
  "geometry": {"coordinates":[-8.39909,40.93242],"type":"Point"}
}