{
  "type": "Feature",
  "properties": {
    "gn:admin1_code":"03",
    "gn:admin2_code":"0209",
    "gn:admin3_code":"20907.0",
    "gn:asciiname":"Sao Miguel do Pinheiro",
    "gn:country_code":"PT",
    "gn:dem":192,
    "gn:feature_class":"P",
    "gn:feature_code":"PPL",
    "gn:name":"S\u00e3o Miguel do Pinheiro",
    "gn:population":0,
    "gn:timezone":"Europe/Lisbon",
    "iso:country":"PT",
    "wof:name":"Sao Miguel do Pinheiro",
    "wof:placetype":"locality"
},
  "geometry": {"coordinates":[-7.83793,37.54551],"type":"Point"}
}