{
  "type": "Feature",
  "properties": {
    "gn:admin1_code":"03",
    "gn:admin2_code":"0211",
    "gn:admin3_code":"21115.0",
    "gn:asciiname":"Nora",
    "gn:country_code":"PT",
    "gn:dem":82,
    "gn:feature_class":"P",
    "gn:feature_code":"PPL",
    "gn:name":"Nora",
    "gn:population":0,
    "gn:timezone":"Europe/Lisbon",
    "iso:country":"PT",
    "wof:name":"Nora",
    "wof:placetype":"locality"
},
  "geometry": {"coordinates":[-8.47941,37.55818],"type":"Point"}
}