{
  "type": "Feature",
  "properties": {
    "gn:country":"PT",
    "gn:fcode":"PPL",
    "gn:population":0,
    "iso:country":"PT",
    "name:ast_x_preferred":[
        "Concei\u00e7\u00e3o"
    ],
    "name:bpy_x_preferred":[
        "\u0995\u09cb\u09a8\u09cd\u09b8\u09c7\u0987\u0995\u09af\u09bc\u09be\u0993"
    ],
    "name:bre_x_preferred":[
        "Concei\u00e7\u00e3o"
    ],
    "name:ceb_x_preferred":[
        "Concei\u00e7\u00e3o"
    ],
    "name:deu_x_preferred":[
        "Concei\u00e7\u00e3o"
    ],
    "name:fra_x_preferred":[
        "Concei\u00e7\u00e3o"
    ],
    "name:nld_x_preferred":[
        "Concei\u00e7\u00e3o"
    ],
    "name:por_x_preferred":[
        "Concei\u00e7\u00e3o"
    ],
    "name:rus_x_preferred":[
        "\u041a\u043e\u043d\u0441\u0435\u0439\u0441\u0430\u043d"
    ],
    "name:spa_x_preferred":[
        "Concei\u00e7\u00e3o"
    ],
    "name:swe_x_preferred":[
        "Concei\u00e7\u00e3o"
    ],
    "name:tur_x_preferred":[
        "Concei\u00e7\u00e3o"
    ],
    "name:ukr_x_preferred":[
        "\u041a\u043e\u043d\u0441\u0435\u0439\u0441\u0430\u043d"
    ],
    "name:und_x_variant":[
        "Fonte Conceicao"
    ],
    "qs_pg:aaroncc":"PT",
    "qs_pg:gn_country":"PT",
    "qs_pg:gn_fcode":"PPL",
    "qs_pg:gn_pop":0,
    "qs_pg:name":"Concei\u00e7\u00e3o",
    "qs_pg:name_adm0":"Portugal",
    "qs_pg:name_adm1":"Faro",
    "qs_pg:photos":44,
    "qs_pg:photos_1k":9,
    "qs_pg:photos_9k":1,
    "qs_pg:photos_9r":2,
    "qs_pg:photos_all":44,
    "qs_pg:photos_sr":2,
    "qs_pg:pop_sr":0,
    "qs_pg:qs_pg_placetype":"locality",
    "qs_pg:qs_pg_placetype_gp":"Town",
    "qs_pg:woe_adm0":23424925,
    "woe:adm0_id":23424925,
    "woe:name_adm0":"Portugal",
    "woe:name_adm1":"Faro",
    "woe:placetype":"Town",
    "wof:name":"Concei\u00e7\u00e3o",
    "wof:placetype":"locality"
},
  "geometry": {"coordinates":[-7.60539,37.15055],"type":"Point"}
}