{
  "type": "Feature",
  "properties": {
    "gn:admin1_code":"16",
    "gn:admin2_code":"1215",
    "gn:admin3_code":"121504.0",
    "gn:asciiname":"Roxa",
    "gn:country_code":"PT",
    "gn:dem":233,
    "gn:feature_class":"P",
    "gn:feature_code":"PPL",
    "gn:name":"Roxa",
    "gn:population":0,
    "gn:timezone":"Europe/Lisbon",
    "iso:country":"PT",
    "wof:name":"Roxa",
    "wof:placetype":"locality"
},
  "geometry": {"coordinates":[-7.73425,38.99264],"type":"Point"}
}