{
  "type": "Feature",
  "properties": {
    "gn:admin1_code":"16",
    "gn:admin2_code":"1215",
    "gn:admin3_code":"121504.0",
    "gn:asciiname":"Roxa",
    "gn:country_code":"PT",
    "gn:dem":233,
    "gn:feature_class":"P",
    "gn:feature_code":"PPL",
    "gn:name":"Roxa",
    "gn:population":0,
    "gn:timezone":"Europe/Lisbon",
    "iso:country":"PT",
    "name:ceb_x_preferred":[
        "Ilha Roxa"
    ],
    "name:deu_x_preferred":[
        "Canhabaque"
    ],
    "name:fra_x_preferred":[
        "Canhabaque"
    ],
    "name:lit_x_preferred":[
        "Ro\u0161a"
    ],
    "name:por_x_preferred":[
        "Canhabaque"
    ],
    "name:ron_x_preferred":[
        "Insula Roxa"
    ],
    "name:spa_x_preferred":[
        "Canhabaque"
    ],
    "name:swe_x_preferred":[
        "Ilha Roxa"
    ],
    "name:zho_x_preferred":[
        "\u7f85\u6c99\u5cf6"
    ],
    "wof:name":"Roxa",
    "wof:placetype":"locality"
},
  "geometry": {"coordinates":[-7.73425,38.99264],"type":"Point"}
}