{
  "type": "Feature",
  "properties": {
    "gn:admin1_code":"14",
    "gn:admin2_code":"1111",
    "gn:admin3_code":"111109.0",
    "gn:asciiname":"Santo Amaro",
    "gn:country_code":"PT",
    "gn:dem":113,
    "gn:feature_class":"P",
    "gn:feature_code":"PPL",
    "gn:name":"Santo Amaro",
    "gn:population":0,
    "gn:timezone":"Europe/Lisbon",
    "iso:country":"PT",
    "wof:name":"Santo Amaro",
    "wof:placetype":"locality"
},
  "geometry": {"coordinates":[-9.37936,38.81587],"type":"Point"}
}