{
  "type": "Feature",
  "properties": {
    "gn:admin1_code":"5.0",
    "gn:admin2_code":"0403",
    "gn:admin3_code":"40314.0",
    "gn:asciiname":"Pombal",
    "gn:country_code":"PT",
    "gn:dem":478,
    "gn:feature_class":"P",
    "gn:feature_code":"PPL",
    "gn:name":"Pombal",
    "gn:population":0,
    "gn:timezone":"Europe/Lisbon",
    "iso:country":"PT",
    "wof:name":"Pombal",
    "wof:placetype":"locality"
},
  "geometry": {"coordinates":[-7.3588,41.28336],"type":"Point"}
}