{
  "type": "Feature",
  "properties": {
    "gn:admin1_code":"20",
    "gn:admin2_code":"1604",
    "gn:admin3_code":"160425.0",
    "gn:asciiname":"Sa",
    "gn:country_code":"PT",
    "gn:dem":149,
    "gn:feature_class":"P",
    "gn:feature_code":"PPL",
    "gn:name":"S\u00e1",
    "gn:population":0,
    "gn:timezone":"Europe/Lisbon",
    "iso:country":"PT",
    "wof:name":"Sa",
    "wof:placetype":"locality"
},
  "geometry": {"coordinates":[-8.35306,42.07335],"type":"Point"}
}