{
  "type": "Feature",
  "properties": {
    "gn:country":"PT",
    "gn:fcode":"PPL",
    "gn:population":0,
    "iso:country":"PT",
    "name:cat_x_preferred":[
        "Nordeste"
    ],
    "name:ceb_x_preferred":[
        "Nordeste"
    ],
    "name:che_x_preferred":[
        "\u041d\u043e\u0440\u0434\u0435\u0448\u0442\u0438"
    ],
    "name:deu_x_preferred":[
        "Nordeste"
    ],
    "name:eng_x_preferred":[
        "Nordeste"
    ],
    "name:fra_x_preferred":[
        "Nordeste"
    ],
    "name:gle_x_preferred":[
        "Nordeste"
    ],
    "name:ita_x_preferred":[
        "Nordeste"
    ],
    "name:jpn_x_preferred":[
        "\u30ce\u30eb\u30c7\u30b9\u30c6"
    ],
    "name:kor_x_preferred":[
        "\ub178\ub974\ub370\uc2a4\ud2b8"
    ],
    "name:nan_x_preferred":[
        "Nordeste"
    ],
    "name:nld_x_preferred":[
        "Nordeste"
    ],
    "name:nob_x_preferred":[
        "Nordeste"
    ],
    "name:pol_x_preferred":[
        "Nordeste"
    ],
    "name:por_x_preferred":[
        "Nordeste"
    ],
    "name:ron_x_preferred":[
        "Nordeste"
    ],
    "name:rus_x_preferred":[
        "\u041d\u043e\u0440\u0434\u0435\u0448\u0442\u0438"
    ],
    "name:spa_x_preferred":[
        "Nordeste"
    ],
    "name:szl_x_preferred":[
        "Nordeste"
    ],
    "name:tat_x_preferred":[
        "\u041d\u043e\u0440\u0434\u0435\u0448\u0442\u0438"
    ],
    "name:tur_x_preferred":[
        "Nordeste"
    ],
    "name:ukr_x_preferred":[
        "\u041d\u043e\u0440\u0434\u0435\u0448\u0442\u0435"
    ],
    "name:vie_x_preferred":[
        "Nordeste"
    ],
    "name:vol_x_preferred":[
        "Nordeste"
    ],
    "name:war_x_preferred":[
        "Nordeste"
    ],
    "name:zho_x_preferred":[
        "\u8afe\u5fb7\u4ec0\u8482"
    ],
    "qs_pg:aaroncc":"PT",
    "qs_pg:gn_country":"PT",
    "qs_pg:gn_fcode":"PPL",
    "qs_pg:gn_pop":0,
    "qs_pg:name":"Nordeste",
    "qs_pg:name_adm0":"Portugal",
    "qs_pg:name_adm1":"Azores",
    "qs_pg:photos":167,
    "qs_pg:photos_1k":34,
    "qs_pg:photos_9k":1,
    "qs_pg:photos_9r":4,
    "qs_pg:photos_all":167,
    "qs_pg:photos_sr":4,
    "qs_pg:pop_sr":0,
    "qs_pg:qs_pg_placetype":"locality",
    "qs_pg:qs_pg_placetype_gp":"Town",
    "qs_pg:woe_adm0":23424925,
    "woe:adm0_id":23424925,
    "woe:name_adm0":"Portugal",
    "woe:name_adm1":"Azores",
    "woe:placetype":"Town",
    "wof:name":"Nordeste",
    "wof:placetype":"locality"
},
  "geometry": {"coordinates":[-25.16667,37.83333],"type":"Point"}
}