{
  "type": "Feature",
  "properties": {
    "gn:admin1_code":"06",
    "gn:admin2_code":"0505",
    "gn:admin3_code":"50517.0",
    "gn:asciiname":"Monte de Sao Domingos Velho",
    "gn:country_code":"PT",
    "gn:dem":318,
    "gn:feature_class":"P",
    "gn:feature_code":"PPL",
    "gn:name":"Monte de S\u00e3o Domingos Velho",
    "gn:population":0,
    "gn:timezone":"Europe/Lisbon",
    "iso:country":"PT",
    "wof:name":"Monte de Sao Domingos Velho",
    "wof:placetype":"locality"
},
  "geometry": {"coordinates":[-7.11433,39.80787],"type":"Point"}
}