{
  "type": "Feature",
  "properties": {
    "gn:country":"PT",
    "gn:fcode":"PPL",
    "gn:population":0,
    "iso:country":"PT",
    "name:ast_x_preferred":[
        "Mondim da Beira"
    ],
    "name:cat_x_preferred":[
        "Mondim da Beira"
    ],
    "name:ceb_x_preferred":[
        "Mondim da Beira"
    ],
    "name:deu_x_preferred":[
        "Mondim da Beira"
    ],
    "name:eng_x_preferred":[
        "Mondim da Beira"
    ],
    "name:fra_x_preferred":[
        "Mondim da Beira"
    ],
    "name:kaz_x_preferred":[
        "\u041c\u043e\u043d\u0434\u0438\u043d-\u0434\u0430-\u0411\u0435\u0439\u0440\u0430"
    ],
    "name:msa_x_preferred":[
        "Mondim da Beira"
    ],
    "name:nan_x_preferred":[
        "Mondim da Beira"
    ],
    "name:nld_x_preferred":[
        "Mondim da Beira"
    ],
    "name:oci_x_preferred":[
        "Mondim da Beira"
    ],
    "name:por_x_preferred":[
        "Mondim da Beira"
    ],
    "name:rus_x_preferred":[
        "\u041c\u043e\u043d\u0434\u0438\u043d-\u0434\u0430-\u0411\u0435\u0439\u0440\u0430"
    ],
    "name:spa_x_preferred":[
        "Mondim da Beira"
    ],
    "name:tur_x_preferred":[
        "Mondim da Beira"
    ],
    "qs_pg:aaroncc":"PT",
    "qs_pg:gn_country":"PT",
    "qs_pg:gn_fcode":"PPL",
    "qs_pg:gn_pop":0,
    "qs_pg:name":"Mondim da Beira",
    "qs_pg:name_adm0":"Portugal",
    "qs_pg:name_adm1":"Viseu",
    "qs_pg:photos_9r":0,
    "qs_pg:photos_sr":0,
    "qs_pg:pop_sr":0,
    "qs_pg:qs_pg_placetype":"locality",
    "qs_pg:qs_pg_placetype_gp":"Town",
    "qs_pg:woe_adm0":23424925,
    "woe:adm0_id":23424925,
    "woe:name_adm0":"Portugal",
    "woe:name_adm1":"Viseu",
    "woe:placetype":"Town",
    "wof:name":"Mondim da Beira",
    "wof:placetype":"locality"
},
  "geometry": {"coordinates":[-7.74546,41.01946],"type":"Point"}
}