{
  "type": "Feature",
  "properties": {
    "gn:admin1_code":"14",
    "gn:admin2_code":"1111",
    "gn:admin3_code":"111111.0",
    "gn:asciiname":"Varzea de Baixo",
    "gn:country_code":"PT",
    "gn:dem":156,
    "gn:feature_class":"P",
    "gn:feature_code":"PPL",
    "gn:name":"V\u00e1rzea de Baixo",
    "gn:population":0,
    "gn:timezone":"Europe/Lisbon",
    "iso:country":"PT",
    "wof:name":"Varzea de Baixo",
    "wof:placetype":"locality"
},
  "geometry": {"coordinates":[-9.40282,38.82717],"type":"Point"}
}