{
  "type": "Feature",
  "properties": {
    "gn:admin1_code":"14",
    "gn:admin2_code":"1109",
    "gn:admin3_code":"110913.0",
    "gn:asciiname":"Casais",
    "gn:country_code":"PT",
    "gn:dem":67,
    "gn:feature_class":"P",
    "gn:feature_code":"PPL",
    "gn:name":"Casais",
    "gn:population":0,
    "gn:timezone":"Europe/Lisbon",
    "iso:country":"PT",
    "wof:name":"Casais",
    "wof:placetype":"locality"
},
  "geometry": {"coordinates":[-9.36667,38.98333],"type":"Point"}
}