{
  "type": "Feature",
  "properties": {
    "gn:admin1_code":"20",
    "gn:admin2_code":"1609",
    "gn:admin3_code":"160932.0",
    "gn:asciiname":"Ribeira",
    "gn:country_code":"PT",
    "gn:dem":15,
    "gn:feature_class":"P",
    "gn:feature_code":"PPL",
    "gn:name":"Ribeira",
    "gn:population":0,
    "gn:timezone":"Europe/Lisbon",
    "iso:country":"PT",
    "wof:name":"Ribeira",
    "wof:placetype":"locality"
},
  "geometry": {"coordinates":[-8.75574,41.70365],"type":"Point"}
}