{
  "type": "Feature",
  "properties": {
    "gn:admin1_code":"07",
    "gn:admin2_code":"0610",
    "gn:admin3_code":"61010.0",
    "gn:asciiname":"Porto Mieiro",
    "gn:country_code":"PT",
    "gn:dem":75,
    "gn:feature_class":"P",
    "gn:feature_code":"PPL",
    "gn:name":"Porto Mieiro",
    "gn:population":0,
    "gn:timezone":"Europe/Lisbon",
    "iso:country":"PT",
    "wof:name":"Porto Mieiro",
    "wof:placetype":"locality"
},
  "geometry": {"coordinates":[-8.68351,40.24578],"type":"Point"}
}