{
  "type": "Feature",
  "properties": {
    "gn:admin1_code":"18",
    "gn:admin2_code":"1407",
    "gn:admin3_code":"140705.0",
    "gn:asciiname":"Meirinho",
    "gn:country_code":"PT",
    "gn:dem":44,
    "gn:feature_class":"P",
    "gn:feature_code":"PPL",
    "gn:name":"Meirinho",
    "gn:population":0,
    "gn:timezone":"Europe/Lisbon",
    "iso:country":"PT",
    "wof:name":"Meirinho",
    "wof:placetype":"locality"
},
  "geometry": {"coordinates":[-8.53484,39.27691],"type":"Point"}
}