{
  "type": "Feature",
  "properties": {
    "gn:admin1_code":"4.0",
    "gn:admin2_code":"0313",
    "gn:admin3_code":"31352.0",
    "gn:asciiname":"Cruz",
    "gn:country_code":"PT",
    "gn:dem":54,
    "gn:feature_class":"P",
    "gn:feature_code":"PPL",
    "gn:name":"Cruz",
    "gn:population":0,
    "gn:timezone":"Europe/Lisbon",
    "iso:country":"PT",
    "name:ces_x_preferred":[
        "Cruz"
    ],
    "name:deu_x_preferred":[
        "Cruz"
    ],
    "wof:name":"Cruz",
    "wof:placetype":"locality"
},
  "geometry": {"coordinates":[-8.44286,41.61583],"type":"Point"}
}