{
  "type": "Feature",
  "properties": {
    "gn:admin1_code":"11.0",
    "gn:admin2_code":"0914",
    "gn:admin3_code":"91409.0",
    "gn:asciiname":"Murca",
    "gn:country_code":"PT",
    "gn:dem":259,
    "gn:feature_class":"P",
    "gn:feature_code":"PPL",
    "gn:name":"Mur\u00e7a",
    "gn:population":0,
    "gn:timezone":"Europe/Lisbon",
    "iso:country":"PT",
    "wof:name":"Murca",
    "wof:placetype":"locality"
},
  "geometry": {"coordinates":[-7.2309,41.10173],"type":"Point"}
}