{
  "type": "Feature",
  "properties": {
    "gn:admin1_code":"20",
    "gn:admin2_code":"1608",
    "gn:admin3_code":"160805.0",
    "gn:asciiname":"Valinha",
    "gn:country_code":"PT",
    "gn:dem":147,
    "gn:feature_class":"P",
    "gn:feature_code":"PPL",
    "gn:name":"Valinha",
    "gn:population":0,
    "gn:timezone":"Europe/Lisbon",
    "iso:country":"PT",
    "wof:name":"Valinha",
    "wof:placetype":"locality"
},
  "geometry": {"coordinates":[-8.62561,41.95375],"type":"Point"}
}