{
  "type": "Feature",
  "properties": {
    "gn:admin1_code":"06",
    "gn:admin2_code":"0502",
    "gn:admin3_code":"50223.0",
    "gn:asciiname":"Sarrasqueira",
    "gn:country_code":"PT",
    "gn:dem":284,
    "gn:feature_class":"P",
    "gn:feature_code":"PPL",
    "gn:name":"Sarrasqueira",
    "gn:population":0,
    "gn:timezone":"Europe/Lisbon",
    "iso:country":"PT",
    "wof:name":"Sarrasqueira",
    "wof:placetype":"locality"
},
  "geometry": {"coordinates":[-7.62788,39.87793],"type":"Point"}
}