{
  "type": "Feature",
  "properties": {
    "gn:country":"PT",
    "gn:fcode":"PPL",
    "gn:population":9618,
    "iso:country":"PT",
    "name:ast_x_preferred":[
        "Madalena"
    ],
    "name:cat_x_preferred":[
        "Madalena"
    ],
    "name:ceb_x_preferred":[
        "Madalena"
    ],
    "name:deu_x_preferred":[
        "Madalena"
    ],
    "name:eng_x_preferred":[
        "Madalena"
    ],
    "name:fra_x_preferred":[
        "Madalena"
    ],
    "name:glg_x_preferred":[
        "Madalena"
    ],
    "name:kaz_x_preferred":[
        "\u041c\u0430\u0434\u0430\u043b\u0435\u043d\u0430"
    ],
    "name:nld_x_preferred":[
        "Madalena"
    ],
    "name:por_x_preferred":[
        "Madalena"
    ],
    "name:rus_x_preferred":[
        "\u041c\u0430\u0434\u0430\u043b\u0435\u043d\u0430"
    ],
    "name:spa_x_preferred":[
        "Madalena"
    ],
    "name:zho_x_preferred":[
        "Madalena"
    ],
    "qs_pg:aaroncc":"PT",
    "qs_pg:gn_country":"PT",
    "qs_pg:gn_fcode":"PPL",
    "qs_pg:gn_pop":9618,
    "qs_pg:name":"Madalena",
    "qs_pg:name_adm0":"Portugal",
    "qs_pg:name_adm1":"Porto",
    "qs_pg:photos_9r":0,
    "qs_pg:photos_sr":0,
    "qs_pg:pop_sr":5,
    "qs_pg:qs_pg_placetype":"locality",
    "qs_pg:qs_pg_placetype_gp":"Town",
    "qs_pg:woe_adm0":23424925,
    "woe:adm0_id":23424925,
    "woe:name_adm0":"Portugal",
    "woe:name_adm1":"Porto",
    "woe:placetype":"Town",
    "wof:name":"Madalena",
    "wof:placetype":"locality",
    "wof:population":9618
},
  "geometry": {"coordinates":[-8.33451,41.21616],"type":"Point"}
}