{
  "type": "Feature",
  "properties": {
    "gn:admin1_code":"09",
    "gn:admin2_code":"0801",
    "gn:admin3_code":"80103.0",
    "gn:asciiname":"Alcaria",
    "gn:country_code":"PT",
    "gn:dem":69,
    "gn:feature_class":"P",
    "gn:feature_code":"PPL",
    "gn:name":"Alcaria",
    "gn:population":0,
    "gn:timezone":"Europe/Lisbon",
    "iso:country":"PT",
    "wof:name":"Alcaria",
    "wof:placetype":"locality"
},
  "geometry": {"coordinates":[-8.20498,37.19159000000001],"type":"Point"}
}