{
  "type": "Feature",
  "properties": {
    "gn:admin1_code":"14",
    "gn:admin2_code":"1109",
    "gn:admin3_code":"110905.0",
    "gn:asciiname":"Enxara do Bispo",
    "gn:country_code":"PT",
    "gn:dem":115,
    "gn:feature_class":"P",
    "gn:feature_code":"PPL",
    "gn:name":"Enxara do Bispo",
    "gn:population":0,
    "gn:timezone":"Europe/Lisbon",
    "iso:country":"PT",
    "wof:name":"Enxara do Bispo",
    "wof:placetype":"locality"
},
  "geometry": {"coordinates":[-9.24084,38.99102],"type":"Point"}
}