{
  "type": "Feature",
  "properties": {
    "gn:admin1_code":"22.0",
    "gn:admin2_code":"1823",
    "gn:admin3_code":"182328.0",
    "gn:asciiname":"Esculca",
    "gn:country_code":"PT",
    "gn:dem":456,
    "gn:feature_class":"P",
    "gn:feature_code":"PPL",
    "gn:name":"Esculca",
    "gn:population":0,
    "gn:timezone":"Europe/Lisbon",
    "iso:country":"PT",
    "wof:name":"Esculca",
    "wof:placetype":"locality"
},
  "geometry": {"coordinates":[-7.89201,40.67392],"type":"Point"}
}