{
  "type": "Feature",
  "properties": {
    "gn:admin1_code":"16",
    "gn:admin2_code":"1209",
    "gn:admin3_code":"120903.0",
    "gn:asciiname":"Polvorosas",
    "gn:country_code":"PT",
    "gn:dem":224,
    "gn:feature_class":"P",
    "gn:feature_code":"PPL",
    "gn:name":"Polvorosas",
    "gn:population":0,
    "gn:timezone":"Europe/Lisbon",
    "iso:country":"PT",
    "wof:name":"Polvorosas",
    "wof:placetype":"locality"
},
  "geometry": {"coordinates":[-7.84273,39.38],"type":"Point"}
}