{
  "type": "Feature",
  "properties": {
    "gn:admin1_code":"09",
    "gn:admin2_code":"0802",
    "gn:admin3_code":"80203.0",
    "gn:asciiname":"Barroso",
    "gn:country_code":"PT",
    "gn:dem":266,
    "gn:feature_class":"P",
    "gn:feature_code":"PPL",
    "gn:name":"Barroso",
    "gn:population":0,
    "gn:timezone":"Europe/Lisbon",
    "iso:country":"PT",
    "wof:name":"Barroso",
    "wof:placetype":"locality"
},
  "geometry": {"coordinates":[-7.82624,37.39756],"type":"Point"}
}