{
  "type": "Feature",
  "properties": {
    "gn:admin1_code":"20.0",
    "gn:admin2_code":"1607",
    "gn:admin3_code":"160715.0",
    "gn:asciiname":"Paredes",
    "gn:country_code":"PT",
    "gn:dem":58,
    "gn:feature_class":"P",
    "gn:feature_code":"PPL",
    "gn:name":"Paredes",
    "gn:population":0,
    "gn:timezone":"Europe/Lisbon",
    "iso:country":"PT",
    "name:ast_x_preferred":[
        "Paredes"
    ],
    "name:cat_x_preferred":[
        "Paredes"
    ],
    "name:ceb_x_preferred":[
        "Paredes"
    ],
    "name:deu_x_preferred":[
        "Paredes"
    ],
    "name:eus_x_preferred":[
        "Paredes"
    ],
    "name:fra_x_preferred":[
        "Paredes"
    ],
    "name:glg_x_preferred":[
        "Paredes"
    ],
    "name:heb_x_preferred":[
        "\u05e4\u05d0\u05e8\u05d3\u05e1"
    ],
    "name:hun_x_preferred":[
        "Paredes"
    ],
    "name:ita_x_preferred":[
        "Paredes"
    ],
    "name:msa_x_preferred":[
        "Paredes"
    ],
    "name:nds_x_preferred":[
        "Paredes"
    ],
    "name:nld_x_preferred":[
        "Paredes"
    ],
    "name:pol_x_preferred":[
        "Paredes"
    ],
    "name:por_x_preferred":[
        "Paredes"
    ],
    "name:rus_x_preferred":[
        "\u041f\u0430\u0440\u0435\u0434\u0435\u0441"
    ],
    "name:scn_x_preferred":[
        "Paredes"
    ],
    "name:spa_x_preferred":[
        "Paredes"
    ],
    "name:srp_x_preferred":[
        "\u041f\u0430\u0440\u0435\u0434\u0435\u0441"
    ],
    "name:swe_x_preferred":[
        "Paredes"
    ],
    "name:ukr_x_preferred":[
        "\u041f\u0430\u0440\u0435\u0434\u0435\u0448"
    ],
    "name:vie_x_preferred":[
        "Paredes"
    ],
    "name:war_x_preferred":[
        "Paredes"
    ],
    "wof:name":"Paredes",
    "wof:placetype":"locality"
},
  "geometry": {"coordinates":[-8.59477,41.82],"type":"Point"}
}