{
  "type": "Feature",
  "properties": {
    "gn:admin1_code":"17.0",
    "gn:admin2_code":"1311",
    "gn:admin3_code":"131125.0",
    "gn:asciiname":"Perozelo",
    "gn:country_code":"PT",
    "gn:dem":312,
    "gn:feature_class":"P",
    "gn:feature_code":"PPL",
    "gn:name":"Perozelo",
    "gn:population":0,
    "gn:timezone":"Europe/Lisbon",
    "iso:country":"PT",
    "wof:name":"Perozelo",
    "wof:placetype":"locality"
},
  "geometry": {"coordinates":[-8.26369,41.14998],"type":"Point"}
}