{
  "type": "Feature",
  "properties": {
    "gn:admin1_code":"09",
    "gn:admin2_code":"0814",
    "gn:admin3_code":"81404.0",
    "gn:asciiname":"Casas Novas",
    "gn:country_code":"PT",
    "gn:dem":201,
    "gn:feature_class":"P",
    "gn:feature_code":"PPL",
    "gn:name":"Casas Novas",
    "gn:population":0,
    "gn:timezone":"Europe/Lisbon",
    "iso:country":"PT",
    "wof:name":"Casas Novas",
    "wof:placetype":"locality"
},
  "geometry": {"coordinates":[-7.75381,37.20585],"type":"Point"}
}