{
  "type": "Feature",
  "properties": {
    "gn:admin1_code":"08",
    "gn:admin2_code":"0705",
    "gn:admin3_code":"70503.0",
    "gn:asciiname":"Monte do Bussalfao",
    "gn:country_code":"PT",
    "gn:dem":236,
    "gn:feature_class":"P",
    "gn:feature_code":"PPL",
    "gn:name":"Monte do Bussalf\u00e3o",
    "gn:population":0,
    "gn:timezone":"Europe/Lisbon",
    "iso:country":"PT",
    "wof:name":"Monte do Bussalfao",
    "wof:placetype":"locality"
},
  "geometry": {"coordinates":[-7.75676,38.57821],"type":"Point"}
}