{
  "type": "Feature",
  "properties": {
    "gn:admin1_code":"04",
    "gn:admin2_code":"0303",
    "gn:admin3_code":"30342.0",
    "gn:asciiname":"Santa Tecla",
    "gn:country_code":"PT",
    "gn:dem":184,
    "gn:feature_class":"P",
    "gn:feature_code":"PPL",
    "gn:name":"Santa Tecla",
    "gn:population":0,
    "gn:timezone":"Europe/Lisbon",
    "iso:country":"PT",
    "name:bre_x_preferred":[
        "Santa Tecla"
    ],
    "name:cat_x_preferred":[
        "Santa Tecla"
    ],
    "name:ceb_x_preferred":[
        "Santa Tecla"
    ],
    "name:fra_x_preferred":[
        "Santa Tecla"
    ],
    "name:ita_x_preferred":[
        "Santa Tecla"
    ],
    "name:nah_x_preferred":[
        "Santa Tecla"
    ],
    "name:nld_x_preferred":[
        "Santa Tecla"
    ],
    "name:por_x_preferred":[
        "Santa Tecla"
    ],
    "name:spa_x_preferred":[
        "Santa Tecla"
    ],
    "name:swe_x_preferred":[
        "Santa Tecla"
    ],
    "wof:name":"Santa Tecla",
    "wof:placetype":"locality"
},
  "geometry": {"coordinates":[-8.41667,41.55],"type":"Point"}
}