{
  "type": "Feature",
  "properties": {
    "gn:admin1_code":"04",
    "gn:admin2_code":"0313",
    "gn:admin3_code":"31339.0",
    "gn:asciiname":"Rio Mau",
    "gn:country_code":"PT",
    "gn:dem":242,
    "gn:feature_class":"P",
    "gn:feature_code":"PPL",
    "gn:name":"Rio Mau",
    "gn:population":0,
    "gn:timezone":"Europe/Lisbon",
    "iso:country":"PT",
    "wof:name":"Rio Mau",
    "wof:placetype":"locality"
},
  "geometry": {"coordinates":[-8.51417,41.69362],"type":"Point"}
}