{
  "type": "Feature",
  "properties": {
    "gn:admin1_code":"19",
    "gn:admin2_code":"1509",
    "gn:admin3_code":"150901.0",
    "gn:asciiname":"Quinta da Corona",
    "gn:country_code":"PT",
    "gn:dem":86,
    "gn:feature_class":"P",
    "gn:feature_code":"PPL",
    "gn:name":"Quinta da Corona",
    "gn:population":0,
    "gn:timezone":"Europe/Lisbon",
    "iso:country":"PT",
    "wof:name":"Quinta da Corona",
    "wof:placetype":"locality"
},
  "geometry": {"coordinates":[-8.49887,37.97192],"type":"Point"}
}