{
  "type": "Feature",
  "properties": {
    "gn:admin1_code":"4.0",
    "gn:asciiname":"Ardegao",
    "gn:country_code":"PT",
    "gn:dem":189,
    "gn:feature_class":"P",
    "gn:feature_code":"PPL",
    "gn:name":"Ardeg\u00e3o",
    "gn:population":0,
    "gn:timezone":"Europe/Lisbon",
    "iso:country":"PT",
    "wof:name":"Ardegao",
    "wof:placetype":"locality"
},
  "geometry": {"coordinates":[-8.60275,41.64629],"type":"Point"}
}