{
  "type": "Feature",
  "properties": {
    "gn:admin1_code":"22.0",
    "gn:admin2_code":"1801",
    "gn:admin3_code":"180101.0",
    "gn:asciiname":"Aldeia de Baixo",
    "gn:country_code":"PT",
    "gn:dem":562,
    "gn:feature_class":"P",
    "gn:feature_code":"PPL",
    "gn:name":"Aldeia de Baixo",
    "gn:population":0,
    "gn:timezone":"Europe/Lisbon",
    "iso:country":"PT",
    "wof:name":"Aldeia de Baixo",
    "wof:placetype":"locality"
},
  "geometry": {"coordinates":[-7.71399,41.11731],"type":"Point"}
}