{
  "type": "Feature",
  "properties": {
    "gn:admin1_code":"23.0",
    "gn:admin2_code":"4302",
    "gn:admin3_code":"430207.0",
    "gn:asciiname":"Santa Rita",
    "gn:cc2":"PT",
    "gn:country_code":"PT",
    "gn:dem":71,
    "gn:feature_class":"P",
    "gn:feature_code":"PPL",
    "gn:name":"Santa Rita",
    "gn:population":0,
    "gn:timezone":"Atlantic/Azores",
    "iso:country":"PT",
    "name:und_x_variant":[
        "Santa Ritta",
        "Santa Rita"
    ],
    "wof:name":"Santa Rita",
    "wof:placetype":"locality"
},
  "geometry": {"coordinates":[-27.08333,38.75],"type":"Point"}
}