{
  "type": "Feature",
  "properties": {
    "gn:admin1_code":"17.0",
    "gn:admin2_code":"1304",
    "gn:admin3_code":"130408.0",
    "gn:asciiname":"Maceda",
    "gn:country_code":"PT",
    "gn:dem":83,
    "gn:feature_class":"P",
    "gn:feature_code":"PPL",
    "gn:name":"Maceda",
    "gn:population":0,
    "gn:timezone":"Europe/Lisbon",
    "iso:country":"PT",
    "name:ceb_x_preferred":[
        "Maceda"
    ],
    "name:deu_x_preferred":[
        "Maceda"
    ],
    "name:glg_x_preferred":[
        "Maceda"
    ],
    "name:nld_x_preferred":[
        "Maceda"
    ],
    "name:pol_x_preferred":[
        "Maceda"
    ],
    "name:por_x_preferred":[
        "Maceda"
    ],
    "name:rus_x_preferred":[
        "\u041c\u0430\u0441\u0435\u0434\u0430"
    ],
    "name:spa_x_preferred":[
        "Maceda"
    ],
    "name:ukr_x_preferred":[
        "\u041c\u0430\u0441\u0435\u0434\u0430"
    ],
    "name:war_x_preferred":[
        "Maceda"
    ],
    "wof:name":"Maceda",
    "wof:placetype":"locality"
},
  "geometry": {"coordinates":[-8.56667,41.16667],"type":"Point"}
}