{
  "type": "Feature",
  "properties": {
    "gn:admin1_code":"17.0",
    "gn:admin2_code":"1317",
    "gn:admin3_code":"131713.0",
    "gn:asciiname":"Leiroz",
    "gn:country_code":"PT",
    "gn:dem":158,
    "gn:feature_class":"P",
    "gn:feature_code":"PPL",
    "gn:name":"Leiroz",
    "gn:population":0,
    "gn:timezone":"Europe/Lisbon",
    "iso:country":"PT",
    "wof:name":"Leiroz",
    "wof:placetype":"locality"
},
  "geometry": {"coordinates":[-8.55697,41.05225],"type":"Point"}
}