{
  "type": "Feature",
  "properties": {
    "gn:admin1_code":"16",
    "gn:admin2_code":"1211",
    "gn:admin3_code":"121102.0",
    "gn:asciiname":"Morenos",
    "gn:country_code":"PT",
    "gn:dem":289,
    "gn:feature_class":"P",
    "gn:feature_code":"PPL",
    "gn:name":"Morenos",
    "gn:population":0,
    "gn:timezone":"Europe/Lisbon",
    "iso:country":"PT",
    "wof:name":"Morenos",
    "wof:placetype":"locality"
},
  "geometry": {"coordinates":[-7.38469,38.98226],"type":"Point"}
}