{
  "type": "Feature",
  "properties": {
    "gn:admin1_code":"09",
    "gn:admin2_code":"0809",
    "gn:admin3_code":"80903.0",
    "gn:asciiname":"Cha da Casinha",
    "gn:country_code":"PT",
    "gn:dem":137,
    "gn:feature_class":"P",
    "gn:feature_code":"PPL",
    "gn:name":"Ch\u00e3 da Casinha",
    "gn:population":0,
    "gn:timezone":"Europe/Lisbon",
    "iso:country":"PT",
    "wof:name":"Cha da Casinha",
    "wof:placetype":"locality"
},
  "geometry": {"coordinates":[-8.63735,37.36973],"type":"Point"}
}