{
  "type": "Feature",
  "properties": {
    "gn:admin1_code":"14",
    "gn:admin2_code":"1111",
    "gn:admin3_code":"111112.0",
    "gn:asciiname":"Penha Longa",
    "gn:country_code":"PT",
    "gn:dem":171,
    "gn:feature_class":"P",
    "gn:feature_code":"PPL",
    "gn:name":"Penha Longa",
    "gn:population":0,
    "gn:timezone":"Europe/Lisbon",
    "iso:country":"PT",
    "wof:name":"Penha Longa",
    "wof:placetype":"locality"
},
  "geometry": {"coordinates":[-9.3968,38.76104],"type":"Point"}
}