{
  "type": "Feature",
  "properties": {
    "gn:admin1_code":"09",
    "gn:admin2_code":"0810",
    "gn:admin3_code":"81002.0",
    "gn:asciiname":"Areias",
    "gn:country_code":"PT",
    "gn:dem":26,
    "gn:feature_class":"P",
    "gn:feature_code":"PPL",
    "gn:name":"Areias",
    "gn:population":0,
    "gn:timezone":"Europe/Lisbon",
    "iso:country":"PT",
    "wof:name":"Areias",
    "wof:placetype":"locality"
},
  "geometry": {"coordinates":[-7.75901,37.0742],"type":"Point"}
}