{
  "type": "Feature",
  "properties": {
    "gn:admin1_code":"20.0",
    "gn:admin2_code":"1605",
    "gn:admin3_code":"160504.0",
    "gn:asciiname":"Nogueira",
    "gn:country_code":"PT",
    "gn:dem":204,
    "gn:feature_class":"P",
    "gn:feature_code":"PPL",
    "gn:name":"Nogueira",
    "gn:population":0,
    "gn:timezone":"Europe/Lisbon",
    "iso:country":"PT",
    "name:cat_x_preferred":[
        "Nogueira"
    ],
    "name:ceb_x_preferred":[
        "Nogueira"
    ],
    "name:deu_x_preferred":[
        "Nogueira"
    ],
    "name:fra_x_preferred":[
        "Nogueira"
    ],
    "name:glg_x_preferred":[
        "Nogueira"
    ],
    "name:jpn_x_preferred":[
        "\u30ce\u30b2\u30a4\u30e9"
    ],
    "name:nld_x_preferred":[
        "Nogueira"
    ],
    "name:por_x_preferred":[
        "Nogueira"
    ],
    "name:rus_x_preferred":[
        "\u041d\u043e\u0433\u0435\u0439\u0440\u0430"
    ],
    "name:spa_x_preferred":[
        "Nogueira"
    ],
    "name:swe_x_preferred":[
        "Nogueira"
    ],
    "name:tur_x_preferred":[
        "Nogueira"
    ],
    "name:ukr_x_preferred":[
        "\u041d\u043e\u0433\u0435\u0439\u0440\u0430"
    ],
    "wof:name":"Nogueira",
    "wof:placetype":"locality"
},
  "geometry": {"coordinates":[-8.63189,41.90949000000001],"type":"Point"}
}