{
  "type": "Feature",
  "properties": {
    "gn:admin1_code":"13",
    "gn:admin2_code":"1013",
    "gn:admin3_code":"101302.0",
    "gn:asciiname":"Ervideira",
    "gn:country_code":"PT",
    "gn:dem":477,
    "gn:feature_class":"P",
    "gn:feature_code":"PPL",
    "gn:name":"Ervideira",
    "gn:population":0,
    "gn:timezone":"Europe/Lisbon",
    "iso:country":"PT",
    "wof:name":"Ervideira",
    "wof:placetype":"locality"
},
  "geometry": {"coordinates":[-8.15423,40.00394],"type":"Point"}
}