{
  "type": "Feature",
  "properties": {
    "gn:admin1_code":"06",
    "gn:admin2_code":"0502",
    "gn:admin3_code":"50216.0",
    "gn:asciiname":"Monforte da Beira",
    "gn:country_code":"PT",
    "gn:dem":310,
    "gn:feature_class":"P",
    "gn:feature_code":"PPL",
    "gn:name":"Monforte da Beira",
    "gn:population":0,
    "gn:timezone":"Europe/Lisbon",
    "iso:country":"PT",
    "wof:name":"Monforte da Beira",
    "wof:placetype":"locality"
},
  "geometry": {"coordinates":[-7.2991,39.73913],"type":"Point"}
}