{
  "type": "Feature",
  "properties": {
    "gn:admin1_code":"13",
    "gn:admin2_code":"1015",
    "gn:admin3_code":"101509.0",
    "gn:asciiname":"Carrinhos",
    "gn:country_code":"PT",
    "gn:dem":148,
    "gn:feature_class":"P",
    "gn:feature_code":"PPL",
    "gn:name":"Carrinhos",
    "gn:population":0,
    "gn:timezone":"Europe/Lisbon",
    "iso:country":"PT",
    "wof:name":"Carrinhos",
    "wof:placetype":"locality"
},
  "geometry": {"coordinates":[-8.66842,39.88816],"type":"Point"}
}