{
  "type": "Feature",
  "properties": {
    "gn:admin1_code":"11.0",
    "gn:admin2_code":"0910",
    "gn:admin3_code":"91001.0",
    "gn:asciiname":"Alverca",
    "gn:country_code":"PT",
    "gn:dem":611,
    "gn:feature_class":"P",
    "gn:feature_code":"PPL",
    "gn:name":"Alverca",
    "gn:population":0,
    "gn:timezone":"Europe/Lisbon",
    "iso:country":"PT",
    "wof:name":"Alverca",
    "wof:placetype":"locality"
},
  "geometry": {"coordinates":[-7.21669,40.70092],"type":"Point"}
}