{
  "type": "Feature",
  "properties": {
    "gn:admin1_code":"14",
    "gn:admin2_code":"1111",
    "gn:admin3_code":"111110.0",
    "gn:asciiname":"Odrinhas",
    "gn:country_code":"PT",
    "gn:dem":159,
    "gn:feature_class":"P",
    "gn:feature_code":"PPL",
    "gn:name":"Odrinhas",
    "gn:population":0,
    "gn:timezone":"Europe/Lisbon",
    "iso:country":"PT",
    "wof:name":"Odrinhas",
    "wof:placetype":"locality"
},
  "geometry": {"coordinates":[-9.37134,38.88244],"type":"Point"}
}