{
  "type": "Feature",
  "properties": {
    "gn:gn_country":"PT",
    "gn:gn_fcode":"PPL",
    "gn:gn_pop":0,
    "iso:country":"PT",
    "name:ceb_x_preferred":[
        "Lomba"
    ],
    "name:deu_x_preferred":[
        "Lomba"
    ],
    "name:fra_x_preferred":[
        "Lomba"
    ],
    "name:glg_x_preferred":[
        "Lomba"
    ],
    "name:nld_x_preferred":[
        "Lomba"
    ],
    "name:por_x_preferred":[
        "Lomba"
    ],
    "name:rus_x_preferred":[
        "\u041b\u043e\u043c\u0431\u0430"
    ],
    "name:swe_x_preferred":[
        "Lomba"
    ],
    "qs_pg:aaroncc":"PT",
    "qs_pg:gn_country":"PT",
    "qs_pg:gn_fcode":"PPL",
    "qs_pg:gn_pop":0,
    "qs_pg:name":"Lomba",
    "qs_pg:name_adm0":"Portugal",
    "qs_pg:name_adm1":"Viana do Castelo",
    "qs_pg:photos":61,
    "qs_pg:photos_1k":12,
    "qs_pg:photos_9k":1,
    "qs_pg:photos_9r":2,
    "qs_pg:photos_all":61,
    "qs_pg:photos_sr":2,
    "qs_pg:pop_sr":0,
    "qs_pg:qs_pg_placetype":"locality",
    "qs_pg:qs_pg_placetype_gp":"Town",
    "qs_pg:woe_adm0":23424925,
    "woe:adm0_id":23424925,
    "woe:name_adm0":"Portugal",
    "woe:name_adm1":"Viana do Castelo",
    "woe:placetype":"Town",
    "wof:name":"Lomba",
    "wof:placetype":"locality"
},
  "geometry": {"coordinates":[-8.84024,41.81808],"type":"Point"}
}