{
  "type": "Feature",
  "properties": {
    "gn:admin1_code":"4.0",
    "gn:admin2_code":"0308",
    "gn:admin3_code":"30873.0",
    "gn:asciiname":"Alem",
    "gn:country_code":"PT",
    "gn:dem":128,
    "gn:feature_class":"P",
    "gn:feature_code":"PPL",
    "gn:name":"Al\u00e9m",
    "gn:population":0,
    "gn:timezone":"Europe/Lisbon",
    "iso:country":"PT",
    "name:fas_x_preferred":[
        "\u0627\u0644\u06cc\u0645"
    ],
    "name:fra_x_preferred":[
        "Alem"
    ],
    "name:nld_x_preferred":[
        "Alem"
    ],
    "name:por_x_preferred":[
        "Alem"
    ],
    "wof:name":"Alem",
    "wof:placetype":"locality"
},
  "geometry": {"coordinates":[-8.34655,41.46528],"type":"Point"}
}