{
  "type": "Feature",
  "properties": {
    "gn:admin1_code":"22",
    "gn:admin2_code":"1817",
    "gn:admin3_code":"181708.0",
    "gn:asciiname":"Ras",
    "gn:country_code":"PT",
    "gn:dem":649,
    "gn:feature_class":"P",
    "gn:feature_code":"PPL",
    "gn:name":"R\u00e3s",
    "gn:population":0,
    "gn:timezone":"Europe/Lisbon",
    "iso:country":"PT",
    "wof:name":"Ras",
    "wof:placetype":"locality"
},
  "geometry": {"coordinates":[-7.63738,40.76208],"type":"Point"}
}