{
  "type": "Feature",
  "properties": {
    "gn:admin1_code":"19",
    "gn:admin2_code":"1503",
    "gn:admin3_code":"150309.0",
    "gn:asciiname":"Marco Cabaco",
    "gn:country_code":"PT",
    "gn:dem":75,
    "gn:feature_class":"P",
    "gn:feature_code":"PPL",
    "gn:name":"Marco Caba\u00e7o",
    "gn:population":0,
    "gn:timezone":"Europe/Lisbon",
    "iso:country":"PT",
    "wof:name":"Marco Cabaco",
    "wof:placetype":"locality"
},
  "geometry": {"coordinates":[-9.19173,38.61609],"type":"Point"}
}