{
  "type": "Feature",
  "properties": {
    "gn:gn_country":"PT",
    "gn:gn_fcode":"PPL",
    "gn:gn_pop":0,
    "iso:country":"PT",
    "name:unk_x_variant":[
        "Vale do Para\u00edso"
    ],
    "qs_pg:aaroncc":"PT",
    "qs_pg:gn_country":"PT",
    "qs_pg:gn_fcode":"PPL",
    "qs_pg:gn_pop":0,
    "qs_pg:name":"Vale do Prado",
    "qs_pg:name_adm0":"Portugal",
    "qs_pg:name_adm1":"Leiria",
    "qs_pg:photos_9r":0,
    "qs_pg:photos_sr":0,
    "qs_pg:pop_sr":0,
    "qs_pg:qs_pg_placetype":"locality",
    "qs_pg:qs_pg_placetype_gp":"Town",
    "qs_pg:woe_adm0":23424925,
    "woe:adm0_id":23424925,
    "woe:name_adm0":"Portugal",
    "woe:name_adm1":"Leiria",
    "woe:placetype":"Town",
    "wof:name":"Vale do Prado",
    "wof:placetype":"locality"
},
  "geometry": {"coordinates":[-8.88575,39.11529],"type":"Point"}
}