{
  "type": "Feature",
  "properties": {
    "gn:admin1_code":"17.0",
    "gn:admin2_code":"1317",
    "gn:admin3_code":"131717.0",
    "gn:asciiname":"Moinhos",
    "gn:country_code":"PT",
    "gn:dem":63,
    "gn:feature_class":"P",
    "gn:feature_code":"PPL",
    "gn:name":"Moinhos",
    "gn:population":0,
    "gn:timezone":"Europe/Lisbon",
    "iso:country":"PT",
    "wof:name":"Moinhos",
    "wof:placetype":"locality"
},
  "geometry": {"coordinates":[-8.62566,41.04129],"type":"Point"}
}