{
  "type": "Feature",
  "properties": {
    "gn:admin1_code":"03",
    "gn:admin2_code":"0202",
    "gn:admin3_code":"20207.0",
    "gn:asciiname":"Senhora da Graca dos Padroes",
    "gn:country_code":"PT",
    "gn:dem":206,
    "gn:feature_class":"P",
    "gn:feature_code":"PPL",
    "gn:name":"Senhora da Gra\u00e7a dos Padr\u00f5es",
    "gn:population":0,
    "gn:timezone":"Europe/Lisbon",
    "iso:country":"PT",
    "wof:name":"Senhora da Graca dos Padroes",
    "wof:placetype":"locality"
},
  "geometry": {"coordinates":[-7.97133,37.56481],"type":"Point"}
}