{
  "type": "Feature",
  "properties": {
    "gn:admin1_code":"21.0",
    "gn:admin2_code":"1703",
    "gn:admin3_code":"170312.0",
    "gn:asciiname":"Fundo de Vila",
    "gn:country_code":"PT",
    "gn:dem":534,
    "gn:feature_class":"P",
    "gn:feature_code":"PPL",
    "gn:name":"Fundo de Vila",
    "gn:population":0,
    "gn:timezone":"Europe/Lisbon",
    "iso:country":"PT",
    "wof:name":"Fundo de Vila",
    "wof:placetype":"locality"
},
  "geometry": {"coordinates":[-7.51068,41.81089],"type":"Point"}
}