{
  "type": "Feature",
  "properties": {
    "gn:admin1_code":"18",
    "gn:admin2_code":"1403",
    "gn:admin3_code":"140304.0",
    "gn:asciiname":"Monte da Varzea",
    "gn:country_code":"PT",
    "gn:dem":30,
    "gn:feature_class":"P",
    "gn:feature_code":"PPL",
    "gn:name":"Monte da V\u00e1rzea",
    "gn:population":0,
    "gn:timezone":"Europe/Lisbon",
    "iso:country":"PT",
    "wof:name":"Monte da Varzea",
    "wof:placetype":"locality"
},
  "geometry": {"coordinates":[-8.55,39.11736],"type":"Point"}
}