{
  "type": "Feature",
  "properties": {
    "gn:admin1_code":"14",
    "gn:admin2_code":"1105",
    "gn:admin3_code":"110502.0",
    "gn:asciiname":"Sao Juliao da Barra",
    "gn:cc2":"PT",
    "gn:country_code":"PT",
    "gn:dem":13,
    "gn:feature_class":"P",
    "gn:feature_code":"PPL",
    "gn:name":"S\u00e3o Juli\u00e3o da Barra",
    "gn:population":0,
    "gn:timezone":"Europe/Lisbon",
    "iso:country":"PT",
    "name:und_x_variant":[
        "S\u00e3o Juli\u00e3o",
        "Torre de S\u00e3o Juli\u00e3o",
        "S\u00e3o Juli\u00e3o da Barra"
    ],
    "wof:name":"Sao Juliao da Barra",
    "wof:placetype":"locality"
},
  "geometry": {"coordinates":[-9.33333,38.68333],"type":"Point"}
}