{
  "type": "Feature",
  "properties": {
    "gn:admin1_code":"04",
    "gn:admin2_code":"0309",
    "gn:admin3_code":"30901.0",
    "gn:asciiname":"Rabuide",
    "gn:country_code":"PT",
    "gn:dem":77,
    "gn:feature_class":"P",
    "gn:feature_code":"PPL",
    "gn:name":"Rabuide",
    "gn:population":0,
    "gn:timezone":"Europe/Lisbon",
    "iso:country":"PT",
    "wof:name":"Rabuide",
    "wof:placetype":"locality"
},
  "geometry": {"coordinates":[-8.33528,41.61403],"type":"Point"}
}