{
  "type": "Feature",
  "properties": {
    "gn:admin1_code":"09",
    "gn:admin2_code":"0813",
    "gn:admin3_code":"81306.0",
    "gn:asciiname":"Monte Velho",
    "gn:country_code":"PT",
    "gn:dem":145,
    "gn:feature_class":"P",
    "gn:feature_code":"PPL",
    "gn:name":"Monte Velho",
    "gn:population":0,
    "gn:timezone":"Europe/Lisbon",
    "iso:country":"PT",
    "wof:name":"Monte Velho",
    "wof:placetype":"locality"
},
  "geometry": {"coordinates":[-8.41777,37.3749],"type":"Point"}
}