{
  "type": "Feature",
  "properties": {
    "gn:country":"PT",
    "gn:fcode":"PPL",
    "gn:population":0,
    "iso:country":"PT",
    "name:ast_x_preferred":[
        "Idanha-a-Velha"
    ],
    "name:ceb_x_preferred":[
        "Idanha-A-Velha"
    ],
    "name:deu_x_preferred":[
        "Idanha-a-Velha"
    ],
    "name:eng_x_preferred":[
        "Idanha-a-Velha"
    ],
    "name:epo_x_preferred":[
        "Idanha-a-Velha"
    ],
    "name:fra_x_preferred":[
        "Idanha-a-Velha"
    ],
    "name:glg_x_preferred":[
        "Idanha-a-Velha"
    ],
    "name:kaz_x_preferred":[
        "\u0418\u0434\u0430\u043d\u044c\u044f-\u0430-\u0412\u0435\u043b\u044c\u044f"
    ],
    "name:lat_x_preferred":[
        "Aegitania"
    ],
    "name:nld_x_preferred":[
        "Idanha-a-Velha"
    ],
    "name:nob_x_preferred":[
        "Idanha-a-Velha"
    ],
    "name:por_x_preferred":[
        "Idanha-a-Velha"
    ],
    "name:rus_x_preferred":[
        "\u0418\u0434\u0430\u043d\u044c\u044f-\u0430-\u0412\u0435\u043b\u044c\u044f"
    ],
    "name:spa_x_preferred":[
        "Idanha-a-Velha"
    ],
    "qs_pg:aaroncc":"PT",
    "qs_pg:gn_country":"PT",
    "qs_pg:gn_fcode":"PPL",
    "qs_pg:gn_pop":0,
    "qs_pg:name":"Idanha-a-Velha",
    "qs_pg:name_adm0":"Portugal",
    "qs_pg:name_adm1":"Castelo Branco",
    "qs_pg:photos":443,
    "qs_pg:photos_1k":90,
    "qs_pg:photos_9k":2,
    "qs_pg:photos_9r":5,
    "qs_pg:photos_all":443,
    "qs_pg:photos_sr":6,
    "qs_pg:pop_sr":0,
    "qs_pg:qs_pg_placetype":"locality",
    "qs_pg:qs_pg_placetype_gp":"Town",
    "qs_pg:woe_adm0":23424925,
    "woe:adm0_id":23424925,
    "woe:name_adm0":"Portugal",
    "woe:name_adm1":"Castelo Branco",
    "woe:placetype":"Town",
    "wof:name":"Idanha-a-Velha",
    "wof:placetype":"locality"
},
  "geometry": {"coordinates":[-7.14348,39.99652],"type":"Point"}
}