{
  "type": "Feature",
  "properties": {
    "gn:admin1_code":"13",
    "gn:admin2_code":"1015",
    "gn:admin3_code":"101517.0",
    "gn:asciiname":"Sobral",
    "gn:country_code":"PT",
    "gn:dem":134,
    "gn:feature_class":"P",
    "gn:feature_code":"PPL",
    "gn:name":"Sobral",
    "gn:population":0,
    "gn:timezone":"Europe/Lisbon",
    "iso:country":"PT",
    "wof:name":"Sobral",
    "wof:placetype":"locality"
},
  "geometry": {"coordinates":[-8.78333,39.91667],"type":"Point"}
}