{
  "type": "Feature",
  "properties": {
    "gn:admin1_code":"13",
    "gn:admin2_code":"1015",
    "gn:admin3_code":"101517.0",
    "gn:asciiname":"Sobral",
    "gn:country_code":"PT",
    "gn:dem":134,
    "gn:feature_class":"P",
    "gn:feature_code":"PPL",
    "gn:name":"Sobral",
    "gn:population":0,
    "gn:timezone":"Europe/Lisbon",
    "iso:country":"PT",
    "name:ara_x_preferred":[
        "\u0633\u0648\u0628\u0631\u0627\u0644"
    ],
    "name:bpy_x_preferred":[
        "\u09b8\u09cb\u09ac\u09cd\u09b0\u09be\u09b2"
    ],
    "name:ceb_x_preferred":[
        "Sobral"
    ],
    "name:deu_x_preferred":[
        "Sobral"
    ],
    "name:fra_x_preferred":[
        "Sobral"
    ],
    "name:glg_x_preferred":[
        "Sobral"
    ],
    "name:heb_x_preferred":[
        "\u05e1\u05d5\u05d1\u05e8\u05d0\u05dc"
    ],
    "name:hin_x_preferred":[
        "\u0938\u094b\u092c\u094d\u0930\u093e\u0932"
    ],
    "name:kor_x_preferred":[
        "\uc18c\ube0c\ub784"
    ],
    "name:mlg_x_preferred":[
        "Sobral"
    ],
    "name:nld_x_preferred":[
        "Sobral"
    ],
    "name:pol_x_preferred":[
        "Sobral"
    ],
    "name:por_x_preferred":[
        "Sobral"
    ],
    "name:rus_x_preferred":[
        "\u0421\u043e\u0431\u0440\u0430\u043b"
    ],
    "name:spa_x_preferred":[
        "Sobral"
    ],
    "name:swe_x_preferred":[
        "Sobral"
    ],
    "name:ukr_x_preferred":[
        "\u0421\u043e\u0431\u0440\u0430\u043b"
    ],
    "wof:name":"Sobral",
    "wof:placetype":"locality"
},
  "geometry": {"coordinates":[-8.78333,39.91667],"type":"Point"}
}