{
  "type": "Feature",
  "properties": {
    "gn:admin1_code":"09",
    "gn:admin2_code":"0805",
    "gn:admin3_code":"80502.0",
    "gn:asciiname":"Porto do Carro",
    "gn:country_code":"PT",
    "gn:dem":57,
    "gn:feature_class":"P",
    "gn:feature_code":"PPL",
    "gn:name":"Porto do Carro",
    "gn:population":0,
    "gn:timezone":"Europe/Lisbon",
    "iso:country":"PT",
    "wof:name":"Porto do Carro",
    "wof:placetype":"locality"
},
  "geometry": {"coordinates":[-7.91315,37.08736],"type":"Point"}
}