{
  "type": "Feature",
  "properties": {
    "gn:admin1_code":"18",
    "gn:admin2_code":"1416",
    "gn:admin3_code":"141613.0",
    "gn:asciiname":"Mocarria",
    "gn:country_code":"PT",
    "gn:dem":102,
    "gn:feature_class":"P",
    "gn:feature_code":"PPL",
    "gn:name":"Mo\u00e7arria",
    "gn:population":0,
    "gn:timezone":"Europe/Lisbon",
    "iso:country":"PT",
    "name:ceb_x_preferred":[
        "Mo\u00e7arria"
    ],
    "name:deu_x_preferred":[
        "Mo\u00e7arria"
    ],
    "name:fra_x_preferred":[
        "Mo\u00e7arria"
    ],
    "name:kaz_x_preferred":[
        "\u041c\u043e\u0441\u0430\u0440\u0440\u0438\u044f"
    ],
    "name:nld_x_preferred":[
        "Mo\u00e7arria"
    ],
    "name:por_x_preferred":[
        "Mo\u00e7arria"
    ],
    "name:rus_x_preferred":[
        "\u041c\u043e\u0441\u0430\u0440\u0440\u0438\u044f"
    ],
    "name:spa_x_preferred":[
        "Mo\u00e7arria"
    ],
    "name:tur_x_preferred":[
        "Mo\u00e7arria"
    ],
    "wof:name":"Mocarria",
    "wof:placetype":"locality"
},
  "geometry": {"coordinates":[-8.77574,39.28221],"type":"Point"}
}