{
  "type": "Feature",
  "properties": {
    "gn:admin1_code":"22.0",
    "gn:admin2_code":"1811",
    "gn:admin3_code":"181103.0",
    "gn:asciiname":"Esmolfe",
    "gn:country_code":"PT",
    "gn:dem":558,
    "gn:feature_class":"P",
    "gn:feature_code":"PPL",
    "gn:name":"Esmolfe",
    "gn:population":0,
    "gn:timezone":"Europe/Lisbon",
    "iso:country":"PT",
    "wof:name":"Esmolfe",
    "wof:placetype":"locality"
},
  "geometry": {"coordinates":[-7.68324,40.67977],"type":"Point"}
}