{
  "type": "Feature",
  "properties": {
    "gn:admin1_code":"21.0",
    "gn:admin2_code":"1703",
    "gn:admin3_code":"170339.0",
    "gn:asciiname":"Argemil",
    "gn:country_code":"PT",
    "gn:dem":863,
    "gn:feature_class":"P",
    "gn:feature_code":"PPL",
    "gn:name":"Argemil",
    "gn:population":0,
    "gn:timezone":"Europe/Lisbon",
    "iso:country":"PT",
    "wof:name":"Argemil",
    "wof:placetype":"locality"
},
  "geometry": {"coordinates":[-7.29329,41.83464],"type":"Point"}
}