{
  "type": "Feature",
  "properties": {
    "gn:admin1_code":"21.0",
    "gn:admin2_code":"1712",
    "gn:admin3_code":"171209.0",
    "gn:asciiname":"Ervoes",
    "gn:country_code":"PT",
    "gn:dem":647,
    "gn:feature_class":"P",
    "gn:feature_code":"PPL",
    "gn:name":"Erv\u00f5es",
    "gn:population":0,
    "gn:timezone":"Europe/Lisbon",
    "iso:country":"PT",
    "wof:name":"Ervoes",
    "wof:placetype":"locality"
},
  "geometry": {"coordinates":[-7.35729,41.65534],"type":"Point"}
}