{
  "type": "Feature",
  "properties": {
    "gn:admin1_code":"06",
    "gn:admin2_code":"0502",
    "gn:admin3_code":"50220.0",
    "gn:asciiname":"Salgueiro do Campo",
    "gn:country_code":"PT",
    "gn:dem":357,
    "gn:feature_class":"P",
    "gn:feature_code":"PPL",
    "gn:name":"Salgueiro do Campo",
    "gn:population":0,
    "gn:timezone":"Europe/Lisbon",
    "iso:country":"PT",
    "wof:name":"Salgueiro do Campo",
    "wof:placetype":"locality"
},
  "geometry": {"coordinates":[-7.57944,39.8907],"type":"Point"}
}