{
  "type": "Feature",
  "properties": {
    "gn:admin1_code":"22.0",
    "gn:admin2_code":"1822",
    "gn:admin3_code":"182206.0",
    "gn:asciiname":"Meieiras",
    "gn:country_code":"PT",
    "gn:dem":801,
    "gn:feature_class":"P",
    "gn:feature_code":"PPL",
    "gn:name":"Meieiras",
    "gn:population":0,
    "gn:timezone":"Europe/Lisbon",
    "iso:country":"PT",
    "wof:name":"Meieiras",
    "wof:placetype":"locality"
},
  "geometry": {"coordinates":[-7.82262,40.87184],"type":"Point"}
}