{
  "type": "Feature",
  "properties": {
    "gn:admin1_code":"16",
    "gn:admin2_code":"1213",
    "gn:admin3_code":"121302.0",
    "gn:asciiname":"Foros da Salgueira",
    "gn:country_code":"PT",
    "gn:dem":79,
    "gn:feature_class":"P",
    "gn:feature_code":"PPL",
    "gn:name":"Foros da Salgueira",
    "gn:population":0,
    "gn:timezone":"Europe/Lisbon",
    "iso:country":"PT",
    "wof:name":"Foros da Salgueira",
    "wof:placetype":"locality"
},
  "geometry": {"coordinates":[-8.07637,39.16419000000001],"type":"Point"}
}