{
  "type": "Feature",
  "properties": {
    "gn:admin1_code":"22.0",
    "gn:admin2_code":"1813",
    "gn:admin3_code":"181303.0",
    "gn:asciiname":"Corvo",
    "gn:country_code":"PT",
    "gn:dem":303,
    "gn:feature_class":"P",
    "gn:feature_code":"PPL",
    "gn:name":"Corvo",
    "gn:population":0,
    "gn:timezone":"Europe/Lisbon",
    "iso:country":"PT",
    "name:cat_x_preferred":[
        "Corvo"
    ],
    "name:ceb_x_preferred":[
        "Corvo"
    ],
    "name:fra_x_preferred":[
        "Corvo"
    ],
    "name:glg_x_preferred":[
        "Corvo"
    ],
    "name:ita_x_preferred":[
        "Corvo"
    ],
    "name:por_x_preferred":[
        "Corvo"
    ],
    "name:slk_x_preferred":[
        "Corvo"
    ],
    "name:spa_x_preferred":[
        "Corvo"
    ],
    "name:ukr_x_preferred":[
        "\u041a\u043e\u0440\u0432\u0443"
    ],
    "wof:name":"Corvo",
    "wof:placetype":"locality"
},
  "geometry": {"coordinates":[-7.96597,41.09922],"type":"Point"}
}