{
  "type": "Feature",
  "properties": {
    "gn:admin1_code":"22.0",
    "gn:admin2_code":"1813",
    "gn:admin3_code":"181303.0",
    "gn:asciiname":"Corvo",
    "gn:country_code":"PT",
    "gn:dem":303,
    "gn:feature_class":"P",
    "gn:feature_code":"PPL",
    "gn:name":"Corvo",
    "gn:population":0,
    "gn:timezone":"Europe/Lisbon",
    "iso:country":"PT",
    "wof:name":"Corvo",
    "wof:placetype":"locality"
},
  "geometry": {"coordinates":[-7.96597,41.09922],"type":"Point"}
}