{
  "type": "Feature",
  "properties": {
    "gn:admin1_code":"07",
    "gn:admin2_code":"0616",
    "gn:admin3_code":"61608.0",
    "gn:asciiname":"Ribeira",
    "gn:country_code":"PT",
    "gn:dem":303,
    "gn:feature_class":"P",
    "gn:feature_code":"PPL",
    "gn:name":"Ribeira",
    "gn:population":0,
    "gn:timezone":"Europe/Lisbon",
    "iso:country":"PT",
    "wof:name":"Ribeira",
    "wof:placetype":"locality"
},
  "geometry": {"coordinates":[-7.92502,40.37315],"type":"Point"}
}