{
  "type": "Feature",
  "properties": {
    "gn:admin1_code":"07",
    "gn:admin2_code":"0616",
    "gn:admin3_code":"61608.0",
    "gn:asciiname":"Ribeira",
    "gn:country_code":"PT",
    "gn:dem":303,
    "gn:feature_class":"P",
    "gn:feature_code":"PPL",
    "gn:name":"Ribeira",
    "gn:population":0,
    "gn:timezone":"Europe/Lisbon",
    "iso:country":"PT",
    "name:bpy_x_preferred":[
        "\u09b0\u09bf\u09ac\u09c7\u0987\u09b0\u09be"
    ],
    "name:bre_x_preferred":[
        "Ribeira"
    ],
    "name:ceb_x_preferred":[
        "Ribeira"
    ],
    "name:deu_x_preferred":[
        "Ribeira"
    ],
    "name:fra_x_preferred":[
        "Ribeira"
    ],
    "name:glg_x_preferred":[
        "Ribeira"
    ],
    "name:ita_x_preferred":[
        "Ribeira"
    ],
    "name:mlg_x_preferred":[
        "Ribeira"
    ],
    "name:msa_x_preferred":[
        "Ribeira"
    ],
    "name:nld_x_preferred":[
        "Ribeira"
    ],
    "name:pol_x_preferred":[
        "Ribeira"
    ],
    "name:por_x_preferred":[
        "Ribeira"
    ],
    "name:rus_x_preferred":[
        "\u0420\u0438\u0431\u0435\u0439\u0440\u0430"
    ],
    "name:swe_x_preferred":[
        "Ribeira"
    ],
    "name:tur_x_preferred":[
        "Ribeira"
    ],
    "name:ukr_x_preferred":[
        "\u0420\u0456\u0431\u0435\u0439\u0440\u0430"
    ],
    "name:vie_x_preferred":[
        "Ribeira"
    ],
    "name:war_x_preferred":[
        "Ribeira"
    ],
    "wof:name":"Ribeira",
    "wof:placetype":"locality"
},
  "geometry": {"coordinates":[-7.92502,40.37315],"type":"Point"}
}