{
  "type": "Feature",
  "properties": {
    "gn:admin1_code":"20",
    "gn:admin2_code":"1608",
    "gn:admin3_code":"160803.0",
    "gn:asciiname":"Vilar",
    "gn:country_code":"PT",
    "gn:dem":71,
    "gn:feature_class":"P",
    "gn:feature_code":"PPL",
    "gn:name":"Vilar",
    "gn:population":0,
    "gn:timezone":"Europe/Lisbon",
    "iso:country":"PT",
    "wof:name":"Vilar",
    "wof:placetype":"locality"
},
  "geometry": {"coordinates":[-8.62554,41.97136],"type":"Point"}
}