{
  "type": "Feature",
  "properties": {
    "gn:admin1_code":"21",
    "gn:admin2_code":"1711",
    "gn:admin3_code":"171108.0",
    "gn:asciiname":"Vila Maior",
    "gn:country_code":"PT",
    "gn:dem":245,
    "gn:feature_class":"P",
    "gn:feature_code":"PPL",
    "gn:name":"Vila Maior",
    "gn:population":0,
    "gn:timezone":"Europe/Lisbon",
    "iso:country":"PT",
    "wof:name":"Vila Maior",
    "wof:placetype":"locality"
},
  "geometry": {"coordinates":[-7.76571,41.18956],"type":"Point"}
}