{
  "type": "Feature",
  "properties": {
    "gn:admin1_code":"09",
    "gn:admin2_code":"0805",
    "gn:admin3_code":"80502.0",
    "gn:asciiname":"Azinhal e Amendoeira",
    "gn:country_code":"PT",
    "gn:dem":141,
    "gn:feature_class":"P",
    "gn:feature_code":"PPL",
    "gn:name":"Azinhal e Amendoeira",
    "gn:population":0,
    "gn:timezone":"Europe/Lisbon",
    "iso:country":"PT",
    "wof:name":"Azinhal e Amendoeira",
    "wof:placetype":"locality"
},
  "geometry": {"coordinates":[-7.88211,37.12212],"type":"Point"}
}