{
  "type": "Feature",
  "properties": {
    "gn:admin1_code":"14",
    "gn:admin2_code":"1102",
    "gn:admin3_code":"110201.0",
    "gn:asciiname":"A dos Arcos",
    "gn:country_code":"PT",
    "gn:dem":295,
    "gn:feature_class":"P",
    "gn:feature_code":"PPL",
    "gn:name":"A dos Arcos",
    "gn:population":0,
    "gn:timezone":"Europe/Lisbon",
    "iso:country":"PT",
    "name:und_x_variant":[
        "Arcos",
        "A dos Arcos"
    ],
    "wof:name":"A dos Arcos",
    "wof:placetype":"locality"
},
  "geometry": {"coordinates":[-9.13347,38.97527],"type":"Point"}
}