{
  "type": "Feature",
  "properties": {
    "gn:admin1_code":"22.0",
    "gn:admin2_code":"1816",
    "gn:admin3_code":"181614.0",
    "gn:asciiname":"Negrosa",
    "gn:country_code":"PT",
    "gn:dem":205,
    "gn:feature_class":"P",
    "gn:feature_code":"PPL",
    "gn:name":"Negrosa",
    "gn:population":0,
    "gn:timezone":"Europe/Lisbon",
    "iso:country":"PT",
    "wof:name":"Negrosa",
    "wof:placetype":"locality"
},
  "geometry": {"coordinates":[-8.06971,40.75672],"type":"Point"}
}