{
  "type": "Feature",
  "properties": {
    "gn:admin1_code":"13",
    "gn:admin2_code":"1010",
    "gn:admin3_code":"101001.0",
    "gn:asciiname":"Bico",
    "gn:country_code":"PT",
    "gn:dem":71,
    "gn:feature_class":"P",
    "gn:feature_code":"PPL",
    "gn:name":"Bico",
    "gn:population":0,
    "gn:timezone":"Europe/Lisbon",
    "iso:country":"PT",
    "name:ceb_x_preferred":[
        "Bico"
    ],
    "name:deu_x_preferred":[
        "Bico"
    ],
    "name:fra_x_preferred":[
        "Bico"
    ],
    "name:glg_x_preferred":[
        "Bico"
    ],
    "name:nld_x_preferred":[
        "Bico"
    ],
    "name:por_x_preferred":[
        "Bico"
    ],
    "name:rus_x_preferred":[
        "\u0411\u0438\u043a\u0443"
    ],
    "name:swe_x_preferred":[
        "Bico"
    ],
    "name:ukr_x_preferred":[
        "\u0411\u0438\u043a\u0443"
    ],
    "wof:name":"Bico",
    "wof:placetype":"locality"
},
  "geometry": {"coordinates":[-8.92716,39.77582],"type":"Point"}
}