{
  "type": "Feature",
  "properties": {
    "gn:admin1_code":"14",
    "gn:admin2_code":"1113",
    "gn:admin3_code":"111305.0",
    "gn:asciiname":"Ribeira Maria Afonso",
    "gn:country_code":"PT",
    "gn:dem":117,
    "gn:feature_class":"P",
    "gn:feature_code":"PPL",
    "gn:name":"Ribeira Maria Afonso",
    "gn:population":0,
    "gn:timezone":"Europe/Lisbon",
    "iso:country":"PT",
    "wof:name":"Ribeira Maria Afonso",
    "wof:placetype":"locality"
},
  "geometry": {"coordinates":[-9.16667,39.05],"type":"Point"}
}