{
  "type": "Feature",
  "properties": {
    "gn:admin1_code":"4.0",
    "gn:admin2_code":"0311",
    "gn:admin3_code":"31108.0",
    "gn:asciiname":"Guilhofrei",
    "gn:country_code":"PT",
    "gn:dem":385,
    "gn:feature_class":"P",
    "gn:feature_code":"PPL",
    "gn:name":"Guilhofrei",
    "gn:population":0,
    "gn:timezone":"Europe/Lisbon",
    "iso:country":"PT",
    "wof:name":"Guilhofrei",
    "wof:placetype":"locality"
},
  "geometry": {"coordinates":[-8.12325,41.5782],"type":"Point"}
}