{
  "type": "Feature",
  "properties": {
    "gn:admin1_code":"13",
    "gn:admin2_code":"1001",
    "gn:admin3_code":"100109.0",
    "gn:asciiname":"Boa Vista de Cima",
    "gn:country_code":"PT",
    "gn:dem":120,
    "gn:feature_class":"P",
    "gn:feature_code":"PPL",
    "gn:name":"Boa Vista de Cima",
    "gn:population":0,
    "gn:timezone":"Europe/Lisbon",
    "iso:country":"PT",
    "wof:name":"Boa Vista de Cima",
    "wof:placetype":"locality"
},
  "geometry": {"coordinates":[-8.95274,39.56994],"type":"Point"}
}