{
  "type": "Feature",
  "properties": {
    "gn:admin1_code":"4.0",
    "gn:admin2_code":"0307",
    "gn:admin3_code":"30708.0",
    "gn:asciiname":"Estoraos",
    "gn:country_code":"PT",
    "gn:dem":393,
    "gn:feature_class":"P",
    "gn:feature_code":"PPL",
    "gn:name":"Estor\u00e3os",
    "gn:population":0,
    "gn:timezone":"Europe/Lisbon",
    "iso:country":"PT",
    "wof:name":"Estoraos",
    "wof:placetype":"locality"
},
  "geometry": {"coordinates":[-8.14499,41.47566],"type":"Point"}
}