{
  "type": "Feature",
  "properties": {
    "gn:admin1_code":"16",
    "gn:admin2_code":"1207",
    "gn:admin3_code":"120708.0",
    "gn:asciiname":"Monte da Alcobaca",
    "gn:country_code":"PT",
    "gn:dem":332,
    "gn:feature_class":"P",
    "gn:feature_code":"PPL",
    "gn:name":"Monte da Alcoba\u00e7a",
    "gn:population":0,
    "gn:timezone":"Europe/Lisbon",
    "iso:country":"PT",
    "wof:name":"Monte da Alcobaca",
    "wof:placetype":"locality"
},
  "geometry": {"coordinates":[-7.18333,38.9237],"type":"Point"}
}