{
  "type": "Feature",
  "properties": {
    "gn:admin1_code":"17",
    "gn:admin2_code":"1310",
    "gn:admin3_code":"131024.0",
    "gn:asciiname":"Vilela",
    "gn:country_code":"PT",
    "gn:dem":276,
    "gn:feature_class":"P",
    "gn:feature_code":"PPL",
    "gn:name":"Vilela",
    "gn:population":0,
    "gn:timezone":"Europe/Lisbon",
    "iso:country":"PT",
    "name:ceb_x_preferred":[
        "Vilela"
    ],
    "name:deu_x_preferred":[
        "Vilela"
    ],
    "name:fra_x_preferred":[
        "Vilela"
    ],
    "name:glg_x_preferred":[
        "Vilela"
    ],
    "name:nld_x_preferred":[
        "Vilela"
    ],
    "name:por_x_preferred":[
        "Vilela"
    ],
    "name:rus_x_preferred":[
        "\u0412\u0438\u043b\u0435\u043b\u0430"
    ],
    "name:spa_x_preferred":[
        "Vilela"
    ],
    "name:swe_x_preferred":[
        "Vilela"
    ],
    "name:ukr_x_preferred":[
        "\u0412\u0456\u043b\u0435\u043b\u0430"
    ],
    "wof:name":"Vilela",
    "wof:placetype":"locality"
},
  "geometry": {"coordinates":[-8.38887,41.23519],"type":"Point"}
}