{
  "type": "Feature",
  "properties": {
    "gn:admin1_code":"23.0",
    "gn:admin2_code":"4101",
    "gn:admin3_code":"410105.0",
    "gn:asciiname":"Sao Pedro",
    "gn:country_code":"PT",
    "gn:dem":153,
    "gn:feature_class":"P",
    "gn:feature_code":"PPL",
    "gn:name":"S\u00e3o Pedro",
    "gn:population":0,
    "gn:timezone":"Atlantic/Azores",
    "iso:country":"PT",
    "name:ceb_x_preferred":[
        "S\u00e3o Pedro"
    ],
    "name:rus_x_preferred":[
        "\u0421\u0430\u043d-\u041f\u0435\u0434\u0440\u0443"
    ],
    "wof:name":"Sao Pedro",
    "wof:placetype":"locality"
},
  "geometry": {"coordinates":[-25.13333,36.96667],"type":"Point"}
}