{
  "type": "Feature",
  "properties": {
    "gn:admin1_code":"7.0",
    "gn:admin2_code":"0601",
    "gn:admin3_code":"60110.0",
    "gn:asciiname":"Casarias",
    "gn:country_code":"PT",
    "gn:dem":550,
    "gn:feature_class":"P",
    "gn:feature_code":"PPL",
    "gn:name":"Casarias",
    "gn:population":0,
    "gn:timezone":"Europe/Lisbon",
    "iso:country":"PT",
    "wof:name":"Casarias",
    "wof:placetype":"locality"
},
  "geometry": {"coordinates":[-7.89781,40.23202],"type":"Point"}
}