{
  "type": "Feature",
  "properties": {
    "gn:admin1_code":"4.0",
    "gn:admin2_code":"0302",
    "gn:admin3_code":"30207.0",
    "gn:asciiname":"Alheira",
    "gn:country_code":"PT",
    "gn:dem":148,
    "gn:feature_class":"P",
    "gn:feature_code":"PPL",
    "gn:name":"Alheira",
    "gn:population":0,
    "gn:timezone":"Europe/Lisbon",
    "iso:country":"PT",
    "name:hye_x_preferred":[
        "\u0531\u056c\u0565\u0575\u0580\u0561"
    ],
    "name:ita_x_preferred":[
        "Alheira"
    ],
    "name:jav_x_preferred":[
        "Alheira"
    ],
    "name:kor_x_preferred":[
        "\uc54c\ub840\uc774\ub77c"
    ],
    "name:lit_x_preferred":[
        "Alheira"
    ],
    "name:pol_x_preferred":[
        "Alheira"
    ],
    "name:por_x_preferred":[
        "Alheira"
    ],
    "name:rus_x_preferred":[
        "\u0410\u043b\u044c\u0435\u0439\u0440\u0430"
    ],
    "name:spa_x_preferred":[
        "Alheira"
    ],
    "wof:name":"Alheira",
    "wof:placetype":"locality"
},
  "geometry": {"coordinates":[-8.56401,41.61221],"type":"Point"}
}