{
  "type": "Feature",
  "properties": {
    "gn:admin1_code":"4.0",
    "gn:admin2_code":"0302",
    "gn:admin3_code":"30207.0",
    "gn:asciiname":"Alheira",
    "gn:country_code":"PT",
    "gn:dem":148,
    "gn:feature_class":"P",
    "gn:feature_code":"PPL",
    "gn:name":"Alheira",
    "gn:population":0,
    "gn:timezone":"Europe/Lisbon",
    "iso:country":"PT",
    "wof:name":"Alheira",
    "wof:placetype":"locality"
},
  "geometry": {"coordinates":[-8.56401,41.61221],"type":"Point"}
}