{
  "type": "Feature",
  "properties": {
    "gn:admin1_code":"20",
    "gn:admin2_code":"1609",
    "gn:admin3_code":"160933.0",
    "gn:asciiname":"Subportela",
    "gn:country_code":"PT",
    "gn:dem":61,
    "gn:feature_class":"P",
    "gn:feature_code":"PPL",
    "gn:name":"Subportela",
    "gn:population":0,
    "gn:timezone":"Europe/Lisbon",
    "iso:country":"PT",
    "wof:name":"Subportela",
    "wof:placetype":"locality"
},
  "geometry": {"coordinates":[-8.71365,41.68357],"type":"Point"}
}