{
  "type": "Feature",
  "properties": {
    "gn:admin1_code":"11",
    "gn:admin2_code":"0911",
    "gn:admin3_code":"91132.0",
    "gn:asciiname":"Valongo de Baixo",
    "gn:country_code":"PT",
    "gn:dem":667,
    "gn:feature_class":"P",
    "gn:feature_code":"PPL",
    "gn:name":"Valongo de Baixo",
    "gn:population":0,
    "gn:timezone":"Europe/Lisbon",
    "iso:country":"PT",
    "wof:name":"Valongo de Baixo",
    "wof:placetype":"locality"
},
  "geometry": {"coordinates":[-7.01667,40.46667],"type":"Point"}
}