{
  "type": "Feature",
  "properties": {
    "gn:admin1_code":"17.0",
    "gn:admin2_code":"1315",
    "gn:admin3_code":"131504.0",
    "gn:asciiname":"Balsa",
    "gn:country_code":"PT",
    "gn:dem":128,
    "gn:feature_class":"P",
    "gn:feature_code":"PPLL",
    "gn:name":"Balsa",
    "gn:population":0,
    "gn:timezone":"Europe/Lisbon",
    "iso:country":"PT",
    "wof:name":"Balsa",
    "wof:placetype":"locality"
},
  "geometry": {"coordinates":[-8.45007,41.22702],"type":"Point"}
}