{
  "type": "Feature",
  "properties": {
    "gn:admin1_code":"09",
    "gn:admin2_code":"0807",
    "gn:admin3_code":"80704.0",
    "gn:asciiname":"Ruivas",
    "gn:country_code":"PT",
    "gn:dem":3,
    "gn:feature_class":"P",
    "gn:feature_code":"PPL",
    "gn:name":"Ruivas",
    "gn:population":0,
    "gn:timezone":"Europe/Lisbon",
    "iso:country":"PT",
    "wof:name":"Ruivas",
    "wof:placetype":"locality"
},
  "geometry": {"coordinates":[-8.65,37.15],"type":"Point"}
}