{
  "type": "Feature",
  "properties": {
    "gn:admin1_code":"14",
    "gn:admin2_code":"1112",
    "gn:admin3_code":"111201.0",
    "gn:asciiname":"Alcareia",
    "gn:country_code":"PT",
    "gn:dem":305,
    "gn:feature_class":"P",
    "gn:feature_code":"PPL",
    "gn:name":"Alcareia",
    "gn:population":0,
    "gn:timezone":"Europe/Lisbon",
    "iso:country":"PT",
    "wof:name":"Alcareia",
    "wof:placetype":"locality"
},
  "geometry": {"coordinates":[-9.15246,38.97363],"type":"Point"}
}