{
  "type": "Feature",
  "properties": {
    "gn:admin1_code":"14",
    "gn:admin2_code":"1114",
    "gn:admin3_code":"111409.0",
    "gn:asciiname":"Conchoso",
    "gn:country_code":"PT",
    "gn:dem":0,
    "gn:feature_class":"P",
    "gn:feature_code":"PPL",
    "gn:name":"Conchoso",
    "gn:population":0,
    "gn:timezone":"Europe/Lisbon",
    "iso:country":"PT",
    "wof:name":"Conchoso",
    "wof:placetype":"locality"
},
  "geometry": {"coordinates":[-8.87806,39.02806],"type":"Point"}
}