{
  "type": "Feature",
  "properties": {
    "gn:admin1_code":"04",
    "gn:admin2_code":"0313",
    "gn:admin3_code":"31352.0",
    "gn:asciiname":"Sampaio",
    "gn:country_code":"PT",
    "gn:dem":49,
    "gn:feature_class":"P",
    "gn:feature_code":"PPL",
    "gn:name":"Sampaio",
    "gn:population":0,
    "gn:timezone":"Europe/Lisbon",
    "iso:country":"PT",
    "wof:name":"Sampaio",
    "wof:placetype":"locality"
},
  "geometry": {"coordinates":[-8.43333,41.61667],"type":"Point"}
}