{
  "type": "Feature",
  "properties": {
    "gn:gn_country":"PT",
    "gn:gn_fcode":"ADM3",
    "gn:gn_pop":0,
    "iso:country":"PT",
    "name:chi_x_preferred":[
        "S\u00e3o Paio de Oleiros"
    ],
    "name:dut_x_preferred":[
        "S\u00e3o Paio de Oleiros"
    ],
    "name:eng_x_preferred":[
        "S\u00e3o Paio de Oleiros"
    ],
    "name:fre_x_preferred":[
        "S\u00e3o Paio de Oleiros"
    ],
    "name:ger_x_preferred":[
        "S\u00e3o Paio de Oleiros"
    ],
    "name:kaz_x_preferred":[
        "\u0421\u0430\u043d-\u041f\u0430\u0439\u044e-\u0434\u0435-\u041e\u043b\u0435\u0439\u0440\u0443\u0448"
    ],
    "name:may_x_preferred":[
        "S\u00e3o Paio de Oleiros"
    ],
    "name:por_x_preferred":[
        "S\u00e3o Paio de Oleiros"
    ],
    "name:rus_x_preferred":[
        "\u0421\u0430\u043d-\u041f\u0430\u0439\u044e-\u0434\u0435-\u041e\u043b\u0435\u0439\u0440\u0443\u0448"
    ],
    "name:spa_x_preferred":[
        "S\u00e3o Paio de Oleiros"
    ],
    "name:tur_x_preferred":[
        "S\u00e3o Paio de Oleiros"
    ],
    "qs_pg:aaroncc":"PT",
    "qs_pg:gn_country":"PT",
    "qs_pg:gn_fcode":"ADM3",
    "qs_pg:gn_pop":0,
    "qs_pg:name":"S\u00e3o Paio de Oleiros",
    "qs_pg:name_adm0":"Portugal",
    "qs_pg:name_adm1":"Aveiro",
    "qs_pg:photos_9k":1,
    "qs_pg:photos_9r":1,
    "qs_pg:photos_all":1,
    "qs_pg:photos_sr":0,
    "qs_pg:pop_sr":0,
    "qs_pg:qs_pg_placetype":"locality",
    "qs_pg:qs_pg_placetype_gp":"Town",
    "qs_pg:woe_adm0":23424925,
    "woe:adm0_id":23424925,
    "woe:name_adm0":"Portugal",
    "woe:name_adm1":"Aveiro",
    "woe:placetype":"Town",
    "wof:name":"S\u00e3o Paio de Oleiros",
    "wof:placetype":"locality"
},
  "geometry": {"coordinates":[-8.59863,40.98802],"type":"Point"}
}