{
  "type": "Feature",
  "properties": {
    "gn:admin1_code":"03",
    "gn:admin2_code":"0202",
    "gn:admin3_code":"20201.0",
    "gn:asciiname":"Curvatos",
    "gn:country_code":"PT",
    "gn:dem":316,
    "gn:feature_class":"P",
    "gn:feature_code":"PPL",
    "gn:name":"Curvatos",
    "gn:population":0,
    "gn:timezone":"Europe/Lisbon",
    "iso:country":"PT",
    "wof:name":"Curvatos",
    "wof:placetype":"locality"
},
  "geometry": {"coordinates":[-8.06168,37.45156],"type":"Point"}
}