{
  "type": "Feature",
  "properties": {
    "gn:admin1_code":"09",
    "gn:admin2_code":"0812",
    "gn:admin3_code":"81201.0",
    "gn:asciiname":"Paco dos Ferreiros",
    "gn:country_code":"PT",
    "gn:dem":304,
    "gn:feature_class":"P",
    "gn:feature_code":"PPL",
    "gn:name":"Pa\u00e7o dos Ferreiros",
    "gn:population":0,
    "gn:timezone":"Europe/Lisbon",
    "iso:country":"PT",
    "wof:name":"Paco dos Ferreiros",
    "wof:placetype":"locality"
},
  "geometry": {"coordinates":[-7.9015,37.15722],"type":"Point"}
}