{
  "type": "Feature",
  "properties": {
    "gn:admin1_code":"09",
    "gn:admin2_code":"0815",
    "gn:admin3_code":"81502.0",
    "gn:asciiname":"Vale de Boi",
    "gn:country_code":"PT",
    "gn:dem":18,
    "gn:feature_class":"P",
    "gn:feature_code":"PPL",
    "gn:name":"Vale de Boi",
    "gn:population":0,
    "gn:timezone":"Europe/Lisbon",
    "iso:country":"PT",
    "wof:name":"Vale de Boi",
    "wof:placetype":"locality"
},
  "geometry": {"coordinates":[-8.81141,37.09087],"type":"Point"}
}