{
  "type": "Feature",
  "properties": {
    "gn:country":"PT",
    "gn:fcode":"PPL",
    "gn:population":0,
    "iso:country":"PT",
    "name:ara_x_preferred":[
        "\u0644\u0627\u0631"
    ],
    "name:ast_x_preferred":[
        "Lares"
    ],
    "name:bel_x_preferred":[
        "\u041b\u0430\u0440\u044b"
    ],
    "name:bul_x_preferred":[
        "\u041b\u0430\u0440\u0438"
    ],
    "name:cat_x_preferred":[
        "Lar"
    ],
    "name:ces_x_preferred":[
        "Larov\u00e9"
    ],
    "name:dan_x_preferred":[
        "Lar"
    ],
    "name:deu_x_preferred":[
        "Laren"
    ],
    "name:ell_x_preferred":[
        "\u039b\u03ac\u03c1\u03b7\u03c4\u03b5\u03c2"
    ],
    "name:est_x_preferred":[
        "Laarid"
    ],
    "name:eus_x_preferred":[
        "Larak"
    ],
    "name:fas_x_preferred":[
        "\u0644\u0627\u0631\u0633"
    ],
    "name:fin_x_preferred":[
        "Laarit"
    ],
    "name:fra_x_preferred":[
        "Lares"
    ],
    "name:heb_x_preferred":[
        "\u05dc\u05d0\u05e8\u05e1"
    ],
    "name:ind_x_preferred":[
        "Lares"
    ],
    "name:ita_x_preferred":[
        "Lari"
    ],
    "name:jpn_x_preferred":[
        "\u30e9\u30ec\u30fc\u30b9"
    ],
    "name:kor_x_preferred":[
        "\ub77c\ub808\uc2a4"
    ],
    "name:lat_x_preferred":[
        "Lar"
    ],
    "name:nld_x_preferred":[
        "Laren"
    ],
    "name:nor_x_preferred":[
        "Larer"
    ],
    "name:pol_x_preferred":[
        "Lary"
    ],
    "name:por_x_preferred":[
        "Lares"
    ],
    "name:ron_x_preferred":[
        "Lares"
    ],
    "name:rus_x_preferred":[
        "\u041b\u0430\u0440\u044b"
    ],
    "name:spa_x_preferred":[
        "Lares"
    ],
    "name:swe_x_preferred":[
        "Larer"
    ],
    "name:tur_x_preferred":[
        "Lares"
    ],
    "name:ukr_x_preferred":[
        "\u041b\u0430\u0440\u0438"
    ],
    "name:zho_x_preferred":[
        "\u62c9\u5c14"
    ],
    "qs_pg:aaroncc":"PT",
    "qs_pg:gn_country":"PT",
    "qs_pg:gn_fcode":"PPL",
    "qs_pg:gn_pop":0,
    "qs_pg:name":"Lares",
    "qs_pg:name_adm0":"Portugal",
    "qs_pg:name_adm1":"Coimbra",
    "qs_pg:photos_9k":1,
    "qs_pg:photos_9r":3,
    "qs_pg:photos_all":120,
    "qs_pg:photos_sr":0,
    "qs_pg:pop_sr":0,
    "qs_pg:qs_pg_placetype":"locality",
    "qs_pg:qs_pg_placetype_gp":"Town",
    "qs_pg:woe_adm0":23424925,
    "woe:adm0_id":23424925,
    "woe:name_adm0":"Portugal",
    "woe:name_adm1":"Coimbra",
    "woe:placetype":"Town",
    "wof:name":"Lares",
    "wof:placetype":"locality"
},
  "geometry": {"coordinates":[-8.78677,40.13004],"type":"Point"}
}