{
  "type": "Feature",
  "properties": {
    "gn:admin1_code":"13",
    "gn:admin2_code":"1016",
    "gn:admin3_code":"101611.0",
    "gn:asciiname":"Ribeira",
    "gn:country_code":"PT",
    "gn:dem":140,
    "gn:feature_class":"P",
    "gn:feature_code":"PPL",
    "gn:name":"Ribeira",
    "gn:population":0,
    "gn:timezone":"Europe/Lisbon",
    "iso:country":"PT",
    "wof:name":"Ribeira",
    "wof:placetype":"locality"
},
  "geometry": {"coordinates":[-8.82079,39.58891],"type":"Point"}
}