{
  "type": "Feature",
  "properties": {
    "gn:admin1_code":"18",
    "gn:admin2_code":"1401",
    "gn:admin3_code":"140104.0",
    "gn:asciiname":"Telhado",
    "gn:country_code":"PT",
    "gn:dem":77,
    "gn:feature_class":"P",
    "gn:feature_code":"PPL",
    "gn:name":"Telhado",
    "gn:population":0,
    "gn:timezone":"Europe/Lisbon",
    "iso:country":"PT",
    "wof:name":"Telhado",
    "wof:placetype":"locality"
},
  "geometry": {"coordinates":[-8.14229,39.38295],"type":"Point"}
}