{
  "type": "Feature",
  "properties": {
    "gn:admin1_code":"7.0",
    "gn:admin2_code":"0606",
    "gn:admin3_code":"60605.0",
    "gn:asciiname":"Inviando",
    "gn:country_code":"PT",
    "gn:dem":185,
    "gn:feature_class":"P",
    "gn:feature_code":"PPL",
    "gn:name":"Inviando",
    "gn:population":0,
    "gn:timezone":"Europe/Lisbon",
    "iso:country":"PT",
    "wof:name":"Inviando",
    "wof:placetype":"locality"
},
  "geometry": {"coordinates":[-8.14784,40.18017],"type":"Point"}
}