{
  "type": "Feature",
  "properties": {
    "gn:admin1_code":"20.0",
    "gn:admin2_code":"1604",
    "gn:admin3_code":"160411.0",
    "gn:asciiname":"Corgo",
    "gn:country_code":"PT",
    "gn:dem":88,
    "gn:feature_class":"P",
    "gn:feature_code":"PPL",
    "gn:name":"Corgo",
    "gn:population":0,
    "gn:timezone":"Europe/Lisbon",
    "iso:country":"PT",
    "wof:name":"Corgo",
    "wof:placetype":"locality"
},
  "geometry": {"coordinates":[-8.45042,42.05734],"type":"Point"}
}