{
  "type": "Feature",
  "properties": {
    "gn:admin1_code":"04",
    "gn:admin2_code":"0312",
    "gn:admin3_code":"31208.0",
    "gn:asciiname":"Senra",
    "gn:country_code":"PT",
    "gn:dem":138,
    "gn:feature_class":"P",
    "gn:feature_code":"PPL",
    "gn:name":"Senra",
    "gn:population":0,
    "gn:timezone":"Europe/Lisbon",
    "iso:country":"PT",
    "name:nld_x_preferred":[
        "Senra"
    ],
    "name:por_x_preferred":[
        "Senra"
    ],
    "name:spa_x_preferred":[
        "Senra"
    ],
    "wof:name":"Senra",
    "wof:placetype":"locality"
},
  "geometry": {"coordinates":[-8.53924,41.40442],"type":"Point"}
}