{
  "type": "Feature",
  "properties": {
    "gn:admin1_code":"16",
    "gn:admin2_code":"1202",
    "gn:admin3_code":"120201.0",
    "gn:asciiname":"Baldio",
    "gn:country_code":"PT",
    "gn:dem":246,
    "gn:feature_class":"P",
    "gn:feature_code":"PPL",
    "gn:name":"Baldio",
    "gn:population":0,
    "gn:timezone":"Europe/Lisbon",
    "iso:country":"PT",
    "wof:name":"Baldio",
    "wof:placetype":"locality"
},
  "geometry": {"coordinates":[-7.1462,39.10911],"type":"Point"}
}