{
  "type": "Feature",
  "properties": {
    "gn:admin1_code":"04",
    "gn:admin2_code":"0312",
    "gn:admin3_code":"31232.0",
    "gn:asciiname":"Pousada de Saramagos",
    "gn:country_code":"PT",
    "gn:dem":178,
    "gn:feature_class":"P",
    "gn:feature_code":"PPL",
    "gn:name":"Pousada de Saramagos",
    "gn:population":0,
    "gn:timezone":"Europe/Lisbon",
    "iso:country":"PT",
    "name:kaz_x_preferred":[
        "\u041f\u043e\u0437\u0430\u0434\u0430-\u0434\u0435-\u0421\u0430\u0440\u0430\u043c\u0430\u0433\u0443\u0448"
    ],
    "name:rus_x_preferred":[
        "\u041f\u043e\u0437\u0430\u0434\u0430-\u0434\u0435-\u0421\u0430\u0440\u0430\u043c\u0430\u0433\u0443\u0448"
    ],
    "name:ukr_x_preferred":[
        "\u041f\u043e\u0437\u0430\u0434\u0430-\u0434\u0435-\u0421\u0430\u0440\u0430\u043c\u0430\u0433\u0443\u0448"
    ],
    "wof:name":"Pousada de Saramagos",
    "wof:placetype":"locality"
},
  "geometry": {"coordinates":[-8.43598,41.4309],"type":"Point"}
}