{
  "type": "Feature",
  "properties": {
    "gn:admin1_code":"22.0",
    "gn:admin2_code":"1820",
    "gn:admin3_code":"182003.0",
    "gn:asciiname":"Formilo",
    "gn:country_code":"PT",
    "gn:dem":708,
    "gn:feature_class":"P",
    "gn:feature_code":"PPL",
    "gn:name":"Formilo",
    "gn:population":0,
    "gn:timezone":"Europe/Lisbon",
    "iso:country":"PT",
    "wof:name":"Formilo",
    "wof:placetype":"locality"
},
  "geometry": {"coordinates":[-7.73714,41.03429000000001],"type":"Point"}
}