{
  "type": "Feature",
  "properties": {
    "gn:admin1_code":"11.0",
    "gn:admin2_code":"0907",
    "gn:admin3_code":"90730.0",
    "gn:asciiname":"Pera do Moco",
    "gn:country_code":"PT",
    "gn:dem":862,
    "gn:feature_class":"P",
    "gn:feature_code":"PPL",
    "gn:name":"Pera do Mo\u00e7o",
    "gn:population":0,
    "gn:timezone":"Europe/Lisbon",
    "iso:country":"PT",
    "wof:name":"Pera do Moco",
    "wof:placetype":"locality"
},
  "geometry": {"coordinates":[-7.2127,40.61406],"type":"Point"}
}