{
  "type": "Feature",
  "properties": {
    "gn:admin1_code":"5.0",
    "gn:admin2_code":"0402",
    "gn:admin3_code":"40219.0",
    "gn:asciiname":"Grijo de Parada",
    "gn:country_code":"PT",
    "gn:dem":758,
    "gn:feature_class":"P",
    "gn:feature_code":"PPL",
    "gn:name":"Grij\u00f3 de Parada",
    "gn:population":0,
    "gn:timezone":"Europe/Lisbon",
    "iso:country":"PT",
    "wof:name":"Grijo de Parada",
    "wof:placetype":"locality"
},
  "geometry": {"coordinates":[-6.68652,41.71649],"type":"Point"}
}