{
  "type": "Feature",
  "properties": {
    "gn:admin1_code":"20.0",
    "gn:admin2_code":"1608",
    "gn:admin3_code":"160815.0",
    "gn:asciiname":"Valenca do Minho",
    "gn:country_code":"PT",
    "gn:dem":13,
    "gn:feature_class":"P",
    "gn:feature_code":"PPL",
    "gn:name":"Valen\u00e7a do Minho",
    "gn:population":0,
    "gn:timezone":"Europe/Lisbon",
    "iso:country":"PT",
    "wof:name":"Valenca do Minho",
    "wof:placetype":"locality"
},
  "geometry": {"coordinates":[-8.64023,42.03363],"type":"Point"}
}