{
  "type": "Feature",
  "properties": {
    "gn:admin1_code":"20.0",
    "gn:admin2_code":"1603",
    "gn:admin3_code":"160312.0",
    "gn:asciiname":"Parada do Monte",
    "gn:country_code":"PT",
    "gn:dem":559,
    "gn:feature_class":"P",
    "gn:feature_code":"PPL",
    "gn:name":"Parada do Monte",
    "gn:population":0,
    "gn:timezone":"Europe/Lisbon",
    "iso:country":"PT",
    "name:kaz_x_preferred":[
        "\u041f\u0430\u0440\u0430\u0434\u0430-\u0434\u0443-\u041c\u043e\u043d\u0442\u0435"
    ],
    "name:rus_x_preferred":[
        "\u041f\u0430\u0440\u0430\u0434\u0430-\u0434\u0443-\u041c\u043e\u043d\u0442\u0435"
    ],
    "wof:name":"Parada do Monte",
    "wof:placetype":"locality"
},
  "geometry": {"coordinates":[-8.26558,42.04356],"type":"Point"}
}