{
  "type": "Feature",
  "properties": {
    "gn:admin1_code":"20.0",
    "gn:admin2_code":"1603",
    "gn:admin3_code":"160312.0",
    "gn:asciiname":"Parada do Monte",
    "gn:country_code":"PT",
    "gn:dem":559,
    "gn:feature_class":"P",
    "gn:feature_code":"PPL",
    "gn:name":"Parada do Monte",
    "gn:population":0,
    "gn:timezone":"Europe/Lisbon",
    "iso:country":"PT",
    "wof:name":"Parada do Monte",
    "wof:placetype":"locality"
},
  "geometry": {"coordinates":[-8.26558,42.04356],"type":"Point"}
}