{
  "type": "Feature",
  "properties": {
    "gn:admin1_code":"18",
    "gn:admin2_code":"1401",
    "gn:admin3_code":"140116.0",
    "gn:asciiname":"Ramalhais",
    "gn:country_code":"PT",
    "gn:dem":170,
    "gn:feature_class":"P",
    "gn:feature_code":"PPL",
    "gn:name":"Ramalhais",
    "gn:population":0,
    "gn:timezone":"Europe/Lisbon",
    "iso:country":"PT",
    "wof:name":"Ramalhais",
    "wof:placetype":"locality"
},
  "geometry": {"coordinates":[-8.05563,39.34061],"type":"Point"}
}