{
  "type": "Feature",
  "properties": {
    "gn:admin1_code":"18",
    "gn:admin2_code":"1415",
    "gn:admin3_code":"141505.0",
    "gn:asciiname":"Monte de Lucas",
    "gn:country_code":"PT",
    "gn:dem":39,
    "gn:feature_class":"P",
    "gn:feature_code":"PPL",
    "gn:name":"Monte de Lucas",
    "gn:population":0,
    "gn:timezone":"Europe/Lisbon",
    "iso:country":"PT",
    "wof:name":"Monte de Lucas",
    "wof:placetype":"locality"
},
  "geometry": {"coordinates":[-8.73333,38.98333],"type":"Point"}
}