{
  "type": "Feature",
  "properties": {
    "gn:admin1_code":"07",
    "gn:admin2_code":"0611",
    "gn:admin3_code":"61118.0",
    "gn:asciiname":"Sobreda",
    "gn:country_code":"PT",
    "gn:dem":389,
    "gn:feature_class":"P",
    "gn:feature_code":"PPL",
    "gn:name":"Sobreda",
    "gn:population":0,
    "gn:timezone":"Europe/Lisbon",
    "iso:country":"PT",
    "wof:name":"Sobreda",
    "wof:placetype":"locality"
},
  "geometry": {"coordinates":[-7.81295,40.45463],"type":"Point"}
}