{
  "type": "Feature",
  "properties": {
    "iso:country":"PT",
    "name:ast_x_preferred":[
        "Sarilhos Pequenos"
    ],
    "name:ceb_x_preferred":[
        "Sarilhos Pequenos"
    ],
    "name:deu_x_preferred":[
        "Sarilhos Pequenos"
    ],
    "name:eng_x_preferred":[
        "Sarilhos Pequenos"
    ],
    "name:fra_x_preferred":[
        "Sarilhos Pequenos"
    ],
    "name:kaz_x_preferred":[
        "\u0421\u0430\u0440\u0438\u043b\u044c\u044e\u0448-\u041f\u0435\u043a\u0435\u043d\u0443\u0448"
    ],
    "name:nld_x_preferred":[
        "Sarilhos Pequenos"
    ],
    "name:por_x_preferred":[
        "Sarilhos Pequenos"
    ],
    "name:rus_x_preferred":[
        "\u0421\u0430\u0440\u0438\u043b\u044c\u044e\u0448-\u041f\u0435\u043a\u0435\u043d\u0443\u0448"
    ],
    "name:spa_x_preferred":[
        "Sarilhos Pequenos"
    ],
    "qs:a0":"Portugal",
    "qs:a1":"*Set\u00fabal",
    "qs:a1r":"0",
    "qs:adm0":"Portugal",
    "qs:la_lc":"*",
    "qs:level":"locality",
    "qs:loc":"Sarilhos Pequenos",
    "qs:loc_alt":"Sarilhos Pequenos",
    "qs:pop":0,
    "qs:type":"buffered point",
    "wd:wordcount":389,
    "wof:lang":[
        "por"
    ],
    "wof:name":"Sarilhos Pequenos",
    "wof:placetype":"locality"
},
  "geometry": {"coordinates":[-8.981943,38.682942],"type":"Point"}
}