{
  "type": "Feature",
  "properties": {
    "iso:country":"PT",
    "wof:name":"San Francisco Xavier",
    "wof:placetype":"neighbourhood"
},
  "geometry": {"coordinates":[-9.21449609152789,38.7109315849957],"type":"Point"}
}