{
  "type": "Feature",
  "properties": {
    "gn:admin1_code":"04",
    "gn:admin2_code":"0302",
    "gn:admin3_code":"30288.0",
    "gn:asciiname":"Vilar de Figos",
    "gn:country_code":"PT",
    "gn:dem":111,
    "gn:feature_class":"P",
    "gn:feature_code":"PPL",
    "gn:name":"Vilar de Figos",
    "gn:population":2066,
    "gn:timezone":"Europe/Lisbon",
    "iso:country":"PT",
    "wof:name":"Vilar de Figos",
    "wof:placetype":"locality",
    "wof:population":2066
},
  "geometry": {"coordinates":[-8.65382,41.47555],"type":"Point"}
}