{
  "type": "Feature",
  "properties": {
    "gn:admin1_code":"14",
    "gn:admin2_code":"1109",
    "gn:admin3_code":"110908.0",
    "gn:asciiname":"Funchal",
    "gn:country_code":"PT",
    "gn:dem":263,
    "gn:feature_class":"P",
    "gn:feature_code":"PPL",
    "gn:name":"Funchal",
    "gn:population":0,
    "gn:timezone":"Europe/Lisbon",
    "iso:country":"PT",
    "wof:name":"Funchal",
    "wof:placetype":"locality"
},
  "geometry": {"coordinates":[-9.28291,38.90906],"type":"Point"}
}