{
  "type": "Feature",
  "properties": {
    "gn:admin1_code":"18",
    "gn:admin2_code":"1413",
    "gn:admin3_code":"141303.0",
    "gn:asciiname":"Colos",
    "gn:country_code":"PT",
    "gn:dem":314,
    "gn:feature_class":"P",
    "gn:feature_code":"PPL",
    "gn:name":"Colos",
    "gn:population":0,
    "gn:timezone":"Europe/Lisbon",
    "iso:country":"PT",
    "name:ceb_x_preferred":[
        "Colos"
    ],
    "name:swe_x_preferred":[
        "Colos"
    ],
    "wof:name":"Colos",
    "wof:placetype":"locality"
},
  "geometry": {"coordinates":[-8.04559,39.72877],"type":"Point"}
}