{
  "type": "Feature",
  "properties": {
    "gn:admin1_code":"7.0",
    "gn:admin2_code":"0610",
    "gn:admin3_code":"61007.0",
    "gn:asciiname":"Bandorreira",
    "gn:country_code":"PT",
    "gn:dem":73,
    "gn:feature_class":"P",
    "gn:feature_code":"PPL",
    "gn:name":"Bandorreira",
    "gn:population":0,
    "gn:timezone":"Europe/Lisbon",
    "iso:country":"PT",
    "wof:name":"Bandorreira",
    "wof:placetype":"locality"
},
  "geometry": {"coordinates":[-8.6622,40.20604],"type":"Point"}
}