{
  "type": "Feature",
  "properties": {
    "gn:admin1_code":"03",
    "gn:admin2_code":"0210",
    "gn:admin3_code":"21005.0",
    "gn:asciiname":"Santo Aleixo",
    "gn:country_code":"PT",
    "gn:dem":259,
    "gn:feature_class":"P",
    "gn:feature_code":"PPL",
    "gn:name":"Santo Aleixo",
    "gn:population":0,
    "gn:timezone":"Europe/Lisbon",
    "iso:country":"PT",
    "wof:name":"Santo Aleixo",
    "wof:placetype":"locality"
},
  "geometry": {"coordinates":[-7.14965,38.06863],"type":"Point"}
}