{
  "type": "Feature",
  "properties": {
    "gn:admin1_code":"13",
    "gn:admin2_code":"1016",
    "gn:admin3_code":"101613.0",
    "gn:asciiname":"Fradilhao",
    "gn:country_code":"PT",
    "gn:dem":457,
    "gn:feature_class":"P",
    "gn:feature_code":"PPL",
    "gn:name":"Fradilh\u00e3o",
    "gn:population":0,
    "gn:timezone":"Europe/Lisbon",
    "iso:country":"PT",
    "wof:name":"Fradilhao",
    "wof:placetype":"locality"
},
  "geometry": {"coordinates":[-8.80914,39.54347],"type":"Point"}
}