{
  "type": "Feature",
  "properties": {
    "gn:admin1_code":"20.0",
    "gn:admin2_code":"1601",
    "gn:admin3_code":"160145.0",
    "gn:asciiname":"Branda de Crastibo",
    "gn:country_code":"PT",
    "gn:dem":760,
    "gn:feature_class":"P",
    "gn:feature_code":"PPL",
    "gn:name":"Branda de Crastib\u00f4",
    "gn:population":0,
    "gn:timezone":"Europe/Lisbon",
    "iso:country":"PT",
    "wof:name":"Branda de Crastibo",
    "wof:placetype":"locality"
},
  "geometry": {"coordinates":[-8.33294,41.98601],"type":"Point"}
}