{
  "type": "Feature",
  "properties": {
    "gn:admin1_code":"09",
    "gn:admin2_code":"0808",
    "gn:admin3_code":"80809.0",
    "gn:asciiname":"Alfeicao",
    "gn:country_code":"PT",
    "gn:dem":239,
    "gn:feature_class":"P",
    "gn:feature_code":"PPL",
    "gn:name":"Alfei\u00e7\u00e3o",
    "gn:population":0,
    "gn:timezone":"Europe/Lisbon",
    "iso:country":"PT",
    "wof:name":"Alfeicao",
    "wof:placetype":"locality"
},
  "geometry": {"coordinates":[-8.05204,37.15722],"type":"Point"}
}