{
  "type": "Feature",
  "properties": {
    "gn:admin1_code":"23.0",
    "gn:admin2_code":"4301",
    "gn:admin3_code":"430118.0",
    "gn:asciiname":"Senhora do Rosario",
    "gn:country_code":"PT",
    "gn:dem":156,
    "gn:feature_class":"P",
    "gn:feature_code":"PPL",
    "gn:name":"Senhora do Ros\u00e1rio",
    "gn:population":0,
    "gn:timezone":"Atlantic/Azores",
    "iso:country":"PT",
    "wof:name":"Senhora do Rosario",
    "wof:placetype":"locality"
},
  "geometry": {"coordinates":[-27.26667,38.68333],"type":"Point"}
}