{
  "type": "Feature",
  "properties": {
    "gn:admin1_code":"6.0",
    "gn:admin2_code":"0501",
    "gn:admin3_code":"50102.0",
    "gn:asciiname":"Malpique",
    "gn:country_code":"PT",
    "gn:dem":479,
    "gn:feature_class":"P",
    "gn:feature_code":"PPL",
    "gn:name":"Malpique",
    "gn:population":0,
    "gn:timezone":"Europe/Lisbon",
    "iso:country":"PT",
    "wof:name":"Malpique",
    "wof:placetype":"locality"
},
  "geometry": {"coordinates":[-7.36538,40.32004000000001],"type":"Point"}
}