{
  "type": "Feature",
  "properties": {
    "gn:admin1_code":"18",
    "gn:admin2_code":"1414",
    "gn:admin3_code":"141408.0",
    "gn:asciiname":"Casais de Vale de Obidos",
    "gn:country_code":"PT",
    "gn:dem":96,
    "gn:feature_class":"P",
    "gn:feature_code":"PPL",
    "gn:name":"Casais de Vale de Obidos",
    "gn:population":0,
    "gn:timezone":"Europe/Lisbon",
    "iso:country":"PT",
    "wof:name":"Casais de Vale de Obidos",
    "wof:placetype":"locality"
},
  "geometry": {"coordinates":[-8.96017,39.30907],"type":"Point"}
}