{
  "type": "Feature",
  "properties": {
    "gn:admin1_code":"13",
    "gn:admin2_code":"1001",
    "gn:admin3_code":"100108.0",
    "gn:asciiname":"Fonte Santa",
    "gn:country_code":"PT",
    "gn:dem":159,
    "gn:feature_class":"P",
    "gn:feature_code":"PPL",
    "gn:name":"Fonte Santa",
    "gn:population":0,
    "gn:timezone":"Europe/Lisbon",
    "iso:country":"PT",
    "wof:name":"Fonte Santa",
    "wof:placetype":"locality"
},
  "geometry": {"coordinates":[-8.94626,39.51531],"type":"Point"}
}