{
  "type": "Feature",
  "properties": {
    "gn:country":"PT",
    "gn:fcode":"PPL",
    "gn:population":4405,
    "iso:country":"PT",
    "name:und_x_variant":[
        "Santa Catharina da Serra"
    ],
    "qs_pg:aaroncc":"PT",
    "qs_pg:gn_country":"PT",
    "qs_pg:gn_fcode":"PPL",
    "qs_pg:gn_pop":4405,
    "qs_pg:name":"Santa Catarina da Serra",
    "qs_pg:name_adm0":"Portugal",
    "qs_pg:name_adm1":"Leiria",
    "qs_pg:photos_9k":1,
    "qs_pg:photos_9r":1,
    "qs_pg:photos_all":2,
    "qs_pg:photos_sr":0,
    "qs_pg:pop_sr":4,
    "qs_pg:qs_pg_placetype":"locality",
    "qs_pg:qs_pg_placetype_gp":"Town",
    "qs_pg:woe_adm0":23424925,
    "woe:adm0_id":23424925,
    "woe:name_adm0":"Portugal",
    "woe:name_adm1":"Leiria",
    "woe:placetype":"Town",
    "wof:name":"Santa Catarina da Serra",
    "wof:placetype":"locality",
    "wof:population":4405
},
  "geometry": {"coordinates":[-8.68679,39.6796],"type":"Point"}
}