{
  "type": "Feature",
  "properties": {
    "gn:admin1_code":"7.0",
    "gn:admin2_code":"0601",
    "gn:admin3_code":"60102.0",
    "gn:asciiname":"Maladao",
    "gn:country_code":"PT",
    "gn:dem":184,
    "gn:feature_class":"P",
    "gn:feature_code":"PPL",
    "gn:name":"Malad\u00e3o",
    "gn:population":0,
    "gn:timezone":"Europe/Lisbon",
    "iso:country":"PT",
    "wof:name":"Maladao",
    "wof:placetype":"locality"
},
  "geometry": {"coordinates":[-8.09894,40.24212],"type":"Point"}
}