{
  "type": "Feature",
  "properties": {
    "gn:admin1_code":"4.0",
    "gn:admin2_code":"0303",
    "gn:admin3_code":"30306.0",
    "gn:asciiname":"Cruz",
    "gn:country_code":"PT",
    "gn:dem":140,
    "gn:feature_class":"P",
    "gn:feature_code":"PPL",
    "gn:name":"Cruz",
    "gn:population":0,
    "gn:timezone":"Europe/Lisbon",
    "iso:country":"PT",
    "name:ces_x_preferred":[
        "Cruz"
    ],
    "name:deu_x_preferred":[
        "Cruz"
    ],
    "wof:name":"Cruz",
    "wof:placetype":"locality"
},
  "geometry": {"coordinates":[-8.44962,41.51414000000001],"type":"Point"}
}