{
  "type": "Feature",
  "properties": {
    "gn:admin1_code":"03",
    "gn:admin2_code":"0209",
    "gn:admin3_code":"20907.0",
    "gn:asciiname":"Corcha",
    "gn:country_code":"PT",
    "gn:dem":277,
    "gn:feature_class":"P",
    "gn:feature_code":"PPL",
    "gn:name":"Corcha",
    "gn:population":0,
    "gn:timezone":"Europe/Lisbon",
    "iso:country":"PT",
    "wof:name":"Corcha",
    "wof:placetype":"locality"
},
  "geometry": {"coordinates":[-7.84474,37.4708],"type":"Point"}
}