{
  "type": "Feature",
  "properties": {
    "gn:admin1_code":"20",
    "gn:admin2_code":"1604",
    "gn:admin3_code":"160411.0",
    "gn:asciiname":"Souto Fiscal",
    "gn:country_code":"PT",
    "gn:dem":268,
    "gn:feature_class":"P",
    "gn:feature_code":"PPL",
    "gn:name":"Souto Fiscal",
    "gn:population":0,
    "gn:timezone":"Europe/Lisbon",
    "iso:country":"PT",
    "wof:name":"Souto Fiscal",
    "wof:placetype":"locality"
},
  "geometry": {"coordinates":[-8.43526,42.04271],"type":"Point"}
}