{
  "type": "Feature",
  "properties": {
    "gn:admin1_code":"5.0",
    "gn:admin2_code":"0412",
    "gn:admin3_code":"41233.0",
    "gn:asciiname":"Cidoes",
    "gn:country_code":"PT",
    "gn:dem":474,
    "gn:feature_class":"P",
    "gn:feature_code":"PPL",
    "gn:name":"Cid\u00f5es",
    "gn:population":0,
    "gn:timezone":"Europe/Lisbon",
    "iso:country":"PT",
    "wof:name":"Cidoes",
    "wof:placetype":"locality"
},
  "geometry": {"coordinates":[-7.02243,41.78832],"type":"Point"}
}