{
  "type": "Feature",
  "properties": {
    "gn:admin1_code":"11.0",
    "gn:admin2_code":"0913",
    "gn:admin3_code":"91308.0",
    "gn:asciiname":"Freches",
    "gn:country_code":"PT",
    "gn:dem":568,
    "gn:feature_class":"P",
    "gn:feature_code":"PPL",
    "gn:name":"Freches",
    "gn:population":0,
    "gn:timezone":"Europe/Lisbon",
    "iso:country":"PT",
    "wof:name":"Freches",
    "wof:placetype":"locality"
},
  "geometry": {"coordinates":[-7.34809,40.73222],"type":"Point"}
}