{
  "type": "Feature",
  "properties": {
    "gn:gn_country":"PT",
    "gn:gn_fcode":"ADM3",
    "gn:gn_pop":0,
    "iso:country":"PT",
    "name:dut_x_preferred":[
        "Aguieira"
    ],
    "name:eng_x_preferred":[
        "Aguieira"
    ],
    "name:fre_x_preferred":[
        "Aguieira"
    ],
    "name:ger_x_preferred":[
        "Aguieira"
    ],
    "name:kaz_x_preferred":[
        "\u0410\u0433\u0438\u0435\u0439\u0440\u0430"
    ],
    "name:ltz_x_preferred":[
        "Aguieira"
    ],
    "name:nan_x_preferred":[
        "Aguieira"
    ],
    "name:por_x_preferred":[
        "Aguieira"
    ],
    "name:rus_x_preferred":[
        "\u0410\u0433\u0438\u0435\u0439\u0440\u0430"
    ],
    "name:spa_x_preferred":[
        "Aguieira"
    ],
    "qs_pg:aaroncc":"PT",
    "qs_pg:gn_country":"PT",
    "qs_pg:gn_fcode":"ADM3",
    "qs_pg:gn_pop":0,
    "qs_pg:name":"Aguieira",
    "qs_pg:name_adm0":"Portugal",
    "qs_pg:name_adm1":"Viseu",
    "qs_pg:photos_9k":1,
    "qs_pg:photos_9r":1,
    "qs_pg:photos_all":4,
    "qs_pg:photos_sr":0,
    "qs_pg:pop_sr":0,
    "qs_pg:qs_pg_placetype":"locality",
    "qs_pg:qs_pg_placetype_gp":"Town",
    "qs_pg:woe_adm0":23424925,
    "woe:adm0_id":23424925,
    "woe:name_adm0":"Portugal",
    "woe:name_adm1":"Viseu",
    "woe:placetype":"Town",
    "wof:name":"Aguieira",
    "wof:placetype":"locality"
},
  "geometry": {"coordinates":[-7.92372,40.5276],"type":"Point"}
}