{
  "type": "Feature",
  "properties": {
    "gn:admin1_code":"18",
    "gn:admin2_code":"1409",
    "gn:admin3_code":"140908.0",
    "gn:asciiname":"Vale de Mulheres",
    "gn:country_code":"PT",
    "gn:dem":94,
    "gn:feature_class":"P",
    "gn:feature_code":"PPL",
    "gn:name":"Vale de Mulheres",
    "gn:population":0,
    "gn:timezone":"Europe/Lisbon",
    "iso:country":"PT",
    "wof:name":"Vale de Mulheres",
    "wof:placetype":"locality"
},
  "geometry": {"coordinates":[-8.36673,38.89906],"type":"Point"}
}