{
  "type": "Feature",
  "properties": {
    "gn:admin1_code":"18",
    "gn:admin2_code":"1418",
    "gn:admin3_code":"141811.0",
    "gn:asciiname":"Carvalheiros",
    "gn:country_code":"PT",
    "gn:dem":121,
    "gn:feature_class":"P",
    "gn:feature_code":"PPL",
    "gn:name":"Carvalheiros",
    "gn:population":0,
    "gn:timezone":"Europe/Lisbon",
    "iso:country":"PT",
    "wof:name":"Carvalheiros",
    "wof:placetype":"locality"
},
  "geometry": {"coordinates":[-8.3844,39.61446],"type":"Point"}
}