{
  "type": "Feature",
  "properties": {
    "gn:admin1_code":"17",
    "gn:admin2_code":"1311",
    "gn:admin3_code":"131122.0",
    "gn:asciiname":"Senhora do Vale",
    "gn:country_code":"PT",
    "gn:dem":140,
    "gn:feature_class":"P",
    "gn:feature_code":"PPL",
    "gn:name":"Senhora do Vale",
    "gn:population":0,
    "gn:timezone":"Europe/Lisbon",
    "iso:country":"PT",
    "wof:name":"Senhora do Vale",
    "wof:placetype":"locality"
},
  "geometry": {"coordinates":[-8.35,41.16667],"type":"Point"}
}