{
  "type": "Feature",
  "properties": {
    "gn:admin1_code":"02",
    "gn:admin2_code":"0107",
    "gn:admin3_code":"10705.0",
    "gn:asciiname":"Silvaldinho",
    "gn:country_code":"PT",
    "gn:dem":71,
    "gn:feature_class":"P",
    "gn:feature_code":"PPL",
    "gn:name":"Silvaldinho",
    "gn:population":0,
    "gn:timezone":"Europe/Lisbon",
    "iso:country":"PT",
    "wof:name":"Silvaldinho",
    "wof:placetype":"locality"
},
  "geometry": {"coordinates":[-8.62679,40.98875],"type":"Point"}
}