{
  "type": "Feature",
  "properties": {
    "gn:admin1_code":"7.0",
    "gn:admin2_code":"0615",
    "gn:admin3_code":"61509.0",
    "gn:asciiname":"Cascao",
    "gn:country_code":"PT",
    "gn:dem":105,
    "gn:feature_class":"P",
    "gn:feature_code":"PPL",
    "gn:name":"Casc\u00e3o",
    "gn:population":0,
    "gn:timezone":"Europe/Lisbon",
    "iso:country":"PT",
    "wof:name":"Cascao",
    "wof:placetype":"locality"
},
  "geometry": {"coordinates":[-8.55625,40.07358],"type":"Point"}
}