{
  "type": "Feature",
  "properties": {
    "gn:admin1_code":"09",
    "gn:admin2_code":"0805",
    "gn:admin3_code":"80506.0",
    "gn:asciiname":"Arabia",
    "gn:country_code":"PT",
    "gn:dem":8,
    "gn:feature_class":"P",
    "gn:feature_code":"PPL",
    "gn:name":"Ar\u00e1bia",
    "gn:population":0,
    "gn:timezone":"Europe/Lisbon",
    "iso:country":"PT",
    "wof:name":"Arabia",
    "wof:placetype":"locality"
},
  "geometry": {"coordinates":[-7.96667,37.01667],"type":"Point"}
}