{
  "type": "Feature",
  "properties": {
    "gn:admin1_code":"14",
    "gn:admin2_code":"1111",
    "gn:admin3_code":"111114.0",
    "gn:asciiname":"Mortena",
    "gn:country_code":"PT",
    "gn:dem":174,
    "gn:feature_class":"P",
    "gn:feature_code":"PPL",
    "gn:name":"Mortena",
    "gn:population":0,
    "gn:timezone":"Europe/Lisbon",
    "iso:country":"PT",
    "name:und_x_variant":[
        "Morlenas",
        "Mortena"
    ],
    "wof:name":"Mortena",
    "wof:placetype":"locality"
},
  "geometry": {"coordinates":[-9.31695,38.84571],"type":"Point"}
}