{
  "type": "Feature",
  "properties": {
    "gn:admin1_code":"04",
    "gn:admin2_code":"0311",
    "gn:admin3_code":"31107.0",
    "gn:asciiname":"Terrafeita",
    "gn:country_code":"PT",
    "gn:dem":500,
    "gn:feature_class":"P",
    "gn:feature_code":"PPL",
    "gn:name":"Terrafeita",
    "gn:population":0,
    "gn:timezone":"Europe/Lisbon",
    "iso:country":"PT",
    "wof:name":"Terrafeita",
    "wof:placetype":"locality"
},
  "geometry": {"coordinates":[-8.15677,41.64582],"type":"Point"}
}