{
  "type": "Feature",
  "properties": {
    "gn:country":"PT",
    "gn:fcode":"PPL",
    "gn:population":0,
    "iso:country":"PT",
    "name:nld_x_preferred":[
        "Casal"
    ],
    "name:swe_x_preferred":[
        "Casal"
    ],
    "qs_pg:aaroncc":"PT",
    "qs_pg:gn_country":"PT",
    "qs_pg:gn_fcode":"PPL",
    "qs_pg:gn_pop":0,
    "qs_pg:name":"Casal",
    "qs_pg:name_adm0":"Portugal",
    "qs_pg:name_adm1":"Porto",
    "qs_pg:photos_9r":0,
    "qs_pg:photos_sr":0,
    "qs_pg:pop_sr":0,
    "qs_pg:qs_pg_placetype":"locality",
    "qs_pg:qs_pg_placetype_gp":"Town",
    "qs_pg:woe_adm0":23424925,
    "woe:adm0_id":23424925,
    "woe:name_adm0":"Portugal",
    "woe:name_adm1":"Porto",
    "woe:placetype":"Town",
    "wof:name":"Casal",
    "wof:placetype":"locality"
},
  "geometry": {"coordinates":[-8.09848,41.24718],"type":"Point"}
}