{
  "type": "Feature",
  "properties": {
    "gn:admin1_code":"22.0",
    "gn:admin2_code":"1821",
    "gn:admin3_code":"182114.0",
    "gn:asciiname":"Couco",
    "gn:country_code":"PT",
    "gn:dem":290,
    "gn:feature_class":"P",
    "gn:feature_code":"PPL",
    "gn:name":"Cou\u00e7o",
    "gn:population":0,
    "gn:timezone":"Europe/Lisbon",
    "iso:country":"PT",
    "wof:name":"Couco",
    "wof:placetype":"locality"
},
  "geometry": {"coordinates":[-8.06353,40.48618],"type":"Point"}
}