{
  "type": "Feature",
  "properties": {
    "gn:admin1_code":"20",
    "gn:admin2_code":"1605",
    "gn:admin3_code":"160516.0",
    "gn:asciiname":"Santa",
    "gn:country_code":"PT",
    "gn:dem":342,
    "gn:feature_class":"P",
    "gn:feature_code":"PPL",
    "gn:name":"Santa",
    "gn:population":0,
    "gn:timezone":"Europe/Lisbon",
    "iso:country":"PT",
    "name:ara_x_preferred":[
        "\u0633\u0627\u0646\u062a\u0627"
    ],
    "name:ben_x_preferred":[
        "\u09b8\u09be\u09a8\u09cd\u09a4\u09be"
    ],
    "name:ell_x_preferred":[
        "\u03a3\u03ac\u03bd\u03c4\u03b1"
    ],
    "name:fas_x_preferred":[
        "\u0633\u0627\u0646\u062a\u0627"
    ],
    "name:heb_x_preferred":[
        "\u05e1\u05e0\u05d8\u05d4"
    ],
    "name:hin_x_preferred":[
        "\u0938\u0947\u0902\u091f\u093e"
    ],
    "name:hun_x_preferred":[
        "Santa"
    ],
    "name:ind_x_preferred":[
        "Santa"
    ],
    "name:kor_x_preferred":[
        "\uc0b0\ud0c0"
    ],
    "name:pol_x_preferred":[
        "Santa"
    ],
    "name:rus_x_preferred":[
        "\u0440\u0435\u043a\u0430 \u0421\u0430\u043d\u0442\u0430"
    ],
    "name:swe_x_preferred":[
        "R\u00edo Santa"
    ],
    "name:tur_x_preferred":[
        "Santa"
    ],
    "name:urd_x_preferred":[
        "\u0633\u0627\u0646\u062a\u0627"
    ],
    "name:vie_x_preferred":[
        "S\u00f4ng Santa"
    ],
    "wof:name":"Santa",
    "wof:placetype":"locality"
},
  "geometry": {"coordinates":[-8.55581,41.91749],"type":"Point"}
}