{
  "type": "Feature",
  "properties": {
    "gn:admin1_code":"20",
    "gn:admin2_code":"1605",
    "gn:admin3_code":"160516.0",
    "gn:asciiname":"Santa",
    "gn:country_code":"PT",
    "gn:dem":342,
    "gn:feature_class":"P",
    "gn:feature_code":"PPL",
    "gn:name":"Santa",
    "gn:population":0,
    "gn:timezone":"Europe/Lisbon",
    "iso:country":"PT",
    "wof:name":"Santa",
    "wof:placetype":"locality"
},
  "geometry": {"coordinates":[-8.55581,41.91749],"type":"Point"}
}