{
  "type": "Feature",
  "properties": {
    "gn:country":"PT",
    "gn:fcode":"PPL",
    "gn:population":0,
    "iso:country":"PT",
    "name:ceb_x_preferred":[
        "Paradela"
    ],
    "name:deu_x_preferred":[
        "Paradela"
    ],
    "name:glg_x_preferred":[
        "Paradela"
    ],
    "name:nld_x_preferred":[
        "Paradela"
    ],
    "name:pol_x_preferred":[
        "Paradela"
    ],
    "name:por_x_preferred":[
        "Paradela"
    ],
    "name:rus_x_preferred":[
        "\u041f\u0430\u0440\u0430\u0434\u0435\u043b\u0430"
    ],
    "name:spa_x_preferred":[
        "Paradela"
    ],
    "name:swe_x_preferred":[
        "Paradela"
    ],
    "name:tur_x_preferred":[
        "Paradela"
    ],
    "name:ukr_x_preferred":[
        "\u041f\u0430\u0440\u0430\u0434\u0435\u043b\u0430"
    ],
    "qs_pg:aaroncc":"PT",
    "qs_pg:gn_country":"PT",
    "qs_pg:gn_fcode":"PPL",
    "qs_pg:gn_pop":0,
    "qs_pg:name":"Paradela",
    "qs_pg:name_adm0":"Portugal",
    "qs_pg:name_adm1":"Braga",
    "qs_pg:photos_9r":0,
    "qs_pg:photos_sr":0,
    "qs_pg:pop_sr":0,
    "qs_pg:qs_pg_placetype":"locality",
    "qs_pg:qs_pg_placetype_gp":"Town",
    "qs_pg:woe_adm0":23424925,
    "woe:adm0_id":23424925,
    "woe:name_adm0":"Portugal",
    "woe:name_adm1":"Braga",
    "woe:placetype":"Town",
    "wof:name":"Paradela",
    "wof:placetype":"locality"
},
  "geometry": {"coordinates":[-8.68038,41.46216],"type":"Point"}
}