{
  "type": "Feature",
  "properties": {
    "gn:admin1_code":"09",
    "gn:admin2_code":"0808",
    "gn:admin3_code":"80809.0",
    "gn:asciiname":"Momprole",
    "gn:country_code":"PT",
    "gn:dem":190,
    "gn:feature_class":"P",
    "gn:feature_code":"PPL",
    "gn:name":"Momprol\u00e9",
    "gn:population":0,
    "gn:timezone":"Europe/Lisbon",
    "iso:country":"PT",
    "wof:name":"Momprole",
    "wof:placetype":"locality"
},
  "geometry": {"coordinates":[-8.06774,37.15363],"type":"Point"}
}