{
  "type": "Feature",
  "properties": {
    "gn:country":"PT",
    "gn:fcode":"PPL",
    "gn:population":0,
    "iso:country":"PT",
    "name:deu_x_preferred":[
        "Arga de Baixo"
    ],
    "name:eng_x_preferred":[
        "Arga de Baixo"
    ],
    "name:fra_x_preferred":[
        "Arga de Baixo"
    ],
    "name:nld_x_preferred":[
        "Arga de Baixo"
    ],
    "name:por_x_preferred":[
        "Arga de Baixo"
    ],
    "name:rus_x_preferred":[
        "\u0410\u0440\u0433\u0430-\u0434\u0435-\u0411\u0430\u0439\u0448\u0443"
    ],
    "name:spa_x_preferred":[
        "Arga de Baixo"
    ],
    "qs_pg:aaroncc":"PT",
    "qs_pg:gn_country":"PT",
    "qs_pg:gn_fcode":"PPL",
    "qs_pg:gn_pop":0,
    "qs_pg:name":"Arga de Baixo",
    "qs_pg:name_adm0":"Portugal",
    "qs_pg:name_adm1":"Viana do Castelo",
    "qs_pg:photos":77,
    "qs_pg:photos_1k":16,
    "qs_pg:photos_9k":1,
    "qs_pg:photos_9r":3,
    "qs_pg:photos_all":77,
    "qs_pg:photos_sr":3,
    "qs_pg:pop_sr":0,
    "qs_pg:qs_pg_placetype":"locality",
    "qs_pg:qs_pg_placetype_gp":"Town",
    "qs_pg:woe_adm0":23424925,
    "woe:adm0_id":23424925,
    "woe:name_adm0":"Portugal",
    "woe:name_adm1":"Viana do Castelo",
    "woe:placetype":"Town",
    "wof:name":"Arga de Baixo",
    "wof:placetype":"locality"
},
  "geometry": {"coordinates":[-8.71268,41.84568],"type":"Point"}
}