{
  "type": "Feature",
  "properties": {
    "gn:admin1_code":"22",
    "gn:admin2_code":"1823",
    "gn:admin3_code":"182304.0",
    "gn:asciiname":"Silgueiros",
    "gn:country_code":"PT",
    "gn:dem":498,
    "gn:feature_class":"P",
    "gn:feature_code":"PPL",
    "gn:name":"Silgueiros",
    "gn:population":0,
    "gn:timezone":"Europe/Lisbon",
    "iso:country":"PT",
    "wof:name":"Silgueiros",
    "wof:placetype":"locality"
},
  "geometry": {"coordinates":[-8.01155,40.71245],"type":"Point"}
}