{
  "type": "Feature",
  "properties": {
    "gn:admin1_code":"2.0",
    "gn:admin2_code":"0104",
    "gn:admin3_code":"10418.0",
    "gn:asciiname":"Folgosinho",
    "gn:country_code":"PT",
    "gn:dem":275,
    "gn:feature_class":"P",
    "gn:feature_code":"PPL",
    "gn:name":"Folgosinho",
    "gn:population":0,
    "gn:timezone":"Europe/Lisbon",
    "iso:country":"PT",
    "wof:name":"Folgosinho",
    "wof:placetype":"locality"
},
  "geometry": {"coordinates":[-8.3262,40.96182],"type":"Point"}
}