{
  "type": "Feature",
  "properties": {
    "gn:admin1_code":"22.0",
    "gn:admin2_code":"1818",
    "gn:admin3_code":"181809.0",
    "gn:asciiname":"Freixinho",
    "gn:country_code":"PT",
    "gn:dem":568,
    "gn:feature_class":"P",
    "gn:feature_code":"PPL",
    "gn:name":"Freixinho",
    "gn:population":0,
    "gn:timezone":"Europe/Lisbon",
    "iso:country":"PT",
    "wof:name":"Freixinho",
    "wof:placetype":"locality"
},
  "geometry": {"coordinates":[-7.52967,40.93694],"type":"Point"}
}