{
  "type": "Feature",
  "properties": {
    "gn:admin1_code":"2.0",
    "gn:admin2_code":"0115",
    "gn:admin3_code":"11507.0",
    "gn:asciiname":"Molaredo",
    "gn:country_code":"PT",
    "gn:dem":22,
    "gn:feature_class":"P",
    "gn:feature_code":"PPL",
    "gn:name":"Molaredo",
    "gn:population":0,
    "gn:timezone":"Europe/Lisbon",
    "iso:country":"PT",
    "wof:name":"Molaredo",
    "wof:placetype":"locality"
},
  "geometry": {"coordinates":[-8.59863,40.83775],"type":"Point"}
}