{
  "type": "Feature",
  "properties": {
    "gn:admin1_code":"17.0",
    "gn:admin2_code":"1312",
    "gn:admin3_code":"131210.0",
    "gn:asciiname":"Bairro Silva Braga",
    "gn:country_code":"PT",
    "gn:dem":100,
    "gn:feature_class":"P",
    "gn:feature_code":"PPL",
    "gn:name":"Bairro Silva Braga",
    "gn:population":0,
    "gn:timezone":"Europe/Lisbon",
    "iso:country":"PT",
    "wof:name":"Bairro Silva Braga",
    "wof:placetype":"locality"
},
  "geometry": {"coordinates":[-8.62681,41.17494],"type":"Point"}
}