{
  "type": "Feature",
  "properties": {
    "gn:admin1_code":"4.0",
    "gn:admin2_code":"0308",
    "gn:admin3_code":"30829.0",
    "gn:asciiname":"Mascotelos",
    "gn:country_code":"PT",
    "gn:dem":284,
    "gn:feature_class":"P",
    "gn:feature_code":"PPL",
    "gn:name":"Mascotelos",
    "gn:population":0,
    "gn:timezone":"Europe/Lisbon",
    "iso:country":"PT",
    "wof:name":"Mascotelos",
    "wof:placetype":"locality"
},
  "geometry": {"coordinates":[-8.31636,41.42312],"type":"Point"}
}