{
  "type": "Feature",
  "properties": {
    "gn:admin1_code":"14",
    "gn:admin2_code":"1112",
    "gn:admin3_code":"111203.0",
    "gn:asciiname":"Cabeda",
    "gn:country_code":"PT",
    "gn:dem":191,
    "gn:feature_class":"P",
    "gn:feature_code":"PPL",
    "gn:name":"Cabeda",
    "gn:population":0,
    "gn:timezone":"Europe/Lisbon",
    "iso:country":"PT",
    "wof:name":"Cabeda",
    "wof:placetype":"locality"
},
  "geometry": {"coordinates":[-9.17122,39.00673],"type":"Point"}
}