{
  "type": "Feature",
  "properties": {
    "gn:admin1_code":"5.0",
    "gn:admin2_code":"0408",
    "gn:admin3_code":"40805.0",
    "gn:asciiname":"Brunhozinho",
    "gn:country_code":"PT",
    "gn:dem":734,
    "gn:feature_class":"P",
    "gn:feature_code":"PPL",
    "gn:name":"Brunhozinho",
    "gn:population":0,
    "gn:timezone":"Europe/Lisbon",
    "iso:country":"PT",
    "wof:name":"Brunhozinho",
    "wof:placetype":"locality"
},
  "geometry": {"coordinates":[-6.5215,41.35952],"type":"Point"}
}