{
  "type": "Feature",
  "properties": {
    "gn:admin1_code":"17.0",
    "gn:admin2_code":"1311",
    "gn:admin3_code":"131120.0",
    "gn:asciiname":"Novelas",
    "gn:country_code":"PT",
    "gn:dem":163,
    "gn:feature_class":"P",
    "gn:feature_code":"PPL",
    "gn:name":"Novelas",
    "gn:population":0,
    "gn:timezone":"Europe/Lisbon",
    "iso:country":"PT",
    "wof:name":"Novelas",
    "wof:placetype":"locality"
},
  "geometry": {"coordinates":[-8.28911,41.2266],"type":"Point"}
}