{
  "type": "Feature",
  "properties": {
    "gn:admin1_code":"18",
    "gn:admin2_code":"1418",
    "gn:admin3_code":"141814.0",
    "gn:asciiname":"Casalinho",
    "gn:country_code":"PT",
    "gn:dem":200,
    "gn:feature_class":"P",
    "gn:feature_code":"PPL",
    "gn:name":"Casalinho",
    "gn:population":0,
    "gn:timezone":"Europe/Lisbon",
    "iso:country":"PT",
    "wof:name":"Casalinho",
    "wof:placetype":"locality"
},
  "geometry": {"coordinates":[-8.45581,39.66397],"type":"Point"}
}