{
  "type": "Feature",
  "properties": {
    "gn:admin1_code":"7.0",
    "gn:admin2_code":"0603",
    "gn:admin3_code":"60304.0",
    "gn:asciiname":"Antanhol",
    "gn:country_code":"PT",
    "gn:dem":110,
    "gn:feature_class":"P",
    "gn:feature_code":"PPL",
    "gn:name":"Antanhol",
    "gn:population":0,
    "gn:timezone":"Europe/Lisbon",
    "iso:country":"PT",
    "wof:name":"Antanhol",
    "wof:placetype":"locality"
},
  "geometry": {"coordinates":[-8.46334,40.16837],"type":"Point"}
}