{
  "type": "Feature",
  "properties": {
    "gn:admin1_code":"22",
    "gn:admin2_code":"1810",
    "gn:admin3_code":"181006.0",
    "gn:asciiname":"Sobreira",
    "gn:country_code":"PT",
    "gn:dem":416,
    "gn:feature_class":"P",
    "gn:feature_code":"PPL",
    "gn:name":"Sobreira",
    "gn:population":0,
    "gn:timezone":"Europe/Lisbon",
    "iso:country":"PT",
    "name:ceb_x_preferred":[
        "Sobreira"
    ],
    "name:fra_x_preferred":[
        "Sobreira"
    ],
    "name:glg_x_preferred":[
        "Sobreira"
    ],
    "wof:name":"Sobreira",
    "wof:placetype":"locality"
},
  "geometry": {"coordinates":[-8.27502,40.68083],"type":"Point"}
}