{
  "type": "Feature",
  "properties": {
    "gn:admin1_code":"2.0",
    "gn:admin2_code":"0101",
    "gn:admin3_code":"10119.0",
    "gn:asciiname":"Arrancada",
    "gn:country_code":"PT",
    "gn:dem":48,
    "gn:feature_class":"P",
    "gn:feature_code":"PPL",
    "gn:name":"Arrancada",
    "gn:population":0,
    "gn:timezone":"Europe/Lisbon",
    "iso:country":"PT",
    "wof:name":"Arrancada",
    "wof:placetype":"locality"
},
  "geometry": {"coordinates":[-8.42388,40.61771],"type":"Point"}
}