{
  "type": "Feature",
  "properties": {
    "gn:admin1_code":"17",
    "gn:admin2_code":"1316",
    "gn:admin3_code":"131625.0",
    "gn:asciiname":"Touguinho",
    "gn:country_code":"PT",
    "gn:dem":42,
    "gn:feature_class":"P",
    "gn:feature_code":"PPL",
    "gn:name":"Touguinho",
    "gn:population":0,
    "gn:timezone":"Europe/Lisbon",
    "iso:country":"PT",
    "wof:name":"Touguinho",
    "wof:placetype":"locality"
},
  "geometry": {"coordinates":[-8.69986,41.38246],"type":"Point"}
}