{
  "type": "Feature",
  "properties": {
    "gn:admin1_code":"18",
    "gn:admin2_code":"1418",
    "gn:admin3_code":"141811.0",
    "gn:asciiname":"Palhava",
    "gn:country_code":"PT",
    "gn:dem":74,
    "gn:feature_class":"P",
    "gn:feature_code":"PPL",
    "gn:name":"Palhav\u00e3",
    "gn:population":0,
    "gn:timezone":"Europe/Lisbon",
    "iso:country":"PT",
    "wof:name":"Palhava",
    "wof:placetype":"locality"
},
  "geometry": {"coordinates":[-8.39814,39.60029],"type":"Point"}
}