{
  "type": "Feature",
  "properties": {
    "gn:admin1_code":"20.0",
    "gn:admin2_code":"1606",
    "gn:admin3_code":"160609.0",
    "gn:asciiname":"Germil",
    "gn:country_code":"PT",
    "gn:dem":616,
    "gn:feature_class":"P",
    "gn:feature_code":"PPL",
    "gn:name":"Germil",
    "gn:population":0,
    "gn:timezone":"Europe/Lisbon",
    "iso:country":"PT",
    "wof:name":"Germil",
    "wof:placetype":"locality"
},
  "geometry": {"coordinates":[-8.26481,41.78155],"type":"Point"}
}