{
  "type": "Feature",
  "properties": {
    "gn:admin1_code":"17.0",
    "gn:admin2_code":"1301",
    "gn:admin3_code":"130107.0",
    "gn:asciiname":"Giao",
    "gn:country_code":"PT",
    "gn:dem":415,
    "gn:feature_class":"P",
    "gn:feature_code":"PPL",
    "gn:name":"Gi\u00e3o",
    "gn:population":0,
    "gn:timezone":"Europe/Lisbon",
    "iso:country":"PT",
    "wof:name":"Giao",
    "wof:placetype":"locality"
},
  "geometry": {"coordinates":[-7.97801,41.25164],"type":"Point"}
}