{
  "type": "Feature",
  "properties": {
    "gn:admin1_code":"02",
    "gn:admin2_code":"0103",
    "gn:admin3_code":"10313.0",
    "gn:asciiname":"Quinta do Perdigao",
    "gn:country_code":"PT",
    "gn:dem":77,
    "gn:feature_class":"P",
    "gn:feature_code":"PPL",
    "gn:name":"Quinta do Perdig\u00e3o",
    "gn:population":0,
    "gn:timezone":"Europe/Lisbon",
    "iso:country":"PT",
    "wof:name":"Quinta do Perdigao",
    "wof:placetype":"locality"
},
  "geometry": {"coordinates":[-8.56927,40.43716],"type":"Point"}
}