{
  "type": "Feature",
  "properties": {
    "gn:admin1_code":"02",
    "gn:admin2_code":"0108",
    "gn:admin3_code":"10807.0",
    "gn:asciiname":"Sao Geraldo",
    "gn:country_code":"PT",
    "gn:dem":7,
    "gn:feature_class":"P",
    "gn:feature_code":"PPL",
    "gn:name":"S\u00e3o Geraldo",
    "gn:population":0,
    "gn:timezone":"Europe/Lisbon",
    "iso:country":"PT",
    "wof:name":"Sao Geraldo",
    "wof:placetype":"locality"
},
  "geometry": {"coordinates":[-8.61349,40.74935],"type":"Point"}
}