{
  "type": "Feature",
  "properties": {
    "gn:admin1_code":"04",
    "gn:admin2_code":"0313",
    "gn:admin3_code":"31351.0",
    "gn:asciiname":"Valbom",
    "gn:country_code":"PT",
    "gn:dem":136,
    "gn:feature_class":"P",
    "gn:feature_code":"PPL",
    "gn:name":"Valbom",
    "gn:population":0,
    "gn:timezone":"Europe/Lisbon",
    "iso:country":"PT",
    "name:und_x_variant":[
        "S\u00e3o Pedro",
        "Valbom"
    ],
    "wof:name":"Valbom",
    "wof:placetype":"locality"
},
  "geometry": {"coordinates":[-8.3484,41.70566],"type":"Point"}
}