{
  "type": "Feature",
  "properties": {
    "gn:admin1_code":"04",
    "gn:admin2_code":"0313",
    "gn:admin3_code":"31351.0",
    "gn:asciiname":"Valbom",
    "gn:country_code":"PT",
    "gn:dem":136,
    "gn:feature_class":"P",
    "gn:feature_code":"PPL",
    "gn:name":"Valbom",
    "gn:population":0,
    "gn:timezone":"Europe/Lisbon",
    "iso:country":"PT",
    "name:ara_x_preferred":[
        "\u0641\u0627\u0644\u0628\u0648\u0645"
    ],
    "name:deu_x_preferred":[
        "Valbom"
    ],
    "name:fas_x_preferred":[
        "\u0648\u0627\u0644\u0628\u0648\u0645"
    ],
    "name:kat_x_preferred":[
        "\u10d5\u10d0\u10da\u10d1\u10dd\u10dc\u10d8"
    ],
    "name:kaz_x_preferred":[
        "\u0412\u0430\u043b\u0431\u043e\u043d"
    ],
    "name:mzn_x_preferred":[
        "\u0648\u0627\u0644\u0628\u0648\u0645"
    ],
    "name:nld_x_preferred":[
        "Valbom"
    ],
    "name:por_x_preferred":[
        "Valbom"
    ],
    "name:ron_x_preferred":[
        "Valbom"
    ],
    "name:rus_x_preferred":[
        "\u0412\u0430\u043b\u0431\u043e\u043d"
    ],
    "name:spa_x_preferred":[
        "Valbom"
    ],
    "name:srp_x_preferred":[
        "\u0412\u0430\u043b\u0431\u043e\u043c"
    ],
    "name:tur_x_preferred":[
        "Valbom"
    ],
    "name:und_x_variant":[
        "S\u00e3o Pedro"
    ],
    "name:zho_x_preferred":[
        "\u74e6\u5c14\u90a6"
    ],
    "wof:name":"Valbom",
    "wof:placetype":"locality"
},
  "geometry": {"coordinates":[-8.3484,41.70566],"type":"Point"}
}