{
  "type": "Feature",
  "properties": {
    "gn:admin1_code":"13",
    "gn:admin2_code":"1008",
    "gn:admin3_code":"100804.0",
    "gn:asciiname":"Carapinhal",
    "gn:country_code":"PT",
    "gn:dem":387,
    "gn:feature_class":"P",
    "gn:feature_code":"PPL",
    "gn:name":"Carapinhal",
    "gn:population":0,
    "gn:timezone":"Europe/Lisbon",
    "iso:country":"PT",
    "wof:name":"Carapinhal",
    "wof:placetype":"locality"
},
  "geometry": {"coordinates":[-8.28184,39.88041],"type":"Point"}
}