{
  "type": "Feature",
  "properties": {
    "gn:gn_country":"PT",
    "gn:gn_fcode":"PPL",
    "gn:gn_pop":0,
    "iso:country":"PT",
    "name:deu_x_preferred":[
        "Topo"
    ],
    "name:eng_x_preferred":[
        "Topo"
    ],
    "name:fra_x_preferred":[
        "Topo"
    ],
    "name:nld_x_preferred":[
        "Vila do Topo"
    ],
    "name:por_x_preferred":[
        "Topo"
    ],
    "name:rus_x_preferred":[
        "\u0412\u0438\u043b\u0430-\u0434\u0443-\u0422\u043e\u043f\u0443"
    ],
    "name:spa_x_preferred":[
        "Topo"
    ],
    "name:unk_x_variant":[
        "Villa do Topo"
    ],
    "qs_pg:aaroncc":"PT",
    "qs_pg:gn_country":"PT",
    "qs_pg:gn_fcode":"PPL",
    "qs_pg:gn_pop":0,
    "qs_pg:name":"Topo",
    "qs_pg:name_adm0":"Portugal",
    "qs_pg:name_adm1":"Azores",
    "qs_pg:photos":46,
    "qs_pg:photos_1k":9,
    "qs_pg:photos_9k":1,
    "qs_pg:photos_9r":2,
    "qs_pg:photos_all":46,
    "qs_pg:photos_sr":2,
    "qs_pg:pop_sr":0,
    "qs_pg:qs_pg_placetype":"locality",
    "qs_pg:qs_pg_placetype_gp":"Town",
    "qs_pg:woe_adm0":23424925,
    "woe:adm0_id":23424925,
    "woe:name_adm0":"Portugal",
    "woe:name_adm1":"Azores",
    "woe:placetype":"Town",
    "wof:name":"Topo",
    "wof:placetype":"locality"
},
  "geometry": {"coordinates":[-27.78333,38.55],"type":"Point"}
}