{
  "type": "Feature",
  "properties": {
    "gn:admin1_code":"09",
    "gn:admin2_code":"0813",
    "gn:admin3_code":"81308.0",
    "gn:asciiname":"Poco da Figueira",
    "gn:country_code":"PT",
    "gn:dem":58,
    "gn:feature_class":"P",
    "gn:feature_code":"PPL",
    "gn:name":"Po\u00e7o da Figueira",
    "gn:population":0,
    "gn:timezone":"Europe/Lisbon",
    "iso:country":"PT",
    "wof:name":"Poco da Figueira",
    "wof:placetype":"locality"
},
  "geometry": {"coordinates":[-8.26399,37.15908],"type":"Point"}
}