{
  "type": "Feature",
  "properties": {
    "gn:admin1_code":"09",
    "gn:admin2_code":"0808",
    "gn:admin3_code":"80802.0",
    "gn:asciiname":"Macheira",
    "gn:country_code":"PT",
    "gn:dem":246,
    "gn:feature_class":"P",
    "gn:feature_code":"PPL",
    "gn:name":"Macheira",
    "gn:population":0,
    "gn:timezone":"Europe/Lisbon",
    "iso:country":"PT",
    "wof:name":"Macheira",
    "wof:placetype":"locality"
},
  "geometry": {"coordinates":[-8.17906,37.25947],"type":"Point"}
}