{
  "type": "Feature",
  "properties": {
    "gn:admin1_code":"09",
    "gn:admin2_code":"0802",
    "gn:admin3_code":"80204.0",
    "gn:asciiname":"Silveira",
    "gn:country_code":"PT",
    "gn:dem":261,
    "gn:feature_class":"P",
    "gn:feature_code":"PPL",
    "gn:name":"Silveira",
    "gn:population":0,
    "gn:timezone":"Europe/Lisbon",
    "iso:country":"PT",
    "wof:name":"Silveira",
    "wof:placetype":"locality"
},
  "geometry": {"coordinates":[-7.5914,37.43286],"type":"Point"}
}