{
  "type": "Feature",
  "properties": {
    "gn:admin1_code":"2.0",
    "gn:admin2_code":"0108",
    "gn:admin3_code":"10807.0",
    "gn:asciiname":"Olas",
    "gn:country_code":"PT",
    "gn:dem":12,
    "gn:feature_class":"P",
    "gn:feature_code":"PPL",
    "gn:name":"Olas",
    "gn:population":0,
    "gn:timezone":"Europe/Lisbon",
    "iso:country":"PT",
    "wof:name":"Olas",
    "wof:placetype":"locality"
},
  "geometry": {"coordinates":[-8.60471,40.75368],"type":"Point"}
}