{
  "type": "Feature",
  "properties": {
    "gn:admin1_code":"23.0",
    "gn:admin2_code":"4601",
    "gn:admin3_code":"460105.0",
    "gn:asciiname":"Adegas",
    "gn:country_code":"PT",
    "gn:dem":79,
    "gn:feature_class":"P",
    "gn:feature_code":"PPL",
    "gn:name":"Adegas",
    "gn:population":0,
    "gn:timezone":"Atlantic/Azores",
    "iso:country":"PT",
    "wof:name":"Adegas",
    "wof:placetype":"locality"
},
  "geometry": {"coordinates":[-28.07419,38.44216],"type":"Point"}
}