{
  "type": "Feature",
  "properties": {
    "gn:admin1_code":"18",
    "gn:admin2_code":"1401",
    "gn:admin3_code":"140118.0",
    "gn:asciiname":"Vale de Acor",
    "gn:country_code":"PT",
    "gn:dem":185,
    "gn:feature_class":"P",
    "gn:feature_code":"PPL",
    "gn:name":"Vale de A\u00e7or",
    "gn:population":0,
    "gn:timezone":"Europe/Lisbon",
    "iso:country":"PT",
    "wof:name":"Vale de Acor",
    "wof:placetype":"locality"
},
  "geometry": {"coordinates":[-8.21553,39.62935],"type":"Point"}
}