{
  "type": "Feature",
  "properties": {
    "gn:admin1_code":"21",
    "gn:admin2_code":"1708",
    "gn:admin3_code":"170804.0",
    "gn:asciiname":"Seara",
    "gn:country_code":"PT",
    "gn:dem":205,
    "gn:feature_class":"P",
    "gn:feature_code":"PPL",
    "gn:name":"Seara",
    "gn:population":0,
    "gn:timezone":"Europe/Lisbon",
    "iso:country":"PT",
    "name:bpy_x_preferred":[
        "\u09b8\u09c7\u09f1\u09be\u09b0\u09be"
    ],
    "name:eus_x_preferred":[
        "Seara"
    ],
    "name:fra_x_preferred":[
        "Seara"
    ],
    "name:ina_x_preferred":[
        "Seara"
    ],
    "name:ita_x_preferred":[
        "Seara"
    ],
    "name:kat_x_preferred":[
        "\u10e1\u10d4\u10d0\u10e0\u10d0"
    ],
    "name:nld_x_preferred":[
        "Seara"
    ],
    "name:nor_x_preferred":[
        "Seara"
    ],
    "name:oci_x_preferred":[
        "Seara"
    ],
    "name:pol_x_preferred":[
        "Seara"
    ],
    "name:por_x_preferred":[
        "Seara"
    ],
    "name:ron_x_preferred":[
        "Seara"
    ],
    "name:rus_x_preferred":[
        "\u0421\u0435\u0430\u0440\u0430"
    ],
    "name:spa_x_preferred":[
        "Seara"
    ],
    "name:vie_x_preferred":[
        "Seara"
    ],
    "name:vol_x_preferred":[
        "Seara"
    ],
    "name:war_x_preferred":[
        "Seara"
    ],
    "name:zho_x_preferred":[
        "\u585e\u963f\u62c9"
    ],
    "wof:name":"Seara",
    "wof:placetype":"locality"
},
  "geometry": {"coordinates":[-7.80031,41.18183],"type":"Point"}
}