{
  "type": "Feature",
  "properties": {
    "gn:admin1_code":"21",
    "gn:admin2_code":"1708",
    "gn:admin3_code":"170804.0",
    "gn:asciiname":"Seara",
    "gn:country_code":"PT",
    "gn:dem":205,
    "gn:feature_class":"P",
    "gn:feature_code":"PPL",
    "gn:name":"Seara",
    "gn:population":0,
    "gn:timezone":"Europe/Lisbon",
    "iso:country":"PT",
    "wof:name":"Seara",
    "wof:placetype":"locality"
},
  "geometry": {"coordinates":[-7.80031,41.18183],"type":"Point"}
}