{
  "type": "Feature",
  "properties": {
    "gn:country":"PT",
    "gn:fcode":"PPL",
    "gn:population":0,
    "iso:country":"PT",
    "name:und_x_variant":[
        "Senhora do Cabo"
    ],
    "qs_pg:aaroncc":"PT",
    "qs_pg:gn_country":"PT",
    "qs_pg:gn_fcode":"PPL",
    "qs_pg:gn_pop":0,
    "qs_pg:name":"Nossa Senhora do Cabo",
    "qs_pg:name_adm0":"Portugal",
    "qs_pg:name_adm1":"Set\u00fabal",
    "qs_pg:photos":3105,
    "qs_pg:photos_1k":629,
    "qs_pg:photos_9k":14,
    "qs_pg:photos_9r":11,
    "qs_pg:photos_all":3105,
    "qs_pg:photos_sr":20,
    "qs_pg:pop_sr":0,
    "qs_pg:qs_pg_placetype":"locality",
    "qs_pg:qs_pg_placetype_gp":"Town",
    "qs_pg:woe_adm0":23424925,
    "woe:adm0_id":23424925,
    "woe:name_adm0":"Portugal",
    "woe:name_adm1":"Set\u00fabal",
    "woe:placetype":"Town",
    "wof:name":"Nossa Senhora do Cabo",
    "wof:placetype":"locality"
},
  "geometry": {"coordinates":[-9.21439,38.4202],"type":"Point"}
}