{
  "type": "Feature",
  "properties": {
    "gn:admin1_code":"06",
    "gn:admin2_code":"0509",
    "gn:admin3_code":"50912.0",
    "gn:asciiname":"Casal da Estrada",
    "gn:country_code":"PT",
    "gn:dem":286,
    "gn:feature_class":"P",
    "gn:feature_code":"PPL",
    "gn:name":"Casal da Estrada",
    "gn:population":0,
    "gn:timezone":"Europe/Lisbon",
    "iso:country":"PT",
    "wof:name":"Casal da Estrada",
    "wof:placetype":"locality"
},
  "geometry": {"coordinates":[-8.06644,39.82386],"type":"Point"}
}