{
  "type": "Feature",
  "properties": {
    "gn:admin1_code":"06",
    "gn:admin2_code":"0509",
    "gn:admin3_code":"50906.0",
    "gn:asciiname":"Sipote",
    "gn:country_code":"PT",
    "gn:dem":455,
    "gn:feature_class":"P",
    "gn:feature_code":"PPL",
    "gn:name":"Sipote",
    "gn:population":0,
    "gn:timezone":"Europe/Lisbon",
    "iso:country":"PT",
    "wof:name":"Sipote",
    "wof:placetype":"locality"
},
  "geometry": {"coordinates":[-7.96709,39.78932],"type":"Point"}
}