{
  "type": "Feature",
  "properties": {
    "gn:admin1_code":"17",
    "gn:admin2_code":"1317",
    "gn:admin3_code":"131724.0",
    "gn:asciiname":"Touca",
    "gn:country_code":"PT",
    "gn:dem":99,
    "gn:feature_class":"P",
    "gn:feature_code":"PPL",
    "gn:name":"Touca",
    "gn:population":0,
    "gn:timezone":"Europe/Lisbon",
    "iso:country":"PT",
    "wof:name":"Touca",
    "wof:placetype":"locality"
},
  "geometry": {"coordinates":[-8.621,41.10974],"type":"Point"}
}