{
  "type": "Feature",
  "properties": {
    "gn:admin1_code":"21.0",
    "gn:admin2_code":"1703",
    "gn:admin3_code":"170341.0",
    "gn:asciiname":"Abobeleira",
    "gn:country_code":"PT",
    "gn:dem":431,
    "gn:feature_class":"P",
    "gn:feature_code":"PPL",
    "gn:name":"Abobeleira",
    "gn:population":0,
    "gn:timezone":"Europe/Lisbon",
    "iso:country":"PT",
    "wof:name":"Abobeleira",
    "wof:placetype":"locality"
},
  "geometry": {"coordinates":[-7.49534,41.7535],"type":"Point"}
}