{
  "type": "Feature",
  "properties": {
    "gn:admin1_code":"16",
    "gn:admin2_code":"1213",
    "gn:admin3_code":"121302.0",
    "gn:asciiname":"Courelas",
    "gn:country_code":"PT",
    "gn:dem":74,
    "gn:feature_class":"P",
    "gn:feature_code":"PPL",
    "gn:name":"Courelas",
    "gn:population":0,
    "gn:timezone":"Europe/Lisbon",
    "iso:country":"PT",
    "wof:name":"Courelas",
    "wof:placetype":"locality"
},
  "geometry": {"coordinates":[-8.16667,39.06667],"type":"Point"}
}