{
  "type": "Feature",
  "properties": {
    "gn:admin1_code":"20.0",
    "gn:admin2_code":"1608",
    "gn:admin3_code":"160807.0",
    "gn:asciiname":"Mondim de Baixo",
    "gn:country_code":"PT",
    "gn:dem":81,
    "gn:feature_class":"P",
    "gn:feature_code":"PPL",
    "gn:name":"Mondim de Baixo",
    "gn:population":0,
    "gn:timezone":"Europe/Lisbon",
    "iso:country":"PT",
    "wof:name":"Mondim de Baixo",
    "wof:placetype":"locality"
},
  "geometry": {"coordinates":[-8.61644,41.99811],"type":"Point"}
}