{
  "type": "Feature",
  "properties": {
    "gn:admin1_code":"13",
    "gn:admin2_code":"1009",
    "gn:admin3_code":"100924.0",
    "gn:asciiname":"Vale da Pedra",
    "gn:country_code":"PT",
    "gn:dem":115,
    "gn:feature_class":"P",
    "gn:feature_code":"PPL",
    "gn:name":"Vale da Pedra",
    "gn:population":0,
    "gn:timezone":"Europe/Lisbon",
    "iso:country":"PT",
    "wof:name":"Vale da Pedra",
    "wof:placetype":"locality"
},
  "geometry": {"coordinates":[-8.78117,39.86246],"type":"Point"}
}