{
  "type": "Feature",
  "properties": {
    "gn:admin1_code":"05",
    "gn:admin2_code":"0410",
    "gn:admin3_code":"41019.0",
    "gn:asciiname":"Ribeirinha",
    "gn:country_code":"PT",
    "gn:dem":201,
    "gn:feature_class":"P",
    "gn:feature_code":"PPL",
    "gn:name":"Ribeirinha",
    "gn:population":0,
    "gn:timezone":"Europe/Lisbon",
    "iso:country":"PT",
    "name:ceb_x_preferred":[
        "Ribeirinha"
    ],
    "name:deu_x_preferred":[
        "Ribeirinha"
    ],
    "name:fra_x_preferred":[
        "Ribeirinha"
    ],
    "name:nld_x_preferred":[
        "Ribeirinha"
    ],
    "name:por_x_preferred":[
        "Ribeirinha"
    ],
    "name:rus_x_preferred":[
        "\u0420\u0438\u0431\u0435\u0439\u0440\u0438\u043d\u044c\u044f"
    ],
    "wof:name":"Ribeirinha",
    "wof:placetype":"locality"
},
  "geometry": {"coordinates":[-7.23723,41.36843],"type":"Point"}
}