{
  "type": "Feature",
  "properties": {
    "gn:admin1_code":"09",
    "gn:admin2_code":"0808",
    "gn:admin3_code":"80804.0",
    "gn:asciiname":"Campina",
    "gn:country_code":"PT",
    "gn:dem":158,
    "gn:feature_class":"P",
    "gn:feature_code":"PPL",
    "gn:name":"Campina",
    "gn:population":0,
    "gn:timezone":"Europe/Lisbon",
    "iso:country":"PT",
    "name:ceb_x_preferred":[
        "Campina"
    ],
    "name:deu_x_preferred":[
        "Campina"
    ],
    "name:fra_x_preferred":[
        "Campina"
    ],
    "name:ita_x_preferred":[
        "Campina"
    ],
    "name:nld_x_preferred":[
        "Campina"
    ],
    "name:por_x_preferred":[
        "Campina"
    ],
    "name:swe_x_preferred":[
        "Campina"
    ],
    "wof:name":"Campina",
    "wof:placetype":"locality"
},
  "geometry": {"coordinates":[-8.133,37.15289],"type":"Point"}
}