{
  "type": "Feature",
  "properties": {
    "gn:admin1_code":"18",
    "gn:admin2_code":"1416",
    "gn:admin3_code":"141604.0",
    "gn:asciiname":"Covao dos Porcos",
    "gn:country_code":"PT",
    "gn:dem":360,
    "gn:feature_class":"P",
    "gn:feature_code":"PPL",
    "gn:name":"Cov\u00e3o dos Porcos",
    "gn:population":0,
    "gn:timezone":"Europe/Lisbon",
    "iso:country":"PT",
    "wof:name":"Covao dos Porcos",
    "wof:placetype":"locality"
},
  "geometry": {"coordinates":[-8.79407,39.47055],"type":"Point"}
}