{
  "type": "Feature",
  "properties": {
    "gn:admin1_code":"20",
    "gn:admin2_code":"1602",
    "gn:admin3_code":"160216.0",
    "gn:asciiname":"Ribas",
    "gn:country_code":"PT",
    "gn:dem":60,
    "gn:feature_class":"P",
    "gn:feature_code":"PPL",
    "gn:name":"Ribas",
    "gn:population":0,
    "gn:timezone":"Europe/Lisbon",
    "iso:country":"PT",
    "wof:name":"Ribas",
    "wof:placetype":"locality"
},
  "geometry": {"coordinates":[-8.8205,41.85506],"type":"Point"}
}