{
  "type": "Feature",
  "properties": {
    "gn:admin1_code":"20",
    "gn:admin2_code":"1602",
    "gn:admin3_code":"160216.0",
    "gn:asciiname":"Ribas",
    "gn:country_code":"PT",
    "gn:dem":60,
    "gn:feature_class":"P",
    "gn:feature_code":"PPL",
    "gn:name":"Ribas",
    "gn:population":0,
    "gn:timezone":"Europe/Lisbon",
    "iso:country":"PT",
    "name:cat_x_preferred":[
        "Ribas"
    ],
    "name:ceb_x_preferred":[
        "Ribas"
    ],
    "name:deu_x_preferred":[
        "Ribas"
    ],
    "name:fra_x_preferred":[
        "Ribas"
    ],
    "name:glg_x_preferred":[
        "Ribas"
    ],
    "name:ita_x_preferred":[
        "Ribas"
    ],
    "name:por_x_preferred":[
        "Ribas"
    ],
    "name:rus_x_preferred":[
        "\u0420\u0438\u0431\u0430\u0441"
    ],
    "name:spa_x_preferred":[
        "Ribas"
    ],
    "name:swe_x_preferred":[
        "Ribas"
    ],
    "name:ukr_x_preferred":[
        "\u0420\u0456\u0431\u0430\u0441"
    ],
    "wof:name":"Ribas",
    "wof:placetype":"locality"
},
  "geometry": {"coordinates":[-8.8205,41.85506],"type":"Point"}
}