{
  "type": "Feature",
  "properties": {
    "gn:admin1_code":"14",
    "gn:admin2_code":"1114",
    "gn:admin3_code":"111409.0",
    "gn:asciiname":"Esperanca",
    "gn:country_code":"PT",
    "gn:dem":1,
    "gn:feature_class":"P",
    "gn:feature_code":"PPL",
    "gn:name":"Esperan\u00e7a",
    "gn:population":0,
    "gn:timezone":"Europe/Lisbon",
    "iso:country":"PT",
    "wof:name":"Esperanca",
    "wof:placetype":"locality"
},
  "geometry": {"coordinates":[-8.87666,39.00212],"type":"Point"}
}