{
  "type": "Feature",
  "properties": {
    "gn:gn_country":"PT",
    "gn:gn_fcode":"PPL",
    "gn:gn_pop":0,
    "iso:country":"PT",
    "name:deu_x_preferred":[
        "Palmeira"
    ],
    "name:eng_x_preferred":[
        "Palmeira"
    ],
    "name:fra_x_preferred":[
        "Palmeira"
    ],
    "name:kaz_x_preferred":[
        "\u041f\u0430\u043b\u043c\u0435\u0439\u0440\u0430"
    ],
    "name:nld_x_preferred":[
        "Palmeira"
    ],
    "name:por_x_preferred":[
        "Palmeira"
    ],
    "name:rus_x_preferred":[
        "\u041f\u0430\u043b\u043c\u0435\u0439\u0440\u0430"
    ],
    "name:spa_x_preferred":[
        "Palmeira"
    ],
    "name:tur_x_preferred":[
        "Palmeira"
    ],
    "name:zho_x_preferred":[
        "\u5e15\u5c14\u6885\u62c9"
    ],
    "qs_pg:aaroncc":"PT",
    "qs_pg:gn_country":"PT",
    "qs_pg:gn_fcode":"PPL",
    "qs_pg:gn_pop":0,
    "qs_pg:name":"Palmeira",
    "qs_pg:name_adm0":"Portugal",
    "qs_pg:name_adm1":"Braga",
    "qs_pg:photos_9k":1,
    "qs_pg:photos_9r":1,
    "qs_pg:photos_all":1,
    "qs_pg:photos_sr":0,
    "qs_pg:pop_sr":0,
    "qs_pg:qs_pg_placetype":"locality",
    "qs_pg:qs_pg_placetype_gp":"Town",
    "qs_pg:woe_adm0":23424925,
    "woe:adm0_id":23424925,
    "woe:name_adm0":"Portugal",
    "woe:name_adm1":"Braga",
    "woe:placetype":"Town",
    "wof:name":"Palmeira",
    "wof:placetype":"locality"
},
  "geometry": {"coordinates":[-8.42754,41.5909],"type":"Point"}
}