{
  "type": "Feature",
  "properties": {
    "gn:admin1_code":"7.0",
    "gn:admin2_code":"0606",
    "gn:admin3_code":"60604.0",
    "gn:asciiname":"Ladeiras",
    "gn:country_code":"PT",
    "gn:dem":514,
    "gn:feature_class":"P",
    "gn:feature_code":"PPL",
    "gn:name":"Ladeiras",
    "gn:population":0,
    "gn:timezone":"Europe/Lisbon",
    "iso:country":"PT",
    "wof:name":"Ladeiras",
    "wof:placetype":"locality"
},
  "geometry": {"coordinates":[-8.12571,40.13296],"type":"Point"}
}