{
  "type": "Feature",
  "properties": {
    "gn:admin1_code":"07",
    "gn:admin2_code":"0610",
    "gn:admin3_code":"61005.0",
    "gn:asciiname":"Quinta de Cavaleiros",
    "gn:country_code":"PT",
    "gn:dem":37,
    "gn:feature_class":"P",
    "gn:feature_code":"PPL",
    "gn:name":"Quinta de Cavaleiros",
    "gn:population":0,
    "gn:timezone":"Europe/Lisbon",
    "iso:country":"PT",
    "wof:name":"Quinta de Cavaleiros",
    "wof:placetype":"locality"
},
  "geometry": {"coordinates":[-8.70771,40.23253],"type":"Point"}
}