{
  "type": "Feature",
  "properties": {
    "gn:admin1_code":"05",
    "gn:admin2_code":"0402",
    "gn:admin3_code":"40239.0",
    "gn:asciiname":"Salsas",
    "gn:country_code":"PT",
    "gn:dem":799,
    "gn:feature_class":"P",
    "gn:feature_code":"PPL",
    "gn:name":"Salsas",
    "gn:population":0,
    "gn:timezone":"Europe/Lisbon",
    "iso:country":"PT",
    "name:ceb_x_preferred":[
        "Salsas"
    ],
    "name:deu_x_preferred":[
        "Salsas"
    ],
    "name:fra_x_preferred":[
        "Salsas"
    ],
    "name:kaz_x_preferred":[
        "\u0421\u0430\u043b\u0441\u0430\u0448"
    ],
    "name:nld_x_preferred":[
        "Salsas"
    ],
    "name:por_x_preferred":[
        "Salsas"
    ],
    "name:rus_x_preferred":[
        "\u0421\u0430\u043b\u0441\u0430\u0448"
    ],
    "name:spa_x_preferred":[
        "Salsas"
    ],
    "name:ukr_x_preferred":[
        "\u0421\u0430\u043b\u0441\u0430\u0448"
    ],
    "name:zho_x_preferred":[
        "\u8428\u5c14\u8428\u65af"
    ],
    "wof:name":"Salsas",
    "wof:placetype":"locality"
},
  "geometry": {"coordinates":[-6.81537,41.63691],"type":"Point"}
}