{
  "type": "Feature",
  "properties": {
    "gn:admin1_code":"05",
    "gn:admin2_code":"0402",
    "gn:admin3_code":"40239.0",
    "gn:asciiname":"Salsas",
    "gn:country_code":"PT",
    "gn:dem":799,
    "gn:feature_class":"P",
    "gn:feature_code":"PPL",
    "gn:name":"Salsas",
    "gn:population":0,
    "gn:timezone":"Europe/Lisbon",
    "iso:country":"PT",
    "wof:name":"Salsas",
    "wof:placetype":"locality"
},
  "geometry": {"coordinates":[-6.81537,41.63691],"type":"Point"}
}