{
  "type": "Feature",
  "properties": {
    "gn:admin1_code":"2.0",
    "gn:admin2_code":"0111",
    "gn:admin3_code":"11102.0",
    "gn:asciiname":"Barcouco",
    "gn:country_code":"PT",
    "gn:dem":128,
    "gn:feature_class":"P",
    "gn:feature_code":"PPL",
    "gn:name":"Barcou\u00e7o",
    "gn:population":0,
    "gn:timezone":"Europe/Lisbon",
    "iso:country":"PT",
    "wof:name":"Barcouco",
    "wof:placetype":"locality"
},
  "geometry": {"coordinates":[-8.47429,40.3031],"type":"Point"}
}