{
  "type": "Feature",
  "properties": {
    "gn:admin1_code":"04",
    "gn:admin2_code":"0310",
    "gn:admin3_code":"31015.0",
    "gn:asciiname":"Vilar-a-Monte",
    "gn:country_code":"PT",
    "gn:dem":284,
    "gn:feature_class":"P",
    "gn:feature_code":"PPL",
    "gn:name":"Vilar-a-Monte",
    "gn:population":0,
    "gn:timezone":"Europe/Lisbon",
    "iso:country":"PT",
    "wof:name":"Vilar-a-Monte",
    "wof:placetype":"locality"
},
  "geometry": {"coordinates":[-8.22638,41.66286],"type":"Point"}
}