{
  "type": "Feature",
  "properties": {
    "gn:admin1_code":"04",
    "gn:admin2_code":"0310",
    "gn:admin3_code":"31006.0",
    "gn:asciiname":"Saim",
    "gn:country_code":"PT",
    "gn:dem":553,
    "gn:feature_class":"P",
    "gn:feature_code":"PPL",
    "gn:name":"Saim",
    "gn:population":0,
    "gn:timezone":"Europe/Lisbon",
    "iso:country":"PT",
    "wof:name":"Saim",
    "wof:placetype":"locality"
},
  "geometry": {"coordinates":[-8.28275,41.71032],"type":"Point"}
}