{
  "type": "Feature",
  "properties": {
    "gn:admin1_code":"09",
    "gn:admin2_code":"0808",
    "gn:admin3_code":"80808.0",
    "gn:asciiname":"Vale de Ras",
    "gn:country_code":"PT",
    "gn:dem":228,
    "gn:feature_class":"P",
    "gn:feature_code":"PPL",
    "gn:name":"Vale de R\u00e3s",
    "gn:population":0,
    "gn:timezone":"Europe/Lisbon",
    "iso:country":"PT",
    "wof:name":"Vale de Ras",
    "wof:placetype":"locality"
},
  "geometry": {"coordinates":[-8.00384,37.12819],"type":"Point"}
}