{
  "type": "Feature",
  "properties": {
    "gn:admin1_code":"22.0",
    "gn:admin2_code":"1804",
    "gn:admin3_code":"180408.0",
    "gn:asciiname":"Guimbra",
    "gn:country_code":"PT",
    "gn:dem":413,
    "gn:feature_class":"P",
    "gn:feature_code":"PPL",
    "gn:name":"Guimbra",
    "gn:population":0,
    "gn:timezone":"Europe/Lisbon",
    "iso:country":"PT",
    "wof:name":"Guimbra",
    "wof:placetype":"locality"
},
  "geometry": {"coordinates":[-8.19968,41.04874],"type":"Point"}
}