{
  "type": "Feature",
  "properties": {
    "gn:admin1_code":"22",
    "gn:admin2_code":"1806",
    "gn:admin3_code":"180618.0",
    "gn:asciiname":"Varzea de Tavares",
    "gn:country_code":"PT",
    "gn:dem":570,
    "gn:feature_class":"P",
    "gn:feature_code":"PPL",
    "gn:name":"V\u00e1rzea de Tavares",
    "gn:population":0,
    "gn:timezone":"Europe/Lisbon",
    "iso:country":"PT",
    "wof:name":"Varzea de Tavares",
    "wof:placetype":"locality"
},
  "geometry": {"coordinates":[-7.60153,40.60696],"type":"Point"}
}