{
  "type": "Feature",
  "properties": {
    "gn:admin1_code":"7.0",
    "gn:admin2_code":"0613",
    "gn:admin3_code":"61310.0",
    "gn:asciiname":"Cacemes",
    "gn:country_code":"PT",
    "gn:dem":230,
    "gn:feature_class":"P",
    "gn:feature_code":"PPL",
    "gn:name":"Cacemes",
    "gn:population":0,
    "gn:timezone":"Europe/Lisbon",
    "iso:country":"PT",
    "wof:name":"Cacemes",
    "wof:placetype":"locality"
},
  "geometry": {"coordinates":[-8.35639,40.34236],"type":"Point"}
}