{
  "type": "Feature",
  "properties": {
    "gn:admin1_code":"13.0",
    "gn:admin2_code":"1007",
    "gn:admin3_code":"100701.0",
    "gn:asciiname":"Botelhas",
    "gn:country_code":"PT",
    "gn:dem":542,
    "gn:feature_class":"P",
    "gn:feature_code":"PPL",
    "gn:name":"Botelhas",
    "gn:population":0,
    "gn:timezone":"Europe/Lisbon",
    "iso:country":"PT",
    "wof:name":"Botelhas",
    "wof:placetype":"locality"
},
  "geometry": {"coordinates":[-8.1842,40.03145],"type":"Point"}
}