{
  "type": "Feature",
  "properties": {
    "gn:admin1_code":"19",
    "gn:admin2_code":"1501",
    "gn:admin3_code":"150103.0",
    "gn:asciiname":"Leziria",
    "gn:country_code":"PT",
    "gn:dem":7,
    "gn:feature_class":"P",
    "gn:feature_code":"PPL",
    "gn:name":"Lez\u00edria",
    "gn:population":0,
    "gn:timezone":"Europe/Lisbon",
    "iso:country":"PT",
    "wof:name":"Leziria",
    "wof:placetype":"locality"
},
  "geometry": {"coordinates":[-8.49898,38.35757],"type":"Point"}
}