{
  "type": "Feature",
  "properties": {
    "gn:admin1_code":"20",
    "gn:admin2_code":"1605",
    "gn:admin3_code":"160502.0",
    "gn:asciiname":"Vilares",
    "gn:country_code":"PT",
    "gn:dem":616,
    "gn:feature_class":"P",
    "gn:feature_code":"PPL",
    "gn:name":"Vilares",
    "gn:population":0,
    "gn:timezone":"Europe/Lisbon",
    "iso:country":"PT",
    "wof:name":"Vilares",
    "wof:placetype":"locality"
},
  "geometry": {"coordinates":[-8.5273,41.87372],"type":"Point"}
}