{
  "type": "Feature",
  "properties": {
    "gn:admin1_code":"5.0",
    "gn:admin2_code":"0412",
    "gn:admin3_code":"41214.0",
    "gn:asciiname":"Ousilhao",
    "gn:country_code":"PT",
    "gn:dem":778,
    "gn:feature_class":"P",
    "gn:feature_code":"PPL",
    "gn:name":"Ousilh\u00e3o",
    "gn:population":0,
    "gn:timezone":"Europe/Lisbon",
    "iso:country":"PT",
    "wof:name":"Ousilhao",
    "wof:placetype":"locality"
},
  "geometry": {"coordinates":[-6.95474,41.79218],"type":"Point"}
}