{
  "type": "Feature",
  "properties": {
    "gn:admin1_code":"16",
    "gn:admin2_code":"1207",
    "gn:admin3_code":"120707.0",
    "gn:asciiname":"Aldeia do Pombal",
    "gn:country_code":"PT",
    "gn:dem":359,
    "gn:feature_class":"P",
    "gn:feature_code":"PPL",
    "gn:name":"Aldeia do Pombal",
    "gn:population":0,
    "gn:timezone":"Europe/Lisbon",
    "iso:country":"PT",
    "wof:name":"Aldeia do Pombal",
    "wof:placetype":"locality"
},
  "geometry": {"coordinates":[-7.21729,38.89714],"type":"Point"}
}