{
  "type": "Feature",
  "properties": {
    "gn:admin1_code":"18",
    "gn:asciiname":"Amoreira",
    "gn:country_code":"PT",
    "gn:dem":94,
    "gn:feature_class":"P",
    "gn:feature_code":"PPL",
    "gn:name":"Amoreira",
    "gn:population":0,
    "gn:timezone":"Europe/Lisbon",
    "iso:country":"PT",
    "wof:name":"Amoreira",
    "wof:placetype":"locality"
},
  "geometry": {"coordinates":[-8.22366,38.99811],"type":"Point"}
}