{
  "type": "Feature",
  "properties": {
    "gn:admin1_code":"16",
    "gn:admin2_code":"1213",
    "gn:admin3_code":"121307.0",
    "gn:asciiname":"Vale da Carreira",
    "gn:country_code":"PT",
    "gn:dem":179,
    "gn:feature_class":"P",
    "gn:feature_code":"PPL",
    "gn:name":"Vale da Carreira",
    "gn:population":0,
    "gn:timezone":"Europe/Lisbon",
    "iso:country":"PT",
    "wof:name":"Vale da Carreira",
    "wof:placetype":"locality"
},
  "geometry": {"coordinates":[-8.12959,39.2717],"type":"Point"}
}