{
  "type": "Feature",
  "properties": {
    "gn:admin1_code":"7.0",
    "gn:admin2_code":"0602",
    "gn:admin3_code":"60203.0",
    "gn:asciiname":"Fornos",
    "gn:country_code":"PT",
    "gn:dem":104,
    "gn:feature_class":"P",
    "gn:feature_code":"PPL",
    "gn:name":"Fornos",
    "gn:population":0,
    "gn:timezone":"Europe/Lisbon",
    "iso:country":"PT",
    "name:ceb_x_preferred":[
        "Fornos"
    ],
    "name:deu_x_preferred":[
        "Fornos"
    ],
    "name:glg_x_preferred":[
        "Fornos"
    ],
    "name:nld_x_preferred":[
        "Fornos"
    ],
    "name:rus_x_preferred":[
        "\u0424\u043e\u0440\u043d\u0443\u0448"
    ],
    "name:spa_x_preferred":[
        "Fornos"
    ],
    "wof:name":"Fornos",
    "wof:placetype":"locality"
},
  "geometry": {"coordinates":[-8.61207,40.27858],"type":"Point"}
}