{
  "type": "Feature",
  "properties": {
    "gn:admin1_code":"20",
    "gn:admin2_code":"1603",
    "gn:admin3_code":"160317.0",
    "gn:asciiname":"Real",
    "gn:country_code":"PT",
    "gn:dem":204,
    "gn:feature_class":"P",
    "gn:feature_code":"PPL",
    "gn:name":"Real",
    "gn:population":0,
    "gn:timezone":"Europe/Lisbon",
    "iso:country":"PT",
    "name:aze_x_preferred":[
        "Real"
    ],
    "name:cat_x_preferred":[
        "Real"
    ],
    "name:ceb_x_preferred":[
        "Real"
    ],
    "name:ces_x_preferred":[
        "Re\u00e1l"
    ],
    "name:deu_x_preferred":[
        "Real"
    ],
    "name:eus_x_preferred":[
        "Real"
    ],
    "name:fas_x_preferred":[
        "\u0631\u0626\u0627\u0644"
    ],
    "name:fra_x_preferred":[
        "Real"
    ],
    "name:glg_x_preferred":[
        "Real"
    ],
    "name:hrv_x_preferred":[
        "Real"
    ],
    "name:ita_x_preferred":[
        "Real"
    ],
    "name:jpn_x_preferred":[
        "\u30ea\u30a2\u30eb"
    ],
    "name:lav_x_preferred":[
        "Real"
    ],
    "name:msa_x_preferred":[
        "Real"
    ],
    "name:nld_x_preferred":[
        "Real"
    ],
    "name:pol_x_preferred":[
        "Real"
    ],
    "name:por_x_preferred":[
        "Real"
    ],
    "name:ron_x_preferred":[
        "Real"
    ],
    "name:rus_x_preferred":[
        "\u0420\u0435\u0430\u043b"
    ],
    "name:sco_x_preferred":[
        "Real"
    ],
    "name:spa_x_preferred":[
        "Real"
    ],
    "name:swe_x_preferred":[
        "Real"
    ],
    "name:ukr_x_preferred":[
        "\u0420\u0435\u0430\u043b"
    ],
    "name:vie_x_preferred":[
        "Real"
    ],
    "name:war_x_preferred":[
        "Real"
    ],
    "wof:name":"Real",
    "wof:placetype":"locality"
},
  "geometry": {"coordinates":[-8.26512,42.10041],"type":"Point"}
}