{
  "type": "Feature",
  "properties": {
    "gn:admin1_code":"20",
    "gn:admin2_code":"1603",
    "gn:admin3_code":"160317.0",
    "gn:asciiname":"Real",
    "gn:country_code":"PT",
    "gn:dem":204,
    "gn:feature_class":"P",
    "gn:feature_code":"PPL",
    "gn:name":"Real",
    "gn:population":0,
    "gn:timezone":"Europe/Lisbon",
    "iso:country":"PT",
    "wof:name":"Real",
    "wof:placetype":"locality"
},
  "geometry": {"coordinates":[-8.26512,42.10041],"type":"Point"}
}