{
  "type": "Feature",
  "properties": {
    "gn:admin1_code":"13",
    "gn:admin2_code":"1009",
    "gn:admin3_code":"100913.0",
    "gn:asciiname":"Vale Salgueiro",
    "gn:country_code":"PT",
    "gn:dem":127,
    "gn:feature_class":"P",
    "gn:feature_code":"PPL",
    "gn:name":"Vale Salgueiro",
    "gn:population":0,
    "gn:timezone":"Europe/Lisbon",
    "iso:country":"PT",
    "wof:name":"Vale Salgueiro",
    "wof:placetype":"locality"
},
  "geometry": {"coordinates":[-8.87149,39.67247],"type":"Point"}
}