{
  "type": "Feature",
  "properties": {
    "gn:admin1_code":"11.0",
    "gn:admin2_code":"0902",
    "gn:admin3_code":"90223.0",
    "gn:asciiname":"Jardo",
    "gn:country_code":"PT",
    "gn:dem":706,
    "gn:feature_class":"P",
    "gn:feature_code":"PPL",
    "gn:name":"Jardo",
    "gn:population":0,
    "gn:timezone":"Europe/Lisbon",
    "iso:country":"PT",
    "wof:name":"Jardo",
    "wof:placetype":"locality"
},
  "geometry": {"coordinates":[-6.94104,40.54721],"type":"Point"}
}