{
  "type": "Feature",
  "properties": {
    "gn:admin1_code":"22.0",
    "gn:admin2_code":"1816",
    "gn:admin3_code":"181608.0",
    "gn:asciiname":"Pindelo dos Milagres",
    "gn:country_code":"PT",
    "gn:dem":457,
    "gn:feature_class":"P",
    "gn:feature_code":"PPL",
    "gn:name":"Pindelo dos Milagres",
    "gn:population":0,
    "gn:timezone":"Europe/Lisbon",
    "iso:country":"PT",
    "wof:name":"Pindelo dos Milagres",
    "wof:placetype":"locality"
},
  "geometry": {"coordinates":[-7.9615,40.80491],"type":"Point"}
}