{
  "type": "Feature",
  "properties": {
    "gn:admin1_code":"21.0",
    "gn:admin2_code":"1703",
    "gn:admin3_code":"170336.0",
    "gn:asciiname":"Fornos",
    "gn:country_code":"PT",
    "gn:dem":488,
    "gn:feature_class":"P",
    "gn:feature_code":"PPL",
    "gn:name":"Fornos",
    "gn:population":0,
    "gn:timezone":"Europe/Lisbon",
    "iso:country":"PT",
    "wof:name":"Fornos",
    "wof:placetype":"locality"
},
  "geometry": {"coordinates":[-7.53955,41.6468],"type":"Point"}
}