{
  "type": "Feature",
  "properties": {
    "gn:admin1_code":"02",
    "gn:admin2_code":"0103",
    "gn:admin3_code":"10311.0",
    "gn:asciiname":"Tamengos",
    "gn:country_code":"PT",
    "gn:dem":42,
    "gn:feature_class":"P",
    "gn:feature_code":"PPL",
    "gn:name":"Tamengos",
    "gn:population":0,
    "gn:timezone":"Europe/Lisbon",
    "iso:country":"PT",
    "wof:name":"Tamengos",
    "wof:placetype":"locality"
},
  "geometry": {"coordinates":[-8.46719,40.41663],"type":"Point"}
}