{
  "type": "Feature",
  "properties": {
    "gn:admin1_code":"13",
    "gn:admin2_code":"1015",
    "gn:admin3_code":"101516.0",
    "gn:asciiname":"Outeiro Martinho",
    "gn:country_code":"PT",
    "gn:dem":115,
    "gn:feature_class":"P",
    "gn:feature_code":"PPL",
    "gn:name":"Outeiro Martinho",
    "gn:population":0,
    "gn:timezone":"Europe/Lisbon",
    "iso:country":"PT",
    "wof:name":"Outeiro Martinho",
    "wof:placetype":"locality"
},
  "geometry": {"coordinates":[-8.78081,39.95913],"type":"Point"}
}