{
  "type": "Feature",
  "properties": {
    "gn:admin1_code":"19",
    "gn:admin2_code":"1508",
    "gn:admin3_code":"150803.0",
    "gn:asciiname":"Cantanhede",
    "gn:country_code":"PT",
    "gn:dem":49,
    "gn:feature_class":"P",
    "gn:feature_code":"PPL",
    "gn:name":"Cantanhede",
    "gn:population":0,
    "gn:timezone":"Europe/Lisbon",
    "iso:country":"PT",
    "name:ceb_x_preferred":[
        "Cantanhede"
    ],
    "name:fra_x_preferred":[
        "Cantanhede"
    ],
    "name:ita_x_preferred":[
        "Cantanhede"
    ],
    "name:nld_x_preferred":[
        "Cantanhede"
    ],
    "name:por_x_preferred":[
        "Cantanhede"
    ],
    "name:rus_x_preferred":[
        "\u041a\u0430\u043d\u0442\u0430\u043d\u044c\u0435\u0434\u0438"
    ],
    "name:spa_x_preferred":[
        "Cantanhede"
    ],
    "name:swe_x_preferred":[
        "Cantanhede"
    ],
    "name:ukr_x_preferred":[
        "\u041a\u0430\u043d\u0442\u0430\u043d\u044c\u0454\u0434\u0435"
    ],
    "name:vie_x_preferred":[
        "Cantanhede"
    ],
    "name:vol_x_preferred":[
        "Cantanhede"
    ],
    "wof:name":"Cantanhede",
    "wof:placetype":"locality"
},
  "geometry": {"coordinates":[-8.91667,38.61667],"type":"Point"}
}