{
  "type": "Feature",
  "properties": {
    "gn:admin1_code":"19",
    "gn:admin2_code":"1508",
    "gn:admin3_code":"150803.0",
    "gn:asciiname":"Cantanhede",
    "gn:country_code":"PT",
    "gn:dem":49,
    "gn:feature_class":"P",
    "gn:feature_code":"PPL",
    "gn:name":"Cantanhede",
    "gn:population":0,
    "gn:timezone":"Europe/Lisbon",
    "iso:country":"PT",
    "wof:name":"Cantanhede",
    "wof:placetype":"locality"
},
  "geometry": {"coordinates":[-8.91667,38.61667],"type":"Point"}
}