{
  "type": "Feature",
  "properties": {
    "gn:admin1_code":"5.0",
    "gn:admin2_code":"0402",
    "gn:admin3_code":"40201.0",
    "gn:asciiname":"Alfaiao",
    "gn:country_code":"PT",
    "gn:dem":551,
    "gn:feature_class":"P",
    "gn:feature_code":"PPL",
    "gn:name":"Alfai\u00e3o",
    "gn:population":173,
    "gn:timezone":"Europe/Lisbon",
    "iso:country":"PT",
    "name:ceb_x_preferred":[
        "Alfai\u00e3o"
    ],
    "name:deu_x_preferred":[
        "Alfai\u00e3o"
    ],
    "name:fra_x_preferred":[
        "Alfai\u00e3o"
    ],
    "name:kaz_x_preferred":[
        "\u0410\u043b\u0444\u0430\u0439\u0430\u043d"
    ],
    "name:nld_x_preferred":[
        "Alfai\u00e3o"
    ],
    "name:por_x_preferred":[
        "Alfai\u00e3o"
    ],
    "name:rus_x_preferred":[
        "\u0410\u043b\u0444\u0430\u0439\u0430\u043d"
    ],
    "name:spa_x_preferred":[
        "Alfai\u00e3o"
    ],
    "name:ukr_x_preferred":[
        "\u0410\u043b\u0444\u0430\u0439\u044f\u043d"
    ],
    "name:und_x_variant":[
        "Alfai\u00e3o"
    ],
    "name:zho_x_preferred":[
        "\u963f\u5c14\u6cd5\u4f0a\u6602"
    ],
    "wof:name":"Alfaiao",
    "wof:placetype":"locality",
    "wof:population":173
},
  "geometry": {"coordinates":[-6.72467,41.7639],"type":"Point"}
}