{
  "type": "Feature",
  "properties": {
    "gn:admin1_code":"5.0",
    "gn:admin2_code":"0402",
    "gn:admin3_code":"40201.0",
    "gn:asciiname":"Alfaiao",
    "gn:country_code":"PT",
    "gn:dem":551,
    "gn:feature_class":"P",
    "gn:feature_code":"PPL",
    "gn:name":"Alfai\u00e3o",
    "gn:population":173,
    "gn:timezone":"Europe/Lisbon",
    "iso:country":"PT",
    "name:und_x_variant":[
        "Alfai\u00e3o"
    ],
    "wof:name":"Alfaiao",
    "wof:placetype":"locality",
    "wof:population":173
},
  "geometry": {"coordinates":[-6.72467,41.7639],"type":"Point"}
}