{
  "type": "Feature",
  "properties": {
    "gn:admin1_code":"07",
    "gn:admin2_code":"0602",
    "gn:admin3_code":"60218.0",
    "gn:asciiname":"Sanguinheira de Cima",
    "gn:country_code":"PT",
    "gn:dem":67,
    "gn:feature_class":"P",
    "gn:feature_code":"PPL",
    "gn:name":"Sanguinheira de Cima",
    "gn:population":0,
    "gn:timezone":"Europe/Lisbon",
    "iso:country":"PT",
    "wof:name":"Sanguinheira de Cima",
    "wof:placetype":"locality"
},
  "geometry": {"coordinates":[-8.70985,40.3203],"type":"Point"}
}