{
  "type": "Feature",
  "properties": {
    "gn:admin1_code":"11.0",
    "gn:admin2_code":"0901",
    "gn:admin3_code":"90101.0",
    "gn:asciiname":"Coja",
    "gn:country_code":"PT",
    "gn:dem":706,
    "gn:feature_class":"P",
    "gn:feature_code":"PPL",
    "gn:name":"Coja",
    "gn:population":0,
    "gn:timezone":"Europe/Lisbon",
    "iso:country":"PT",
    "wof:name":"Coja",
    "wof:placetype":"locality"
},
  "geometry": {"coordinates":[-7.56647,40.80528],"type":"Point"}
}