{
  "type": "Feature",
  "properties": {
    "gn:admin1_code":"2.0",
    "gn:admin2_code":"0114",
    "gn:admin3_code":"11401.0",
    "gn:asciiname":"Azerveira",
    "gn:country_code":"PT",
    "gn:dem":53,
    "gn:feature_class":"P",
    "gn:feature_code":"PPL",
    "gn:name":"Azerveira",
    "gn:population":0,
    "gn:timezone":"Europe/Lisbon",
    "iso:country":"PT",
    "wof:name":"Azerveira",
    "wof:placetype":"locality"
},
  "geometry": {"coordinates":[-8.60881,40.51036],"type":"Point"}
}