{
  "type": "Feature",
  "properties": {
    "gn:admin1_code":"2.0",
    "gn:admin2_code":"0109",
    "gn:admin3_code":"10928.0",
    "gn:asciiname":"Macieira",
    "gn:country_code":"PT",
    "gn:dem":133,
    "gn:feature_class":"P",
    "gn:feature_code":"PPL",
    "gn:name":"Macieira",
    "gn:population":0,
    "gn:timezone":"Europe/Lisbon",
    "iso:country":"PT",
    "name:ceb_x_preferred":[
        "Macieira"
    ],
    "name:deu_x_preferred":[
        "Macieira"
    ],
    "name:fra_x_preferred":[
        "Macieira"
    ],
    "name:ita_x_preferred":[
        "Macieira"
    ],
    "name:nld_x_preferred":[
        "Macieira"
    ],
    "name:por_x_preferred":[
        "Macieira"
    ],
    "name:rus_x_preferred":[
        "\u041c\u0430\u0441\u0438\u0435\u0439\u0440\u0430"
    ],
    "name:swe_x_preferred":[
        "Macieira"
    ],
    "name:ukr_x_preferred":[
        "\u041c\u0430\u0441\u0456\u0454\u0439\u0440\u0430"
    ],
    "name:vie_x_preferred":[
        "Macieira"
    ],
    "wof:name":"Macieira",
    "wof:placetype":"locality"
},
  "geometry": {"coordinates":[-8.55282,40.91106],"type":"Point"}
}