{
  "type": "Feature",
  "properties": {
    "gn:admin1_code":"2.0",
    "gn:admin2_code":"0109",
    "gn:admin3_code":"10928.0",
    "gn:asciiname":"Macieira",
    "gn:country_code":"PT",
    "gn:dem":133,
    "gn:feature_class":"P",
    "gn:feature_code":"PPL",
    "gn:name":"Macieira",
    "gn:population":0,
    "gn:timezone":"Europe/Lisbon",
    "iso:country":"PT",
    "wof:name":"Macieira",
    "wof:placetype":"locality"
},
  "geometry": {"coordinates":[-8.55282,40.91106],"type":"Point"}
}