{
  "type": "Feature",
  "properties": {
    "gn:admin1_code":"5.0",
    "gn:admin2_code":"0402",
    "gn:admin3_code":"40231.0",
    "gn:asciiname":"Pombares",
    "gn:country_code":"PT",
    "gn:dem":986,
    "gn:feature_class":"P",
    "gn:feature_code":"PPL",
    "gn:name":"Pombares",
    "gn:population":0,
    "gn:timezone":"Europe/Lisbon",
    "iso:country":"PT",
    "wof:name":"Pombares",
    "wof:placetype":"locality"
},
  "geometry": {"coordinates":[-6.88899,41.64011],"type":"Point"}
}