{
  "type": "Feature",
  "properties": {
    "gn:admin1_code":"08",
    "gn:admin2_code":"0702",
    "gn:admin3_code":"70206.0",
    "gn:asciiname":"Aldeia do Rebocho",
    "gn:country_code":"PT",
    "gn:dem":243,
    "gn:feature_class":"P",
    "gn:feature_code":"PPL",
    "gn:name":"Aldeia do Rebocho",
    "gn:population":0,
    "gn:timezone":"Europe/Lisbon",
    "iso:country":"PT",
    "wof:name":"Aldeia do Rebocho",
    "wof:placetype":"locality"
},
  "geometry": {"coordinates":[-7.77885,38.84547],"type":"Point"}
}