{
  "type": "Feature",
  "properties": {
    "gn:admin1_code":"04",
    "gn:admin2_code":"0313",
    "gn:admin3_code":"31319.0",
    "gn:asciiname":"Sao Mamede",
    "gn:country_code":"PT",
    "gn:dem":466,
    "gn:feature_class":"P",
    "gn:feature_code":"PPL",
    "gn:name":"S\u00e3o Mamede",
    "gn:population":0,
    "gn:timezone":"Europe/Lisbon",
    "iso:country":"PT",
    "wof:name":"Sao Mamede",
    "wof:placetype":"locality"
},
  "geometry": {"coordinates":[-8.47386,41.71651],"type":"Point"}
}