{
  "type": "Feature",
  "properties": {
    "gn:admin1_code":"11.0",
    "gn:admin2_code":"0913",
    "gn:admin3_code":"91327.0",
    "gn:asciiname":"Boca d'Homem",
    "gn:country_code":"PT",
    "gn:dem":555,
    "gn:feature_class":"P",
    "gn:feature_code":"PPL",
    "gn:name":"Boca d\u2019Homem",
    "gn:population":0,
    "gn:timezone":"Europe/Lisbon",
    "iso:country":"PT",
    "wof:name":"Boca d'Homem",
    "wof:placetype":"locality"
},
  "geometry": {"coordinates":[-7.25716,40.72192],"type":"Point"}
}