{
  "type": "Feature",
  "properties": {
    "gn:admin1_code":"22.0",
    "gn:admin2_code":"1807",
    "gn:admin3_code":"180703.0",
    "gn:asciiname":"Arcozelo da Torre",
    "gn:country_code":"PT",
    "gn:dem":595,
    "gn:feature_class":"P",
    "gn:feature_code":"PPL",
    "gn:name":"Arcozelo da Torre",
    "gn:population":0,
    "gn:timezone":"Europe/Lisbon",
    "iso:country":"PT",
    "wof:name":"Arcozelo da Torre",
    "wof:placetype":"locality"
},
  "geometry": {"coordinates":[-7.5864,40.96569],"type":"Point"}
}