{
  "type": "Feature",
  "properties": {
    "gn:admin1_code":"13",
    "gn:admin2_code":"1013",
    "gn:admin3_code":"101301.0",
    "gn:asciiname":"Outao",
    "gn:country_code":"PT",
    "gn:dem":356,
    "gn:feature_class":"P",
    "gn:feature_code":"PPL",
    "gn:name":"Out\u00e3o",
    "gn:population":0,
    "gn:timezone":"Europe/Lisbon",
    "iso:country":"PT",
    "wof:name":"Outao",
    "wof:placetype":"locality"
},
  "geometry": {"coordinates":[-8.2165,39.91673],"type":"Point"}
}