{
  "type": "Feature",
  "properties": {
    "iso:country":"PT",
    "qs_pg:aaroncc":"PT",
    "qs_pg:name":"Quinta Velha",
    "qs_pg:name_adm0":"Portugal",
    "qs_pg:name_adm1":"Faro",
    "qs_pg:photos":26,
    "qs_pg:photos_1k":5,
    "qs_pg:photos_9k":1,
    "qs_pg:photos_9r":2,
    "qs_pg:photos_all":26,
    "qs_pg:photos_sr":2,
    "qs_pg:pop_sr":0,
    "qs_pg:qs_pg_placetype":"locality",
    "qs_pg:qs_pg_placetype_gp":"Town",
    "qs_pg:woe_adm0":23424925,
    "woe:adm0_id":23424925,
    "woe:name_adm0":"Portugal",
    "woe:name_adm1":"Faro",
    "woe:placetype":"Town",
    "wof:name":"Quinta Velha",
    "wof:placetype":"locality"
},
  "geometry": {"coordinates":[-8.698682,37.201449],"type":"Point"}
}