{
  "type": "Feature",
  "properties": {
    "iso:country":"PT",
    "name:pol_x_preferred":[
        "S\u00e3o Mamede"
    ],
    "wof:name":"Sao Mamede",
    "wof:placetype":"neighbourhood"
},
  "geometry": {"coordinates":[-9.15180031832897,38.71956800534151],"type":"Point"}
}