{
  "type": "Feature",
  "properties": {
    "gn:admin1_code":"09",
    "gn:admin2_code":"0807",
    "gn:admin3_code":"80701.0",
    "gn:asciiname":"Lagoa da Rosa",
    "gn:country_code":"PT",
    "gn:dem":66,
    "gn:feature_class":"P",
    "gn:feature_code":"PPL",
    "gn:name":"Lagoa da Rosa",
    "gn:population":0,
    "gn:timezone":"Europe/Lisbon",
    "iso:country":"PT",
    "wof:name":"Lagoa da Rosa",
    "wof:placetype":"locality"
},
  "geometry": {"coordinates":[-8.75547,37.13677],"type":"Point"}
}