{
  "type": "Feature",
  "properties": {
    "gn:admin1_code":"13",
    "gn:admin2_code":"1009",
    "gn:admin3_code":"100903.0",
    "gn:asciiname":"Cabecas",
    "gn:country_code":"PT",
    "gn:dem":91,
    "gn:feature_class":"P",
    "gn:feature_code":"PPL",
    "gn:name":"Cabe\u00e7as",
    "gn:population":0,
    "gn:timezone":"Europe/Lisbon",
    "iso:country":"PT",
    "wof:name":"Cabecas",
    "wof:placetype":"locality"
},
  "geometry": {"coordinates":[-8.83491,39.6995],"type":"Point"}
}