{
  "type": "Feature",
  "properties": {
    "gn:admin1_code":"09",
    "gn:admin2_code":"0807",
    "gn:admin3_code":"80703.0",
    "gn:asciiname":"Alagoas",
    "gn:country_code":"PT",
    "gn:dem":29,
    "gn:feature_class":"P",
    "gn:feature_code":"PPL",
    "gn:name":"Alagoas",
    "gn:population":0,
    "gn:timezone":"Europe/Lisbon",
    "iso:country":"PT",
    "wof:name":"Alagoas",
    "wof:placetype":"locality"
},
  "geometry": {"coordinates":[-8.76609,37.07838],"type":"Point"}
}