{
  "type": "Feature",
  "properties": {
    "gn:admin1_code":"11.0",
    "gn:admin2_code":"0901",
    "gn:admin3_code":"90102.0",
    "gn:asciiname":"Carapito",
    "gn:country_code":"PT",
    "gn:dem":702,
    "gn:feature_class":"P",
    "gn:feature_code":"PPL",
    "gn:name":"Carapito",
    "gn:population":442,
    "gn:timezone":"Europe/Lisbon",
    "iso:country":"PT",
    "name:ceb_x_preferred":[
        "Carapito"
    ],
    "name:deu_x_preferred":[
        "Carapito"
    ],
    "name:kaz_x_preferred":[
        "\u041a\u0430\u0440\u0430\u043f\u0438\u0442\u0443"
    ],
    "name:mwl_x_preferred":[
        "Carapito"
    ],
    "name:nld_x_preferred":[
        "Carapito"
    ],
    "name:por_x_preferred":[
        "Carapito"
    ],
    "name:rus_x_preferred":[
        "\u041a\u0430\u0440\u0430\u043f\u0438\u0442\u0443"
    ],
    "name:spa_x_preferred":[
        "Carapito"
    ],
    "name:tur_x_preferred":[
        "Carapito"
    ],
    "wof:name":"Carapito",
    "wof:placetype":"locality",
    "wof:population":442
},
  "geometry": {"coordinates":[-7.46303,40.76711],"type":"Point"}
}