{
  "type": "Feature",
  "properties": {
    "gn:admin1_code":"7.0",
    "gn:admin2_code":"0602",
    "gn:admin3_code":"60204.0",
    "gn:asciiname":"Lemede",
    "gn:country_code":"PT",
    "gn:dem":115,
    "gn:feature_class":"P",
    "gn:feature_code":"PPL",
    "gn:name":"Lemede",
    "gn:population":0,
    "gn:timezone":"Europe/Lisbon",
    "iso:country":"PT",
    "wof:name":"Lemede",
    "wof:placetype":"locality"
},
  "geometry": {"coordinates":[-8.62185,40.32103],"type":"Point"}
}