{
  "type": "Feature",
  "properties": {
    "gn:admin1_code":"20",
    "gn:admin2_code":"1604",
    "gn:admin3_code":"160426.0",
    "gn:asciiname":"Sago",
    "gn:country_code":"PT",
    "gn:dem":175,
    "gn:feature_class":"P",
    "gn:feature_code":"PPL",
    "gn:name":"Sago",
    "gn:population":0,
    "gn:timezone":"Europe/Lisbon",
    "iso:country":"PT",
    "wof:name":"Sago",
    "wof:placetype":"locality"
},
  "geometry": {"coordinates":[-8.46062,42.03601],"type":"Point"}
}