{
  "type": "Feature",
  "properties": {
    "gn:admin1_code":"6.0",
    "gn:admin2_code":"0504",
    "gn:admin3_code":"50412.0",
    "gn:asciiname":"Castelejo",
    "gn:country_code":"PT",
    "gn:dem":477,
    "gn:feature_class":"P",
    "gn:feature_code":"PPL",
    "gn:name":"Castelejo",
    "gn:population":0,
    "gn:timezone":"Europe/Lisbon",
    "iso:country":"PT",
    "name:und_x_variant":[
        "Eburobricis",
        "Aebura",
        "Castelejo",
        "Eburobriga"
    ],
    "wof:name":"Castelejo",
    "wof:placetype":"locality"
},
  "geometry": {"coordinates":[-7.57697,40.12392],"type":"Point"}
}