{
  "type": "Feature",
  "properties": {
    "gn:admin1_code":"22",
    "gn:admin2_code":"1810",
    "gn:admin3_code":"181007.0",
    "gn:asciiname":"Ribeiradio",
    "gn:country_code":"PT",
    "gn:dem":256,
    "gn:feature_class":"P",
    "gn:feature_code":"PPL",
    "gn:name":"Ribeiradio",
    "gn:population":0,
    "gn:timezone":"Europe/Lisbon",
    "iso:country":"PT",
    "wof:name":"Ribeiradio",
    "wof:placetype":"locality"
},
  "geometry": {"coordinates":[-8.30107,40.73284],"type":"Point"}
}