{
  "type": "Feature",
  "properties": {
    "gn:admin1_code":"14",
    "gn:admin2_code":"1109",
    "gn:admin3_code":"110912.0",
    "gn:asciiname":"Gales",
    "gn:country_code":"PT",
    "gn:dem":241,
    "gn:feature_class":"P",
    "gn:feature_code":"PPL",
    "gn:name":"Gal\u00e9s",
    "gn:population":0,
    "gn:timezone":"Europe/Lisbon",
    "iso:country":"PT",
    "name:ceb_x_preferred":[
        "Gales"
    ],
    "name:deu_x_preferred":[
        "Gales"
    ],
    "name:glg_x_preferred":[
        "Gal\u00e9s"
    ],
    "name:lmo_x_preferred":[
        "Gales"
    ],
    "name:pol_x_preferred":[
        "Gales"
    ],
    "name:por_x_preferred":[
        "Gal\u00eas"
    ],
    "name:swe_x_preferred":[
        "Gales"
    ],
    "name:tgl_x_preferred":[
        "Gales"
    ],
    "wof:name":"Gales",
    "wof:placetype":"locality"
},
  "geometry": {"coordinates":[-9.25888,38.89855],"type":"Point"}
}