{
  "type": "Feature",
  "properties": {
    "gn:admin1_code":"18",
    "gn:admin2_code":"1418",
    "gn:admin3_code":"141815.0",
    "gn:asciiname":"Alqueidaozinho",
    "gn:country_code":"PT",
    "gn:dem":245,
    "gn:feature_class":"P",
    "gn:feature_code":"PPL",
    "gn:name":"Alqueid\u00e3ozinho",
    "gn:population":0,
    "gn:timezone":"Europe/Lisbon",
    "iso:country":"PT",
    "wof:name":"Alqueidaozinho",
    "wof:placetype":"locality"
},
  "geometry": {"coordinates":[-8.27651,39.58716],"type":"Point"}
}