{
  "type": "Feature",
  "properties": {
    "gn:admin1_code":"18",
    "gn:admin2_code":"1414",
    "gn:admin3_code":"141405.0",
    "gn:asciiname":"Carvalhais",
    "gn:country_code":"PT",
    "gn:dem":149,
    "gn:feature_class":"P",
    "gn:feature_code":"PPL",
    "gn:name":"Carvalhais",
    "gn:population":0,
    "gn:timezone":"Europe/Lisbon",
    "iso:country":"PT",
    "name:und_x_variant":[
        "Carvalhaes",
        "Carvalhais"
    ],
    "wof:name":"Carvalhais",
    "wof:placetype":"locality"
},
  "geometry": {"coordinates":[-8.88108,39.38481],"type":"Point"}
}