{
  "type": "Feature",
  "properties": {
    "gn:admin1_code":"06",
    "gn:admin2_code":"0502",
    "gn:admin3_code":"50223.0",
    "gn:asciiname":"Mendares",
    "gn:country_code":"PT",
    "gn:dem":322,
    "gn:feature_class":"P",
    "gn:feature_code":"PPL",
    "gn:name":"Mendares",
    "gn:population":0,
    "gn:timezone":"Europe/Lisbon",
    "iso:country":"PT",
    "wof:name":"Mendares",
    "wof:placetype":"locality"
},
  "geometry": {"coordinates":[-7.62227,39.85266],"type":"Point"}
}