{
  "type": "Feature",
  "properties": {
    "gn:admin1_code":"18",
    "gn:admin2_code":"1416",
    "gn:admin3_code":"141622.0",
    "gn:asciiname":"Nabais",
    "gn:country_code":"PT",
    "gn:dem":76,
    "gn:feature_class":"P",
    "gn:feature_code":"PPL",
    "gn:name":"Nabais",
    "gn:population":0,
    "gn:timezone":"Europe/Lisbon",
    "iso:country":"PT",
    "wof:name":"Nabais",
    "wof:placetype":"locality"
},
  "geometry": {"coordinates":[-8.66585,39.35176],"type":"Point"}
}