{
  "type": "Feature",
  "properties": {
    "gn:admin1_code":"13",
    "gn:admin2_code":"1012",
    "gn:admin3_code":"101208.0",
    "gn:asciiname":"Quinta das Janelas",
    "gn:country_code":"PT",
    "gn:dem":52,
    "gn:feature_class":"P",
    "gn:feature_code":"PPL",
    "gn:name":"Quinta das Janelas",
    "gn:population":0,
    "gn:timezone":"Europe/Lisbon",
    "iso:country":"PT",
    "wof:name":"Quinta das Janelas",
    "wof:placetype":"locality"
},
  "geometry": {"coordinates":[-9.13681,39.37085],"type":"Point"}
}