{
  "type": "Feature",
  "properties": {
    "gn:admin1_code":"18",
    "gn:admin2_code":"1409",
    "gn:admin3_code":"140902.0",
    "gn:asciiname":"Aguas Belas",
    "gn:country_code":"PT",
    "gn:dem":37,
    "gn:feature_class":"P",
    "gn:feature_code":"PPL",
    "gn:name":"\u00c1guas Belas",
    "gn:population":0,
    "gn:timezone":"Europe/Lisbon",
    "iso:country":"PT",
    "wof:name":"Aguas Belas",
    "wof:placetype":"locality"
},
  "geometry": {"coordinates":[-8.39113,38.9861],"type":"Point"}
}