{
  "type": "Feature",
  "properties": {
    "gn:admin1_code":"20",
    "gn:admin2_code":"1602",
    "gn:admin3_code":"160220.0",
    "gn:asciiname":"Vile",
    "gn:country_code":"PT",
    "gn:dem":45,
    "gn:feature_class":"P",
    "gn:feature_code":"PPL",
    "gn:name":"Vile",
    "gn:population":0,
    "gn:timezone":"Europe/Lisbon",
    "iso:country":"PT",
    "name:ceb_x_preferred":[
        "Vile"
    ],
    "name:deu_x_preferred":[
        "Vile"
    ],
    "name:fra_x_preferred":[
        "Vile"
    ],
    "name:hun_x_preferred":[
        "Vile"
    ],
    "name:ita_x_preferred":[
        "Vile"
    ],
    "name:nds_x_preferred":[
        "Vile"
    ],
    "name:por_x_preferred":[
        "Vile"
    ],
    "name:rus_x_preferred":[
        "Vile"
    ],
    "name:spa_x_preferred":[
        "Vile"
    ],
    "name:srp_x_preferred":[
        "\u0412\u0438\u043b\u0435"
    ],
    "name:swe_x_preferred":[
        "Vile"
    ],
    "wof:name":"Vile",
    "wof:placetype":"locality"
},
  "geometry": {"coordinates":[-8.8373,41.81379],"type":"Point"}
}