{
  "type": "Feature",
  "properties": {
    "gn:admin1_code":"20",
    "gn:admin2_code":"1602",
    "gn:admin3_code":"160220.0",
    "gn:asciiname":"Vile",
    "gn:country_code":"PT",
    "gn:dem":45,
    "gn:feature_class":"P",
    "gn:feature_code":"PPL",
    "gn:name":"Vile",
    "gn:population":0,
    "gn:timezone":"Europe/Lisbon",
    "iso:country":"PT",
    "wof:name":"Vile",
    "wof:placetype":"locality"
},
  "geometry": {"coordinates":[-8.8373,41.81379],"type":"Point"}
}