{
  "type": "Feature",
  "properties": {
    "gn:admin1_code":"2.0",
    "gn:admin2_code":"0113",
    "gn:admin3_code":"11305.0",
    "gn:asciiname":"Macieira de Sarnes",
    "gn:country_code":"PT",
    "gn:dem":253,
    "gn:feature_class":"P",
    "gn:feature_code":"PPL",
    "gn:name":"Macieira de Sarnes",
    "gn:population":0,
    "gn:timezone":"Europe/Lisbon",
    "iso:country":"PT",
    "wof:name":"Macieira de Sarnes",
    "wof:placetype":"locality"
},
  "geometry": {"coordinates":[-8.46161,40.90703],"type":"Point"}
}