{
  "type": "Feature",
  "properties": {
    "gn:admin1_code":"06",
    "gn:admin2_code":"0503",
    "gn:admin3_code":"50328.0",
    "gn:asciiname":"Vales do Rio",
    "gn:country_code":"PT",
    "gn:dem":441,
    "gn:elevation":"440.0",
    "gn:feature_class":"P",
    "gn:feature_code":"PPL",
    "gn:name":"Vales do Rio",
    "gn:population":674,
    "gn:timezone":"Europe/Lisbon",
    "iso:country":"PT",
    "wof:name":"Vales do Rio",
    "wof:placetype":"locality",
    "wof:population":674
},
  "geometry": {"coordinates":[-7.54547,40.20171],"type":"Point"}
}