{
  "type": "Feature",
  "properties": {
    "gn:admin1_code":"17",
    "gn:admin2_code":"1313",
    "gn:admin3_code":"131308.0",
    "gn:asciiname":"Rapijais",
    "gn:country_code":"PT",
    "gn:dem":105,
    "gn:feature_class":"P",
    "gn:feature_code":"PPL",
    "gn:name":"Rapij\u00e3is",
    "gn:population":0,
    "gn:timezone":"Europe/Lisbon",
    "iso:country":"PT",
    "wof:name":"Rapijais",
    "wof:placetype":"locality"
},
  "geometry": {"coordinates":[-8.71204,41.43041],"type":"Point"}
}