{
  "type": "Feature",
  "properties": {
    "gn:admin1_code":"4.0",
    "gn:admin2_code":"0305",
    "gn:admin3_code":"30518.0",
    "gn:asciiname":"Lamelas",
    "gn:country_code":"PT",
    "gn:dem":336,
    "gn:feature_class":"P",
    "gn:feature_code":"PPL",
    "gn:name":"Lamelas",
    "gn:population":0,
    "gn:timezone":"Europe/Lisbon",
    "iso:country":"PT",
    "wof:name":"Lamelas",
    "wof:placetype":"locality"
},
  "geometry": {"coordinates":[-8.02549,41.44238],"type":"Point"}
}