{
  "type": "Feature",
  "properties": {
    "gn:admin1_code":"4.0",
    "gn:admin2_code":"0305",
    "gn:admin3_code":"30518.0",
    "gn:asciiname":"Lamelas",
    "gn:country_code":"PT",
    "gn:dem":336,
    "gn:feature_class":"P",
    "gn:feature_code":"PPL",
    "gn:name":"Lamelas",
    "gn:population":0,
    "gn:timezone":"Europe/Lisbon",
    "iso:country":"PT",
    "name:ceb_x_preferred":[
        "Lamelas"
    ],
    "name:deu_x_preferred":[
        "Lamelas"
    ],
    "name:kaz_x_preferred":[
        "\u041b\u0430\u043c\u0435\u043b\u0430\u0448"
    ],
    "name:nld_x_preferred":[
        "Lamelas"
    ],
    "name:por_x_preferred":[
        "Lamelas"
    ],
    "name:rus_x_preferred":[
        "\u041b\u0430\u043c\u0435\u043b\u0430\u0448"
    ],
    "name:spa_x_preferred":[
        "Lamelas"
    ],
    "name:tur_x_preferred":[
        "Lamelas"
    ],
    "name:zho_x_preferred":[
        "\u62c9\u6885\u62c9\u4ec0"
    ],
    "wof:name":"Lamelas",
    "wof:placetype":"locality"
},
  "geometry": {"coordinates":[-8.02549,41.44238],"type":"Point"}
}