{
  "type": "Feature",
  "properties": {
    "gn:admin1_code":"21.0",
    "gn:admin2_code":"1706",
    "gn:admin3_code":"170629.0",
    "gn:asciiname":"Pedrario",
    "gn:country_code":"PT",
    "gn:dem":952,
    "gn:feature_class":"P",
    "gn:feature_code":"PPL",
    "gn:name":"Pedr\u00e1rio",
    "gn:population":0,
    "gn:timezone":"Europe/Lisbon",
    "iso:country":"PT",
    "wof:name":"Pedrario",
    "wof:placetype":"locality"
},
  "geometry": {"coordinates":[-7.64084,41.80941],"type":"Point"}
}