{
  "type": "Feature",
  "properties": {
    "gn:admin1_code":"22.0",
    "gn:admin2_code":"1813",
    "gn:admin3_code":"181302.0",
    "gn:asciiname":"Portejoes",
    "gn:country_code":"PT",
    "gn:dem":155,
    "gn:feature_class":"P",
    "gn:feature_code":"PPL",
    "gn:name":"Portej\u00f5es",
    "gn:population":0,
    "gn:timezone":"Europe/Lisbon",
    "iso:country":"PT",
    "wof:name":"Portejoes",
    "wof:placetype":"locality"
},
  "geometry": {"coordinates":[-7.89504,41.1221],"type":"Point"}
}