{
  "type": "Feature",
  "properties": {
    "gn:country":"PT",
    "gn:fcode":"PPL",
    "gn:population":0,
    "iso:country":"PT",
    "name:ast_x_preferred":[
        "Borralha"
    ],
    "name:bul_x_preferred":[
        "\u0411\u043e\u0440\u0430\u043b\u0445\u0430"
    ],
    "name:ceb_x_preferred":[
        "Borralha"
    ],
    "name:deu_x_preferred":[
        "Borralha"
    ],
    "name:eng_x_preferred":[
        "Borralha"
    ],
    "name:fra_x_preferred":[
        "Borralha"
    ],
    "name:kaz_x_preferred":[
        "\u0411\u043e\u0440\u0440\u0430\u043b\u044c\u044f"
    ],
    "name:mwl_x_preferred":[
        "Borralha"
    ],
    "name:nld_x_preferred":[
        "Borralha"
    ],
    "name:por_x_preferred":[
        "Borralha"
    ],
    "name:rus_x_preferred":[
        "\u0411\u043e\u0440\u0440\u0430\u043b\u044c\u044f"
    ],
    "name:spa_x_preferred":[
        "Borralha"
    ],
    "name:tur_x_preferred":[
        "Borralha"
    ],
    "name:ukr_x_preferred":[
        "\u0411\u043e\u0440\u0440\u0430\u043b\u044f"
    ],
    "name:zho_x_preferred":[
        "\u535a\u62c9\u5229\u4e9a"
    ],
    "qs_pg:aaroncc":"PT",
    "qs_pg:gn_country":"PT",
    "qs_pg:gn_fcode":"PPL",
    "qs_pg:gn_pop":0,
    "qs_pg:name":"Borralha",
    "qs_pg:name_adm0":"Portugal",
    "qs_pg:name_adm1":"Aveiro",
    "qs_pg:photos_9k":1,
    "qs_pg:photos_9r":1,
    "qs_pg:photos_all":5,
    "qs_pg:photos_sr":0,
    "qs_pg:pop_sr":0,
    "qs_pg:qs_pg_placetype":"locality",
    "qs_pg:qs_pg_placetype_gp":"Town",
    "qs_pg:woe_adm0":23424925,
    "woe:adm0_id":23424925,
    "woe:name_adm0":"Portugal",
    "woe:name_adm1":"Aveiro",
    "woe:placetype":"Town",
    "wof:name":"Borralha",
    "wof:placetype":"locality"
},
  "geometry": {"coordinates":[-8.43897,40.56005],"type":"Point"}
}