{
  "type": "Feature",
  "properties": {
    "gn:admin1_code":"14",
    "gn:admin2_code":"1101",
    "gn:admin3_code":"110102.0",
    "gn:asciiname":"Arneiros",
    "gn:country_code":"PT",
    "gn:dem":132,
    "gn:feature_class":"P",
    "gn:feature_code":"PPL",
    "gn:name":"Arneiros",
    "gn:population":0,
    "gn:timezone":"Europe/Lisbon",
    "iso:country":"PT",
    "wof:name":"Arneiros",
    "wof:placetype":"locality"
},
  "geometry": {"coordinates":[-9.12693,39.09981],"type":"Point"}
}