{
  "type": "Feature",
  "properties": {
    "gn:admin1_code":"2.0",
    "gn:admin2_code":"0112",
    "gn:admin3_code":"11202.0",
    "gn:asciiname":"Canto do Arego",
    "gn:country_code":"PT",
    "gn:dem":9,
    "gn:feature_class":"P",
    "gn:feature_code":"PPL",
    "gn:name":"Canto do Arego",
    "gn:population":0,
    "gn:timezone":"Europe/Lisbon",
    "iso:country":"PT",
    "wof:name":"Canto do Arego",
    "wof:placetype":"locality"
},
  "geometry": {"coordinates":[-8.64549,40.7558],"type":"Point"}
}