{
  "type": "Feature",
  "properties": {
    "gn:admin1_code":"4.0",
    "gn:admin2_code":"0301",
    "gn:admin3_code":"30103.0",
    "gn:asciiname":"Monte",
    "gn:country_code":"PT",
    "gn:dem":135,
    "gn:feature_class":"P",
    "gn:feature_code":"PPL",
    "gn:name":"Monte",
    "gn:population":0,
    "gn:timezone":"Europe/Lisbon",
    "iso:country":"PT",
    "wof:name":"Monte",
    "wof:placetype":"locality"
},
  "geometry": {"coordinates":[-8.37222,41.64081],"type":"Point"}
}