{
  "type": "Feature",
  "properties": {
    "gn:admin1_code":"19",
    "gn:admin2_code":"1508",
    "gn:admin3_code":"150805.0",
    "gn:asciiname":"Pegos Claros",
    "gn:country_code":"PT",
    "gn:dem":47,
    "gn:feature_class":"P",
    "gn:feature_code":"PPL",
    "gn:name":"Pegos Claros",
    "gn:population":0,
    "gn:timezone":"Europe/Lisbon",
    "iso:country":"PT",
    "wof:name":"Pegos Claros",
    "wof:placetype":"locality"
},
  "geometry": {"coordinates":[-8.68949,38.66745],"type":"Point"}
}