{
  "type": "Feature",
  "properties": {
    "gn:admin1_code":"17.0",
    "gn:admin2_code":"1302",
    "gn:admin3_code":"130205.0",
    "gn:asciiname":"Furacasas",
    "gn:country_code":"PT",
    "gn:dem":714,
    "gn:feature_class":"P",
    "gn:feature_code":"PPL",
    "gn:name":"Furacasas",
    "gn:population":0,
    "gn:timezone":"Europe/Lisbon",
    "iso:country":"PT",
    "wof:name":"Furacasas",
    "wof:placetype":"locality"
},
  "geometry": {"coordinates":[-7.95374,41.17412],"type":"Point"}
}