{
  "type": "Feature",
  "properties": {
    "gn:admin1_code":"14",
    "gn:admin2_code":"1101",
    "gn:admin3_code":"110102.0",
    "gn:asciiname":"Aldeia Galega da Merceana",
    "gn:country_code":"PT",
    "gn:dem":122,
    "gn:feature_class":"P",
    "gn:feature_code":"PPL",
    "gn:name":"Aldeia Galega da Merceana",
    "gn:population":0,
    "gn:timezone":"Europe/Lisbon",
    "iso:country":"PT",
    "name:ceb_x_preferred":[
        "Aldeia Galega da Merceana"
    ],
    "name:deu_x_preferred":[
        "Aldeia Galega da Merceana"
    ],
    "name:fas_x_preferred":[
        "\u0627\u0644\u062f\u06cc\u0627 \u06af\u0627\u0644\u06af\u0627 \u062f\u0648 \u0645\u0631\u0634\u0646\u0627"
    ],
    "name:nld_x_preferred":[
        "Aldeia Galega da Merceana"
    ],
    "name:pol_x_preferred":[
        "Aldeia Galega da Merceana"
    ],
    "name:por_x_preferred":[
        "Aldeia Galega da Merceana"
    ],
    "name:spa_x_preferred":[
        "Aldeia Galega da Merceana"
    ],
    "wof:name":"Aldeia Galega da Merceana",
    "wof:placetype":"locality"
},
  "geometry": {"coordinates":[-9.11254,39.08207],"type":"Point"}
}