{
  "type": "Feature",
  "properties": {
    "gn:admin1_code":"14",
    "gn:admin2_code":"1101",
    "gn:admin3_code":"110102.0",
    "gn:asciiname":"Aldeia Galega da Merceana",
    "gn:country_code":"PT",
    "gn:dem":122,
    "gn:feature_class":"P",
    "gn:feature_code":"PPL",
    "gn:name":"Aldeia Galega da Merceana",
    "gn:population":0,
    "gn:timezone":"Europe/Lisbon",
    "iso:country":"PT",
    "wof:name":"Aldeia Galega da Merceana",
    "wof:placetype":"locality"
},
  "geometry": {"coordinates":[-9.11254,39.08207],"type":"Point"}
}