{
  "type": "Feature",
  "properties": {
    "gn:admin1_code":"22.0",
    "gn:admin2_code":"1804",
    "gn:admin3_code":"180403.0",
    "gn:asciiname":"Medados",
    "gn:country_code":"PT",
    "gn:dem":299,
    "gn:feature_class":"P",
    "gn:feature_code":"PPL",
    "gn:name":"Medados",
    "gn:population":0,
    "gn:timezone":"Europe/Lisbon",
    "iso:country":"PT",
    "wof:name":"Medados",
    "wof:placetype":"locality"
},
  "geometry": {"coordinates":[-8.09909,41.08228],"type":"Point"}
}