{
  "type": "Feature",
  "properties": {
    "gn:admin1_code":"04",
    "gn:admin2_code":"0308",
    "gn:admin3_code":"30808.0",
    "gn:asciiname":"Sorrego",
    "gn:country_code":"PT",
    "gn:dem":131,
    "gn:feature_class":"P",
    "gn:feature_code":"PPL",
    "gn:name":"Sorrego",
    "gn:population":0,
    "gn:timezone":"Europe/Lisbon",
    "iso:country":"PT",
    "wof:name":"Sorrego",
    "wof:placetype":"locality"
},
  "geometry": {"coordinates":[-8.34056,41.49883],"type":"Point"}
}