{
  "type": "Feature",
  "properties": {
    "gn:admin1_code":"13",
    "gn:admin2_code":"1001",
    "gn:admin3_code":"100111.0",
    "gn:asciiname":"Abadessa",
    "gn:country_code":"PT",
    "gn:dem":177,
    "gn:feature_class":"P",
    "gn:feature_code":"PPL",
    "gn:name":"Abadessa",
    "gn:population":0,
    "gn:timezone":"Europe/Lisbon",
    "iso:country":"PT",
    "wof:name":"Abadessa",
    "wof:placetype":"locality"
},
  "geometry": {"coordinates":[-8.93666,39.56204],"type":"Point"}
}