{
  "type": "Feature",
  "properties": {
    "gn:admin1_code":"06",
    "gn:admin2_code":"0504",
    "gn:admin3_code":"50423.0",
    "gn:asciiname":"Quintas",
    "gn:country_code":"PT",
    "gn:dem":494,
    "gn:feature_class":"P",
    "gn:feature_code":"PPL",
    "gn:name":"Quintas",
    "gn:population":0,
    "gn:timezone":"Europe/Lisbon",
    "iso:country":"PT",
    "wof:name":"Quintas",
    "wof:placetype":"locality"
},
  "geometry": {"coordinates":[-7.29715,40.24303],"type":"Point"}
}