{
  "type": "Feature",
  "properties": {
    "iso:country":"PT",
    "qs_pg:aaroncc":"PT",
    "qs_pg:name":"Cabo Lu\u00eds",
    "qs_pg:name_adm0":"Portugal",
    "qs_pg:name_adm1":"Aveiro",
    "qs_pg:photos":17,
    "qs_pg:photos_1k":3,
    "qs_pg:photos_9k":1,
    "qs_pg:photos_9r":1,
    "qs_pg:photos_all":17,
    "qs_pg:photos_sr":1,
    "qs_pg:pop_sr":0,
    "qs_pg:qs_pg_placetype":"locality",
    "qs_pg:qs_pg_placetype_gp":"Town",
    "qs_pg:woe_adm0":23424925,
    "woe:adm0_id":23424925,
    "woe:name_adm0":"Portugal",
    "woe:name_adm1":"Aveiro",
    "woe:placetype":"Town",
    "wof:name":"Cabo Lu\u00eds",
    "wof:placetype":"locality"
},
  "geometry": {"coordinates":[-8.621349,40.650559],"type":"Point"}
}