{
  "type": "Feature",
  "properties": {
    "gn:admin1_code":"7.0",
    "gn:admin2_code":"0616",
    "gn:admin3_code":"61602.0",
    "gn:asciiname":"Candosa",
    "gn:country_code":"PT",
    "gn:dem":355,
    "gn:feature_class":"P",
    "gn:feature_code":"PPL",
    "gn:name":"Candosa",
    "gn:population":0,
    "gn:timezone":"Europe/Lisbon",
    "iso:country":"PT",
    "wof:name":"Candosa",
    "wof:placetype":"locality"
},
  "geometry": {"coordinates":[-7.96959,40.34728],"type":"Point"}
}