{
  "type": "Feature",
  "properties": {
    "gn:admin1_code":"2.0",
    "gn:admin2_code":"0102",
    "gn:admin3_code":"10201.0",
    "gn:asciiname":"Frias de Baixo",
    "gn:country_code":"PT",
    "gn:dem":84,
    "gn:feature_class":"P",
    "gn:feature_code":"PPL",
    "gn:name":"Frias de Baixo",
    "gn:population":0,
    "gn:timezone":"Europe/Lisbon",
    "iso:country":"PT",
    "wof:name":"Frias de Baixo",
    "wof:placetype":"locality"
},
  "geometry": {"coordinates":[-8.50436,40.66422],"type":"Point"}
}