{
  "type": "Feature",
  "properties": {
    "gn:admin1_code":"20.0",
    "gn:admin2_code":"1604",
    "gn:admin3_code":"160416.0",
    "gn:asciiname":"Cachada",
    "gn:country_code":"PT",
    "gn:dem":84,
    "gn:feature_class":"P",
    "gn:feature_code":"PPL",
    "gn:name":"Cachada",
    "gn:population":0,
    "gn:timezone":"Europe/Lisbon",
    "iso:country":"PT",
    "wof:name":"Cachada",
    "wof:placetype":"locality"
},
  "geometry": {"coordinates":[-8.3674,42.081],"type":"Point"}
}