{
  "type": "Feature",
  "properties": {
    "gn:admin1_code":"14",
    "gn:admin2_code":"1113",
    "gn:admin3_code":"111318.0",
    "gn:asciiname":"Montengrao",
    "gn:country_code":"PT",
    "gn:dem":89,
    "gn:feature_class":"P",
    "gn:feature_code":"PPL",
    "gn:name":"Montengr\u00e3o",
    "gn:population":0,
    "gn:timezone":"Europe/Lisbon",
    "iso:country":"PT",
    "wof:name":"Montengrao",
    "wof:placetype":"locality"
},
  "geometry": {"coordinates":[-9.29471,39.06316],"type":"Point"}
}