{
  "type": "Feature",
  "properties": {
    "gn:admin1_code":"20.0",
    "gn:admin2_code":"1603",
    "gn:admin3_code":"160302.0",
    "gn:asciiname":"Seara",
    "gn:country_code":"PT",
    "gn:dem":1138,
    "gn:feature_class":"P",
    "gn:feature_code":"PPL",
    "gn:name":"Seara",
    "gn:population":0,
    "gn:timezone":"Europe/Lisbon",
    "iso:country":"PT",
    "wof:name":"Seara",
    "wof:placetype":"locality"
},
  "geometry": {"coordinates":[-8.12315,42.0222],"type":"Point"}
}