{
  "type": "Feature",
  "properties": {
    "gn:admin1_code":"21",
    "gn:admin2_code":"1714",
    "gn:admin3_code":"171425.0",
    "gn:asciiname":"Vila Mea",
    "gn:country_code":"PT",
    "gn:dem":771,
    "gn:feature_class":"P",
    "gn:feature_code":"PPL",
    "gn:name":"Vila Me\u00e3",
    "gn:population":0,
    "gn:timezone":"Europe/Lisbon",
    "iso:country":"PT",
    "wof:name":"Vila Mea",
    "wof:placetype":"locality"
},
  "geometry": {"coordinates":[-7.66792,41.35973],"type":"Point"}
}