{
  "type": "Feature",
  "properties": {
    "gn:admin1_code":"7.0",
    "gn:admin2_code":"0605",
    "gn:admin3_code":"60508.0",
    "gn:asciiname":"Gigante",
    "gn:country_code":"PT",
    "gn:dem":73,
    "gn:feature_class":"P",
    "gn:feature_code":"PPL",
    "gn:name":"Gigante",
    "gn:population":0,
    "gn:timezone":"Europe/Lisbon",
    "iso:country":"PT",
    "name:ceb_x_preferred":[
        "Gigante"
    ],
    "name:deu_x_preferred":[
        "Gigante"
    ],
    "name:fra_x_preferred":[
        "Gigante"
    ],
    "name:ita_x_preferred":[
        "Gigante"
    ],
    "name:nld_x_preferred":[
        "Gigante"
    ],
    "name:por_x_preferred":[
        "Gigante"
    ],
    "name:spa_x_preferred":[
        "Gigante"
    ],
    "name:swe_x_preferred":[
        "Gigante"
    ],
    "name:ukr_x_preferred":[
        "\u0414\u0436\u0438\u0433\u0430\u043d\u0442\u0435"
    ],
    "wof:name":"Gigante",
    "wof:placetype":"locality"
},
  "geometry": {"coordinates":[-8.82522,40.02605],"type":"Point"}
}