{
  "type": "Feature",
  "properties": {
    "gn:admin1_code":"22.0",
    "gn:admin2_code":"1806",
    "gn:admin3_code":"180616.0",
    "gn:asciiname":"Casais",
    "gn:country_code":"PT",
    "gn:dem":568,
    "gn:feature_class":"P",
    "gn:feature_code":"PPL",
    "gn:name":"Casais",
    "gn:population":0,
    "gn:timezone":"Europe/Lisbon",
    "iso:country":"PT",
    "name:ceb_x_preferred":[
        "Casais"
    ],
    "name:deu_x_preferred":[
        "Casais"
    ],
    "name:fra_x_preferred":[
        "Casais"
    ],
    "name:glg_x_preferred":[
        "Casais"
    ],
    "name:nld_x_preferred":[
        "Casais"
    ],
    "name:por_x_preferred":[
        "Casais"
    ],
    "name:rus_x_preferred":[
        "\u041a\u0430\u0437\u0430\u0439\u0448"
    ],
    "name:spa_x_preferred":[
        "Casais"
    ],
    "name:tur_x_preferred":[
        "Casais"
    ],
    "wof:name":"Casais",
    "wof:placetype":"locality"
},
  "geometry": {"coordinates":[-7.5985,40.63965],"type":"Point"}
}