{
  "type": "Feature",
  "properties": {
    "gn:gn_country":"PT",
    "gn:gn_fcode":"PPL",
    "gn:gn_pop":0,
    "iso:country":"PT",
    "name:ceb_x_preferred":[
        "Barcelinhos"
    ],
    "name:deu_x_preferred":[
        "Barcelinhos"
    ],
    "name:kaz_x_preferred":[
        "\u0411\u0430\u0440\u0441\u0435\u043b\u0438\u043d\u044c\u044e\u0448"
    ],
    "name:nld_x_preferred":[
        "Barcelinhos"
    ],
    "name:por_x_preferred":[
        "Barcelinhos"
    ],
    "name:rus_x_preferred":[
        "\u0411\u0430\u0440\u0441\u0435\u043b\u0438\u043d\u044c\u044e\u0448"
    ],
    "name:spa_x_preferred":[
        "Barcelinhos"
    ],
    "name:ukr_x_preferred":[
        "\u0411\u0430\u0440\u0441\u0435\u043b\u0456\u043d\u044e\u0448"
    ],
    "name:zho_x_preferred":[
        "\u5df4\u585e\u5229\u7ebd\u4ec0"
    ],
    "qs_pg:aaroncc":"PT",
    "qs_pg:gn_country":"PT",
    "qs_pg:gn_fcode":"PPL",
    "qs_pg:gn_pop":0,
    "qs_pg:name":"Barcelinhos",
    "qs_pg:name_adm0":"Portugal",
    "qs_pg:name_adm1":"Braga",
    "qs_pg:photos":301,
    "qs_pg:photos_1k":61,
    "qs_pg:photos_9k":1,
    "qs_pg:photos_9r":5,
    "qs_pg:photos_all":301,
    "qs_pg:photos_sr":5,
    "qs_pg:pop_sr":0,
    "qs_pg:qs_pg_placetype":"locality",
    "qs_pg:qs_pg_placetype_gp":"Town",
    "qs_pg:woe_adm0":23424925,
    "woe:adm0_id":23424925,
    "woe:name_adm0":"Portugal",
    "woe:name_adm1":"Braga",
    "woe:placetype":"Town",
    "wof:name":"Barcelinhos",
    "wof:placetype":"locality"
},
  "geometry": {"coordinates":[-8.62138,41.52656],"type":"Point"}
}