{
  "type": "Feature",
  "properties": {
    "gn:admin1_code":"19",
    "gn:admin2_code":"1502",
    "gn:admin3_code":"150201.0",
    "gn:asciiname":"Rilvas",
    "gn:country_code":"PT",
    "gn:dem":4,
    "gn:feature_class":"P",
    "gn:feature_code":"PPL",
    "gn:name":"Rilvas",
    "gn:population":0,
    "gn:timezone":"Europe/Lisbon",
    "iso:country":"PT",
    "wof:name":"Rilvas",
    "wof:placetype":"locality"
},
  "geometry": {"coordinates":[-8.88451,38.71059],"type":"Point"}
}