{
  "type": "Feature",
  "properties": {
    "gn:admin1_code":"05",
    "gn:admin2_code":"0402",
    "gn:admin3_code":"40213.0",
    "gn:asciiname":"Terroso",
    "gn:country_code":"PT",
    "gn:dem":881,
    "gn:feature_class":"P",
    "gn:feature_code":"PPL",
    "gn:name":"Terroso",
    "gn:population":0,
    "gn:timezone":"Europe/Lisbon",
    "iso:country":"PT",
    "wof:name":"Terroso",
    "wof:placetype":"locality"
},
  "geometry": {"coordinates":[-6.84641,41.88071],"type":"Point"}
}