{
  "type": "Feature",
  "properties": {
    "gn:admin1_code":"03",
    "gn:admin2_code":"0211",
    "gn:admin3_code":"21103.0",
    "gn:asciiname":"Nave Redonda",
    "gn:country_code":"PT",
    "gn:dem":142,
    "gn:feature_class":"P",
    "gn:feature_code":"PPL",
    "gn:name":"Nave Redonda",
    "gn:population":0,
    "gn:timezone":"Europe/Lisbon",
    "iso:country":"PT",
    "wof:name":"Nave Redonda",
    "wof:placetype":"locality"
},
  "geometry": {"coordinates":[-8.48435,37.4035],"type":"Point"}
}