{
  "type": "Feature",
  "properties": {
    "gn:admin1_code":"04",
    "gn:admin2_code":"0312",
    "gn:admin3_code":"31233.0",
    "gn:asciiname":"Requiao",
    "gn:country_code":"PT",
    "gn:dem":115,
    "gn:feature_class":"P",
    "gn:feature_code":"PPL",
    "gn:name":"Requi\u00e3o",
    "gn:population":0,
    "gn:timezone":"Europe/Lisbon",
    "iso:country":"PT",
    "name:und_x_variant":[
        "Requi\u00e3o"
    ],
    "wof:name":"Requiao",
    "wof:placetype":"locality"
},
  "geometry": {"coordinates":[-8.4801,41.40994],"type":"Point"}
}