{
  "type": "Feature",
  "properties": {
    "gn:admin1_code":"20",
    "gn:admin2_code":"1609",
    "gn:admin3_code":"160928.0",
    "gn:asciiname":"Talhareses",
    "gn:country_code":"PT",
    "gn:dem":31,
    "gn:feature_class":"P",
    "gn:feature_code":"PPL",
    "gn:name":"Talhareses",
    "gn:population":0,
    "gn:timezone":"Europe/Lisbon",
    "iso:country":"PT",
    "wof:name":"Talhareses",
    "wof:placetype":"locality"
},
  "geometry": {"coordinates":[-8.77125,41.70184],"type":"Point"}
}