{
  "type": "Feature",
  "properties": {
    "gn:admin1_code":"18",
    "gn:admin2_code":"1407",
    "gn:admin3_code":"140705.0",
    "gn:asciiname":"Comenda",
    "gn:country_code":"PT",
    "gn:dem":28,
    "gn:feature_class":"P",
    "gn:feature_code":"PPL",
    "gn:name":"Comenda",
    "gn:population":0,
    "gn:timezone":"Europe/Lisbon",
    "iso:country":"PT",
    "name:por_x_preferred":[
        "comenda"
    ],
    "wof:name":"Comenda",
    "wof:placetype":"locality"
},
  "geometry": {"coordinates":[-8.53903,39.29023],"type":"Point"}
}