{
  "type": "Feature",
  "properties": {
    "gn:admin1_code":"21.0",
    "gn:admin2_code":"1714",
    "gn:admin3_code":"171420.0",
    "gn:asciiname":"Parada de Cunhos",
    "gn:country_code":"PT",
    "gn:dem":409,
    "gn:feature_class":"P",
    "gn:feature_code":"PPL",
    "gn:name":"Parada de Cunhos",
    "gn:population":0,
    "gn:timezone":"Europe/Lisbon",
    "iso:country":"PT",
    "wof:name":"Parada de Cunhos",
    "wof:placetype":"locality"
},
  "geometry": {"coordinates":[-7.7637,41.28522],"type":"Point"}
}