{
  "type": "Feature",
  "properties": {
    "gn:admin1_code":"23.0",
    "gn:asciiname":"Agriao",
    "gn:country_code":"PT",
    "gn:dem":-9999,
    "gn:feature_class":"P",
    "gn:feature_code":"PPL",
    "gn:name":"Agri\u00e3o",
    "gn:population":0,
    "gn:timezone":"Atlantic/Azores",
    "iso:country":"PT",
    "wof:name":"Agriao",
    "wof:placetype":"locality"
},
  "geometry": {"coordinates":[-25.28333,37.73333],"type":"Point"}
}