{
  "type": "Feature",
  "properties": {
    "gn:admin1_code":"7.0",
    "gn:admin2_code":"0606",
    "gn:admin3_code":"60602.0",
    "gn:asciiname":"Capelo",
    "gn:country_code":"PT",
    "gn:dem":520,
    "gn:feature_class":"P",
    "gn:feature_code":"PPL",
    "gn:name":"Capelo",
    "gn:population":0,
    "gn:timezone":"Europe/Lisbon",
    "iso:country":"PT",
    "wof:name":"Capelo",
    "wof:placetype":"locality"
},
  "geometry": {"coordinates":[-8.04303,40.15214],"type":"Point"}
}