{
  "type": "Feature",
  "properties": {
    "gn:admin1_code":"21.0",
    "gn:admin2_code":"1709",
    "gn:admin3_code":"170906.0",
    "gn:asciiname":"Melhe",
    "gn:country_code":"PT",
    "gn:dem":410,
    "gn:feature_class":"P",
    "gn:feature_code":"PPL",
    "gn:name":"Melhe",
    "gn:population":0,
    "gn:timezone":"Europe/Lisbon",
    "iso:country":"PT",
    "wof:name":"Melhe",
    "wof:placetype":"locality"
},
  "geometry": {"coordinates":[-7.78295,41.56752],"type":"Point"}
}