{
  "type": "Feature",
  "properties": {
    "gn:admin1_code":"21.0",
    "gn:admin2_code":"1712",
    "gn:admin3_code":"171221.0",
    "gn:asciiname":"Paradela",
    "gn:country_code":"PT",
    "gn:dem":638,
    "gn:feature_class":"P",
    "gn:feature_code":"PPL",
    "gn:name":"Paradela",
    "gn:population":0,
    "gn:timezone":"Europe/Lisbon",
    "iso:country":"PT",
    "wof:name":"Paradela",
    "wof:placetype":"locality"
},
  "geometry": {"coordinates":[-7.39418,41.60475],"type":"Point"}
}