{
  "type": "Feature",
  "properties": {
    "gn:admin1_code":"11",
    "gn:admin2_code":"0906",
    "gn:admin3_code":"90617.0",
    "gn:asciiname":"Sao Paio",
    "gn:country_code":"PT",
    "gn:dem":532,
    "gn:feature_class":"P",
    "gn:feature_code":"PPL",
    "gn:name":"S\u00e3o Paio",
    "gn:population":0,
    "gn:timezone":"Europe/Lisbon",
    "iso:country":"PT",
    "wof:name":"Sao Paio",
    "wof:placetype":"locality"
},
  "geometry": {"coordinates":[-7.58332,40.51181],"type":"Point"}
}