{
  "type": "Feature",
  "properties": {
    "gn:admin1_code":"2.0",
    "gn:admin2_code":"0108",
    "gn:admin3_code":"10805.0",
    "gn:asciiname":"Fonte",
    "gn:country_code":"PT",
    "gn:dem":4,
    "gn:feature_class":"P",
    "gn:feature_code":"PPL",
    "gn:name":"Fonte",
    "gn:population":0,
    "gn:timezone":"Europe/Lisbon",
    "iso:country":"PT",
    "wof:name":"Fonte",
    "wof:placetype":"locality"
},
  "geometry": {"coordinates":[-8.62971,40.80287],"type":"Point"}
}