{
  "type": "Feature",
  "properties": {
    "gn:admin1_code":"6.0",
    "gn:admin2_code":"0505",
    "gn:admin3_code":"50508.0",
    "gn:asciiname":"Cidral",
    "gn:country_code":"PT",
    "gn:dem":500,
    "gn:feature_class":"P",
    "gn:feature_code":"PPL",
    "gn:name":"Cidral",
    "gn:population":0,
    "gn:timezone":"Europe/Lisbon",
    "iso:country":"PT",
    "wof:name":"Cidral",
    "wof:placetype":"locality"
},
  "geometry": {"coordinates":[-7.10653,40.0591],"type":"Point"}
}