{
  "type": "Feature",
  "properties": {
    "gn:admin1_code":"06",
    "gn:admin2_code":"0508",
    "gn:admin3_code":"50801.0",
    "gn:asciiname":"Sobrainho",
    "gn:country_code":"PT",
    "gn:dem":406,
    "gn:feature_class":"P",
    "gn:feature_code":"PPL",
    "gn:name":"Sobrainho",
    "gn:population":0,
    "gn:timezone":"Europe/Lisbon",
    "iso:country":"PT",
    "wof:name":"Sobrainho",
    "wof:placetype":"locality"
},
  "geometry": {"coordinates":[-7.7873,39.81905],"type":"Point"}
}