{
  "type": "Feature",
  "properties": {
    "gn:admin1_code":"13",
    "gn:admin2_code":"1015",
    "gn:admin3_code":"101501.0",
    "gn:asciiname":"Ramalhais de Cima",
    "gn:country_code":"PT",
    "gn:dem":283,
    "gn:feature_class":"P",
    "gn:feature_code":"PPL",
    "gn:name":"Ramalhais de Cima",
    "gn:population":0,
    "gn:timezone":"Europe/Lisbon",
    "iso:country":"PT",
    "wof:name":"Ramalhais de Cima",
    "wof:placetype":"locality"
},
  "geometry": {"coordinates":[-8.52936,39.90347],"type":"Point"}
}