{
  "type": "Feature",
  "properties": {
    "gn:admin1_code":"7.0",
    "gn:admin2_code":"0602",
    "gn:admin3_code":"60204.0",
    "gn:asciiname":"Franciscas",
    "gn:country_code":"PT",
    "gn:dem":42,
    "gn:feature_class":"P",
    "gn:feature_code":"PPL",
    "gn:name":"Franciscas",
    "gn:population":0,
    "gn:timezone":"Europe/Lisbon",
    "iso:country":"PT",
    "wof:name":"Franciscas",
    "wof:placetype":"locality"
},
  "geometry": {"coordinates":[-8.63487,40.37101],"type":"Point"}
}