{
  "type": "Feature",
  "properties": {
    "gn:admin1_code":"17",
    "gn:admin2_code":"1317",
    "gn:admin3_code":"131708.0",
    "gn:asciiname":"Portelinha",
    "gn:country_code":"PT",
    "gn:dem":107,
    "gn:feature_class":"P",
    "gn:feature_code":"PPL",
    "gn:name":"Portelinha",
    "gn:population":0,
    "gn:timezone":"Europe/Lisbon",
    "iso:country":"PT",
    "wof:name":"Portelinha",
    "wof:placetype":"locality"
},
  "geometry": {"coordinates":[-8.4635,41.05819],"type":"Point"}
}