{
  "type": "Feature",
  "properties": {
    "gn:admin1_code":"04",
    "gn:admin2_code":"0303",
    "gn:admin3_code":"30357.0",
    "gn:asciiname":"Vendas",
    "gn:country_code":"PT",
    "gn:dem":171,
    "gn:feature_class":"P",
    "gn:feature_code":"PPL",
    "gn:name":"Vendas",
    "gn:population":0,
    "gn:timezone":"Europe/Lisbon",
    "iso:country":"PT",
    "wof:name":"Vendas",
    "wof:placetype":"locality"
},
  "geometry": {"coordinates":[-8.47611,41.48454],"type":"Point"}
}