{
  "type": "Feature",
  "properties": {
    "gn:admin1_code":"7.0",
    "gn:admin2_code":"0615",
    "gn:admin3_code":"61509.0",
    "gn:asciiname":"Gabrieis",
    "gn:country_code":"PT",
    "gn:dem":11,
    "gn:feature_class":"P",
    "gn:feature_code":"PPL",
    "gn:name":"Gabrieis",
    "gn:population":0,
    "gn:timezone":"Europe/Lisbon",
    "iso:country":"PT",
    "wof:name":"Gabrieis",
    "wof:placetype":"locality"
},
  "geometry": {"coordinates":[-8.63333,40.06667],"type":"Point"}
}