{
  "type": "Feature",
  "properties": {
    "gn:admin1_code":"4.0",
    "gn:admin2_code":"0302",
    "gn:admin3_code":"30238.0",
    "gn:asciiname":"Goios",
    "gn:country_code":"PT",
    "gn:dem":105,
    "gn:feature_class":"P",
    "gn:feature_code":"PPL",
    "gn:name":"Goios",
    "gn:population":0,
    "gn:timezone":"Europe/Lisbon",
    "iso:country":"PT",
    "wof:name":"Goios",
    "wof:placetype":"locality"
},
  "geometry": {"coordinates":[-8.62114,41.47116],"type":"Point"}
}