{
  "type": "Feature",
  "properties": {
    "gn:admin1_code":"18",
    "gn:admin2_code":"1418",
    "gn:admin3_code":"141813.0",
    "gn:asciiname":"Cochoes",
    "gn:country_code":"PT",
    "gn:dem":75,
    "gn:feature_class":"P",
    "gn:feature_code":"PPL",
    "gn:name":"Coch\u00f5es",
    "gn:population":0,
    "gn:timezone":"Europe/Lisbon",
    "iso:country":"PT",
    "wof:name":"Cochoes",
    "wof:placetype":"locality"
},
  "geometry": {"coordinates":[-8.37266,39.54152],"type":"Point"}
}