{
  "type": "Feature",
  "properties": {
    "gn:admin1_code":"18",
    "gn:admin2_code":"1413",
    "gn:admin3_code":"141302.0",
    "gn:asciiname":"Monte Fundeiro",
    "gn:country_code":"PT",
    "gn:dem":365,
    "gn:feature_class":"P",
    "gn:feature_code":"PPL",
    "gn:name":"Monte Fundeiro",
    "gn:population":0,
    "gn:timezone":"Europe/Lisbon",
    "iso:country":"PT",
    "wof:name":"Monte Fundeiro",
    "wof:placetype":"locality"
},
  "geometry": {"coordinates":[-7.99156,39.64825],"type":"Point"}
}