{
  "type": "Feature",
  "properties": {
    "gn:country":"PT",
    "gn:fcode":"PPL",
    "gn:population":3739,
    "iso:country":"PT",
    "name:cat_x_preferred":[
        "Marv\u00e3o"
    ],
    "name:ceb_x_preferred":[
        "Marv\u00e3o"
    ],
    "name:ces_x_preferred":[
        "Marv\u00e3o"
    ],
    "name:deu_x_preferred":[
        "Marv\u00e3o"
    ],
    "name:eng_x_preferred":[
        "Marv\u00e3o"
    ],
    "name:eus_x_preferred":[
        "Marvao"
    ],
    "name:fin_x_preferred":[
        "Marv\u00e3o"
    ],
    "name:fra_x_preferred":[
        "Marv\u00e3o"
    ],
    "name:glg_x_preferred":[
        "Marv\u00e3o"
    ],
    "name:ita_x_preferred":[
        "Marv\u00e3o"
    ],
    "name:jpn_x_preferred":[
        "\u30de\u30eb\u30f4\u30a1\u30aa\u30f3"
    ],
    "name:msa_x_preferred":[
        "Marv\u00e3o"
    ],
    "name:nan_x_preferred":[
        "Marv\u00e3o"
    ],
    "name:nld_x_preferred":[
        "Marv\u00e3o"
    ],
    "name:pol_x_preferred":[
        "Marv\u00e3o"
    ],
    "name:por_x_preferred":[
        "Marv\u00e3o"
    ],
    "name:rus_x_preferred":[
        "\u041c\u0430\u0440\u0432\u0430\u043d"
    ],
    "name:spa_x_preferred":[
        "Marv\u00e3o"
    ],
    "name:swe_x_preferred":[
        "Marv\u00e3o"
    ],
    "name:tur_x_preferred":[
        "Marv\u00e3o"
    ],
    "name:ukr_x_preferred":[
        "\u041c\u0430\u0440\u0432\u0430\u043d"
    ],
    "name:vie_x_preferred":[
        "Marv\u00e3o"
    ],
    "name:vol_x_preferred":[
        "Marv\u00e3o"
    ],
    "name:war_x_preferred":[
        "Marv\u00e3o"
    ],
    "name:zho_x_preferred":[
        "\u99ac\u723e\u65fa"
    ],
    "qs_pg:aaroncc":"PT",
    "qs_pg:gn_country":"PT",
    "qs_pg:gn_fcode":"PPL",
    "qs_pg:gn_pop":3739,
    "qs_pg:name":"Marv\u00e3o",
    "qs_pg:name_adm0":"Portugal",
    "qs_pg:name_adm1":"Portalegre",
    "qs_pg:photos":2029,
    "qs_pg:photos_1k":411,
    "qs_pg:photos_9k":9,
    "qs_pg:photos_9r":9,
    "qs_pg:photos_all":2029,
    "qs_pg:photos_sr":15,
    "qs_pg:pop_sr":4,
    "qs_pg:qs_pg_placetype":"locality",
    "qs_pg:qs_pg_placetype_gp":"Town",
    "qs_pg:woe_adm0":23424925,
    "woe:adm0_id":23424925,
    "woe:name_adm0":"Portugal",
    "woe:name_adm1":"Portalegre",
    "woe:placetype":"Town",
    "wof:name":"Marv\u00e3o",
    "wof:placetype":"locality",
    "wof:population":3739
},
  "geometry": {"coordinates":[-7.37663,39.39377],"type":"Point"}
}