{
  "type": "Feature",
  "properties": {
    "gn:admin1_code":"18",
    "gn:admin2_code":"1407",
    "gn:admin3_code":"140707.0",
    "gn:asciiname":"Arripiado",
    "gn:country_code":"PT",
    "gn:dem":94,
    "gn:feature_class":"P",
    "gn:feature_code":"PPL",
    "gn:name":"Arripiado",
    "gn:population":0,
    "gn:timezone":"Europe/Lisbon",
    "iso:country":"PT",
    "wof:name":"Arripiado",
    "wof:placetype":"locality"
},
  "geometry": {"coordinates":[-8.4038,39.45148],"type":"Point"}
}