{
  "type": "Feature",
  "properties": {
    "gn:admin1_code":"4.0",
    "gn:admin2_code":"0302",
    "gn:admin3_code":"30224.0",
    "gn:asciiname":"Albagado",
    "gn:country_code":"PT",
    "gn:dem":72,
    "gn:feature_class":"P",
    "gn:feature_code":"PPL",
    "gn:name":"Albagado",
    "gn:population":0,
    "gn:timezone":"Europe/Lisbon",
    "iso:country":"PT",
    "wof:name":"Albagado",
    "wof:placetype":"locality"
},
  "geometry": {"coordinates":[-8.61563,41.63587],"type":"Point"}
}