{
  "type": "Feature",
  "properties": {
    "gn:admin1_code":"13",
    "gn:admin2_code":"1015",
    "gn:admin3_code":"101511.0",
    "gn:asciiname":"Sao Tiago de Litem",
    "gn:country_code":"PT",
    "gn:dem":202,
    "gn:feature_class":"P",
    "gn:feature_code":"PPL",
    "gn:name":"S\u00e3o Tiago de Lit\u00e9m",
    "gn:population":0,
    "gn:timezone":"Europe/Lisbon",
    "iso:country":"PT",
    "wof:name":"Sao Tiago de Litem",
    "wof:placetype":"locality"
},
  "geometry": {"coordinates":[-8.60206,39.84552],"type":"Point"}
}