{
  "type": "Feature",
  "properties": {
    "gn:gn_country":"PT",
    "gn:gn_fcode":"ADM3",
    "gn:gn_pop":0,
    "iso:country":"PT",
    "name:ceb_x_preferred":[
        "Santiago Maior"
    ],
    "name:deu_x_preferred":[
        "Santiago Maior"
    ],
    "name:fra_x_preferred":[
        "Santiago Maior"
    ],
    "name:nld_x_preferred":[
        "Santiago Maior"
    ],
    "name:por_x_preferred":[
        "Santiago Maior"
    ],
    "name:rus_x_preferred":[
        "\u0421\u0430\u043d\u0442\u044c\u044f\u0433\u0443-\u041c\u0430\u0439\u043e\u0440"
    ],
    "name:sco_x_preferred":[
        "Santiago Maior"
    ],
    "name:spa_x_preferred":[
        "Santiago Maior"
    ],
    "name:ukr_x_preferred":[
        "\u0421\u0430\u043d\u0442\u0456\u0430\u0433\u0443-\u041c\u0430\u0439\u043e\u0440"
    ],
    "qs_pg:aaroncc":"PT",
    "qs_pg:gn_country":"PT",
    "qs_pg:gn_fcode":"ADM3",
    "qs_pg:gn_pop":0,
    "qs_pg:name":"Santiago Maior",
    "qs_pg:name_adm0":"Portugal",
    "qs_pg:name_adm1":"Portalegre",
    "qs_pg:photos":55,
    "qs_pg:photos_1k":11,
    "qs_pg:photos_9k":1,
    "qs_pg:photos_9r":2,
    "qs_pg:photos_all":55,
    "qs_pg:photos_sr":2,
    "qs_pg:pop_sr":0,
    "qs_pg:qs_pg_placetype":"locality",
    "qs_pg:qs_pg_placetype_gp":"Town",
    "qs_pg:woe_adm0":23424925,
    "woe:adm0_id":23424925,
    "woe:name_adm0":"Portugal",
    "woe:name_adm1":"Portalegre",
    "woe:placetype":"Town",
    "wof:name":"Santiago Maior",
    "wof:placetype":"locality"
},
  "geometry": {"coordinates":[-7.50753,39.46222],"type":"Point"}
}