{
  "type": "Feature",
  "properties": {
    "gn:admin1_code":"22.0",
    "gn:admin2_code":"1823",
    "gn:admin3_code":"182302.0",
    "gn:asciiname":"Brufe",
    "gn:country_code":"PT",
    "gn:dem":552,
    "gn:feature_class":"P",
    "gn:feature_code":"PPL",
    "gn:name":"Brufe",
    "gn:population":0,
    "gn:timezone":"Europe/Lisbon",
    "iso:country":"PT",
    "wof:name":"Brufe",
    "wof:placetype":"locality"
},
  "geometry": {"coordinates":[-7.78063,40.73957],"type":"Point"}
}