{
  "type": "Feature",
  "properties": {
    "gn:admin1_code":"14",
    "gn:admin2_code":"1103",
    "gn:admin3_code":"110304.0",
    "gn:asciiname":"Quinta de Vale de Fornos",
    "gn:country_code":"PT",
    "gn:dem":43,
    "gn:feature_class":"P",
    "gn:feature_code":"PPL",
    "gn:name":"Quinta de Vale de Fornos",
    "gn:population":0,
    "gn:timezone":"Europe/Lisbon",
    "iso:country":"PT",
    "wof:name":"Quinta de Vale de Fornos",
    "wof:placetype":"locality"
},
  "geometry": {"coordinates":[-8.86757,39.09564],"type":"Point"}
}