{
  "type": "Feature",
  "properties": {
    "gn:admin1_code":"17.0",
    "gn:admin2_code":"1310",
    "gn:admin3_code":"131011.0",
    "gn:asciiname":"Guardao",
    "gn:country_code":"PT",
    "gn:dem":170,
    "gn:feature_class":"P",
    "gn:feature_code":"PPL",
    "gn:name":"Guard\u00e3o",
    "gn:population":0,
    "gn:timezone":"Europe/Lisbon",
    "iso:country":"PT",
    "wof:name":"Guardao",
    "wof:placetype":"locality"
},
  "geometry": {"coordinates":[-8.42319,41.18416],"type":"Point"}
}