{
  "type": "Feature",
  "properties": {
    "gn:admin1_code":"18",
    "gn:admin2_code":"1404",
    "gn:admin3_code":"140401.0",
    "gn:asciiname":"Outeiro do Rato",
    "gn:country_code":"PT",
    "gn:dem":47,
    "gn:feature_class":"P",
    "gn:feature_code":"PPL",
    "gn:name":"Outeiro do Rato",
    "gn:population":0,
    "gn:timezone":"Europe/Lisbon",
    "iso:country":"PT",
    "wof:name":"Outeiro do Rato",
    "wof:placetype":"locality"
},
  "geometry": {"coordinates":[-8.56667,39.25],"type":"Point"}
}