{
  "type": "Feature",
  "properties": {
    "gn:admin1_code":"08",
    "gn:admin2_code":"0714",
    "gn:admin3_code":"71404.0",
    "gn:asciiname":"Loureiro",
    "gn:country_code":"PT",
    "gn:dem":353,
    "gn:feature_class":"P",
    "gn:feature_code":"PPL",
    "gn:name":"Loureiro",
    "gn:population":0,
    "gn:timezone":"Europe/Lisbon",
    "iso:country":"PT",
    "wof:name":"Loureiro",
    "wof:placetype":"locality"
},
  "geometry": {"coordinates":[-7.39748,38.72217],"type":"Point"}
}