{
  "type": "Feature",
  "properties": {
    "gn:admin1_code":"08",
    "gn:admin2_code":"0714",
    "gn:admin3_code":"71404.0",
    "gn:asciiname":"Loureiro",
    "gn:country_code":"PT",
    "gn:dem":353,
    "gn:feature_class":"P",
    "gn:feature_code":"PPL",
    "gn:name":"Loureiro",
    "gn:population":0,
    "gn:timezone":"Europe/Lisbon",
    "iso:country":"PT",
    "name:ceb_x_preferred":[
        "Loureiro"
    ],
    "name:deu_x_preferred":[
        "Loureiro"
    ],
    "name:fra_x_preferred":[
        "Loureiro"
    ],
    "name:glg_x_preferred":[
        "Loureiro"
    ],
    "name:jpn_x_preferred":[
        "\u30eb\u30fc\u30ec\u30a4\u30ed"
    ],
    "name:nld_x_preferred":[
        "Loureiro"
    ],
    "name:pol_x_preferred":[
        "Loureiro"
    ],
    "name:por_x_preferred":[
        "Loureiro"
    ],
    "name:spa_x_preferred":[
        "Loureiro"
    ],
    "name:ukr_x_preferred":[
        "\u041b\u043e\u0440\u0435\u0439\u0440\u0443"
    ],
    "wof:name":"Loureiro",
    "wof:placetype":"locality"
},
  "geometry": {"coordinates":[-7.39748,38.72217],"type":"Point"}
}