{
  "type": "Feature",
  "properties": {
    "gn:admin1_code":"11.0",
    "gn:admin2_code":"0901",
    "gn:admin3_code":"90110.0",
    "gn:asciiname":"Pinheiro",
    "gn:country_code":"PT",
    "gn:dem":691,
    "gn:feature_class":"P",
    "gn:feature_code":"PPL",
    "gn:name":"Pinheiro",
    "gn:population":232,
    "gn:timezone":"Europe/Lisbon",
    "iso:country":"PT",
    "wof:name":"Pinheiro",
    "wof:placetype":"locality",
    "wof:population":232
},
  "geometry": {"coordinates":[-7.60226,40.80426],"type":"Point"}
}