{
  "type": "Feature",
  "properties": {
    "gn:admin1_code":"4.0",
    "gn:admin2_code":"0303",
    "gn:admin3_code":"30319.0",
    "gn:asciiname":"Barros",
    "gn:country_code":"PT",
    "gn:dem":211,
    "gn:feature_class":"P",
    "gn:feature_code":"PPL",
    "gn:name":"Barros",
    "gn:population":0,
    "gn:timezone":"Europe/Lisbon",
    "iso:country":"PT",
    "wof:name":"Barros",
    "wof:placetype":"locality"
},
  "geometry": {"coordinates":[-8.39034,41.56303],"type":"Point"}
}