{
  "type": "Feature",
  "properties": {
    "gn:admin1_code":"7.0",
    "gn:admin2_code":"0603",
    "gn:admin3_code":"60316.0",
    "gn:asciiname":"Bordalo",
    "gn:country_code":"PT",
    "gn:dem":107,
    "gn:feature_class":"P",
    "gn:feature_code":"PPL",
    "gn:name":"Bordalo",
    "gn:population":0,
    "gn:timezone":"Europe/Lisbon",
    "iso:country":"PT",
    "wof:name":"Bordalo",
    "wof:placetype":"locality"
},
  "geometry": {"coordinates":[-8.44698,40.19306],"type":"Point"}
}