{
  "type": "Feature",
  "properties": {
    "gn:admin1_code":"07",
    "gn:admin2_code":"0611",
    "gn:admin3_code":"61107.0",
    "gn:asciiname":"Povoa das Quartas",
    "gn:country_code":"PT",
    "gn:dem":585,
    "gn:feature_class":"P",
    "gn:feature_code":"PPL",
    "gn:name":"P\u00f3voa das Quartas",
    "gn:population":0,
    "gn:timezone":"Europe/Lisbon",
    "iso:country":"PT",
    "wof:name":"Povoa das Quartas",
    "wof:placetype":"locality"
},
  "geometry": {"coordinates":[-7.80283,40.36341],"type":"Point"}
}