{
  "type": "Feature",
  "properties": {
    "gn:admin1_code":"7.0",
    "gn:admin2_code":"0603",
    "gn:admin3_code":"60312.0",
    "gn:asciiname":"Picoto",
    "gn:country_code":"PT",
    "gn:dem":136,
    "gn:feature_class":"P",
    "gn:feature_code":"PPL",
    "gn:name":"Picoto",
    "gn:population":0,
    "gn:timezone":"Europe/Lisbon",
    "iso:country":"PT",
    "wof:name":"Picoto",
    "wof:placetype":"locality"
},
  "geometry": {"coordinates":[-8.46653,40.15202],"type":"Point"}
}