{
  "type": "Feature",
  "properties": {
    "gn:admin1_code":"18",
    "gn:admin2_code":"1421",
    "gn:admin3_code":"142108.0",
    "gn:asciiname":"Ramalheira",
    "gn:country_code":"PT",
    "gn:dem":112,
    "gn:feature_class":"P",
    "gn:feature_code":"PPL",
    "gn:name":"Ramalheira",
    "gn:population":0,
    "gn:timezone":"Europe/Lisbon",
    "iso:country":"PT",
    "wof:name":"Ramalheira",
    "wof:placetype":"locality"
},
  "geometry": {"coordinates":[-8.4613,39.73214],"type":"Point"}
}