{
  "type": "Feature",
  "properties": {
    "gn:admin1_code":"09",
    "gn:admin2_code":"0808",
    "gn:admin3_code":"80807.0",
    "gn:asciiname":"Vendas Novas",
    "gn:country_code":"PT",
    "gn:dem":208,
    "gn:feature_class":"P",
    "gn:feature_code":"PPL",
    "gn:name":"Vendas Novas",
    "gn:population":0,
    "gn:timezone":"Europe/Lisbon",
    "iso:country":"PT",
    "wof:name":"Vendas Novas",
    "wof:placetype":"locality"
},
  "geometry": {"coordinates":[-8.0306,37.24348],"type":"Point"}
}