{
  "type": "Feature",
  "properties": {
    "gn:admin1_code":"09",
    "gn:admin2_code":"0808",
    "gn:admin3_code":"80807.0",
    "gn:asciiname":"Vendas Novas",
    "gn:country_code":"PT",
    "gn:dem":208,
    "gn:feature_class":"P",
    "gn:feature_code":"PPL",
    "gn:name":"Vendas Novas",
    "gn:population":0,
    "gn:timezone":"Europe/Lisbon",
    "iso:country":"PT",
    "name:ara_x_preferred":[
        "\u0641\u064a\u0646\u062f\u0627\u0633 \u0646\u0648\u0641\u0627\u0633"
    ],
    "name:cat_x_preferred":[
        "Vendas Novas"
    ],
    "name:ceb_x_preferred":[
        "Vendas Novas"
    ],
    "name:deu_x_preferred":[
        "Vendas Novas"
    ],
    "name:eus_x_preferred":[
        "Vendas Novas"
    ],
    "name:fas_x_preferred":[
        "\u0648\u0646\u062f\u0633 \u0646\u0648\u0633 \u0645\u0648\u0646\u06cc\u06a9\u06cc\u067e\u0644\u06cc\u062a\u06cc"
    ],
    "name:fra_x_preferred":[
        "Vendas Novas"
    ],
    "name:glg_x_preferred":[
        "Vendas Novas"
    ],
    "name:hun_x_preferred":[
        "Vendas Novas"
    ],
    "name:ita_x_preferred":[
        "Vendas Novas"
    ],
    "name:kat_x_preferred":[
        "\u10d5\u10d4\u10dc\u10d3\u10d0\u10e8-\u10dc\u10dd\u10d5\u10d0\u10e8\u10d8"
    ],
    "name:mzn_x_preferred":[
        "\u0648\u0646\u062f\u0627\u0633 \u0646\u0648\u0627\u0633"
    ],
    "name:nld_x_preferred":[
        "Vendas Novas"
    ],
    "name:pol_x_preferred":[
        "Vendas Novas"
    ],
    "name:por_x_preferred":[
        "Vendas Novas"
    ],
    "name:ron_x_preferred":[
        "Vendas Novas"
    ],
    "name:rus_x_preferred":[
        "\u0412\u0435\u043d\u0434\u0430\u0448-\u041d\u043e\u0432\u0430\u0448"
    ],
    "name:spa_x_preferred":[
        "Vendas Novas"
    ],
    "name:tur_x_preferred":[
        "Vendas Novas"
    ],
    "name:ukr_x_preferred":[
        "\u0412\u0435\u043d\u0434\u0430\u0448-\u041d\u043e\u0432\u0430\u0448"
    ],
    "name:vie_x_preferred":[
        "Vendas Novas"
    ],
    "name:vol_x_preferred":[
        "Vendas Novas"
    ],
    "name:war_x_preferred":[
        "Vendas Novas"
    ],
    "name:zho_x_preferred":[
        "\u65b0\u6587\u9054\u4ec0"
    ],
    "wof:name":"Vendas Novas",
    "wof:placetype":"locality"
},
  "geometry": {"coordinates":[-8.0306,37.24348],"type":"Point"}
}