{
  "type": "Feature",
  "properties": {
    "gn:admin1_code":"02",
    "gn:admin2_code":"0101",
    "gn:admin3_code":"10112.0",
    "gn:asciiname":"Sernada",
    "gn:cc2":"PT",
    "gn:country_code":"PT",
    "gn:dem":92,
    "gn:feature_class":"P",
    "gn:feature_code":"PPL",
    "gn:name":"Sernada",
    "gn:population":0,
    "gn:timezone":"Europe/Lisbon",
    "iso:country":"PT",
    "name:und_x_variant":[
        "Sarnadas",
        "Sarnada",
        "Sernada"
    ],
    "wof:name":"Sernada",
    "wof:placetype":"locality"
},
  "geometry": {"coordinates":[-8.45,40.66667],"type":"Point"}
}