{
  "type": "Feature",
  "properties": {
    "gn:admin1_code":"21",
    "gn:admin2_code":"1712",
    "gn:admin3_code":"171218.0",
    "gn:asciiname":"Sanfins",
    "gn:country_code":"PT",
    "gn:dem":434,
    "gn:feature_class":"P",
    "gn:feature_code":"PPL",
    "gn:name":"Sanfins",
    "gn:population":0,
    "gn:timezone":"Europe/Lisbon",
    "iso:country":"PT",
    "wof:name":"Sanfins",
    "wof:placetype":"locality"
},
  "geometry": {"coordinates":[-7.34833,41.59326],"type":"Point"}
}