{
  "type": "Feature",
  "properties": {
    "gn:admin1_code":"21.0",
    "gn:admin2_code":"1712",
    "gn:admin3_code":"171217.0",
    "gn:asciiname":"Lilela",
    "gn:country_code":"PT",
    "gn:dem":260,
    "gn:feature_class":"P",
    "gn:feature_code":"PPL",
    "gn:name":"Lilela",
    "gn:population":0,
    "gn:timezone":"Europe/Lisbon",
    "iso:country":"PT",
    "wof:name":"Lilela",
    "wof:placetype":"locality"
},
  "geometry": {"coordinates":[-7.25803,41.5329],"type":"Point"}
}