{
  "type": "Feature",
  "properties": {
    "gn:admin1_code":"07",
    "gn:admin2_code":"0601",
    "gn:admin3_code":"60113.0",
    "gn:asciiname":"Vilarinho",
    "gn:country_code":"PT",
    "gn:dem":224,
    "gn:feature_class":"P",
    "gn:feature_code":"PPL",
    "gn:name":"Vilarinho",
    "gn:population":0,
    "gn:timezone":"Europe/Lisbon",
    "iso:country":"PT",
    "wof:name":"Vilarinho",
    "wof:placetype":"locality"
},
  "geometry": {"coordinates":[-8.17729,40.22774],"type":"Point"}
}