{
  "type": "Feature",
  "properties": {
    "gn:admin1_code":"18",
    "gn:admin2_code":"1402",
    "gn:admin3_code":"140201.0",
    "gn:asciiname":"Goucharia",
    "gn:country_code":"PT",
    "gn:dem":80,
    "gn:feature_class":"P",
    "gn:feature_code":"PPL",
    "gn:name":"Goucharia",
    "gn:population":0,
    "gn:timezone":"Europe/Lisbon",
    "iso:country":"PT",
    "wof:name":"Goucharia",
    "wof:placetype":"locality"
},
  "geometry": {"coordinates":[-8.64517,39.47632],"type":"Point"}
}