{
  "type": "Feature",
  "properties": {
    "gn:admin1_code":"19",
    "gn:admin2_code":"1509",
    "gn:admin3_code":"150910.0",
    "gn:asciiname":"Cruz de Joao Mendes",
    "gn:country_code":"PT",
    "gn:dem":282,
    "gn:feature_class":"P",
    "gn:feature_code":"PPL",
    "gn:name":"Cruz de Jo\u00e3o Mendes",
    "gn:population":0,
    "gn:timezone":"Europe/Lisbon",
    "iso:country":"PT",
    "wof:name":"Cruz de Joao Mendes",
    "wof:placetype":"locality"
},
  "geometry": {"coordinates":[-8.6398,38.09087],"type":"Point"}
}