{
  "type": "Feature",
  "properties": {
    "gn:admin1_code":"13",
    "gn:admin2_code":"1004",
    "gn:admin3_code":"100403.0",
    "gn:asciiname":"Sao Mamede",
    "gn:country_code":"PT",
    "gn:dem":375,
    "gn:feature_class":"P",
    "gn:feature_code":"PPL",
    "gn:name":"S\u00e3o Mamede",
    "gn:population":0,
    "gn:timezone":"Europe/Lisbon",
    "iso:country":"PT",
    "name:und_x_variant":[
        "S\u00e3o Mamede"
    ],
    "wof:name":"Sao Mamede",
    "wof:placetype":"locality"
},
  "geometry": {"coordinates":[-8.71694,39.62347000000001],"type":"Point"}
}