{
  "type": "Feature",
  "properties": {
    "gn:admin1_code":"22.0",
    "gn:admin2_code":"1814",
    "gn:admin3_code":"181404.0",
    "gn:asciiname":"Coval",
    "gn:country_code":"PT",
    "gn:dem":180,
    "gn:feature_class":"P",
    "gn:feature_code":"PPL",
    "gn:name":"Coval",
    "gn:population":0,
    "gn:timezone":"Europe/Lisbon",
    "iso:country":"PT",
    "wof:name":"Coval",
    "wof:placetype":"locality"
},
  "geometry": {"coordinates":[-8.15522,40.38461],"type":"Point"}
}