{
  "type": "Feature",
  "properties": {
    "gn:admin1_code":"19",
    "gn:admin2_code":"1506",
    "gn:admin3_code":"150601.0",
    "gn:asciiname":"Manhosa",
    "gn:country_code":"PT",
    "gn:dem":25,
    "gn:feature_class":"P",
    "gn:feature_code":"PPL",
    "gn:name":"Manhosa",
    "gn:population":0,
    "gn:timezone":"Europe/Lisbon",
    "iso:country":"PT",
    "wof:name":"Manhosa",
    "wof:placetype":"locality"
},
  "geometry": {"coordinates":[-9.01667,38.63333],"type":"Point"}
}