{
  "type": "Feature",
  "properties": {
    "gn:admin1_code":"13",
    "gn:admin2_code":"1001",
    "gn:admin3_code":"100111.0",
    "gn:asciiname":"Chiqueda de Baixo",
    "gn:country_code":"PT",
    "gn:dem":48,
    "gn:feature_class":"P",
    "gn:feature_code":"PPL",
    "gn:name":"Chiqueda de Baixo",
    "gn:population":0,
    "gn:timezone":"Europe/Lisbon",
    "iso:country":"PT",
    "wof:name":"Chiqueda de Baixo",
    "wof:placetype":"locality"
},
  "geometry": {"coordinates":[-8.95265,39.54261],"type":"Point"}
}