{
  "type": "Feature",
  "properties": {
    "gn:admin1_code":"20",
    "gn:admin2_code":"1610",
    "gn:admin3_code":"161001.0",
    "gn:asciiname":"Sobreiro",
    "gn:country_code":"PT",
    "gn:dem":19,
    "gn:feature_class":"P",
    "gn:feature_code":"PPL",
    "gn:name":"Sobreiro",
    "gn:population":0,
    "gn:timezone":"Europe/Lisbon",
    "iso:country":"PT",
    "name:por_x_preferred":[
        "Sobreiro"
    ],
    "name:ukr_x_preferred":[
        "\u0421\u043e\u0431\u0440\u0435\u0439\u0440\u043e"
    ],
    "wof:name":"Sobreiro",
    "wof:placetype":"locality"
},
  "geometry": {"coordinates":[-8.71345,41.97096],"type":"Point"}
}