{
  "type": "Feature",
  "properties": {
    "gn:admin1_code":"22.0",
    "gn:admin2_code":"1806",
    "gn:admin3_code":"180606.0",
    "gn:asciiname":"Gandufe",
    "gn:country_code":"PT",
    "gn:dem":423,
    "gn:feature_class":"P",
    "gn:feature_code":"PPL",
    "gn:name":"Gandufe",
    "gn:population":0,
    "gn:timezone":"Europe/Lisbon",
    "iso:country":"PT",
    "wof:name":"Gandufe",
    "wof:placetype":"locality"
},
  "geometry": {"coordinates":[-7.80447,40.56587],"type":"Point"}
}