{
  "type": "Feature",
  "properties": {
    "gn:admin1_code":"13",
    "gn:admin2_code":"1001",
    "gn:admin3_code":"100113.0",
    "gn:asciiname":"Casais de Santa Teresa",
    "gn:country_code":"PT",
    "gn:dem":204,
    "gn:feature_class":"P",
    "gn:feature_code":"PPL",
    "gn:name":"Casais de Santa Teresa",
    "gn:population":0,
    "gn:timezone":"Europe/Lisbon",
    "iso:country":"PT",
    "wof:name":"Casais de Santa Teresa",
    "wof:placetype":"locality"
},
  "geometry": {"coordinates":[-8.88661,39.57023],"type":"Point"}
}