{
  "type": "Feature",
  "properties": {
    "gn:admin1_code":"7.0",
    "gn:admin2_code":"0602",
    "gn:admin3_code":"60206.0",
    "gn:asciiname":"Picoto",
    "gn:country_code":"PT",
    "gn:dem":56,
    "gn:feature_class":"P",
    "gn:feature_code":"PPL",
    "gn:name":"Picoto",
    "gn:population":0,
    "gn:timezone":"Europe/Lisbon",
    "iso:country":"PT",
    "wof:name":"Picoto",
    "wof:placetype":"locality"
},
  "geometry": {"coordinates":[-8.62208,40.44828],"type":"Point"}
}