{
  "type": "Feature",
  "properties": {
    "gn:admin1_code":"02",
    "gn:admin2_code":"0101",
    "gn:admin3_code":"10110.0",
    "gn:asciiname":"Vouga",
    "gn:country_code":"PT",
    "gn:dem":21,
    "gn:feature_class":"P",
    "gn:feature_code":"PPL",
    "gn:name":"Vouga",
    "gn:population":0,
    "gn:timezone":"Europe/Lisbon",
    "iso:country":"PT",
    "wof:name":"Vouga",
    "wof:placetype":"locality"
},
  "geometry": {"coordinates":[-8.47116,40.63917],"type":"Point"}
}