{
  "type": "Feature",
  "properties": {
    "gn:country":"PT",
    "gn:fcode":"PPL",
    "gn:population":5575,
    "iso:country":"PT",
    "name:ast_x_preferred":[
        "S\u00e3o Roque"
    ],
    "name:ceb_x_preferred":[
        "S\u00e3o Roque"
    ],
    "name:deu_x_preferred":[
        "S\u00e3o Roque"
    ],
    "name:eng_x_preferred":[
        "S\u00e3o Roque"
    ],
    "name:fra_x_preferred":[
        "S\u00e3o Roque"
    ],
    "name:kaz_x_preferred":[
        "\u0421\u0430\u043d-\u0420\u043e\u043a\u0435"
    ],
    "name:nan_x_preferred":[
        "S\u00e3o Roque"
    ],
    "name:nld_x_preferred":[
        "S\u00e3o Roque"
    ],
    "name:por_x_preferred":[
        "S\u00e3o Roque"
    ],
    "name:rus_x_preferred":[
        "\u0421\u0430\u043d-\u0420\u043e\u043a\u0435"
    ],
    "name:spa_x_preferred":[
        "S\u00e3o Roque"
    ],
    "name:ukr_x_preferred":[
        "\u0421\u0430\u043d-\u0420\u043e\u043a\u0435"
    ],
    "name:zho_x_preferred":[
        "S\u00e3o Roque"
    ],
    "qs_pg:aaroncc":"PT",
    "qs_pg:gn_country":"PT",
    "qs_pg:gn_fcode":"PPL",
    "qs_pg:gn_pop":5575,
    "qs_pg:name":"S\u00e3o Roque",
    "qs_pg:name_adm0":"Portugal",
    "qs_pg:name_adm1":"Aveiro",
    "qs_pg:photos_9k":1,
    "qs_pg:photos_9r":1,
    "qs_pg:photos_all":1,
    "qs_pg:photos_sr":0,
    "qs_pg:pop_sr":5,
    "qs_pg:qs_pg_placetype":"locality",
    "qs_pg:qs_pg_placetype_gp":"Town",
    "qs_pg:woe_adm0":23424925,
    "woe:adm0_id":23424925,
    "woe:name_adm0":"Portugal",
    "woe:name_adm1":"Aveiro",
    "woe:placetype":"Town",
    "wof:name":"S\u00e3o Roque",
    "wof:placetype":"locality",
    "wof:population":5575
},
  "geometry": {"coordinates":[-8.47149,40.87216],"type":"Point"}
}