{
  "type": "Feature",
  "properties": {
    "gn:admin1_code":"04",
    "gn:admin2_code":"0313",
    "gn:admin3_code":"31338.0",
    "gn:asciiname":"Rua",
    "gn:country_code":"PT",
    "gn:dem":269,
    "gn:feature_class":"P",
    "gn:feature_code":"PPL",
    "gn:name":"Rua",
    "gn:population":0,
    "gn:timezone":"Europe/Lisbon",
    "iso:country":"PT",
    "name:ceb_x_preferred":[
        "Rua"
    ],
    "name:deu_x_preferred":[
        "Rua"
    ],
    "name:fra_x_preferred":[
        "Rua"
    ],
    "name:nld_x_preferred":[
        "Rua"
    ],
    "name:por_x_preferred":[
        "Rua"
    ],
    "name:spa_x_preferred":[
        "Rua"
    ],
    "name:swe_x_preferred":[
        "Rua"
    ],
    "wof:name":"Rua",
    "wof:placetype":"locality"
},
  "geometry": {"coordinates":[-8.50465,41.67066],"type":"Point"}
}