{
  "type": "Feature",
  "properties": {
    "gn:admin1_code":"22.0",
    "gn:admin2_code":"1813",
    "gn:admin3_code":"181307.0",
    "gn:asciiname":"Louredo",
    "gn:country_code":"PT",
    "gn:dem":182,
    "gn:feature_class":"P",
    "gn:feature_code":"PPL",
    "gn:name":"Louredo",
    "gn:population":0,
    "gn:timezone":"Europe/Lisbon",
    "iso:country":"PT",
    "name:ceb_x_preferred":[
        "Louredo"
    ],
    "name:deu_x_preferred":[
        "Louredo"
    ],
    "name:fra_x_preferred":[
        "Louredo"
    ],
    "name:glg_x_preferred":[
        "Louredo"
    ],
    "name:nld_x_preferred":[
        "Louredo"
    ],
    "name:por_x_preferred":[
        "Louredo"
    ],
    "name:rus_x_preferred":[
        "\u041b\u043e\u0440\u0435\u0434\u0443"
    ],
    "name:spa_x_preferred":[
        "Louredo"
    ],
    "name:ukr_x_preferred":[
        "\u041b\u043e\u0440\u0435\u0434\u0443"
    ],
    "wof:name":"Louredo",
    "wof:placetype":"locality"
},
  "geometry": {"coordinates":[-8.01559,41.09551],"type":"Point"}
}