{
  "type": "Feature",
  "properties": {
    "gn:admin1_code":"22.0",
    "gn:admin2_code":"1813",
    "gn:admin3_code":"181307.0",
    "gn:asciiname":"Louredo",
    "gn:country_code":"PT",
    "gn:dem":182,
    "gn:feature_class":"P",
    "gn:feature_code":"PPL",
    "gn:name":"Louredo",
    "gn:population":0,
    "gn:timezone":"Europe/Lisbon",
    "iso:country":"PT",
    "wof:name":"Louredo",
    "wof:placetype":"locality"
},
  "geometry": {"coordinates":[-8.01559,41.09551],"type":"Point"}
}