{
  "type": "Feature",
  "properties": {
    "gn:admin1_code":"19",
    "gn:admin2_code":"1509",
    "gn:admin3_code":"150903.0",
    "gn:asciiname":"Vale Coelho",
    "gn:country_code":"PT",
    "gn:dem":155,
    "gn:feature_class":"P",
    "gn:feature_code":"PPL",
    "gn:name":"Vale Coelho",
    "gn:population":0,
    "gn:timezone":"Europe/Lisbon",
    "iso:country":"PT",
    "wof:name":"Vale Coelho",
    "wof:placetype":"locality"
},
  "geometry": {"coordinates":[-8.68169,37.81683],"type":"Point"}
}