{
  "type": "Feature",
  "properties": {
    "gn:admin1_code":"03",
    "gn:admin2_code":"0202",
    "gn:admin3_code":"20206.0",
    "gn:asciiname":"Corte Fidalgo",
    "gn:country_code":"PT",
    "gn:dem":388,
    "gn:feature_class":"P",
    "gn:feature_code":"PPL",
    "gn:name":"Corte Fidalgo",
    "gn:population":0,
    "gn:timezone":"Europe/Lisbon",
    "iso:country":"PT",
    "wof:name":"Corte Fidalgo",
    "wof:placetype":"locality"
},
  "geometry": {"coordinates":[-8.05299,37.33211],"type":"Point"}
}