{
  "type": "Feature",
  "properties": {
    "gn:admin1_code":"23.0",
    "gn:asciiname":"Rua de Alem",
    "gn:cc2":"PT",
    "gn:country_code":"PT",
    "gn:dem":-9999,
    "gn:feature_class":"P",
    "gn:feature_code":"PPL",
    "gn:name":"Rua de Al\u00e9m",
    "gn:population":0,
    "gn:timezone":"Atlantic/Azores",
    "iso:country":"PT",
    "name:und_x_variant":[
        "Ria de Al\u00e9m",
        "Rua de Al\u00e9m"
    ],
    "wof:name":"Rua de Alem",
    "wof:placetype":"locality"
},
  "geometry": {"coordinates":[-28.66667,38.51667],"type":"Point"}
}