{
  "type": "Feature",
  "properties": {
    "gn:admin1_code":"14",
    "gn:admin2_code":"1114",
    "gn:admin3_code":"111402.0",
    "gn:asciiname":"Adarse",
    "gn:country_code":"PT",
    "gn:dem":8,
    "gn:feature_class":"P",
    "gn:feature_code":"PPL",
    "gn:name":"Adarse",
    "gn:population":0,
    "gn:timezone":"Europe/Lisbon",
    "iso:country":"PT",
    "wof:name":"Adarse",
    "wof:placetype":"locality"
},
  "geometry": {"coordinates":[-9.0206,38.90224],"type":"Point"}
}