{
  "type": "Feature",
  "properties": {
    "gn:admin1_code":"09",
    "gn:admin2_code":"0805",
    "gn:admin3_code":"80505.0",
    "gn:asciiname":"Vale de Carneiros",
    "gn:country_code":"PT",
    "gn:dem":17,
    "gn:feature_class":"P",
    "gn:feature_code":"PPL",
    "gn:name":"Vale de Carneiros",
    "gn:population":0,
    "gn:timezone":"Europe/Lisbon",
    "iso:country":"PT",
    "wof:name":"Vale de Carneiros",
    "wof:placetype":"locality"
},
  "geometry": {"coordinates":[-7.92404,37.03225],"type":"Point"}
}