{
  "type": "Feature",
  "properties": {
    "gn:admin1_code":"23.0",
    "gn:admin2_code":"4205",
    "gn:admin3_code":"420505.0",
    "gn:asciiname":"Lombinha da Maia",
    "gn:country_code":"PT",
    "gn:dem":330,
    "gn:feature_class":"P",
    "gn:feature_code":"PPL",
    "gn:name":"Lombinha da Maia",
    "gn:population":0,
    "gn:timezone":"Atlantic/Azores",
    "iso:country":"PT",
    "wof:name":"Lombinha da Maia",
    "wof:placetype":"locality"
},
  "geometry": {"coordinates":[-25.36667000000001,37.81667],"type":"Point"}
}