{
  "type": "Feature",
  "properties": {
    "gn:admin1_code":"7.0",
    "gn:admin2_code":"0605",
    "gn:admin3_code":"60509.0",
    "gn:asciiname":"Casal Novo",
    "gn:country_code":"PT",
    "gn:dem":94,
    "gn:feature_class":"P",
    "gn:feature_code":"PPL",
    "gn:name":"Casal Novo",
    "gn:population":0,
    "gn:timezone":"Europe/Lisbon",
    "iso:country":"PT",
    "wof:name":"Casal Novo",
    "wof:placetype":"locality"
},
  "geometry": {"coordinates":[-8.79233,40.05329],"type":"Point"}
}