{
  "type": "Feature",
  "properties": {
    "gn:admin1_code":"17.0",
    "gn:admin2_code":"1312",
    "gn:admin3_code":"131211.0",
    "gn:asciiname":"Pereiro",
    "gn:cc2":"PT",
    "gn:country_code":"PT",
    "gn:dem":75,
    "gn:feature_class":"P",
    "gn:feature_code":"PPL",
    "gn:name":"Pereiro",
    "gn:population":0,
    "gn:timezone":"Europe/Lisbon",
    "iso:country":"PT",
    "name:ceb_x_preferred":[
        "Pereiro"
    ],
    "name:deu_x_preferred":[
        "Pereiro"
    ],
    "name:glg_x_preferred":[
        "Pereiro"
    ],
    "name:nld_x_preferred":[
        "Pereiro"
    ],
    "name:por_x_preferred":[
        "Pereiro"
    ],
    "name:rus_x_preferred":[
        "\u041f\u0435\u0440\u0435\u0439\u0440\u043e"
    ],
    "name:spa_x_preferred":[
        "Pereiro"
    ],
    "name:swe_x_preferred":[
        "Pereiro"
    ],
    "name:tur_x_preferred":[
        "Pereiro"
    ],
    "name:und_x_variant":[
        "Pereira"
    ],
    "wof:name":"Pereiro",
    "wof:placetype":"locality"
},
  "geometry": {"coordinates":[-8.65476,41.17376],"type":"Point"}
}