{
  "type": "Feature",
  "properties": {
    "gn:admin1_code":"16",
    "gn:admin2_code":"1213",
    "gn:admin3_code":"121304.0",
    "gn:asciiname":"Arrao de Cima",
    "gn:country_code":"PT",
    "gn:dem":135,
    "gn:feature_class":"P",
    "gn:feature_code":"PPL",
    "gn:name":"Arr\u00e3o de Cima",
    "gn:population":0,
    "gn:timezone":"Europe/Lisbon",
    "iso:country":"PT",
    "wof:name":"Arrao de Cima",
    "wof:placetype":"locality"
},
  "geometry": {"coordinates":[-8.2861,39.15084],"type":"Point"}
}