{
  "type": "Feature",
  "properties": {
    "gn:admin1_code":"21.0",
    "gn:admin2_code":"1706",
    "gn:admin3_code":"170602.0",
    "gn:asciiname":"Cambezes do Rio",
    "gn:country_code":"PT",
    "gn:dem":1009,
    "gn:feature_class":"P",
    "gn:feature_code":"PPL",
    "gn:name":"Cambezes do Rio",
    "gn:population":0,
    "gn:timezone":"Europe/Lisbon",
    "iso:country":"PT",
    "wof:name":"Cambezes do Rio",
    "wof:placetype":"locality"
},
  "geometry": {"coordinates":[-7.83718,41.80277],"type":"Point"}
}