{
  "type": "Feature",
  "properties": {
    "gn:admin1_code":"21",
    "gn:admin2_code":"1706",
    "gn:admin3_code":"170634.0",
    "gn:asciiname":"Telhado",
    "gn:country_code":"PT",
    "gn:dem":1052,
    "gn:feature_class":"P",
    "gn:feature_code":"PPL",
    "gn:name":"Telhado",
    "gn:population":0,
    "gn:timezone":"Europe/Lisbon",
    "iso:country":"PT",
    "wof:name":"Telhado",
    "wof:placetype":"locality"
},
  "geometry": {"coordinates":[-7.85211,41.71037000000001],"type":"Point"}
}