{
  "type": "Feature",
  "properties": {
    "gn:admin1_code":"22.0",
    "gn:admin2_code":"1817",
    "gn:admin3_code":"181706.0",
    "gn:asciiname":"Mioma",
    "gn:country_code":"PT",
    "gn:dem":618,
    "gn:feature_class":"P",
    "gn:feature_code":"PPL",
    "gn:name":"Mioma",
    "gn:population":0,
    "gn:timezone":"Europe/Lisbon",
    "iso:country":"PT",
    "wof:name":"Mioma",
    "wof:placetype":"locality"
},
  "geometry": {"coordinates":[-7.72247,40.74967],"type":"Point"}
}