{
  "type": "Feature",
  "properties": {
    "gn:admin1_code":"22.0",
    "gn:admin2_code":"1817",
    "gn:admin3_code":"181707.0",
    "gn:asciiname":"Lajedo",
    "gn:country_code":"PT",
    "gn:dem":514,
    "gn:feature_class":"P",
    "gn:feature_code":"PPL",
    "gn:name":"Lajedo",
    "gn:population":0,
    "gn:timezone":"Europe/Lisbon",
    "iso:country":"PT",
    "name:ceb_x_preferred":[
        "Lajedo"
    ],
    "name:deu_x_preferred":[
        "Lajedo"
    ],
    "name:nld_x_preferred":[
        "Lajedo"
    ],
    "name:por_x_preferred":[
        "Lajedo"
    ],
    "name:rus_x_preferred":[
        "\u041b\u0430\u0436\u0435\u0434\u0443"
    ],
    "name:swe_x_preferred":[
        "Lajedo"
    ],
    "name:und_x_variant":[
        "Lagedo"
    ],
    "wof:name":"Lajedo",
    "wof:placetype":"locality"
},
  "geometry": {"coordinates":[-7.7087,40.71153],"type":"Point"}
}