{
  "type": "Feature",
  "properties": {
    "gn:admin1_code":"20.0",
    "gn:admin2_code":"1604",
    "gn:admin3_code":"160401.0",
    "gn:asciiname":"Gandrachao",
    "gn:country_code":"PT",
    "gn:dem":471,
    "gn:feature_class":"P",
    "gn:feature_code":"PPL",
    "gn:name":"Gandrach\u00e3o",
    "gn:population":0,
    "gn:timezone":"Europe/Lisbon",
    "iso:country":"PT",
    "wof:name":"Gandrachao",
    "wof:placetype":"locality"
},
  "geometry": {"coordinates":[-8.52321,41.98156],"type":"Point"}
}