{
  "type": "Feature",
  "properties": {
    "gn:admin1_code":"11.0",
    "gn:admin2_code":"0909",
    "gn:admin3_code":"90911.0",
    "gn:asciiname":"Pai Penela",
    "gn:country_code":"PT",
    "gn:dem":771,
    "gn:feature_class":"P",
    "gn:feature_code":"PPL",
    "gn:name":"Pai Penela",
    "gn:population":0,
    "gn:timezone":"Europe/Lisbon",
    "iso:country":"PT",
    "wof:name":"Pai Penela",
    "wof:placetype":"locality"
},
  "geometry": {"coordinates":[-7.29765,40.90331],"type":"Point"}
}