{
  "type": "Feature",
  "properties": {
    "gn:admin1_code":"06",
    "gn:admin2_code":"0506",
    "gn:admin3_code":"50604.0",
    "gn:asciiname":"Povoa da Carvalha",
    "gn:country_code":"PT",
    "gn:dem":394,
    "gn:feature_class":"P",
    "gn:feature_code":"PPL",
    "gn:name":"P\u00f3voa da Carvalha",
    "gn:population":0,
    "gn:timezone":"Europe/Lisbon",
    "iso:country":"PT",
    "wof:name":"Povoa da Carvalha",
    "wof:placetype":"locality"
},
  "geometry": {"coordinates":[-7.7623,39.88315],"type":"Point"}
}