{
  "type": "Feature",
  "properties": {
    "gn:admin1_code":"14",
    "gn:admin2_code":"1113",
    "gn:admin3_code":"111308.0",
    "gn:asciiname":"Povoa",
    "gn:country_code":"PT",
    "gn:dem":82,
    "gn:feature_class":"P",
    "gn:feature_code":"PPL",
    "gn:name":"P\u00f3voa",
    "gn:population":0,
    "gn:timezone":"Europe/Lisbon",
    "iso:country":"PT",
    "wof:name":"Povoa",
    "wof:placetype":"locality"
},
  "geometry": {"coordinates":[-9.16373,39.15479000000001],"type":"Point"}
}