{
  "type": "Feature",
  "properties": {
    "gn:admin1_code":"09",
    "gn:admin2_code":"0814",
    "gn:admin3_code":"81405.0",
    "gn:asciiname":"Fonte Salgada",
    "gn:country_code":"PT",
    "gn:dem":20,
    "gn:feature_class":"P",
    "gn:feature_code":"PPL",
    "gn:name":"Fonte Salgada",
    "gn:population":0,
    "gn:timezone":"Europe/Lisbon",
    "iso:country":"PT",
    "wof:name":"Fonte Salgada",
    "wof:placetype":"locality"
},
  "geometry": {"coordinates":[-7.63333,37.16645],"type":"Point"}
}