{
  "type": "Feature",
  "properties": {
    "gn:admin1_code":"14",
    "gn:admin2_code":"1105",
    "gn:admin3_code":"110502.0",
    "gn:asciiname":"Arneiro",
    "gn:country_code":"PT",
    "gn:dem":76,
    "gn:feature_class":"P",
    "gn:feature_code":"PPL",
    "gn:name":"Arneiro",
    "gn:population":0,
    "gn:timezone":"Europe/Lisbon",
    "iso:country":"PT",
    "wof:name":"Arneiro",
    "wof:placetype":"locality"
},
  "geometry": {"coordinates":[-9.32566,38.70562],"type":"Point"}
}