{
  "type": "Feature",
  "properties": {
    "gn:admin1_code":"6.0",
    "gn:admin2_code":"0504",
    "gn:admin3_code":"50424.0",
    "gn:asciiname":"Canada",
    "gn:country_code":"PT",
    "gn:dem":440,
    "gn:feature_class":"P",
    "gn:feature_code":"PPLL",
    "gn:name":"Canada",
    "gn:population":0,
    "gn:timezone":"Europe/Lisbon",
    "iso:country":"PT",
    "wof:name":"Canada",
    "wof:placetype":"locality"
},
  "geometry": {"coordinates":[-7.67631,40.13341],"type":"Point"}
}