{
  "type": "Feature",
  "properties": {
    "gn:admin1_code":"16",
    "gn:admin2_code":"1215",
    "gn:admin3_code":"121502.0",
    "gn:asciiname":"Monte da Capela",
    "gn:country_code":"PT",
    "gn:dem":216,
    "gn:feature_class":"P",
    "gn:feature_code":"PPL",
    "gn:name":"Monte da Capela",
    "gn:population":0,
    "gn:timezone":"Europe/Lisbon",
    "iso:country":"PT",
    "wof:name":"Monte da Capela",
    "wof:placetype":"locality"
},
  "geometry": {"coordinates":[-7.84196,38.9873],"type":"Point"}
}