{
  "type": "Feature",
  "properties": {
    "gn:admin1_code":"16",
    "gn:admin2_code":"1207",
    "gn:admin3_code":"120708.0",
    "gn:asciiname":"Quinta das Longas",
    "gn:country_code":"PT",
    "gn:dem":321,
    "gn:feature_class":"P",
    "gn:feature_code":"PPL",
    "gn:name":"Quinta das Longas",
    "gn:population":0,
    "gn:timezone":"Europe/Lisbon",
    "iso:country":"PT",
    "wof:name":"Quinta das Longas",
    "wof:placetype":"locality"
},
  "geometry": {"coordinates":[-7.18527,38.94224000000001],"type":"Point"}
}