{
  "type": "Feature",
  "properties": {
    "gn:admin1_code":"10",
    "gn:asciiname":"Eiras",
    "gn:country_code":"PT",
    "gn:dem":-9999,
    "gn:feature_class":"P",
    "gn:feature_code":"PPL",
    "gn:name":"Eiras",
    "gn:population":0,
    "gn:timezone":"Atlantic/Madeira",
    "iso:country":"PT",
    "wof:name":"Eiras",
    "wof:placetype":"locality"
},
  "geometry": {"coordinates":[-16.78333,32.68333],"type":"Point"}
}