{
  "type": "Feature",
  "properties": {
    "gn:admin1_code":"13",
    "gn:admin2_code":"1013",
    "gn:admin3_code":"101301.0",
    "gn:asciiname":"Casal dos Ferreiros",
    "gn:country_code":"PT",
    "gn:dem":346,
    "gn:feature_class":"P",
    "gn:feature_code":"PPL",
    "gn:name":"Casal dos Ferreiros",
    "gn:population":0,
    "gn:timezone":"Europe/Lisbon",
    "iso:country":"PT",
    "wof:name":"Casal dos Ferreiros",
    "wof:placetype":"locality"
},
  "geometry": {"coordinates":[-8.21603,39.88976],"type":"Point"}
}