{
  "type": "Feature",
  "properties": {
    "gn:admin1_code":"14",
    "gn:admin2_code":"1101",
    "gn:admin3_code":"110105.0",
    "gn:asciiname":"Meca",
    "gn:country_code":"PT",
    "gn:dem":17,
    "gn:feature_class":"P",
    "gn:feature_code":"PPL",
    "gn:name":"Meca",
    "gn:population":0,
    "gn:timezone":"Europe/Lisbon",
    "iso:country":"PT",
    "wof:name":"Meca",
    "wof:placetype":"locality"
},
  "geometry": {"coordinates":[-8.99236,39.00564],"type":"Point"}
}