{
  "type": "Feature",
  "properties": {
    "gn:admin1_code":"17",
    "gn:admin2_code":"1314",
    "gn:admin3_code":"131416.0",
    "gn:asciiname":"Sarnada",
    "gn:country_code":"PT",
    "gn:dem":102,
    "gn:feature_class":"P",
    "gn:feature_code":"PPL",
    "gn:name":"Sarnada",
    "gn:population":0,
    "gn:timezone":"Europe/Lisbon",
    "iso:country":"PT",
    "wof:name":"Sarnada",
    "wof:placetype":"locality"
},
  "geometry": {"coordinates":[-8.44639,41.35652],"type":"Point"}
}