{
  "type": "Feature",
  "properties": {
    "gn:admin1_code":"19.0",
    "gn:admin2_code":"1501",
    "gn:admin3_code":"150101.0",
    "gn:asciiname":"Foros de Albergaria",
    "gn:country_code":"PT",
    "gn:dem":82,
    "gn:feature_class":"P",
    "gn:feature_code":"PPL",
    "gn:name":"Foros de Albergaria",
    "gn:population":0,
    "gn:timezone":"Europe/Lisbon",
    "iso:country":"PT",
    "wof:name":"Foros de Albergaria",
    "wof:placetype":"locality"
},
  "geometry": {"coordinates":[-8.54462,38.29357],"type":"Point"}
}