{
  "type": "Feature",
  "properties": {
    "gn:admin1_code":"13.0",
    "gn:admin2_code":"1015",
    "gn:admin3_code":"101506.0",
    "gn:asciiname":"Cavadas",
    "gn:country_code":"PT",
    "gn:dem":49,
    "gn:feature_class":"P",
    "gn:feature_code":"PPL",
    "gn:name":"Cavadas",
    "gn:population":0,
    "gn:timezone":"Europe/Lisbon",
    "iso:country":"PT",
    "wof:name":"Cavadas",
    "wof:placetype":"locality"
},
  "geometry": {"coordinates":[-8.75,40.03333],"type":"Point"}
}