{
  "type": "Feature",
  "properties": {
    "gn:country":"PT",
    "gn:fcode":"PPL",
    "gn:population":0,
    "iso:country":"PT",
    "qs_pg:aaroncc":"PT",
    "qs_pg:gn_country":"PT",
    "qs_pg:gn_fcode":"PPL",
    "qs_pg:gn_pop":0,
    "qs_pg:name":"Seixas",
    "qs_pg:name_adm0":"Portugal",
    "qs_pg:name_adm1":"Viana do Castelo",
    "qs_pg:photos":42,
    "qs_pg:photos_1k":9,
    "qs_pg:photos_9k":1,
    "qs_pg:photos_9r":2,
    "qs_pg:photos_all":42,
    "qs_pg:photos_sr":2,
    "qs_pg:pop_sr":0,
    "qs_pg:qs_pg_placetype":"locality",
    "qs_pg:qs_pg_placetype_gp":"Town",
    "qs_pg:woe_adm0":23424925,
    "woe:adm0_id":23424925,
    "woe:name_adm0":"Portugal",
    "woe:name_adm1":"Viana do Castelo",
    "woe:placetype":"Town",
    "wof:name":"Seixas",
    "wof:placetype":"locality"
},
  "geometry": {"coordinates":[-8.81645,41.89658],"type":"Point"}
}