{
  "type": "Feature",
  "properties": {
    "gn:admin1_code":"4.0",
    "gn:admin2_code":"0307",
    "gn:admin3_code":"30711.0",
    "gn:asciiname":"Felgueiras",
    "gn:country_code":"PT",
    "gn:dem":591,
    "gn:feature_class":"P",
    "gn:feature_code":"PPL",
    "gn:name":"Felgueiras",
    "gn:population":0,
    "gn:timezone":"Europe/Lisbon",
    "iso:country":"PT",
    "name:ara_x_preferred":[
        "\u0641\u064a\u0644\u062c\u0648\u064a\u0631\u0627\u0633"
    ],
    "name:cat_x_preferred":[
        "Felgueiras"
    ],
    "name:ceb_x_preferred":[
        "Felgueiras"
    ],
    "name:deu_x_preferred":[
        "Felgueiras"
    ],
    "name:epo_x_preferred":[
        "Felgueiras"
    ],
    "name:eus_x_preferred":[
        "Felgueiras"
    ],
    "name:fas_x_preferred":[
        "\u0641\u0644\u06af\u0648\u0626\u06cc\u0631\u0627\u0633"
    ],
    "name:fra_x_preferred":[
        "Felgueiras"
    ],
    "name:glg_x_preferred":[
        "Felgueiras"
    ],
    "name:ita_x_preferred":[
        "Felgueiras"
    ],
    "name:kat_x_preferred":[
        "\u10e4\u10d4\u10da\u10d2\u10d4\u10d8\u10e0\u10d0\u10e8\u10d8"
    ],
    "name:lat_x_preferred":[
        "Felgaria"
    ],
    "name:lit_x_preferred":[
        "Felgeirasas"
    ],
    "name:mzn_x_preferred":[
        "\u0641\u0644\u06af\u0648\u0626\u06cc\u0631\u0627\u0633"
    ],
    "name:nld_x_preferred":[
        "Felgueiras"
    ],
    "name:pol_x_preferred":[
        "Felgueiras"
    ],
    "name:por_x_preferred":[
        "Felgueiras"
    ],
    "name:ron_x_preferred":[
        "Felgueiras"
    ],
    "name:rus_x_preferred":[
        "\u0424\u0435\u043b\u0433\u0435\u0439\u0440\u0430\u0448"
    ],
    "name:spa_x_preferred":[
        "Felgueiras"
    ],
    "name:tur_x_preferred":[
        "Felgueiras"
    ],
    "name:ukr_x_preferred":[
        "\u0424\u0435\u043b\u0433\u0435\u0439\u0440\u0430\u0448"
    ],
    "name:vie_x_preferred":[
        "Felgueiras"
    ],
    "name:vol_x_preferred":[
        "Felgueiras"
    ],
    "name:war_x_preferred":[
        "Felgueiras"
    ],
    "name:zho_x_preferred":[
        "\u8d39\u5c14\u76d6\u62c9\u4ec0"
    ],
    "wof:name":"Felgueiras",
    "wof:placetype":"locality"
},
  "geometry": {"coordinates":[-8.11973,41.51793],"type":"Point"}
}