{
  "type": "Feature",
  "properties": {
    "gn:admin1_code":"16",
    "gn:admin2_code":"1214",
    "gn:admin3_code":"121410.0",
    "gn:asciiname":"Monte da Quinta",
    "gn:country_code":"PT",
    "gn:dem":336,
    "gn:feature_class":"P",
    "gn:feature_code":"PPL",
    "gn:name":"Monte da Quinta",
    "gn:population":0,
    "gn:timezone":"Europe/Lisbon",
    "iso:country":"PT",
    "wof:name":"Monte da Quinta",
    "wof:placetype":"locality"
},
  "geometry": {"coordinates":[-7.40351,39.19019],"type":"Point"}
}