{
  "type": "Feature",
  "properties": {
    "gn:admin1_code":"16",
    "gn:admin2_code":"1212",
    "gn:admin3_code":"121208.0",
    "gn:asciiname":"Sao Pedro",
    "gn:country_code":"PT",
    "gn:dem":263,
    "gn:feature_class":"P",
    "gn:feature_code":"PPL",
    "gn:name":"S\u00e3o Pedro",
    "gn:population":0,
    "gn:timezone":"Europe/Lisbon",
    "iso:country":"PT",
    "wof:name":"Sao Pedro",
    "wof:placetype":"locality"
},
  "geometry": {"coordinates":[-7.73297,39.57154],"type":"Point"}
}