{
  "type": "Feature",
  "properties": {
    "gn:admin1_code":"02",
    "gn:admin2_code":"0114",
    "gn:admin3_code":"11402.0",
    "gn:asciiname":"Quinta da Gala",
    "gn:country_code":"PT",
    "gn:dem":59,
    "gn:feature_class":"P",
    "gn:feature_code":"PPL",
    "gn:name":"Quinta da Gala",
    "gn:population":0,
    "gn:timezone":"Europe/Lisbon",
    "iso:country":"PT",
    "wof:name":"Quinta da Gala",
    "wof:placetype":"locality"
},
  "geometry": {"coordinates":[-8.55712,40.47714000000001],"type":"Point"}
}