{
  "type": "Feature",
  "properties": {
    "gn:admin1_code":"11.0",
    "gn:admin2_code":"0902",
    "gn:admin3_code":"90218.0",
    "gn:asciiname":"Monte Perobolso",
    "gn:country_code":"PT",
    "gn:dem":798,
    "gn:feature_class":"P",
    "gn:feature_code":"PPL",
    "gn:name":"Monte Perobolso",
    "gn:population":0,
    "gn:timezone":"Europe/Lisbon",
    "iso:country":"PT",
    "wof:name":"Monte Perobolso",
    "wof:placetype":"locality"
},
  "geometry": {"coordinates":[-6.98016,40.5537],"type":"Point"}
}