{
  "type": "Feature",
  "properties": {
    "gn:admin1_code":"04",
    "gn:admin2_code":"0313",
    "gn:admin3_code":"31342.0",
    "gn:asciiname":"Portelo",
    "gn:country_code":"PT",
    "gn:dem":43,
    "gn:feature_class":"P",
    "gn:feature_code":"PPL",
    "gn:name":"Portelo",
    "gn:population":0,
    "gn:timezone":"Europe/Lisbon",
    "iso:country":"PT",
    "wof:name":"Portelo",
    "wof:placetype":"locality"
},
  "geometry": {"coordinates":[-8.47108,41.60714],"type":"Point"}
}