{
  "type": "Feature",
  "properties": {
    "gn:admin1_code":"18",
    "gn:admin2_code":"1421",
    "gn:admin3_code":"142108.0",
    "gn:asciiname":"Fonte Fria",
    "gn:country_code":"PT",
    "gn:dem":150,
    "gn:feature_class":"P",
    "gn:feature_code":"PPL",
    "gn:name":"Fonte Fria",
    "gn:population":0,
    "gn:timezone":"Europe/Lisbon",
    "iso:country":"PT",
    "wof:name":"Fonte Fria",
    "wof:placetype":"locality"
},
  "geometry": {"coordinates":[-8.4842,39.8203],"type":"Point"}
}