{
  "type": "Feature",
  "properties": {
    "gn:admin1_code":"17",
    "gn:admin2_code":"1301",
    "gn:admin3_code":"130139.0",
    "gn:asciiname":"Vila Chao do Marao",
    "gn:country_code":"PT",
    "gn:dem":337,
    "gn:feature_class":"P",
    "gn:feature_code":"PPL",
    "gn:name":"Vila Ch\u00e3o do Mar\u00e3o",
    "gn:population":0,
    "gn:timezone":"Europe/Lisbon",
    "iso:country":"PT",
    "wof:name":"Vila Chao do Marao",
    "wof:placetype":"locality"
},
  "geometry": {"coordinates":[-8.0271,41.2909],"type":"Point"}
}