{
  "type": "Feature",
  "properties": {
    "iso:country":"PT",
    "name:ara_x_preferred":[
        "\u062a\u0648\u0646\u0633"
    ],
    "name:dut_x_preferred":[
        "Tunes"
    ],
    "name:eng_x_preferred":[
        "Tunes"
    ],
    "name:fre_x_preferred":[
        "Tunes"
    ],
    "name:ger_x_preferred":[
        "Tunes"
    ],
    "name:kaz_x_preferred":[
        "\u0422\u0443\u043d\u0435\u0448"
    ],
    "name:nan_x_preferred":[
        "Tunes"
    ],
    "name:por_x_preferred":[
        "Tunes"
    ],
    "name:rus_x_preferred":[
        "\u0422\u0443\u043d\u0435\u0448"
    ],
    "name:spa_x_preferred":[
        "Tunes"
    ],
    "name:tur_x_preferred":[
        "Tunes"
    ],
    "qs:a0":"Portugal",
    "qs:a1":"*Faro",
    "qs:a1r":"0",
    "qs:adm0":"Portugal",
    "qs:la_lc":"*",
    "qs:level":"locality",
    "qs:loc":"Tunes",
    "qs:loc_alt":"Tunes",
    "qs:pop":0,
    "qs:type":"buffered point",
    "wof:lang":[
        "por"
    ],
    "wof:name":"Tunes",
    "wof:placetype":"locality"
},
  "geometry": {"coordinates":[-8.284686,37.164692],"type":"Point"}
}