{
  "type": "Feature",
  "properties": {
    "gn:admin1_code":"20.0",
    "gn:admin2_code":"1606",
    "gn:admin3_code":"160603.0",
    "gn:asciiname":"Bravais",
    "gn:country_code":"PT",
    "gn:dem":62,
    "gn:feature_class":"P",
    "gn:feature_code":"PPL",
    "gn:name":"Brav\u00e3is",
    "gn:population":0,
    "gn:timezone":"Europe/Lisbon",
    "iso:country":"PT",
    "wof:name":"Bravais",
    "wof:placetype":"locality"
},
  "geometry": {"coordinates":[-8.44999,41.80048],"type":"Point"}
}