{
  "type": "Feature",
  "properties": {
    "gn:admin1_code":"18",
    "gn:admin2_code":"1403",
    "gn:admin3_code":"140304.0",
    "gn:asciiname":"Salgueiral",
    "gn:country_code":"PT",
    "gn:dem":52,
    "gn:feature_class":"P",
    "gn:feature_code":"PPL",
    "gn:name":"Salgueiral",
    "gn:population":0,
    "gn:timezone":"Europe/Lisbon",
    "iso:country":"PT",
    "wof:name":"Salgueiral",
    "wof:placetype":"locality"
},
  "geometry": {"coordinates":[-8.49325,39.11705],"type":"Point"}
}