{
  "type": "Feature",
  "properties": {
    "gn:admin1_code":"7.0",
    "gn:admin2_code":"0604",
    "gn:admin3_code":"60406.0",
    "gn:asciiname":"Casal do Missa",
    "gn:country_code":"PT",
    "gn:dem":111,
    "gn:feature_class":"P",
    "gn:feature_code":"PPL",
    "gn:name":"Casal do Missa",
    "gn:population":0,
    "gn:timezone":"Europe/Lisbon",
    "iso:country":"PT",
    "wof:name":"Casal do Missa",
    "wof:placetype":"locality"
},
  "geometry": {"coordinates":[-8.58846,40.10964],"type":"Point"}
}