{
  "type": "Feature",
  "properties": {
    "gn:admin1_code":"7.0",
    "gn:admin2_code":"0606",
    "gn:admin3_code":"60601.0",
    "gn:asciiname":"Mega Cimeira",
    "gn:country_code":"PT",
    "gn:dem":450,
    "gn:feature_class":"P",
    "gn:feature_code":"PPL",
    "gn:name":"Mega Cimeira",
    "gn:population":0,
    "gn:timezone":"Europe/Lisbon",
    "iso:country":"PT",
    "wof:name":"Mega Cimeira",
    "wof:placetype":"locality"
},
  "geometry": {"coordinates":[-8.14948,40.01869],"type":"Point"}
}