{
  "type": "Feature",
  "properties": {
    "gn:country":"PT",
    "gn:fcode":"PPL",
    "gn:population":0,
    "iso:country":"PT",
    "name:ceb_x_preferred":[
        "Vilar Seco"
    ],
    "name:deu_x_preferred":[
        "Vilar Seco"
    ],
    "name:fra_x_preferred":[
        "Vilar Seco"
    ],
    "name:nld_x_preferred":[
        "Vilar Seco"
    ],
    "name:por_x_preferred":[
        "Vilar Seco"
    ],
    "name:rus_x_preferred":[
        "\u0412\u0438\u043b\u0430\u0440-\u0421\u0435\u043a\u0443"
    ],
    "qs_pg:aaroncc":"PT",
    "qs_pg:gn_country":"PT",
    "qs_pg:gn_fcode":"PPL",
    "qs_pg:gn_pop":0,
    "qs_pg:name":"Vilar Seco",
    "qs_pg:name_adm0":"Portugal",
    "qs_pg:name_adm1":"Viseu",
    "qs_pg:photos_9k":1,
    "qs_pg:photos_9r":1,
    "qs_pg:photos_all":6,
    "qs_pg:photos_sr":0,
    "qs_pg:pop_sr":0,
    "qs_pg:qs_pg_placetype":"locality",
    "qs_pg:qs_pg_placetype_gp":"Town",
    "qs_pg:woe_adm0":23424925,
    "woe:adm0_id":23424925,
    "woe:name_adm0":"Portugal",
    "woe:name_adm1":"Viseu",
    "woe:placetype":"Town",
    "wof:name":"Vilar Seco",
    "wof:placetype":"locality"
},
  "geometry": {"coordinates":[-7.86455,40.55969],"type":"Point"}
}