{
  "type": "Feature",
  "properties": {
    "gn:admin1_code":"11.0",
    "gn:admin2_code":"0912",
    "gn:admin3_code":"91212.0",
    "gn:asciiname":"Cabeco de Eiras",
    "gn:country_code":"PT",
    "gn:dem":620,
    "gn:feature_class":"P",
    "gn:feature_code":"PPL",
    "gn:name":"Cabe\u00e7o de Eiras",
    "gn:population":0,
    "gn:timezone":"Europe/Lisbon",
    "iso:country":"PT",
    "wof:name":"Cabeco de Eiras",
    "wof:placetype":"locality"
},
  "geometry": {"coordinates":[-7.77963,40.34468],"type":"Point"}
}