{
  "type": "Feature",
  "properties": {
    "gn:admin1_code":"22.0",
    "gn:admin2_code":"1810",
    "gn:admin3_code":"181007.0",
    "gn:asciiname":"Lameiro Longo",
    "gn:country_code":"PT",
    "gn:dem":708,
    "gn:feature_class":"P",
    "gn:feature_code":"PPL",
    "gn:name":"Lameiro Longo",
    "gn:population":0,
    "gn:timezone":"Europe/Lisbon",
    "iso:country":"PT",
    "wof:name":"Lameiro Longo",
    "wof:placetype":"locality"
},
  "geometry": {"coordinates":[-8.29798,40.7033],"type":"Point"}
}