{
  "type": "Feature",
  "properties": {
    "gn:admin1_code":"7.0",
    "gn:admin2_code":"0615",
    "gn:admin3_code":"61507.0",
    "gn:asciiname":"Pombalinho",
    "gn:country_code":"PT",
    "gn:dem":299,
    "gn:feature_class":"P",
    "gn:feature_code":"PPL",
    "gn:name":"Pombalinho",
    "gn:population":0,
    "gn:timezone":"Europe/Lisbon",
    "iso:country":"PT",
    "name:deu_x_preferred":[
        "Pombalinho"
    ],
    "name:fra_x_preferred":[
        "Pombalinho"
    ],
    "name:ita_x_preferred":[
        "Pombalinho"
    ],
    "name:kaz_x_preferred":[
        "\u041f\u043e\u043c\u0431\u0430\u043b\u0438\u043d\u044c\u044e"
    ],
    "name:nld_x_preferred":[
        "Pombalinho"
    ],
    "name:por_x_preferred":[
        "Pombalinho"
    ],
    "name:rus_x_preferred":[
        "\u041f\u043e\u043c\u0431\u0430\u043b\u0438\u043d\u044c\u044e"
    ],
    "name:spa_x_preferred":[
        "Pombalinho"
    ],
    "name:tur_x_preferred":[
        "Pombalinho"
    ],
    "wof:name":"Pombalinho",
    "wof:placetype":"locality"
},
  "geometry": {"coordinates":[-8.46873,40.01283],"type":"Point"}
}