{
  "type": "Feature",
  "properties": {
    "gn:admin1_code":"22.0",
    "gn:admin2_code":"1823",
    "gn:admin3_code":"182307.0",
    "gn:asciiname":"Cavernais",
    "gn:country_code":"PT",
    "gn:dem":590,
    "gn:feature_class":"P",
    "gn:feature_code":"PPL",
    "gn:name":"Cavern\u00e3is",
    "gn:population":0,
    "gn:timezone":"Europe/Lisbon",
    "iso:country":"PT",
    "wof:name":"Cavernais",
    "wof:placetype":"locality"
},
  "geometry": {"coordinates":[-7.83325,40.71042],"type":"Point"}
}