{
  "type": "Feature",
  "properties": {
    "gn:admin1_code":"09",
    "gn:admin2_code":"0802",
    "gn:admin3_code":"80205.0",
    "gn:asciiname":"Taipas",
    "gn:country_code":"PT",
    "gn:dem":280,
    "gn:feature_class":"P",
    "gn:feature_code":"PPL",
    "gn:name":"Taipas",
    "gn:population":0,
    "gn:timezone":"Europe/Lisbon",
    "iso:country":"PT",
    "wof:name":"Taipas",
    "wof:placetype":"locality"
},
  "geometry": {"coordinates":[-7.71589,37.31796],"type":"Point"}
}