{
  "type": "Feature",
  "properties": {
    "gn:admin1_code":"13",
    "gn:admin2_code":"1004",
    "gn:admin3_code":"100402.0",
    "gn:asciiname":"Alcaidaria",
    "gn:country_code":"PT",
    "gn:dem":130,
    "gn:feature_class":"P",
    "gn:feature_code":"PPL",
    "gn:name":"Alcaidaria",
    "gn:population":0,
    "gn:timezone":"Europe/Lisbon",
    "iso:country":"PT",
    "wof:name":"Alcaidaria",
    "wof:placetype":"locality"
},
  "geometry": {"coordinates":[-8.77631,39.6619],"type":"Point"}
}