{
  "type": "Feature",
  "properties": {
    "gn:admin1_code":"4.0",
    "gn:admin2_code":"0303",
    "gn:admin3_code":"30316.0",
    "gn:asciiname":"Espadanido",
    "gn:country_code":"PT",
    "gn:dem":208,
    "gn:feature_class":"P",
    "gn:feature_code":"PPL",
    "gn:name":"Espadanido",
    "gn:population":0,
    "gn:timezone":"Europe/Lisbon",
    "iso:country":"PT",
    "wof:name":"Espadanido",
    "wof:placetype":"locality"
},
  "geometry": {"coordinates":[-8.40447,41.53919000000001],"type":"Point"}
}