{
  "type": "Feature",
  "properties": {
    "gn:admin1_code":"18",
    "gn:admin2_code":"1401",
    "gn:admin3_code":"140119.0",
    "gn:asciiname":"Sobral Basto",
    "gn:country_code":"PT",
    "gn:dem":198,
    "gn:feature_class":"P",
    "gn:feature_code":"PPL",
    "gn:name":"Sobral Basto",
    "gn:population":0,
    "gn:timezone":"Europe/Lisbon",
    "iso:country":"PT",
    "wof:name":"Sobral Basto",
    "wof:placetype":"locality"
},
  "geometry": {"coordinates":[-8.20873,39.5848],"type":"Point"}
}