{
  "type": "Feature",
  "properties": {
    "gn:admin1_code":"11.0",
    "gn:admin2_code":"0913",
    "gn:admin3_code":"91321.0",
    "gn:asciiname":"Falachos",
    "gn:country_code":"PT",
    "gn:dem":655,
    "gn:feature_class":"P",
    "gn:feature_code":"PPL",
    "gn:name":"Falachos",
    "gn:population":0,
    "gn:timezone":"Europe/Lisbon",
    "iso:country":"PT",
    "wof:name":"Falachos",
    "wof:placetype":"locality"
},
  "geometry": {"coordinates":[-7.30712,40.78097],"type":"Point"}
}