{
  "type": "Feature",
  "properties": {
    "gn:admin1_code":"09",
    "gn:admin2_code":"0808",
    "gn:admin3_code":"80811.0",
    "gn:asciiname":"Cerro da Cova",
    "gn:country_code":"PT",
    "gn:dem":235,
    "gn:feature_class":"P",
    "gn:feature_code":"PPL",
    "gn:name":"Cerro da Cova",
    "gn:population":0,
    "gn:timezone":"Europe/Lisbon",
    "iso:country":"PT",
    "wof:name":"Cerro da Cova",
    "wof:placetype":"locality"
},
  "geometry": {"coordinates":[-8.0441,37.20207],"type":"Point"}
}