{
  "type": "Feature",
  "properties": {
    "gn:admin1_code":"13",
    "gn:admin2_code":"1006",
    "gn:admin3_code":"100609.0",
    "gn:asciiname":"Guisado",
    "gn:country_code":"PT",
    "gn:dem":85,
    "gn:feature_class":"P",
    "gn:feature_code":"PPL",
    "gn:name":"Guisado",
    "gn:population":0,
    "gn:timezone":"Europe/Lisbon",
    "iso:country":"PT",
    "wof:name":"Guisado",
    "wof:placetype":"locality"
},
  "geometry": {"coordinates":[-9.10378,39.44133],"type":"Point"}
}