{
  "type": "Feature",
  "properties": {
    "gn:admin1_code":"22.0",
    "gn:admin2_code":"1804",
    "gn:admin3_code":"180409.0",
    "gn:asciiname":"Ervilhais",
    "gn:country_code":"PT",
    "gn:dem":760,
    "gn:feature_class":"P",
    "gn:feature_code":"PPL",
    "gn:name":"Ervilhais",
    "gn:population":0,
    "gn:timezone":"Europe/Lisbon",
    "iso:country":"PT",
    "name:und_x_variant":[
        "Lugar Grande",
        "Ervilhais"
    ],
    "wof:name":"Ervilhais",
    "wof:placetype":"locality"
},
  "geometry": {"coordinates":[-8.13899,41.02992],"type":"Point"}
}