{
  "type": "Feature",
  "properties": {
    "gn:admin1_code":"04",
    "gn:admin2_code":"0303",
    "gn:admin3_code":"30354.0",
    "gn:asciiname":"Sampaio",
    "gn:country_code":"PT",
    "gn:dem":147,
    "gn:feature_class":"P",
    "gn:feature_code":"PPL",
    "gn:name":"Sampaio",
    "gn:population":0,
    "gn:timezone":"Europe/Lisbon",
    "iso:country":"PT",
    "name:bpy_x_preferred":[
        "\u09b8\u09be\u09ae\u09aa\u09be\u0987\u0993"
    ],
    "name:epo_x_preferred":[
        "Sampaio"
    ],
    "name:eus_x_preferred":[
        "Sampaio"
    ],
    "name:fra_x_preferred":[
        "Sampaio"
    ],
    "name:hye_x_preferred":[
        "\u054d\u0561\u0574\u057a\u0561\u0575\u0578\u0582"
    ],
    "name:ita_x_preferred":[
        "Sampaio"
    ],
    "name:kaz_x_preferred":[
        "\u0421\u0430\u043c\u043f\u0430\u044e"
    ],
    "name:nld_x_preferred":[
        "Sampaio"
    ],
    "name:nor_x_preferred":[
        "Sampaio"
    ],
    "name:por_x_preferred":[
        "Sampaio"
    ],
    "name:ron_x_preferred":[
        "Sampaio"
    ],
    "name:rus_x_preferred":[
        "\u0421\u0430\u043c\u043f\u0430\u044e"
    ],
    "name:spa_x_preferred":[
        "Sampaio"
    ],
    "name:vie_x_preferred":[
        "Sampaio"
    ],
    "name:vol_x_preferred":[
        "Sampaio"
    ],
    "name:war_x_preferred":[
        "Sampaio"
    ],
    "name:zho_x_preferred":[
        "\u6851\u5e15\u7ea6"
    ],
    "wof:name":"Sampaio",
    "wof:placetype":"locality"
},
  "geometry": {"coordinates":[-8.46274,41.53393],"type":"Point"}
}