{
  "type": "Feature",
  "properties": {
    "gn:gn_country":"PT",
    "gn:gn_fcode":"ADM3",
    "gn:gn_pop":0,
    "iso:country":"PT",
    "name:dut_x_preferred":[
        "Nossa Senhora da Boa F\u00e9"
    ],
    "name:eng_x_preferred":[
        "Nossa Senhora da Boa F\u00e9"
    ],
    "name:fre_x_preferred":[
        "Nossa Senhora da Boa F\u00e9"
    ],
    "name:ger_x_preferred":[
        "Nossa Senhora da Boa F\u00e9"
    ],
    "name:kaz_x_preferred":[
        "\u041d\u043e\u0441\u0441\u0430-\u0421\u0435\u043d\u044c\u043e\u0440\u0430-\u0434\u0430-\u0411\u043e\u0430-\u0424\u0435"
    ],
    "name:por_x_preferred":[
        "Nossa Senhora da Boa F\u00e9"
    ],
    "name:rus_x_preferred":[
        "\u041d\u043e\u0441\u0441\u0430-\u0421\u0435\u043d\u044c\u043e\u0440\u0430-\u0434\u0430-\u0411\u043e\u0430-\u0424\u0435"
    ],
    "name:spa_x_preferred":[
        "Nossa Senhora da Boa F\u00e9"
    ],
    "name:tur_x_preferred":[
        "Nossa Senhora da Boa F\u00e9"
    ],
    "qs_pg:aaroncc":"PT",
    "qs_pg:gn_country":"PT",
    "qs_pg:gn_fcode":"ADM3",
    "qs_pg:gn_pop":0,
    "qs_pg:name":"Nossa Senhora da Boa F\u00e9",
    "qs_pg:name_adm0":"Portugal",
    "qs_pg:name_adm1":"Evora",
    "qs_pg:photos":138,
    "qs_pg:photos_1k":28,
    "qs_pg:photos_9k":1,
    "qs_pg:photos_9r":3,
    "qs_pg:photos_all":138,
    "qs_pg:photos_sr":3,
    "qs_pg:pop_sr":0,
    "qs_pg:qs_pg_placetype":"locality",
    "qs_pg:qs_pg_placetype_gp":"Town",
    "qs_pg:woe_adm0":23424925,
    "woe:adm0_id":23424925,
    "woe:name_adm0":"Portugal",
    "woe:name_adm1":"Evora",
    "woe:placetype":"Town",
    "wof:name":"Nossa Senhora da Boa F\u00e9",
    "wof:placetype":"locality"
},
  "geometry": {"coordinates":[-8.08733,38.54878],"type":"Point"}
}