{
  "type": "Feature",
  "properties": {
    "gn:gn_country":"PT",
    "iso:country":"PT",
    "qs_pg:aaroncc":"PT",
    "qs_pg:gn_country":"PT",
    "qs_pg:name":"Fonte Santa",
    "qs_pg:name_adm0":"Portugal",
    "qs_pg:name_adm1":"Castelo Branco",
    "qs_pg:photos":40,
    "qs_pg:photos_1k":8,
    "qs_pg:photos_9k":1,
    "qs_pg:photos_9r":2,
    "qs_pg:photos_all":40,
    "qs_pg:photos_sr":2,
    "qs_pg:pop_sr":0,
    "qs_pg:qs_pg_placetype":"locality",
    "qs_pg:qs_pg_placetype_gp":"Town",
    "qs_pg:woe_adm0":23424925,
    "woe:adm0_id":23424925,
    "woe:name_adm0":"Portugal",
    "woe:name_adm1":"Castelo Branco",
    "woe:placetype":"Town",
    "wof:name":"Fonte Santa",
    "wof:placetype":"locality"
},
  "geometry": {"coordinates":[-6.876153,40.00053],"type":"Point"}
}