{
  "type": "Feature",
  "properties": {
    "gn:admin1_code":"4.0",
    "gn:admin2_code":"0304",
    "gn:admin3_code":"30405.0",
    "gn:asciiname":"Carrazedo",
    "gn:country_code":"PT",
    "gn:dem":658,
    "gn:feature_class":"P",
    "gn:feature_code":"PPL",
    "gn:name":"Carrazedo",
    "gn:population":0,
    "gn:timezone":"Europe/Lisbon",
    "iso:country":"PT",
    "wof:name":"Carrazedo",
    "wof:placetype":"locality"
},
  "geometry": {"coordinates":[-8.04231,41.58801],"type":"Point"}
}