{
  "type": "Feature",
  "properties": {
    "gn:admin1_code":"20.0",
    "gn:admin2_code":"1609",
    "gn:admin3_code":"160918.0",
    "gn:asciiname":"Balteiro",
    "gn:country_code":"PT",
    "gn:dem":70,
    "gn:feature_class":"P",
    "gn:feature_code":"PPL",
    "gn:name":"Balteiro",
    "gn:population":0,
    "gn:timezone":"Europe/Lisbon",
    "iso:country":"PT",
    "wof:name":"Balteiro",
    "wof:placetype":"locality"
},
  "geometry": {"coordinates":[-8.70314,41.75702],"type":"Point"}
}