{
  "type": "Feature",
  "properties": {
    "gn:admin1_code":"09",
    "gn:admin2_code":"0808",
    "gn:admin3_code":"80809.0",
    "gn:asciiname":"Cerro",
    "gn:country_code":"PT",
    "gn:dem":142,
    "gn:feature_class":"P",
    "gn:feature_code":"PPL",
    "gn:name":"Cerro",
    "gn:population":0,
    "gn:timezone":"Europe/Lisbon",
    "iso:country":"PT",
    "name:ceb_x_preferred":[
        "Cerro"
    ],
    "name:deu_x_preferred":[
        "Cerro"
    ],
    "name:fra_x_preferred":[
        "Cerro"
    ],
    "name:ita_x_preferred":[
        "Cerro"
    ],
    "name:pms_x_preferred":[
        "Cerro"
    ],
    "name:por_x_preferred":[
        "Cerro"
    ],
    "name:rus_x_preferred":[
        "\u0421\u0435\u0440\u0440\u043e"
    ],
    "name:spa_x_preferred":[
        "Cerro"
    ],
    "name:srp_x_preferred":[
        "\u010cero"
    ],
    "name:swe_x_preferred":[
        "Cerro"
    ],
    "wof:name":"Cerro",
    "wof:placetype":"locality"
},
  "geometry": {"coordinates":[-8.09094,37.18342],"type":"Point"}
}