{
  "type": "Feature",
  "properties": {
    "gn:admin1_code":"11",
    "gn:admin2_code":"0911",
    "gn:admin3_code":"91124.0",
    "gn:asciiname":"Quintas de Sao Bartolomeu",
    "gn:country_code":"PT",
    "gn:dem":782,
    "gn:feature_class":"P",
    "gn:feature_code":"PPL",
    "gn:name":"Quintas de S\u00e3o Bartolomeu",
    "gn:population":0,
    "gn:timezone":"Europe/Lisbon",
    "iso:country":"PT",
    "wof:name":"Quintas de Sao Bartolomeu",
    "wof:placetype":"locality"
},
  "geometry": {"coordinates":[-7.09923,40.37175],"type":"Point"}
}