{
  "type": "Feature",
  "properties": {
    "iso:country":"PT",
    "name:chi_x_preferred":[
        "Rebord\u00f5es"
    ],
    "name:deu_x_preferred":[
        "Rebord\u00f5es"
    ],
    "name:dut_x_preferred":[
        "Rebord\u00f5es"
    ],
    "name:eng_x_preferred":[
        "Rebord\u00f5es"
    ],
    "name:fre_x_preferred":[
        "Rebord\u00f5es"
    ],
    "name:ger_x_preferred":[
        "Rebord\u00f5es"
    ],
    "name:kaz_x_preferred":[
        "\u0420\u0435\u0431\u043e\u0440\u0434\u043e\u0439\u043d\u0448"
    ],
    "name:may_x_preferred":[
        "Rebord\u00f5es"
    ],
    "name:msa_x_preferred":[
        "Rebord\u00f5es"
    ],
    "name:nld_x_preferred":[
        "Rebord\u00f5es"
    ],
    "name:por_x_colloquial":[
        "Rebordoes"
    ],
    "name:por_x_preferred":[
        "Rebord\u00f5es"
    ],
    "name:rus_x_preferred":[
        "\u0420\u0435\u0431\u043e\u0440\u0434\u043e\u0439\u043d\u0448"
    ],
    "name:spa_x_preferred":[
        "Rebord\u00f5es"
    ],
    "name:tur_x_preferred":[
        "Rebord\u00f5es"
    ],
    "name:zho_x_preferred":[
        "\u96f7\u535a\u5c14\u4e1c\u4f0a\u4ec0"
    ],
    "qs:a0":"Portugal",
    "qs:a1":"*Porto",
    "qs:a1r":"0",
    "qs:adm0":"Portugal",
    "qs:la_lc":"*",
    "qs:level":"locality",
    "qs:loc":"Rebord\u00f5es",
    "qs:loc_alt":"Rebordoes",
    "qs:pop":0,
    "qs:type":"buffered point",
    "wd:wordcount":233,
    "wof:lang":[
        "por"
    ],
    "wof:name":"Rebord\u00f5es",
    "wof:placetype":"locality"
},
  "geometry": {"coordinates":[-8.43465,41.35243],"type":"Point"}
}