{
  "type": "Feature",
  "properties": {
    "gn:admin1_code":"20",
    "gn:admin2_code":"1607",
    "gn:admin3_code":"160703.0",
    "gn:asciiname":"Terra Feita",
    "gn:country_code":"PT",
    "gn:dem":63,
    "gn:feature_class":"P",
    "gn:feature_code":"PPL",
    "gn:name":"Terra Feita",
    "gn:population":0,
    "gn:timezone":"Europe/Lisbon",
    "iso:country":"PT",
    "wof:name":"Terra Feita",
    "wof:placetype":"locality"
},
  "geometry": {"coordinates":[-8.66206,41.76391],"type":"Point"}
}