{
  "type": "Feature",
  "properties": {
    "gn:admin1_code":"04",
    "gn:admin2_code":"0302",
    "gn:admin3_code":"30208.0",
    "gn:asciiname":"Varziela",
    "gn:country_code":"PT",
    "gn:dem":85,
    "gn:feature_class":"P",
    "gn:feature_code":"PPL",
    "gn:name":"Varziela",
    "gn:population":0,
    "gn:timezone":"Europe/Lisbon",
    "iso:country":"PT",
    "wof:name":"Varziela",
    "wof:placetype":"locality"
},
  "geometry": {"coordinates":[-8.62033,41.49692],"type":"Point"}
}