{
  "type": "Feature",
  "properties": {
    "gn:admin1_code":"2.0",
    "gn:admin2_code":"0117",
    "gn:admin3_code":"11708.0",
    "gn:asciiname":"Macida",
    "gn:country_code":"PT",
    "gn:dem":283,
    "gn:feature_class":"P",
    "gn:feature_code":"PPL",
    "gn:name":"Macida",
    "gn:population":0,
    "gn:timezone":"Europe/Lisbon",
    "iso:country":"PT",
    "wof:name":"Macida",
    "wof:placetype":"locality"
},
  "geometry": {"coordinates":[-8.36386,40.6666],"type":"Point"}
}