{
  "type": "Feature",
  "properties": {
    "gn:admin1_code":"14",
    "gn:admin2_code":"1101",
    "gn:admin3_code":"110102.0",
    "gn:asciiname":"Barbas de Porco",
    "gn:country_code":"PT",
    "gn:dem":123,
    "gn:feature_class":"P",
    "gn:feature_code":"PPL",
    "gn:name":"Barbas de Porco",
    "gn:population":0,
    "gn:timezone":"Europe/Lisbon",
    "iso:country":"PT",
    "wof:name":"Barbas de Porco",
    "wof:placetype":"locality"
},
  "geometry": {"coordinates":[-9.131,39.08707],"type":"Point"}
}