{
  "type": "Feature",
  "properties": {
    "gn:admin1_code":"5.0",
    "gn:admin2_code":"0403",
    "gn:admin3_code":"40306.0",
    "gn:asciiname":"Besteiros",
    "gn:country_code":"PT",
    "gn:dem":780,
    "gn:feature_class":"P",
    "gn:feature_code":"PPL",
    "gn:name":"Besteiros",
    "gn:population":0,
    "gn:timezone":"Europe/Lisbon",
    "iso:country":"PT",
    "wof:name":"Besteiros",
    "wof:placetype":"locality"
},
  "geometry": {"coordinates":[-7.26198,41.21559],"type":"Point"}
}