{
  "type": "Feature",
  "properties": {
    "gn:admin1_code":"08",
    "gn:admin2_code":"0711",
    "gn:admin3_code":"71101.0",
    "gn:asciiname":"Sao Marcos do Campo",
    "gn:country_code":"PT",
    "gn:dem":213,
    "gn:feature_class":"P",
    "gn:feature_code":"PPL",
    "gn:name":"S\u00e3o Marcos do Campo",
    "gn:population":0,
    "gn:timezone":"Europe/Lisbon",
    "iso:country":"PT",
    "name:und_x_variant":[
        "Campo",
        "Campo S\u00e3o Margos",
        "S\u00e3o Marcos do Campo"
    ],
    "wof:name":"Sao Marcos do Campo",
    "wof:placetype":"locality"
},
  "geometry": {"coordinates":[-7.51134,38.34016],"type":"Point"}
}