{
  "type": "Feature",
  "properties": {
    "gn:admin1_code":"10",
    "gn:admin2_code":"3110",
    "gn:admin3_code":"311001.0",
    "gn:asciiname":"Malhada",
    "gn:country_code":"PT",
    "gn:dem":429,
    "gn:feature_class":"P",
    "gn:feature_code":"PPL",
    "gn:name":"Malhada",
    "gn:population":0,
    "gn:timezone":"Atlantic/Madeira",
    "iso:country":"PT",
    "name:bpy_x_preferred":[
        "\u09ae\u09be\u09b2\u09b9\u09be\u09a1\u09be"
    ],
    "name:epo_x_preferred":[
        "Malhada"
    ],
    "name:eus_x_preferred":[
        "Malhada"
    ],
    "name:fra_x_preferred":[
        "Malhada"
    ],
    "name:hye_x_preferred":[
        "\u0544\u0561\u056c\u0575\u0561\u0564\u0561"
    ],
    "name:ita_x_preferred":[
        "Malhada"
    ],
    "name:kat_x_preferred":[
        "\u10db\u10d0\u10da\u10d8\u10d0\u10d3\u10d0"
    ],
    "name:kaz_x_preferred":[
        "\u041c\u0430\u043b\u044c\u044f\u0434\u0430"
    ],
    "name:mlg_x_preferred":[
        "Malhada"
    ],
    "name:nld_x_preferred":[
        "Malhada"
    ],
    "name:nor_x_preferred":[
        "Malhada"
    ],
    "name:pol_x_preferred":[
        "Malhada"
    ],
    "name:por_x_preferred":[
        "Malhada"
    ],
    "name:ron_x_preferred":[
        "Malhada"
    ],
    "name:rus_x_preferred":[
        "\u041c\u0430\u043b\u044c\u044f\u0434\u0430"
    ],
    "name:vie_x_preferred":[
        "Malhada"
    ],
    "name:vol_x_preferred":[
        "Malhada"
    ],
    "name:war_x_preferred":[
        "Malhada"
    ],
    "name:zho_x_preferred":[
        "\u9a6c\u5229\u4e9a\u8fbe"
    ],
    "wof:name":"Malhada",
    "wof:placetype":"locality"
},
  "geometry": {"coordinates":[-16.98333,32.81667],"type":"Point"}
}