{
  "type": "Feature",
  "properties": {
    "gn:admin1_code":"16",
    "gn:admin2_code":"1203",
    "gn:admin3_code":"120302.0",
    "gn:asciiname":"Senhora da Rabaca",
    "gn:country_code":"PT",
    "gn:dem":111,
    "gn:feature_class":"P",
    "gn:feature_code":"PPL",
    "gn:name":"Senhora da Raba\u00e7a",
    "gn:population":0,
    "gn:timezone":"Europe/Lisbon",
    "iso:country":"PT",
    "wof:name":"Senhora da Rabaca",
    "wof:placetype":"locality"
},
  "geometry": {"coordinates":[-8.06523,39.07919],"type":"Point"}
}