{
  "type": "Feature",
  "properties": {
    "gn:admin1_code":"22.0",
    "gn:admin2_code":"1814",
    "gn:admin3_code":"181409.0",
    "gn:asciiname":"Nagosela",
    "gn:country_code":"PT",
    "gn:dem":208,
    "gn:feature_class":"P",
    "gn:feature_code":"PPL",
    "gn:name":"Nagosela",
    "gn:population":0,
    "gn:timezone":"Europe/Lisbon",
    "iso:country":"PT",
    "wof:name":"Nagosela",
    "wof:placetype":"locality"
},
  "geometry": {"coordinates":[-8.0702,40.45167],"type":"Point"}
}