{
  "type": "Feature",
  "properties": {
    "gn:admin1_code":"09",
    "gn:admin2_code":"0805",
    "gn:admin3_code":"80503.0",
    "gn:asciiname":"Colmeal",
    "gn:country_code":"PT",
    "gn:dem":134,
    "gn:feature_class":"P",
    "gn:feature_code":"PPL",
    "gn:name":"Colmeal",
    "gn:population":0,
    "gn:timezone":"Europe/Lisbon",
    "iso:country":"PT",
    "wof:name":"Colmeal",
    "wof:placetype":"locality"
},
  "geometry": {"coordinates":[-7.9519,37.10157],"type":"Point"}
}