{
  "type": "Feature",
  "properties": {
    "gn:admin1_code":"22.0",
    "gn:admin2_code":"1823",
    "gn:admin3_code":"182332.0",
    "gn:asciiname":"Figueiro",
    "gn:country_code":"PT",
    "gn:dem":423,
    "gn:feature_class":"P",
    "gn:feature_code":"PPL",
    "gn:name":"Figueiro",
    "gn:population":0,
    "gn:timezone":"Europe/Lisbon",
    "iso:country":"PT",
    "wof:name":"Figueiro",
    "wof:placetype":"locality"
},
  "geometry": {"coordinates":[-7.97431,40.65929000000001],"type":"Point"}
}