{
  "type": "Feature",
  "properties": {
    "gn:gn_country":"PT",
    "gn:gn_fcode":"PPL",
    "gn:gn_pop":0,
    "iso:country":"PT",
    "name:ast_x_preferred":[
        "Sosa"
    ],
    "name:cat_x_preferred":[
        "Sosa"
    ],
    "name:ceb_x_preferred":[
        "Sosa"
    ],
    "name:deu_x_preferred":[
        "Sosa"
    ],
    "name:eng_x_preferred":[
        "Sosa"
    ],
    "name:fra_x_preferred":[
        "Sosa"
    ],
    "name:glg_x_preferred":[
        "Sosa"
    ],
    "name:kaz_x_preferred":[
        "\u0421\u043e\u0437\u0430"
    ],
    "name:nan_x_preferred":[
        "Sosa"
    ],
    "name:por_x_preferred":[
        "Sosa"
    ],
    "name:rus_x_preferred":[
        "\u0421\u043e\u0437\u0430"
    ],
    "name:spa_x_preferred":[
        "Sosa"
    ],
    "name:tur_x_preferred":[
        "Sosa"
    ],
    "name:ukr_x_preferred":[
        "\u0421\u043e\u0437\u0430"
    ],
    "name:unk_x_variant":[
        "S\u00f4za"
    ],
    "name:zho_x_preferred":[
        "\u7d22\u8428"
    ],
    "qs_pg:aaroncc":"PT",
    "qs_pg:gn_country":"PT",
    "qs_pg:gn_fcode":"PPL",
    "qs_pg:gn_pop":0,
    "qs_pg:name":"Sosa",
    "qs_pg:name_adm0":"Portugal",
    "qs_pg:name_adm1":"Aveiro",
    "qs_pg:photos_9k":1,
    "qs_pg:photos_9r":1,
    "qs_pg:photos_all":1,
    "qs_pg:photos_sr":0,
    "qs_pg:pop_sr":0,
    "qs_pg:qs_pg_placetype":"locality",
    "qs_pg:qs_pg_placetype_gp":"Town",
    "qs_pg:woe_adm0":23424925,
    "woe:adm0_id":23424925,
    "woe:name_adm0":"Portugal",
    "woe:name_adm1":"Aveiro",
    "woe:placetype":"Town",
    "wof:name":"Sosa",
    "wof:placetype":"locality"
},
  "geometry": {"coordinates":[-8.65785,40.54399],"type":"Point"}
}