{
  "type": "Feature",
  "properties": {
    "gn:admin1_code":"14",
    "gn:admin2_code":"1113",
    "gn:admin3_code":"111315.0",
    "gn:asciiname":"Lugar d'Alem",
    "gn:country_code":"PT",
    "gn:dem":35,
    "gn:feature_class":"P",
    "gn:feature_code":"PPL",
    "gn:name":"Lugar d\u2019Al\u00e9m",
    "gn:population":0,
    "gn:timezone":"Europe/Lisbon",
    "iso:country":"PT",
    "wof:name":"Lugar d'Alem",
    "wof:placetype":"locality"
},
  "geometry": {"coordinates":[-9.29978,39.10371],"type":"Point"}
}