{
  "type": "Feature",
  "properties": {
    "gn:admin1_code":"7.0",
    "gn:admin2_code":"0613",
    "gn:admin3_code":"61301.0",
    "gn:asciiname":"Lourinhal",
    "gn:country_code":"PT",
    "gn:dem":264,
    "gn:feature_class":"P",
    "gn:feature_code":"PPL",
    "gn:name":"Lourinhal",
    "gn:population":0,
    "gn:timezone":"Europe/Lisbon",
    "iso:country":"PT",
    "wof:name":"Lourinhal",
    "wof:placetype":"locality"
},
  "geometry": {"coordinates":[-8.30185,40.3469],"type":"Point"}
}