{
  "type": "Feature",
  "properties": {
    "gn:admin1_code":"17.0",
    "gn:admin2_code":"1315",
    "gn:admin3_code":"131503.0",
    "gn:asciiname":"Costa",
    "gn:country_code":"PT",
    "gn:dem":109,
    "gn:feature_class":"P",
    "gn:feature_code":"PPL",
    "gn:name":"Costa",
    "gn:population":0,
    "gn:timezone":"Europe/Lisbon",
    "iso:country":"PT",
    "wof:name":"Costa",
    "wof:placetype":"locality"
},
  "geometry": {"coordinates":[-8.55,41.21667],"type":"Point"}
}