{
  "type": "Feature",
  "properties": {
    "gn:admin1_code":"04",
    "gn:admin2_code":"0309",
    "gn:admin3_code":"30923.0",
    "gn:asciiname":"Sao Joao de Rei",
    "gn:country_code":"PT",
    "gn:dem":181,
    "gn:feature_class":"P",
    "gn:feature_code":"PPL",
    "gn:name":"S\u00e3o Jo\u00e3o de Rei",
    "gn:population":0,
    "gn:timezone":"Europe/Lisbon",
    "iso:country":"PT",
    "wof:name":"Sao Joao de Rei",
    "wof:placetype":"locality"
},
  "geometry": {"coordinates":[-8.2921,41.62154],"type":"Point"}
}