{
  "type": "Feature",
  "properties": {
    "gn:admin1_code":"04",
    "gn:admin2_code":"0307",
    "gn:admin3_code":"30729.0",
    "gn:asciiname":"Silvares",
    "gn:country_code":"PT",
    "gn:dem":415,
    "gn:feature_class":"P",
    "gn:feature_code":"PPL",
    "gn:name":"Silvares",
    "gn:population":0,
    "gn:timezone":"Europe/Lisbon",
    "iso:country":"PT",
    "name:und_x_variant":[
        "S\u00e3o Martinho",
        "Silvares"
    ],
    "wof:name":"Silvares",
    "wof:placetype":"locality"
},
  "geometry": {"coordinates":[-8.16813,41.41374],"type":"Point"}
}