{
  "type": "Feature",
  "properties": {
    "gn:admin1_code":"18",
    "gn:admin2_code":"1416",
    "gn:admin3_code":"141622.0",
    "gn:asciiname":"Quinta da Requeixada",
    "gn:country_code":"PT",
    "gn:dem":27,
    "gn:feature_class":"P",
    "gn:feature_code":"PPL",
    "gn:name":"Quinta da Requeixada",
    "gn:population":0,
    "gn:timezone":"Europe/Lisbon",
    "iso:country":"PT",
    "wof:name":"Quinta da Requeixada",
    "wof:placetype":"locality"
},
  "geometry": {"coordinates":[-8.58325,39.34487],"type":"Point"}
}