{
  "type": "Feature",
  "properties": {
    "gn:admin1_code":"13",
    "gn:admin2_code":"1009",
    "gn:admin3_code":"100920.0",
    "gn:asciiname":"Touria",
    "gn:country_code":"PT",
    "gn:dem":145,
    "gn:feature_class":"P",
    "gn:feature_code":"PPL",
    "gn:name":"Touria",
    "gn:population":0,
    "gn:timezone":"Europe/Lisbon",
    "iso:country":"PT",
    "wof:name":"Touria",
    "wof:placetype":"locality"
},
  "geometry": {"coordinates":[-8.75635,39.72828],"type":"Point"}
}