{
  "type": "Feature",
  "properties": {
    "gn:admin1_code":"7.0",
    "gn:admin2_code":"0606",
    "gn:admin3_code":"60603.0",
    "gn:asciiname":"Adela",
    "gn:country_code":"PT",
    "gn:dem":588,
    "gn:feature_class":"P",
    "gn:feature_code":"PPL",
    "gn:name":"\u00c1dela",
    "gn:population":0,
    "gn:timezone":"Europe/Lisbon",
    "iso:country":"PT",
    "name:ceb_x_preferred":[
        "Adela"
    ],
    "name:ces_x_preferred":[
        "Ad\u00e9la"
    ],
    "name:nld_x_preferred":[
        "Adela"
    ],
    "name:por_x_preferred":[
        "Adela"
    ],
    "name:ron_x_preferred":[
        "Adela"
    ],
    "name:rus_x_preferred":[
        "\u0410\u0434\u0435\u043b\u0430"
    ],
    "name:slk_x_preferred":[
        "Adela"
    ],
    "name:spa_x_preferred":[
        "Adela"
    ],
    "name:swe_x_preferred":[
        "Adela"
    ],
    "wof:name":"Adela",
    "wof:placetype":"locality"
},
  "geometry": {"coordinates":[-7.99067,40.17595],"type":"Point"}
}