{
  "type": "Feature",
  "properties": {
    "gn:admin1_code":"19",
    "gn:admin2_code":"1501",
    "gn:admin3_code":"150104.0",
    "gn:asciiname":"Porto do Rei",
    "gn:country_code":"PT",
    "gn:dem":37,
    "gn:feature_class":"P",
    "gn:feature_code":"PPL",
    "gn:name":"Porto do Rei",
    "gn:population":0,
    "gn:timezone":"Europe/Lisbon",
    "iso:country":"PT",
    "wof:name":"Porto do Rei",
    "wof:placetype":"locality"
},
  "geometry": {"coordinates":[-8.40532,38.29042000000001],"type":"Point"}
}