{
  "type": "Feature",
  "properties": {
    "gn:admin1_code":"17.0",
    "gn:admin2_code":"1306",
    "gn:admin3_code":"130609.0",
    "gn:asciiname":"Monte das Pedras",
    "gn:country_code":"PT",
    "gn:dem":80,
    "gn:feature_class":"P",
    "gn:feature_code":"PPL",
    "gn:name":"Monte das Pedras",
    "gn:population":0,
    "gn:timezone":"Europe/Lisbon",
    "iso:country":"PT",
    "wof:name":"Monte das Pedras",
    "wof:placetype":"locality"
},
  "geometry": {"coordinates":[-8.66136,41.23965],"type":"Point"}
}