{
  "type": "Feature",
  "properties": {
    "gn:admin1_code":"06",
    "gn:admin2_code":"0503",
    "gn:admin3_code":"50322.0",
    "gn:asciiname":"Sobral de Casegas",
    "gn:country_code":"PT",
    "gn:dem":615,
    "gn:feature_class":"P",
    "gn:feature_code":"PPL",
    "gn:name":"Sobral de Casegas",
    "gn:population":0,
    "gn:timezone":"Europe/Lisbon",
    "iso:country":"PT",
    "wof:name":"Sobral de Casegas",
    "wof:placetype":"locality"
},
  "geometry": {"coordinates":[-7.75,40.21667],"type":"Point"}
}