{
  "type": "Feature",
  "properties": {
    "gn:admin1_code":"21",
    "gn:admin2_code":"1707",
    "gn:admin3_code":"170708.0",
    "gn:asciiname":"Valongo de Milhais",
    "gn:country_code":"PT",
    "gn:dem":525,
    "gn:feature_class":"P",
    "gn:feature_code":"PPL",
    "gn:name":"Valongo de Milhais",
    "gn:population":0,
    "gn:timezone":"Europe/Lisbon",
    "iso:country":"PT",
    "wof:name":"Valongo de Milhais",
    "wof:placetype":"locality"
},
  "geometry": {"coordinates":[-7.44326,41.44473],"type":"Point"}
}