{
  "type": "Feature",
  "properties": {
    "gn:admin1_code":"11.0",
    "gn:admin2_code":"0905",
    "gn:admin3_code":"90504.0",
    "gn:asciiname":"Figueiro da Granja",
    "gn:country_code":"PT",
    "gn:dem":476,
    "gn:feature_class":"P",
    "gn:feature_code":"PPL",
    "gn:name":"Figueiro da Granja",
    "gn:population":0,
    "gn:timezone":"Europe/Lisbon",
    "iso:country":"PT",
    "wof:name":"Figueiro da Granja",
    "wof:placetype":"locality"
},
  "geometry": {"coordinates":[-7.49716,40.63278],"type":"Point"}
}