{
  "type": "Feature",
  "properties": {
    "gn:admin1_code":"7.0",
    "gn:admin2_code":"0613",
    "gn:admin3_code":"61305.0",
    "gn:asciiname":"Coico",
    "gn:country_code":"PT",
    "gn:dem":121,
    "gn:feature_class":"P",
    "gn:feature_code":"PPL",
    "gn:name":"Coi\u00e7o",
    "gn:population":0,
    "gn:timezone":"Europe/Lisbon",
    "iso:country":"PT",
    "wof:name":"Coico",
    "wof:placetype":"locality"
},
  "geometry": {"coordinates":[-8.24363,40.30667],"type":"Point"}
}