{
  "type": "Feature",
  "properties": {
    "gn:admin1_code":"09",
    "gn:admin2_code":"0813",
    "gn:admin3_code":"81305.0",
    "gn:asciiname":"Monte Alto",
    "gn:country_code":"PT",
    "gn:dem":162,
    "gn:feature_class":"P",
    "gn:feature_code":"PPL",
    "gn:name":"Monte Alto",
    "gn:population":0,
    "gn:timezone":"Europe/Lisbon",
    "iso:country":"PT",
    "name:ceb_x_preferred":[
        "Monte Alto"
    ],
    "name:ita_x_preferred":[
        "Monte Alto"
    ],
    "name:mlg_x_preferred":[
        "Monte Alto"
    ],
    "name:nld_x_preferred":[
        "Monte Alto"
    ],
    "name:pol_x_preferred":[
        "Monte Alto"
    ],
    "name:por_x_preferred":[
        "Monte Alto"
    ],
    "name:srp_x_preferred":[
        "\u041c\u043e\u043d\u0442\u0435 \u0410\u043b\u0442\u043e"
    ],
    "name:swe_x_preferred":[
        "Monte Alto"
    ],
    "wof:name":"Monte Alto",
    "wof:placetype":"locality"
},
  "geometry": {"coordinates":[-8.23958,37.31678],"type":"Point"}
}