{
  "type": "Feature",
  "properties": {
    "gn:admin1_code":"7.0",
    "gn:admin2_code":"0615",
    "gn:admin3_code":"61505.0",
    "gn:asciiname":"Piquete",
    "gn:country_code":"PT",
    "gn:dem":24,
    "gn:feature_class":"P",
    "gn:feature_code":"PPL",
    "gn:name":"Piquete",
    "gn:population":0,
    "gn:timezone":"Europe/Lisbon",
    "iso:country":"PT",
    "name:bpy_x_preferred":[
        "\u09aa\u09bf\u0995\u09c1\u09af\u09bc\u09c7\u099f\u09c7"
    ],
    "name:ceb_x_preferred":[
        "Piquete"
    ],
    "name:epo_x_preferred":[
        "Piquete"
    ],
    "name:eus_x_preferred":[
        "Piquete"
    ],
    "name:fra_x_preferred":[
        "Piquete"
    ],
    "name:ita_x_preferred":[
        "Piquete"
    ],
    "name:kaz_x_preferred":[
        "\u041f\u0438\u043a\u0435\u0442\u0438"
    ],
    "name:mlg_x_preferred":[
        "Piquete"
    ],
    "name:nld_x_preferred":[
        "Piquete"
    ],
    "name:nor_x_preferred":[
        "Piquete"
    ],
    "name:pol_x_preferred":[
        "Piquete"
    ],
    "name:por_x_preferred":[
        "Piquete"
    ],
    "name:ron_x_preferred":[
        "Piquete"
    ],
    "name:rus_x_preferred":[
        "\u041f\u0438\u043a\u0435\u0442\u0438"
    ],
    "name:sco_x_preferred":[
        "Piquete"
    ],
    "name:swe_x_preferred":[
        "Piquete"
    ],
    "name:vie_x_preferred":[
        "Piquete"
    ],
    "name:vol_x_preferred":[
        "Piquete"
    ],
    "name:war_x_preferred":[
        "Piquete"
    ],
    "name:zho_x_preferred":[
        "\u76ae\u514b\u8482"
    ],
    "wof:name":"Piquete",
    "wof:placetype":"locality"
},
  "geometry": {"coordinates":[-8.65361,40.08022],"type":"Point"}
}