{
  "type": "Feature",
  "properties": {
    "gn:admin1_code":"13",
    "gn:admin2_code":"1015",
    "gn:admin3_code":"101506.0",
    "gn:asciiname":"Casal do Loureiro",
    "gn:country_code":"PT",
    "gn:dem":36,
    "gn:feature_class":"P",
    "gn:feature_code":"PPL",
    "gn:name":"Casal do Loureiro",
    "gn:population":0,
    "gn:timezone":"Europe/Lisbon",
    "iso:country":"PT",
    "wof:name":"Casal do Loureiro",
    "wof:placetype":"locality"
},
  "geometry": {"coordinates":[-8.73036,40.00806],"type":"Point"}
}