{
  "type": "Feature",
  "properties": {
    "gn:admin1_code":"2.0",
    "gn:admin2_code":"0118",
    "gn:admin3_code":"11802.0",
    "gn:asciiname":"Fonte do Rei",
    "gn:country_code":"PT",
    "gn:dem":54,
    "gn:feature_class":"P",
    "gn:feature_code":"PPL",
    "gn:name":"Fonte do Rei",
    "gn:population":0,
    "gn:timezone":"Europe/Lisbon",
    "iso:country":"PT",
    "wof:name":"Fonte do Rei",
    "wof:placetype":"locality"
},
  "geometry": {"coordinates":[-8.64852,40.44685],"type":"Point"}
}