{
  "type": "Feature",
  "properties": {
    "gn:admin1_code":"22.0",
    "gn:admin2_code":"1821",
    "gn:admin3_code":"182121.0",
    "gn:asciiname":"Carvalhal da Mulher",
    "gn:country_code":"PT",
    "gn:dem":745,
    "gn:feature_class":"P",
    "gn:feature_code":"PPL",
    "gn:name":"Carvalhal da Mulher",
    "gn:population":0,
    "gn:timezone":"Europe/Lisbon",
    "iso:country":"PT",
    "wof:name":"Carvalhal da Mulher",
    "wof:placetype":"locality"
},
  "geometry": {"coordinates":[-8.13455,40.61137],"type":"Point"}
}