{
  "type": "Feature",
  "properties": {
    "gn:admin1_code":"07",
    "gn:admin2_code":"0605",
    "gn:admin3_code":"60501.0",
    "gn:asciiname":"Santo Amaro da Amoreira",
    "gn:country_code":"PT",
    "gn:dem":95,
    "gn:feature_class":"P",
    "gn:feature_code":"PPL",
    "gn:name":"Santo Amaro da Amoreira",
    "gn:population":0,
    "gn:timezone":"Europe/Lisbon",
    "iso:country":"PT",
    "wof:name":"Santo Amaro da Amoreira",
    "wof:placetype":"locality"
},
  "geometry": {"coordinates":[-8.80276,40.20035],"type":"Point"}
}