{
  "type": "Feature",
  "properties": {
    "gn:admin1_code":"18",
    "gn:admin2_code":"1418",
    "gn:admin3_code":"141815.0",
    "gn:asciiname":"Pederneira",
    "gn:country_code":"PT",
    "gn:dem":270,
    "gn:feature_class":"P",
    "gn:feature_code":"PPL",
    "gn:name":"Pederneira",
    "gn:population":0,
    "gn:timezone":"Europe/Lisbon",
    "iso:country":"PT",
    "name:por_x_preferred":[
        "Pederneira"
    ],
    "wof:name":"Pederneira",
    "wof:placetype":"locality"
},
  "geometry": {"coordinates":[-8.28491,39.59598],"type":"Point"}
}