{
  "type": "Feature",
  "properties": {
    "gn:admin1_code":"02",
    "gn:admin2_code":"0108",
    "gn:admin3_code":"10807.0",
    "gn:asciiname":"Santa Luzia",
    "gn:country_code":"PT",
    "gn:dem":5,
    "gn:feature_class":"P",
    "gn:feature_code":"PPL",
    "gn:name":"Santa Luzia",
    "gn:population":0,
    "gn:timezone":"Europe/Lisbon",
    "iso:country":"PT",
    "wof:name":"Santa Luzia",
    "wof:placetype":"locality"
},
  "geometry": {"coordinates":[-8.62628,40.75126],"type":"Point"}
}