{
  "type": "Feature",
  "properties": {
    "gn:admin1_code":"17.0",
    "gn:admin2_code":"1317",
    "gn:admin3_code":"131706.0",
    "gn:asciiname":"Bagaco",
    "gn:country_code":"PT",
    "gn:dem":149,
    "gn:feature_class":"P",
    "gn:feature_code":"PPL",
    "gn:name":"Baga\u00e7o",
    "gn:population":0,
    "gn:timezone":"Europe/Lisbon",
    "iso:country":"PT",
    "wof:name":"Bagaco",
    "wof:placetype":"locality"
},
  "geometry": {"coordinates":[-8.57518,41.04321],"type":"Point"}
}