{
  "type": "Feature",
  "properties": {
    "gn:admin1_code":"7.0",
    "gn:admin2_code":"0611",
    "gn:admin3_code":"61107.0",
    "gn:asciiname":"Lagos da Beira",
    "gn:country_code":"PT",
    "gn:dem":540,
    "gn:feature_class":"P",
    "gn:feature_code":"PPL",
    "gn:name":"Lagos da Beira",
    "gn:population":0,
    "gn:timezone":"Europe/Lisbon",
    "iso:country":"PT",
    "wof:name":"Lagos da Beira",
    "wof:placetype":"locality"
},
  "geometry": {"coordinates":[-7.82867,40.37506],"type":"Point"}
}