{
  "type": "Feature",
  "properties": {
    "gn:admin1_code":"18",
    "gn:admin2_code":"1405",
    "gn:admin3_code":"140502.0",
    "gn:asciiname":"Guarita dos Bebados",
    "gn:country_code":"PT",
    "gn:dem":41,
    "gn:feature_class":"P",
    "gn:feature_code":"PPL",
    "gn:name":"Guarita dos B\u00eabados",
    "gn:population":0,
    "gn:timezone":"Europe/Lisbon",
    "iso:country":"PT",
    "wof:name":"Guarita dos Bebados",
    "wof:placetype":"locality"
},
  "geometry": {"coordinates":[-8.72765,38.81423],"type":"Point"}
}