{
  "type": "Feature",
  "properties": {
    "gn:admin1_code":"6.0",
    "gn:admin2_code":"0503",
    "gn:admin3_code":"50323.0",
    "gn:asciiname":"Gibaltar",
    "gn:country_code":"PT",
    "gn:dem":542,
    "gn:feature_class":"P",
    "gn:feature_code":"PPL",
    "gn:name":"Gibaltar",
    "gn:population":0,
    "gn:timezone":"Europe/Lisbon",
    "iso:country":"PT",
    "wof:name":"Gibaltar",
    "wof:placetype":"locality"
},
  "geometry": {"coordinates":[-7.45325,40.32495],"type":"Point"}
}