{
  "type": "Feature",
  "properties": {
    "gn:admin1_code":"20.0",
    "gn:admin2_code":"1607",
    "gn:admin3_code":"160737.0",
    "gn:asciiname":"Cedofeitas",
    "gn:country_code":"PT",
    "gn:dem":253,
    "gn:feature_class":"P",
    "gn:feature_code":"PPL",
    "gn:name":"Cedofeitas",
    "gn:population":0,
    "gn:timezone":"Europe/Lisbon",
    "iso:country":"PT",
    "wof:name":"Cedofeitas",
    "wof:placetype":"locality"
},
  "geometry": {"coordinates":[-8.53288,41.8039],"type":"Point"}
}