{
  "type": "Feature",
  "properties": {
    "gn:admin1_code":"20.0",
    "gn:admin2_code":"1608",
    "gn:admin3_code":"160808.0",
    "gn:asciiname":"Baroso",
    "gn:country_code":"PT",
    "gn:dem":54,
    "gn:feature_class":"P",
    "gn:feature_code":"PPL",
    "gn:name":"Baroso",
    "gn:population":0,
    "gn:timezone":"Europe/Lisbon",
    "iso:country":"PT",
    "wof:name":"Baroso",
    "wof:placetype":"locality"
},
  "geometry": {"coordinates":[-8.60936,42.0451],"type":"Point"}
}