{
  "type": "Feature",
  "properties": {
    "gn:admin1_code":"4.0",
    "gn:admin2_code":"0303",
    "gn:admin3_code":"30320.0",
    "gn:asciiname":"Guisande",
    "gn:country_code":"PT",
    "gn:dem":238,
    "gn:feature_class":"P",
    "gn:feature_code":"PPL",
    "gn:name":"Guisande",
    "gn:population":1053,
    "gn:timezone":"Europe/Lisbon",
    "iso:country":"PT",
    "name:ceb_x_preferred":[
        "Guisande"
    ],
    "name:deu_x_preferred":[
        "Guisande"
    ],
    "name:fra_x_preferred":[
        "Guisande"
    ],
    "name:glg_x_preferred":[
        "Guisande"
    ],
    "name:nld_x_preferred":[
        "Guisande"
    ],
    "name:por_x_preferred":[
        "Guisande"
    ],
    "name:rus_x_preferred":[
        "\u0413\u0438\u0437\u0430\u043d\u0434\u0435"
    ],
    "wof:name":"Guisande",
    "wof:placetype":"locality",
    "wof:population":1053
},
  "geometry": {"coordinates":[-8.44564,41.48264],"type":"Point"}
}