{
  "type": "Feature",
  "properties": {
    "gn:admin1_code":"4.0",
    "gn:admin2_code":"0303",
    "gn:admin3_code":"30320.0",
    "gn:asciiname":"Guisande",
    "gn:country_code":"PT",
    "gn:dem":238,
    "gn:feature_class":"P",
    "gn:feature_code":"PPL",
    "gn:name":"Guisande",
    "gn:population":1053,
    "gn:timezone":"Europe/Lisbon",
    "iso:country":"PT",
    "wof:name":"Guisande",
    "wof:placetype":"locality",
    "wof:population":1053
},
  "geometry": {"coordinates":[-8.44564,41.48264],"type":"Point"}
}