{
  "type": "Feature",
  "properties": {
    "gn:admin1_code":"18",
    "gn:admin2_code":"1418",
    "gn:admin3_code":"141815.0",
    "gn:asciiname":"Pai d'Aviz",
    "gn:country_code":"PT",
    "gn:dem":220,
    "gn:feature_class":"P",
    "gn:feature_code":"PPL",
    "gn:name":"Pai d\u2019Aviz",
    "gn:population":0,
    "gn:timezone":"Europe/Lisbon",
    "iso:country":"PT",
    "wof:name":"Pai d'Aviz",
    "wof:placetype":"locality"
},
  "geometry": {"coordinates":[-8.32301,39.59511],"type":"Point"}
}