{
  "type": "Feature",
  "properties": {
    "gn:admin1_code":"21.0",
    "gn:admin2_code":"1711",
    "gn:admin3_code":"171106.0",
    "gn:asciiname":"Medroes",
    "gn:country_code":"PT",
    "gn:dem":602,
    "gn:feature_class":"P",
    "gn:feature_code":"PPL",
    "gn:name":"Medr\u00f5es",
    "gn:population":0,
    "gn:timezone":"Europe/Lisbon",
    "iso:country":"PT",
    "wof:name":"Medroes",
    "wof:placetype":"locality"
},
  "geometry": {"coordinates":[-7.82004,41.21364000000001],"type":"Point"}
}