{
  "type": "Feature",
  "properties": {
    "gn:admin1_code":"22.0",
    "gn:admin2_code":"1807",
    "gn:admin3_code":"180707.0",
    "gn:asciiname":"Caria",
    "gn:country_code":"PT",
    "gn:dem":797,
    "gn:feature_class":"P",
    "gn:feature_code":"PPL",
    "gn:name":"Caria",
    "gn:population":0,
    "gn:timezone":"Europe/Lisbon",
    "iso:country":"PT",
    "name:afr_x_preferred":[
        "Kari\u00eb"
    ],
    "name:ara_x_preferred":[
        "\u0643\u0627\u0631\u064a\u0627"
    ],
    "name:aze_x_preferred":[
        "Kariya"
    ],
    "name:bel_x_preferred":[
        "\u041a\u0430\u0440\u044b\u044f"
    ],
    "name:bre_x_preferred":[
        "Karia"
    ],
    "name:bul_x_preferred":[
        "\u041a\u0430\u0440\u0438\u044f"
    ],
    "name:cat_x_preferred":[
        "C\u00e0ria"
    ],
    "name:ces_x_preferred":[
        "K\u00e1rie"
    ],
    "name:cym_x_preferred":[
        "Caria"
    ],
    "name:dan_x_preferred":[
        "Karien"
    ],
    "name:deu_x_preferred":[
        "Karien"
    ],
    "name:ell_x_preferred":[
        "\u039a\u03b1\u03c1\u03af\u03b1"
    ],
    "name:epo_x_preferred":[
        "Kario"
    ],
    "name:est_x_preferred":[
        "Kaaria"
    ],
    "name:eus_x_preferred":[
        "Karia"
    ],
    "name:fas_x_preferred":[
        "\u06a9\u0627\u0631\u06cc\u0627"
    ],
    "name:fin_x_preferred":[
        "Kaaria"
    ],
    "name:fra_x_preferred":[
        "Carie"
    ],
    "name:glg_x_preferred":[
        "Caria"
    ],
    "name:heb_x_preferred":[
        "\u05e7\u05d0\u05e8\u05d9\u05d4"
    ],
    "name:hrv_x_preferred":[
        "Karija"
    ],
    "name:hun_x_preferred":[
        "K\u00e1ria"
    ],
    "name:hye_x_preferred":[
        "\u053f\u0561\u0580\u056b\u0561"
    ],
    "name:ind_x_preferred":[
        "Karia"
    ],
    "name:ita_x_preferred":[
        "Caria"
    ],
    "name:jpn_x_preferred":[
        "\u30ab\u30ea\u30a2"
    ],
    "name:kat_x_preferred":[
        "\u10d9\u10d0\u10e0\u10d8\u10d0"
    ],
    "name:kor_x_preferred":[
        "\uce74\ub9ac\uc544"
    ],
    "name:lat_x_preferred":[
        "Caria"
    ],
    "name:lit_x_preferred":[
        "Karija"
    ],
    "name:nld_x_preferred":[
        "Kari\u00eb"
    ],
    "name:nor_x_preferred":[
        "Karia"
    ],
    "name:pol_x_preferred":[
        "Karia"
    ],
    "name:por_x_preferred":[
        "C\u00e1ria"
    ],
    "name:ron_x_preferred":[
        "Caria"
    ],
    "name:rus_x_preferred":[
        "\u041a\u0430\u0440\u0438\u044f"
    ],
    "name:slk_x_preferred":[
        "K\u00e1ria"
    ],
    "name:slv_x_preferred":[
        "Karija"
    ],
    "name:spa_x_preferred":[
        "Caria"
    ],
    "name:srp_x_preferred":[
        "Karija"
    ],
    "name:swe_x_preferred":[
        "Karien"
    ],
    "name:tur_x_preferred":[
        "Karya"
    ],
    "name:ukr_x_preferred":[
        "\u041a\u0430\u0440\u0456\u044f"
    ],
    "name:uzb_x_preferred":[
        "Kariya"
    ],
    "name:vie_x_preferred":[
        "Caria"
    ],
    "name:zho_x_preferred":[
        "\u5361\u91cc\u4e9a"
    ],
    "wof:name":"Caria",
    "wof:placetype":"locality"
},
  "geometry": {"coordinates":[-7.59884,40.93252],"type":"Point"}
}