{
  "type": "Feature",
  "properties": {
    "gn:admin1_code":"16",
    "gn:admin2_code":"1214",
    "gn:admin3_code":"121407.0",
    "gn:asciiname":"Freguesia",
    "gn:cc2":"PT",
    "gn:country_code":"PT",
    "gn:dem":412,
    "gn:feature_class":"P",
    "gn:feature_code":"PPL",
    "gn:name":"Freguesia",
    "gn:population":0,
    "gn:timezone":"Europe/Lisbon",
    "iso:country":"PT",
    "name:arg_x_preferred":[
        "Fregues\u00eda"
    ],
    "name:ast_x_preferred":[
        "Freguesia"
    ],
    "name:cat_x_preferred":[
        "Freguesia"
    ],
    "name:dan_x_preferred":[
        "Freguesia"
    ],
    "name:deu_x_preferred":[
        "Freguesia"
    ],
    "name:epo_x_preferred":[
        "Freguesia"
    ],
    "name:fin_x_preferred":[
        "Freguesia"
    ],
    "name:fra_x_preferred":[
        "Freguesia"
    ],
    "name:glg_x_preferred":[
        "Fregues\u00eda"
    ],
    "name:heb_x_preferred":[
        "\u05e4\u05e8\u05d2\u05d6\u05d9\u05d4"
    ],
    "name:ita_x_preferred":[
        "Freguesia"
    ],
    "name:lat_x_preferred":[
        "Parochia"
    ],
    "name:mwl_x_preferred":[
        "Fraguesie"
    ],
    "name:nld_x_preferred":[
        "Freguesia"
    ],
    "name:oci_x_preferred":[
        "Freguesia"
    ],
    "name:por_x_preferred":[
        "Freguesia"
    ],
    "name:rus_x_preferred":[
        "\u0424\u0440\u0435\u0433\u0435\u0437\u0438\u044f"
    ],
    "name:sco_x_preferred":[
        "Freguesia"
    ],
    "name:spa_x_preferred":[
        "Freguesia"
    ],
    "name:swe_x_preferred":[
        "Freguesia"
    ],
    "name:ukr_x_preferred":[
        "\u041f\u0430\u0440\u0430\u0444\u0456\u0457 \u041f\u043e\u0440\u0442\u0443\u0433\u0430\u043b\u0456\u0457"
    ],
    "name:und_x_variant":[
        "Freguezia"
    ],
    "name:urd_x_preferred":[
        "\u0641\u0631\u06cc\u06af\u06cc\u0632\u06cc\u0627"
    ],
    "name:vie_x_preferred":[
        "Freguesia"
    ],
    "name:zho_x_preferred":[
        "\u5802\u533a"
    ],
    "wof:name":"Freguesia",
    "wof:placetype":"locality"
},
  "geometry": {"coordinates":[-7.26667,39.28333],"type":"Point"}
}