{
  "type": "Feature",
  "properties": {
    "gn:admin1_code":"07",
    "gn:admin2_code":"0615",
    "gn:admin3_code":"61510.0",
    "gn:asciiname":"Tapeus",
    "gn:country_code":"PT",
    "gn:dem":96,
    "gn:feature_class":"P",
    "gn:feature_code":"PPL",
    "gn:name":"Tapeus",
    "gn:population":0,
    "gn:timezone":"Europe/Lisbon",
    "iso:country":"PT",
    "wof:name":"Tapeus",
    "wof:placetype":"locality"
},
  "geometry": {"coordinates":[-8.53931,40.03732],"type":"Point"}
}