{
  "type": "Feature",
  "properties": {
    "gn:admin1_code":"2.0",
    "gn:admin2_code":"0109",
    "gn:admin3_code":"10903.0",
    "gn:asciiname":"Mota",
    "gn:country_code":"PT",
    "gn:dem":153,
    "gn:feature_class":"P",
    "gn:feature_code":"PPL",
    "gn:name":"Mota",
    "gn:population":0,
    "gn:timezone":"Europe/Lisbon",
    "iso:country":"PT",
    "wof:name":"Mota",
    "wof:placetype":"locality"
},
  "geometry": {"coordinates":[-8.44859,40.9949],"type":"Point"}
}