{
  "type": "Feature",
  "properties": {
    "gn:admin1_code":"23.0",
    "gn:admin2_code":"4401",
    "gn:admin3_code":"440104.0",
    "gn:asciiname":"Achada",
    "gn:country_code":"PT",
    "gn:dem":43,
    "gn:feature_class":"P",
    "gn:feature_code":"PPL",
    "gn:name":"Achada",
    "gn:population":0,
    "gn:timezone":"Atlantic/Azores",
    "iso:country":"PT",
    "name:ceb_x_preferred":[
        "Achada"
    ],
    "name:deu_x_preferred":[
        "Achada"
    ],
    "name:msa_x_preferred":[
        "Achada"
    ],
    "name:por_x_preferred":[
        "Achada"
    ],
    "name:rus_x_preferred":[
        "\u0410\u0448\u0430\u0434\u0430"
    ],
    "name:spa_x_preferred":[
        "Achada"
    ],
    "wof:name":"Achada",
    "wof:placetype":"locality"
},
  "geometry": {"coordinates":[-28.03333,39.08333],"type":"Point"}
}