{
  "type": "Feature",
  "properties": {
    "gn:admin1_code":"20",
    "gn:admin2_code":"1609",
    "gn:admin3_code":"160925.0",
    "gn:asciiname":"Rocha",
    "gn:country_code":"PT",
    "gn:dem":45,
    "gn:feature_class":"P",
    "gn:feature_code":"PPL",
    "gn:name":"Rocha",
    "gn:population":0,
    "gn:timezone":"Europe/Lisbon",
    "iso:country":"PT",
    "wof:name":"Rocha",
    "wof:placetype":"locality"
},
  "geometry": {"coordinates":[-8.7851,41.73606],"type":"Point"}
}