{
  "type": "Feature",
  "properties": {
    "gn:admin1_code":"20.0",
    "gn:admin2_code":"1607",
    "gn:admin3_code":"160712.0",
    "gn:asciiname":"Cabracao",
    "gn:country_code":"PT",
    "gn:dem":146,
    "gn:feature_class":"P",
    "gn:feature_code":"PPL",
    "gn:name":"Cabra\u00e7\u00e3o",
    "gn:population":0,
    "gn:timezone":"Europe/Lisbon",
    "iso:country":"PT",
    "wof:name":"Cabracao",
    "wof:placetype":"locality"
},
  "geometry": {"coordinates":[-8.65098,41.83284],"type":"Point"}
}