{
  "type": "Feature",
  "properties": {
    "gn:admin1_code":"21.0",
    "gn:admin2_code":"1714",
    "gn:admin3_code":"171421.0",
    "gn:asciiname":"Pena",
    "gn:country_code":"PT",
    "gn:dem":803,
    "gn:feature_class":"P",
    "gn:feature_code":"PPL",
    "gn:name":"Pena",
    "gn:population":0,
    "gn:timezone":"Europe/Lisbon",
    "iso:country":"PT",
    "wof:name":"Pena",
    "wof:placetype":"locality"
},
  "geometry": {"coordinates":[-7.81556,41.29096],"type":"Point"}
}