{
  "type": "Feature",
  "properties": {
    "gn:admin1_code":"14",
    "gn:admin2_code":"1109",
    "gn:admin3_code":"110913.0",
    "gn:asciiname":"Junqueiros",
    "gn:country_code":"PT",
    "gn:dem":59,
    "gn:feature_class":"P",
    "gn:feature_code":"PPL",
    "gn:name":"Junqueiros",
    "gn:population":0,
    "gn:timezone":"Europe/Lisbon",
    "iso:country":"PT",
    "wof:name":"Junqueiros",
    "wof:placetype":"locality"
},
  "geometry": {"coordinates":[-9.38437,38.98724],"type":"Point"}
}