{
  "type": "Feature",
  "properties": {
    "gn:admin1_code":"2.0",
    "gn:admin2_code":"0104",
    "gn:admin3_code":"10402.0",
    "gn:asciiname":"Cortegada",
    "gn:country_code":"PT",
    "gn:dem":347,
    "gn:feature_class":"P",
    "gn:feature_code":"PPL",
    "gn:name":"Cortegada",
    "gn:population":0,
    "gn:timezone":"Europe/Lisbon",
    "iso:country":"PT",
    "wof:name":"Cortegada",
    "wof:placetype":"locality"
},
  "geometry": {"coordinates":[-8.16667,40.96667],"type":"Point"}
}