{
  "type": "Feature",
  "properties": {
    "gn:admin1_code":"2.0",
    "gn:admin2_code":"0104",
    "gn:admin3_code":"10402.0",
    "gn:asciiname":"Cortegada",
    "gn:country_code":"PT",
    "gn:dem":347,
    "gn:feature_class":"P",
    "gn:feature_code":"PPL",
    "gn:name":"Cortegada",
    "gn:population":0,
    "gn:timezone":"Europe/Lisbon",
    "iso:country":"PT",
    "name:ara_x_preferred":[
        "\u0643\u0648\u0631\u062a\u064a\u063a\u0627\u062f\u0627"
    ],
    "name:cat_x_preferred":[
        "Cortegada"
    ],
    "name:ceb_x_preferred":[
        "Cortegada"
    ],
    "name:eus_x_preferred":[
        "Cortegada"
    ],
    "name:fra_x_preferred":[
        "Cortegada"
    ],
    "name:glg_x_preferred":[
        "Cortegada"
    ],
    "name:hun_x_preferred":[
        "Cortegada"
    ],
    "name:ita_x_preferred":[
        "Cortegada"
    ],
    "name:jpn_x_preferred":[
        "\u30b3\u30eb\u30c6\u30ac\u30fc\u30c0"
    ],
    "name:kaz_x_preferred":[
        "\u041a\u043e\u0440\u0442\u0435\u0433\u0430\u0434\u0430"
    ],
    "name:lmo_x_preferred":[
        "Cortegada"
    ],
    "name:msa_x_preferred":[
        "Cortegada"
    ],
    "name:nld_x_preferred":[
        "Cortegada"
    ],
    "name:oci_x_preferred":[
        "Cortegada"
    ],
    "name:pol_x_preferred":[
        "Cortegada"
    ],
    "name:por_x_preferred":[
        "Cortegada"
    ],
    "name:rus_x_preferred":[
        "\u041a\u043e\u0440\u0442\u0435\u0433\u0430\u0434\u0430"
    ],
    "name:sco_x_preferred":[
        "Cortegada"
    ],
    "name:spa_x_preferred":[
        "Cortegada"
    ],
    "name:swe_x_preferred":[
        "Cortegada"
    ],
    "name:tur_x_preferred":[
        "Cortegada"
    ],
    "name:ukr_x_preferred":[
        "\u041a\u043e\u0440\u0442\u0435\u0433\u0430\u0434\u0430"
    ],
    "name:uzb_x_preferred":[
        "Cortegada"
    ],
    "name:vie_x_preferred":[
        "Cortegada"
    ],
    "name:war_x_preferred":[
        "Cortegada"
    ],
    "name:zho_x_preferred":[
        "\u79d1\u5c14\u7279\u52a0\u8fbe"
    ],
    "wof:name":"Cortegada",
    "wof:placetype":"locality"
},
  "geometry": {"coordinates":[-8.16667,40.96667],"type":"Point"}
}