{
  "type": "Feature",
  "properties": {
    "gn:admin1_code":"13",
    "gn:admin2_code":"1013",
    "gn:admin3_code":"101301.0",
    "gn:asciiname":"Graca",
    "gn:country_code":"PT",
    "gn:dem":337,
    "gn:feature_class":"P",
    "gn:feature_code":"PPL",
    "gn:name":"Gra\u00e7a",
    "gn:population":0,
    "gn:timezone":"Europe/Lisbon",
    "iso:country":"PT",
    "wof:name":"Graca",
    "wof:placetype":"locality"
},
  "geometry": {"coordinates":[-8.22329,39.89361],"type":"Point"}
}