{
  "type": "Feature",
  "properties": {
    "gn:admin1_code":"22.0",
    "gn:admin2_code":"1803",
    "gn:admin3_code":"180304.0",
    "gn:asciiname":"Bracos de La",
    "gn:country_code":"PT",
    "gn:dem":607,
    "gn:feature_class":"P",
    "gn:feature_code":"PPL",
    "gn:name":"Bra\u00e7os de L\u00e1",
    "gn:population":0,
    "gn:timezone":"Europe/Lisbon",
    "iso:country":"PT",
    "wof:name":"Bracos de La",
    "wof:placetype":"locality"
},
  "geometry": {"coordinates":[-7.93324,40.90723],"type":"Point"}
}