{
  "type": "Feature",
  "properties": {
    "gn:admin1_code":"19",
    "gn:asciiname":"Vale da Isca",
    "gn:country_code":"PT",
    "gn:dem":229,
    "gn:feature_class":"P",
    "gn:feature_code":"PPL",
    "gn:name":"Vale da Isca",
    "gn:population":0,
    "gn:timezone":"Europe/Lisbon",
    "iso:country":"PT",
    "wof:name":"Vale da Isca",
    "wof:placetype":"locality"
},
  "geometry": {"coordinates":[-8.45799,37.66449],"type":"Point"}
}