{
  "type": "Feature",
  "properties": {
    "gn:admin1_code":"21.0",
    "gn:admin2_code":"1713",
    "gn:admin3_code":"171315.0",
    "gn:asciiname":"Eiriz",
    "gn:country_code":"PT",
    "gn:dem":658,
    "gn:feature_class":"P",
    "gn:feature_code":"PPL",
    "gn:name":"Eiriz",
    "gn:population":0,
    "gn:timezone":"Europe/Lisbon",
    "iso:country":"PT",
    "wof:name":"Eiriz",
    "wof:placetype":"locality"
},
  "geometry": {"coordinates":[-7.58049,41.55157],"type":"Point"}
}