{
  "type": "Feature",
  "properties": {
    "iso:country":"PT",
    "qs_pg:aaroncc":"PT",
    "qs_pg:name":"Braga-S\u00e3o V\u00edtor",
    "qs_pg:name_adm0":"Portugal",
    "qs_pg:name_adm1":"Braga",
    "qs_pg:photos":22,
    "qs_pg:photos_1k":4,
    "qs_pg:photos_9k":1,
    "qs_pg:photos_9r":1,
    "qs_pg:photos_all":22,
    "qs_pg:photos_sr":1,
    "qs_pg:pop_sr":0,
    "qs_pg:qs_pg_placetype":"locality",
    "qs_pg:qs_pg_placetype_gp":"Town",
    "qs_pg:woe_adm0":23424925,
    "woe:adm0_id":23424925,
    "woe:name_adm0":"Portugal",
    "woe:name_adm1":"Braga",
    "woe:placetype":"Town",
    "wof:name":"Braga-S\u00e3o V\u00edtor",
    "wof:placetype":"locality"
},
  "geometry": {"coordinates":[-8.4097275,41.554581],"type":"Point"}
}