{
  "type": "Feature",
  "properties": {
    "gn:admin1_code":"4.0",
    "gn:admin2_code":"0308",
    "gn:admin3_code":"30806.0",
    "gn:asciiname":"Baiona",
    "gn:country_code":"PT",
    "gn:dem":140,
    "gn:feature_class":"P",
    "gn:feature_code":"PPLL",
    "gn:name":"Baiona",
    "gn:population":0,
    "gn:timezone":"Europe/Lisbon",
    "iso:country":"PT",
    "name:bre_x_preferred":[
        "Baiona"
    ],
    "name:ceb_x_preferred":[
        "Baiona"
    ],
    "name:eus_x_preferred":[
        "Baiona"
    ],
    "name:glg_x_preferred":[
        "Baiona"
    ],
    "name:ita_x_preferred":[
        "Baiona"
    ],
    "name:lat_x_preferred":[
        "Baiona"
    ],
    "name:por_x_preferred":[
        "Baiona"
    ],
    "name:spa_x_preferred":[
        "Baiona"
    ],
    "name:swe_x_preferred":[
        "Baiona"
    ],
    "wof:name":"Baiona",
    "wof:placetype":"locality"
},
  "geometry": {"coordinates":[-8.33407,41.49927],"type":"Point"}
}