{
  "type": "Feature",
  "properties": {
    "gn:admin1_code":"09",
    "gn:admin2_code":"0808",
    "gn:admin3_code":"80802.0",
    "gn:asciiname":"Julia",
    "gn:country_code":"PT",
    "gn:dem":220,
    "gn:feature_class":"P",
    "gn:feature_code":"PPL",
    "gn:name":"J\u00falia",
    "gn:population":0,
    "gn:timezone":"Europe/Lisbon",
    "iso:country":"PT",
    "wof:name":"Julia",
    "wof:placetype":"locality"
},
  "geometry": {"coordinates":[-8.16332,37.23438],"type":"Point"}
}