{
  "type": "Feature",
  "properties": {
    "gn:admin1_code":"22",
    "gn:admin2_code":"1823",
    "gn:admin3_code":"182323.0",
    "gn:asciiname":"Travassos de Baixo",
    "gn:country_code":"PT",
    "gn:dem":465,
    "gn:feature_class":"P",
    "gn:feature_code":"PPL",
    "gn:name":"Travass\u00f3s de Baixo",
    "gn:population":0,
    "gn:timezone":"Europe/Lisbon",
    "iso:country":"PT",
    "wof:name":"Travassos de Baixo",
    "wof:placetype":"locality"
},
  "geometry": {"coordinates":[-7.88455,40.67948],"type":"Point"}
}