{
  "type": "Feature",
  "properties": {
    "gn:admin1_code":"08",
    "gn:admin2_code":"0707",
    "gn:admin3_code":"70704.0",
    "gn:asciiname":"Monte das Casas Velhas",
    "gn:country_code":"PT",
    "gn:dem":170,
    "gn:feature_class":"P",
    "gn:feature_code":"PPL",
    "gn:name":"Monte das Casas Velhas",
    "gn:population":0,
    "gn:timezone":"Europe/Lisbon",
    "iso:country":"PT",
    "wof:name":"Monte das Casas Velhas",
    "wof:placetype":"locality"
},
  "geometry": {"coordinates":[-7.96233,38.86874],"type":"Point"}
}