{
  "type": "Feature",
  "properties": {
    "gn:admin1_code":"17.0",
    "gn:admin2_code":"1317",
    "gn:admin3_code":"131724.0",
    "gn:asciiname":"Cadavao",
    "gn:country_code":"PT",
    "gn:dem":66,
    "gn:feature_class":"P",
    "gn:feature_code":"PPL",
    "gn:name":"Cadav\u00e3o",
    "gn:population":0,
    "gn:timezone":"Europe/Lisbon",
    "iso:country":"PT",
    "wof:name":"Cadavao",
    "wof:placetype":"locality"
},
  "geometry": {"coordinates":[-8.61679,41.08553],"type":"Point"}
}