{
  "type": "Feature",
  "properties": {
    "gn:admin1_code":"18",
    "gn:admin2_code":"1401",
    "gn:admin3_code":"140102.0",
    "gn:asciiname":"Hortas",
    "gn:country_code":"PT",
    "gn:dem":32,
    "gn:feature_class":"P",
    "gn:feature_code":"PPL",
    "gn:name":"Hortas",
    "gn:population":0,
    "gn:timezone":"Europe/Lisbon",
    "iso:country":"PT",
    "wof:name":"Hortas",
    "wof:placetype":"locality"
},
  "geometry": {"coordinates":[-8.18333,39.46667],"type":"Point"}
}