{
  "type": "Feature",
  "properties": {
    "gn:admin1_code":"14",
    "gn:admin2_code":"1111",
    "gn:admin3_code":"111112.0",
    "gn:asciiname":"Palacio do Ramalhao",
    "gn:country_code":"PT",
    "gn:dem":207,
    "gn:feature_class":"P",
    "gn:feature_code":"PPL",
    "gn:name":"Pal\u00e1cio do Ramalh\u00e3o",
    "gn:population":0,
    "gn:timezone":"Europe/Lisbon",
    "iso:country":"PT",
    "wof:name":"Palacio do Ramalhao",
    "wof:placetype":"locality"
},
  "geometry": {"coordinates":[-9.36667,38.78333],"type":"Point"}
}