{
  "type": "Feature",
  "properties": {
    "gn:admin1_code":"4.0",
    "gn:admin2_code":"0310",
    "gn:admin3_code":"31007.0",
    "gn:asciiname":"Bergaco",
    "gn:country_code":"PT",
    "gn:dem":720,
    "gn:feature_class":"P",
    "gn:feature_code":"PPL",
    "gn:name":"Berga\u00e7o",
    "gn:population":0,
    "gn:timezone":"Europe/Lisbon",
    "iso:country":"PT",
    "wof:name":"Bergaco",
    "wof:placetype":"locality"
},
  "geometry": {"coordinates":[-8.29039,41.76357],"type":"Point"}
}