{
  "type": "Feature",
  "properties": {
    "gn:admin1_code":"21.0",
    "gn:admin2_code":"1710",
    "gn:admin3_code":"171003.0",
    "gn:asciiname":"Gouvaes",
    "gn:country_code":"PT",
    "gn:dem":512,
    "gn:feature_class":"P",
    "gn:feature_code":"PPL",
    "gn:name":"Gouv\u00e3es",
    "gn:population":0,
    "gn:timezone":"Europe/Lisbon",
    "iso:country":"PT",
    "wof:name":"Gouvaes",
    "wof:placetype":"locality"
},
  "geometry": {"coordinates":[-7.57435,41.19709],"type":"Point"}
}