{
  "type": "Feature",
  "properties": {
    "iso:country":"PT",
    "qs_pg:aaroncc":"PT",
    "qs_pg:name":"Herdade da Mitra",
    "qs_pg:name_adm0":"Portugal",
    "qs_pg:name_adm1":"Evora",
    "qs_pg:photos":468,
    "qs_pg:photos_1k":95,
    "qs_pg:photos_9k":2,
    "qs_pg:photos_9r":5,
    "qs_pg:photos_all":468,
    "qs_pg:photos_sr":7,
    "qs_pg:pop_sr":0,
    "qs_pg:qs_pg_placetype":"locality",
    "qs_pg:qs_pg_placetype_gp":"Town",
    "qs_pg:woe_adm0":23424925,
    "woe:adm0_id":23424925,
    "woe:name_adm0":"Portugal",
    "woe:name_adm1":"Evora",
    "woe:placetype":"Town",
    "wof:name":"Herdade da Mitra",
    "wof:placetype":"locality"
},
  "geometry": {"coordinates":[-8.012294,38.535544],"type":"Point"}
}