{
  "type": "Feature",
  "properties": {
    "gn:gn_country":"PT",
    "gn:gn_fcode":"PPL",
    "gn:gn_pop":0,
    "iso:country":"PT",
    "qs_pg:aaroncc":"PT",
    "qs_pg:gn_country":"PT",
    "qs_pg:gn_fcode":"PPL",
    "qs_pg:gn_pop":0,
    "qs_pg:name":"Valongo",
    "qs_pg:name_adm0":"Portugal",
    "qs_pg:name_adm1":"Lisboa",
    "qs_pg:photos":187,
    "qs_pg:photos_1k":38,
    "qs_pg:photos_9k":1,
    "qs_pg:photos_9r":4,
    "qs_pg:photos_all":187,
    "qs_pg:photos_sr":4,
    "qs_pg:pop_sr":0,
    "qs_pg:qs_pg_placetype":"locality",
    "qs_pg:qs_pg_placetype_gp":"Town",
    "qs_pg:woe_adm0":23424925,
    "woe:adm0_id":23424925,
    "woe:name_adm0":"Portugal",
    "woe:name_adm1":"Lisboa",
    "woe:placetype":"Town",
    "wof:name":"Valongo",
    "wof:placetype":"locality"
},
  "geometry": {"coordinates":[-9.40804,39.02701],"type":"Point"}
}