{
  "type": "Feature",
  "properties": {
    "gn:gn_country":"PT",
    "gn:gn_fcode":"PPL",
    "gn:gn_pop":0,
    "iso:country":"PT",
    "name:ara_x_preferred":[
        "\u0641\u0627\u0644\u0648\u0646\u063a\u0648"
    ],
    "name:cat_x_preferred":[
        "Valongo"
    ],
    "name:ceb_x_preferred":[
        "Valongo"
    ],
    "name:deu_x_preferred":[
        "Valongo"
    ],
    "name:eus_x_preferred":[
        "Valongo"
    ],
    "name:fra_x_preferred":[
        "Valongo"
    ],
    "name:glg_x_preferred":[
        "Valongo"
    ],
    "name:hye_x_preferred":[
        "\u054e\u0561\u056c\u0578\u0576\u0563\u0578\u0582"
    ],
    "name:ita_x_preferred":[
        "Valongo"
    ],
    "name:kat_x_preferred":[
        "\u10d5\u10d0\u10da\u10dd\u10dc\u10d2\u10e3"
    ],
    "name:kaz_x_preferred":[
        "\u0412\u0430\u043b\u043e\u043d\u0433\u0443"
    ],
    "name:mzn_x_preferred":[
        "\u0648\u0627\u0644\u0648\u0646\u06af\u0648"
    ],
    "name:nld_x_preferred":[
        "Valongo"
    ],
    "name:pol_x_preferred":[
        "Valongo"
    ],
    "name:por_x_preferred":[
        "Valongo"
    ],
    "name:ron_x_preferred":[
        "Valongo"
    ],
    "name:rus_x_preferred":[
        "\u0412\u0430\u043b\u043e\u043d\u0433\u0443"
    ],
    "name:sco_x_preferred":[
        "Valongo"
    ],
    "name:spa_x_preferred":[
        "Valongo"
    ],
    "name:tur_x_preferred":[
        "Valongo"
    ],
    "name:ukr_x_preferred":[
        "\u0412\u0430\u043b\u043e\u043d\u0433\u0443"
    ],
    "name:vie_x_preferred":[
        "Valongo"
    ],
    "name:vol_x_preferred":[
        "Valongo"
    ],
    "name:war_x_preferred":[
        "Valongo Municipality"
    ],
    "name:zho_x_preferred":[
        "\u74e6\u9686\u53e4"
    ],
    "qs_pg:aaroncc":"PT",
    "qs_pg:gn_country":"PT",
    "qs_pg:gn_fcode":"PPL",
    "qs_pg:gn_pop":0,
    "qs_pg:name":"Valongo",
    "qs_pg:name_adm0":"Portugal",
    "qs_pg:name_adm1":"Lisboa",
    "qs_pg:photos":187,
    "qs_pg:photos_1k":38,
    "qs_pg:photos_9k":1,
    "qs_pg:photos_9r":4,
    "qs_pg:photos_all":187,
    "qs_pg:photos_sr":4,
    "qs_pg:pop_sr":0,
    "qs_pg:qs_pg_placetype":"locality",
    "qs_pg:qs_pg_placetype_gp":"Town",
    "qs_pg:woe_adm0":23424925,
    "woe:adm0_id":23424925,
    "woe:name_adm0":"Portugal",
    "woe:name_adm1":"Lisboa",
    "woe:placetype":"Town",
    "wof:name":"Valongo",
    "wof:placetype":"locality"
},
  "geometry": {"coordinates":[-9.40804,39.02701],"type":"Point"}
}