{
  "type": "Feature",
  "properties": {
    "gn:admin1_code":"22",
    "gn:admin2_code":"1824",
    "gn:admin3_code":"182402.0",
    "gn:asciiname":"Tourelhe",
    "gn:country_code":"PT",
    "gn:dem":500,
    "gn:feature_class":"P",
    "gn:feature_code":"PPL",
    "gn:name":"Tourelhe",
    "gn:population":0,
    "gn:timezone":"Europe/Lisbon",
    "iso:country":"PT",
    "wof:name":"Tourelhe",
    "wof:placetype":"locality"
},
  "geometry": {"coordinates":[-8.14993,40.68265],"type":"Point"}
}