{
  "type": "Feature",
  "properties": {
    "gn:admin1_code":"22.0",
    "gn:admin2_code":"1821",
    "gn:admin3_code":"182101.0",
    "gn:asciiname":"Barreiro de Besteiros",
    "gn:country_code":"PT",
    "gn:dem":222,
    "gn:feature_class":"P",
    "gn:feature_code":"PPL",
    "gn:name":"Barreiro de Besteiros",
    "gn:population":0,
    "gn:timezone":"Europe/Lisbon",
    "iso:country":"PT",
    "wof:name":"Barreiro de Besteiros",
    "wof:placetype":"locality"
},
  "geometry": {"coordinates":[-8.18021,40.51109],"type":"Point"}
}