{
  "type": "Feature",
  "properties": {
    "gn:admin1_code":"22",
    "gn:admin2_code":"1823",
    "gn:admin3_code":"182310.0",
    "gn:asciiname":"Zonho",
    "gn:country_code":"PT",
    "gn:dem":716,
    "gn:feature_class":"P",
    "gn:feature_code":"PPL",
    "gn:name":"Zonho",
    "gn:population":0,
    "gn:timezone":"Europe/Lisbon",
    "iso:country":"PT",
    "wof:name":"Zonho",
    "wof:placetype":"locality"
},
  "geometry": {"coordinates":[-7.81859,40.81675],"type":"Point"}
}