{
  "type": "Feature",
  "properties": {
    "gn:country":"PT",
    "gn:fcode":"PPL",
    "gn:population":0,
    "iso:country":"PT",
    "name:ceb_x_preferred":[
        "Venda Nova"
    ],
    "name:deu_x_preferred":[
        "Venda Nova"
    ],
    "name:fra_x_preferred":[
        "Venda Nova"
    ],
    "name:nld_x_preferred":[
        "Venda Nova"
    ],
    "name:por_x_preferred":[
        "Venda Nova"
    ],
    "name:rus_x_preferred":[
        "\u0412\u0435\u043d\u0434\u0430-\u041d\u043e\u0432\u0430"
    ],
    "qs_pg:aaroncc":"PT",
    "qs_pg:gn_country":"PT",
    "qs_pg:gn_fcode":"PPL",
    "qs_pg:gn_pop":0,
    "qs_pg:name":"Venda Nova",
    "qs_pg:name_adm0":"Portugal",
    "qs_pg:name_adm1":"Vila Real",
    "qs_pg:photos":40,
    "qs_pg:photos_1k":8,
    "qs_pg:photos_9k":1,
    "qs_pg:photos_9r":2,
    "qs_pg:photos_all":40,
    "qs_pg:photos_sr":2,
    "qs_pg:pop_sr":4,
    "qs_pg:qs_pg_placetype":"locality",
    "qs_pg:qs_pg_placetype_gp":"Town",
    "qs_pg:woe_adm0":23424925,
    "woe:adm0_id":23424925,
    "woe:name_adm0":"Portugal",
    "woe:name_adm1":"Vila Real",
    "woe:placetype":"Town",
    "wof:name":"Venda Nova",
    "wof:placetype":"locality"
},
  "geometry": {"coordinates":[-7.9594,41.67282],"type":"Point"}
}