{
  "type": "Feature",
  "properties": {
    "gn:gn_country":"PT",
    "gn:gn_fcode":"ADM3",
    "gn:gn_pop":1494,
    "gn:population":1494,
    "iso:country":"PT",
    "qs_pg:aaroncc":"PT",
    "qs_pg:gn_country":"PT",
    "qs_pg:gn_fcode":"ADM3",
    "qs_pg:gn_pop":1494,
    "qs_pg:name":"Longomel",
    "qs_pg:photos_9r":0,
    "qs_pg:photos_sr":0,
    "qs_pg:pop_sr":3,
    "qs_pg:qs_pg_placetype":"localadmin",
    "wof:name":"Longomel",
    "wof:placetype":"localadmin",
    "wof:population":1494
},
  "geometry": {"coordinates":[-7.99252,39.33715],"type":"Point"}
}