{
  "type": "Feature",
  "properties": {
    "gn:admin1_code":"16",
    "gn:admin2_code":"1209",
    "gn:admin3_code":"120902.0",
    "gn:asciiname":"Arriacha Fundeira",
    "gn:country_code":"PT",
    "gn:dem":193,
    "gn:feature_class":"P",
    "gn:feature_code":"PPL",
    "gn:name":"Arriacha Fundeira",
    "gn:population":0,
    "gn:timezone":"Europe/Lisbon",
    "iso:country":"PT",
    "wof:name":"Arriacha Fundeira",
    "wof:placetype":"locality"
},
  "geometry": {"coordinates":[-7.95839,39.50961],"type":"Point"}
}