{
  "type": "Feature",
  "properties": {
    "gn:admin1_code":"04",
    "gn:admin2_code":"0303",
    "gn:admin3_code":"30325.0",
    "gn:asciiname":"Sobrado",
    "gn:country_code":"PT",
    "gn:dem":31,
    "gn:feature_class":"P",
    "gn:feature_code":"PPL",
    "gn:name":"Sobrado",
    "gn:population":0,
    "gn:timezone":"Europe/Lisbon",
    "iso:country":"PT",
    "wof:name":"Sobrado",
    "wof:placetype":"locality"
},
  "geometry": {"coordinates":[-8.47394,41.57635],"type":"Point"}
}