{
  "type": "Feature",
  "properties": {
    "gn:admin1_code":"20.0",
    "gn:admin2_code":"1604",
    "gn:admin3_code":"160423.0",
    "gn:asciiname":"Pereira",
    "gn:country_code":"PT",
    "gn:dem":186,
    "gn:feature_class":"P",
    "gn:feature_code":"PPL",
    "gn:name":"Pereira",
    "gn:population":0,
    "gn:timezone":"Europe/Lisbon",
    "iso:country":"PT",
    "wof:name":"Pereira",
    "wof:placetype":"locality"
},
  "geometry": {"coordinates":[-8.48287,41.98803],"type":"Point"}
}