{
  "type": "Feature",
  "properties": {
    "gn:gn_country":"PT",
    "iso:country":"PT",
    "qs_pg:aaroncc":"PT",
    "qs_pg:gn_country":"PT",
    "qs_pg:name":"Banda de Al\u00e9m",
    "qs_pg:name_adm0":"Portugal",
    "qs_pg:name_adm1":"Madeira",
    "qs_pg:photos":42,
    "qs_pg:photos_1k":9,
    "qs_pg:photos_9k":1,
    "qs_pg:photos_9r":2,
    "qs_pg:photos_all":42,
    "qs_pg:photos_sr":2,
    "qs_pg:pop_sr":0,
    "qs_pg:qs_pg_placetype":"locality",
    "qs_pg:qs_pg_placetype_gp":"Town",
    "qs_pg:woe_adm0":23424925,
    "woe:adm0_id":23424925,
    "woe:name_adm0":"Portugal",
    "woe:name_adm1":"Madeira",
    "woe:placetype":"Town",
    "wof:name":"Banda de Al\u00e9m",
    "wof:placetype":"locality"
},
  "geometry": {"coordinates":[-17.137126,32.7014105],"type":"Point"}
}