{
  "type": "Feature",
  "properties": {
    "gn:admin1_code":"05",
    "gn:admin2_code":"0402",
    "gn:admin3_code":"40211.0",
    "gn:asciiname":"Vila Mea",
    "gn:country_code":"PT",
    "gn:dem":871,
    "gn:feature_class":"P",
    "gn:feature_code":"PPL",
    "gn:name":"Vila Me\u00e3",
    "gn:population":0,
    "gn:timezone":"Europe/Lisbon",
    "iso:country":"PT",
    "wof:name":"Vila Mea",
    "wof:placetype":"locality"
},
  "geometry": {"coordinates":[-6.59015,41.83633],"type":"Point"}
}