{
  "type": "Feature",
  "properties": {
    "gn:admin1_code":"16",
    "gn:admin2_code":"1203",
    "gn:admin3_code":"120306.0",
    "gn:asciiname":"Monte Padrao",
    "gn:country_code":"PT",
    "gn:dem":188,
    "gn:feature_class":"P",
    "gn:feature_code":"PPL",
    "gn:name":"Monte Padr\u00e3o",
    "gn:population":0,
    "gn:timezone":"Europe/Lisbon",
    "iso:country":"PT",
    "wof:name":"Monte Padrao",
    "wof:placetype":"locality"
},
  "geometry": {"coordinates":[-7.7702,39.06809000000001],"type":"Point"}
}