{
  "type": "Feature",
  "properties": {
    "gn:admin1_code":"16",
    "gn:admin2_code":"1212",
    "gn:admin3_code":"121205.0",
    "gn:asciiname":"Montalvao",
    "gn:country_code":"PT",
    "gn:dem":337,
    "gn:feature_class":"P",
    "gn:feature_code":"PPL",
    "gn:name":"Montalv\u00e3o",
    "gn:population":0,
    "gn:timezone":"Europe/Lisbon",
    "iso:country":"PT",
    "wof:name":"Montalvao",
    "wof:placetype":"locality"
},
  "geometry": {"coordinates":[-7.52782,39.59564],"type":"Point"}
}