{
  "type": "Feature",
  "properties": {
    "gn:admin1_code":"14",
    "gn:admin2_code":"1112",
    "gn:admin3_code":"111202.0",
    "gn:asciiname":"Boco",
    "gn:country_code":"PT",
    "gn:dem":248,
    "gn:feature_class":"P",
    "gn:feature_code":"PPL",
    "gn:name":"Boco",
    "gn:population":0,
    "gn:timezone":"Europe/Lisbon",
    "iso:country":"PT",
    "name:deu_x_preferred":[
        "Boco"
    ],
    "name:spa_x_preferred":[
        "Boco"
    ],
    "wof:name":"Boco",
    "wof:placetype":"locality"
},
  "geometry": {"coordinates":[-9.17386,38.96124],"type":"Point"}
}