{
  "type": "Feature",
  "properties": {
    "gn:admin1_code":"08",
    "gn:admin2_code":"0705",
    "gn:admin3_code":"70504.0",
    "gn:asciiname":"Barrocal",
    "gn:country_code":"PT",
    "gn:dem":244,
    "gn:feature_class":"P",
    "gn:feature_code":"PPL",
    "gn:name":"Barrocal",
    "gn:population":0,
    "gn:timezone":"Europe/Lisbon",
    "iso:country":"PT",
    "wof:name":"Barrocal",
    "wof:placetype":"locality"
},
  "geometry": {"coordinates":[-8.00276,38.51082],"type":"Point"}
}