{
  "type": "Feature",
  "properties": {
    "gn:admin1_code":"09",
    "gn:admin2_code":"0805",
    "gn:admin3_code":"80501.0",
    "gn:asciiname":"Pe do Outeiro",
    "gn:country_code":"PT",
    "gn:dem":90,
    "gn:feature_class":"P",
    "gn:feature_code":"PPL",
    "gn:name":"P\u00e9 do Outeiro",
    "gn:population":0,
    "gn:timezone":"Europe/Lisbon",
    "iso:country":"PT",
    "wof:name":"Pe do Outeiro",
    "wof:placetype":"locality"
},
  "geometry": {"coordinates":[-7.9044,37.06654],"type":"Point"}
}