{
  "type": "Feature",
  "properties": {
    "gn:admin1_code":"03",
    "gn:admin2_code":"0203",
    "gn:admin3_code":"20302.0",
    "gn:asciiname":"Monte do Rio Seco",
    "gn:country_code":"PT",
    "gn:dem":116,
    "gn:feature_class":"P",
    "gn:feature_code":"PPL",
    "gn:name":"Monte do Rio Seco",
    "gn:population":0,
    "gn:timezone":"Europe/Lisbon",
    "iso:country":"PT",
    "wof:name":"Monte do Rio Seco",
    "wof:placetype":"locality"
},
  "geometry": {"coordinates":[-8.09591,38.24244],"type":"Point"}
}