{
  "type": "Feature",
  "properties": {
    "gn:admin1_code":"7.0",
    "gn:admin2_code":"0607",
    "gn:admin3_code":"60705.0",
    "gn:asciiname":"Franco de Baixo",
    "gn:country_code":"PT",
    "gn:dem":628,
    "gn:feature_class":"P",
    "gn:feature_code":"PPL",
    "gn:name":"Franco de Baixo",
    "gn:population":0,
    "gn:timezone":"Europe/Lisbon",
    "iso:country":"PT",
    "wof:name":"Franco de Baixo",
    "wof:placetype":"locality"
},
  "geometry": {"coordinates":[-8.18732,40.11098],"type":"Point"}
}