{
  "type": "Feature",
  "properties": {
    "gn:admin1_code":"17.0",
    "gn:admin2_code":"1306",
    "gn:admin3_code":"130617.0",
    "gn:asciiname":"Chapeleiro",
    "gn:country_code":"PT",
    "gn:dem":107,
    "gn:feature_class":"P",
    "gn:feature_code":"PPL",
    "gn:name":"Chapeleiro",
    "gn:population":0,
    "gn:timezone":"Europe/Lisbon",
    "iso:country":"PT",
    "wof:name":"Chapeleiro",
    "wof:placetype":"locality"
},
  "geometry": {"coordinates":[-8.57534,41.18059],"type":"Point"}
}