{
  "type": "Feature",
  "properties": {
    "gn:admin1_code":"14",
    "gn:admin2_code":"1109",
    "gn:admin3_code":"110909.0",
    "gn:asciiname":"Paz",
    "gn:country_code":"PT",
    "gn:dem":203,
    "gn:feature_class":"P",
    "gn:feature_code":"PPL",
    "gn:name":"Paz",
    "gn:population":0,
    "gn:timezone":"Europe/Lisbon",
    "iso:country":"PT",
    "name:aze_x_preferred":[
        "Paz"
    ],
    "name:bre_x_preferred":[
        "Paz"
    ],
    "name:ceb_x_preferred":[
        "Paz"
    ],
    "name:ces_x_preferred":[
        "Paz"
    ],
    "name:fin_x_preferred":[
        "Paz"
    ],
    "name:fra_x_preferred":[
        "Paz"
    ],
    "name:glg_x_preferred":[
        "Paz"
    ],
    "name:heb_x_preferred":[
        "\u05e4\u05d6"
    ],
    "name:hun_x_preferred":[
        "Paz"
    ],
    "name:lit_x_preferred":[
        "Pazas"
    ],
    "name:por_x_preferred":[
        "Paz"
    ],
    "name:rus_x_preferred":[
        "\u041f\u0430\u0437"
    ],
    "name:spa_x_preferred":[
        "Paz"
    ],
    "name:swe_x_preferred":[
        "Paz"
    ],
    "name:ukr_x_preferred":[
        "\u041f\u0430\u0437"
    ],
    "wof:name":"Paz",
    "wof:placetype":"locality"
},
  "geometry": {"coordinates":[-9.32825,38.94862],"type":"Point"}
}