{
  "type": "Feature",
  "properties": {
    "gn:admin1_code":"14",
    "gn:admin2_code":"1109",
    "gn:admin3_code":"110909.0",
    "gn:asciiname":"Paz",
    "gn:country_code":"PT",
    "gn:dem":203,
    "gn:feature_class":"P",
    "gn:feature_code":"PPL",
    "gn:name":"Paz",
    "gn:population":0,
    "gn:timezone":"Europe/Lisbon",
    "iso:country":"PT",
    "wof:name":"Paz",
    "wof:placetype":"locality"
},
  "geometry": {"coordinates":[-9.32825,38.94862],"type":"Point"}
}