{
  "type": "Feature",
  "properties": {
    "gn:admin1_code":"2.0",
    "gn:admin2_code":"0119",
    "gn:admin3_code":"11905.0",
    "gn:asciiname":"Folhense",
    "gn:country_code":"PT",
    "gn:dem":768,
    "gn:feature_class":"P",
    "gn:feature_code":"PPL",
    "gn:name":"Folhense",
    "gn:population":0,
    "gn:timezone":"Europe/Lisbon",
    "iso:country":"PT",
    "wof:name":"Folhense",
    "wof:placetype":"locality"
},
  "geometry": {"coordinates":[-8.34548,40.78905],"type":"Point"}
}