{
  "type": "Feature",
  "properties": {
    "gn:admin1_code":"7.0",
    "gn:admin2_code":"0601",
    "gn:admin3_code":"60105.0",
    "gn:asciiname":"Celavisa",
    "gn:country_code":"PT",
    "gn:dem":266,
    "gn:feature_class":"P",
    "gn:feature_code":"PPL",
    "gn:name":"Celavisa",
    "gn:population":0,
    "gn:timezone":"Europe/Lisbon",
    "iso:country":"PT",
    "wof:name":"Celavisa",
    "wof:placetype":"locality"
},
  "geometry": {"coordinates":[-8.05654,40.18988],"type":"Point"}
}