{
  "type": "Feature",
  "properties": {
    "iso:country":"PT",
    "name:pol_x_preferred":[
        "Po\u00e7o de Bispo"
    ],
    "wof:name":"Poco de Bispo",
    "wof:placetype":"neighbourhood"
},
  "geometry": {"coordinates":[-9.10196127347699,38.74550725954846],"type":"Point"}
}