{
  "type": "Feature",
  "properties": {
    "gn:admin1_code":"06",
    "gn:admin2_code":"0502",
    "gn:admin3_code":"50222.0",
    "gn:asciiname":"Tripeiro",
    "gn:country_code":"PT",
    "gn:dem":324,
    "gn:feature_class":"P",
    "gn:feature_code":"PPL",
    "gn:name":"Tripeiro",
    "gn:population":0,
    "gn:timezone":"Europe/Lisbon",
    "iso:country":"PT",
    "wof:name":"Tripeiro",
    "wof:placetype":"locality"
},
  "geometry": {"coordinates":[-7.62453,39.98677],"type":"Point"}
}