{
  "type": "Feature",
  "properties": {
    "gn:admin1_code":"5.0",
    "gn:admin2_code":"0401",
    "gn:admin3_code":"40105.0",
    "gn:asciiname":"Picoes",
    "gn:country_code":"PT",
    "gn:dem":430,
    "gn:feature_class":"P",
    "gn:feature_code":"PPL",
    "gn:name":"Pic\u00f5es",
    "gn:population":0,
    "gn:timezone":"Europe/Lisbon",
    "iso:country":"PT",
    "wof:name":"Picoes",
    "wof:placetype":"locality"
},
  "geometry": {"coordinates":[-6.95001,41.25702],"type":"Point"}
}