{
  "type": "Feature",
  "properties": {
    "gn:admin1_code":"16",
    "gn:admin2_code":"1207",
    "gn:admin3_code":"120705.0",
    "gn:asciiname":"Casa de Cantoneiros",
    "gn:country_code":"PT",
    "gn:dem":253,
    "gn:feature_class":"P",
    "gn:feature_code":"PPL",
    "gn:name":"Casa de Cantoneiros",
    "gn:population":0,
    "gn:timezone":"Europe/Lisbon",
    "iso:country":"PT",
    "wof:name":"Casa de Cantoneiros",
    "wof:placetype":"locality"
},
  "geometry": {"coordinates":[-7.11667,38.95],"type":"Point"}
}