{
  "type": "Feature",
  "properties": {
    "gn:admin1_code":"13",
    "gn:admin2_code":"1009",
    "gn:admin3_code":"100911.0",
    "gn:asciiname":"Vidigal de Baixo",
    "gn:country_code":"PT",
    "gn:dem":66,
    "gn:feature_class":"P",
    "gn:feature_code":"PPL",
    "gn:name":"Vidigal de Baixo",
    "gn:population":0,
    "gn:timezone":"Europe/Lisbon",
    "iso:country":"PT",
    "wof:name":"Vidigal de Baixo",
    "wof:placetype":"locality"
},
  "geometry": {"coordinates":[-8.78333,39.71667],"type":"Point"}
}