{
  "type": "Feature",
  "properties": {
    "gn:admin1_code":"7.0",
    "gn:admin2_code":"0607",
    "gn:admin3_code":"60703.0",
    "gn:asciiname":"Casal Novo",
    "gn:country_code":"PT",
    "gn:dem":530,
    "gn:feature_class":"P",
    "gn:feature_code":"PPL",
    "gn:name":"Casal Novo",
    "gn:population":0,
    "gn:timezone":"Europe/Lisbon",
    "iso:country":"PT",
    "wof:name":"Casal Novo",
    "wof:placetype":"locality"
},
  "geometry": {"coordinates":[-8.23576,40.09236],"type":"Point"}
}