{
  "type": "Feature",
  "properties": {
    "gn:admin1_code":"22.0",
    "gn:admin2_code":"1820",
    "gn:admin3_code":"182007.0",
    "gn:asciiname":"Esporoes",
    "gn:country_code":"PT",
    "gn:dem":567,
    "gn:feature_class":"P",
    "gn:feature_code":"PPL",
    "gn:name":"Espor\u00f5es",
    "gn:population":0,
    "gn:timezone":"Europe/Lisbon",
    "iso:country":"PT",
    "wof:name":"Esporoes",
    "wof:placetype":"locality"
},
  "geometry": {"coordinates":[-7.783,41.0196],"type":"Point"}
}