{
  "type": "Feature",
  "properties": {
    "gn:admin1_code":"04",
    "gn:admin2_code":"0306",
    "gn:admin3_code":"30614.0",
    "gn:asciiname":"Santa Marinha",
    "gn:country_code":"PT",
    "gn:dem":31,
    "gn:feature_class":"P",
    "gn:feature_code":"PPL",
    "gn:name":"Santa Marinha",
    "gn:population":0,
    "gn:timezone":"Europe/Lisbon",
    "iso:country":"PT",
    "wof:name":"Santa Marinha",
    "wof:placetype":"locality"
},
  "geometry": {"coordinates":[-8.70322,41.50041],"type":"Point"}
}