{
  "type": "Feature",
  "properties": {
    "gn:admin1_code":"04",
    "gn:admin2_code":"0306",
    "gn:admin3_code":"30614.0",
    "gn:asciiname":"Santa Marinha",
    "gn:country_code":"PT",
    "gn:dem":31,
    "gn:feature_class":"P",
    "gn:feature_code":"PPL",
    "gn:name":"Santa Marinha",
    "gn:population":0,
    "gn:timezone":"Europe/Lisbon",
    "iso:country":"PT",
    "name:ceb_x_preferred":[
        "Santa Marinha"
    ],
    "name:deu_x_preferred":[
        "Santa Marinha"
    ],
    "name:nld_x_preferred":[
        "Santa Marinha"
    ],
    "name:por_x_preferred":[
        "Santa Marinha"
    ],
    "name:rus_x_preferred":[
        "\u0421\u0430\u043d\u0442\u0430-\u041c\u0430\u0440\u0438\u043d\u044c\u044f"
    ],
    "wof:name":"Santa Marinha",
    "wof:placetype":"locality"
},
  "geometry": {"coordinates":[-8.70322,41.50041],"type":"Point"}
}