{
  "type": "Feature",
  "properties": {
    "gn:admin1_code":"16",
    "gn:admin2_code":"1210",
    "gn:admin3_code":"121001.0",
    "gn:asciiname":"Gamacha",
    "gn:country_code":"PT",
    "gn:dem":375,
    "gn:feature_class":"P",
    "gn:feature_code":"PPL",
    "gn:name":"Gamacha",
    "gn:population":0,
    "gn:timezone":"Europe/Lisbon",
    "iso:country":"PT",
    "wof:name":"Gamacha",
    "wof:placetype":"locality"
},
  "geometry": {"coordinates":[-7.38351,39.44485],"type":"Point"}
}