{
  "type": "Feature",
  "properties": {
    "gn:admin1_code":"11.0",
    "gn:admin2_code":"0910",
    "gn:admin3_code":"91019.0",
    "gn:asciiname":"Pomares",
    "gn:country_code":"PT",
    "gn:dem":731,
    "gn:feature_class":"P",
    "gn:feature_code":"PPL",
    "gn:name":"Pomares",
    "gn:population":0,
    "gn:timezone":"Europe/Lisbon",
    "iso:country":"PT",
    "wof:name":"Pomares",
    "wof:placetype":"locality"
},
  "geometry": {"coordinates":[-7.13868,40.64261],"type":"Point"}
}