{
  "type": "Feature",
  "properties": {
    "gn:admin1_code":"18",
    "gn:admin2_code":"1421",
    "gn:admin3_code":"142114.0",
    "gn:asciiname":"Rezouro",
    "gn:country_code":"PT",
    "gn:dem":223,
    "gn:feature_class":"P",
    "gn:feature_code":"PPL",
    "gn:name":"Rezouro",
    "gn:population":0,
    "gn:timezone":"Europe/Lisbon",
    "iso:country":"PT",
    "wof:name":"Rezouro",
    "wof:placetype":"locality"
},
  "geometry": {"coordinates":[-8.59154,39.75463],"type":"Point"}
}