{
  "type": "Feature",
  "properties": {
    "gn:admin1_code":"22.0",
    "gn:admin2_code":"1803",
    "gn:admin3_code":"180317.0",
    "gn:asciiname":"Pepim",
    "gn:country_code":"PT",
    "gn:dem":595,
    "gn:feature_class":"P",
    "gn:feature_code":"PPL",
    "gn:name":"Pepim",
    "gn:population":0,
    "gn:timezone":"Europe/Lisbon",
    "iso:country":"PT",
    "wof:name":"Pepim",
    "wof:placetype":"locality"
},
  "geometry": {"coordinates":[-7.95899,40.88964],"type":"Point"}
}