{
  "type": "Feature",
  "properties": {
    "gn:admin1_code":"02",
    "gn:admin2_code":"0117",
    "gn:admin3_code":"11709.0",
    "gn:asciiname":"Reguengo",
    "gn:country_code":"PT",
    "gn:dem":538,
    "gn:feature_class":"P",
    "gn:feature_code":"PPL",
    "gn:name":"Reguengo",
    "gn:population":0,
    "gn:timezone":"Europe/Lisbon",
    "iso:country":"PT",
    "name:fra_x_preferred":[
        "Reguengo"
    ],
    "name:glg_x_preferred":[
        "Reguengo"
    ],
    "name:por_x_preferred":[
        "Reguengo"
    ],
    "name:spa_x_preferred":[
        "Reguengo"
    ],
    "wof:name":"Reguengo",
    "wof:placetype":"locality"
},
  "geometry": {"coordinates":[-8.38687,40.78223],"type":"Point"}
}