{
  "type": "Feature",
  "properties": {
    "gn:admin1_code":"14",
    "gn:admin2_code":"1108",
    "gn:admin3_code":"110811.0",
    "gn:asciiname":"Montoito",
    "gn:country_code":"PT",
    "gn:dem":94,
    "gn:feature_class":"P",
    "gn:feature_code":"PPL",
    "gn:name":"Montoito",
    "gn:population":0,
    "gn:timezone":"Europe/Lisbon",
    "iso:country":"PT",
    "wof:name":"Montoito",
    "wof:placetype":"locality"
},
  "geometry": {"coordinates":[-9.3307,39.24315],"type":"Point"}
}