{
  "type": "Feature",
  "properties": {
    "gn:admin1_code":"09",
    "gn:admin2_code":"0802",
    "gn:admin3_code":"80203.0",
    "gn:asciiname":"Corte Serranos",
    "gn:country_code":"PT",
    "gn:dem":337,
    "gn:feature_class":"P",
    "gn:feature_code":"PPL",
    "gn:name":"Corte Serranos",
    "gn:population":0,
    "gn:timezone":"Europe/Lisbon",
    "iso:country":"PT",
    "wof:name":"Corte Serranos",
    "wof:placetype":"locality"
},
  "geometry": {"coordinates":[-7.81512,37.38057],"type":"Point"}
}