{
  "type": "Feature",
  "properties": {
    "gn:admin1_code":"21",
    "gn:admin2_code":"1711",
    "gn:admin3_code":"171108.0",
    "gn:asciiname":"Remostia",
    "gn:country_code":"PT",
    "gn:dem":246,
    "gn:feature_class":"P",
    "gn:feature_code":"PPL",
    "gn:name":"Remostia",
    "gn:population":0,
    "gn:timezone":"Europe/Lisbon",
    "iso:country":"PT",
    "wof:name":"Remostia",
    "wof:placetype":"locality"
},
  "geometry": {"coordinates":[-7.77682,41.17832],"type":"Point"}
}