{
  "type": "Feature",
  "properties": {
    "gn:admin1_code":"14",
    "gn:admin2_code":"1111",
    "gn:admin3_code":"111109.0",
    "gn:asciiname":"Rale",
    "gn:country_code":"PT",
    "gn:dem":143,
    "gn:feature_class":"P",
    "gn:feature_code":"PPL",
    "gn:name":"Rale",
    "gn:population":0,
    "gn:timezone":"Europe/Lisbon",
    "iso:country":"PT",
    "wof:name":"Rale",
    "wof:placetype":"locality"
},
  "geometry": {"coordinates":[-9.36141,38.82691],"type":"Point"}
}