{
  "type": "Feature",
  "properties": {
    "gn:admin1_code":"21.0",
    "gn:admin2_code":"1706",
    "gn:admin3_code":"170604.0",
    "gn:asciiname":"Aldeia Nova de Sao Mateus",
    "gn:country_code":"PT",
    "gn:dem":1030,
    "gn:feature_class":"P",
    "gn:feature_code":"PPL",
    "gn:name":"Aldeia Nova de S\u00e3o Mateus",
    "gn:population":0,
    "gn:timezone":"Europe/Lisbon",
    "iso:country":"PT",
    "wof:name":"Aldeia Nova de Sao Mateus",
    "wof:placetype":"locality"
},
  "geometry": {"coordinates":[-7.69857,41.8053],"type":"Point"}
}