{
  "type": "Feature",
  "properties": {
    "gn:admin1_code":"14",
    "gn:admin2_code":"1101",
    "gn:admin3_code":"110109.0",
    "gn:asciiname":"Aldeia",
    "gn:country_code":"PT",
    "gn:dem":32,
    "gn:feature_class":"P",
    "gn:feature_code":"PPL",
    "gn:name":"Aldeia",
    "gn:population":0,
    "gn:timezone":"Europe/Lisbon",
    "iso:country":"PT",
    "wof:name":"Aldeia",
    "wof:placetype":"locality"
},
  "geometry": {"coordinates":[-8.9722,39.10854000000001],"type":"Point"}
}