{
  "type": "Feature",
  "properties": {
    "gn:country":"PT",
    "gn:fcode":"PPL",
    "gn:population":0,
    "iso:country":"PT",
    "name:ceb_x_preferred":[
        "Santa Clara-A-Velha"
    ],
    "name:deu_x_preferred":[
        "Santa Clara-a-Velha"
    ],
    "name:kaz_x_preferred":[
        "\u0421\u0430\u043d\u0442\u0430-\u041a\u043b\u0430\u0440\u0430-\u0430-\u0412\u0435\u043b\u044c\u044f"
    ],
    "name:nld_x_preferred":[
        "Santa Clara-a-Velha"
    ],
    "name:por_x_preferred":[
        "Santa Clara-a-Velha"
    ],
    "name:rus_x_preferred":[
        "\u0421\u0430\u043d\u0442\u0430-\u041a\u043b\u0430\u0440\u0430-\u0430-\u0412\u0435\u043b\u044c\u044f"
    ],
    "name:spa_x_preferred":[
        "Santa Clara-a-Velha"
    ],
    "name:ukr_x_preferred":[
        "\u0421\u0430\u043d\u0442\u0430-\u041a\u043b\u0430\u0440\u0430-\u0430-\u0412\u0435\u043b\u044f"
    ],
    "name:zho_x_preferred":[
        "\u65e7\u5723\u514b\u62c9\u62c9"
    ],
    "qs_pg:aaroncc":"PT",
    "qs_pg:gn_country":"PT",
    "qs_pg:gn_fcode":"PPL",
    "qs_pg:gn_pop":0,
    "qs_pg:name":"Santa Clara-a-Velha",
    "qs_pg:name_adm0":"Portugal",
    "qs_pg:name_adm1":"Beja",
    "qs_pg:photos":130,
    "qs_pg:photos_1k":26,
    "qs_pg:photos_9k":1,
    "qs_pg:photos_9r":3,
    "qs_pg:photos_all":130,
    "qs_pg:photos_sr":3,
    "qs_pg:pop_sr":0,
    "qs_pg:qs_pg_placetype":"locality",
    "qs_pg:qs_pg_placetype_gp":"Town",
    "qs_pg:woe_adm0":23424925,
    "woe:adm0_id":23424925,
    "woe:name_adm0":"Portugal",
    "woe:name_adm1":"Beja",
    "woe:placetype":"Town",
    "wof:name":"Santa Clara-a-Velha",
    "wof:placetype":"locality"
},
  "geometry": {"coordinates":[-8.47558,37.5166],"type":"Point"}
}