{
  "type": "Feature",
  "properties": {
    "gn:admin1_code":"18",
    "gn:admin2_code":"1409",
    "gn:admin3_code":"140904.0",
    "gn:asciiname":"Maria do Sizo",
    "gn:country_code":"PT",
    "gn:dem":15,
    "gn:feature_class":"P",
    "gn:feature_code":"PPL",
    "gn:name":"Maria do Sizo",
    "gn:population":0,
    "gn:timezone":"Europe/Lisbon",
    "iso:country":"PT",
    "wof:name":"Maria do Sizo",
    "wof:placetype":"locality"
},
  "geometry": {"coordinates":[-8.66512,38.95426],"type":"Point"}
}