{
  "type": "Feature",
  "properties": {
    "gn:country":"PT",
    "gn:fcode":"PPL",
    "gn:population":0,
    "iso:country":"PT",
    "name:deu_x_preferred":[
        "P\u00f3voa de Rio de Moinhos"
    ],
    "name:eng_x_preferred":[
        "P\u00f3voa de Rio de Moinhos"
    ],
    "name:fra_x_preferred":[
        "P\u00f3voa de Rio de Moinhos"
    ],
    "name:kaz_x_preferred":[
        "\u041f\u043e\u0432\u0443\u0430-\u0434\u0435-\u0420\u0438\u0443-\u0434\u0435-\u041c\u043e\u0438\u043d\u044c\u044e\u0448"
    ],
    "name:nld_x_preferred":[
        "P\u00f3voa de Rio de Moinhos"
    ],
    "name:por_x_preferred":[
        "P\u00f3voa de Rio de Moinhos"
    ],
    "name:rus_x_preferred":[
        "\u041f\u043e\u0432\u0443\u0430-\u0434\u0435-\u0420\u0438\u0443-\u0434\u0435-\u041c\u043e\u0438\u043d\u044c\u044e\u0448"
    ],
    "name:spa_x_preferred":[
        "P\u00f3voa de Rio de Moinhos"
    ],
    "qs_pg:aaroncc":"PT",
    "qs_pg:gn_country":"PT",
    "qs_pg:gn_fcode":"PPL",
    "qs_pg:gn_pop":0,
    "qs_pg:name":"P\u00f3voa de Rio de Moinhos",
    "qs_pg:name_adm0":"Portugal",
    "qs_pg:name_adm1":"Castelo Branco",
    "qs_pg:photos":170,
    "qs_pg:photos_1k":34,
    "qs_pg:photos_9k":1,
    "qs_pg:photos_9r":4,
    "qs_pg:photos_all":170,
    "qs_pg:photos_sr":4,
    "qs_pg:pop_sr":0,
    "qs_pg:qs_pg_placetype":"locality",
    "qs_pg:qs_pg_placetype_gp":"Town",
    "qs_pg:woe_adm0":23424925,
    "woe:adm0_id":23424925,
    "woe:name_adm0":"Portugal",
    "woe:name_adm1":"Castelo Branco",
    "woe:placetype":"Town",
    "wof:name":"P\u00f3voa de Rio de Moinhos",
    "wof:placetype":"locality"
},
  "geometry": {"coordinates":[-7.50339,39.94063],"type":"Point"}
}