{
  "type": "Feature",
  "properties": {
    "gn:admin1_code":"14",
    "gn:admin2_code":"1109",
    "gn:admin3_code":"110908.0",
    "gn:asciiname":"Mata Grande",
    "gn:country_code":"PT",
    "gn:dem":123,
    "gn:feature_class":"P",
    "gn:feature_code":"PPL",
    "gn:name":"Mata Grande",
    "gn:population":0,
    "gn:timezone":"Europe/Lisbon",
    "iso:country":"PT",
    "name:ara_x_preferred":[
        "\u0645\u0627\u062a\u0627 \u063a\u0631\u0627\u0646\u062f\u064a"
    ],
    "name:bpy_x_preferred":[
        "\u09ae\u09be\u099f\u09be \u0997\u09cd\u09b0\u09be\u09a8\u09cd\u09a1\u09c7"
    ],
    "name:ceb_x_preferred":[
        "Mata Grande"
    ],
    "name:epo_x_preferred":[
        "Mata Grande"
    ],
    "name:eus_x_preferred":[
        "Mata Grande"
    ],
    "name:fra_x_preferred":[
        "Mata Grande"
    ],
    "name:hye_x_preferred":[
        "\u0544\u0561\u057f\u0561 \u0533\u0580\u0561\u0576\u0564\u056b"
    ],
    "name:ind_x_preferred":[
        "Mata Grande"
    ],
    "name:ita_x_preferred":[
        "Mata Grande"
    ],
    "name:kat_x_preferred":[
        "\u10db\u10d0\u10e2\u10d0-\u10d2\u10e0\u10d0\u10dc\u10d3\u10d8"
    ],
    "name:nld_x_preferred":[
        "Mata Grande"
    ],
    "name:nor_x_preferred":[
        "Mata Grande"
    ],
    "name:por_x_preferred":[
        "Mata Grande"
    ],
    "name:ron_x_preferred":[
        "Mata Grande"
    ],
    "name:rus_x_preferred":[
        "\u041c\u0430\u0442\u0430-\u0413\u0440\u0430\u043d\u0434\u0438"
    ],
    "name:swe_x_preferred":[
        "Mata Grande"
    ],
    "name:vie_x_preferred":[
        "Mata Grande"
    ],
    "name:vol_x_preferred":[
        "Mata Grande"
    ],
    "name:war_x_preferred":[
        "Mata Grande"
    ],
    "name:zho_x_preferred":[
        "\u5927\u9a6c\u5854"
    ],
    "wof:name":"Mata Grande",
    "wof:placetype":"locality"
},
  "geometry": {"coordinates":[-9.3213,38.89943],"type":"Point"}
}