{
  "type": "Feature",
  "properties": {
    "gn:admin1_code":"10",
    "gn:admin2_code":"3104",
    "gn:admin3_code":"310404.0",
    "gn:asciiname":"Faja do Mar",
    "gn:country_code":"PT",
    "gn:dem":130,
    "gn:feature_class":"P",
    "gn:feature_code":"PPL",
    "gn:name":"Faj\u00e3 do Mar",
    "gn:population":0,
    "gn:timezone":"Atlantic/Madeira",
    "iso:country":"PT",
    "wof:name":"Faja do Mar",
    "wof:placetype":"locality"
},
  "geometry": {"coordinates":[-16.81667,32.76667],"type":"Point"}
}