{
  "type": "Feature",
  "properties": {
    "gn:admin1_code":"5.0",
    "gn:admin2_code":"0405",
    "gn:admin3_code":"40511.0",
    "gn:asciiname":"Corujas",
    "gn:country_code":"PT",
    "gn:dem":721,
    "gn:feature_class":"P",
    "gn:feature_code":"PPL",
    "gn:name":"Corujas",
    "gn:population":0,
    "gn:timezone":"Europe/Lisbon",
    "iso:country":"PT",
    "wof:name":"Corujas",
    "wof:placetype":"locality"
},
  "geometry": {"coordinates":[-6.96782,41.60169000000001],"type":"Point"}
}