{
  "type": "Feature",
  "properties": {
    "gn:admin1_code":"09",
    "gn:admin2_code":"0801",
    "gn:admin3_code":"80103.0",
    "gn:asciiname":"Ameijoafas",
    "gn:country_code":"PT",
    "gn:dem":122,
    "gn:feature_class":"P",
    "gn:feature_code":"PPL",
    "gn:name":"Ameijoafas",
    "gn:population":0,
    "gn:timezone":"Europe/Lisbon",
    "iso:country":"PT",
    "wof:name":"Ameijoafas",
    "wof:placetype":"locality"
},
  "geometry": {"coordinates":[-8.1887,37.17534000000001],"type":"Point"}
}