{
  "type": "Feature",
  "properties": {
    "gn:admin1_code":"2.0",
    "gn:admin2_code":"0101",
    "gn:admin3_code":"10107.0",
    "gn:asciiname":"Castanheira do Vouga",
    "gn:country_code":"PT",
    "gn:dem":165,
    "gn:feature_class":"P",
    "gn:feature_code":"PPL",
    "gn:name":"Castanheira do Vouga",
    "gn:population":0,
    "gn:timezone":"Europe/Lisbon",
    "iso:country":"PT",
    "wof:name":"Castanheira do Vouga",
    "wof:placetype":"locality"
},
  "geometry": {"coordinates":[-8.36668,40.56898],"type":"Point"}
}