{
  "type": "Feature",
  "properties": {
    "gn:admin1_code":"17.0",
    "gn:admin2_code":"1303",
    "gn:admin3_code":"130324.0",
    "gn:asciiname":"Calvario",
    "gn:country_code":"PT",
    "gn:dem":435,
    "gn:feature_class":"P",
    "gn:feature_code":"PPL",
    "gn:name":"Calv\u00e1rio",
    "gn:population":0,
    "gn:timezone":"Europe/Lisbon",
    "iso:country":"PT",
    "wof:name":"Calvario",
    "wof:placetype":"locality"
},
  "geometry": {"coordinates":[-8.17686,41.38839],"type":"Point"}
}