{
  "type": "Feature",
  "properties": {
    "gn:admin1_code":"7.0",
    "gn:admin2_code":"0613",
    "gn:admin3_code":"61307.0",
    "gn:asciiname":"Ponte",
    "gn:country_code":"PT",
    "gn:dem":105,
    "gn:feature_class":"P",
    "gn:feature_code":"PPL",
    "gn:name":"Ponte",
    "gn:population":0,
    "gn:timezone":"Europe/Lisbon",
    "iso:country":"PT",
    "name:bul_x_preferred":[
        "\u041f\u043e\u043d\u0442\u0435"
    ],
    "name:cat_x_preferred":[
        "Ponte"
    ],
    "name:ceb_x_preferred":[
        "Ponte"
    ],
    "name:deu_x_preferred":[
        "Ponte"
    ],
    "name:epo_x_preferred":[
        "Ponte"
    ],
    "name:fas_x_preferred":[
        "\u067e\u0648\u0646\u062a\u0647"
    ],
    "name:fra_x_preferred":[
        "Ponte"
    ],
    "name:glg_x_preferred":[
        "Ponte"
    ],
    "name:heb_x_preferred":[
        "\u05e4\u05d5\u05e0\u05d8\u05d4"
    ],
    "name:hye_x_preferred":[
        "\u054a\u0578\u0576\u057f\u0565"
    ],
    "name:ita_x_preferred":[
        "Ponte"
    ],
    "name:jpn_x_preferred":[
        "\u30dd\u30f3\u30c6"
    ],
    "name:kaz_x_preferred":[
        "\u041f\u043e\u043d\u0442\u0435"
    ],
    "name:nld_x_preferred":[
        "Ponte"
    ],
    "name:pol_x_preferred":[
        "Ponte"
    ],
    "name:por_x_preferred":[
        "Ponte"
    ],
    "name:rus_x_preferred":[
        "\u041f\u043e\u043d\u0442\u0435"
    ],
    "name:spa_x_preferred":[
        "Ponte"
    ],
    "name:srp_x_preferred":[
        "Ponte"
    ],
    "name:swe_x_preferred":[
        "Ponte"
    ],
    "name:ukr_x_preferred":[
        "\u041f\u043e\u043d\u0442\u0435"
    ],
    "wof:name":"Ponte",
    "wof:placetype":"locality"
},
  "geometry": {"coordinates":[-8.28333,40.26667],"type":"Point"}
}