{
  "type": "Feature",
  "properties": {
    "gn:admin1_code":"4.0",
    "gn:admin2_code":"0305",
    "gn:admin3_code":"30505.0",
    "gn:asciiname":"Alfarela",
    "gn:country_code":"PT",
    "gn:dem":691,
    "gn:feature_class":"P",
    "gn:feature_code":"PPL",
    "gn:name":"Alfarela",
    "gn:population":0,
    "gn:timezone":"Europe/Lisbon",
    "iso:country":"PT",
    "wof:name":"Alfarela",
    "wof:placetype":"locality"
},
  "geometry": {"coordinates":[-8.05307,41.41486],"type":"Point"}
}