{
  "type": "Feature",
  "properties": {
    "gn:admin1_code":"05",
    "gn:admin2_code":"0403",
    "gn:admin3_code":"40316.0",
    "gn:asciiname":"Seixo de Anciaes",
    "gn:country_code":"PT",
    "gn:dem":659,
    "gn:feature_class":"P",
    "gn:feature_code":"PPL",
    "gn:name":"Seixo de Anci\u00e3es",
    "gn:population":0,
    "gn:timezone":"Europe/Lisbon",
    "iso:country":"PT",
    "wof:name":"Seixo de Anciaes",
    "wof:placetype":"locality"
},
  "geometry": {"coordinates":[-7.26549,41.19014],"type":"Point"}
}