{
  "type": "Feature",
  "properties": {
    "gn:admin1_code":"17",
    "gn:admin2_code":"1313",
    "gn:admin3_code":"131307.0",
    "gn:asciiname":"Valdoia",
    "gn:country_code":"PT",
    "gn:dem":21,
    "gn:feature_class":"P",
    "gn:feature_code":"PPL",
    "gn:name":"Valdoia",
    "gn:population":0,
    "gn:timezone":"Europe/Lisbon",
    "iso:country":"PT",
    "wof:name":"Valdoia",
    "wof:placetype":"locality"
},
  "geometry": {"coordinates":[-8.75401,41.44994000000001],"type":"Point"}
}