{
  "type": "Feature",
  "properties": {
    "gn:admin1_code":"16",
    "gn:admin2_code":"1205",
    "gn:admin3_code":"120502.0",
    "gn:asciiname":"Gancho",
    "gn:country_code":"PT",
    "gn:dem":439,
    "gn:feature_class":"P",
    "gn:feature_code":"PPL",
    "gn:name":"Gancho",
    "gn:population":0,
    "gn:timezone":"Europe/Lisbon",
    "iso:country":"PT",
    "wof:name":"Gancho",
    "wof:placetype":"locality"
},
  "geometry": {"coordinates":[-7.4364,39.43202],"type":"Point"}
}