{
  "type": "Feature",
  "properties": {
    "gn:admin1_code":"20.0",
    "gn:admin2_code":"1607",
    "gn:admin3_code":"160721.0",
    "gn:asciiname":"Bouca Velha",
    "gn:country_code":"PT",
    "gn:dem":7,
    "gn:feature_class":"P",
    "gn:feature_code":"PPL",
    "gn:name":"Bou\u00e7a Velha",
    "gn:population":0,
    "gn:timezone":"Europe/Lisbon",
    "iso:country":"PT",
    "wof:name":"Bouca Velha",
    "wof:placetype":"locality"
},
  "geometry": {"coordinates":[-8.66476,41.74124000000001],"type":"Point"}
}