{
  "type": "Feature",
  "properties": {
    "gn:admin1_code":"2.0",
    "gn:admin2_code":"0101",
    "gn:admin3_code":"10103.0",
    "gn:asciiname":"Garrido",
    "gn:country_code":"PT",
    "gn:dem":45,
    "gn:feature_class":"P",
    "gn:feature_code":"PPL",
    "gn:name":"Garrido",
    "gn:population":0,
    "gn:timezone":"Europe/Lisbon",
    "iso:country":"PT",
    "name:cat_x_preferred":[
        "Garrido"
    ],
    "name:ceb_x_preferred":[
        "Garrido"
    ],
    "name:deu_x_preferred":[
        "Garrido"
    ],
    "name:fra_x_preferred":[
        "Garrido"
    ],
    "name:heb_x_preferred":[
        "\u05d2\u05d0\u05e8\u05d9\u05d3\u05d5"
    ],
    "name:ita_x_preferred":[
        "Garrido"
    ],
    "name:pol_x_preferred":[
        "Garrido"
    ],
    "name:por_x_preferred":[
        "Garrido"
    ],
    "name:rus_x_preferred":[
        "\u0413\u0430\u0440\u0440\u0438\u0434\u043e"
    ],
    "name:spa_x_preferred":[
        "Garrido"
    ],
    "name:swe_x_preferred":[
        "Garrido"
    ],
    "wof:name":"Garrido",
    "wof:placetype":"locality"
},
  "geometry": {"coordinates":[-8.42398,40.52633],"type":"Point"}
}