{
  "type": "Feature",
  "properties": {
    "gn:admin1_code":"2.0",
    "gn:admin2_code":"0101",
    "gn:admin3_code":"10103.0",
    "gn:asciiname":"Garrido",
    "gn:country_code":"PT",
    "gn:dem":45,
    "gn:feature_class":"P",
    "gn:feature_code":"PPL",
    "gn:name":"Garrido",
    "gn:population":0,
    "gn:timezone":"Europe/Lisbon",
    "iso:country":"PT",
    "wof:name":"Garrido",
    "wof:placetype":"locality"
},
  "geometry": {"coordinates":[-8.42398,40.52633],"type":"Point"}
}