{
  "type": "Feature",
  "properties": {
    "gn:admin1_code":"04",
    "gn:admin2_code":"0312",
    "gn:admin3_code":"31220.0",
    "gn:asciiname":"Pouve",
    "gn:country_code":"PT",
    "gn:dem":81,
    "gn:feature_class":"P",
    "gn:feature_code":"PPL",
    "gn:name":"Pouve",
    "gn:population":0,
    "gn:timezone":"Europe/Lisbon",
    "iso:country":"PT",
    "wof:name":"Pouve",
    "wof:placetype":"locality"
},
  "geometry": {"coordinates":[-8.48549,41.39792],"type":"Point"}
}