{
  "type": "Feature",
  "properties": {
    "gn:admin1_code":"20.0",
    "gn:admin2_code":"1601",
    "gn:admin3_code":"160130.0",
    "gn:asciiname":"Gondiao",
    "gn:country_code":"PT",
    "gn:dem":372,
    "gn:feature_class":"P",
    "gn:feature_code":"PPL",
    "gn:name":"Gondi\u00e3o",
    "gn:population":0,
    "gn:timezone":"Europe/Lisbon",
    "iso:country":"PT",
    "wof:name":"Gondiao",
    "wof:placetype":"locality"
},
  "geometry": {"coordinates":[-8.47149,41.87033],"type":"Point"}
}