{
  "type": "Feature",
  "properties": {
    "gn:admin1_code":"7.0",
    "gn:admin2_code":"0611",
    "gn:admin3_code":"61105.0",
    "gn:asciiname":"Fiais do Ervedal",
    "gn:country_code":"PT",
    "gn:dem":303,
    "gn:feature_class":"P",
    "gn:feature_code":"PPL",
    "gn:name":"Fiais do Ervedal",
    "gn:population":0,
    "gn:timezone":"Europe/Lisbon",
    "iso:country":"PT",
    "wof:name":"Fiais do Ervedal",
    "wof:placetype":"locality"
},
  "geometry": {"coordinates":[-7.91667,40.41667],"type":"Point"}
}