{
  "type": "Feature",
  "properties": {
    "iso:country":"PT",
    "qs_pg:aaroncc":"PT",
    "qs_pg:name":"Monte Novo de Palma",
    "qs_pg:name_adm0":"Portugal",
    "qs_pg:name_adm1":"Set\u00fabal",
    "qs_pg:photos":20,
    "qs_pg:photos_1k":4,
    "qs_pg:photos_9k":1,
    "qs_pg:photos_9r":1,
    "qs_pg:photos_all":20,
    "qs_pg:photos_sr":1,
    "qs_pg:pop_sr":0,
    "qs_pg:qs_pg_placetype":"locality",
    "qs_pg:qs_pg_placetype_gp":"Town",
    "qs_pg:woe_adm0":23424925,
    "woe:adm0_id":23424925,
    "woe:name_adm0":"Portugal",
    "woe:name_adm1":"Set\u00fabal",
    "woe:placetype":"Town",
    "wof:name":"Monte Novo de Palma",
    "wof:placetype":"locality"
},
  "geometry": {"coordinates":[-8.6376135,38.4314125],"type":"Point"}
}