{
  "type": "Feature",
  "properties": {
    "gn:admin1_code":"04",
    "gn:admin2_code":"0302",
    "gn:admin3_code":"30276.0",
    "gn:asciiname":"Vila Verde",
    "gn:country_code":"PT",
    "gn:dem":163,
    "gn:feature_class":"P",
    "gn:feature_code":"PPL",
    "gn:name":"Vila Verde",
    "gn:population":0,
    "gn:timezone":"Europe/Lisbon",
    "iso:country":"PT",
    "wof:name":"Vila Verde",
    "wof:placetype":"locality"
},
  "geometry": {"coordinates":[-8.63095,41.59466],"type":"Point"}
}