{
  "type": "Feature",
  "properties": {
    "gn:admin1_code":"11.0",
    "gn:admin2_code":"0906",
    "gn:admin3_code":"90620.0",
    "gn:asciiname":"Ponte Nova",
    "gn:country_code":"PT",
    "gn:dem":315,
    "gn:feature_class":"P",
    "gn:feature_code":"PPL",
    "gn:name":"Ponte Nova",
    "gn:population":0,
    "gn:timezone":"Europe/Lisbon",
    "iso:country":"PT",
    "name:ara_x_preferred":[
        "\u0628\u0644\u062f\u064a\u0629 \u0628\u0648\u0646\u062a\u064a \u0646\u0648\u0641\u0627"
    ],
    "name:bpy_x_preferred":[
        "\u09aa\u09cb\u09a8\u09cd\u099f\u09c7 \u09a8\u09cb\u09ad\u09be"
    ],
    "name:ceb_x_preferred":[
        "Ponte Nova"
    ],
    "name:deu_x_preferred":[
        "Ponte Nova"
    ],
    "name:epo_x_preferred":[
        "Ponte Nova"
    ],
    "name:eus_x_preferred":[
        "Ponte Nova"
    ],
    "name:fra_x_preferred":[
        "Ponte Nova"
    ],
    "name:ita_x_preferred":[
        "Ponte Nova"
    ],
    "name:kat_x_preferred":[
        "\u10de\u10dd\u10dc\u10e2\u10d8-\u10dc\u10dd\u10d5\u10d0"
    ],
    "name:kaz_x_preferred":[
        "\u041f\u043e\u043d\u0442\u0438-\u041d\u043e\u0432\u0430"
    ],
    "name:mlg_x_preferred":[
        "Ponte Nova"
    ],
    "name:nld_x_preferred":[
        "Ponte Nova"
    ],
    "name:nor_x_preferred":[
        "Ponte Nova"
    ],
    "name:pol_x_preferred":[
        "Ponte Nova"
    ],
    "name:por_x_preferred":[
        "Ponte Nova"
    ],
    "name:ron_x_preferred":[
        "Ponte Nova"
    ],
    "name:rus_x_preferred":[
        "\u041f\u043e\u043d\u0442\u0438-\u041d\u043e\u0432\u0430"
    ],
    "name:spa_x_preferred":[
        "Ponte Nova"
    ],
    "name:swe_x_preferred":[
        "Ponte Nova"
    ],
    "name:tha_x_preferred":[
        "\u0e1b\u0e07\u0e0a\u0e35\u0e19\u0e2d\u0e27\u0e32"
    ],
    "name:vie_x_preferred":[
        "Ponte Nova"
    ],
    "name:vol_x_preferred":[
        "Ponte Nova"
    ],
    "name:war_x_preferred":[
        "Ponte Nova"
    ],
    "name:zho_x_preferred":[
        "\u84ec\u8482\u8bfa\u74e6"
    ],
    "wof:name":"Ponte Nova",
    "wof:placetype":"locality"
},
  "geometry": {"coordinates":[-7.56631,40.5856],"type":"Point"}
}