{
  "type": "Feature",
  "properties": {
    "gn:admin1_code":"11.0",
    "gn:admin2_code":"0906",
    "gn:admin3_code":"90620.0",
    "gn:asciiname":"Ponte Nova",
    "gn:country_code":"PT",
    "gn:dem":315,
    "gn:feature_class":"P",
    "gn:feature_code":"PPL",
    "gn:name":"Ponte Nova",
    "gn:population":0,
    "gn:timezone":"Europe/Lisbon",
    "iso:country":"PT",
    "wof:name":"Ponte Nova",
    "wof:placetype":"locality"
},
  "geometry": {"coordinates":[-7.56631,40.5856],"type":"Point"}
}