{
  "type": "Feature",
  "properties": {
    "gn:admin1_code":"18",
    "gn:admin2_code":"1416",
    "gn:admin3_code":"141627.0",
    "gn:asciiname":"Quinta de Sao Martinho",
    "gn:country_code":"PT",
    "gn:dem":42,
    "gn:feature_class":"P",
    "gn:feature_code":"PPL",
    "gn:name":"Quinta de S\u00e3o Martinho",
    "gn:population":0,
    "gn:timezone":"Europe/Lisbon",
    "iso:country":"PT",
    "wof:name":"Quinta de Sao Martinho",
    "wof:placetype":"locality"
},
  "geometry": {"coordinates":[-8.75164,39.27215],"type":"Point"}
}