{
  "type": "Feature",
  "properties": {
    "gn:admin1_code":"7.0",
    "gn:admin2_code":"0601",
    "gn:admin3_code":"60113.0",
    "gn:asciiname":"Alcaria",
    "gn:country_code":"PT",
    "gn:dem":252,
    "gn:feature_class":"P",
    "gn:feature_code":"PPL",
    "gn:name":"Alcaria",
    "gn:population":0,
    "gn:timezone":"Europe/Lisbon",
    "iso:country":"PT",
    "wof:name":"Alcaria",
    "wof:placetype":"locality"
},
  "geometry": {"coordinates":[-8.10866,40.20291],"type":"Point"}
}