{
  "type": "Feature",
  "properties": {
    "gn:admin1_code":"20.0",
    "gn:admin2_code":"1605",
    "gn:admin3_code":"160505.0",
    "gn:asciiname":"Coura",
    "gn:country_code":"PT",
    "gn:dem":169,
    "gn:feature_class":"P",
    "gn:feature_code":"PPL",
    "gn:name":"Coura",
    "gn:population":0,
    "gn:timezone":"Europe/Lisbon",
    "iso:country":"PT",
    "name:ceb_x_preferred":[
        "Coura"
    ],
    "name:deu_x_preferred":[
        "Coura"
    ],
    "name:fra_x_preferred":[
        "Coura"
    ],
    "name:nld_x_preferred":[
        "Coura"
    ],
    "name:por_x_preferred":[
        "Coura"
    ],
    "wof:name":"Coura",
    "wof:placetype":"locality"
},
  "geometry": {"coordinates":[-8.65084,41.8791],"type":"Point"}
}