{
  "type": "Feature",
  "properties": {
    "gn:admin1_code":"13",
    "gn:admin2_code":"1009",
    "gn:admin3_code":"100923.0",
    "gn:asciiname":"Souto de Baixo",
    "gn:country_code":"PT",
    "gn:dem":72,
    "gn:feature_class":"P",
    "gn:feature_code":"PPL",
    "gn:name":"Souto de Baixo",
    "gn:population":0,
    "gn:timezone":"Europe/Lisbon",
    "iso:country":"PT",
    "wof:name":"Souto de Baixo",
    "wof:placetype":"locality"
},
  "geometry": {"coordinates":[-8.74495,39.75382000000001],"type":"Point"}
}