{
  "type": "Feature",
  "properties": {
    "gn:admin1_code":"07",
    "gn:admin2_code":"0612",
    "gn:admin3_code":"61206.0",
    "gn:asciiname":"Soeirinho",
    "gn:country_code":"PT",
    "gn:dem":764,
    "gn:feature_class":"P",
    "gn:feature_code":"PPL",
    "gn:name":"Soeirinho",
    "gn:population":0,
    "gn:timezone":"Europe/Lisbon",
    "iso:country":"PT",
    "wof:name":"Soeirinho",
    "wof:placetype":"locality"
},
  "geometry": {"coordinates":[-7.97483,40.09113],"type":"Point"}
}