{
  "type": "Feature",
  "properties": {
    "gn:admin1_code":"09",
    "gn:admin2_code":"0813",
    "gn:admin3_code":"81305.0",
    "gn:asciiname":"Barradas",
    "gn:country_code":"PT",
    "gn:dem":175,
    "gn:feature_class":"P",
    "gn:feature_code":"PPL",
    "gn:name":"Barradas",
    "gn:population":0,
    "gn:timezone":"Europe/Lisbon",
    "iso:country":"PT",
    "wof:name":"Barradas",
    "wof:placetype":"locality"
},
  "geometry": {"coordinates":[-8.30246,37.26462],"type":"Point"}
}