{
  "type": "Feature",
  "properties": {
    "gn:admin1_code":"14",
    "gn:admin2_code":"1109",
    "gn:admin3_code":"110913.0",
    "gn:asciiname":"Paco das Ilhas",
    "gn:country_code":"PT",
    "gn:dem":91,
    "gn:feature_class":"P",
    "gn:feature_code":"PPL",
    "gn:name":"Pa\u00e7o das Ilhas",
    "gn:population":0,
    "gn:timezone":"Europe/Lisbon",
    "iso:country":"PT",
    "wof:name":"Paco das Ilhas",
    "wof:placetype":"locality"
},
  "geometry": {"coordinates":[-9.40408,38.99816],"type":"Point"}
}