{
  "type": "Feature",
  "properties": {
    "gn:admin1_code":"13",
    "gn:admin2_code":"1003",
    "gn:admin3_code":"100306.0",
    "gn:asciiname":"Eira da Pedra",
    "gn:country_code":"PT",
    "gn:dem":306,
    "gn:feature_class":"P",
    "gn:feature_code":"PPL",
    "gn:name":"Eira da Pedra",
    "gn:population":0,
    "gn:timezone":"Europe/Lisbon",
    "iso:country":"PT",
    "wof:name":"Eira da Pedra",
    "wof:placetype":"locality"
},
  "geometry": {"coordinates":[-8.38916,39.86623],"type":"Point"}
}