{
  "type": "Feature",
  "properties": {
    "iso:country":"PT",
    "name:ast_x_preferred":[
        "Cacia"
    ],
    "name:ceb_x_preferred":[
        "Cacia"
    ],
    "name:che_x_preferred":[
        "\u041a\u0430\u0441\u0438\u044f"
    ],
    "name:deu_x_preferred":[
        "Cacia"
    ],
    "name:eng_x_preferred":[
        "Cacia"
    ],
    "name:fra_x_preferred":[
        "Cacia"
    ],
    "name:ita_x_preferred":[
        "Cacia"
    ],
    "name:kaz_x_preferred":[
        "\u041a\u0430\u0441\u0438\u044f"
    ],
    "name:msa_x_preferred":[
        "Cacia"
    ],
    "name:nan_x_preferred":[
        "Cacia"
    ],
    "name:nld_x_preferred":[
        "Cacia"
    ],
    "name:por_x_preferred":[
        "Cacia"
    ],
    "name:rus_x_preferred":[
        "\u041a\u0430\u0441\u0438\u044f"
    ],
    "name:spa_x_preferred":[
        "Cacia"
    ],
    "name:tat_x_preferred":[
        "\u041a\u0430\u0441\u0438\u044f"
    ],
    "name:ukr_x_preferred":[
        "\u041a\u0430\u0441\u0456\u044f"
    ],
    "name:zho_x_preferred":[
        "\u5361\u897f\u4e9a"
    ],
    "qs:a0":"Portugal",
    "qs:a1":"*Aveiro",
    "qs:a1r":"0",
    "qs:adm0":"Portugal",
    "qs:la_lc":"*",
    "qs:level":"locality",
    "qs:loc":"Cacia",
    "qs:loc_alt":"Cacia",
    "qs:pop":0,
    "qs:type":"buffered point",
    "wd:wordcount":1496,
    "wof:lang":[
        "por"
    ],
    "wof:name":"Cacia",
    "wof:placetype":"locality"
},
  "geometry": {"coordinates":[-8.588141,40.678644],"type":"Point"}
}