{
  "type": "Feature",
  "properties": {
    "gn:admin1_code":"14",
    "gn:admin2_code":"1109",
    "gn:admin3_code":"110901.0",
    "gn:asciiname":"Abobreira",
    "gn:country_code":"PT",
    "gn:dem":111,
    "gn:feature_class":"P",
    "gn:feature_code":"PPL",
    "gn:name":"Abobreira",
    "gn:population":0,
    "gn:timezone":"Europe/Lisbon",
    "iso:country":"PT",
    "wof:name":"Abobreira",
    "wof:placetype":"locality"
},
  "geometry": {"coordinates":[-9.29651,39.02193],"type":"Point"}
}