{
  "type": "Feature",
  "properties": {
    "gn:admin1_code":"07",
    "gn:asciiname":"Quinta dos Cozinheiros",
    "gn:country_code":"PT",
    "gn:dem":99,
    "gn:feature_class":"P",
    "gn:feature_code":"PPL",
    "gn:name":"Quinta dos Cozinheiros",
    "gn:population":0,
    "gn:timezone":"Europe/Lisbon",
    "iso:country":"PT",
    "wof:name":"Quinta dos Cozinheiros",
    "wof:placetype":"locality"
},
  "geometry": {"coordinates":[-8.79571,40.02159],"type":"Point"}
}