{
  "type": "Feature",
  "properties": {
    "gn:admin1_code":"14",
    "gn:admin2_code":"1111",
    "gn:admin3_code":"111112.0",
    "gn:asciiname":"Chao de Meninos",
    "gn:country_code":"PT",
    "gn:dem":287,
    "gn:feature_class":"P",
    "gn:feature_code":"PPL",
    "gn:name":"Ch\u00e3o de Meninos",
    "gn:population":0,
    "gn:timezone":"Europe/Lisbon",
    "iso:country":"PT",
    "wof:name":"Chao de Meninos",
    "wof:placetype":"locality"
},
  "geometry": {"coordinates":[-9.37342,38.79189],"type":"Point"}
}