{
  "type": "Feature",
  "properties": {
    "gn:admin1_code":"14",
    "gn:admin2_code":"1109",
    "gn:admin3_code":"110901.0",
    "gn:asciiname":"Livramento",
    "gn:country_code":"PT",
    "gn:dem":122,
    "gn:feature_class":"P",
    "gn:feature_code":"PPL",
    "gn:name":"Livramento",
    "gn:population":0,
    "gn:timezone":"Europe/Lisbon",
    "iso:country":"PT",
    "name:bpy_x_preferred":[
        "\u09b2\u09bf\u09ad\u09cd\u09b0\u09be\u09ae\u09c7\u09a8\u099f\u09cb"
    ],
    "name:ceb_x_preferred":[
        "Livramento"
    ],
    "name:deu_x_preferred":[
        "Livramento"
    ],
    "name:fra_x_preferred":[
        "Livramento"
    ],
    "name:nld_x_preferred":[
        "Livramento"
    ],
    "name:por_x_preferred":[
        "Livramento"
    ],
    "name:rus_x_preferred":[
        "\u041b\u0438\u0432\u0440\u0430\u043c\u0435\u043d\u0442\u0443"
    ],
    "name:swe_x_preferred":[
        "Livramento"
    ],
    "wof:name":"Livramento",
    "wof:placetype":"locality"
},
  "geometry": {"coordinates":[-9.29247,39.00668],"type":"Point"}
}