{
  "type": "Feature",
  "properties": {
    "gn:admin1_code":"11.0",
    "gn:admin2_code":"0907",
    "gn:admin3_code":"90718.0",
    "gn:asciiname":"Fernao Joanes",
    "gn:country_code":"PT",
    "gn:dem":916,
    "gn:feature_class":"P",
    "gn:feature_code":"PPL",
    "gn:name":"Fern\u00e3o Joanes",
    "gn:population":0,
    "gn:timezone":"Europe/Lisbon",
    "iso:country":"PT",
    "wof:name":"Fernao Joanes",
    "wof:placetype":"locality"
},
  "geometry": {"coordinates":[-7.35515,40.48571],"type":"Point"}
}