{
  "type": "Feature",
  "properties": {
    "gn:admin1_code":"20.0",
    "gn:admin2_code":"1609",
    "gn:admin3_code":"160925.0",
    "gn:asciiname":"Outeiro",
    "gn:country_code":"PT",
    "gn:dem":81,
    "gn:feature_class":"P",
    "gn:feature_code":"PPL",
    "gn:name":"Outeiro",
    "gn:population":0,
    "gn:timezone":"Europe/Lisbon",
    "iso:country":"PT",
    "name:ceb_x_preferred":[
        "Outeiro"
    ],
    "name:deu_x_preferred":[
        "Outeiro"
    ],
    "name:fra_x_preferred":[
        "Outeiro"
    ],
    "name:glg_x_preferred":[
        "Outeiro"
    ],
    "name:nld_x_preferred":[
        "Outeiro"
    ],
    "name:por_x_preferred":[
        "Outeiro"
    ],
    "name:swe_x_preferred":[
        "Outeiro"
    ],
    "name:tur_x_preferred":[
        "Outeiro"
    ],
    "name:ukr_x_preferred":[
        "\u041e\u0442\u0435\u0439\u0440\u0443"
    ],
    "wof:name":"Outeiro",
    "wof:placetype":"locality"
},
  "geometry": {"coordinates":[-8.78517,41.74721],"type":"Point"}
}