{
  "type": "Feature",
  "properties": {
    "gn:admin1_code":"14",
    "gn:admin2_code":"1111",
    "gn:admin3_code":"111105.0",
    "gn:asciiname":"Capuchos",
    "gn:cc2":"PT",
    "gn:country_code":"PT",
    "gn:dem":356,
    "gn:feature_class":"P",
    "gn:feature_code":"PPL",
    "gn:name":"Capuchos",
    "gn:population":0,
    "gn:timezone":"Europe/Lisbon",
    "iso:country":"PT",
    "name:por_x_preferred":[
        "Capuchos"
    ],
    "name:und_x_variant":[
        "Miradouro dos Capuchos"
    ],
    "wof:name":"Capuchos",
    "wof:placetype":"locality"
},
  "geometry": {"coordinates":[-9.43333,38.78333],"type":"Point"}
}