{
  "type": "Feature",
  "properties": {
    "gn:admin1_code":"4.0",
    "gn:admin2_code":"0304",
    "gn:admin3_code":"30414.0",
    "gn:asciiname":"Ponte de Pe",
    "gn:country_code":"PT",
    "gn:dem":299,
    "gn:feature_class":"P",
    "gn:feature_code":"PPL",
    "gn:name":"Ponte de P\u00e9",
    "gn:population":0,
    "gn:timezone":"Europe/Lisbon",
    "iso:country":"PT",
    "wof:name":"Ponte de Pe",
    "wof:placetype":"locality"
},
  "geometry": {"coordinates":[-7.97974,41.51695],"type":"Point"}
}