{
  "type": "Feature",
  "properties": {
    "gn:admin1_code":"13",
    "gn:admin2_code":"1015",
    "gn:admin3_code":"101503.0",
    "gn:asciiname":"Ladeira",
    "gn:country_code":"PT",
    "gn:dem":121,
    "gn:feature_class":"P",
    "gn:feature_code":"PPL",
    "gn:name":"Ladeira",
    "gn:population":0,
    "gn:timezone":"Europe/Lisbon",
    "iso:country":"PT",
    "wof:name":"Ladeira",
    "wof:placetype":"locality"
},
  "geometry": {"coordinates":[-8.67253,39.94906],"type":"Point"}
}