{
  "type": "Feature",
  "properties": {
    "gn:admin1_code":"20",
    "gn:admin2_code":"1601",
    "gn:admin3_code":"160149.0",
    "gn:asciiname":"Vale",
    "gn:country_code":"PT",
    "gn:dem":172,
    "gn:feature_class":"P",
    "gn:feature_code":"PPL",
    "gn:name":"Vale",
    "gn:population":0,
    "gn:timezone":"Europe/Lisbon",
    "iso:country":"PT",
    "wof:name":"Vale",
    "wof:placetype":"locality"
},
  "geometry": {"coordinates":[-8.3721,41.83600000000001],"type":"Point"}
}