{
  "type": "Feature",
  "properties": {
    "gn:admin1_code":"20",
    "gn:admin2_code":"1601",
    "gn:admin3_code":"160149.0",
    "gn:asciiname":"Vale",
    "gn:country_code":"PT",
    "gn:dem":172,
    "gn:feature_class":"P",
    "gn:feature_code":"PPL",
    "gn:name":"Vale",
    "gn:population":0,
    "gn:timezone":"Europe/Lisbon",
    "iso:country":"PT",
    "name:ceb_x_preferred":[
        "Vale"
    ],
    "name:deu_x_preferred":[
        "Vale"
    ],
    "name:epo_x_preferred":[
        "Vale"
    ],
    "name:fin_x_preferred":[
        "Vale"
    ],
    "name:fra_x_preferred":[
        "Vale"
    ],
    "name:glg_x_preferred":[
        "Vale"
    ],
    "name:hun_x_preferred":[
        "Vale"
    ],
    "name:ita_x_preferred":[
        "Vale"
    ],
    "name:nld_x_preferred":[
        "Vale"
    ],
    "name:nor_x_preferred":[
        "Vale"
    ],
    "name:pol_x_preferred":[
        "Vale"
    ],
    "name:por_x_preferred":[
        "Vale"
    ],
    "name:ron_x_preferred":[
        "Vale"
    ],
    "name:rus_x_preferred":[
        "Vale"
    ],
    "name:spa_x_preferred":[
        "Vale"
    ],
    "name:srp_x_preferred":[
        "\u0412\u0435\u0458\u043b"
    ],
    "name:swe_x_preferred":[
        "Vale"
    ],
    "wof:name":"Vale",
    "wof:placetype":"locality"
},
  "geometry": {"coordinates":[-8.3721,41.83600000000001],"type":"Point"}
}