{
  "type": "Feature",
  "properties": {
    "gn:country":"PT",
    "gn:fcode":"ADM3",
    "gn:population":0,
    "iso:country":"PT",
    "name:cat_x_preferred":[
        "Alij\u00f3"
    ],
    "name:ceb_x_preferred":[
        "Alij\u00f3"
    ],
    "name:deu_x_preferred":[
        "Alij\u00f3"
    ],
    "name:fin_x_preferred":[
        "Alij\u00f3"
    ],
    "name:fra_x_preferred":[
        "Alij\u00f3"
    ],
    "name:hye_x_preferred":[
        "\u0531\u056c\u056b\u056a\u0578"
    ],
    "name:ita_x_preferred":[
        "Alij\u00f3"
    ],
    "name:kaz_x_preferred":[
        "\u0410\u043b\u0438\u0436\u043e"
    ],
    "name:msa_x_preferred":[
        "Alij\u00f3"
    ],
    "name:mwl_x_preferred":[
        "Alij\u00f3"
    ],
    "name:nld_x_preferred":[
        "Alij\u00f3"
    ],
    "name:pol_x_preferred":[
        "Alij\u00f3"
    ],
    "name:por_x_preferred":[
        "Alij\u00f3"
    ],
    "name:rus_x_preferred":[
        "\u0410\u043b\u0438\u0436\u043e"
    ],
    "name:spa_x_preferred":[
        "Alij\u00f3"
    ],
    "name:tur_x_preferred":[
        "Alij\u00f3"
    ],
    "name:ukr_x_preferred":[
        "\u0410\u043b\u0456\u0436\u043e"
    ],
    "name:vie_x_preferred":[
        "Alij\u00f3"
    ],
    "name:vol_x_preferred":[
        "Alij\u00f3"
    ],
    "name:war_x_preferred":[
        "Alij\u00f3"
    ],
    "name:zho_x_preferred":[
        "\u963f\u5229\u82e5"
    ],
    "qs_pg:aaroncc":"PT",
    "qs_pg:gn_country":"PT",
    "qs_pg:gn_fcode":"ADM3",
    "qs_pg:gn_pop":0,
    "qs_pg:name":"Alij\u00f3",
    "qs_pg:photos_9r":0,
    "qs_pg:photos_sr":0,
    "qs_pg:pop_sr":0,
    "qs_pg:qs_pg_placetype":"localadmin",
    "wof:name":"Alij\u00f3",
    "wof:placetype":"localadmin"
},
  "geometry": {"coordinates":[-7.45902,41.28063],"type":"Point"}
}