{
  "type": "Feature",
  "properties": {
    "gn:admin1_code":"04",
    "gn:admin2_code":"0303",
    "gn:admin3_code":"30301.0",
    "gn:asciiname":"Redondo",
    "gn:country_code":"PT",
    "gn:dem":95,
    "gn:feature_class":"P",
    "gn:feature_code":"PPL",
    "gn:name":"Redondo",
    "gn:population":0,
    "gn:timezone":"Europe/Lisbon",
    "iso:country":"PT",
    "wof:name":"Redondo",
    "wof:placetype":"locality"
},
  "geometry": {"coordinates":[-8.39613,41.59282],"type":"Point"}
}