{
  "type": "Feature",
  "properties": {
    "gn:admin1_code":"18",
    "gn:admin2_code":"1409",
    "gn:admin3_code":"140906.0",
    "gn:asciiname":"Barrancosas",
    "gn:country_code":"PT",
    "gn:dem":101,
    "gn:feature_class":"P",
    "gn:feature_code":"PPL",
    "gn:name":"Barrancosas",
    "gn:population":0,
    "gn:timezone":"Europe/Lisbon",
    "iso:country":"PT",
    "wof:name":"Barrancosas",
    "wof:placetype":"locality"
},
  "geometry": {"coordinates":[-8.40604,39.03358],"type":"Point"}
}