{
  "type": "Feature",
  "properties": {
    "gn:admin1_code":"23.0",
    "gn:admin2_code":"4801",
    "gn:admin3_code":"480104.0",
    "gn:asciiname":"Costa",
    "gn:country_code":"PT",
    "gn:dem":200,
    "gn:feature_class":"P",
    "gn:feature_code":"PPLL",
    "gn:name":"Costa",
    "gn:population":0,
    "gn:timezone":"Atlantic/Azores",
    "iso:country":"PT",
    "wof:name":"Costa",
    "wof:placetype":"locality"
},
  "geometry": {"coordinates":[-31.24177,39.38483],"type":"Point"}
}