{
  "type": "Feature",
  "properties": {
    "gn:admin1_code":"23.0",
    "gn:admin2_code":"4801",
    "gn:admin3_code":"480104.0",
    "gn:asciiname":"Costa",
    "gn:country_code":"PT",
    "gn:dem":200,
    "gn:feature_class":"P",
    "gn:feature_code":"PPLL",
    "gn:name":"Costa",
    "gn:population":0,
    "gn:timezone":"Atlantic/Azores",
    "iso:country":"PT",
    "name:bre_x_preferred":[
        "Costa"
    ],
    "name:cat_x_preferred":[
        "Costa"
    ],
    "name:ceb_x_preferred":[
        "Costa"
    ],
    "name:ces_x_preferred":[
        "Costa"
    ],
    "name:deu_x_preferred":[
        "Costa"
    ],
    "name:epo_x_preferred":[
        "Costa"
    ],
    "name:fin_x_preferred":[
        "Costa"
    ],
    "name:fra_x_preferred":[
        "Costa"
    ],
    "name:glg_x_preferred":[
        "Costa"
    ],
    "name:heb_x_preferred":[
        "\u05e7\u05d5\u05e1\u05d8\u05d4"
    ],
    "name:ita_x_preferred":[
        "Costa"
    ],
    "name:jpn_x_preferred":[
        "\u30b3\u30b9\u30bf"
    ],
    "name:kor_x_preferred":[
        "\ucf54\uc2a4\ud0c0"
    ],
    "name:lat_x_preferred":[
        "Costa"
    ],
    "name:lav_x_preferred":[
        "Costa"
    ],
    "name:lmo_x_preferred":[
        "C\u00f2sta"
    ],
    "name:nld_x_preferred":[
        "Costa"
    ],
    "name:pms_x_preferred":[
        "C\u00f2sta"
    ],
    "name:pol_x_preferred":[
        "Costa"
    ],
    "name:por_x_preferred":[
        "Costa"
    ],
    "name:rus_x_preferred":[
        "\u041a\u043e\u0441\u0442\u0430"
    ],
    "name:scn_x_preferred":[
        "Costa"
    ],
    "name:spa_x_preferred":[
        "Costa"
    ],
    "name:srp_x_preferred":[
        "\u041a\u043e\u0441\u0442\u0430"
    ],
    "name:swe_x_preferred":[
        "Costa"
    ],
    "name:tur_x_preferred":[
        "Costa"
    ],
    "name:ukr_x_preferred":[
        "\u041a\u043e\u0441\u0442\u0430"
    ],
    "name:zho_x_preferred":[
        "\u79d1\u65af\u5854"
    ],
    "wof:name":"Costa",
    "wof:placetype":"locality"
},
  "geometry": {"coordinates":[-31.24177,39.38483],"type":"Point"}
}