{
  "type": "Feature",
  "properties": {
    "gn:gn_country":"PT",
    "gn:gn_fcode":"PPL",
    "gn:gn_pop":0,
    "iso:country":"PT",
    "name:ceb_x_preferred":[
        "Rebordelo"
    ],
    "name:deu_x_preferred":[
        "Rebordelo"
    ],
    "name:fra_x_preferred":[
        "Rebordelo"
    ],
    "name:glg_x_preferred":[
        "Rebordelo"
    ],
    "name:nds_x_preferred":[
        "Rebordelo"
    ],
    "name:nld_x_preferred":[
        "Rebordelo"
    ],
    "name:por_x_preferred":[
        "Rebordelo"
    ],
    "name:rus_x_preferred":[
        "\u0420\u0435\u0431\u043e\u0440\u0434\u0435\u043b\u0443"
    ],
    "name:ukr_x_preferred":[
        "\u0420\u0435\u0431\u043e\u0440\u0434\u0435\u043b\u0443"
    ],
    "name:unk_x_variant":[
        "Rebordello"
    ],
    "qs_pg:aaroncc":"PT",
    "qs_pg:gn_country":"PT",
    "qs_pg:gn_fcode":"PPL",
    "qs_pg:gn_pop":0,
    "qs_pg:name":"Rebordelo",
    "qs_pg:name_adm0":"Portugal",
    "qs_pg:name_adm1":"Bragan\u00e7a",
    "qs_pg:photos":72,
    "qs_pg:photos_1k":15,
    "qs_pg:photos_9k":1,
    "qs_pg:photos_9r":2,
    "qs_pg:photos_all":72,
    "qs_pg:photos_sr":2,
    "qs_pg:pop_sr":0,
    "qs_pg:qs_pg_placetype":"locality",
    "qs_pg:qs_pg_placetype_gp":"Town",
    "qs_pg:woe_adm0":23424925,
    "woe:adm0_id":23424925,
    "woe:name_adm0":"Portugal",
    "woe:name_adm1":"Bragan\u00e7a",
    "woe:placetype":"Town",
    "wof:name":"Rebordelo",
    "wof:placetype":"locality"
},
  "geometry": {"coordinates":[-7.1623,41.73907],"type":"Point"}
}