{
  "type": "Feature",
  "properties": {
    "gn:admin1_code":"11",
    "gn:admin2_code":"0914",
    "gn:admin3_code":"91412.0",
    "gn:asciiname":"Tomadias",
    "gn:country_code":"PT",
    "gn:dem":476,
    "gn:feature_class":"P",
    "gn:feature_code":"PPL",
    "gn:name":"Tomadias",
    "gn:population":0,
    "gn:timezone":"Europe/Lisbon",
    "iso:country":"PT",
    "wof:name":"Tomadias",
    "wof:placetype":"locality"
},
  "geometry": {"coordinates":[-7.13389,40.97444],"type":"Point"}
}