{
  "type": "Feature",
  "properties": {
    "gn:admin1_code":"03",
    "gn:admin2_code":"0202",
    "gn:admin3_code":"20203.0",
    "gn:asciiname":"A do Neves",
    "gn:country_code":"PT",
    "gn:dem":265,
    "gn:feature_class":"P",
    "gn:feature_code":"PPL",
    "gn:name":"A do Neves",
    "gn:population":0,
    "gn:timezone":"Europe/Lisbon",
    "iso:country":"PT",
    "wof:name":"A do Neves",
    "wof:placetype":"locality"
},
  "geometry": {"coordinates":[-8.08498,37.57944000000001],"type":"Point"}
}