{
  "type": "Feature",
  "properties": {
    "gn:admin1_code":"16",
    "gn:admin2_code":"1214",
    "gn:admin3_code":"121407.0",
    "gn:asciiname":"Valinho",
    "gn:country_code":"PT",
    "gn:dem":412,
    "gn:feature_class":"P",
    "gn:feature_code":"PPL",
    "gn:name":"Valinho",
    "gn:population":0,
    "gn:timezone":"Europe/Lisbon",
    "iso:country":"PT",
    "wof:name":"Valinho",
    "wof:placetype":"locality"
},
  "geometry": {"coordinates":[-7.26667,39.28333],"type":"Point"}
}