{
  "type": "Feature",
  "properties": {
    "gn:admin1_code":"22.0",
    "gn:admin2_code":"1823",
    "gn:admin3_code":"182317.0",
    "gn:asciiname":"Pindelo",
    "gn:country_code":"PT",
    "gn:dem":376,
    "gn:feature_class":"P",
    "gn:feature_code":"PPL",
    "gn:name":"Pindelo",
    "gn:population":0,
    "gn:timezone":"Europe/Lisbon",
    "iso:country":"PT",
    "wof:name":"Pindelo",
    "wof:placetype":"locality"
},
  "geometry": {"coordinates":[-7.93648,40.58034],"type":"Point"}
}