{
  "type": "Feature",
  "properties": {
    "gn:admin1_code":"11.0",
    "gn:admin2_code":"0912",
    "gn:admin3_code":"91227.0",
    "gn:asciiname":"Barreosa",
    "gn:country_code":"PT",
    "gn:dem":369,
    "gn:feature_class":"P",
    "gn:feature_code":"PPL",
    "gn:name":"Barreosa",
    "gn:population":0,
    "gn:timezone":"Europe/Lisbon",
    "iso:country":"PT",
    "wof:name":"Barreosa",
    "wof:placetype":"locality"
},
  "geometry": {"coordinates":[-7.75743,40.29253],"type":"Point"}
}