{
  "type": "Feature",
  "properties": {
    "gn:admin1_code":"21.0",
    "gn:admin2_code":"1707",
    "gn:admin3_code":"170701.0",
    "gn:asciiname":"Martim",
    "gn:country_code":"PT",
    "gn:dem":372,
    "gn:feature_class":"P",
    "gn:feature_code":"PPL",
    "gn:name":"Martim",
    "gn:population":0,
    "gn:timezone":"Europe/Lisbon",
    "iso:country":"PT",
    "wof:name":"Martim",
    "wof:placetype":"locality"
},
  "geometry": {"coordinates":[-7.40137,41.36792],"type":"Point"}
}