{
  "type": "Feature",
  "properties": {
    "gn:admin1_code":"22",
    "gn:admin2_code":"1817",
    "gn:admin3_code":"181708.0",
    "gn:asciiname":"Soitos de Golfar",
    "gn:country_code":"PT",
    "gn:dem":638,
    "gn:feature_class":"P",
    "gn:feature_code":"PPL",
    "gn:name":"Soitos de Golfar",
    "gn:population":0,
    "gn:timezone":"Europe/Lisbon",
    "iso:country":"PT",
    "wof:name":"Soitos de Golfar",
    "wof:placetype":"locality"
},
  "geometry": {"coordinates":[-7.6191,40.75476],"type":"Point"}
}