{
  "type": "Feature",
  "properties": {
    "gn:admin1_code":"10.0",
    "gn:admin2_code":"3108",
    "gn:admin3_code":"310803.0",
    "gn:asciiname":"Canico de Baixo",
    "gn:country_code":"PT",
    "gn:dem":58,
    "gn:feature_class":"P",
    "gn:feature_code":"PPL",
    "gn:name":"Cani\u00e7o de Baixo",
    "gn:population":0,
    "gn:timezone":"Atlantic/Madeira",
    "iso:country":"PT",
    "wof:name":"Canico de Baixo",
    "wof:placetype":"locality"
},
  "geometry": {"coordinates":[-16.83329,32.64245],"type":"Point"}
}