{
  "type": "Feature",
  "properties": {
    "gn:admin1_code":"13",
    "gn:admin2_code":"1009",
    "gn:admin3_code":"100922.0",
    "gn:asciiname":"Pedrome",
    "gn:country_code":"PT",
    "gn:dem":310,
    "gn:feature_class":"P",
    "gn:feature_code":"PPL",
    "gn:name":"Pedrome",
    "gn:population":0,
    "gn:timezone":"Europe/Lisbon",
    "iso:country":"PT",
    "wof:name":"Pedrome",
    "wof:placetype":"locality"
},
  "geometry": {"coordinates":[-8.67631,39.67528],"type":"Point"}
}