{
  "type": "Feature",
  "properties": {
    "gn:country":"PT",
    "gn:fcode":"PPL",
    "gn:population":0,
    "iso:country":"PT",
    "name:por_x_preferred":[
        "Aboim da N\u00f3brega"
    ],
    "name:por_x_variant":[
        "Aboim"
    ],
    "qs_pg:aaroncc":"PT",
    "qs_pg:gn_country":"PT",
    "qs_pg:gn_fcode":"PPL",
    "qs_pg:gn_pop":0,
    "qs_pg:name":"Aboim da N\u00f3brega",
    "qs_pg:name_adm0":"Portugal",
    "qs_pg:name_adm1":"Braga",
    "qs_pg:photos_9k":1,
    "qs_pg:photos_9r":1,
    "qs_pg:photos_all":1,
    "qs_pg:photos_sr":0,
    "qs_pg:pop_sr":0,
    "qs_pg:qs_pg_placetype":"locality",
    "qs_pg:qs_pg_placetype_gp":"Town",
    "qs_pg:woe_adm0":23424925,
    "woe:adm0_id":23424925,
    "woe:name_adm0":"Portugal",
    "woe:name_adm1":"Braga",
    "woe:placetype":"Town",
    "wof:name":"Aboim da N\u00f3brega",
    "wof:placetype":"locality",
    "wof:population":987
},
  "geometry": {"coordinates":[-8.39169,41.75206],"type":"Point"}
}