{
  "type": "Feature",
  "properties": {
    "gn:admin1_code":"22.0",
    "gn:admin2_code":"1805",
    "gn:admin3_code":"180505.0",
    "gn:asciiname":"Lagares",
    "gn:country_code":"PT",
    "gn:dem":65,
    "gn:feature_class":"P",
    "gn:feature_code":"PPL",
    "gn:name":"Lagares",
    "gn:population":0,
    "gn:timezone":"Europe/Lisbon",
    "iso:country":"PT",
    "wof:name":"Lagares",
    "wof:placetype":"locality"
},
  "geometry": {"coordinates":[-7.80248,41.15319],"type":"Point"}
}