{
  "type": "Feature",
  "properties": {
    "gn:admin1_code":"08",
    "gn:admin2_code":"0701",
    "gn:admin3_code":"70106.0",
    "gn:asciiname":"Vara",
    "gn:country_code":"PT",
    "gn:dem":263,
    "gn:feature_class":"P",
    "gn:feature_code":"PPL",
    "gn:name":"Vara",
    "gn:population":0,
    "gn:timezone":"Europe/Lisbon",
    "iso:country":"PT",
    "wof:name":"Vara",
    "wof:placetype":"locality"
},
  "geometry": {"coordinates":[-7.35523,38.74176],"type":"Point"}
}