{
  "type": "Feature",
  "properties": {
    "gn:admin1_code":"08",
    "gn:admin2_code":"0701",
    "gn:admin3_code":"70106.0",
    "gn:asciiname":"Vara",
    "gn:country_code":"PT",
    "gn:dem":263,
    "gn:feature_class":"P",
    "gn:feature_code":"PPL",
    "gn:name":"Vara",
    "gn:population":0,
    "gn:timezone":"Europe/Lisbon",
    "iso:country":"PT",
    "name:cat_x_preferred":[
        "Vara"
    ],
    "name:ceb_x_preferred":[
        "Vara"
    ],
    "name:deu_x_preferred":[
        "Vara"
    ],
    "name:epo_x_preferred":[
        "Vara"
    ],
    "name:est_x_preferred":[
        "Vara"
    ],
    "name:fin_x_preferred":[
        "Vara"
    ],
    "name:fra_x_preferred":[
        "Vara"
    ],
    "name:ita_x_preferred":[
        "Vara"
    ],
    "name:lim_x_preferred":[
        "Vara"
    ],
    "name:nld_x_preferred":[
        "Vara"
    ],
    "name:nno_x_preferred":[
        "Vara"
    ],
    "name:por_x_preferred":[
        "Vara"
    ],
    "name:ron_x_preferred":[
        "Vara"
    ],
    "name:rus_x_preferred":[
        "\u0412\u0430\u0440\u0430"
    ],
    "name:sco_x_preferred":[
        "Vara"
    ],
    "name:spa_x_preferred":[
        "Vara"
    ],
    "name:swe_x_preferred":[
        "Vara"
    ],
    "name:ukr_x_preferred":[
        "\u0412\u0430\u0440\u0430"
    ],
    "wof:name":"Vara",
    "wof:placetype":"locality"
},
  "geometry": {"coordinates":[-7.35523,38.74176],"type":"Point"}
}