{
  "type": "Feature",
  "properties": {
    "gn:admin1_code":"02",
    "gn:admin2_code":"0114",
    "gn:admin3_code":"11404.0",
    "gn:asciiname":"Vila Verde",
    "gn:country_code":"PT",
    "gn:dem":39,
    "gn:feature_class":"P",
    "gn:feature_code":"PPL",
    "gn:name":"Vila Verde",
    "gn:population":0,
    "gn:timezone":"Europe/Lisbon",
    "iso:country":"PT",
    "wof:name":"Vila Verde",
    "wof:placetype":"locality"
},
  "geometry": {"coordinates":[-8.51758,40.5174],"type":"Point"}
}