{
  "type": "Feature",
  "properties": {
    "gn:admin1_code":"18",
    "gn:admin2_code":"1411",
    "gn:admin3_code":"141107.0",
    "gn:asciiname":"Sobral",
    "gn:country_code":"PT",
    "gn:dem":311,
    "gn:feature_class":"P",
    "gn:feature_code":"PPL",
    "gn:name":"Sobral",
    "gn:population":0,
    "gn:timezone":"Europe/Lisbon",
    "iso:country":"PT",
    "wof:name":"Sobral",
    "wof:placetype":"locality"
},
  "geometry": {"coordinates":[-8.32534,39.66965],"type":"Point"}
}