{
  "type": "Feature",
  "properties": {
    "gn:admin1_code":"23.0",
    "gn:admin2_code":"4301",
    "gn:admin3_code":"430116.0",
    "gn:asciiname":"Sao Bartolomeu",
    "gn:country_code":"PT",
    "gn:dem":64,
    "gn:feature_class":"P",
    "gn:feature_code":"PPL",
    "gn:name":"S\u00e3o Bartolomeu",
    "gn:population":1983,
    "gn:timezone":"Atlantic/Azores",
    "iso:country":"PT",
    "name:und_x_variant":[
        "S\u00e3o Bartholomeu",
        "S\u00e3o Bartolomeu"
    ],
    "wof:name":"Sao Bartolomeu",
    "wof:placetype":"locality",
    "wof:population":1983
},
  "geometry": {"coordinates":[-27.29349,38.67491],"type":"Point"}
}