{
  "type": "Feature",
  "properties": {
    "gn:admin1_code":"03",
    "gn:admin2_code":"0211",
    "gn:admin3_code":"21113.0",
    "gn:asciiname":"Fornalhas",
    "gn:country_code":"PT",
    "gn:dem":85,
    "gn:feature_class":"P",
    "gn:feature_code":"PPL",
    "gn:name":"Fornalhas",
    "gn:population":0,
    "gn:timezone":"Europe/Lisbon",
    "iso:country":"PT",
    "wof:name":"Fornalhas",
    "wof:placetype":"locality"
},
  "geometry": {"coordinates":[-8.4452,37.83428],"type":"Point"}
}