{
  "type": "Feature",
  "properties": {
    "gn:admin1_code":"16",
    "gn:admin2_code":"1213",
    "gn:admin3_code":"121301.0",
    "gn:asciiname":"Monte da Torpada",
    "gn:country_code":"PT",
    "gn:dem":157,
    "gn:feature_class":"P",
    "gn:feature_code":"PPL",
    "gn:name":"Monte da Torpada",
    "gn:population":0,
    "gn:timezone":"Europe/Lisbon",
    "iso:country":"PT",
    "wof:name":"Monte da Torpada",
    "wof:placetype":"locality"
},
  "geometry": {"coordinates":[-8.0098,39.12875],"type":"Point"}
}