{
  "type": "Feature",
  "properties": {
    "gn:admin1_code":"09",
    "gn:admin2_code":"0801",
    "gn:admin3_code":"80103.0",
    "gn:asciiname":"Aroal",
    "gn:country_code":"PT",
    "gn:dem":121,
    "gn:feature_class":"P",
    "gn:feature_code":"PPL",
    "gn:name":"Aroal",
    "gn:population":0,
    "gn:timezone":"Europe/Lisbon",
    "iso:country":"PT",
    "wof:name":"Aroal",
    "wof:placetype":"locality"
},
  "geometry": {"coordinates":[-8.17063,37.14959],"type":"Point"}
}