{
  "type": "Feature",
  "properties": {
    "gn:gn_country":"PT",
    "gn:gn_fcode":"PPL",
    "gn:gn_pop":794,
    "gn:population":794,
    "iso:country":"PT",
    "name:eng_x_preferred":[
        "Carvoeiro"
    ],
    "name:rus_x_preferred":[
        "\u041a\u0430\u0440\u0432\u043e\u0435\u0439\u0440\u043e"
    ],
    "qs_pg:aaroncc":"PT",
    "qs_pg:gn_country":"PT",
    "qs_pg:gn_fcode":"PPL",
    "qs_pg:gn_pop":794,
    "qs_pg:name":"Carvoeiro",
    "qs_pg:name_adm0":"Portugal",
    "qs_pg:name_adm1":"Santar\u00e9m",
    "qs_pg:photos_9k":1,
    "qs_pg:photos_9r":1,
    "qs_pg:photos_all":5,
    "qs_pg:photos_sr":0,
    "qs_pg:pop_sr":2,
    "qs_pg:qs_pg_placetype":"locality",
    "qs_pg:qs_pg_placetype_gp":"Town",
    "qs_pg:woe_adm0":23424925,
    "woe:adm0_id":23424925,
    "woe:name_adm0":"Portugal",
    "woe:name_adm1":"Santar\u00e9m",
    "woe:placetype":"Town",
    "wof:name":"Carvoeiro",
    "wof:placetype":"locality",
    "wof:population":794
},
  "geometry": {"coordinates":[-7.92325,39.62472],"type":"Point"}
}