{
  "type": "Feature",
  "properties": {
    "gn:admin1_code":"22",
    "gn:admin2_code":"1823",
    "gn:admin3_code":"182304.0",
    "gn:asciiname":"Travanca Grande",
    "gn:country_code":"PT",
    "gn:dem":467,
    "gn:feature_class":"P",
    "gn:feature_code":"PPL",
    "gn:name":"Travanca Grande",
    "gn:population":0,
    "gn:timezone":"Europe/Lisbon",
    "iso:country":"PT",
    "wof:name":"Travanca Grande",
    "wof:placetype":"locality"
},
  "geometry": {"coordinates":[-7.96148,40.71989],"type":"Point"}
}