{
  "type": "Feature",
  "properties": {
    "gn:admin1_code":"18",
    "gn:admin2_code":"1407",
    "gn:admin3_code":"140706.0",
    "gn:asciiname":"Moinhola",
    "gn:country_code":"PT",
    "gn:dem":71,
    "gn:feature_class":"P",
    "gn:feature_code":"PPL",
    "gn:name":"Moinhola",
    "gn:population":0,
    "gn:timezone":"Europe/Lisbon",
    "iso:country":"PT",
    "wof:name":"Moinhola",
    "wof:placetype":"locality"
},
  "geometry": {"coordinates":[-8.37323,39.17714],"type":"Point"}
}