{
  "type": "Feature",
  "properties": {
    "gn:admin1_code":"04",
    "gn:admin2_code":"0308",
    "gn:admin3_code":"30826.0",
    "gn:asciiname":"Quintais",
    "gn:country_code":"PT",
    "gn:dem":252,
    "gn:feature_class":"P",
    "gn:feature_code":"PPL",
    "gn:name":"Quint\u00e3is",
    "gn:population":0,
    "gn:timezone":"Europe/Lisbon",
    "iso:country":"PT",
    "wof:name":"Quintais",
    "wof:placetype":"locality"
},
  "geometry": {"coordinates":[-8.39767,41.47157],"type":"Point"}
}