{
  "type": "Feature",
  "properties": {
    "gn:admin1_code":"07",
    "gn:admin2_code":"0612",
    "gn:admin3_code":"61201.0",
    "gn:asciiname":"Sanguessuga",
    "gn:country_code":"PT",
    "gn:dem":652,
    "gn:feature_class":"P",
    "gn:feature_code":"PPL",
    "gn:name":"Sanguessuga",
    "gn:population":0,
    "gn:timezone":"Europe/Lisbon",
    "iso:country":"PT",
    "wof:name":"Sanguessuga",
    "wof:placetype":"locality"
},
  "geometry": {"coordinates":[-7.89422,40.10385],"type":"Point"}
}