{
  "type": "Feature",
  "properties": {
    "gn:admin1_code":"14",
    "gn:admin2_code":"1114",
    "gn:admin3_code":"111403.0",
    "gn:asciiname":"Cachoeiras",
    "gn:country_code":"PT",
    "gn:dem":109,
    "gn:feature_class":"P",
    "gn:feature_code":"PPL",
    "gn:name":"Cachoeiras",
    "gn:population":0,
    "gn:timezone":"Europe/Lisbon",
    "iso:country":"PT",
    "name:ceb_x_preferred":[
        "Cachoeiras"
    ],
    "name:swe_x_preferred":[
        "Cachoeiras"
    ],
    "wof:name":"Cachoeiras",
    "wof:placetype":"locality"
},
  "geometry": {"coordinates":[-9.01873,38.98491],"type":"Point"}
}