{
  "type": "Feature",
  "properties": {
    "gn:admin1_code":"7.0",
    "gn:admin2_code":"0617",
    "gn:admin3_code":"61703.0",
    "gn:asciiname":"Abraveia",
    "gn:country_code":"PT",
    "gn:dem":182,
    "gn:feature_class":"P",
    "gn:feature_code":"PPL",
    "gn:name":"Abraveia",
    "gn:population":0,
    "gn:timezone":"Europe/Lisbon",
    "iso:country":"PT",
    "wof:name":"Abraveia",
    "wof:placetype":"locality"
},
  "geometry": {"coordinates":[-8.27773,40.19613],"type":"Point"}
}