{
  "type": "Feature",
  "properties": {
    "gn:admin1_code":"18",
    "gn:admin2_code":"1418",
    "gn:admin3_code":"141815.0",
    "gn:asciiname":"Eira do Chao",
    "gn:country_code":"PT",
    "gn:dem":227,
    "gn:feature_class":"P",
    "gn:feature_code":"PPL",
    "gn:name":"Eira do Ch\u00e3o",
    "gn:population":0,
    "gn:timezone":"Europe/Lisbon",
    "iso:country":"PT",
    "wof:name":"Eira do Chao",
    "wof:placetype":"locality"
},
  "geometry": {"coordinates":[-8.26197,39.58991],"type":"Point"}
}