{
  "type": "Feature",
  "properties": {
    "gn:admin1_code":"11.0",
    "gn:admin2_code":"0910",
    "gn:admin3_code":"91005.0",
    "gn:asciiname":"Bouca Cova",
    "gn:country_code":"PT",
    "gn:dem":588,
    "gn:feature_class":"P",
    "gn:feature_code":"PPL",
    "gn:name":"Bou\u00e7a Cova",
    "gn:population":0,
    "gn:timezone":"Europe/Lisbon",
    "iso:country":"PT",
    "wof:name":"Bouca Cova",
    "wof:placetype":"locality"
},
  "geometry": {"coordinates":[-7.2407,40.69935],"type":"Point"}
}