{
  "type": "Feature",
  "properties": {
    "gn:country":"PT",
    "gn:fcode":"PPL",
    "gn:population":0,
    "iso:country":"PT",
    "name:ast_x_preferred":[
        "Freixianda"
    ],
    "name:ceb_x_preferred":[
        "Freixianda"
    ],
    "name:deu_x_preferred":[
        "Freixianda"
    ],
    "name:eng_x_preferred":[
        "Freixianda"
    ],
    "name:fra_x_preferred":[
        "Freixianda"
    ],
    "name:ita_x_preferred":[
        "Freixianda"
    ],
    "name:kaz_x_preferred":[
        "\u0424\u0440\u0435\u0439\u0448\u0438\u0430\u043d\u0434\u0430"
    ],
    "name:msa_x_preferred":[
        "Freixianda"
    ],
    "name:nan_x_preferred":[
        "Freixianda"
    ],
    "name:nld_x_preferred":[
        "Freixianda"
    ],
    "name:por_x_preferred":[
        "Freixianda"
    ],
    "name:rus_x_preferred":[
        "\u0424\u0440\u0435\u0439\u0448\u0438\u0430\u043d\u0434\u0430"
    ],
    "name:spa_x_preferred":[
        "Freixianda"
    ],
    "name:tur_x_preferred":[
        "Freixianda"
    ],
    "qs_pg:aaroncc":"PT",
    "qs_pg:gn_country":"PT",
    "qs_pg:gn_fcode":"PPL",
    "qs_pg:gn_pop":0,
    "qs_pg:name":"Freixianda",
    "qs_pg:name_adm0":"Portugal",
    "qs_pg:name_adm1":"Santar\u00e9m",
    "qs_pg:photos_9k":1,
    "qs_pg:photos_9r":1,
    "qs_pg:photos_all":2,
    "qs_pg:photos_sr":0,
    "qs_pg:pop_sr":0,
    "qs_pg:qs_pg_placetype":"locality",
    "qs_pg:qs_pg_placetype_gp":"Town",
    "qs_pg:woe_adm0":23424925,
    "woe:adm0_id":23424925,
    "woe:name_adm0":"Portugal",
    "woe:name_adm1":"Santar\u00e9m",
    "woe:placetype":"Town",
    "wof:name":"Freixianda",
    "wof:placetype":"locality"
},
  "geometry": {"coordinates":[-8.45882,39.75947],"type":"Point"}
}