{
  "type": "Feature",
  "properties": {
    "gn:admin1_code":"09",
    "gn:admin2_code":"0804",
    "gn:admin3_code":"80403.0",
    "gn:asciiname":"Funchosa",
    "gn:country_code":"PT",
    "gn:dem":209,
    "gn:feature_class":"P",
    "gn:feature_code":"PPL",
    "gn:name":"Funchosa",
    "gn:population":0,
    "gn:timezone":"Europe/Lisbon",
    "iso:country":"PT",
    "wof:name":"Funchosa",
    "wof:placetype":"locality"
},
  "geometry": {"coordinates":[-7.6178,37.30093],"type":"Point"}
}