{
  "type": "Feature",
  "properties": {
    "gn:admin1_code":"20.0",
    "gn:admin2_code":"1607",
    "gn:admin3_code":"160713.0",
    "gn:asciiname":"Portal",
    "gn:country_code":"PT",
    "gn:dem":145,
    "gn:feature_class":"P",
    "gn:feature_code":"PPL",
    "gn:name":"Portal",
    "gn:population":0,
    "gn:timezone":"Europe/Lisbon",
    "iso:country":"PT",
    "wof:name":"Portal",
    "wof:placetype":"locality"
},
  "geometry": {"coordinates":[-8.5709,41.80376],"type":"Point"}
}