{
  "type": "Feature",
  "properties": {
    "gn:admin1_code":"4.0",
    "gn:admin2_code":"0303",
    "gn:admin3_code":"30319.0",
    "gn:asciiname":"Bela Vista",
    "gn:country_code":"PT",
    "gn:dem":247,
    "gn:feature_class":"P",
    "gn:feature_code":"PPL",
    "gn:name":"Bela Vista",
    "gn:population":0,
    "gn:timezone":"Europe/Lisbon",
    "iso:country":"PT",
    "name:ukr_x_preferred":[
        "\u0411\u0435\u043b\u0430-\u0412\u0456\u0441\u0442\u0430"
    ],
    "wof:name":"Bela Vista",
    "wof:placetype":"locality"
},
  "geometry": {"coordinates":[-8.37568,41.57145],"type":"Point"}
}