{
  "type": "Feature",
  "properties": {
    "gn:admin1_code":"20.0",
    "gn:admin2_code":"1609",
    "gn:admin3_code":"160906.0",
    "gn:asciiname":"Capareiros",
    "gn:country_code":"PT",
    "gn:dem":81,
    "gn:feature_class":"P",
    "gn:feature_code":"PPL",
    "gn:name":"Capareiros",
    "gn:population":0,
    "gn:timezone":"Europe/Lisbon",
    "iso:country":"PT",
    "wof:name":"Capareiros",
    "wof:placetype":"locality"
},
  "geometry": {"coordinates":[-8.68333,41.65],"type":"Point"}
}