{
  "type": "Feature",
  "properties": {
    "gn:admin1_code":"13",
    "gn:admin2_code":"1007",
    "gn:admin3_code":"100701.0",
    "gn:asciiname":"Sarnadas",
    "gn:country_code":"PT",
    "gn:dem":633,
    "gn:feature_class":"P",
    "gn:feature_code":"PPL",
    "gn:name":"Sarnadas",
    "gn:population":0,
    "gn:timezone":"Europe/Lisbon",
    "iso:country":"PT",
    "wof:name":"Sarnadas",
    "wof:placetype":"locality"
},
  "geometry": {"coordinates":[-8.18774,40.05467],"type":"Point"}
}