{
  "type": "Feature",
  "properties": {
    "gn:country":"PT",
    "gn:fcode":"PPL",
    "gn:population":0,
    "iso:country":"PT",
    "name:ast_x_preferred":[
        "Espinheiro"
    ],
    "name:ceb_x_preferred":[
        "Espinheiro"
    ],
    "name:che_x_preferred":[
        "\u042d\u0448\u043f\u0438\u043d\u044c\u0435\u0439\u0440\u0443"
    ],
    "name:deu_x_preferred":[
        "Espinheiro"
    ],
    "name:eng_x_preferred":[
        "Espinheiro"
    ],
    "name:fra_x_preferred":[
        "Espinheiro"
    ],
    "name:nld_x_preferred":[
        "Espinheiro"
    ],
    "name:por_x_preferred":[
        "Espinheiro"
    ],
    "name:rus_x_preferred":[
        "\u042d\u0448\u043f\u0438\u043d\u044c\u0435\u0439\u0440\u0443"
    ],
    "name:spa_x_preferred":[
        "Espinheiro"
    ],
    "name:tat_x_preferred":[
        "\u042d\u0448\u043f\u0438\u043d\u044c\u0435\u0439\u0440\u0443"
    ],
    "qs_pg:aaroncc":"PT",
    "qs_pg:gn_country":"PT",
    "qs_pg:gn_fcode":"PPL",
    "qs_pg:gn_pop":0,
    "qs_pg:name":"Espinheiro",
    "qs_pg:name_adm0":"Portugal",
    "qs_pg:name_adm1":"Santar\u00e9m",
    "qs_pg:photos_9r":0,
    "qs_pg:photos_sr":0,
    "qs_pg:pop_sr":0,
    "qs_pg:qs_pg_placetype":"locality",
    "qs_pg:qs_pg_placetype_gp":"Town",
    "qs_pg:woe_adm0":23424925,
    "woe:adm0_id":23424925,
    "woe:name_adm0":"Portugal",
    "woe:name_adm1":"Santar\u00e9m",
    "woe:placetype":"Town",
    "wof:name":"Espinheiro",
    "wof:placetype":"locality"
},
  "geometry": {"coordinates":[-8.73859,39.42094],"type":"Point"}
}