{
  "type": "Feature",
  "properties": {
    "gn:admin1_code":"2.0",
    "gn:admin2_code":"0109",
    "gn:admin3_code":"10918.0",
    "gn:asciiname":"Lapa de Cima",
    "gn:country_code":"PT",
    "gn:dem":89,
    "gn:feature_class":"P",
    "gn:feature_code":"PPL",
    "gn:name":"Lapa de Cima",
    "gn:population":0,
    "gn:timezone":"Europe/Lisbon",
    "iso:country":"PT",
    "wof:name":"Lapa de Cima",
    "wof:placetype":"locality"
},
  "geometry": {"coordinates":[-8.59916,40.98919],"type":"Point"}
}