{
  "type": "Feature",
  "properties": {
    "gn:admin1_code":"2.0",
    "gn:admin2_code":"0114",
    "gn:admin3_code":"11404.0",
    "gn:asciiname":"Cercal de Baixo",
    "gn:country_code":"PT",
    "gn:dem":16,
    "gn:feature_class":"P",
    "gn:feature_code":"PPL",
    "gn:name":"Cercal de Baixo",
    "gn:population":0,
    "gn:timezone":"Europe/Lisbon",
    "iso:country":"PT",
    "wof:name":"Cercal de Baixo",
    "wof:placetype":"locality"
},
  "geometry": {"coordinates":[-8.47293,40.52258],"type":"Point"}
}