{
  "type": "Feature",
  "properties": {
    "gn:admin1_code":"07",
    "gn:admin2_code":"0612",
    "gn:admin3_code":"61201.0",
    "gn:asciiname":"Vale de Mosqueiro",
    "gn:country_code":"PT",
    "gn:dem":677,
    "gn:feature_class":"P",
    "gn:feature_code":"PPL",
    "gn:name":"Vale de Mosqueiro",
    "gn:population":0,
    "gn:timezone":"Europe/Lisbon",
    "iso:country":"PT",
    "wof:name":"Vale de Mosqueiro",
    "wof:placetype":"locality"
},
  "geometry": {"coordinates":[-7.86185,40.07135],"type":"Point"}
}