{
  "type": "Feature",
  "properties": {
    "gn:admin1_code":"02",
    "gn:admin2_code":"0101",
    "gn:admin3_code":"10115.0",
    "gn:asciiname":"Povoa da Igreja",
    "gn:country_code":"PT",
    "gn:dem":57,
    "gn:feature_class":"P",
    "gn:feature_code":"PPL",
    "gn:name":"P\u00f3voa da Igreja",
    "gn:population":0,
    "gn:timezone":"Europe/Lisbon",
    "iso:country":"PT",
    "wof:name":"Povoa da Igreja",
    "wof:placetype":"locality"
},
  "geometry": {"coordinates":[-8.46667,40.56667],"type":"Point"}
}