{
  "type": "Feature",
  "properties": {
    "gn:admin1_code":"22.0",
    "gn:admin2_code":"1821",
    "gn:admin3_code":"182123.0",
    "gn:asciiname":"Carvalhal",
    "gn:country_code":"PT",
    "gn:dem":308,
    "gn:feature_class":"P",
    "gn:feature_code":"PPL",
    "gn:name":"Carvalhal",
    "gn:population":0,
    "gn:timezone":"Europe/Lisbon",
    "iso:country":"PT",
    "name:ceb_x_preferred":[
        "Carvalhal"
    ],
    "name:deu_x_preferred":[
        "Carvalhal"
    ],
    "name:fra_x_preferred":[
        "Carvalhal"
    ],
    "name:kaz_x_preferred":[
        "\u041a\u0430\u0440\u0432\u0430\u043b\u044c\u044f\u043b"
    ],
    "name:nld_x_preferred":[
        "Carvalhal"
    ],
    "name:por_x_preferred":[
        "Carvalhal"
    ],
    "name:rus_x_preferred":[
        "\u041a\u0430\u0440\u0432\u0430\u043b\u044c\u044f\u043b"
    ],
    "name:spa_x_preferred":[
        "Carvalhal"
    ],
    "name:ukr_x_preferred":[
        "\u041a\u0430\u0440\u0432\u0430\u043b\u044f\u043b"
    ],
    "wof:name":"Carvalhal",
    "wof:placetype":"locality"
},
  "geometry": {"coordinates":[-8.09157,40.51028],"type":"Point"}
}