{
  "type": "Feature",
  "properties": {
    "gn:admin1_code":"18",
    "gn:admin2_code":"1414",
    "gn:admin3_code":"141407.0",
    "gn:asciiname":"Vale de Marinhos",
    "gn:country_code":"PT",
    "gn:dem":50,
    "gn:feature_class":"P",
    "gn:feature_code":"PPL",
    "gn:name":"Vale de Marinhos",
    "gn:population":0,
    "gn:timezone":"Europe/Lisbon",
    "iso:country":"PT",
    "wof:name":"Vale de Marinhos",
    "wof:placetype":"locality"
},
  "geometry": {"coordinates":[-8.83268,39.34721],"type":"Point"}
}