{
  "type": "Feature",
  "properties": {
    "gn:admin1_code":"7.0",
    "gn:admin2_code":"0603",
    "gn:admin3_code":"60324.0",
    "gn:asciiname":"Castanheira",
    "gn:country_code":"PT",
    "gn:dem":57,
    "gn:feature_class":"P",
    "gn:feature_code":"PPL",
    "gn:name":"Castanheira",
    "gn:population":0,
    "gn:timezone":"Europe/Lisbon",
    "iso:country":"PT",
    "name:bpy_x_preferred":[
        "\u0995\u09be\u09b8\u09cd\u099f\u09be\u09a8\u09b9\u09c7\u0987\u09b0\u09be"
    ],
    "name:ceb_x_preferred":[
        "Castanheira"
    ],
    "name:deu_x_preferred":[
        "Castanheira"
    ],
    "name:fra_x_preferred":[
        "Castanheira"
    ],
    "name:nld_x_preferred":[
        "Castanheira"
    ],
    "name:por_x_preferred":[
        "Castanheira"
    ],
    "name:rus_x_preferred":[
        "\u041a\u0430\u0448\u0442\u0430\u043d\u044c\u0435\u0439\u0440\u0430"
    ],
    "name:swe_x_preferred":[
        "Castanheira"
    ],
    "name:tur_x_preferred":[
        "Castanheira"
    ],
    "name:ukr_x_preferred":[
        "\u041a\u0430\u0448\u0442\u0430\u043d\u044c\u0454\u0439\u0440\u0430"
    ],
    "wof:name":"Castanheira",
    "wof:placetype":"locality"
},
  "geometry": {"coordinates":[-8.54153,40.22878],"type":"Point"}
}