{
  "type": "Feature",
  "properties": {
    "gn:admin1_code":"2.0",
    "gn:admin2_code":"0104",
    "gn:admin3_code":"10411.0",
    "gn:asciiname":"Orbida",
    "gn:country_code":"PT",
    "gn:dem":288,
    "gn:feature_class":"P",
    "gn:feature_code":"PPL",
    "gn:name":"\u00d3rbida",
    "gn:population":0,
    "gn:timezone":"Europe/Lisbon",
    "iso:country":"PT",
    "wof:name":"Orbida",
    "wof:placetype":"locality"
},
  "geometry": {"coordinates":[-8.42008,40.96311],"type":"Point"}
}