{
  "type": "Feature",
  "properties": {
    "gn:admin1_code":"2.0",
    "gn:admin2_code":"0103",
    "gn:admin3_code":"10314.0",
    "gn:asciiname":"Paredes do Bairro",
    "gn:country_code":"PT",
    "gn:dem":88,
    "gn:feature_class":"P",
    "gn:feature_code":"PPL",
    "gn:name":"Paredes do Bairro",
    "gn:population":0,
    "gn:timezone":"Europe/Lisbon",
    "iso:country":"PT",
    "wof:name":"Paredes do Bairro",
    "wof:placetype":"locality"
},
  "geometry": {"coordinates":[-8.50661,40.45032],"type":"Point"}
}