{
  "type": "Feature",
  "properties": {
    "gn:admin1_code":"22.0",
    "gn:admin2_code":"1813",
    "gn:admin3_code":"181314.0",
    "gn:asciiname":"Casal",
    "gn:country_code":"PT",
    "gn:dem":556,
    "gn:feature_class":"P",
    "gn:feature_code":"PPL",
    "gn:name":"Casal",
    "gn:population":0,
    "gn:timezone":"Europe/Lisbon",
    "iso:country":"PT",
    "name:nld_x_preferred":[
        "Casal"
    ],
    "name:swe_x_preferred":[
        "Casal"
    ],
    "wof:name":"Casal",
    "wof:placetype":"locality"
},
  "geometry": {"coordinates":[-7.88004,41.11447],"type":"Point"}
}