{
  "type": "Feature",
  "properties": {
    "gn:admin1_code":"4.0",
    "gn:admin2_code":"0303",
    "gn:admin3_code":"30361.0",
    "gn:asciiname":"Celeiroz",
    "gn:country_code":"PT",
    "gn:dem":162,
    "gn:feature_class":"P",
    "gn:feature_code":"PPL",
    "gn:name":"Celeiroz",
    "gn:population":0,
    "gn:timezone":"Europe/Lisbon",
    "iso:country":"PT",
    "wof:name":"Celeiroz",
    "wof:placetype":"locality"
},
  "geometry": {"coordinates":[-8.46169,41.51152],"type":"Point"}
}