{
  "type": "Feature",
  "properties": {
    "gn:admin1_code":"02",
    "gn:admin2_code":"0119",
    "gn:admin3_code":"11901.0",
    "gn:asciiname":"Souto Mau",
    "gn:country_code":"PT",
    "gn:dem":387,
    "gn:feature_class":"P",
    "gn:feature_code":"PPL",
    "gn:name":"Souto Mau",
    "gn:population":0,
    "gn:timezone":"Europe/Lisbon",
    "iso:country":"PT",
    "wof:name":"Souto Mau",
    "wof:placetype":"locality"
},
  "geometry": {"coordinates":[-8.27895,40.78782],"type":"Point"}
}