{
  "type": "Feature",
  "properties": {
    "gn:admin1_code":"21.0",
    "gn:admin2_code":"1708",
    "gn:admin3_code":"170810.0",
    "gn:asciiname":"Escavedas",
    "gn:country_code":"PT",
    "gn:dem":217,
    "gn:feature_class":"P",
    "gn:feature_code":"PPL",
    "gn:name":"Esc\u00e1vedas",
    "gn:population":0,
    "gn:timezone":"Europe/Lisbon",
    "iso:country":"PT",
    "wof:name":"Escavedas",
    "wof:placetype":"locality"
},
  "geometry": {"coordinates":[-7.73028,41.20322],"type":"Point"}
}