{
  "type": "Feature",
  "properties": {
    "gn:country":"PT",
    "gn:fcode":"PPL",
    "gn:population":0,
    "iso:country":"PT",
    "name:ceb_x_preferred":[
        "Jardim da Serra"
    ],
    "name:deu_x_preferred":[
        "Jardim da Serra"
    ],
    "name:fra_x_preferred":[
        "Jardim da Serra"
    ],
    "name:kaz_x_preferred":[
        "\u0416\u0430\u0440\u0434\u0438\u043d-\u0434\u0430-\u0421\u0435\u0440\u0440\u0430"
    ],
    "name:por_x_preferred":[
        "Jardim da Serra"
    ],
    "name:rus_x_preferred":[
        "\u0416\u0430\u0440\u0434\u0438\u043d-\u0434\u0430-\u0421\u0435\u0440\u0440\u0430"
    ],
    "name:spa_x_preferred":[
        "Jardim da Serra"
    ],
    "qs_pg:aaroncc":"PT",
    "qs_pg:gn_country":"PT",
    "qs_pg:gn_fcode":"PPL",
    "qs_pg:gn_pop":0,
    "qs_pg:name":"Jardim da Serra",
    "qs_pg:name_adm0":"Portugal",
    "qs_pg:name_adm1":"Madeira",
    "qs_pg:photos":5,
    "qs_pg:photos_1k":1,
    "qs_pg:photos_9k":1,
    "qs_pg:photos_9r":1,
    "qs_pg:photos_all":5,
    "qs_pg:photos_sr":1,
    "qs_pg:pop_sr":0,
    "qs_pg:qs_pg_placetype":"locality",
    "qs_pg:qs_pg_placetype_gp":"Town",
    "qs_pg:woe_adm0":23424925,
    "woe:adm0_id":23424925,
    "woe:name_adm0":"Portugal",
    "woe:name_adm1":"Madeira",
    "woe:placetype":"Town",
    "wof:name":"Jardim da Serra",
    "wof:placetype":"locality"
},
  "geometry": {"coordinates":[-16.99392,32.69687],"type":"Point"}
}