{
  "type": "Feature",
  "properties": {
    "gn:admin1_code":"2.0",
    "gn:admin2_code":"0101",
    "gn:admin3_code":"10107.0",
    "gn:asciiname":"Massadas",
    "gn:country_code":"PT",
    "gn:dem":173,
    "gn:feature_class":"P",
    "gn:feature_code":"PPL",
    "gn:name":"Massadas",
    "gn:population":0,
    "gn:timezone":"Europe/Lisbon",
    "iso:country":"PT",
    "wof:name":"Massadas",
    "wof:placetype":"locality"
},
  "geometry": {"coordinates":[-8.36672,40.57761],"type":"Point"}
}