{
  "type": "Feature",
  "properties": {
    "gn:gn_country":"PT",
    "gn:gn_fcode":"PPL",
    "gn:gn_pop":0,
    "iso:country":"PT",
    "name:dut_x_preferred":[
        "Lovelhe"
    ],
    "name:eng_x_preferred":[
        "Lovelhe"
    ],
    "name:fre_x_preferred":[
        "Lovelhe"
    ],
    "name:ger_x_preferred":[
        "Lovelhe"
    ],
    "name:kaz_x_preferred":[
        "\u041b\u043e\u0432\u0435\u043b\u044c\u0435"
    ],
    "name:por_x_preferred":[
        "Lovelhe"
    ],
    "name:rus_x_preferred":[
        "\u041b\u043e\u0432\u0435\u043b\u044c\u0435"
    ],
    "name:spa_x_preferred":[
        "Lovelhe"
    ],
    "name:tur_x_preferred":[
        "Lovelhe"
    ],
    "qs_pg:aaroncc":"PT",
    "qs_pg:gn_country":"PT",
    "qs_pg:gn_fcode":"PPL",
    "qs_pg:gn_pop":0,
    "qs_pg:name":"Lovelhe",
    "qs_pg:name_adm0":"Portugal",
    "qs_pg:name_adm1":"Viana do Castelo",
    "qs_pg:photos":53,
    "qs_pg:photos_1k":11,
    "qs_pg:photos_9k":1,
    "qs_pg:photos_9r":2,
    "qs_pg:photos_all":53,
    "qs_pg:photos_sr":2,
    "qs_pg:pop_sr":0,
    "qs_pg:qs_pg_placetype":"locality",
    "qs_pg:qs_pg_placetype_gp":"Town",
    "qs_pg:woe_adm0":23424925,
    "woe:adm0_id":23424925,
    "woe:name_adm0":"Portugal",
    "woe:name_adm1":"Viana do Castelo",
    "woe:placetype":"Town",
    "wof:name":"Lovelhe",
    "wof:placetype":"locality"
},
  "geometry": {"coordinates":[-8.73577,41.95563],"type":"Point"}
}