{
  "type": "Feature",
  "properties": {
    "gn:admin1_code":"17",
    "gn:admin2_code":"1303",
    "gn:admin3_code":"130331.0",
    "gn:asciiname":"Vila Cova",
    "gn:country_code":"PT",
    "gn:dem":316,
    "gn:feature_class":"P",
    "gn:feature_code":"PPL",
    "gn:name":"Vila Cova",
    "gn:population":0,
    "gn:timezone":"Europe/Lisbon",
    "iso:country":"PT",
    "name:ceb_x_preferred":[
        "Vila Cova"
    ],
    "name:deu_x_preferred":[
        "Vila Cova"
    ],
    "name:fra_x_preferred":[
        "Vila Cova"
    ],
    "name:nld_x_preferred":[
        "Vila Cova"
    ],
    "name:por_x_preferred":[
        "Vila Cova"
    ],
    "name:rus_x_preferred":[
        "\u0412\u0438\u043b\u0430-\u041a\u043e\u0432\u0430"
    ],
    "name:spa_x_preferred":[
        "Vila Cova"
    ],
    "name:tur_x_preferred":[
        "Vila Cova"
    ],
    "name:ukr_x_preferred":[
        "\u0412\u0456\u043b\u0430-\u041a\u043e\u0432\u0430"
    ],
    "wof:name":"Vila Cova",
    "wof:placetype":"locality"
},
  "geometry": {"coordinates":[-8.15709,41.32412],"type":"Point"}
}