{
  "type": "Feature",
  "properties": {
    "gn:admin1_code":"17",
    "gn:admin2_code":"1303",
    "gn:admin3_code":"130331.0",
    "gn:asciiname":"Vila Cova",
    "gn:country_code":"PT",
    "gn:dem":316,
    "gn:feature_class":"P",
    "gn:feature_code":"PPL",
    "gn:name":"Vila Cova",
    "gn:population":0,
    "gn:timezone":"Europe/Lisbon",
    "iso:country":"PT",
    "wof:name":"Vila Cova",
    "wof:placetype":"locality"
},
  "geometry": {"coordinates":[-8.15709,41.32412],"type":"Point"}
}