{
  "type": "Feature",
  "properties": {
    "gn:admin1_code":"20.0",
    "gn:admin2_code":"1609",
    "gn:admin3_code":"160922.0",
    "gn:asciiname":"Paco",
    "gn:country_code":"PT",
    "gn:dem":129,
    "gn:feature_class":"P",
    "gn:feature_code":"PPL",
    "gn:name":"Pa\u00e7o",
    "gn:population":0,
    "gn:timezone":"Europe/Lisbon",
    "iso:country":"PT",
    "name:ita_x_preferred":[
        "Paco"
    ],
    "wof:name":"Paco",
    "wof:placetype":"locality"
},
  "geometry": {"coordinates":[-8.70974,41.66845],"type":"Point"}
}