{
  "type": "Feature",
  "properties": {
    "gn:admin1_code":"03",
    "gn:admin2_code":"0209",
    "gn:admin3_code":"20905.0",
    "gn:asciiname":"Monte Moreanes",
    "gn:country_code":"PT",
    "gn:dem":140,
    "gn:feature_class":"P",
    "gn:feature_code":"PPL",
    "gn:name":"Monte Moreanes",
    "gn:population":0,
    "gn:timezone":"Europe/Lisbon",
    "iso:country":"PT",
    "wof:name":"Monte Moreanes",
    "wof:placetype":"locality"
},
  "geometry": {"coordinates":[-7.56029,37.65005],"type":"Point"}
}