{
  "type": "Feature",
  "properties": {
    "gn:admin1_code":"20.0",
    "gn:admin2_code":"1605",
    "gn:admin3_code":"160517.0",
    "gn:asciiname":"Cabo",
    "gn:country_code":"PT",
    "gn:dem":493,
    "gn:feature_class":"P",
    "gn:feature_code":"PPL",
    "gn:name":"Cabo",
    "gn:population":0,
    "gn:timezone":"Europe/Lisbon",
    "iso:country":"PT",
    "wof:name":"Cabo",
    "wof:placetype":"locality"
},
  "geometry": {"coordinates":[-8.55394,41.95174],"type":"Point"}
}