{
  "type": "Feature",
  "properties": {
    "gn:admin1_code":"13",
    "gn:admin2_code":"1009",
    "gn:admin3_code":"100901.0",
    "gn:asciiname":"Coucinheira",
    "gn:country_code":"PT",
    "gn:dem":68,
    "gn:feature_class":"P",
    "gn:feature_code":"PPL",
    "gn:name":"Coucinheira",
    "gn:population":0,
    "gn:timezone":"Europe/Lisbon",
    "iso:country":"PT",
    "wof:name":"Coucinheira",
    "wof:placetype":"locality"
},
  "geometry": {"coordinates":[-8.88715,39.80414],"type":"Point"}
}