{
  "type": "Feature",
  "properties": {
    "gn:admin1_code":"21",
    "gn:admin2_code":"1706",
    "gn:admin3_code":"170620.0",
    "gn:asciiname":"Sendim",
    "gn:country_code":"PT",
    "gn:dem":1134,
    "gn:feature_class":"P",
    "gn:feature_code":"PPL",
    "gn:name":"Sendim",
    "gn:population":0,
    "gn:timezone":"Europe/Madrid",
    "iso:country":"PT",
    "wof:name":"Sendim",
    "wof:placetype":"locality"
},
  "geometry": {"coordinates":[-7.76297,41.89292],"type":"Point"}
}