{
  "type": "Feature",
  "properties": {
    "gn:admin1_code":"5.0",
    "gn:admin2_code":"0404",
    "gn:admin3_code":"40401.0",
    "gn:asciiname":"Fornos",
    "gn:country_code":"PT",
    "gn:dem":717,
    "gn:feature_class":"P",
    "gn:feature_code":"PPL",
    "gn:name":"Fornos",
    "gn:population":0,
    "gn:timezone":"Europe/Lisbon",
    "iso:country":"PT",
    "name:rus_x_preferred":[
        "\u0424\u043e\u0440\u043d\u0443\u0448"
    ],
    "name:ukr_x_preferred":[
        "\u0424\u043e\u0440\u043d\u0443\u0448"
    ],
    "name:zho_x_preferred":[
        "\u798f\u5c14\u52aa\u4ec0"
    ],
    "wof:name":"Fornos",
    "wof:placetype":"locality"
},
  "geometry": {"coordinates":[-6.75549,41.18771],"type":"Point"}
}