{
  "type": "Feature",
  "properties": {
    "gn:admin1_code":"13",
    "gn:asciiname":"Silveira Grande",
    "gn:country_code":"PT",
    "gn:dem":532,
    "gn:feature_class":"P",
    "gn:feature_code":"PPL",
    "gn:name":"Silveira Grande",
    "gn:population":0,
    "gn:timezone":"Europe/Lisbon",
    "iso:country":"PT",
    "wof:name":"Silveira Grande",
    "wof:placetype":"locality"
},
  "geometry": {"coordinates":[-8.29065,39.985],"type":"Point"}
}