{
  "type": "Feature",
  "properties": {
    "gn:admin1_code":"18",
    "gn:admin2_code":"1413",
    "gn:admin3_code":"141304.0",
    "gn:asciiname":"Capela",
    "gn:country_code":"PT",
    "gn:dem":329,
    "gn:feature_class":"P",
    "gn:feature_code":"PPL",
    "gn:name":"Capela",
    "gn:population":0,
    "gn:timezone":"Europe/Lisbon",
    "iso:country":"PT",
    "name:ceb_x_preferred":[
        "Capela"
    ],
    "name:deu_x_preferred":[
        "Capela"
    ],
    "name:fra_x_preferred":[
        "Capela"
    ],
    "name:ita_x_preferred":[
        "Capela"
    ],
    "name:nld_x_preferred":[
        "Capela"
    ],
    "name:nor_x_preferred":[
        "Capela"
    ],
    "name:por_x_preferred":[
        "Capela"
    ],
    "name:ron_x_preferred":[
        "Capela"
    ],
    "name:swe_x_preferred":[
        "Capela"
    ],
    "name:vol_x_preferred":[
        "Capela"
    ],
    "wof:name":"Capela",
    "wof:placetype":"locality"
},
  "geometry": {"coordinates":[-7.94362,39.64159],"type":"Point"}
}