{
  "type": "Feature",
  "properties": {
    "gn:admin1_code":"03",
    "gn:admin2_code":"0205",
    "gn:admin3_code":"20507.0",
    "gn:asciiname":"Pisoes",
    "gn:country_code":"PT",
    "gn:dem":80,
    "gn:feature_class":"P",
    "gn:feature_code":"PPL",
    "gn:name":"Pis\u00f5es",
    "gn:population":0,
    "gn:timezone":"Europe/Lisbon",
    "iso:country":"PT",
    "wof:name":"Pisoes",
    "wof:placetype":"locality"
},
  "geometry": {"coordinates":[-7.69334,37.96809],"type":"Point"}
}