{
  "type": "Feature",
  "properties": {
    "gn:gn_country":"PT",
    "gn:gn_fcode":"PPL",
    "gn:gn_pop":1016,
    "gn:population":1016,
    "iso:country":"PT",
    "name:arg_x_preferred":[
        "Faj\u00e3 da Ovelha"
    ],
    "name:ceb_x_preferred":[
        "Faj\u00e3 da Ovelha"
    ],
    "name:deu_x_preferred":[
        "Faj\u00e3 da Ovelha"
    ],
    "name:fra_x_preferred":[
        "Faj\u00e3 da Ovelha"
    ],
    "name:kaz_x_preferred":[
        "\u0424\u0430\u0436\u0430\u043d-\u0434\u0430-\u041e\u0432\u0435\u043b\u044c\u044f"
    ],
    "name:nld_x_preferred":[
        "Faj\u00e3 da Ovelha"
    ],
    "name:por_x_preferred":[
        "Faj\u00e3 da Ovelha"
    ],
    "name:rus_x_preferred":[
        "\u0424\u0430\u0436\u0430\u043d-\u0434\u0430-\u041e\u0432\u0435\u043b\u044c\u044f"
    ],
    "name:spa_x_preferred":[
        "Faj\u00e3 da Ovelha"
    ],
    "name:unk_x_variant":[
        "Faia da Ovelha"
    ],
    "qs_pg:aaroncc":"PT",
    "qs_pg:gn_country":"PT",
    "qs_pg:gn_fcode":"PPL",
    "qs_pg:gn_pop":1016,
    "qs_pg:name":"Faj\u00e3 da Ovelha",
    "qs_pg:name_adm0":"Portugal",
    "qs_pg:name_adm1":"Madeira",
    "qs_pg:photos":4,
    "qs_pg:photos_1k":1,
    "qs_pg:photos_9k":1,
    "qs_pg:photos_9r":1,
    "qs_pg:photos_all":4,
    "qs_pg:photos_sr":1,
    "qs_pg:pop_sr":3,
    "qs_pg:qs_pg_placetype":"locality",
    "qs_pg:qs_pg_placetype_gp":"Town",
    "qs_pg:woe_adm0":23424925,
    "woe:adm0_id":23424925,
    "woe:name_adm0":"Portugal",
    "woe:name_adm1":"Madeira",
    "woe:placetype":"Town",
    "wof:name":"Faj\u00e3 da Ovelha",
    "wof:placetype":"locality",
    "wof:population":1016
},
  "geometry": {"coordinates":[-17.23412,32.77457],"type":"Point"}
}