{
  "type": "Feature",
  "properties": {
    "gn:admin1_code":"04",
    "gn:admin2_code":"0307",
    "gn:admin3_code":"30723.0",
    "gn:asciiname":"Regadas",
    "gn:country_code":"PT",
    "gn:dem":469,
    "gn:feature_class":"P",
    "gn:feature_code":"PPL",
    "gn:name":"Regadas",
    "gn:population":0,
    "gn:timezone":"Europe/Lisbon",
    "iso:country":"PT",
    "wof:name":"Regadas",
    "wof:placetype":"locality"
},
  "geometry": {"coordinates":[-8.15153,41.39909],"type":"Point"}
}