{
  "type": "Feature",
  "properties": {
    "gn:admin1_code":"7.0",
    "gn:admin2_code":"0611",
    "gn:admin3_code":"61113.0",
    "gn:asciiname":"Penalva de Alva",
    "gn:country_code":"PT",
    "gn:dem":282,
    "gn:feature_class":"P",
    "gn:feature_code":"PPL",
    "gn:name":"Penalva de Alva",
    "gn:population":0,
    "gn:timezone":"Europe/Lisbon",
    "iso:country":"PT",
    "wof:name":"Penalva de Alva",
    "wof:placetype":"locality"
},
  "geometry": {"coordinates":[-7.82852,40.33598],"type":"Point"}
}