{
  "type": "Feature",
  "properties": {
    "gn:admin1_code":"03",
    "gn:admin2_code":"0213",
    "gn:admin3_code":"21301.0",
    "gn:asciiname":"Aldeia Nova de Sao Bento",
    "gn:country_code":"PT",
    "gn:dem":250,
    "gn:feature_class":"P",
    "gn:feature_code":"PPL",
    "gn:name":"Aldeia Nova de S\u00e3o Bento",
    "gn:population":4040,
    "gn:timezone":"Europe/Lisbon",
    "iso:country":"PT",
    "name:und_x_variant":[
        "S\u00e3o Bento",
        "Aldeia Nova",
        "Aldeia Nova de S\u00e3o Bento"
    ],
    "wof:name":"Aldeia Nova de Sao Bento",
    "wof:placetype":"locality",
    "wof:population":4040
},
  "geometry": {"coordinates":[-7.40804,37.92603],"type":"Point"}
}