{
  "type": "Feature",
  "properties": {
    "gn:admin1_code":"2.0",
    "gn:admin2_code":"0103",
    "gn:admin3_code":"10315.0",
    "gn:asciiname":"Alpalhao",
    "gn:country_code":"PT",
    "gn:dem":57,
    "gn:feature_class":"P",
    "gn:feature_code":"PPL",
    "gn:name":"Alpalh\u00e3o",
    "gn:population":0,
    "gn:timezone":"Europe/Lisbon",
    "iso:country":"PT",
    "wof:name":"Alpalhao",
    "wof:placetype":"locality"
},
  "geometry": {"coordinates":[-8.44856,40.40242],"type":"Point"}
}