{
  "type": "Feature",
  "properties": {
    "gn:admin1_code":"16",
    "gn:admin2_code":"1202",
    "gn:admin3_code":"120202.0",
    "gn:asciiname":"Esperanca",
    "gn:country_code":"PT",
    "gn:dem":344,
    "gn:feature_class":"P",
    "gn:feature_code":"PPL",
    "gn:name":"Esperan\u00e7a",
    "gn:population":0,
    "gn:timezone":"Europe/Lisbon",
    "iso:country":"PT",
    "wof:name":"Esperanca",
    "wof:placetype":"locality"
},
  "geometry": {"coordinates":[-7.19466,39.16001],"type":"Point"}
}