{
  "type": "Feature",
  "properties": {
    "gn:admin1_code":"2.0",
    "gn:admin2_code":"0118",
    "gn:admin3_code":"11803.0",
    "gn:asciiname":"Fonte de Angiao",
    "gn:country_code":"PT",
    "gn:dem":49,
    "gn:feature_class":"P",
    "gn:feature_code":"PPL",
    "gn:name":"Fonte de Angi\u00e3o",
    "gn:population":0,
    "gn:timezone":"Europe/Lisbon",
    "iso:country":"PT",
    "wof:name":"Fonte de Angiao",
    "wof:placetype":"locality"
},
  "geometry": {"coordinates":[-8.67306,40.45051],"type":"Point"}
}