{
  "type": "Feature",
  "properties": {
    "gn:admin1_code":"07",
    "gn:admin2_code":"0603",
    "gn:admin3_code":"60331.0",
    "gn:asciiname":"Rios Frios",
    "gn:country_code":"PT",
    "gn:dem":44,
    "gn:feature_class":"P",
    "gn:feature_code":"PPL",
    "gn:name":"Rios Frios",
    "gn:population":0,
    "gn:timezone":"Europe/Lisbon",
    "iso:country":"PT",
    "wof:name":"Rios Frios",
    "wof:placetype":"locality"
},
  "geometry": {"coordinates":[-8.47489,40.27555],"type":"Point"}
}