{
  "type": "Feature",
  "properties": {
    "gn:admin1_code":"05",
    "gn:admin2_code":"0402",
    "gn:admin3_code":"40248.0",
    "gn:asciiname":"Vidoedo",
    "gn:country_code":"PT",
    "gn:dem":824,
    "gn:feature_class":"P",
    "gn:feature_code":"PPL",
    "gn:name":"Vidoedo",
    "gn:population":0,
    "gn:timezone":"Europe/Lisbon",
    "iso:country":"PT",
    "wof:name":"Vidoedo",
    "wof:placetype":"locality"
},
  "geometry": {"coordinates":[-6.83396,41.6941],"type":"Point"}
}