{
  "type": "Feature",
  "properties": {
    "gn:admin1_code":"18",
    "gn:admin2_code":"1406",
    "gn:admin3_code":"140601.0",
    "gn:asciiname":"Quinta da Aramanha",
    "gn:country_code":"PT",
    "gn:dem":7,
    "gn:feature_class":"P",
    "gn:feature_code":"PPL",
    "gn:name":"Quinta da Aramanha",
    "gn:population":0,
    "gn:timezone":"Europe/Lisbon",
    "iso:country":"PT",
    "wof:name":"Quinta da Aramanha",
    "wof:placetype":"locality"
},
  "geometry": {"coordinates":[-8.77472,39.13683],"type":"Point"}
}