{
  "type": "Feature",
  "properties": {
    "gn:admin1_code":"09",
    "gn:admin2_code":"0802",
    "gn:admin3_code":"80204.0",
    "gn:asciiname":"Matos",
    "gn:country_code":"PT",
    "gn:dem":215,
    "gn:feature_class":"P",
    "gn:feature_code":"PPL",
    "gn:name":"Matos",
    "gn:population":0,
    "gn:timezone":"Europe/Lisbon",
    "iso:country":"PT",
    "name:deu_x_preferred":[
        "Matos"
    ],
    "name:fra_x_preferred":[
        "Matos"
    ],
    "name:nld_x_preferred":[
        "Matos"
    ],
    "name:por_x_preferred":[
        "Matos"
    ],
    "name:rus_x_preferred":[
        "\u041c\u0430\u0442\u043e\u0441"
    ],
    "name:spa_x_preferred":[
        "Matos"
    ],
    "name:ukr_x_preferred":[
        "\u041c\u0430\u0442\u043e\u0441"
    ],
    "wof:name":"Matos",
    "wof:placetype":"locality"
},
  "geometry": {"coordinates":[-7.61472,37.42298],"type":"Point"}
}