{
  "type": "Feature",
  "properties": {
    "gn:admin1_code":"13.0",
    "gn:admin2_code":"1001",
    "gn:admin3_code":"100112.0",
    "gn:asciiname":"Serra de Mangues",
    "gn:country_code":"PT",
    "gn:dem":76,
    "gn:feature_class":"P",
    "gn:feature_code":"PPL",
    "gn:name":"Serra de Mangues",
    "gn:population":0,
    "gn:timezone":"Europe/Lisbon",
    "iso:country":"PT",
    "wof:name":"Serra de Mangues",
    "wof:placetype":"locality"
},
  "geometry": {"coordinates":[-9.12041,39.53043],"type":"Point"}
}