{
  "type": "Feature",
  "properties": {
    "gn:admin1_code":"2.0",
    "gn:admin2_code":"0113",
    "gn:admin3_code":"11304.0",
    "gn:asciiname":"Graciosa",
    "gn:country_code":"PT",
    "gn:dem":98,
    "gn:feature_class":"P",
    "gn:feature_code":"PPL",
    "gn:name":"Graciosa",
    "gn:population":0,
    "gn:timezone":"Europe/Lisbon",
    "iso:country":"PT",
    "wof:name":"Graciosa",
    "wof:placetype":"locality"
},
  "geometry": {"coordinates":[-8.51655,40.78133],"type":"Point"}
}