{
  "type": "Feature",
  "properties": {
    "gn:admin1_code":"2.0",
    "gn:admin2_code":"0113",
    "gn:admin3_code":"11304.0",
    "gn:asciiname":"Graciosa",
    "gn:country_code":"PT",
    "gn:dem":98,
    "gn:feature_class":"P",
    "gn:feature_code":"PPL",
    "gn:name":"Graciosa",
    "gn:population":0,
    "gn:timezone":"Europe/Lisbon",
    "iso:country":"PT",
    "name:bel_x_preferred":[
        "\u0413\u0440\u0430\u0441\u0456\u0451\u0437\u0430"
    ],
    "name:cat_x_preferred":[
        "Graciosa"
    ],
    "name:ceb_x_preferred":[
        "Ilha Graciosa"
    ],
    "name:ces_x_preferred":[
        "Graciosa"
    ],
    "name:deu_x_preferred":[
        "Graciosa"
    ],
    "name:ell_x_preferred":[
        "\u0393\u03ba\u03c1\u03b1\u03c3\u03b9\u03cc\u03c3\u03b1"
    ],
    "name:est_x_preferred":[
        "Graciosa"
    ],
    "name:eus_x_preferred":[
        "Graciosa"
    ],
    "name:fra_x_preferred":[
        "Graciosa"
    ],
    "name:glg_x_preferred":[
        "Illa Graciosa"
    ],
    "name:heb_x_preferred":[
        "\u05d2\u05e8\u05e1\u05d9\u05d5\u05e1\u05d4"
    ],
    "name:ita_x_preferred":[
        "Graciosa"
    ],
    "name:jpn_x_preferred":[
        "\u30b0\u30e9\u30b7\u30aa\u30fc\u30b6\u5cf6"
    ],
    "name:kor_x_preferred":[
        "\uadf8\ub77c\uc2dc\uc624\uc790\uc12c"
    ],
    "name:lit_x_preferred":[
        "Grasioza"
    ],
    "name:mkd_x_preferred":[
        "\u0413\u0440\u0430\u0441\u0438\u043e\u0437\u0430"
    ],
    "name:nld_x_preferred":[
        "Graciosa"
    ],
    "name:nno_x_preferred":[
        "Graciosa"
    ],
    "name:pol_x_preferred":[
        "Graciosa"
    ],
    "name:por_x_preferred":[
        "Graciosa"
    ],
    "name:rus_x_preferred":[
        "\u0413\u0440\u0430\u0441\u0438\u043e\u0437\u0430"
    ],
    "name:slk_x_preferred":[
        "Graciosa"
    ],
    "name:spa_x_preferred":[
        "Isla Graciosa"
    ],
    "name:swa_x_preferred":[
        "Graciosa"
    ],
    "name:swe_x_preferred":[
        "Graciosa"
    ],
    "name:ukr_x_preferred":[
        "\u0413\u0440\u0430\u0441\u0456\u043e\u0437\u0430"
    ],
    "name:zho_x_preferred":[
        "\u683c\u62c9\u897f\u5967\u85a9\u5cf6"
    ],
    "wof:name":"Graciosa",
    "wof:placetype":"locality"
},
  "geometry": {"coordinates":[-8.51655,40.78133],"type":"Point"}
}