{
  "type": "Feature",
  "properties": {
    "gn:admin1_code":"2.0",
    "gn:admin2_code":"0111",
    "gn:admin3_code":"11103.0",
    "gn:asciiname":"Casal Comba",
    "gn:country_code":"PT",
    "gn:dem":76,
    "gn:feature_class":"P",
    "gn:feature_code":"PPL",
    "gn:name":"Casal Comba",
    "gn:population":0,
    "gn:timezone":"Europe/Lisbon",
    "iso:country":"PT",
    "wof:name":"Casal Comba",
    "wof:placetype":"locality"
},
  "geometry": {"coordinates":[-8.46759,40.36653],"type":"Point"}
}