{
  "type": "Feature",
  "properties": {
    "gn:admin1_code":"16",
    "gn:admin2_code":"1210",
    "gn:admin3_code":"121004.0",
    "gn:asciiname":"Porto Espada",
    "gn:country_code":"PT",
    "gn:dem":592,
    "gn:feature_class":"P",
    "gn:feature_code":"PPL",
    "gn:name":"Porto Espada",
    "gn:population":0,
    "gn:timezone":"Europe/Lisbon",
    "iso:country":"PT",
    "name:und_x_variant":[
        "Porto da Espada"
    ],
    "wof:name":"Porto Espada",
    "wof:placetype":"locality"
},
  "geometry": {"coordinates":[-7.35277,39.35474],"type":"Point"}
}