{
  "type": "Feature",
  "properties": {
    "gn:admin1_code":"07",
    "gn:admin2_code":"0604",
    "gn:admin3_code":"60410.0",
    "gn:asciiname":"Povoa da Pega",
    "gn:country_code":"PT",
    "gn:dem":159,
    "gn:feature_class":"P",
    "gn:feature_code":"PPL",
    "gn:name":"P\u00f3voa da Pega",
    "gn:population":0,
    "gn:timezone":"Europe/Lisbon",
    "iso:country":"PT",
    "wof:name":"Povoa da Pega",
    "wof:placetype":"locality"
},
  "geometry": {"coordinates":[-8.4557,40.07432],"type":"Point"}
}