{
  "type": "Feature",
  "properties": {
    "gn:admin1_code":"19",
    "gn:admin2_code":"1503",
    "gn:admin3_code":"150302.0",
    "gn:asciiname":"Costas de Cao",
    "gn:country_code":"PT",
    "gn:dem":107,
    "gn:feature_class":"P",
    "gn:feature_code":"PPL",
    "gn:name":"Costas de C\u00e3o",
    "gn:population":0,
    "gn:timezone":"Europe/Lisbon",
    "iso:country":"PT",
    "wof:name":"Costas de Cao",
    "wof:placetype":"locality"
},
  "geometry": {"coordinates":[-9.21163,38.66464000000001],"type":"Point"}
}