{
  "type": "Feature",
  "properties": {
    "gn:admin1_code":"18",
    "gn:admin2_code":"1417",
    "gn:admin3_code":"141702.0",
    "gn:asciiname":"Codes",
    "gn:country_code":"PT",
    "gn:dem":185,
    "gn:feature_class":"P",
    "gn:feature_code":"PPL",
    "gn:name":"Codes",
    "gn:population":0,
    "gn:timezone":"Europe/Lisbon",
    "iso:country":"PT",
    "wof:name":"Codes",
    "wof:placetype":"locality"
},
  "geometry": {"coordinates":[-8.15147,39.61601],"type":"Point"}
}