{
  "type": "Feature",
  "properties": {
    "gn:admin1_code":"11.0",
    "gn:admin2_code":"0907",
    "gn:admin3_code":"90744.0",
    "gn:asciiname":"Amoreiras",
    "gn:country_code":"PT",
    "gn:dem":452,
    "gn:feature_class":"P",
    "gn:feature_code":"PPL",
    "gn:name":"Amoreiras",
    "gn:population":0,
    "gn:timezone":"Europe/Lisbon",
    "iso:country":"PT",
    "wof:name":"Amoreiras",
    "wof:placetype":"locality"
},
  "geometry": {"coordinates":[-7.29642,40.62763],"type":"Point"}
}