{
  "type": "Feature",
  "properties": {
    "gn:admin1_code":"17.0",
    "gn:admin2_code":"1302",
    "gn:admin3_code":"130203.0",
    "gn:asciiname":"Covelas",
    "gn:country_code":"PT",
    "gn:dem":207,
    "gn:feature_class":"P",
    "gn:feature_code":"PPL",
    "gn:name":"Covelas",
    "gn:population":0,
    "gn:timezone":"Europe/Lisbon",
    "iso:country":"PT",
    "wof:name":"Covelas",
    "wof:placetype":"locality"
},
  "geometry": {"coordinates":[-7.9862,41.11581],"type":"Point"}
}