{
  "type": "Feature",
  "properties": {
    "gn:admin1_code":"17.0",
    "gn:admin2_code":"1305",
    "gn:admin3_code":"130526.0",
    "gn:asciiname":"Alentem",
    "gn:country_code":"PT",
    "gn:dem":247,
    "gn:feature_class":"P",
    "gn:feature_code":"PPL",
    "gn:name":"Alentem",
    "gn:population":0,
    "gn:timezone":"Europe/Lisbon",
    "iso:country":"PT",
    "wof:name":"Alentem",
    "wof:placetype":"locality"
},
  "geometry": {"coordinates":[-8.22479,41.28266],"type":"Point"}
}