{
  "type": "Feature",
  "properties": {
    "gn:admin1_code":"2.0",
    "gn:admin2_code":"0101",
    "gn:admin3_code":"10104.0",
    "gn:asciiname":"Macoida",
    "gn:country_code":"PT",
    "gn:dem":163,
    "gn:feature_class":"P",
    "gn:feature_code":"PPL",
    "gn:name":"Ma\u00e7oida",
    "gn:population":0,
    "gn:timezone":"Europe/Lisbon",
    "iso:country":"PT",
    "wof:name":"Macoida",
    "wof:placetype":"locality"
},
  "geometry": {"coordinates":[-8.38529,40.60383],"type":"Point"}
}