{
  "type": "Feature",
  "properties": {
    "gn:admin1_code":"14",
    "gn:admin2_code":"1111",
    "gn:admin3_code":"111103.0",
    "gn:asciiname":"Covas de Ferro",
    "gn:country_code":"PT",
    "gn:dem":291,
    "gn:feature_class":"P",
    "gn:feature_code":"PPL",
    "gn:name":"Covas de Ferro",
    "gn:population":0,
    "gn:timezone":"Europe/Lisbon",
    "iso:country":"PT",
    "name:und_x_variant":[
        "Covas",
        "Covas de Ferro"
    ],
    "wof:name":"Covas de Ferro",
    "wof:placetype":"locality"
},
  "geometry": {"coordinates":[-9.25264,38.86596],"type":"Point"}
}