{
  "type": "Feature",
  "properties": {
    "gn:admin1_code":"18",
    "gn:admin2_code":"1419",
    "gn:admin3_code":"141913.0",
    "gn:asciiname":"Marruas",
    "gn:country_code":"PT",
    "gn:dem":120,
    "gn:feature_class":"P",
    "gn:feature_code":"PPL",
    "gn:name":"Marruas",
    "gn:population":0,
    "gn:timezone":"Europe/Lisbon",
    "iso:country":"PT",
    "wof:name":"Marruas",
    "wof:placetype":"locality"
},
  "geometry": {"coordinates":[-8.5825,39.4668],"type":"Point"}
}