{
  "type": "Feature",
  "properties": {
    "gn:admin1_code":"17",
    "gn:admin2_code":"1317",
    "gn:admin3_code":"131722.0",
    "gn:asciiname":"Praia de Valadares",
    "gn:country_code":"PT",
    "gn:dem":10,
    "gn:feature_class":"P",
    "gn:feature_code":"PPL",
    "gn:name":"Praia de Valadares",
    "gn:population":0,
    "gn:timezone":"Europe/Lisbon",
    "iso:country":"PT",
    "wof:name":"Praia de Valadares",
    "wof:placetype":"locality"
},
  "geometry": {"coordinates":[-8.65592,41.09169],"type":"Point"}
}