{
  "type": "Feature",
  "properties": {
    "iso:country":"PT",
    "name:por_x_preferred":[
        "Damaia"
    ],
    "qs:gn_adm0_cc":"PT",
    "qs:gn_fcode":"PPL",
    "qs:gn_local":8010569,
    "qs:gn_nam_loc":"Amadora, Lisboa, PT",
    "qs:gn_namadm1":"14",
    "qs:gn_name":"Damaia",
    "qs:local_max":284,
    "qs:local_sum":342,
    "qs:localhoods":3,
    "qs:name":"Damaia",
    "qs:name_adm0":"Portugal",
    "qs:name_adm1":"Lisboa",
    "qs:name_adm2":"Amadora",
    "qs:name_local":"Amadora",
    "qs:photo_max":20,
    "qs:photo_sum":50,
    "qs:placetype":"Suburb",
    "qs:quad_count":7,
    "qs:woe_adm0":23424925,
    "qs:woe_adm1":2346573,
    "qs:woe_adm2":12596416,
    "qs:woe_lau":0,
    "qs:woe_local":12596416,
    "qs:woe_ver":"7.10.0",
    "wof:lang":[
        "por"
    ],
    "wof:name":"Damaia",
    "wof:placetype":"neighbourhood"
},
  "geometry": {"coordinates":[-9.20962,38.751724],"type":"Point"}
}