{
  "type": "Feature",
  "properties": {
    "gn:admin1_code":"22.0",
    "gn:admin2_code":"1823",
    "gn:admin3_code":"182304.0",
    "gn:asciiname":"Pereiras",
    "gn:country_code":"PT",
    "gn:dem":494,
    "gn:feature_class":"P",
    "gn:feature_code":"PPL",
    "gn:name":"Pereiras",
    "gn:population":0,
    "gn:timezone":"Europe/Lisbon",
    "iso:country":"PT",
    "name:bpy_x_preferred":[
        "\u09aa\u09c7\u09b0\u09c7\u0987\u09b0\u09be\u09b8"
    ],
    "name:ceb_x_preferred":[
        "Pereiras"
    ],
    "name:epo_x_preferred":[
        "Pereiras"
    ],
    "name:eus_x_preferred":[
        "Pereiras"
    ],
    "name:fra_x_preferred":[
        "Pereiras"
    ],
    "name:ita_x_preferred":[
        "Pereiras"
    ],
    "name:kaz_x_preferred":[
        "\u041f\u0435\u0440\u0435\u0439\u0440\u0430\u0441"
    ],
    "name:mlg_x_preferred":[
        "Pereiras"
    ],
    "name:nld_x_preferred":[
        "Pereiras"
    ],
    "name:nor_x_preferred":[
        "Pereiras"
    ],
    "name:pol_x_preferred":[
        "Pereiras"
    ],
    "name:por_x_preferred":[
        "Pereiras"
    ],
    "name:ron_x_preferred":[
        "Pereiras"
    ],
    "name:rus_x_preferred":[
        "\u041f\u0435\u0440\u0435\u0439\u0440\u0430\u0441"
    ],
    "name:swe_x_preferred":[
        "Pereiras"
    ],
    "name:vol_x_preferred":[
        "Pereiras"
    ],
    "name:war_x_preferred":[
        "Pereiras"
    ],
    "name:zho_x_preferred":[
        "\u4f69\u96f7\u62c9\u65af"
    ],
    "wof:name":"Pereiras",
    "wof:placetype":"locality"
},
  "geometry": {"coordinates":[-7.99719,40.70929],"type":"Point"}
}