{
  "type": "Feature",
  "properties": {
    "gn:admin1_code":"22.0",
    "gn:admin2_code":"1823",
    "gn:admin3_code":"182304.0",
    "gn:asciiname":"Pereiras",
    "gn:country_code":"PT",
    "gn:dem":494,
    "gn:feature_class":"P",
    "gn:feature_code":"PPL",
    "gn:name":"Pereiras",
    "gn:population":0,
    "gn:timezone":"Europe/Lisbon",
    "iso:country":"PT",
    "wof:name":"Pereiras",
    "wof:placetype":"locality"
},
  "geometry": {"coordinates":[-7.99719,40.70929],"type":"Point"}
}