{
  "type": "Feature",
  "properties": {
    "gn:admin1_code":"11.0",
    "gn:admin2_code":"0903",
    "gn:admin3_code":"90310.0",
    "gn:asciiname":"Mesquitela",
    "gn:country_code":"PT",
    "gn:dem":425,
    "gn:feature_class":"P",
    "gn:feature_code":"PPL",
    "gn:name":"Mesquitela",
    "gn:population":0,
    "gn:timezone":"Europe/Lisbon",
    "iso:country":"PT",
    "name:deu_x_preferred":[
        "Mesquitela"
    ],
    "name:kaz_x_preferred":[
        "\u041c\u0435\u0448\u043a\u0438\u0442\u0435\u043b\u0430"
    ],
    "name:nld_x_preferred":[
        "Mesquitela"
    ],
    "name:por_x_preferred":[
        "Mesquitela"
    ],
    "name:rus_x_preferred":[
        "\u041c\u0435\u0448\u043a\u0438\u0442\u0435\u043b\u0430"
    ],
    "name:spa_x_preferred":[
        "Mesquitela"
    ],
    "wof:name":"Mesquitela",
    "wof:placetype":"locality"
},
  "geometry": {"coordinates":[-7.49073,40.58873],"type":"Point"}
}