{
  "type": "Feature",
  "properties": {
    "gn:admin1_code":"11.0",
    "gn:admin2_code":"0903",
    "gn:admin3_code":"90310.0",
    "gn:asciiname":"Mesquitela",
    "gn:country_code":"PT",
    "gn:dem":425,
    "gn:feature_class":"P",
    "gn:feature_code":"PPL",
    "gn:name":"Mesquitela",
    "gn:population":0,
    "gn:timezone":"Europe/Lisbon",
    "iso:country":"PT",
    "wof:name":"Mesquitela",
    "wof:placetype":"locality"
},
  "geometry": {"coordinates":[-7.49073,40.58873],"type":"Point"}
}