{
  "type": "Feature",
  "properties": {
    "gn:admin1_code":"09",
    "gn:admin2_code":"0801",
    "gn:admin3_code":"80101.0",
    "gn:asciiname":"Vale de Santa Maria",
    "gn:country_code":"PT",
    "gn:dem":65,
    "gn:feature_class":"P",
    "gn:feature_code":"PPL",
    "gn:name":"Vale de Santa Maria",
    "gn:population":0,
    "gn:timezone":"Europe/Lisbon",
    "iso:country":"PT",
    "wof:name":"Vale de Santa Maria",
    "wof:placetype":"locality"
},
  "geometry": {"coordinates":[-8.26406,37.10096],"type":"Point"}
}