{
  "type": "Feature",
  "properties": {
    "gn:admin1_code":"7.0",
    "gn:admin2_code":"0615",
    "gn:admin3_code":"61509.0",
    "gn:asciiname":"Goncalinha",
    "gn:country_code":"PT",
    "gn:dem":59,
    "gn:feature_class":"P",
    "gn:feature_code":"PPL",
    "gn:name":"Gon\u00e7alinha",
    "gn:population":0,
    "gn:timezone":"Europe/Lisbon",
    "iso:country":"PT",
    "wof:name":"Goncalinha",
    "wof:placetype":"locality"
},
  "geometry": {"coordinates":[-8.60378,40.01495],"type":"Point"}
}