{
  "type": "Feature",
  "properties": {
    "gn:admin1_code":"06",
    "gn:admin2_code":"0509",
    "gn:admin3_code":"50911.0",
    "gn:asciiname":"Casal dos Bufos",
    "gn:country_code":"PT",
    "gn:dem":415,
    "gn:feature_class":"P",
    "gn:feature_code":"PPL",
    "gn:name":"Casal dos Bufos",
    "gn:population":0,
    "gn:timezone":"Europe/Lisbon",
    "iso:country":"PT",
    "wof:name":"Casal dos Bufos",
    "wof:placetype":"locality"
},
  "geometry": {"coordinates":[-8.12069,39.91452],"type":"Point"}
}