{
  "type": "Feature",
  "properties": {
    "iso:country":"PT",
    "qs_pg:aaroncc":"PT",
    "qs_pg:name":"Lomba de Santa Barbara",
    "qs_pg:name_adm0":"Portugal",
    "qs_pg:name_adm1":"Azores",
    "qs_pg:photos":5,
    "qs_pg:photos_1k":1,
    "qs_pg:photos_9k":1,
    "qs_pg:photos_9r":1,
    "qs_pg:photos_all":5,
    "qs_pg:photos_sr":1,
    "qs_pg:pop_sr":0,
    "qs_pg:qs_pg_placetype":"locality",
    "qs_pg:qs_pg_placetype_gp":"Town",
    "qs_pg:woe_adm0":23424925,
    "woe:adm0_id":23424925,
    "woe:name_adm0":"Portugal",
    "woe:name_adm1":"Azores",
    "woe:placetype":"Town",
    "wof:name":"Lomba de Santa Barbara",
    "wof:placetype":"locality"
},
  "geometry": {"coordinates":[-25.557148,37.791722],"type":"Point"}
}