{
  "type": "Feature",
  "properties": {
    "gn:admin1_code":"22",
    "gn:admin2_code":"1804",
    "gn:admin3_code":"180412.0",
    "gn:asciiname":"Vilar de Arca",
    "gn:country_code":"PT",
    "gn:dem":667,
    "gn:feature_class":"P",
    "gn:feature_code":"PPL",
    "gn:name":"Vilar de Arca",
    "gn:population":0,
    "gn:timezone":"Europe/Lisbon",
    "iso:country":"PT",
    "wof:name":"Vilar de Arca",
    "wof:placetype":"locality"
},
  "geometry": {"coordinates":[-8.17591,41.03239],"type":"Point"}
}