{
  "type": "Feature",
  "properties": {
    "gn:admin1_code":"08",
    "gn:admin2_code":"0709",
    "gn:admin3_code":"70903.0",
    "gn:asciiname":"Monte Negro",
    "gn:country_code":"PT",
    "gn:dem":220,
    "gn:feature_class":"P",
    "gn:feature_code":"PPL",
    "gn:name":"Monte Negro",
    "gn:population":0,
    "gn:timezone":"Europe/Lisbon",
    "iso:country":"PT",
    "wof:name":"Monte Negro",
    "wof:placetype":"locality"
},
  "geometry": {"coordinates":[-7.74916,38.38787],"type":"Point"}
}