{
  "type": "Feature",
  "properties": {
    "gn:admin1_code":"09",
    "gn:admin2_code":"0808",
    "gn:admin3_code":"80808.0",
    "gn:asciiname":"Concelho",
    "gn:country_code":"PT",
    "gn:dem":313,
    "gn:feature_class":"P",
    "gn:feature_code":"PPL",
    "gn:name":"Concelho",
    "gn:population":0,
    "gn:timezone":"Europe/Lisbon",
    "iso:country":"PT",
    "name:cat_x_preferred":[
        "Concelho"
    ],
    "name:ita_x_preferred":[
        "Concelho"
    ],
    "name:pol_x_preferred":[
        "Concelho"
    ],
    "name:spa_x_preferred":[
        "Concelho"
    ],
    "wof:name":"Concelho",
    "wof:placetype":"locality"
},
  "geometry": {"coordinates":[-7.97025,37.16228],"type":"Point"}
}