{
  "type": "Feature",
  "properties": {
    "gn:country":"PT",
    "gn:fcode":"PPL",
    "gn:population":0,
    "iso:country":"PT",
    "name:bpy_x_preferred":[
        "\u0986\u0997\u09c1\u09f1\u09be\u09b8 \u09ab\u09cd\u09b0\u09bf\u09af\u09bc\u09be\u09b8"
    ],
    "name:eus_x_preferred":[
        "\u00c1guas Frias"
    ],
    "name:fra_x_preferred":[
        "\u00c1guas Frias"
    ],
    "name:ina_x_preferred":[
        "\u00c1guas Frias"
    ],
    "name:ita_x_preferred":[
        "\u00c1guas Frias"
    ],
    "name:kat_x_preferred":[
        "\u10d0\u10d2\u10e3\u10d0\u10e1-\u10e4\u10e0\u10d8\u10d0\u10e1\u10d8"
    ],
    "name:nld_x_preferred":[
        "\u00c1guas Frias"
    ],
    "name:nor_x_preferred":[
        "\u00c1guas Frias"
    ],
    "name:oci_x_preferred":[
        "\u00c1guas Frias"
    ],
    "name:pol_x_preferred":[
        "\u00c1guas Frias"
    ],
    "name:por_x_preferred":[
        "\u00c1guas Frias"
    ],
    "name:ron_x_preferred":[
        "\u00c1guas Frias"
    ],
    "name:rus_x_preferred":[
        "\u0410\u0433\u0443\u0430\u0441-\u0424\u0440\u0438\u0430\u0441"
    ],
    "name:spa_x_preferred":[
        "\u00c1guas Frias"
    ],
    "name:vie_x_preferred":[
        "\u00c1guas Frias"
    ],
    "name:vol_x_preferred":[
        "\u00c1guas Frias"
    ],
    "name:war_x_preferred":[
        "\u00c1guas Frias"
    ],
    "name:zho_x_preferred":[
        "\u963f\u74dc\u65af\u5f17\u91cc\u4e9a\u65af"
    ],
    "qs_pg:aaroncc":"PT",
    "qs_pg:gn_country":"PT",
    "qs_pg:gn_fcode":"PPL",
    "qs_pg:gn_pop":0,
    "qs_pg:name":"\u00c1guas Frias",
    "qs_pg:name_adm0":"Portugal",
    "qs_pg:name_adm1":"Vila Real",
    "qs_pg:photos":649,
    "qs_pg:photos_1k":132,
    "qs_pg:photos_9k":3,
    "qs_pg:photos_9r":5,
    "qs_pg:photos_all":649,
    "qs_pg:photos_sr":8,
    "qs_pg:pop_sr":0,
    "qs_pg:qs_pg_placetype":"locality",
    "qs_pg:qs_pg_placetype_gp":"Town",
    "qs_pg:woe_adm0":23424925,
    "woe:adm0_id":23424925,
    "woe:name_adm0":"Portugal",
    "woe:name_adm1":"Vila Real",
    "woe:placetype":"Town",
    "wof:name":"\u00c1guas Frias",
    "wof:placetype":"locality"
},
  "geometry": {"coordinates":[-7.35232,41.76881],"type":"Point"}
}