{
  "type": "Feature",
  "properties": {
    "gn:admin1_code":"7.0",
    "gn:admin2_code":"0603",
    "gn:admin3_code":"60310.0",
    "gn:asciiname":"Conraria",
    "gn:country_code":"PT",
    "gn:dem":67,
    "gn:feature_class":"P",
    "gn:feature_code":"PPL",
    "gn:name":"Conraria",
    "gn:population":0,
    "gn:timezone":"Europe/Lisbon",
    "iso:country":"PT",
    "wof:name":"Conraria",
    "wof:placetype":"locality"
},
  "geometry": {"coordinates":[-8.39772,40.17672],"type":"Point"}
}