{
  "type": "Feature",
  "properties": {
    "gn:admin1_code":"21.0",
    "gn:admin2_code":"1714",
    "gn:admin3_code":"171426.0",
    "gn:asciiname":"Arrabaes",
    "gn:country_code":"PT",
    "gn:dem":672,
    "gn:feature_class":"P",
    "gn:feature_code":"PPL",
    "gn:name":"Arrab\u00e3es",
    "gn:population":0,
    "gn:timezone":"Europe/Lisbon",
    "iso:country":"PT",
    "wof:name":"Arrabaes",
    "wof:placetype":"locality"
},
  "geometry": {"coordinates":[-7.81289,41.28139],"type":"Point"}
}