{
  "type": "Feature",
  "properties": {
    "gn:admin1_code":"19",
    "gn:admin2_code":"1509",
    "gn:admin3_code":"150904.0",
    "gn:asciiname":"Ermidas",
    "gn:country_code":"PT",
    "gn:dem":82,
    "gn:feature_class":"P",
    "gn:feature_code":"PPL",
    "gn:name":"Ermidas",
    "gn:population":0,
    "gn:timezone":"Europe/Lisbon",
    "iso:country":"PT",
    "name:und_x_variant":[
        "Ermidas Gare",
        "Ermidas"
    ],
    "wof:name":"Ermidas",
    "wof:placetype":"locality"
},
  "geometry": {"coordinates":[-8.414,38.00538],"type":"Point"}
}