{
  "type": "Feature",
  "properties": {
    "gn:admin1_code":"4.0",
    "gn:admin2_code":"0306",
    "gn:admin3_code":"30602.0",
    "gn:asciiname":"Igreja",
    "gn:country_code":"PT",
    "gn:dem":8,
    "gn:feature_class":"P",
    "gn:feature_code":"PPL",
    "gn:name":"Igreja",
    "gn:population":0,
    "gn:timezone":"Europe/Lisbon",
    "iso:country":"PT",
    "wof:name":"Igreja",
    "wof:placetype":"locality"
},
  "geometry": {"coordinates":[-8.76842,41.48351],"type":"Point"}
}