{
  "type": "Feature",
  "properties": {
    "gn:admin1_code":"22",
    "gn:admin2_code":"1816",
    "gn:admin3_code":"181606.0",
    "gn:asciiname":"Ucha",
    "gn:country_code":"PT",
    "gn:dem":445,
    "gn:feature_class":"P",
    "gn:feature_code":"PPL",
    "gn:name":"Ucha",
    "gn:population":0,
    "gn:timezone":"Europe/Lisbon",
    "iso:country":"PT",
    "name:ceb_x_preferred":[
        "Ucha"
    ],
    "name:deu_x_preferred":[
        "Ucha"
    ],
    "name:nld_x_preferred":[
        "Ucha"
    ],
    "name:por_x_preferred":[
        "Ucha"
    ],
    "name:rus_x_preferred":[
        "\u0423\u0448\u0430"
    ],
    "name:spa_x_preferred":[
        "Ucha"
    ],
    "name:ukr_x_preferred":[
        "\u0423\u0448\u0430"
    ],
    "name:urd_x_preferred":[
        "\u0627\u0686\u0627"
    ],
    "wof:name":"Ucha",
    "wof:placetype":"locality"
},
  "geometry": {"coordinates":[-8.01396,40.81773],"type":"Point"}
}