{
  "type": "Feature",
  "properties": {
    "gn:admin1_code":"14",
    "gn:admin2_code":"1113",
    "gn:admin3_code":"111318.0",
    "gn:asciiname":"Carregueira",
    "gn:country_code":"PT",
    "gn:dem":44,
    "gn:feature_class":"P",
    "gn:feature_code":"PPL",
    "gn:name":"Carregueira",
    "gn:population":0,
    "gn:timezone":"Europe/Lisbon",
    "iso:country":"PT",
    "wof:name":"Carregueira",
    "wof:placetype":"locality"
},
  "geometry": {"coordinates":[-9.3581,39.06074],"type":"Point"}
}