{
  "type": "Feature",
  "properties": {
    "gn:admin1_code":"20.0",
    "gn:admin2_code":"1601",
    "gn:admin3_code":"160128.0",
    "gn:asciiname":"Estanque",
    "gn:country_code":"PT",
    "gn:dem":79,
    "gn:feature_class":"P",
    "gn:feature_code":"PPL",
    "gn:name":"Estanque",
    "gn:population":0,
    "gn:timezone":"Europe/Lisbon",
    "iso:country":"PT",
    "wof:name":"Estanque",
    "wof:placetype":"locality"
},
  "geometry": {"coordinates":[-8.42883,41.87335],"type":"Point"}
}