{
  "type": "Feature",
  "properties": {
    "gn:admin1_code":"21.0",
    "gn:admin2_code":"1706",
    "gn:admin3_code":"170616.0",
    "gn:asciiname":"Carvalhais",
    "gn:country_code":"PT",
    "gn:dem":941,
    "gn:feature_class":"P",
    "gn:feature_code":"PPL",
    "gn:name":"Carvalhais",
    "gn:population":0,
    "gn:timezone":"Europe/Lisbon",
    "iso:country":"PT",
    "wof:name":"Carvalhais",
    "wof:placetype":"locality"
},
  "geometry": {"coordinates":[-7.7421,41.73218],"type":"Point"}
}