{
  "type": "Feature",
  "properties": {
    "gn:admin1_code":"06",
    "gn:admin2_code":"0508",
    "gn:admin3_code":"50804.0",
    "gn:asciiname":"Relva da Louca",
    "gn:country_code":"PT",
    "gn:dem":417,
    "gn:feature_class":"P",
    "gn:feature_code":"PPL",
    "gn:name":"Relva da Lou\u00e7a",
    "gn:population":0,
    "gn:timezone":"Europe/Lisbon",
    "iso:country":"PT",
    "wof:name":"Relva da Louca",
    "wof:placetype":"locality"
},
  "geometry": {"coordinates":[-7.94075,39.72219000000001],"type":"Point"}
}