{
  "type": "Feature",
  "properties": {
    "gn:admin1_code":"4.0",
    "gn:admin2_code":"0302",
    "gn:admin3_code":"30277.0",
    "gn:asciiname":"Freiao",
    "gn:country_code":"PT",
    "gn:dem":23,
    "gn:feature_class":"P",
    "gn:feature_code":"PPL",
    "gn:name":"Frei\u00e3o",
    "gn:population":0,
    "gn:timezone":"Europe/Lisbon",
    "iso:country":"PT",
    "wof:name":"Freiao",
    "wof:placetype":"locality"
},
  "geometry": {"coordinates":[-8.59113,41.54505],"type":"Point"}
}