{
  "type": "Feature",
  "properties": {
    "gn:admin1_code":"17.0",
    "gn:admin2_code":"1311",
    "gn:admin3_code":"131129.0",
    "gn:asciiname":"Novelhos",
    "gn:country_code":"PT",
    "gn:dem":91,
    "gn:feature_class":"P",
    "gn:feature_code":"PPL",
    "gn:name":"Novelhos",
    "gn:population":0,
    "gn:timezone":"Europe/Lisbon",
    "iso:country":"PT",
    "wof:name":"Novelhos",
    "wof:placetype":"locality"
},
  "geometry": {"coordinates":[-8.27747,41.1014],"type":"Point"}
}