{
  "type": "Feature",
  "properties": {
    "gn:country":"PT",
    "gn:fcode":"PPLX",
    "gn:population":3,
    "iso:country":"PT",
    "qs_pg:aaroncc":"PT",
    "qs_pg:gn_country":"PT",
    "qs_pg:gn_fcode":"PPLX",
    "qs_pg:gn_pop":3,
    "qs_pg:name":"Selvagem Grande",
    "qs_pg:photos_9r":0,
    "qs_pg:photos_sr":0,
    "qs_pg:pop_sr":1,
    "qs_pg:qs_pg_placetype":"neighbourhood",
    "wof:name":"Selvagem Grande",
    "wof:placetype":"neighbourhood",
    "wof:population":3
},
  "geometry": {"coordinates":[-15.86666,30.14631],"type":"Point"}
}