{
  "type": "Feature",
  "properties": {
    "gn:admin1_code":"17",
    "gn:admin2_code":"1302",
    "gn:admin3_code":"130202.0",
    "gn:asciiname":"Varzea",
    "gn:country_code":"PT",
    "gn:dem":455,
    "gn:feature_class":"P",
    "gn:feature_code":"PPL",
    "gn:name":"V\u00e1rzea",
    "gn:population":0,
    "gn:timezone":"Europe/Lisbon",
    "iso:country":"PT",
    "wof:name":"Varzea",
    "wof:placetype":"locality"
},
  "geometry": {"coordinates":[-8.02581,41.15851],"type":"Point"}
}