{
  "type": "Feature",
  "properties": {
    "gn:admin1_code":"09",
    "gn:admin2_code":"0808",
    "gn:admin3_code":"80811.0",
    "gn:asciiname":"Venda Nova",
    "gn:country_code":"PT",
    "gn:dem":269,
    "gn:feature_class":"P",
    "gn:feature_code":"PPL",
    "gn:name":"Venda Nova",
    "gn:population":0,
    "gn:timezone":"Europe/Lisbon",
    "iso:country":"PT",
    "name:ceb_x_preferred":[
        "Venda Nova"
    ],
    "name:deu_x_preferred":[
        "Venda Nova"
    ],
    "name:fra_x_preferred":[
        "Venda Nova"
    ],
    "name:nld_x_preferred":[
        "Venda Nova"
    ],
    "name:por_x_preferred":[
        "Venda Nova"
    ],
    "name:rus_x_preferred":[
        "\u0412\u0435\u043d\u0434\u0430-\u041d\u043e\u0432\u0430"
    ],
    "wof:name":"Venda Nova",
    "wof:placetype":"locality"
},
  "geometry": {"coordinates":[-8.02881,37.20584],"type":"Point"}
}