{
  "type": "Feature",
  "properties": {
    "gn:admin1_code":"18",
    "gn:admin2_code":"1401",
    "gn:admin3_code":"140112.0",
    "gn:asciiname":"Sao Miguel de Rio Torto",
    "gn:country_code":"PT",
    "gn:dem":143,
    "gn:feature_class":"P",
    "gn:feature_code":"PPL",
    "gn:name":"S\u00e3o Miguel de Rio Torto",
    "gn:population":4881,
    "gn:timezone":"Europe/Lisbon",
    "iso:country":"PT",
    "wof:name":"Sao Miguel de Rio Torto",
    "wof:placetype":"locality",
    "wof:population":4881
},
  "geometry": {"coordinates":[-8.21667,39.43333],"type":"Point"}
}