{
  "type": "Feature",
  "properties": {
    "gn:admin1_code":"7.0",
    "gn:admin2_code":"0604",
    "gn:admin3_code":"60401.0",
    "gn:asciiname":"Casal da Legua",
    "gn:country_code":"PT",
    "gn:dem":62,
    "gn:feature_class":"P",
    "gn:feature_code":"PPL",
    "gn:name":"Casal da L\u00e9gua",
    "gn:population":0,
    "gn:timezone":"Europe/Lisbon",
    "iso:country":"PT",
    "wof:name":"Casal da Legua",
    "wof:placetype":"locality"
},
  "geometry": {"coordinates":[-8.54927,40.14719],"type":"Point"}
}