{
  "type": "Feature",
  "properties": {
    "gn:admin1_code":"09",
    "gn:admin2_code":"0814",
    "gn:admin3_code":"81401.0",
    "gn:asciiname":"Casas Baixas",
    "gn:country_code":"PT",
    "gn:dem":351,
    "gn:feature_class":"P",
    "gn:feature_code":"PPL",
    "gn:name":"Casas Baixas",
    "gn:population":0,
    "gn:timezone":"Europe/Lisbon",
    "iso:country":"PT",
    "wof:name":"Casas Baixas",
    "wof:placetype":"locality"
},
  "geometry": {"coordinates":[-7.78028,37.34283],"type":"Point"}
}