{
  "type": "Feature",
  "properties": {
    "gn:admin1_code":"7.0",
    "gn:admin2_code":"0613",
    "gn:admin3_code":"61302.0",
    "gn:asciiname":"Mata de Maxial",
    "gn:country_code":"PT",
    "gn:dem":210,
    "gn:feature_class":"P",
    "gn:feature_code":"PPL",
    "gn:name":"Mata de Maxial",
    "gn:population":0,
    "gn:timezone":"Europe/Lisbon",
    "iso:country":"PT",
    "wof:name":"Mata de Maxial",
    "wof:placetype":"locality"
},
  "geometry": {"coordinates":[-8.38,40.28539],"type":"Point"}
}