{
  "type": "Feature",
  "properties": {
    "gn:admin1_code":"7.0",
    "gn:admin2_code":"0609",
    "gn:admin3_code":"60903.0",
    "gn:asciiname":"Pedreira",
    "gn:country_code":"PT",
    "gn:dem":170,
    "gn:feature_class":"P",
    "gn:feature_code":"PPL",
    "gn:name":"Pedreira",
    "gn:population":0,
    "gn:timezone":"Europe/Lisbon",
    "iso:country":"PT",
    "name:ceb_x_preferred":[
        "Pedreira"
    ],
    "name:deu_x_preferred":[
        "Pedreira"
    ],
    "name:fra_x_preferred":[
        "Pedreira"
    ],
    "name:glg_x_preferred":[
        "Pedreira"
    ],
    "name:nds_x_preferred":[
        "Pedreira"
    ],
    "name:nld_x_preferred":[
        "Pedreira"
    ],
    "name:por_x_preferred":[
        "Pedreira"
    ],
    "name:swe_x_preferred":[
        "Pedreira"
    ],
    "name:tur_x_preferred":[
        "Pedreira"
    ],
    "wof:name":"Pedreira",
    "wof:placetype":"locality"
},
  "geometry": {"coordinates":[-8.33252,40.13223],"type":"Point"}
}