{
  "type": "Feature",
  "properties": {
    "gn:admin1_code":"20.0",
    "gn:admin2_code":"1606",
    "gn:admin3_code":"160607.0",
    "gn:asciiname":"Lourido",
    "gn:country_code":"PT",
    "gn:dem":194,
    "gn:feature_class":"P",
    "gn:feature_code":"PPL",
    "gn:name":"Lourido",
    "gn:population":0,
    "gn:timezone":"Europe/Lisbon",
    "iso:country":"PT",
    "wof:name":"Lourido",
    "wof:placetype":"locality"
},
  "geometry": {"coordinates":[-8.28251,41.82152],"type":"Point"}
}