{
  "type": "Feature",
  "properties": {
    "gn:admin1_code":"21",
    "gn:admin2_code":"1709",
    "gn:admin3_code":"170905.0",
    "gn:asciiname":"Ruival",
    "gn:country_code":"PT",
    "gn:dem":319,
    "gn:feature_class":"P",
    "gn:feature_code":"PPL",
    "gn:name":"Ruival",
    "gn:population":0,
    "gn:timezone":"Europe/Lisbon",
    "iso:country":"PT",
    "wof:name":"Ruival",
    "wof:placetype":"locality"
},
  "geometry": {"coordinates":[-7.80008,41.52987],"type":"Point"}
}