{
  "type": "Feature",
  "properties": {
    "gn:admin1_code":"20.0",
    "gn:admin2_code":"1609",
    "gn:admin3_code":"160909.0",
    "gn:asciiname":"Gandarinha",
    "gn:country_code":"PT",
    "gn:dem":109,
    "gn:feature_class":"P",
    "gn:feature_code":"PPL",
    "gn:name":"Gandarinha",
    "gn:population":0,
    "gn:timezone":"Europe/Lisbon",
    "iso:country":"PT",
    "wof:name":"Gandarinha",
    "wof:placetype":"locality"
},
  "geometry": {"coordinates":[-8.66541,41.65385],"type":"Point"}
}