{
  "type": "Feature",
  "properties": {
    "gn:admin1_code":"21",
    "gn:admin2_code":"1712",
    "gn:admin3_code":"171217.0",
    "gn:asciiname":"Povoa",
    "gn:country_code":"PT",
    "gn:dem":280,
    "gn:feature_class":"P",
    "gn:feature_code":"PPL",
    "gn:name":"P\u00f3voa",
    "gn:population":0,
    "gn:timezone":"Europe/Lisbon",
    "iso:country":"PT",
    "wof:name":"Povoa",
    "wof:placetype":"locality"
},
  "geometry": {"coordinates":[-7.28357,41.52097],"type":"Point"}
}