{
  "type": "Feature",
  "properties": {
    "gn:admin1_code":"5.0",
    "gn:admin2_code":"0408",
    "gn:admin3_code":"40809.0",
    "gn:asciiname":"Meirinhos",
    "gn:country_code":"PT",
    "gn:dem":528,
    "gn:feature_class":"P",
    "gn:feature_code":"PPL",
    "gn:name":"Meirinhos",
    "gn:population":0,
    "gn:timezone":"Europe/Lisbon",
    "iso:country":"PT",
    "wof:name":"Meirinhos",
    "wof:placetype":"locality"
},
  "geometry": {"coordinates":[-6.8258,41.26349],"type":"Point"}
}