{
  "type": "Feature",
  "properties": {
    "gn:admin1_code":"13",
    "gn:admin2_code":"1008",
    "gn:admin3_code":"100801.0",
    "gn:asciiname":"Almofala de Cima",
    "gn:country_code":"PT",
    "gn:dem":354,
    "gn:feature_class":"P",
    "gn:feature_code":"PPL",
    "gn:name":"Almofala de Cima",
    "gn:population":0,
    "gn:timezone":"Europe/Lisbon",
    "iso:country":"PT",
    "wof:name":"Almofala de Cima",
    "wof:placetype":"locality"
},
  "geometry": {"coordinates":[-8.33545,39.90648],"type":"Point"}
}