{
  "type": "Feature",
  "properties": {
    "gn:admin1_code":"04",
    "gn:admin2_code":"0309",
    "gn:admin3_code":"30921.0",
    "gn:asciiname":"Rendufinho",
    "gn:country_code":"PT",
    "gn:dem":338,
    "gn:feature_class":"P",
    "gn:feature_code":"PPL",
    "gn:name":"Rendufinho",
    "gn:population":0,
    "gn:timezone":"Europe/Lisbon",
    "iso:country":"PT",
    "wof:name":"Rendufinho",
    "wof:placetype":"locality"
},
  "geometry": {"coordinates":[-8.2654,41.60998],"type":"Point"}
}