{
  "type": "Feature",
  "properties": {
    "iso:country":"PT",
    "name:pol_x_preferred":[
        "S\u00e3o Nicolau"
    ],
    "wof:name":"Sao Nicolau",
    "wof:placetype":"neighbourhood"
},
  "geometry": {"coordinates":[-9.13919750589652,38.70699392392049],"type":"Point"}
}