{
  "type": "Feature",
  "properties": {
    "gn:admin1_code":"06",
    "gn:admin2_code":"0511",
    "gn:admin3_code":"51104.0",
    "gn:asciiname":"Cerejal",
    "gn:country_code":"PT",
    "gn:dem":285,
    "gn:feature_class":"P",
    "gn:feature_code":"PPL",
    "gn:name":"Cerejal",
    "gn:population":0,
    "gn:timezone":"Europe/Lisbon",
    "iso:country":"PT",
    "wof:name":"Cerejal",
    "wof:placetype":"locality"
},
  "geometry": {"coordinates":[-7.69848,39.70098],"type":"Point"}
}