{
  "type": "Feature",
  "properties": {
    "gn:admin1_code":"18",
    "gn:admin2_code":"1401",
    "gn:admin3_code":"140118.0",
    "gn:asciiname":"Fontes",
    "gn:country_code":"PT",
    "gn:dem":227,
    "gn:feature_class":"P",
    "gn:feature_code":"PPL",
    "gn:name":"Fontes",
    "gn:population":627,
    "gn:timezone":"Europe/Lisbon",
    "iso:country":"PT",
    "wof:name":"Fontes",
    "wof:placetype":"locality",
    "wof:population":627
},
  "geometry": {"coordinates":[-8.23137,39.60674],"type":"Point"}
}