{
  "type": "Feature",
  "properties": {
    "gn:admin1_code":"16",
    "gn:admin2_code":"1213",
    "gn:admin3_code":"121306.0",
    "gn:asciiname":"Hospicio",
    "gn:country_code":"PT",
    "gn:dem":151,
    "gn:feature_class":"P",
    "gn:feature_code":"PPL",
    "gn:name":"Hosp\u00edcio",
    "gn:population":0,
    "gn:timezone":"Europe/Lisbon",
    "iso:country":"PT",
    "wof:name":"Hospicio",
    "wof:placetype":"locality"
},
  "geometry": {"coordinates":[-7.96667,39.25236],"type":"Point"}
}