{
  "type": "Feature",
  "properties": {
    "gn:admin1_code":"14",
    "gn:admin2_code":"1112",
    "gn:admin3_code":"111202.0",
    "gn:asciiname":"Moita",
    "gn:country_code":"PT",
    "gn:dem":214,
    "gn:feature_class":"P",
    "gn:feature_code":"PPL",
    "gn:name":"Moita",
    "gn:population":0,
    "gn:timezone":"Europe/Lisbon",
    "iso:country":"PT",
    "name:cat_x_preferred":[
        "Moita"
    ],
    "name:ceb_x_preferred":[
        "Moita"
    ],
    "name:deu_x_preferred":[
        "Moita"
    ],
    "name:epo_x_preferred":[
        "Moita"
    ],
    "name:eus_x_preferred":[
        "Moita"
    ],
    "name:fin_x_preferred":[
        "Moita"
    ],
    "name:fra_x_preferred":[
        "Moita"
    ],
    "name:hun_x_preferred":[
        "Moita"
    ],
    "name:ita_x_preferred":[
        "Moita"
    ],
    "name:msa_x_preferred":[
        "Perbandaran Moita"
    ],
    "name:nld_x_preferred":[
        "Moita"
    ],
    "name:oci_x_preferred":[
        "Moita"
    ],
    "name:pol_x_preferred":[
        "Moita"
    ],
    "name:por_x_preferred":[
        "Moita"
    ],
    "name:rus_x_preferred":[
        "\u041c\u043e\u0439\u0442\u0430"
    ],
    "name:spa_x_preferred":[
        "Moita"
    ],
    "name:tur_x_preferred":[
        "Moita"
    ],
    "name:ukr_x_preferred":[
        "\u041c\u043e\u0439\u0442\u0430"
    ],
    "name:vie_x_preferred":[
        "Moita"
    ],
    "name:vol_x_preferred":[
        "Moita"
    ],
    "name:war_x_preferred":[
        "Moita"
    ],
    "name:zho_x_preferred":[
        "\u83ab\u4f0a\u5854"
    ],
    "wof:name":"Moita",
    "wof:placetype":"locality"
},
  "geometry": {"coordinates":[-9.1937,38.97022],"type":"Point"}
}