{
  "type": "Feature",
  "properties": {
    "gn:admin1_code":"14",
    "gn:admin2_code":"1112",
    "gn:admin3_code":"111202.0",
    "gn:asciiname":"Moita",
    "gn:country_code":"PT",
    "gn:dem":214,
    "gn:feature_class":"P",
    "gn:feature_code":"PPL",
    "gn:name":"Moita",
    "gn:population":0,
    "gn:timezone":"Europe/Lisbon",
    "iso:country":"PT",
    "wof:name":"Moita",
    "wof:placetype":"locality"
},
  "geometry": {"coordinates":[-9.1937,38.97022],"type":"Point"}
}