{
  "type": "Feature",
  "properties": {
    "gn:admin1_code":"06",
    "gn:admin2_code":"0509",
    "gn:admin3_code":"50907.0",
    "gn:asciiname":"Feiteira",
    "gn:country_code":"PT",
    "gn:dem":597,
    "gn:feature_class":"P",
    "gn:feature_code":"PPL",
    "gn:name":"Feiteira",
    "gn:population":0,
    "gn:timezone":"Europe/Lisbon",
    "iso:country":"PT",
    "wof:name":"Feiteira",
    "wof:placetype":"locality"
},
  "geometry": {"coordinates":[-7.98448,39.85212],"type":"Point"}
}