{
  "type": "Feature",
  "properties": {
    "gn:gn_country":"PT",
    "gn:gn_fcode":"PPL",
    "gn:gn_pop":5085,
    "gn:population":5085,
    "iso:country":"PT",
    "name:ast_x_preferred":[
        "Louri\u00e7al"
    ],
    "name:cat_x_preferred":[
        "Louri\u00e7al"
    ],
    "name:ceb_x_preferred":[
        "Louri\u00e7al"
    ],
    "name:deu_x_preferred":[
        "Louri\u00e7al"
    ],
    "name:eng_x_preferred":[
        "Louri\u00e7al"
    ],
    "name:fra_x_preferred":[
        "Louri\u00e7al"
    ],
    "name:kaz_x_preferred":[
        "\u041b\u043e\u0440\u0438\u0441\u0430\u043b"
    ],
    "name:msa_x_preferred":[
        "Louri\u00e7al"
    ],
    "name:nan_x_preferred":[
        "Louri\u00e7al"
    ],
    "name:nld_x_preferred":[
        "Louri\u00e7al"
    ],
    "name:por_x_preferred":[
        "Louri\u00e7al"
    ],
    "name:rus_x_preferred":[
        "\u041b\u043e\u0440\u0438\u0441\u0430\u043b"
    ],
    "name:spa_x_preferred":[
        "Louri\u00e7al"
    ],
    "qs_pg:aaroncc":"PT",
    "qs_pg:gn_country":"PT",
    "qs_pg:gn_fcode":"PPL",
    "qs_pg:gn_pop":5085,
    "qs_pg:name":"Louri\u00e7al",
    "qs_pg:name_adm0":"Portugal",
    "qs_pg:name_adm1":"Aveiro",
    "qs_pg:photos_9r":0,
    "qs_pg:photos_sr":0,
    "qs_pg:pop_sr":5,
    "qs_pg:qs_pg_placetype":"locality",
    "qs_pg:qs_pg_placetype_gp":"Town",
    "qs_pg:woe_adm0":23424925,
    "woe:adm0_id":23424925,
    "woe:name_adm0":"Portugal",
    "woe:name_adm1":"Aveiro",
    "woe:placetype":"Town",
    "wof:name":"Louri\u00e7al",
    "wof:placetype":"locality",
    "wof:population":5085
},
  "geometry": {"coordinates":[-8.73736,40.0039],"type":"Point"}
}