{
  "type": "Feature",
  "properties": {
    "gn:admin1_code":"04",
    "gn:admin2_code":"0312",
    "gn:admin3_code":"31237.0",
    "gn:asciiname":"Veiga",
    "gn:country_code":"PT",
    "gn:dem":120,
    "gn:feature_class":"P",
    "gn:feature_code":"PPL",
    "gn:name":"Veiga",
    "gn:population":0,
    "gn:timezone":"Europe/Lisbon",
    "iso:country":"PT",
    "wof:name":"Veiga",
    "wof:placetype":"locality"
},
  "geometry": {"coordinates":[-8.51667,41.46667],"type":"Point"}
}