{
  "type": "Feature",
  "properties": {
    "gn:admin1_code":"06",
    "gn:admin2_code":"0502",
    "gn:admin3_code":"50203.0",
    "gn:asciiname":"Azinheira",
    "gn:country_code":"PT",
    "gn:dem":367,
    "gn:feature_class":"P",
    "gn:feature_code":"PPL",
    "gn:name":"Azinheira",
    "gn:population":0,
    "gn:timezone":"Europe/Lisbon",
    "iso:country":"PT",
    "wof:name":"Azinheira",
    "wof:placetype":"locality"
},
  "geometry": {"coordinates":[-7.58375,39.78488],"type":"Point"}
}