{
  "type": "Feature",
  "properties": {
    "gn:admin1_code":"03",
    "gn:admin2_code":"0209",
    "gn:admin3_code":"20901.0",
    "gn:asciiname":"Atafona",
    "gn:country_code":"PT",
    "gn:dem":159,
    "gn:feature_class":"P",
    "gn:feature_code":"PPL",
    "gn:name":"Atafona",
    "gn:population":0,
    "gn:timezone":"Europe/Lisbon",
    "iso:country":"PT",
    "wof:name":"Atafona",
    "wof:placetype":"locality"
},
  "geometry": {"coordinates":[-7.88251,37.77797],"type":"Point"}
}