{
  "type": "Feature",
  "properties": {
    "gn:admin1_code":"7.0",
    "gn:admin2_code":"0602",
    "gn:admin3_code":"60207.0",
    "gn:asciiname":"Corgos",
    "gn:country_code":"PT",
    "gn:dem":59,
    "gn:feature_class":"P",
    "gn:feature_code":"PPL",
    "gn:name":"Corgos",
    "gn:population":0,
    "gn:timezone":"Europe/Lisbon",
    "iso:country":"PT",
    "wof:name":"Corgos",
    "wof:placetype":"locality"
},
  "geometry": {"coordinates":[-8.63333,40.41667],"type":"Point"}
}