{
  "type": "Feature",
  "properties": {
    "gn:admin1_code":"21.0",
    "gn:admin2_code":"1701",
    "gn:admin3_code":"170118.0",
    "gn:asciiname":"Cabeda",
    "gn:country_code":"PT",
    "gn:dem":502,
    "gn:feature_class":"P",
    "gn:feature_code":"PPL",
    "gn:name":"Cabeda",
    "gn:population":0,
    "gn:timezone":"Europe/Lisbon",
    "iso:country":"PT",
    "wof:name":"Cabeda",
    "wof:placetype":"locality"
},
  "geometry": {"coordinates":[-7.55978,41.30655],"type":"Point"}
}