{
  "type": "Feature",
  "properties": {
    "gn:admin1_code":"22.0",
    "gn:admin2_code":"1824",
    "gn:admin3_code":"182410.0",
    "gn:asciiname":"Nogueira",
    "gn:country_code":"PT",
    "gn:dem":295,
    "gn:feature_class":"P",
    "gn:feature_code":"PPL",
    "gn:name":"Nogueira",
    "gn:population":0,
    "gn:timezone":"Europe/Lisbon",
    "iso:country":"PT",
    "wof:name":"Nogueira",
    "wof:placetype":"locality"
},
  "geometry": {"coordinates":[-8.02166,40.73789],"type":"Point"}
}