{
  "type": "Feature",
  "properties": {
    "gn:admin1_code":"4.0",
    "gn:admin2_code":"0304",
    "gn:admin3_code":"30415.0",
    "gn:asciiname":"Eiro",
    "gn:country_code":"PT",
    "gn:dem":457,
    "gn:feature_class":"P",
    "gn:feature_code":"PPL",
    "gn:name":"Eir\u00f3",
    "gn:population":0,
    "gn:timezone":"Europe/Lisbon",
    "iso:country":"PT",
    "wof:name":"Eiro",
    "wof:placetype":"locality"
},
  "geometry": {"coordinates":[-7.97139,41.55018],"type":"Point"}
}