{
  "type": "Feature",
  "properties": {
    "gn:admin1_code":"13",
    "gn:admin2_code":"1005",
    "gn:admin3_code":"100503.0",
    "gn:asciiname":"Rolica",
    "gn:country_code":"PT",
    "gn:dem":33,
    "gn:feature_class":"P",
    "gn:feature_code":"PPL",
    "gn:name":"Roli\u00e7a",
    "gn:population":0,
    "gn:timezone":"Europe/Lisbon",
    "iso:country":"PT",
    "name:und_x_variant":[
        "Roli\u00e7a"
    ],
    "wof:name":"Rolica",
    "wof:placetype":"locality"
},
  "geometry": {"coordinates":[-9.18376,39.31315],"type":"Point"}
}