{
  "type": "Feature",
  "properties": {
    "gn:admin1_code":"17.0",
    "gn:admin2_code":"1301",
    "gn:admin3_code":"130124.0",
    "gn:asciiname":"Oliveira",
    "gn:country_code":"PT",
    "gn:dem":215,
    "gn:feature_class":"P",
    "gn:feature_code":"PPL",
    "gn:name":"Oliveira",
    "gn:population":0,
    "gn:timezone":"Europe/Lisbon",
    "iso:country":"PT",
    "wof:name":"Oliveira",
    "wof:placetype":"locality"
},
  "geometry": {"coordinates":[-8.20168,41.25741],"type":"Point"}
}