{
  "type": "Feature",
  "properties": {
    "gn:admin1_code":"04",
    "gn:admin2_code":"0312",
    "gn:admin3_code":"31208.0",
    "gn:asciiname":"Ribainho",
    "gn:country_code":"PT",
    "gn:dem":88,
    "gn:feature_class":"P",
    "gn:feature_code":"PPL",
    "gn:name":"Ribainho",
    "gn:population":0,
    "gn:timezone":"Europe/Lisbon",
    "iso:country":"PT",
    "wof:name":"Ribainho",
    "wof:placetype":"locality"
},
  "geometry": {"coordinates":[-8.52066,41.39346],"type":"Point"}
}