{
  "type": "Feature",
  "properties": {
    "gn:admin1_code":"18",
    "gn:admin2_code":"1411",
    "gn:admin3_code":"141105.0",
    "gn:asciiname":"Rio Cimeiro",
    "gn:country_code":"PT",
    "gn:dem":201,
    "gn:feature_class":"P",
    "gn:feature_code":"PPL",
    "gn:name":"Rio Cimeiro",
    "gn:population":0,
    "gn:timezone":"Europe/Lisbon",
    "iso:country":"PT",
    "wof:name":"Rio Cimeiro",
    "wof:placetype":"locality"
},
  "geometry": {"coordinates":[-8.23803,39.76128],"type":"Point"}
}