{
  "type": "Feature",
  "properties": {
    "gn:admin1_code":"07",
    "gn:admin2_code":"0603",
    "gn:admin3_code":"60329.0",
    "gn:asciiname":"Zorro",
    "gn:country_code":"PT",
    "gn:dem":128,
    "gn:feature_class":"P",
    "gn:feature_code":"PPL",
    "gn:name":"Zorro",
    "gn:population":0,
    "gn:timezone":"Europe/Lisbon",
    "iso:country":"PT",
    "name:ara_x_preferred":[
        "\u0632\u0648\u0631\u0648"
    ],
    "name:arg_x_preferred":[
        "El Zorro"
    ],
    "name:bre_x_preferred":[
        "Zorro"
    ],
    "name:bul_x_preferred":[
        "\u0417\u043e\u0440\u043e"
    ],
    "name:ces_x_preferred":[
        "Zorro"
    ],
    "name:dan_x_preferred":[
        "Zorro"
    ],
    "name:deu_x_preferred":[
        "Zorro"
    ],
    "name:ell_x_preferred":[
        "\u0396\u03bf\u03c1\u03cc"
    ],
    "name:epo_x_preferred":[
        "Zorro"
    ],
    "name:eus_x_preferred":[
        "Zorro"
    ],
    "name:fas_x_preferred":[
        "\u0632\u0648\u0631\u0648"
    ],
    "name:fin_x_preferred":[
        "Zorro"
    ],
    "name:fra_x_preferred":[
        "Zorro"
    ],
    "name:frp_x_preferred":[
        "Zorr\u00f4"
    ],
    "name:gle_x_preferred":[
        "Zorro"
    ],
    "name:heb_x_preferred":[
        "\u05d6\u05d5\u05e8\u05d5"
    ],
    "name:hun_x_preferred":[
        "Zorro"
    ],
    "name:hye_x_preferred":[
        "\u0536\u0578\u0580\u0578"
    ],
    "name:ind_x_preferred":[
        "Zorro"
    ],
    "name:ita_x_preferred":[
        "Zorro"
    ],
    "name:jpn_x_preferred":[
        "\u602a\u5091\u30be\u30ed"
    ],
    "name:nld_x_preferred":[
        "Zorro"
    ],
    "name:nor_x_preferred":[
        "Zorro"
    ],
    "name:pol_x_preferred":[
        "Zorro"
    ],
    "name:por_x_preferred":[
        "Zorro"
    ],
    "name:ron_x_preferred":[
        "Zorro"
    ],
    "name:rus_x_preferred":[
        "\u0417\u043e\u0440\u0440\u043e"
    ],
    "name:spa_x_preferred":[
        "El Zorro"
    ],
    "name:swe_x_preferred":[
        "Zorro"
    ],
    "name:tgl_x_preferred":[
        "Zorro"
    ],
    "name:tur_x_preferred":[
        "Zorro"
    ],
    "name:ukr_x_preferred":[
        "\u0417\u043e\u0440\u0440\u043e"
    ],
    "name:vie_x_preferred":[
        "Zorro"
    ],
    "wof:name":"Zorro",
    "wof:placetype":"locality"
},
  "geometry": {"coordinates":[-8.35425,40.20254],"type":"Point"}
}