{
  "type": "Feature",
  "properties": {
    "gn:admin1_code":"07",
    "gn:admin2_code":"0603",
    "gn:admin3_code":"60329.0",
    "gn:asciiname":"Zorro",
    "gn:country_code":"PT",
    "gn:dem":128,
    "gn:feature_class":"P",
    "gn:feature_code":"PPL",
    "gn:name":"Zorro",
    "gn:population":0,
    "gn:timezone":"Europe/Lisbon",
    "iso:country":"PT",
    "wof:name":"Zorro",
    "wof:placetype":"locality"
},
  "geometry": {"coordinates":[-8.35425,40.20254],"type":"Point"}
}