{
  "type": "Feature",
  "properties": {
    "gn:admin1_code":"19",
    "gn:admin2_code":"1509",
    "gn:admin3_code":"150903.0",
    "gn:asciiname":"Corgos",
    "gn:country_code":"PT",
    "gn:dem":123,
    "gn:feature_class":"P",
    "gn:feature_code":"PPL",
    "gn:name":"Corgos",
    "gn:population":0,
    "gn:timezone":"Europe/Lisbon",
    "iso:country":"PT",
    "wof:name":"Corgos",
    "wof:placetype":"locality"
},
  "geometry": {"coordinates":[-8.65345,37.85279],"type":"Point"}
}