{
  "type": "Feature",
  "properties": {
    "gn:admin1_code":"06",
    "gn:admin2_code":"0503",
    "gn:admin3_code":"50315.0",
    "gn:asciiname":"Quinta da Franca de Baixo",
    "gn:country_code":"PT",
    "gn:dem":437,
    "gn:feature_class":"P",
    "gn:feature_code":"PPL",
    "gn:name":"Quinta da Fran\u00e7a de Baixo",
    "gn:population":0,
    "gn:timezone":"Europe/Lisbon",
    "iso:country":"PT",
    "wof:name":"Quinta da Franca de Baixo",
    "wof:placetype":"locality"
},
  "geometry": {"coordinates":[-7.43234,40.27371],"type":"Point"}
}