{
  "type": "Feature",
  "properties": {
    "gn:admin1_code":"08",
    "gn:admin2_code":"0709",
    "gn:admin3_code":"70902.0",
    "gn:asciiname":"Cu Marinho",
    "gn:country_code":"PT",
    "gn:dem":306,
    "gn:feature_class":"P",
    "gn:feature_code":"PPL",
    "gn:name":"Cu Marinho",
    "gn:population":0,
    "gn:timezone":"Europe/Lisbon",
    "iso:country":"PT",
    "wof:name":"Cu Marinho",
    "wof:placetype":"locality"
},
  "geometry": {"coordinates":[-7.64504,38.3316],"type":"Point"}
}