{
  "type": "Feature",
  "properties": {
    "gn:admin1_code":"14",
    "gn:admin2_code":"1102",
    "gn:admin3_code":"110201.0",
    "gn:asciiname":"Alcubela de Baixo",
    "gn:country_code":"PT",
    "gn:dem":194,
    "gn:feature_class":"P",
    "gn:feature_code":"PPL",
    "gn:name":"Alcubela de Baixo",
    "gn:population":0,
    "gn:timezone":"Europe/Lisbon",
    "iso:country":"PT",
    "wof:name":"Alcubela de Baixo",
    "wof:placetype":"locality"
},
  "geometry": {"coordinates":[-9.15045,38.95373],"type":"Point"}
}