{
  "type": "Feature",
  "properties": {
    "gn:admin1_code":"20.0",
    "gn:admin2_code":"1603",
    "gn:admin3_code":"160302.0",
    "gn:asciiname":"Queimadelo",
    "gn:country_code":"PT",
    "gn:dem":1066,
    "gn:feature_class":"P",
    "gn:feature_code":"PPL",
    "gn:name":"Queimadelo",
    "gn:population":0,
    "gn:timezone":"Europe/Lisbon",
    "iso:country":"PT",
    "wof:name":"Queimadelo",
    "wof:placetype":"locality"
},
  "geometry": {"coordinates":[-8.15031,42.055],"type":"Point"}
}