{
  "type": "Feature",
  "properties": {
    "gn:admin1_code":"20.0",
    "gn:admin2_code":"1605",
    "gn:admin3_code":"160501.0",
    "gn:asciiname":"Agualonga",
    "gn:country_code":"PT",
    "gn:dem":289,
    "gn:feature_class":"P",
    "gn:feature_code":"PPL",
    "gn:name":"Agualonga",
    "gn:population":0,
    "gn:timezone":"Europe/Lisbon",
    "iso:country":"PT",
    "name:ceb_x_preferred":[
        "Agualonga"
    ],
    "name:deu_x_preferred":[
        "Agualonga"
    ],
    "name:fas_x_preferred":[
        "\u0627\u06af\u0648\u0627\u0644\u0627\u0646\u06af\u0627"
    ],
    "name:kaz_x_preferred":[
        "\u0410\u0433\u0443\u0430\u043b\u043e\u043d\u0433\u0430"
    ],
    "name:nld_x_preferred":[
        "Agualonga"
    ],
    "name:por_x_preferred":[
        "Agualonga"
    ],
    "name:rus_x_preferred":[
        "\u0410\u0433\u0443\u0430\u043b\u043e\u043d\u0433\u0430"
    ],
    "name:spa_x_preferred":[
        "Agualonga"
    ],
    "name:urd_x_preferred":[
        "\u0627\u06af\u0648\u0627\u0644\u0648\u0646\u06af\u0627"
    ],
    "wof:name":"Agualonga",
    "wof:placetype":"locality"
},
  "geometry": {"coordinates":[-8.61657,41.88903],"type":"Point"}
}