{
  "type": "Feature",
  "properties": {
    "gn:admin1_code":"11",
    "gn:admin2_code":"0912",
    "gn:admin3_code":"91227.0",
    "gn:asciiname":"Vide",
    "gn:country_code":"PT",
    "gn:dem":298,
    "gn:feature_class":"P",
    "gn:feature_code":"PPL",
    "gn:name":"Vide",
    "gn:population":761,
    "gn:timezone":"Europe/Lisbon",
    "iso:country":"PT",
    "wof:name":"Vide",
    "wof:placetype":"locality",
    "wof:population":761
},
  "geometry": {"coordinates":[-7.78401,40.29528],"type":"Point"}
}