{
  "type": "Feature",
  "properties": {
    "gn:admin1_code":"20.0",
    "gn:admin2_code":"1606",
    "gn:admin3_code":"160602.0",
    "gn:asciiname":"Boivaes",
    "gn:country_code":"PT",
    "gn:dem":377,
    "gn:feature_class":"P",
    "gn:feature_code":"PPL",
    "gn:name":"Boiv\u00e3es",
    "gn:population":0,
    "gn:timezone":"Europe/Lisbon",
    "iso:country":"PT",
    "wof:name":"Boivaes",
    "wof:placetype":"locality"
},
  "geometry": {"coordinates":[-8.4523,41.7634],"type":"Point"}
}