{
  "type": "Feature",
  "properties": {
    "gn:admin1_code":"14",
    "gn:admin2_code":"1108",
    "gn:admin3_code":"110801.0",
    "gn:asciiname":"Casa Nova",
    "gn:country_code":"PT",
    "gn:dem":72,
    "gn:feature_class":"P",
    "gn:feature_code":"PPL",
    "gn:name":"Casa Nova",
    "gn:population":0,
    "gn:timezone":"Europe/Lisbon",
    "iso:country":"PT",
    "wof:name":"Casa Nova",
    "wof:placetype":"locality"
},
  "geometry": {"coordinates":[-9.31644,39.22139],"type":"Point"}
}