{
  "type": "Feature",
  "properties": {
    "gn:admin1_code":"7.0",
    "gn:admin2_code":"0616",
    "gn:admin3_code":"61613.0",
    "gn:asciiname":"Casal da Igreja",
    "gn:country_code":"PT",
    "gn:dem":225,
    "gn:feature_class":"P",
    "gn:feature_code":"PPL",
    "gn:name":"Casal da Igreja",
    "gn:population":0,
    "gn:timezone":"Europe/Lisbon",
    "iso:country":"PT",
    "wof:name":"Casal da Igreja",
    "wof:placetype":"locality"
},
  "geometry": {"coordinates":[-8.05914,40.3193],"type":"Point"}
}