{
  "type": "Feature",
  "properties": {
    "gn:admin1_code":"07",
    "gn:admin2_code":"0605",
    "gn:admin3_code":"60501.0",
    "gn:asciiname":"Porto Carvalhal",
    "gn:country_code":"PT",
    "gn:dem":34,
    "gn:feature_class":"P",
    "gn:feature_code":"PPL",
    "gn:name":"Porto Carvalhal",
    "gn:population":0,
    "gn:timezone":"Europe/Lisbon",
    "iso:country":"PT",
    "wof:name":"Porto Carvalhal",
    "wof:placetype":"locality"
},
  "geometry": {"coordinates":[-8.77688,40.1915],"type":"Point"}
}