{
  "type": "Feature",
  "properties": {
    "gn:admin1_code":"20.0",
    "gn:admin2_code":"1608",
    "gn:admin3_code":"160804.0",
    "gn:asciiname":"Outeiro",
    "gn:country_code":"PT",
    "gn:dem":16,
    "gn:feature_class":"P",
    "gn:feature_code":"PPL",
    "gn:name":"Outeiro",
    "gn:population":0,
    "gn:timezone":"Europe/Madrid",
    "iso:country":"PT",
    "name:ceb_x_preferred":[
        "Outeiro"
    ],
    "name:deu_x_preferred":[
        "Outeiro"
    ],
    "name:fra_x_preferred":[
        "Outeiro"
    ],
    "name:glg_x_preferred":[
        "Outeiro"
    ],
    "name:nld_x_preferred":[
        "Outeiro"
    ],
    "name:por_x_preferred":[
        "Outeiro"
    ],
    "name:swe_x_preferred":[
        "Outeiro"
    ],
    "name:tur_x_preferred":[
        "Outeiro"
    ],
    "name:ukr_x_preferred":[
        "\u041e\u0442\u0435\u0439\u0440\u0443"
    ],
    "wof:name":"Outeiro",
    "wof:placetype":"locality"
},
  "geometry": {"coordinates":[-8.65395,42.01731],"type":"Point"}
}