{
  "type": "Feature",
  "properties": {
    "gn:admin1_code":"20.0",
    "gn:admin2_code":"1608",
    "gn:admin3_code":"160804.0",
    "gn:asciiname":"Outeiro",
    "gn:country_code":"PT",
    "gn:dem":16,
    "gn:feature_class":"P",
    "gn:feature_code":"PPL",
    "gn:name":"Outeiro",
    "gn:population":0,
    "gn:timezone":"Europe/Madrid",
    "iso:country":"PT",
    "wof:name":"Outeiro",
    "wof:placetype":"locality"
},
  "geometry": {"coordinates":[-8.65395,42.01731],"type":"Point"}
}