{
  "type": "Feature",
  "properties": {
    "gn:country":"PT",
    "gn:fcode":"ADM3",
    "gn:population":0,
    "iso:country":"PT",
    "name:bpy_x_preferred":[
        "\u09b8\u09be\u0993 \u09ac\u09c7\u09a8\u099f\u09cb"
    ],
    "name:ceb_x_preferred":[
        "S\u00e3o Bento"
    ],
    "name:deu_x_preferred":[
        "S\u00e3o Bento"
    ],
    "name:fra_x_preferred":[
        "S\u00e3o Bento"
    ],
    "name:ita_x_preferred":[
        "S\u00e3o Bento"
    ],
    "name:kaz_x_preferred":[
        "\u0421\u0430\u043d-\u0411\u0435\u043d\u0442\u0443"
    ],
    "name:nld_x_preferred":[
        "S\u00e3o Bento"
    ],
    "name:nor_x_preferred":[
        "S\u00e3o Bento"
    ],
    "name:pol_x_preferred":[
        "S\u00e3o Bento"
    ],
    "name:por_x_preferred":[
        "S\u00e3o Bento"
    ],
    "name:rus_x_preferred":[
        "\u0421\u0430\u043d-\u0411\u0435\u043d\u0442\u0443"
    ],
    "name:spa_x_preferred":[
        "S\u00e3o Bento"
    ],
    "name:swe_x_preferred":[
        "S\u00e3o Bento"
    ],
    "name:vie_x_preferred":[
        "S\u00e3o Bento"
    ],
    "name:vol_x_preferred":[
        "S\u00e3o Bento"
    ],
    "qs_pg:aaroncc":"PT",
    "qs_pg:gn_country":"PT",
    "qs_pg:gn_fcode":"ADM3",
    "qs_pg:gn_pop":0,
    "qs_pg:name":"S\u00e3o Bento",
    "qs_pg:photos_9r":0,
    "qs_pg:photos_sr":0,
    "qs_pg:pop_sr":0,
    "qs_pg:qs_pg_placetype":"localadmin",
    "wof:name":"S\u00e3o Bento",
    "wof:placetype":"localadmin"
},
  "geometry": {"coordinates":[-8.77317,39.51778],"type":"Point"}
}