{
  "type": "Feature",
  "properties": {
    "gn:gn_country":"PT",
    "gn:gn_fcode":"PPL",
    "gn:gn_pop":4169,
    "gn:population":4169,
    "iso:country":"PT",
    "name:chi_x_preferred":[
        "Pardilh\u00f3"
    ],
    "name:dut_x_preferred":[
        "Pardilh\u00f3"
    ],
    "name:eng_x_preferred":[
        "Pardilh\u00f3"
    ],
    "name:fre_x_preferred":[
        "Pardilh\u00f3"
    ],
    "name:ger_x_preferred":[
        "Pardilh\u00f3"
    ],
    "name:kaz_x_preferred":[
        "\u041f\u0430\u0440\u0434\u0438\u043b\u044c\u043e"
    ],
    "name:por_x_preferred":[
        "Pardilh\u00f3"
    ],
    "name:rus_x_preferred":[
        "\u041f\u0430\u0440\u0434\u0438\u043b\u044c\u043e"
    ],
    "name:spa_x_preferred":[
        "Pardilh\u00f3"
    ],
    "qs_pg:aaroncc":"PT",
    "qs_pg:gn_country":"PT",
    "qs_pg:gn_fcode":"PPL",
    "qs_pg:gn_pop":4169,
    "qs_pg:name":"Pardilh\u00f3",
    "qs_pg:name_adm0":"Portugal",
    "qs_pg:name_adm1":"Aveiro",
    "qs_pg:photos_9k":1,
    "qs_pg:photos_9r":1,
    "qs_pg:photos_all":10,
    "qs_pg:photos_sr":0,
    "qs_pg:pop_sr":4,
    "qs_pg:qs_pg_placetype":"locality",
    "qs_pg:qs_pg_placetype_gp":"Town",
    "qs_pg:woe_adm0":23424925,
    "woe:adm0_id":23424925,
    "woe:name_adm0":"Portugal",
    "woe:name_adm1":"Aveiro",
    "woe:placetype":"Town",
    "wof:name":"Pardilh\u00f3",
    "wof:placetype":"locality",
    "wof:population":4169
},
  "geometry": {"coordinates":[-8.62598,40.79925],"type":"Point"}
}