{
  "type": "Feature",
  "properties": {
    "gn:admin1_code":"11.0",
    "gn:admin2_code":"0913",
    "gn:admin3_code":"91312.0",
    "gn:asciiname":"Golfar",
    "gn:country_code":"PT",
    "gn:dem":785,
    "gn:feature_class":"P",
    "gn:feature_code":"PPL",
    "gn:name":"Golfar",
    "gn:population":0,
    "gn:timezone":"Europe/Lisbon",
    "iso:country":"PT",
    "wof:name":"Golfar",
    "wof:placetype":"locality"
},
  "geometry": {"coordinates":[-7.334,40.81461],"type":"Point"}
}