{
  "type": "Feature",
  "properties": {
    "gn:admin1_code":"21.0",
    "gn:admin2_code":"1712",
    "gn:admin3_code":"171207.0",
    "gn:asciiname":"Avarenta",
    "gn:country_code":"PT",
    "gn:dem":485,
    "gn:feature_class":"P",
    "gn:feature_code":"PPL",
    "gn:name":"Avarenta",
    "gn:population":0,
    "gn:timezone":"Europe/Lisbon",
    "iso:country":"PT",
    "wof:name":"Avarenta",
    "wof:placetype":"locality"
},
  "geometry": {"coordinates":[-7.39266,41.57214000000001],"type":"Point"}
}