{
  "type": "Feature",
  "properties": {
    "gn:admin1_code":"4.0",
    "gn:admin2_code":"0313",
    "gn:admin3_code":"31326.0",
    "gn:asciiname":"Marrancos",
    "gn:country_code":"PT",
    "gn:dem":198,
    "gn:feature_class":"P",
    "gn:feature_code":"PPL",
    "gn:name":"Marrancos",
    "gn:population":0,
    "gn:timezone":"Europe/Lisbon",
    "iso:country":"PT",
    "wof:name":"Marrancos",
    "wof:placetype":"locality"
},
  "geometry": {"coordinates":[-8.52022,41.66693],"type":"Point"}
}