{
  "type": "Feature",
  "properties": {
    "gn:admin1_code":"2.0",
    "gn:admin2_code":"0109",
    "gn:admin3_code":"10910.0",
    "gn:asciiname":"Casal de Aca",
    "gn:country_code":"PT",
    "gn:dem":214,
    "gn:feature_class":"P",
    "gn:feature_code":"PPL",
    "gn:name":"Casal de A\u00e7a",
    "gn:population":0,
    "gn:timezone":"Europe/Lisbon",
    "iso:country":"PT",
    "wof:name":"Casal de Aca",
    "wof:placetype":"locality"
},
  "geometry": {"coordinates":[-8.47587,40.9791],"type":"Point"}
}