{
  "type": "Feature",
  "properties": {
    "gn:admin1_code":"13",
    "gn:admin2_code":"1001",
    "gn:admin3_code":"100107.0",
    "gn:asciiname":"Casalinho",
    "gn:country_code":"PT",
    "gn:dem":19,
    "gn:feature_class":"P",
    "gn:feature_code":"PPL",
    "gn:name":"Casalinho",
    "gn:population":0,
    "gn:timezone":"Europe/Lisbon",
    "iso:country":"PT",
    "wof:name":"Casalinho",
    "wof:placetype":"locality"
},
  "geometry": {"coordinates":[-8.98276,39.58964],"type":"Point"}
}