{
  "type": "Feature",
  "properties": {
    "gn:admin1_code":"20",
    "gn:admin2_code":"1609",
    "gn:admin3_code":"160915.0",
    "gn:asciiname":"Taboneira",
    "gn:country_code":"PT",
    "gn:dem":18,
    "gn:feature_class":"P",
    "gn:feature_code":"PPL",
    "gn:name":"Taboneira",
    "gn:population":0,
    "gn:timezone":"Europe/Lisbon",
    "iso:country":"PT",
    "wof:name":"Taboneira",
    "wof:placetype":"locality"
},
  "geometry": {"coordinates":[-8.68541,41.74109],"type":"Point"}
}