{
  "type": "Feature",
  "properties": {
    "gn:admin1_code":"20.0",
    "gn:admin2_code":"1610",
    "gn:admin3_code":"161012.0",
    "gn:asciiname":"Armada",
    "gn:country_code":"PT",
    "gn:dem":270,
    "gn:feature_class":"P",
    "gn:feature_code":"PPL",
    "gn:name":"Armada",
    "gn:population":0,
    "gn:timezone":"Europe/Lisbon",
    "iso:country":"PT",
    "wof:name":"Armada",
    "wof:placetype":"locality"
},
  "geometry": {"coordinates":[-8.66302,41.929],"type":"Point"}
}