{
  "type": "Feature",
  "properties": {
    "gn:admin1_code":"20.0",
    "gn:admin2_code":"1610",
    "gn:admin3_code":"161012.0",
    "gn:asciiname":"Armada",
    "gn:country_code":"PT",
    "gn:dem":270,
    "gn:feature_class":"P",
    "gn:feature_code":"PPL",
    "gn:name":"Armada",
    "gn:population":0,
    "gn:timezone":"Europe/Lisbon",
    "iso:country":"PT",
    "name:afr_x_preferred":[
        "Armada"
    ],
    "name:ara_x_preferred":[
        "\u0627\u0644\u0623\u0631\u0645\u0627\u062f\u0627"
    ],
    "name:cat_x_preferred":[
        "Armada"
    ],
    "name:ces_x_preferred":[
        "Arm\u00e1da"
    ],
    "name:deu_x_preferred":[
        "Armada"
    ],
    "name:ell_x_preferred":[
        "\u0391\u03c1\u03bc\u03ac\u03b4\u03b1"
    ],
    "name:fin_x_preferred":[
        "Armada"
    ],
    "name:fra_x_preferred":[
        "Armada"
    ],
    "name:glg_x_preferred":[
        "Armada"
    ],
    "name:heb_x_preferred":[
        "\u05d0\u05e8\u05de\u05d3\u05d4"
    ],
    "name:ind_x_preferred":[
        "Armada"
    ],
    "name:ita_x_preferred":[
        "Armada"
    ],
    "name:jpn_x_preferred":[
        "\u30a2\u30eb\u30de\u30c0"
    ],
    "name:kor_x_preferred":[
        "\uc544\ub9c8\ub2e4"
    ],
    "name:nld_x_preferred":[
        "Armada"
    ],
    "name:pol_x_preferred":[
        "Armada"
    ],
    "name:por_x_preferred":[
        "Armada"
    ],
    "name:rus_x_preferred":[
        "\u0410\u0440\u043c\u0430\u0434\u0430"
    ],
    "name:slk_x_preferred":[
        "Arm\u00e1da"
    ],
    "name:slv_x_preferred":[
        "Armada"
    ],
    "name:swe_x_preferred":[
        "Armada"
    ],
    "name:tur_x_preferred":[
        "Armada"
    ],
    "name:ukr_x_preferred":[
        "\u0410\u0440\u043c\u0430\u0434\u0430"
    ],
    "wof:name":"Armada",
    "wof:placetype":"locality"
},
  "geometry": {"coordinates":[-8.66302,41.929],"type":"Point"}
}