{
  "type": "Feature",
  "properties": {
    "gn:admin1_code":"5.0",
    "gn:admin2_code":"0412",
    "gn:admin3_code":"41213.0",
    "gn:asciiname":"Nunes",
    "gn:country_code":"PT",
    "gn:dem":558,
    "gn:feature_class":"P",
    "gn:feature_code":"PPL",
    "gn:name":"Nunes",
    "gn:population":0,
    "gn:timezone":"Europe/Lisbon",
    "iso:country":"PT",
    "name:bre_x_preferred":[
        "Nunes"
    ],
    "wof:name":"Nunes",
    "wof:placetype":"locality"
},
  "geometry": {"coordinates":[-6.98485,41.79517],"type":"Point"}
}