{
  "type": "Feature",
  "properties": {
    "gn:admin1_code":"08",
    "gn:admin2_code":"0701",
    "gn:admin3_code":"70101.0",
    "gn:asciiname":"Telheiros",
    "gn:country_code":"PT",
    "gn:dem":324,
    "gn:feature_class":"P",
    "gn:feature_code":"PPL",
    "gn:name":"Telheiros",
    "gn:population":0,
    "gn:timezone":"Europe/Lisbon",
    "iso:country":"PT",
    "wof:name":"Telheiros",
    "wof:placetype":"locality"
},
  "geometry": {"coordinates":[-7.40242,38.69651],"type":"Point"}
}