{
  "type": "Feature",
  "properties": {
    "gn:admin1_code":"21",
    "gn:admin2_code":"1701",
    "gn:admin3_code":"170117.0",
    "gn:asciiname":"Vila Verde",
    "gn:country_code":"PT",
    "gn:dem":716,
    "gn:feature_class":"P",
    "gn:feature_code":"PPL",
    "gn:name":"Vila Verde",
    "gn:population":0,
    "gn:timezone":"Europe/Lisbon",
    "iso:country":"PT",
    "wof:name":"Vila Verde",
    "wof:placetype":"locality"
},
  "geometry": {"coordinates":[-7.54896,41.36381],"type":"Point"}
}