{
  "type": "Feature",
  "properties": {
    "gn:admin1_code":"5.0",
    "gn:admin2_code":"0407",
    "gn:admin3_code":"40733.0",
    "gn:asciiname":"Miradeses",
    "gn:country_code":"PT",
    "gn:dem":252,
    "gn:feature_class":"P",
    "gn:feature_code":"PPL",
    "gn:name":"Miradeses",
    "gn:population":0,
    "gn:timezone":"Europe/Lisbon",
    "iso:country":"PT",
    "wof:name":"Miradeses",
    "wof:placetype":"locality"
},
  "geometry": {"coordinates":[-7.25683,41.56944],"type":"Point"}
}