{
  "type": "Feature",
  "properties": {
    "gn:admin1_code":"13",
    "gn:admin2_code":"1015",
    "gn:admin3_code":"101514.0",
    "gn:asciiname":"Pipa",
    "gn:country_code":"PT",
    "gn:dem":250,
    "gn:feature_class":"P",
    "gn:feature_code":"PPL",
    "gn:name":"Pipa",
    "gn:population":0,
    "gn:timezone":"Europe/Lisbon",
    "iso:country":"PT",
    "wof:name":"Pipa",
    "wof:placetype":"locality"
},
  "geometry": {"coordinates":[-8.54869,39.83312],"type":"Point"}
}