{
  "type": "Feature",
  "properties": {
    "gn:admin1_code":"13",
    "gn:admin2_code":"1015",
    "gn:admin3_code":"101514.0",
    "gn:asciiname":"Pipa",
    "gn:country_code":"PT",
    "gn:dem":250,
    "gn:feature_class":"P",
    "gn:feature_code":"PPL",
    "gn:name":"Pipa",
    "gn:population":0,
    "gn:timezone":"Europe/Lisbon",
    "iso:country":"PT",
    "name:cat_x_preferred":[
        "Pipa"
    ],
    "name:cdo_x_preferred":[
        "B\u00ec-b\u00e0"
    ],
    "name:ces_x_preferred":[
        "Pipa"
    ],
    "name:dan_x_preferred":[
        "Biwa"
    ],
    "name:deu_x_preferred":[
        "Pipa"
    ],
    "name:epo_x_preferred":[
        "\u0108inbivo"
    ],
    "name:eus_x_preferred":[
        "Pipa"
    ],
    "name:fin_x_preferred":[
        "Pipa"
    ],
    "name:fra_x_preferred":[
        "Pipa"
    ],
    "name:hun_x_preferred":[
        "Pi-p\u00e1"
    ],
    "name:hye_x_preferred":[
        "\u054a\u056b\u057a\u0561"
    ],
    "name:ind_x_preferred":[
        "Pipa"
    ],
    "name:jpn_x_preferred":[
        "\u7435\u7436#\u4e2d\u56fd\u7435\u7436"
    ],
    "name:msa_x_preferred":[
        "Pipa"
    ],
    "name:nld_x_preferred":[
        "Pipa"
    ],
    "name:nor_x_preferred":[
        "Pipa"
    ],
    "name:oci_x_preferred":[
        "Pipa"
    ],
    "name:pol_x_preferred":[
        "Pipa"
    ],
    "name:rus_x_preferred":[
        "\u041f\u0438\u043f\u0430"
    ],
    "name:slv_x_preferred":[
        "Pipa"
    ],
    "name:spa_x_preferred":[
        "Pipa"
    ],
    "name:tha_x_preferred":[
        "\u0e1c\u0e35\u0e1c\u0e32"
    ],
    "name:tur_x_preferred":[
        "Pipa"
    ],
    "name:ukr_x_preferred":[
        "\u041f\u0456\u043f\u0430"
    ],
    "name:zho_x_preferred":[
        "\u4e2d\u570b\u7435\u7436"
    ],
    "wof:name":"Pipa",
    "wof:placetype":"locality"
},
  "geometry": {"coordinates":[-8.54869,39.83312],"type":"Point"}
}