{
  "type": "Feature",
  "properties": {
    "gn:admin1_code":"13",
    "gn:admin2_code":"1016",
    "gn:admin3_code":"101606.0",
    "gn:asciiname":"Andainho",
    "gn:country_code":"PT",
    "gn:dem":117,
    "gn:feature_class":"P",
    "gn:feature_code":"PPL",
    "gn:name":"Andainho",
    "gn:population":0,
    "gn:timezone":"Europe/Lisbon",
    "iso:country":"PT",
    "wof:name":"Andainho",
    "wof:placetype":"locality"
},
  "geometry": {"coordinates":[-8.89068,39.6373],"type":"Point"}
}