{
  "type": "Feature",
  "properties": {
    "gn:admin1_code":"7.0",
    "gn:admin2_code":"0605",
    "gn:admin3_code":"60509.0",
    "gn:asciiname":"Outeiro",
    "gn:country_code":"PT",
    "gn:dem":87,
    "gn:feature_class":"P",
    "gn:feature_code":"PPL",
    "gn:name":"Outeiro",
    "gn:population":0,
    "gn:timezone":"Europe/Lisbon",
    "iso:country":"PT",
    "wof:name":"Outeiro",
    "wof:placetype":"locality"
},
  "geometry": {"coordinates":[-8.81302,40.05998],"type":"Point"}
}