{
  "type": "Feature",
  "properties": {
    "gn:admin1_code":"13",
    "gn:admin2_code":"1013",
    "gn:admin3_code":"101303.0",
    "gn:asciiname":"Vila Facaia",
    "gn:country_code":"PT",
    "gn:dem":392,
    "gn:feature_class":"P",
    "gn:feature_code":"PPL",
    "gn:name":"Vila Facaia",
    "gn:population":0,
    "gn:timezone":"Europe/Lisbon",
    "iso:country":"PT",
    "wof:name":"Vila Facaia",
    "wof:placetype":"locality"
},
  "geometry": {"coordinates":[-8.2233,39.93567],"type":"Point"}
}