{
  "type": "Feature",
  "properties": {
    "gn:admin1_code":"22.0",
    "gn:admin2_code":"1819",
    "gn:admin3_code":"181903.0",
    "gn:asciiname":"Barcos",
    "gn:country_code":"PT",
    "gn:dem":614,
    "gn:feature_class":"P",
    "gn:feature_code":"PPL",
    "gn:name":"Barcos",
    "gn:population":0,
    "gn:timezone":"Europe/Lisbon",
    "iso:country":"PT",
    "wof:name":"Barcos",
    "wof:placetype":"locality"
},
  "geometry": {"coordinates":[-7.59955,41.12232],"type":"Point"}
}