{
  "type": "Feature",
  "properties": {
    "gn:admin1_code":"2.0",
    "gn:admin2_code":"0104",
    "gn:admin3_code":"10413.0",
    "gn:asciiname":"Estrada",
    "gn:country_code":"PT",
    "gn:dem":395,
    "gn:feature_class":"P",
    "gn:feature_code":"PPL",
    "gn:name":"Estrada",
    "gn:population":0,
    "gn:timezone":"Europe/Lisbon",
    "iso:country":"PT",
    "name:cat_x_preferred":[
        "Estrada"
    ],
    "name:ceb_x_preferred":[
        "Estrada"
    ],
    "name:ces_x_preferred":[
        "Estrada"
    ],
    "name:deu_x_preferred":[
        "Estrada"
    ],
    "name:fra_x_preferred":[
        "Estrada"
    ],
    "name:ita_x_preferred":[
        "Estrada"
    ],
    "name:jpn_x_preferred":[
        "\u30a8\u30b9\u30c8\u30e9\u30fc\u30c0"
    ],
    "name:nld_x_preferred":[
        "Estrada"
    ],
    "name:pol_x_preferred":[
        "Estrada"
    ],
    "name:rus_x_preferred":[
        "\u042d\u0441\u0442\u0440\u0430\u0434\u0430"
    ],
    "name:spa_x_preferred":[
        "Estrada"
    ],
    "name:srp_x_preferred":[
        "\u0415\u0441\u0442\u0440\u0430\u0434\u0430"
    ],
    "name:swe_x_preferred":[
        "Estrada"
    ],
    "wof:name":"Estrada",
    "wof:placetype":"locality"
},
  "geometry": {"coordinates":[-8.37029,40.93774000000001],"type":"Point"}
}