{
  "type": "Feature",
  "properties": {
    "gn:admin1_code":"05",
    "gn:admin2_code":"0406",
    "gn:admin3_code":"40616.0",
    "gn:asciiname":"Vila Cha",
    "gn:country_code":"PT",
    "gn:dem":694,
    "gn:feature_class":"P",
    "gn:feature_code":"PPL",
    "gn:name":"Vila Ch\u00e3",
    "gn:population":0,
    "gn:timezone":"Europe/Lisbon",
    "iso:country":"PT",
    "wof:name":"Vila Cha",
    "wof:placetype":"locality"
},
  "geometry": {"coordinates":[-6.34408,41.42746],"type":"Point"}
}