{
  "type": "Feature",
  "properties": {
    "gn:admin1_code":"13",
    "gn:admin2_code":"1012",
    "gn:admin3_code":"101201.0",
    "gn:asciiname":"Sancheira Pequena",
    "gn:country_code":"PT",
    "gn:dem":96,
    "gn:feature_class":"P",
    "gn:feature_code":"PPL",
    "gn:name":"Sancheira Pequena",
    "gn:population":0,
    "gn:timezone":"Europe/Lisbon",
    "iso:country":"PT",
    "wof:name":"Sancheira Pequena",
    "wof:placetype":"locality"
},
  "geometry": {"coordinates":[-9.07559,39.34657],"type":"Point"}
}