{
  "type": "Feature",
  "properties": {
    "gn:admin1_code":"4.0",
    "gn:admin2_code":"0313",
    "gn:admin3_code":"31342.0",
    "gn:asciiname":"Fontainha",
    "gn:country_code":"PT",
    "gn:dem":22,
    "gn:feature_class":"P",
    "gn:feature_code":"PPL",
    "gn:name":"Fontainha",
    "gn:population":0,
    "gn:timezone":"Europe/Lisbon",
    "iso:country":"PT",
    "wof:name":"Fontainha",
    "wof:placetype":"locality"
},
  "geometry": {"coordinates":[-8.46891,41.5984],"type":"Point"}
}