{
  "type": "Feature",
  "properties": {
    "gn:admin1_code":"14",
    "gn:admin2_code":"1113",
    "gn:admin3_code":"111305.0",
    "gn:asciiname":"Boligueira",
    "gn:country_code":"PT",
    "gn:dem":123,
    "gn:feature_class":"P",
    "gn:feature_code":"PPL",
    "gn:name":"Boligueira",
    "gn:population":0,
    "gn:timezone":"Europe/Lisbon",
    "iso:country":"PT",
    "wof:name":"Boligueira",
    "wof:placetype":"locality"
},
  "geometry": {"coordinates":[-9.16216,39.04968],"type":"Point"}
}