{
  "type": "Feature",
  "properties": {
    "gn:admin1_code":"22.0",
    "gn:asciiname":"Foz Dao",
    "gn:country_code":"PT",
    "gn:dem":124,
    "gn:feature_class":"P",
    "gn:feature_code":"PPL",
    "gn:name":"Foz D\u00e3o",
    "gn:population":0,
    "gn:timezone":"Europe/Lisbon",
    "iso:country":"PT",
    "wof:name":"Foz Dao",
    "wof:placetype":"locality"
},
  "geometry": {"coordinates":[-8.18679,40.3346],"type":"Point"}
}