{
  "type": "Feature",
  "properties": {
    "gn:admin1_code":"02",
    "gn:admin2_code":"0118",
    "gn:admin3_code":"11810.0",
    "gn:asciiname":"Sao Romao",
    "gn:country_code":"PT",
    "gn:dem":22,
    "gn:feature_class":"P",
    "gn:feature_code":"PPL",
    "gn:name":"S\u00e3o Rom\u00e3o",
    "gn:population":0,
    "gn:timezone":"Europe/Lisbon",
    "iso:country":"PT",
    "wof:name":"Sao Romao",
    "wof:placetype":"locality"
},
  "geometry": {"coordinates":[-8.6694,40.51663],"type":"Point"}
}