{
  "type": "Feature",
  "properties": {
    "gn:admin1_code":"2.0",
    "gn:admin2_code":"0107",
    "gn:admin3_code":"10701.0",
    "gn:asciiname":"Esmojais",
    "gn:country_code":"PT",
    "gn:dem":79,
    "gn:feature_class":"P",
    "gn:feature_code":"PPL",
    "gn:name":"Esmoj\u00e3is",
    "gn:population":0,
    "gn:timezone":"Europe/Lisbon",
    "iso:country":"PT",
    "wof:name":"Esmojais",
    "wof:placetype":"locality"
},
  "geometry": {"coordinates":[-8.61103,40.99862],"type":"Point"}
}