{
  "type": "Feature",
  "properties": {
    "gn:admin1_code":"2.0",
    "gn:admin2_code":"0111",
    "gn:admin3_code":"11102.0",
    "gn:asciiname":"Cavaleiros",
    "gn:country_code":"PT",
    "gn:dem":47,
    "gn:feature_class":"P",
    "gn:feature_code":"PPL",
    "gn:name":"Cavaleiros",
    "gn:population":0,
    "gn:timezone":"Europe/Lisbon",
    "iso:country":"PT",
    "wof:name":"Cavaleiros",
    "wof:placetype":"locality"
},
  "geometry": {"coordinates":[-8.49668,40.29894],"type":"Point"}
}