{
  "type": "Feature",
  "properties": {
    "gn:admin1_code":"05",
    "gn:admin2_code":"0401",
    "gn:admin3_code":"40120.0",
    "gn:asciiname":"Vilares de Vilarica",
    "gn:country_code":"PT",
    "gn:dem":413,
    "gn:feature_class":"P",
    "gn:feature_code":"PPL",
    "gn:name":"Vilares de Vilari\u00e7a",
    "gn:population":0,
    "gn:timezone":"Europe/Lisbon",
    "iso:country":"PT",
    "wof:name":"Vilares de Vilarica",
    "wof:placetype":"locality"
},
  "geometry": {"coordinates":[-7.03827,41.39086],"type":"Point"}
}