{
  "type": "Feature",
  "properties": {
    "gn:admin1_code":"20",
    "gn:admin2_code":"1607",
    "gn:admin3_code":"160737.0",
    "gn:asciiname":"Sao Mamede",
    "gn:country_code":"PT",
    "gn:dem":439,
    "gn:feature_class":"P",
    "gn:feature_code":"PPL",
    "gn:name":"S\u00e3o Mamede",
    "gn:population":0,
    "gn:timezone":"Europe/Lisbon",
    "iso:country":"PT",
    "wof:name":"Sao Mamede",
    "wof:placetype":"locality"
},
  "geometry": {"coordinates":[-8.52619,41.81138],"type":"Point"}
}