{
  "type": "Feature",
  "properties": {
    "gn:admin1_code":"21",
    "gn:admin2_code":"1703",
    "gn:admin3_code":"170320.0",
    "gn:asciiname":"Vila Verde",
    "gn:country_code":"PT",
    "gn:dem":357,
    "gn:feature_class":"P",
    "gn:feature_code":"PPL",
    "gn:name":"Vila Verde",
    "gn:population":0,
    "gn:timezone":"Europe/Lisbon",
    "iso:country":"PT",
    "name:cat_x_preferred":[
        "Vila Verde"
    ],
    "name:ceb_x_preferred":[
        "Vila Verde"
    ],
    "name:deu_x_preferred":[
        "Vila Verde"
    ],
    "name:eus_x_preferred":[
        "Vila Verde"
    ],
    "name:fin_x_preferred":[
        "Vila Verde"
    ],
    "name:fra_x_preferred":[
        "Vila Verde"
    ],
    "name:ita_x_preferred":[
        "Vila Verde"
    ],
    "name:kaz_x_preferred":[
        "\u0412\u0438\u043b\u0430-\u0412\u0435\u0440\u0434\u0435"
    ],
    "name:msa_x_preferred":[
        "Vila Verde Municipality"
    ],
    "name:mwl_x_preferred":[
        "Vila Verde"
    ],
    "name:nld_x_preferred":[
        "Vila Verde"
    ],
    "name:nor_x_preferred":[
        "Vila Verde"
    ],
    "name:pol_x_preferred":[
        "Vila Verde"
    ],
    "name:por_x_preferred":[
        "Vila Verde"
    ],
    "name:rus_x_preferred":[
        "\u0412\u0438\u043b\u0430-\u0412\u0435\u0440\u0434\u0438"
    ],
    "name:spa_x_preferred":[
        "Vila Verde"
    ],
    "name:swe_x_preferred":[
        "Vila Verde"
    ],
    "name:tur_x_preferred":[
        "Vila Verde"
    ],
    "name:ukr_x_preferred":[
        "\u0412\u0456\u043b\u0430-\u0412\u0435\u0440\u0434\u0435"
    ],
    "name:vie_x_preferred":[
        "Vila Verde"
    ],
    "name:vol_x_preferred":[
        "Vila Verde"
    ],
    "name:war_x_preferred":[
        "Vila Verde"
    ],
    "name:zho_x_preferred":[
        "\u97cb\u723e\u8fea\u93ae"
    ],
    "wof:name":"Vila Verde",
    "wof:placetype":"locality"
},
  "geometry": {"coordinates":[-7.55225,41.63191],"type":"Point"}
}