{
  "type": "Feature",
  "properties": {
    "gn:admin1_code":"21",
    "gn:admin2_code":"1712",
    "gn:admin3_code":"171228.0",
    "gn:asciiname":"Valverde",
    "gn:country_code":"PT",
    "gn:dem":430,
    "gn:feature_class":"P",
    "gn:feature_code":"PPL",
    "gn:name":"Valverde",
    "gn:population":0,
    "gn:timezone":"Europe/Lisbon",
    "iso:country":"PT",
    "name:ara_x_preferred":[
        "\u0641\u0627\u0644\u0641\u064a\u0631\u062f\u064a"
    ],
    "name:arg_x_preferred":[
        "Valverde"
    ],
    "name:bul_x_preferred":[
        "\u0412\u0430\u043b\u0432\u0435\u0440\u0434\u0435"
    ],
    "name:cat_x_preferred":[
        "Valverde"
    ],
    "name:ceb_x_preferred":[
        "Valverde"
    ],
    "name:ces_x_preferred":[
        "Valverde"
    ],
    "name:deu_x_preferred":[
        "Valverde"
    ],
    "name:ell_x_preferred":[
        "\u0392\u03b1\u03bb\u03b2\u03ad\u03c1\u03b4\u03b5"
    ],
    "name:epo_x_preferred":[
        "Valverde"
    ],
    "name:eus_x_preferred":[
        "Valverde"
    ],
    "name:fra_x_preferred":[
        "Valverde"
    ],
    "name:glg_x_preferred":[
        "Valverde"
    ],
    "name:ita_x_preferred":[
        "Valverde"
    ],
    "name:jpn_x_preferred":[
        "\u30f4\u30a1\u30eb\u30f4\u30a7\u30eb\u30c7"
    ],
    "name:kor_x_preferred":[
        "\ubc1c\ubca0\ub974\ub370"
    ],
    "name:lav_x_preferred":[
        "Valverde"
    ],
    "name:lit_x_preferred":[
        "Valverd\u0117"
    ],
    "name:lmo_x_preferred":[
        "Valverde"
    ],
    "name:nap_x_preferred":[
        "Valverde"
    ],
    "name:nds_x_preferred":[
        "Valverde"
    ],
    "name:nld_x_preferred":[
        "Valverde"
    ],
    "name:nor_x_preferred":[
        "Valverde"
    ],
    "name:oci_x_preferred":[
        "Valverde"
    ],
    "name:pms_x_preferred":[
        "Valverde"
    ],
    "name:pol_x_preferred":[
        "Valverde"
    ],
    "name:por_x_preferred":[
        "Valverde"
    ],
    "name:rus_x_preferred":[
        "\u0412\u0430\u043b\u0432\u0435\u0440\u0434\u0435"
    ],
    "name:spa_x_preferred":[
        "Valverde"
    ],
    "name:srp_x_preferred":[
        "\u0412\u0430\u043b\u0432\u0435\u0440\u0434\u0435"
    ],
    "name:swe_x_preferred":[
        "Valverde"
    ],
    "name:ukr_x_preferred":[
        "\u0412\u0430\u043b\u044c\u0432\u0435\u0440\u0434\u0435"
    ],
    "wof:name":"Valverde",
    "wof:placetype":"locality"
},
  "geometry": {"coordinates":[-7.27478,41.5948],"type":"Point"}
}