{
  "type": "Feature",
  "properties": {
    "gn:admin1_code":"14",
    "gn:admin2_code":"1109",
    "gn:admin3_code":"110904.0",
    "gn:asciiname":"Azenhas",
    "gn:country_code":"PT",
    "gn:dem":65,
    "gn:feature_class":"P",
    "gn:feature_code":"PPL",
    "gn:name":"Azenhas",
    "gn:population":0,
    "gn:timezone":"Europe/Lisbon",
    "iso:country":"PT",
    "wof:name":"Azenhas",
    "wof:placetype":"locality"
},
  "geometry": {"coordinates":[-9.38603,39.0573],"type":"Point"}
}