{
  "type": "Feature",
  "properties": {
    "gn:admin1_code":"4.0",
    "gn:admin2_code":"0313",
    "gn:admin3_code":"31303.0",
    "gn:asciiname":"Atais",
    "gn:country_code":"PT",
    "gn:dem":194,
    "gn:feature_class":"P",
    "gn:feature_code":"PPL",
    "gn:name":"At\u00e3is",
    "gn:population":0,
    "gn:timezone":"Europe/Lisbon",
    "iso:country":"PT",
    "wof:name":"Atais",
    "wof:placetype":"locality"
},
  "geometry": {"coordinates":[-8.40853,41.7131],"type":"Point"}
}