{
  "type": "Feature",
  "properties": {
    "gn:admin1_code":"06",
    "gn:admin2_code":"0509",
    "gn:admin3_code":"50912.0",
    "gn:asciiname":"Aldeia da Ribeira Fundeira",
    "gn:country_code":"PT",
    "gn:dem":281,
    "gn:feature_class":"P",
    "gn:feature_code":"PPL",
    "gn:name":"Aldeia da Ribeira Fundeira",
    "gn:population":0,
    "gn:timezone":"Europe/Lisbon",
    "iso:country":"PT",
    "wof:name":"Aldeia da Ribeira Fundeira",
    "wof:placetype":"locality"
},
  "geometry": {"coordinates":[-8.06215,39.81925],"type":"Point"}
}