{
  "type": "Feature",
  "properties": {
    "gn:admin1_code":"09",
    "gn:admin2_code":"0808",
    "gn:admin3_code":"80804.0",
    "gn:asciiname":"Vale Rodrigo",
    "gn:country_code":"PT",
    "gn:dem":202,
    "gn:feature_class":"P",
    "gn:feature_code":"PPL",
    "gn:name":"Vale Rodrigo",
    "gn:population":0,
    "gn:timezone":"Europe/Lisbon",
    "iso:country":"PT",
    "wof:name":"Vale Rodrigo",
    "wof:placetype":"locality"
},
  "geometry": {"coordinates":[-8.14996,37.16191],"type":"Point"}
}