{
  "type": "Feature",
  "properties": {
    "gn:admin1_code":"18",
    "gn:admin2_code":"1401",
    "gn:admin3_code":"140110.0",
    "gn:asciiname":"Favaqueira",
    "gn:country_code":"PT",
    "gn:dem":213,
    "gn:feature_class":"P",
    "gn:feature_code":"PPL",
    "gn:name":"Favaqueira",
    "gn:population":0,
    "gn:timezone":"Europe/Lisbon",
    "iso:country":"PT",
    "wof:name":"Favaqueira",
    "wof:placetype":"locality"
},
  "geometry": {"coordinates":[-8.08804,39.37356],"type":"Point"}
}