{
  "type": "Feature",
  "properties": {
    "gn:admin1_code":"11.0",
    "gn:admin2_code":"0902",
    "gn:admin3_code":"90213.0",
    "gn:asciiname":"Malhada Sorda",
    "gn:country_code":"PT",
    "gn:dem":778,
    "gn:feature_class":"P",
    "gn:feature_code":"PPL",
    "gn:name":"Malhada Sorda",
    "gn:population":0,
    "gn:timezone":"Europe/Lisbon",
    "iso:country":"PT",
    "wof:name":"Malhada Sorda",
    "wof:placetype":"locality"
},
  "geometry": {"coordinates":[-6.91457,40.5354],"type":"Point"}
}