{
  "type": "Feature",
  "properties": {
    "gn:admin1_code":"11.0",
    "gn:admin2_code":"0902",
    "gn:admin3_code":"90213.0",
    "gn:asciiname":"Malhada Sorda",
    "gn:country_code":"PT",
    "gn:dem":778,
    "gn:feature_class":"P",
    "gn:feature_code":"PPL",
    "gn:name":"Malhada Sorda",
    "gn:population":0,
    "gn:timezone":"Europe/Lisbon",
    "iso:country":"PT",
    "name:ceb_x_preferred":[
        "Malhada Sorda"
    ],
    "name:deu_x_preferred":[
        "Malhada Sorda"
    ],
    "name:kaz_x_preferred":[
        "\u041c\u0430\u043b\u044c\u044f\u0434\u0430-\u0421\u043e\u0440\u0434\u0430"
    ],
    "name:nld_x_preferred":[
        "Malhada Sorda"
    ],
    "name:por_x_preferred":[
        "Malhada Sorda"
    ],
    "name:rus_x_preferred":[
        "\u041c\u0430\u043b\u044c\u044f\u0434\u0430-\u0421\u043e\u0440\u0434\u0430"
    ],
    "name:spa_x_preferred":[
        "Malhada Sorda"
    ],
    "wof:name":"Malhada Sorda",
    "wof:placetype":"locality"
},
  "geometry": {"coordinates":[-6.91457,40.5354],"type":"Point"}
}