{
  "type": "Feature",
  "properties": {
    "gn:admin1_code":"2.0",
    "gn:admin2_code":"0104",
    "gn:admin3_code":"10416.0",
    "gn:asciiname":"Monte de Moncao",
    "gn:country_code":"PT",
    "gn:dem":551,
    "gn:feature_class":"P",
    "gn:feature_code":"PPL",
    "gn:name":"Monte de Mon\u00e7\u00e3o",
    "gn:population":0,
    "gn:timezone":"Europe/Lisbon",
    "iso:country":"PT",
    "wof:name":"Monte de Moncao",
    "wof:placetype":"locality"
},
  "geometry": {"coordinates":[-8.25,40.95],"type":"Point"}
}