{
  "type": "Feature",
  "properties": {
    "gn:admin1_code":"07",
    "gn:admin2_code":"0602",
    "gn:admin3_code":"60216.0",
    "gn:asciiname":"Quinta",
    "gn:country_code":"PT",
    "gn:dem":51,
    "gn:feature_class":"P",
    "gn:feature_code":"PPL",
    "gn:name":"Quinta",
    "gn:population":0,
    "gn:timezone":"Europe/Lisbon",
    "iso:country":"PT",
    "wof:name":"Quinta",
    "wof:placetype":"locality"
},
  "geometry": {"coordinates":[-8.67675,40.41948],"type":"Point"}
}