{
  "type": "Feature",
  "properties": {
    "gn:admin1_code":"07",
    "gn:admin2_code":"0602",
    "gn:admin3_code":"60216.0",
    "gn:asciiname":"Quinta",
    "gn:country_code":"PT",
    "gn:dem":51,
    "gn:feature_class":"P",
    "gn:feature_code":"PPL",
    "gn:name":"Quinta",
    "gn:population":0,
    "gn:timezone":"Europe/Lisbon",
    "iso:country":"PT",
    "name:ceb_x_preferred":[
        "Quinta"
    ],
    "name:ces_x_preferred":[
        "Kvinta"
    ],
    "name:deu_x_preferred":[
        "Quinta"
    ],
    "name:fra_x_preferred":[
        "Quinte"
    ],
    "name:glg_x_preferred":[
        "Quinta"
    ],
    "name:ita_x_preferred":[
        "Quinta"
    ],
    "name:por_x_preferred":[
        "Quinta"
    ],
    "name:rus_x_preferred":[
        "\u041a\u0438\u043d\u0442\u0430"
    ],
    "name:spa_x_preferred":[
        "Quinta"
    ],
    "name:srp_x_preferred":[
        "\u041a\u0432\u0438\u043d\u0442\u0430"
    ],
    "name:swe_x_preferred":[
        "Quinta"
    ],
    "wof:name":"Quinta",
    "wof:placetype":"locality"
},
  "geometry": {"coordinates":[-8.67675,40.41948],"type":"Point"}
}