{
  "type": "Feature",
  "properties": {
    "gn:admin1_code":"13",
    "gn:admin2_code":"1001",
    "gn:admin3_code":"100108.0",
    "gn:asciiname":"Chao do Galego",
    "gn:country_code":"PT",
    "gn:dem":176,
    "gn:feature_class":"P",
    "gn:feature_code":"PPL",
    "gn:name":"Ch\u00e3o do Galego",
    "gn:population":0,
    "gn:timezone":"Europe/Lisbon",
    "iso:country":"PT",
    "wof:name":"Chao do Galego",
    "wof:placetype":"locality"
},
  "geometry": {"coordinates":[-8.95646,39.49012000000001],"type":"Point"}
}